{
  "type": "FeatureCollection",
  "features": [
    {
      "type": "Feature",
      "id": "node/7821340729",
      "properties": {
        "timestamp": "2020-08-17T23:00:24Z",
        "version": 1,
        "changeset": 89540771,
        "waterway": "waterfall",
        "id": "node/7821340729"
      },
      "geometry": {
        "type": "Point",
        "coordinates": [
          -54.023383,
          -30.4432975
        ]
      }
    },
    {
      "type": "Feature",
      "id": "node/9007073315",
      "properties": {
        "timestamp": "2021-08-15T11:18:21Z",
        "version": 2,
        "changeset": 109697051,
        "name": "Cascata do Guajuviras",
        "waterway": "waterfall",
        "id": "node/9007073315"
      },
      "geometry": {
        "type": "Point",
        "coordinates": [
          -53.9499253,
          -30.5248985
        ]
      }
    }
  ]
}
