{
  "type": "FeatureCollection",
  "features": [
    {
      "type": "Feature",
      "id": "node/4154229204",
      "properties": {
        "timestamp": "2016-04-28T20:33:53Z",
        "version": 1,
        "changeset": 38966069,
        "amenity": "dentist",
        "name": "Angelo",
        "id": "node/4154229204"
      },
      "geometry": {
        "type": "Point",
        "coordinates": [
          -45.0839642,
          -21.8810872
        ]
      }
    }
  ]
}
