{
  "type": "FeatureCollection",
  "features": [
    {
      "type": "Feature",
      "id": "node/2239585760",
      "properties": {
        "timestamp": "2017-03-31T16:56:21Z",
        "version": 2,
        "changeset": 47332124,
        "addr:housenumber": "1",
        "addr:street": "Rua das Margaridas",
        "email": "contatos@pousadacoscorais.com.br",
        "name": "Pousada Costa dos Corais",
        "phone": "+55-212789-1038",
        "tourism": "guest_house",
        "website": "http://www.pousadacoscorais.com.br/",
        "id": "node/2239585760"
      },
      "geometry": {
        "type": "Point",
        "coordinates": [
          -44.0237089,
          -22.9624749
        ]
      }
    },
    {
      "type": "Feature",
      "id": "node/8495254438",
      "properties": {
        "timestamp": "2021-03-07T23:42:52Z",
        "version": 1,
        "changeset": 100595896,
        "addr:city": "Mangaratiba",
        "addr:housenumber": "290",
        "addr:postcode": "23860000",
        "addr:street": "Rua Azalea dos Amores",
        "addr:suburb": "Ibicuí",
        "air_conditioning": "yes",
        "guest_house": "guest_house",
        "internet_access": "yes",
        "internet_access:fee": "no",
        "name": "Nalu Beach House",
        "operator": "Isabela, Rafael e Thiago",
        "phone": "+55 21 99631-0021",
        "rooms": "6",
        "tourism": "guest_house",
        "website": "https://www.instagram.com/nalu_ibicui/",
        "id": "node/8495254438"
      },
      "geometry": {
        "type": "Point",
        "coordinates": [
          -44.0216415,
          -22.9611153
        ]
      }
    }
  ]
}
