{
  "type": "FeatureCollection",
  "features": [
    {
      "type": "Feature",
      "id": "node/7112918085",
      "properties": {
        "timestamp": "2021-11-27T14:59:24Z",
        "version": 3,
        "changeset": 114297430,
        "name": "Hotel de Trânsito-praças",
        "natural": "hot_spring",
        "tourism": "hotel",
        "id": "node/7112918085"
      },
      "geometry": {
        "type": "Point",
        "coordinates": [
          -43.9863716,
          -23.0611422
        ]
      }
    },
    {
      "type": "Feature",
      "id": "node/8349530938",
      "properties": {
        "timestamp": "2021-01-22T15:22:25Z",
        "version": 1,
        "changeset": 97983235,
        "name": "Hotel Portobelo",
        "tourism": "hotel",
        "id": "node/8349530938"
      },
      "geometry": {
        "type": "Point",
        "coordinates": [
          -44.0736618,
          -22.9506174
        ]
      }
    },
    {
      "type": "Feature",
      "id": "node/8349530940",
      "properties": {
        "timestamp": "2021-01-22T15:22:25Z",
        "version": 1,
        "changeset": 97983235,
        "name": "ClubMed",
        "tourism": "hotel",
        "id": "node/8349530940"
      },
      "geometry": {
        "type": "Point",
        "coordinates": [
          -44.097201,
          -22.9942963
        ]
      }
    }
  ]
}
