{
  "type": "FeatureCollection",
  "features": [
    {
      "type": "Feature",
      "id": "node/8895736614",
      "properties": {
        "timestamp": "2021-07-05T18:58:28Z",
        "version": 1,
        "changeset": 107456463,
        "amenity": "school",
        "name": "Colegio Estadual Santo Antão",
        "opening_hours": "Mo-Fr 08:30-20:00; Sa,Su 08:00-15:00; PH off",
        "wheelchair": "yes",
        "id": "node/8895736614"
      },
      "geometry": {
        "type": "Point",
        "coordinates": [
          -53.6656433,
          -25.8817792
        ]
      }
    }
  ]
}
