{
  "type": "FeatureCollection",
  "features": [
    {
      "type": "Feature",
      "id": "node/8533384083",
      "properties": {
        "timestamp": "2021-03-18T18:20:35Z",
        "version": 1,
        "changeset": 101279405,
        "historic": "memorial",
        "inscription": "Cangaço",
        "memorial": "war_memorial",
        "name": "Morte de Lídia",
        "note": "Local da morte da cangaceira Lídia pelo seu companheiro o Cangaceiro Zé Baiano",
        "id": "node/8533384083"
      },
      "geometry": {
        "type": "Point",
        "coordinates": [
          -37.747972,
          -9.7607365
        ]
      }
    }
  ]
}
