{
  "type": "FeatureCollection",
  "features": [
    {
      "type": "Feature",
      "id": "node/3662452761",
      "properties": {
        "timestamp": "2018-01-25T00:10:46Z",
        "version": 2,
        "changeset": 55727687,
        "amenity": "school",
        "name": "Escola Mundurucu",
        "source": "IBGE",
        "id": "node/3662452761"
      },
      "geometry": {
        "type": "Point",
        "coordinates": [
          -57.8928472,
          -7.4402824
        ]
      }
    }
  ]
}
