{
  "type": "FeatureCollection",
  "features": [
    {
      "type": "Feature",
      "id": "node/9645835499",
      "properties": {
        "timestamp": "2022-04-06T14:24:21Z",
        "version": 1,
        "changeset": 119390251,
        "alt_name": "Salto do Antonio Game",
        "operator": "Munduruku",
        "waterway": "waterfall",
        "id": "node/9645835499"
      },
      "geometry": {
        "type": "Point",
        "coordinates": [
          -57.2806052,
          -7.7832303
        ]
      }
    },
    {
      "type": "Feature",
      "id": "node/9645870530",
      "properties": {
        "timestamp": "2022-04-06T14:24:21Z",
        "version": 1,
        "changeset": 119390251,
        "waterway": "waterfall",
        "id": "node/9645870530"
      },
      "geometry": {
        "type": "Point",
        "coordinates": [
          -57.2564634,
          -7.8330676
        ]
      }
    },
    {
      "type": "Feature",
      "id": "node/9645870599",
      "properties": {
        "timestamp": "2022-04-06T14:24:21Z",
        "version": 1,
        "changeset": 119390251,
        "waterway": "waterfall",
        "id": "node/9645870599"
      },
      "geometry": {
        "type": "Point",
        "coordinates": [
          -57.1627308,
          -7.8505098
        ]
      }
    },
    {
      "type": "Feature",
      "id": "node/9645870753",
      "properties": {
        "timestamp": "2022-04-06T14:24:21Z",
        "version": 1,
        "changeset": 119390251,
        "waterway": "waterfall",
        "id": "node/9645870753"
      },
      "geometry": {
        "type": "Point",
        "coordinates": [
          -57.3139934,
          -7.7417955
        ]
      }
    }
  ]
}
