{
  "type": "FeatureCollection",
  "features": [
    {
      "type": "Feature",
      "id": "node/8636188386",
      "properties": {
        "timestamp": "2021-04-16T18:19:33Z",
        "version": 1,
        "changeset": 103075689,
        "amenity": "library",
        "name": "Biblioteca Pública Municipal Padre Teodoro Strick",
        "id": "node/8636188386"
      },
      "geometry": {
        "type": "Point",
        "coordinates": [
          -50.001312,
          -26.979732
        ]
      }
    }
  ]
}
