{
  "type": "FeatureCollection",
  "features": [
    {
      "type": "Feature",
      "id": "node/10955944662",
      "properties": {
        "timestamp": "2024-06-26T13:59:32Z",
        "version": 2,
        "changeset": 153204445,
        "addr:city": "Saúde - Bahia",
        "addr:postcode": "44740-000",
        "addr:street": "Rua Zilda Pereira e Avenida Edgar Pereira",
        "addr:suburb": "Centro",
        "amenity": "hospital",
        "emergency": "yes",
        "healthcare": "hospital",
        "healthcare:speciality": "general",
        "internet_access": "wlan",
        "name": "HMNSS - Hospital M. Nossa Senhora da Saúde",
        "operator": "prefeitura",
        "operator:type": "government",
        "wheelchair": "yes",
        "id": "node/10955944662"
      },
      "geometry": {
        "type": "Point",
        "coordinates": [
          -40.420616,
          -10.9449014
        ]
      }
    },
    {
      "type": "Feature",
      "id": "node/10993142614",
      "properties": {
        "timestamp": "2025-01-19T14:09:28Z",
        "version": 7,
        "changeset": 161526031,
        "amenity": "hospital",
        "healthcare": "hospital",
        "name": "Laboratório de Analises e Pesquisas Clinicas (LAPEC) - Saúde",
        "id": "node/10993142614"
      },
      "geometry": {
        "type": "Point",
        "coordinates": [
          -40.4210161,
          -10.9414531
        ]
      }
    }
  ]
}
