{
  "type": "FeatureCollection",
  "features": [
    {
      "type": "Feature",
      "id": "node/10955944662",
      "properties": {
        "timestamp": "2023-06-04T21:41:27Z",
        "version": 1,
        "changeset": 136949019,
        "addr:city": "Saúde - Bahia",
        "addr:postcode": "44740-000",
        "addr:street": "Rua Zilda Pereira e Avenida Edgar Pereira",
        "addr:suburb": "Centro",
        "amenity": "hospital",
        "emergency": "yes",
        "healthcare": "hospital",
        "healthcare:speciality": "general",
        "internet_access": "wlan",
        "name": "HMNSS - Hospital M. Nossa Senhora da Saúde",
        "operator": "prefeitura",
        "operator:type": "government",
        "wheelchair": "yes",
        "id": "node/10955944662"
      },
      "geometry": {
        "type": "Point",
        "coordinates": [
          -40.4206951,
          -10.9448722
        ]
      }
    }
  ]
}
