{
  "type": "FeatureCollection",
  "features": [
    {
      "type": "Feature",
      "id": "node/7352028230",
      "properties": {
        "timestamp": "2020-03-31T18:04:17Z",
        "version": 1,
        "changeset": 82885648,
        "government": "register_office",
        "name": "Cartório de Ambrosina",
        "office": "government",
        "id": "node/7352028230"
      },
      "geometry": {
        "type": "Point",
        "coordinates": [
          -40.2629785,
          -7.7605115
        ]
      }
    }
  ]
}
