{
  "type": "FeatureCollection",
  "features": [
    {
      "type": "Feature",
      "id": "node/7352028199",
      "properties": {
        "timestamp": "2020-03-31T18:04:17Z",
        "version": 1,
        "changeset": 82885648,
        "name": "Grande Serra",
        "tourism": "hotel",
        "id": "node/7352028199"
      },
      "geometry": {
        "type": "Point",
        "coordinates": [
          -40.2647976,
          -7.7593309
        ]
      }
    }
  ]
}
