{
  "type": "FeatureCollection",
  "features": [
    {
      "type": "Feature",
      "id": "node/12410505518",
      "properties": {
        "timestamp": "2024-12-11T01:48:47Z",
        "version": 1,
        "changeset": 160149432,
        "name": "Pousada Fazenda Vale Verde",
        "tourism": "hotel",
        "id": "node/12410505518"
      },
      "geometry": {
        "type": "Point",
        "coordinates": [
          -47.9451245,
          -24.3603258
        ]
      }
    }
  ]
}
