{
  "type": "FeatureCollection",
  "features": [
    {
      "type": "Feature",
      "id": "node/4689088520",
      "properties": {
        "timestamp": "2017-02-16T16:35:10Z",
        "version": 1,
        "changeset": 46141729,
        "description": "Monumento inaugurado em 17 de agosto de 2012, por ocasião das festividades do Acendimento da Chama Crioula.",
        "historic": "monument",
        "name": "Cuia do Chimarrão",
        "id": "node/4689088520"
      },
      "geometry": {
        "type": "Point",
        "coordinates": [
          -52.1921965,
          -29.6067067
        ]
      }
    },
    {
      "type": "Feature",
      "id": "node/4689088522",
      "properties": {
        "timestamp": "2020-08-25T04:22:59Z",
        "version": 4,
        "changeset": 89886798,
        "description": "Homenagem aos expedicionários de Venâncio Aires que lutaram na 2ª Guerra Mundial, que acabou em 1945. ",
        "historic": "monument",
        "name": "Homenagem aos Expedicionários",
        "id": "node/4689088522"
      },
      "geometry": {
        "type": "Point",
        "coordinates": [
          -52.1926962,
          -29.6105057
        ]
      }
    },
    {
      "type": "Feature",
      "id": "node/6824287024",
      "properties": {
        "timestamp": "2019-09-26T01:31:54Z",
        "version": 2,
        "changeset": 74933240,
        "description": "Cruz em madeira, em frente ao salão de eventos, recordando a passagem das missões católicas de 1984.",
        "historic": "monument",
        "inscription": "Jesus Cristo - Ontem, Hoje e Sempre",
        "material": "wood",
        "memorial": "cross",
        "name": "Monumento das missões católicas de 1984",
        "id": "node/6824287024"
      },
      "geometry": {
        "type": "Point",
        "coordinates": [
          -52.1437559,
          -29.5903763
        ]
      }
    },
    {
      "type": "Feature",
      "id": "node/7841871500",
      "properties": {
        "timestamp": "2020-08-25T04:22:59Z",
        "version": 1,
        "changeset": 89886798,
        "historic": "monument",
        "id": "node/7841871500"
      },
      "geometry": {
        "type": "Point",
        "coordinates": [
          -52.1921036,
          -29.6103686
        ]
      }
    }
  ]
}
