{
  "type": "FeatureCollection",
  "features": [
    {
      "type": "Feature",
      "id": "node/2920178835",
      "properties": {
        "timestamp": "2021-06-29T12:58:50Z",
        "version": 4,
        "changeset": 107150008,
        "amenity": "doctors",
        "healthcare": "doctor",
        "name": "Clínica Médica",
        "id": "node/2920178835"
      },
      "geometry": {
        "type": "Point",
        "coordinates": [
          -42.6272211,
          -19.5218284
        ]
      }
    }
  ]
}
