{
  "type": "FeatureCollection",
  "features": [
    {
      "type": "Feature",
      "id": "node/2973092425",
      "properties": {
        "timestamp": "2017-03-01T14:24:44Z",
        "version": 3,
        "changeset": 46495655,
        "amenity": "drinking_water",
        "name": "Biquinha",
        "id": "node/2973092425"
      },
      "geometry": {
        "type": "Point",
        "coordinates": [
          -42.6684925,
          -19.464767
        ]
      }
    }
  ]
}
