{
  "type": "FeatureCollection",
  "features": [
    {
      "type": "Feature",
      "id": "node/3502845059",
      "properties": {
        "timestamp": "2015-05-07T12:15:03Z",
        "version": 1,
        "changeset": 30871673,
        "amenity": "school",
        "name": "EMEIEF Prof Maria do Carmo da Silva Julião",
        "id": "node/3502845059"
      },
      "geometry": {
        "type": "Point",
        "coordinates": [
          -49.5192441,
          -22.3592341
        ]
      }
    },
    {
      "type": "Feature",
      "id": "node/3502845060",
      "properties": {
        "timestamp": "2015-05-07T12:15:03Z",
        "version": 1,
        "changeset": 30871673,
        "amenity": "school",
        "name": "Escola Estadual Coronel Eduardo de Souza Porto",
        "id": "node/3502845060"
      },
      "geometry": {
        "type": "Point",
        "coordinates": [
          -49.52012,
          -22.3592213
        ]
      }
    }
  ]
}
