{
  "type": "FeatureCollection",
  "features": [
    {
      "type": "Feature",
      "id": "node/3315091760",
      "properties": {
        "timestamp": "2015-01-28T03:54:24Z",
        "version": 2,
        "changeset": 28457185,
        "alt_name": "Busto de Gomes Jardim",
        "historic": "memorial",
        "name": "Erma de Gomes Jardim",
        "id": "node/3315091760"
      },
      "geometry": {
        "type": "Point",
        "coordinates": [
          -51.3171776,
          -30.1100541
        ]
      }
    },
    {
      "type": "Feature",
      "id": "node/8952595972",
      "properties": {
        "timestamp": "2021-07-31T20:43:06Z",
        "version": 2,
        "changeset": 108956838,
        "description": "outras fontes: http://amaguaiba.org/marco-farroupilha/",
        "historic": "memorial",
        "inscription": "Localizado na Praia da Alegria, marca o ponto de partida do primeiro contingente farrapo, vitorioso na Batalha da Ponte da Azenha, em 20 de Setembro de 1835",
        "material": "stone",
        "memorial": "war_memorial",
        "name": "Marco Farroupilha",
        "source": "local knowledge;streetlevel imagery",
        "wikidata": "Q209297",
        "wikipedia": "pt:Guerra dos Farrapos",
        "id": "node/8952595972"
      },
      "geometry": {
        "type": "Point",
        "coordinates": [
          -51.3112477,
          -30.137849
        ]
      }
    }
  ]
}
