{
  "type": "FeatureCollection",
  "features": [
    {
      "type": "Feature",
      "id": "node/2863453848",
      "properties": {
        "timestamp": "2014-05-17T03:41:46Z",
        "version": 1,
        "changeset": 22382244,
        "historic": "memorial",
        "name": "Gruta",
        "id": "node/2863453848"
      },
      "geometry": {
        "type": "Point",
        "coordinates": [
          -53.3019139,
          -24.6421261
        ]
      }
    }
  ]
}
