{
  "type": "FeatureCollection",
  "features": [
    {
      "type": "Feature",
      "id": "node/10083709030",
      "properties": {
        "timestamp": "2022-10-19T18:21:00Z",
        "version": 2,
        "changeset": 127799655,
        "addr:city": "Virginópolis",
        "addr:housenumber": "85",
        "addr:postcode": "39730-000",
        "addr:street": "Rua Francisco Dias",
        "addr:suburb": "Centro",
        "name": "Restaurante e Hotel Colonial",
        "phone": "+55 33 3416 1150",
        "tourism": "hotel",
        "id": "node/10083709030"
      },
      "geometry": {
        "type": "Point",
        "coordinates": [
          -42.7040822,
          -18.8209462
        ]
      }
    },
    {
      "type": "Feature",
      "id": "node/10083709048",
      "properties": {
        "timestamp": "2022-10-08T13:02:47Z",
        "version": 1,
        "changeset": 127200238,
        "addr:city": "Virginópolis",
        "addr:housenumber": "345",
        "addr:postcode": "39730-000",
        "addr:street": "Praça Dona Augusta Campos",
        "addr:suburb": "Centro",
        "email": "hotelravelly@hotmail.com",
        "name": "Hotel Ravelly",
        "phone": "+55 33 3416 2531",
        "tourism": "hotel",
        "id": "node/10083709048"
      },
      "geometry": {
        "type": "Point",
        "coordinates": [
          -42.704478,
          -18.8211027
        ]
      }
    }
  ]
}
