{
  "type": "FeatureCollection",
  "features": [
    {
      "type": "Feature",
      "id": "node/12063556907",
      "properties": {
        "timestamp": "2025-03-05T12:53:28Z",
        "version": 2,
        "changeset": 163243858,
        "addr:city": "Balneário Barra do Sul",
        "addr:street": "Rua Rio Negrinho",
        "addr:suburb": "Centro",
        "amenity": "veterinary",
        "name": "Kinas Consultório Veterinário e Pet Shop",
        "opening_hours": "Mo-Sa 08:00-18:00; PH off",
        "id": "node/12063556907"
      },
      "geometry": {
        "type": "Point",
        "coordinates": [
          -48.6039977,
          -26.4598367
        ]
      }
    }
  ]
}
