{
  "type": "FeatureCollection",
  "features": [
    {
      "type": "Feature",
      "id": "node/6819881322",
      "properties": {
        "timestamp": "2019-09-24T12:33:36Z",
        "version": 1,
        "changeset": 74855402,
        "addr:postcode": "69490-000",
        "addr:street": "Avenida 25 de Março",
        "amenity": "hospital",
        "internet_access": "wlan",
        "name": "Unidade Mista de Maraã",
        "opening_hours": "24/7",
        "id": "node/6819881322"
      },
      "geometry": {
        "type": "Point",
        "coordinates": [
          -65.5910004,
          -1.8601237
        ]
      }
    },
    {
      "type": "Feature",
      "id": "node/6819919085",
      "properties": {
        "timestamp": "2019-09-24T12:46:58Z",
        "version": 1,
        "changeset": 74856119,
        "addr:postcode": "69490-000",
        "addr:street": "Avenida 25 de Março",
        "amenity": "hospital",
        "name": "Unidade Mista de Maraã",
        "opening_hours": "24/7",
        "id": "node/6819919085"
      },
      "geometry": {
        "type": "Point",
        "coordinates": [
          -65.5907062,
          -1.8598962
        ]
      }
    }
  ]
}
