{
  "type": "FeatureCollection",
  "features": [
    {
      "type": "Feature",
      "id": "node/12739526755",
      "properties": {
        "timestamp": "2025-04-08T18:02:20Z",
        "version": 2,
        "changeset": 164691753,
        "addr:city": "Itapeva",
        "addr:housenumber": "800",
        "addr:postcode": "18400140",
        "addr:street": "Rua Coronel Crescencio",
        "addr:suburb": "Centro",
        "email": "desitapeva@itesp.sp.gov.br",
        "government": "public_service",
        "name": "Fundação Instituto de Terras do Estado de São Paulo - ITESP",
        "office": "government",
        "opening_hours": "Mo-Fr 08:00-17:00",
        "operator": "Governo do Estado de São Paulo",
        "operator:wikidata": "Q10290787",
        "phone": "+55 15 35213864",
        "website": "www.itesp.sp.gov.br",
        "id": "node/12739526755"
      },
      "geometry": {
        "type": "Point",
        "coordinates": [
          -48.8752245,
          -23.987397
        ]
      }
    }
  ]
}
