{
  "type": "FeatureCollection",
  "features": [
    {
      "type": "Feature",
      "id": "node/3487882555",
      "properties": {
        "timestamp": "2015-05-02T20:47:08Z",
        "version": 2,
        "changeset": 30732096,
        "name": "Cachoeira da Invernada",
        "waterway": "waterfall",
        "id": "node/3487882555"
      },
      "geometry": {
        "type": "Point",
        "coordinates": [
          -49.0801202,
          -24.142285
        ]
      }
    },
    {
      "type": "Feature",
      "id": "node/3487882568",
      "properties": {
        "timestamp": "2015-05-02T20:47:08Z",
        "version": 2,
        "changeset": 30732096,
        "name": "Cachoeira 3 Quedas",
        "waterway": "waterfall",
        "id": "node/3487882568"
      },
      "geometry": {
        "type": "Point",
        "coordinates": [
          -49.085169,
          -24.1443085
        ]
      }
    }
  ]
}
