{
  "type": "FeatureCollection",
  "features": [
    {
      "type": "Feature",
      "id": "node/2498726236",
      "properties": {
        "timestamp": "2017-11-07T21:48:46Z",
        "version": 2,
        "changeset": 53594608,
        "name": "Cascata Cevilha",
        "waterway": "waterfall",
        "id": "node/2498726236"
      },
      "geometry": {
        "type": "Point",
        "coordinates": [
          -50.909176,
          -28.1445207
        ]
      }
    },
    {
      "type": "Feature",
      "id": "node/5217032107",
      "properties": {
        "timestamp": "2017-11-07T21:48:36Z",
        "version": 1,
        "changeset": 53594608,
        "waterway": "waterfall",
        "id": "node/5217032107"
      },
      "geometry": {
        "type": "Point",
        "coordinates": [
          -50.9119695,
          -28.1448002
        ]
      }
    },
    {
      "type": "Feature",
      "id": "node/5217032108",
      "properties": {
        "timestamp": "2017-11-07T21:48:36Z",
        "version": 1,
        "changeset": 53594608,
        "waterway": "waterfall",
        "id": "node/5217032108"
      },
      "geometry": {
        "type": "Point",
        "coordinates": [
          -50.9100376,
          -28.1449267
        ]
      }
    },
    {
      "type": "Feature",
      "id": "node/5217041563",
      "properties": {
        "timestamp": "2022-09-16T12:46:52Z",
        "version": 3,
        "changeset": 126263101,
        "waterway": "waterfall",
        "id": "node/5217041563"
      },
      "geometry": {
        "type": "Point",
        "coordinates": [
          -50.9545964,
          -28.1753141
        ]
      }
    }
  ]
}
