{
  "type": "FeatureCollection",
  "features": [
    {
      "type": "Feature",
      "id": "node/5176231521",
      "properties": {
        "timestamp": "2017-10-19T11:50:32Z",
        "version": 1,
        "changeset": 53066538,
        "addr:postcode": "48410000",
        "amenity": "hospital",
        "name": "Hospital de Cícero Dantas",
        "id": "node/5176231521"
      },
      "geometry": {
        "type": "Point",
        "coordinates": [
          -38.3807154,
          -10.5976873
        ]
      }
    }
  ]
}
