{
  "type": "FeatureCollection",
  "features": [
    {
      "type": "Feature",
      "id": "node/9344055045",
      "properties": {
        "timestamp": "2021-12-16T15:27:08Z",
        "version": 1,
        "changeset": 115014474,
        "amenity": "doctors",
        "name": "Dr. Jaime Marques",
        "id": "node/9344055045"
      },
      "geometry": {
        "type": "Point",
        "coordinates": [
          -39.2653057,
          -3.2775461
        ]
      }
    },
    {
      "type": "Feature",
      "id": "node/9344055054",
      "properties": {
        "timestamp": "2021-12-16T15:27:08Z",
        "version": 1,
        "changeset": 115014474,
        "amenity": "doctors",
        "name": "Clinica Dr. Dagmauro",
        "id": "node/9344055054"
      },
      "geometry": {
        "type": "Point",
        "coordinates": [
          -39.2650267,
          -3.2778039
        ]
      }
    }
  ]
}
