{
  "type": "FeatureCollection",
  "features": [
    {
      "type": "Feature",
      "id": "node/3925867485",
      "properties": {
        "timestamp": "2019-06-24T02:31:06Z",
        "version": 3,
        "changeset": 71544934,
        "amenity": "hospital",
        "emergency": "yes",
        "healthcare": "hospital",
        "healthcare:speciality": "general;radiology",
        "name": "Hospital Municipal de Trairi Ceará",
        "operator": "Prefeitura Municipal de Trairi",
        "phone": "+558533511504",
        "source": "local knowledge;aerial imagery",
        "wheelchair": "yes",
        "id": "node/3925867485"
      },
      "geometry": {
        "type": "Point",
        "coordinates": [
          -39.2639202,
          -3.2841671
        ]
      }
    }
  ]
}
