{
  "type": "FeatureCollection",
  "features": [
    {
      "type": "Feature",
      "id": "node/2830711353",
      "properties": {
        "timestamp": "2014-05-02T04:24:43Z",
        "version": 1,
        "changeset": 22076594,
        "amenity": "library",
        "name": "Biblioteca Municipal",
        "id": "node/2830711353"
      },
      "geometry": {
        "type": "Point",
        "coordinates": [
          -36.352725,
          -9.7835819
        ]
      }
    }
  ]
}
