{
  "type": "FeatureCollection",
  "features": [
    {
      "type": "Feature",
      "id": "node/10597841667",
      "properties": {
        "timestamp": "2023-02-01T03:48:04Z",
        "version": 1,
        "changeset": 131945339,
        "addr:street": "Rua Ferreirinha",
        "name": "Centro Administrativo",
        "office": "government",
        "id": "node/10597841667"
      },
      "geometry": {
        "type": "Point",
        "coordinates": [
          -50.4964771,
          -20.9320763
        ]
      }
    }
  ]
}
