{
  "type": "FeatureCollection",
  "features": [
    {
      "type": "Feature",
      "id": "node/10597841668",
      "properties": {
        "timestamp": "2023-02-01T03:48:04Z",
        "version": 1,
        "changeset": 131945339,
        "addr:street": "Avenida dos Eugênios",
        "amenity": "pharmacy",
        "healthcare": "pharmacy",
        "name": "Farmácia Municipal",
        "id": "node/10597841668"
      },
      "geometry": {
        "type": "Point",
        "coordinates": [
          -50.4963379,
          -20.9317769
        ]
      }
    },
    {
      "type": "Feature",
      "id": "node/10597841686",
      "properties": {
        "timestamp": "2023-02-01T03:48:04Z",
        "version": 1,
        "changeset": 131945339,
        "addr:street": "Rua Doutor Pio Prado",
        "amenity": "pharmacy",
        "healthcare": "pharmacy",
        "id": "node/10597841686"
      },
      "geometry": {
        "type": "Point",
        "coordinates": [
          -50.4956739,
          -20.9358807
        ]
      }
    },
    {
      "type": "Feature",
      "id": "node/10597841687",
      "properties": {
        "timestamp": "2023-02-01T03:48:04Z",
        "version": 1,
        "changeset": 131945339,
        "addr:street": "Rua Santo Antônio do Aracanguá",
        "amenity": "pharmacy",
        "healthcare": "pharmacy",
        "id": "node/10597841687"
      },
      "geometry": {
        "type": "Point",
        "coordinates": [
          -50.4961884,
          -20.9359378
        ]
      }
    }
  ]
}
