{
  "type": "FeatureCollection",
  "features": [
    {
      "type": "Feature",
      "id": "node/4218077583",
      "properties": {
        "timestamp": "2024-02-27T13:57:16Z",
        "version": 5,
        "changeset": 147974442,
        "ele": "2",
        "historic": "monument",
        "name": "Monumento à Romiseta",
        "id": "node/4218077583"
      },
      "geometry": {
        "type": "Point",
        "coordinates": [
          -47.3864573,
          -22.768553
        ]
      }
    },
    {
      "type": "Feature",
      "id": "node/4249857818",
      "properties": {
        "timestamp": "2020-08-10T17:35:27Z",
        "version": 3,
        "changeset": 89210651,
        "ele": "3",
        "historic": "monument",
        "name": "Monumento Maçônico",
        "id": "node/4249857818"
      },
      "geometry": {
        "type": "Point",
        "coordinates": [
          -47.4308154,
          -22.7559344
        ]
      }
    },
    {
      "type": "Feature",
      "id": "node/4532797312",
      "properties": {
        "timestamp": "2016-12-01T20:38:55Z",
        "version": 1,
        "changeset": 44096596,
        "historic": "monument",
        "name": "Relógio Solar",
        "id": "node/4532797312"
      },
      "geometry": {
        "type": "Point",
        "coordinates": [
          -47.3695553,
          -22.7515156
        ]
      }
    },
    {
      "type": "Feature",
      "id": "node/4798882621",
      "properties": {
        "timestamp": "2017-04-17T13:11:56Z",
        "version": 1,
        "changeset": 47870649,
        "ele": "4",
        "historic": "monument",
        "id": "node/4798882621"
      },
      "geometry": {
        "type": "Point",
        "coordinates": [
          -47.4249252,
          -22.7524755
        ]
      }
    }
  ]
}
