{
  "type": "FeatureCollection",
  "features": [
    {
      "type": "Feature",
      "id": "node/4778927011",
      "properties": {
        "timestamp": "2022-06-24T19:47:26Z",
        "version": 3,
        "changeset": 122816614,
        "name": "Pousada Vila Viva",
        "tourism": "guest_house",
        "id": "node/4778927011"
      },
      "geometry": {
        "type": "Point",
        "coordinates": [
          -45.9612449,
          -22.7572496
        ]
      }
    }
  ]
}
