{
  "type": "FeatureCollection",
  "features": [
    {
      "type": "Feature",
      "id": "node/5485747658",
      "properties": {
        "timestamp": "2018-03-18T06:16:12Z",
        "version": 1,
        "changeset": 57282539,
        "shop": "bicycle",
        "id": "node/5485747658"
      },
      "geometry": {
        "type": "Point",
        "coordinates": [
          -41.6985807,
          -17.1883162
        ]
      }
    }
  ]
}
