{
  "type": "FeatureCollection",
  "features": [
    {
      "type": "Feature",
      "id": "node/2016919680",
      "properties": {
        "timestamp": "2012-11-16T18:24:31Z",
        "version": 1,
        "changeset": 13896972,
        "amenity": "pharmacy",
        "name": "Farmácias São João",
        "id": "node/2016919680"
      },
      "geometry": {
        "type": "Point",
        "coordinates": [
          -55.1270245,
          -29.5560626
        ]
      }
    }
  ]
}
