{
  "type": "FeatureCollection",
  "features": [
    {
      "type": "Feature",
      "id": "node/8293104183",
      "properties": {
        "timestamp": "2021-07-17T12:56:52Z",
        "version": 2,
        "changeset": 108159226,
        "access": "yes",
        "amenity": "toilets",
        "fee": "no",
        "name": "Banheiro Público",
        "operator": "Prefeitura Municipal de Itamogi",
        "toilets:disposal": "flush",
        "unisex": "yes",
        "id": "node/8293104183"
      },
      "geometry": {
        "type": "Point",
        "coordinates": [
          -47.0487069,
          -21.0783427
        ]
      }
    }
  ]
}
