{
  "type": "FeatureCollection",
  "features": [
    {
      "type": "Feature",
      "id": "node/2078393421",
      "properties": {
        "timestamp": "2012-12-22T09:05:18Z",
        "version": 1,
        "changeset": 14363404,
        "name": "Bicicletaria Pedalão",
        "shop": "bicycle",
        "id": "node/2078393421"
      },
      "geometry": {
        "type": "Point",
        "coordinates": [
          -48.6199595,
          -17.7467397
        ]
      }
    }
  ]
}
