{
  "type": "FeatureCollection",
  "features": [
    {
      "type": "Feature",
      "id": "node/2507166329",
      "properties": {
        "timestamp": "2013-10-24T12:05:10Z",
        "version": 1,
        "changeset": 18518761,
        "historic": "monument",
        "name": "Praça Angelo Darolt",
        "id": "node/2507166329"
      },
      "geometry": {
        "type": "Point",
        "coordinates": [
          -54.0936374,
          -25.2954021
        ]
      }
    },
    {
      "type": "Feature",
      "id": "node/5563164436",
      "properties": {
        "timestamp": "2018-04-19T00:39:45Z",
        "version": 1,
        "changeset": 58219169,
        "historic": "monument",
        "name": "Cuia de Chimarrão Do CTG",
        "id": "node/5563164436"
      },
      "geometry": {
        "type": "Point",
        "coordinates": [
          -54.0539526,
          -25.2658472
        ]
      }
    }
  ]
}
