{
  "type": "FeatureCollection",
  "features": [
    {
      "type": "Feature",
      "id": "node/2768853597",
      "properties": {
        "timestamp": "2020-08-11T04:49:04Z",
        "version": 3,
        "changeset": 89226441,
        "addr:city": "Medianeira",
        "addr:housenumber": "1597",
        "addr:postcode": "85884000",
        "addr:street": "Avenida Brasília",
        "amenity": "pharmacy",
        "healthcare": "pharmacy",
        "name": "Nissei Drugstore",
        "opening_hours": "Mo-Sa 07:00-23:00; Su 09:00-20:00",
        "id": "node/2768853597"
      },
      "geometry": {
        "type": "Point",
        "coordinates": [
          -54.0936112,
          -25.2935226
        ]
      }
    },
    {
      "type": "Feature",
      "id": "node/4088030180",
      "properties": {
        "timestamp": "2021-10-01T16:29:15Z",
        "version": 3,
        "changeset": 111971751,
        "amenity": "pharmacy",
        "healthcare": "pharmacy",
        "name": "COOPERFARMA",
        "id": "node/4088030180"
      },
      "geometry": {
        "type": "Point",
        "coordinates": [
          -54.1171195,
          -25.3020034
        ]
      }
    }
  ]
}
