{
  "type": "FeatureCollection",
  "features": [
    {
      "type": "Feature",
      "id": "node/4800023721",
      "properties": {
        "timestamp": "2017-04-18T01:10:45Z",
        "version": 1,
        "changeset": 47888628,
        "name": "Pousada Ira",
        "name:pt": "Pousada Ira",
        "tourism": "guest_house",
        "id": "node/4800023721"
      },
      "geometry": {
        "type": "Point",
        "coordinates": [
          -46.6602845,
          -10.1695112
        ]
      }
    },
    {
      "type": "Feature",
      "id": "node/5922513886",
      "properties": {
        "timestamp": "2018-09-22T14:38:10Z",
        "version": 1,
        "changeset": 62827639,
        "name": "Pousada Cachoeira do Jalapão",
        "tourism": "guest_house",
        "id": "node/5922513886"
      },
      "geometry": {
        "type": "Point",
        "coordinates": [
          -46.670225,
          -10.162773
        ]
      }
    }
  ]
}
