{
  "type": "FeatureCollection",
  "features": [
    {
      "type": "Feature",
      "id": "node/6379919285",
      "properties": {
        "timestamp": "2019-04-03T01:48:29Z",
        "version": 1,
        "changeset": 68819234,
        "historic": "monument",
        "name": "Monumento Leonardo Mota",
        "id": "node/6379919285"
      },
      "geometry": {
        "type": "Point",
        "coordinates": [
          -39.7144553,
          -5.454257
        ]
      }
    },
    {
      "type": "Feature",
      "id": "node/7601232858",
      "properties": {
        "timestamp": "2020-06-08T03:12:06Z",
        "version": 1,
        "changeset": 86325267,
        "access": "yes",
        "historic": "monument",
        "inscription": "Pedra Branca que da nome há cidade",
        "name": "Pedra Branca",
        "id": "node/7601232858"
      },
      "geometry": {
        "type": "Point",
        "coordinates": [
          -39.7156338,
          -5.4537088
        ]
      }
    }
  ]
}
