{
  "type": "FeatureCollection",
  "features": [
    {
      "type": "Feature",
      "id": "node/10221839256",
      "properties": {
        "timestamp": "2022-11-27T18:01:25Z",
        "version": 1,
        "changeset": 129443717,
        "historic": "monument",
        "id": "node/10221839256"
      },
      "geometry": {
        "type": "Point",
        "coordinates": [
          -45.4029572,
          -23.8052514
        ]
      }
    },
    {
      "type": "Feature",
      "id": "node/10231874980",
      "properties": {
        "timestamp": "2022-12-01T22:04:41Z",
        "version": 1,
        "changeset": 129621866,
        "historic": "monument",
        "name": "Cruzeiro",
        "id": "node/10231874980"
      },
      "geometry": {
        "type": "Point",
        "coordinates": [
          -45.510473,
          -23.8336431
        ]
      }
    }
  ]
}
