{
  "type": "FeatureCollection",
  "features": [
    {
      "type": "Feature",
      "id": "node/4637824657",
      "properties": {
        "timestamp": "2024-12-11T15:41:03Z",
        "version": 2,
        "changeset": 160173938,
        "addr:city": "Gavião",
        "addr:postcode": "44650-000",
        "addr:street": "Praça lando Moura",
        "addr:suburb": "centro",
        "amenity": "school",
        "name": "Escola Mul. Durvalina de Oliveira Cunha",
        "nohousenumber": "yes",
        "id": "node/4637824657"
      },
      "geometry": {
        "type": "Point",
        "coordinates": [
          -39.7802463,
          -11.4684551
        ]
      }
    },
    {
      "type": "Feature",
      "id": "node/4638122478",
      "properties": {
        "timestamp": "2017-01-27T17:40:30Z",
        "version": 1,
        "changeset": 45568481,
        "amenity": "school",
        "name": "Colégio Estadual Nossa Senhora da Conceição",
        "id": "node/4638122478"
      },
      "geometry": {
        "type": "Point",
        "coordinates": [
          -39.7857499,
          -11.4724465
        ]
      }
    },
    {
      "type": "Feature",
      "id": "node/4638138125",
      "properties": {
        "timestamp": "2017-01-27T17:49:05Z",
        "version": 1,
        "changeset": 45568755,
        "amenity": "school",
        "name": "Antiga Escola Antonio Vieira",
        "id": "node/4638138125"
      },
      "geometry": {
        "type": "Point",
        "coordinates": [
          -39.7849552,
          -11.4688772
        ]
      }
    }
  ]
}
