{
  "type": "FeatureCollection",
  "features": [
    {
      "type": "Feature",
      "id": "node/8416829817",
      "properties": {
        "timestamp": "2021-02-12T01:23:13Z",
        "version": 1,
        "changeset": 99139412,
        "addr:street": "Rua José Pedro de Assis",
        "name": "Mecânico de bicicletas e motos",
        "shop": "bicycle",
        "id": "node/8416829817"
      },
      "geometry": {
        "type": "Point",
        "coordinates": [
          -49.3654666,
          -25.8645342
        ]
      }
    }
  ]
}
