{
  "type": "FeatureCollection",
  "features": [
    {
      "type": "Feature",
      "id": "node/7329193069",
      "properties": {
        "timestamp": "2020-03-31T12:44:24Z",
        "version": 2,
        "changeset": 82872091,
        "name": "Cachoeira das Andorinhas",
        "waterway": "waterfall",
        "id": "node/7329193069"
      },
      "geometry": {
        "type": "Point",
        "coordinates": [
          -41.8582267,
          -20.3743507
        ]
      }
    }
  ]
}
