{
  "type": "FeatureCollection",
  "features": [
    {
      "type": "Feature",
      "id": "node/8707909823",
      "properties": {
        "timestamp": "2021-05-07T01:32:33Z",
        "version": 1,
        "changeset": 104280240,
        "amenity": "school",
        "id": "node/8707909823"
      },
      "geometry": {
        "type": "Point",
        "coordinates": [
          -47.5002611,
          -22.9818835
        ]
      }
    },
    {
      "type": "Feature",
      "id": "node/8707909824",
      "properties": {
        "timestamp": "2021-05-07T01:32:33Z",
        "version": 1,
        "changeset": 104280240,
        "amenity": "school",
        "id": "node/8707909824"
      },
      "geometry": {
        "type": "Point",
        "coordinates": [
          -47.4907174,
          -22.9764935
        ]
      }
    },
    {
      "type": "Feature",
      "id": "node/8707921546",
      "properties": {
        "timestamp": "2021-05-07T01:40:52Z",
        "version": 1,
        "changeset": 104280400,
        "amenity": "school",
        "name": "EMEI Emília Benvenuto Ortolani",
        "id": "node/8707921546"
      },
      "geometry": {
        "type": "Point",
        "coordinates": [
          -47.5021433,
          -22.9830335
        ]
      }
    }
  ]
}
