{
  "type": "FeatureCollection",
  "features": [
    {
      "type": "Feature",
      "id": "node/6481918517",
      "properties": {
        "timestamp": "2019-05-18T04:09:10Z",
        "version": 1,
        "changeset": 70378245,
        "amenity": "cinema",
        "name": "Cine Teca",
        "id": "node/6481918517"
      },
      "geometry": {
        "type": "Point",
        "coordinates": [
          -41.51727,
          -17.8647747
        ]
      }
    }
  ]
}
