{
  "type": "FeatureCollection",
  "features": [
    {
      "type": "Feature",
      "id": "node/3124632348",
      "properties": {
        "timestamp": "2014-10-11T20:09:21Z",
        "version": 1,
        "changeset": 26012098,
        "amenity": "clinic",
        "name": "Posto de Saúde",
        "source": "Bing;IBGE",
        "id": "node/3124632348"
      },
      "geometry": {
        "type": "Point",
        "coordinates": [
          -45.2356457,
          -20.1541929
        ]
      }
    }
  ]
}
