{
  "type": "FeatureCollection",
  "features": [
    {
      "type": "Feature",
      "id": "node/9011007479",
      "properties": {
        "timestamp": "2021-08-16T19:31:18Z",
        "version": 1,
        "changeset": 109769291,
        "addr:city": "Valparaíso I",
        "addr:postcode": "72876-015",
        "addr:street": "Quadra 7",
        "addr:suburb": "Etapa A",
        "amenity": "arts_centre",
        "name": "Batalha Taça de Sangue",
        "opening_hours": "Sexta às 19h",
        "opening_hours:covid19": "Online",
        "website": "https://www.facebook.com/tacadesangue/",
        "wikiversity": "https://pt.wikiversity.org/wiki/Batalha_Ta%C3%A7a_de_Sangue",
        "id": "node/9011007479"
      },
      "geometry": {
        "type": "Point",
        "coordinates": [
          -47.982002,
          -16.069735
        ]
      }
    }
  ]
}
