{
  "type": "FeatureCollection",
  "features": [
    {
      "type": "Feature",
      "id": "node/2076515212",
      "properties": {
        "timestamp": "2020-07-31T14:42:22Z",
        "version": 6,
        "changeset": 88787716,
        "addr:city": "Laguna",
        "addr:housenumber": "280",
        "addr:postcode": "88790-000",
        "addr:street": "Rua Osvaldo Aranha",
        "addr:suburb": "Centro",
        "amenity": "hospital",
        "emergency": "yes",
        "healthcare": "hospital",
        "name": "Hospital de Caridade Senhor Bom Jesus dos Passos",
        "id": "node/2076515212"
      },
      "geometry": {
        "type": "Point",
        "coordinates": [
          -48.7798716,
          -28.4856776
        ]
      }
    }
  ]
}
