{
  "type": "FeatureCollection",
  "features": [
    {
      "type": "Feature",
      "id": "node/8636241999",
      "properties": {
        "timestamp": "2021-04-16T18:19:44Z",
        "version": 1,
        "changeset": 103075689,
        "amenity": "library",
        "name": "Biblioteca Pública Municipal Cruz e Souza",
        "id": "node/8636241999"
      },
      "geometry": {
        "type": "Point",
        "coordinates": [
          -49.79344,
          -27.303793
        ]
      }
    }
  ]
}
