{
  "type": "FeatureCollection",
  "features": [
    {
      "type": "Feature",
      "id": "node/3940872027",
      "properties": {
        "timestamp": "2016-01-12T03:29:51Z",
        "version": 1,
        "changeset": 36517353,
        "amenity": "library",
        "name": "Biblioteca Pública",
        "id": "node/3940872027"
      },
      "geometry": {
        "type": "Point",
        "coordinates": [
          -53.0072073,
          -24.0488977
        ]
      }
    }
  ]
}
