{
  "type": "FeatureCollection",
  "features": [
    {
      "type": "Feature",
      "id": "node/12165558569",
      "properties": {
        "timestamp": "2024-09-09T13:31:22Z",
        "version": 1,
        "changeset": 156394882,
        "access": "yes",
        "historic": "monument",
        "name": "Monumento Sanfona",
        "id": "node/12165558569"
      },
      "geometry": {
        "type": "Point",
        "coordinates": [
          -42.0118319,
          -9.0152088
        ]
      }
    }
  ]
}
