{
  "type": "FeatureCollection",
  "features": [
    {
      "type": "Feature",
      "id": "node/12753180501",
      "properties": {
        "timestamp": "2025-04-13T22:48:29Z",
        "version": 1,
        "changeset": 164915042,
        "name": "Hotel Cascata",
        "tourism": "hotel",
        "id": "node/12753180501"
      },
      "geometry": {
        "type": "Point",
        "coordinates": [
          -59.9484458,
          -15.0068462
        ]
      }
    }
  ]
}
