{
  "type": "FeatureCollection",
  "features": [
    {
      "type": "Feature",
      "id": "node/12063069253",
      "properties": {
        "timestamp": "2024-07-19T12:10:09Z",
        "version": 1,
        "changeset": 154140671,
        "historic": "memorial",
        "memorial": "plaque",
        "name": "Mestre Janguinho",
        "id": "node/12063069253"
      },
      "geometry": {
        "type": "Point",
        "coordinates": [
          -48.3300139,
          -25.2994361
        ]
      }
    }
  ]
}
