{
  "type": "FeatureCollection",
  "features": [
    {
      "type": "Feature",
      "id": "node/2630211807",
      "properties": {
        "timestamp": "2014-01-29T14:14:52Z",
        "version": 5,
        "changeset": 20265998,
        "addr:city": "Guaraqueçaba",
        "addr:housenumber": "47",
        "addr:postcode": "83.390-000",
        "addr:street": "Avenida Maria Carolina de Lisboa",
        "amenity": "pharmacy",
        "atm": "yes",
        "dispensing": "no",
        "drive_through": "no",
        "internet_access": "no",
        "name": "Guaraquefarma",
        "phone": "+55 41 3482-1495",
        "id": "node/2630211807"
      },
      "geometry": {
        "type": "Point",
        "coordinates": [
          -48.326997,
          -25.297579
        ]
      }
    }
  ]
}
