{
  "type": "FeatureCollection",
  "features": [
    {
      "type": "Feature",
      "id": "node/5969399809",
      "properties": {
        "timestamp": "2018-10-09T15:00:05Z",
        "version": 1,
        "changeset": 63349813,
        "name": "Câmara Municipal Do Porto Alegre Do Norte",
        "office": "government",
        "id": "node/5969399809"
      },
      "geometry": {
        "type": "Point",
        "coordinates": [
          -51.6353437,
          -10.8838206
        ]
      }
    }
  ]
}
