{
  "type": "FeatureCollection",
  "features": [
    {
      "type": "Feature",
      "id": "node/5969399808",
      "properties": {
        "timestamp": "2018-10-09T14:59:56Z",
        "version": 1,
        "changeset": 63349813,
        "amenity": "pharmacy",
        "name": "Drogaria Letícia",
        "id": "node/5969399808"
      },
      "geometry": {
        "type": "Point",
        "coordinates": [
          -51.6328201,
          -10.8756893
        ]
      }
    }
  ]
}
