{
  "type": "FeatureCollection",
  "features": [
    {
      "type": "Feature",
      "id": "node/7576253412",
      "properties": {
        "timestamp": "2020-05-31T22:53:56Z",
        "version": 1,
        "changeset": 86023767,
        "name": "EMATER",
        "office": "government",
        "id": "node/7576253412"
      },
      "geometry": {
        "type": "Point",
        "coordinates": [
          -53.8751824,
          -25.0536304
        ]
      }
    }
  ]
}
