{
  "type": "FeatureCollection",
  "features": [
    {
      "type": "Feature",
      "id": "node/11161718560",
      "properties": {
        "timestamp": "2023-11-06T14:24:27Z",
        "version": 3,
        "changeset": 143695843,
        "addr:city": "Canindé",
        "addr:housenumber": "S/N",
        "addr:postcode": "627000-00",
        "addr:street": "Avenida Doutor Luciano Magalhães",
        "addr:suburb": "Santa Luzia",
        "amenity": "college",
        "capacity": "500 Pessoas",
        "check_date": "2023-09-01",
        "description": "Escola estadual de nível médio e profissional em tempo integral.",
        "email": "eeepjosevidal@escola.ce.gov.br",
        "grades": "10-12",
        "image": "https://www.ceara.gov.br/wp-content/uploads/2017/11/20171116153419__MG_6906.jpg",
        "internet_access": "wired",
        "internet_access:fee": "no",
        "internet_access:ssid": "LEI_3",
        "level": "2",
        "name": "Eeep José Vidal Alves",
        "opening_hours": "Mo-Sa 06:30-17:40",
        "operator": "Maria Taylana Queiroz Martins",
        "operator:type": "public",
        "phone": "+55 (85) 3343-1703",
        "polling_station": "yes",
        "religion": "none",
        "source": "local knowledge",
        "start_date": "2023-09-01",
        "website": "https://www.instagram.com/eeepjosevidal/?hl=pt",
        "wheelchair": "yes",
        "id": "node/11161718560"
      },
      "geometry": {
        "type": "Point",
        "coordinates": [
          -39.3187116,
          -4.3487478
        ]
      }
    }
  ]
}
