{
  "type": "FeatureCollection",
  "features": [
    {
      "type": "Feature",
      "id": "node/5306930852",
      "properties": {
        "timestamp": "2020-08-26T05:27:00Z",
        "version": 4,
        "changeset": 89946796,
        "addr:city": "Itapecerica",
        "addr:postcode": "35550-000",
        "addr:street": "Rua Necéssio Dos Santos",
        "addr:suburb": "Centro",
        "government": "register_office",
        "name": "Cartorio Malachias",
        "office": "government",
        "id": "node/5306930852"
      },
      "geometry": {
        "type": "Point",
        "coordinates": [
          -45.1258841,
          -20.469124
        ]
      }
    }
  ]
}
