{
  "type": "FeatureCollection",
  "features": [
    {
      "type": "Feature",
      "id": "node/4045246585",
      "properties": {
        "timestamp": "2016-03-07T06:50:35Z",
        "version": 1,
        "changeset": 37659424,
        "name": "Jardim Recando das Palmeiras",
        "tourism": "hotel",
        "id": "node/4045246585"
      },
      "geometry": {
        "type": "Point",
        "coordinates": [
          -40.4523433,
          -3.5397008
        ]
      }
    },
    {
      "type": "Feature",
      "id": "node/4045246697",
      "properties": {
        "timestamp": "2016-03-07T06:50:36Z",
        "version": 1,
        "changeset": 37659424,
        "name": "Meruoca Apart Hotel",
        "tourism": "hotel",
        "id": "node/4045246697"
      },
      "geometry": {
        "type": "Point",
        "coordinates": [
          -40.4569968,
          -3.5392447
        ]
      }
    }
  ]
}
