{
  "type": "FeatureCollection",
  "features": [
    {
      "type": "Feature",
      "id": "node/6446364289",
      "properties": {
        "timestamp": "2019-05-03T19:15:38Z",
        "version": 1,
        "changeset": 69858069,
        "amenity": "nursing_home",
        "name": "Faz gema do caarapo",
        "id": "node/6446364289"
      },
      "geometry": {
        "type": "Point",
        "coordinates": [
          -55.0480219,
          -22.5851737
        ]
      }
    }
  ]
}
