{
  "type": "FeatureCollection",
  "features": [
    {
      "type": "Feature",
      "id": "node/3819756525",
      "properties": {
        "timestamp": "2017-12-10T21:36:55Z",
        "version": 3,
        "changeset": 54523297,
        "name": "Cachoeira dos Mascates",
        "waterway": "waterfall",
        "id": "node/3819756525"
      },
      "geometry": {
        "type": "Point",
        "coordinates": [
          -47.1316951,
          -18.5026832
        ]
      }
    },
    {
      "type": "Feature",
      "id": "node/3819780330",
      "properties": {
        "timestamp": "2020-02-19T19:33:52Z",
        "version": 2,
        "changeset": 81237356,
        "name": "Cachoeira do Córrego Coromandel",
        "waterway": "waterfall",
        "id": "node/3819780330"
      },
      "geometry": {
        "type": "Point",
        "coordinates": [
          -47.1799238,
          -18.4525152
        ]
      }
    },
    {
      "type": "Feature",
      "id": "node/5275618821",
      "properties": {
        "timestamp": "2017-12-10T21:37:10Z",
        "version": 2,
        "changeset": 54523297,
        "name": "Cachoeira do Muquém",
        "waterway": "waterfall",
        "id": "node/5275618821"
      },
      "geometry": {
        "type": "Point",
        "coordinates": [
          -47.1426675,
          -18.1789986
        ]
      }
    },
    {
      "type": "Feature",
      "id": "node/5275618822",
      "properties": {
        "timestamp": "2017-12-10T21:37:10Z",
        "version": 2,
        "changeset": 54523297,
        "name": "Cachoeira do Santo Inácio",
        "waterway": "waterfall",
        "id": "node/5275618822"
      },
      "geometry": {
        "type": "Point",
        "coordinates": [
          -47.0371588,
          -18.5483949
        ]
      }
    }
  ]
}
