{
  "type": "FeatureCollection",
  "features": [
    {
      "type": "Feature",
      "id": "node/3786044259",
      "properties": {
        "timestamp": "2020-01-14T00:52:00Z",
        "version": 2,
        "changeset": 79537620,
        "addr:city": "Macaé",
        "addr:housenumber": "566",
        "addr:street": "Rua Eusébio de Queiroz",
        "amenity": "dentist",
        "healthcare": "dentist",
        "name": "Pronto Socorro Odontológico",
        "operator": "Prefeitura de Macaé",
        "id": "node/3786044259"
      },
      "geometry": {
        "type": "Point",
        "coordinates": [
          -41.781737,
          -22.375601
        ]
      }
    },
    {
      "type": "Feature",
      "id": "node/3786070957",
      "properties": {
        "timestamp": "2023-07-03T02:07:37Z",
        "version": 3,
        "changeset": 138044056,
        "addr:city": "Macaé",
        "addr:housenumber": "411",
        "addr:postcode": "27910-310",
        "addr:street": "Rua Marechal Deodoro",
        "amenity": "dentist",
        "healthcare": "dentist",
        "name": "Uniodonto",
        "ref:CNES": "5020271",
        "ref:vatin": "BR72515208000154",
        "id": "node/3786070957"
      },
      "geometry": {
        "type": "Point",
        "coordinates": [
          -41.781531,
          -22.374268
        ]
      }
    },
    {
      "type": "Feature",
      "id": "node/4659336490",
      "properties": {
        "timestamp": "2017-02-03T11:36:41Z",
        "version": 1,
        "changeset": 45775783,
        "addr:housenumber": "8",
        "addr:street": "Rua Jorge Reid",
        "amenity": "dentist",
        "name": "Oralis Saúde Bucal",
        "id": "node/4659336490"
      },
      "geometry": {
        "type": "Point",
        "coordinates": [
          -41.7960495,
          -22.4030701
        ]
      }
    }
  ]
}
