{
  "type": "FeatureCollection",
  "features": [
    {
      "type": "Feature",
      "id": "node/3795297857",
      "properties": {
        "timestamp": "2020-01-14T00:38:02Z",
        "version": 2,
        "changeset": 79537447,
        "addr:city": "Macaé",
        "addr:housenumber": "119",
        "addr:postcode": "27913-190",
        "addr:street": "Rua Doutor Bueno",
        "amenity": "doctors",
        "healthcare": "doctor",
        "name": "Arlênio Lopes dos Santos",
        "id": "node/3795297857"
      },
      "geometry": {
        "type": "Point",
        "coordinates": [
          -41.775144,
          -22.378251
        ]
      }
    },
    {
      "type": "Feature",
      "id": "node/12029703403",
      "properties": {
        "timestamp": "2024-07-02T18:14:49Z",
        "version": 1,
        "changeset": 153470554,
        "addr:city": "Macaé",
        "addr:housenumber": "111",
        "addr:postcode": "27920-180",
        "addr:street": "Rua Mar del Plata",
        "addr:suburb": "Cavaleiros",
        "amenity": "doctors",
        "healthcare": "doctor",
        "mobile": "+55 22 998853506",
        "name": "Centro Médico Cavaleiros",
        "opening_hours": "Segunda à Sexta das 08:00 até as 18:00",
        "id": "node/12029703403"
      },
      "geometry": {
        "type": "Point",
        "coordinates": [
          -41.8004701,
          -22.4054168
        ]
      }
    }
  ]
}
