{
  "type": "FeatureCollection",
  "features": [
    {
      "type": "Feature",
      "id": "node/3795297857",
      "properties": {
        "timestamp": "2020-01-14T00:38:02Z",
        "version": 2,
        "changeset": 79537447,
        "addr:city": "Macaé",
        "addr:housenumber": "119",
        "addr:postcode": "27913-190",
        "addr:street": "Rua Doutor Bueno",
        "amenity": "doctors",
        "healthcare": "doctor",
        "name": "Arlênio Lopes dos Santos",
        "id": "node/3795297857"
      },
      "geometry": {
        "type": "Point",
        "coordinates": [
          -41.775144,
          -22.378251
        ]
      }
    }
  ]
}
