{
  "type": "FeatureCollection",
  "features": [
    {
      "type": "Feature",
      "id": "node/10824943676",
      "properties": {
        "timestamp": "2023-05-25T06:02:34Z",
        "version": 2,
        "changeset": 136526217,
        "addr:city": "Três Marias",
        "addr:housenumber": "1",
        "addr:postcode": "39205-000",
        "addr:street": "Rua Presidente John Kennedy",
        "addr:suburb": "Centro",
        "amenity": "hospital",
        "healthcare": "hospital",
        "name": "Hospital São Francisco",
        "ref:CNES": "2796112",
        "ref:vatin": "BR18048223000194",
        "id": "node/10824943676"
      },
      "geometry": {
        "type": "Point",
        "coordinates": [
          -45.2321272,
          -18.2034115
        ]
      }
    }
  ]
}
