{
  "type": "FeatureCollection",
  "features": [
    {
      "type": "Feature",
      "id": "node/1025364505",
      "properties": {
        "timestamp": "2024-07-01T23:50:06Z",
        "version": 5,
        "changeset": 153433140,
        "amenity": "cinema",
        "brand": "Cinemark",
        "brand:wikidata": "Q707530",
        "brand:wikipedia": "en:Cinemark Theatres",
        "check_date": "2024-07-01",
        "name": "Cinemark Riomar",
        "id": "node/1025364505"
      },
      "geometry": {
        "type": "Point",
        "coordinates": [
          -37.0472486,
          -10.9454771
        ]
      }
    },
    {
      "type": "Feature",
      "id": "node/1025364571",
      "properties": {
        "timestamp": "2024-07-06T04:05:57Z",
        "version": 7,
        "changeset": 153609960,
        "amenity": "cinema",
        "brand": "Cinemark",
        "brand:wikidata": "Q707530",
        "brand:wikipedia": "en:Cinemark Theatres",
        "check_date": "2024-07-06",
        "name": "Cinemark",
        "source": "survey",
        "id": "node/1025364571"
      },
      "geometry": {
        "type": "Point",
        "coordinates": [
          -37.059534,
          -10.9431993
        ]
      }
    },
    {
      "type": "Feature",
      "id": "node/9410916212",
      "properties": {
        "timestamp": "2022-01-11T18:17:31Z",
        "version": 1,
        "changeset": 116035436,
        "amenity": "cinema",
        "name": "Cine Vitória",
        "id": "node/9410916212"
      },
      "geometry": {
        "type": "Point",
        "coordinates": [
          -37.0509976,
          -10.9121753
        ]
      }
    },
    {
      "type": "Feature",
      "id": "node/10926353815",
      "properties": {
        "timestamp": "2023-05-25T13:51:34Z",
        "version": 1,
        "changeset": 136545406,
        "amenity": "cinema",
        "name": "Centerplex Cinemas",
        "id": "node/10926353815"
      },
      "geometry": {
        "type": "Point",
        "coordinates": [
          -37.0498994,
          -10.9015649
        ]
      }
    }
  ]
}
