{
  "type": "FeatureCollection",
  "features": [
    {
      "type": "Feature",
      "id": "node/9119949257",
      "properties": {
        "timestamp": "2022-07-19T02:27:03Z",
        "version": 3,
        "changeset": 123784754,
        "addr:city": "Rodeio",
        "addr:housenumber": "705",
        "addr:postcode": "89136-000",
        "addr:street": "Rua Germano Depiné",
        "addr:suburb": "Gávea",
        "description": "Hospedaria e Quintal Criativo",
        "name": "Quinta da Gávea",
        "phone": "+55 47 3333-0751",
        "tourism": "guest_house",
        "website": "https://www.quintadagavea.com.br/",
        "id": "node/9119949257"
      },
      "geometry": {
        "type": "Point",
        "coordinates": [
          -49.3554858,
          -26.9176244
        ]
      }
    }
  ]
}
