{
  "type": "FeatureCollection",
  "features": [
    {
      "type": "Feature",
      "id": "node/3484967658",
      "properties": {
        "timestamp": "2023-06-07T19:54:47Z",
        "version": 3,
        "changeset": 137069947,
        "addr:city": "Salto",
        "addr:housenumber": "09",
        "addr:postcode": "13323-324",
        "addr:street": "Rua Gaspar de Lemos",
        "addr:suburb": "CECAP",
        "amenity": "kindergarten",
        "check_date": "2023-06-07",
        "name": "CEMUS XII - Educação Infantil II e III",
        "operator": "Prefeitura da Estância Turística de Salto",
        "phone": "+55 11 4029-0917",
        "id": "node/3484967658"
      },
      "geometry": {
        "type": "Point",
        "coordinates": [
          -47.2716555,
          -23.2098623
        ]
      }
    }
  ]
}
