{
  "type": "FeatureCollection",
  "features": [
    {
      "type": "Feature",
      "id": "node/3224773951",
      "properties": {
        "timestamp": "2023-05-03T18:09:17Z",
        "version": 2,
        "changeset": 135671869,
        "waterway": "waterfall",
        "id": "node/3224773951"
      },
      "geometry": {
        "type": "Point",
        "coordinates": [
          -49.0231829,
          -27.3869046
        ]
      }
    },
    {
      "type": "Feature",
      "id": "node/6208030085",
      "properties": {
        "timestamp": "2023-05-06T18:20:50Z",
        "version": 4,
        "changeset": 135787478,
        "name": "Cascata do Alho",
        "waterway": "waterfall",
        "id": "node/6208030085"
      },
      "geometry": {
        "type": "Point",
        "coordinates": [
          -48.9906,
          -27.4328642
        ]
      }
    },
    {
      "type": "Feature",
      "id": "node/10873929541",
      "properties": {
        "timestamp": "2023-05-06T18:20:50Z",
        "version": 1,
        "changeset": 135787478,
        "waterway": "waterfall",
        "id": "node/10873929541"
      },
      "geometry": {
        "type": "Point",
        "coordinates": [
          -48.9499993,
          -27.4192271
        ]
      }
    }
  ]
}
