{
  "type": "FeatureCollection",
  "features": [
    {
      "type": "Feature",
      "id": "node/5809817502",
      "properties": {
        "timestamp": "2018-08-05T06:42:16Z",
        "version": 1,
        "changeset": 61367212,
        "historic": "memorial",
        "name": "Escultura Nova Londrina 50 Anos",
        "id": "node/5809817502"
      },
      "geometry": {
        "type": "Point",
        "coordinates": [
          -52.9825824,
          -22.7653459
        ]
      }
    },
    {
      "type": "Feature",
      "id": "node/5809817889",
      "properties": {
        "timestamp": "2018-08-05T06:42:52Z",
        "version": 1,
        "changeset": 61367223,
        "historic": "memorial",
        "name": "Busto Romeu Barbosa de Souza",
        "id": "node/5809817889"
      },
      "geometry": {
        "type": "Point",
        "coordinates": [
          -52.9813286,
          -22.7642071
        ]
      }
    }
  ]
}
