{
  "type": "FeatureCollection",
  "features": [
    {
      "type": "Feature",
      "id": "node/8735951145",
      "properties": {
        "timestamp": "2021-08-09T22:21:00Z",
        "version": 2,
        "changeset": 109430773,
        "addr:housenumber": "1223",
        "addr:street": "Rua Manoel Gonçalves",
        "amenity": "dentist",
        "healthcare": "dentist",
        "name": "Oral Pop",
        "id": "node/8735951145"
      },
      "geometry": {
        "type": "Point",
        "coordinates": [
          -37.9910622,
          -5.0735626
        ]
      }
    },
    {
      "type": "Feature",
      "id": "node/8736259254",
      "properties": {
        "timestamp": "2021-08-14T17:49:59Z",
        "version": 3,
        "changeset": 109678584,
        "addr:housenumber": "2",
        "addr:street": "Rua Raimundo Gonçalves Ferreira Lima",
        "amenity": "dentist",
        "healthcare": "dentist",
        "name": "Consultório Dr Carlos Renato de Carvalho",
        "phone": "+55 88 3423 1101",
        "id": "node/8736259254"
      },
      "geometry": {
        "type": "Point",
        "coordinates": [
          -37.9840916,
          -5.0764284
        ]
      }
    }
  ]
}
