{
  "type": "FeatureCollection",
  "features": [
    {
      "type": "Feature",
      "id": "node/6381613113",
      "properties": {
        "timestamp": "2019-04-03T18:30:39Z",
        "version": 1,
        "changeset": 68852666,
        "internet_access": "yes",
        "name": "Pousada e Clube Serrano",
        "tourism": "hotel",
        "id": "node/6381613113"
      },
      "geometry": {
        "type": "Point",
        "coordinates": [
          -37.9911579,
          -5.0738651
        ]
      }
    },
    {
      "type": "Feature",
      "id": "node/8743674990",
      "properties": {
        "timestamp": "2021-08-12T13:07:43Z",
        "version": 2,
        "changeset": 109574400,
        "addr:street": "Rodovia Izaú Ferreira Maia",
        "name": "Pousada",
        "phone": "+55 88 9 9615 4054",
        "tourism": "hotel",
        "id": "node/8743674990"
      },
      "geometry": {
        "type": "Point",
        "coordinates": [
          -37.9806862,
          -5.0580626
        ]
      }
    }
  ]
}
