{
  "type": "FeatureCollection",
  "features": [
    {
      "type": "Feature",
      "id": "node/5859920958",
      "properties": {
        "timestamp": "2023-01-22T23:23:12Z",
        "version": 3,
        "changeset": 131585120,
        "amenity": "kindergarten",
        "name": "Escola Municipal de Educação Infantil Chapeuzinho Vermelho",
        "id": "node/5859920958"
      },
      "geometry": {
        "type": "Point",
        "coordinates": [
          -50.1339732,
          -29.9717003
        ]
      }
    },
    {
      "type": "Feature",
      "id": "node/10281331146",
      "properties": {
        "timestamp": "2022-12-22T23:05:25Z",
        "version": 1,
        "changeset": 130395684,
        "amenity": "kindergarten",
        "name": "EMEI Peixinho Dourado",
        "id": "node/10281331146"
      },
      "geometry": {
        "type": "Point",
        "coordinates": [
          -50.1064537,
          -29.9155959
        ]
      }
    }
  ]
}
