{
  "type": "FeatureCollection",
  "features": [
    {
      "type": "Feature",
      "id": "node/11547133545",
      "properties": {
        "timestamp": "2024-01-24T18:00:22Z",
        "version": 1,
        "changeset": 146640856,
        "amenity": "health_post",
        "name": "PS Valter Cavalcante Amorim",
        "id": "node/11547133545"
      },
      "geometry": {
        "type": "Point",
        "coordinates": [
          -40.8721733,
          -7.9729571
        ]
      }
    }
  ]
}
