{
  "type": "FeatureCollection",
  "features": [
    {
      "type": "Feature",
      "id": "node/9173516963",
      "properties": {
        "timestamp": "2022-01-31T23:58:25Z",
        "version": 2,
        "changeset": 116844543,
        "amenity": "pharmacy",
        "healthcare": "pharmacy",
        "name": "Farma Coelho - Farmácia de Manipulação",
        "id": "node/9173516963"
      },
      "geometry": {
        "type": "Point",
        "coordinates": [
          -41.1483994,
          -8.1413097
        ]
      }
    },
    {
      "type": "Feature",
      "id": "node/9175533273",
      "properties": {
        "timestamp": "2021-10-15T23:23:55Z",
        "version": 1,
        "changeset": 112562440,
        "amenity": "pharmacy",
        "name": "Farma Alves",
        "id": "node/9175533273"
      },
      "geometry": {
        "type": "Point",
        "coordinates": [
          -41.1327591,
          -8.13661
        ]
      }
    }
  ]
}
