{
  "type": "FeatureCollection",
  "features": [
    {
      "type": "Feature",
      "id": "node/10123848693",
      "properties": {
        "timestamp": "2022-10-23T13:17:54Z",
        "version": 1,
        "changeset": 127957190,
        "name": "Secretaria da Agricultura Municipal",
        "office": "government",
        "id": "node/10123848693"
      },
      "geometry": {
        "type": "Point",
        "coordinates": [
          -54.8368016,
          -28.1186791
        ]
      }
    }
  ]
}
