{
  "type": "FeatureCollection",
  "features": [
    {
      "type": "Feature",
      "id": "node/2661555916",
      "properties": {
        "timestamp": "2014-02-08T17:53:57Z",
        "version": 1,
        "changeset": 20451209,
        "name": "Hotel Rio Pomba",
        "tourism": "hotel",
        "id": "node/2661555916"
      },
      "geometry": {
        "type": "Point",
        "coordinates": [
          -42.183454,
          -21.535411
        ]
      }
    },
    {
      "type": "Feature",
      "id": "node/2661555919",
      "properties": {
        "timestamp": "2014-02-08T17:53:57Z",
        "version": 1,
        "changeset": 20451209,
        "name": "Hotel das Águas",
        "tourism": "hotel",
        "id": "node/2661555919"
      },
      "geometry": {
        "type": "Point",
        "coordinates": [
          -42.1845919,
          -21.5424688
        ]
      }
    },
    {
      "type": "Feature",
      "id": "node/2661555921",
      "properties": {
        "timestamp": "2014-02-08T17:53:57Z",
        "version": 1,
        "changeset": 20451209,
        "name": "Hotel Água Viva",
        "tourism": "hotel",
        "id": "node/2661555921"
      },
      "geometry": {
        "type": "Point",
        "coordinates": [
          -42.1778347,
          -21.5425523
        ]
      }
    },
    {
      "type": "Feature",
      "id": "node/8986792846",
      "properties": {
        "timestamp": "2021-08-06T22:18:54Z",
        "version": 1,
        "changeset": 109286404,
        "addr:city": "Santo Antônio de Pádua",
        "addr:housenumber": "193",
        "addr:street": "Rod. Pres. Joao Goulart",
        "addr:suburb": "Tavares",
        "name": "Hotel Deolinda",
        "tourism": "hotel",
        "id": "node/8986792846"
      },
      "geometry": {
        "type": "Point",
        "coordinates": [
          -42.1783336,
          -21.5422832
        ]
      }
    }
  ]
}
