{
  "type": "FeatureCollection",
  "features": [
    {
      "type": "Feature",
      "id": "node/5060241327",
      "properties": {
        "timestamp": "2017-08-26T13:27:34Z",
        "version": 1,
        "changeset": 51459109,
        "service:bicycle:repair": "yes",
        "shop": "bicycle",
        "id": "node/5060241327"
      },
      "geometry": {
        "type": "Point",
        "coordinates": [
          -57.5479073,
          -30.2076626
        ]
      }
    }
  ]
}
