{
  "type": "FeatureCollection",
  "features": [
    {
      "type": "Feature",
      "id": "node/6470495108",
      "properties": {
        "timestamp": "2019-05-13T16:42:48Z",
        "version": 1,
        "changeset": 70200860,
        "amenity": "cinema",
        "name": "Cine Gama de Colatina",
        "id": "node/6470495108"
      },
      "geometry": {
        "type": "Point",
        "coordinates": [
          -40.6275621,
          -19.5345695
        ]
      }
    }
  ]
}
