{
  "type": "FeatureCollection",
  "features": [
    {
      "type": "Feature",
      "id": "node/10691488200",
      "properties": {
        "timestamp": "2023-02-24T18:57:01Z",
        "version": 1,
        "changeset": 132980717,
        "amenity": "clinic",
        "healthcare": "clinic",
        "name": "policlinica da Amazonia",
        "id": "node/10691488200"
      },
      "geometry": {
        "type": "Point",
        "coordinates": [
          -55.8639781,
          -1.7728052
        ]
      }
    }
  ]
}
