{
  "type": "FeatureCollection",
  "features": [
    {
      "type": "Feature",
      "id": "node/10691420325",
      "properties": {
        "timestamp": "2023-02-25T20:49:40Z",
        "version": 3,
        "changeset": 133021735,
        "addr:city": "oriximiná",
        "addr:housenumber": "3860",
        "addr:postcode": "68270-000",
        "addr:street": "Avenida Sete de Setembro",
        "addr:suburb": "sao jose operario",
        "amenity": "kindergarten",
        "name": "EMEI PLÁCIDA FARIAS DE BRITO",
        "id": "node/10691420325"
      },
      "geometry": {
        "type": "Point",
        "coordinates": [
          -55.8562317,
          -1.7792553
        ]
      }
    }
  ]
}
