{
  "type": "FeatureCollection",
  "features": [
    {
      "type": "Feature",
      "id": "node/5089272126",
      "properties": {
        "timestamp": "2017-09-08T17:02:14Z",
        "version": 1,
        "changeset": 51853105,
        "name": "Pousada Alvorada",
        "name:pt": "Pousada Alvorada",
        "tourism": "guest_house",
        "id": "node/5089272126"
      },
      "geometry": {
        "type": "Point",
        "coordinates": [
          -35.6328642,
          -7.0377606
        ]
      }
    },
    {
      "type": "Feature",
      "id": "node/5089313521",
      "properties": {
        "timestamp": "2017-09-08T17:02:11Z",
        "version": 1,
        "changeset": 51853105,
        "name": "Pousada do Pandeiro",
        "name:pt": "Pousada do Pandeiro",
        "tourism": "guest_house",
        "id": "node/5089313521"
      },
      "geometry": {
        "type": "Point",
        "coordinates": [
          -35.6238878,
          -7.053528
        ]
      }
    },
    {
      "type": "Feature",
      "id": "node/5089313522",
      "properties": {
        "timestamp": "2017-09-08T17:02:15Z",
        "version": 1,
        "changeset": 51853105,
        "name": "Pousada e Restaurante Central",
        "name:pt": "Pousada e Restaurante Central",
        "tourism": "guest_house",
        "id": "node/5089313522"
      },
      "geometry": {
        "type": "Point",
        "coordinates": [
          -35.6332467,
          -7.0374116
        ]
      }
    }
  ]
}
