{
  "type": "FeatureCollection",
  "features": [
    {
      "type": "Feature",
      "id": "node/5489805135",
      "properties": {
        "timestamp": "2021-02-20T07:07:48Z",
        "version": 2,
        "changeset": 99628106,
        "amenity": "clinic",
        "healthcare": "clinic",
        "name": "Dr. Iran Campos",
        "id": "node/5489805135"
      },
      "geometry": {
        "type": "Point",
        "coordinates": [
          -37.7461426,
          -6.3509951
        ]
      }
    }
  ]
}
