{
  "type": "FeatureCollection",
  "features": [
    {
      "type": "Feature",
      "id": "node/1511418802",
      "properties": {
        "timestamp": "2011-11-22T13:05:49Z",
        "version": 2,
        "changeset": 9908737,
        "amenity": "kindergarten",
        "name": "Casa da Criança Ana Neri",
        "id": "node/1511418802"
      },
      "geometry": {
        "type": "Point",
        "coordinates": [
          -38.9602187,
          -12.606349
        ]
      }
    },
    {
      "type": "Feature",
      "id": "node/1511418809",
      "properties": {
        "timestamp": "2017-03-04T13:53:42Z",
        "version": 2,
        "changeset": 46573005,
        "amenity": "kindergarten",
        "name": "Escola Creche Eliza Ferreira Masceno",
        "id": "node/1511418809"
      },
      "geometry": {
        "type": "Point",
        "coordinates": [
          -38.954823,
          -12.6195444
        ]
      }
    },
    {
      "type": "Feature",
      "id": "node/1659977250",
      "properties": {
        "timestamp": "2014-07-23T14:10:05Z",
        "version": 2,
        "changeset": 24312571,
        "amenity": "kindergarten",
        "name": "Creche",
        "id": "node/1659977250"
      },
      "geometry": {
        "type": "Point",
        "coordinates": [
          -38.9614999,
          -12.5987786
        ]
      }
    },
    {
      "type": "Feature",
      "id": "node/1778010093",
      "properties": {
        "timestamp": "2012-06-06T12:46:39Z",
        "version": 1,
        "changeset": 11815496,
        "amenity": "kindergarten",
        "name": "Creche Eulálio Pereira",
        "id": "node/1778010093"
      },
      "geometry": {
        "type": "Point",
        "coordinates": [
          -38.9691766,
          -12.5927267
        ]
      }
    }
  ]
}
