{
  "type": "FeatureCollection",
  "features": [
    {
      "type": "Feature",
      "id": "node/2388652258",
      "properties": {
        "timestamp": "2021-03-07T20:52:37Z",
        "version": 4,
        "changeset": 100591703,
        "addr:city": "Cachoeira",
        "addr:place": "Lar Aconchego",
        "addr:street": "Rua Benjamin Constant",
        "amenity": "nursing_home",
        "name": "Lar Aconchego",
        "id": "node/2388652258"
      },
      "geometry": {
        "type": "Point",
        "coordinates": [
          -38.9617088,
          -12.6050367
        ]
      }
    }
  ]
}
