{
  "type": "FeatureCollection",
  "features": [
    {
      "type": "Feature",
      "id": "node/1800116010",
      "properties": {
        "timestamp": "2021-03-31T13:49:57Z",
        "version": 3,
        "changeset": 102060039,
        "addr:city": "Oiapoque",
        "amenity": "dentist",
        "healthcare": "dentist",
        "name": "Odonto Center",
        "id": "node/1800116010"
      },
      "geometry": {
        "type": "Point",
        "coordinates": [
          -51.8360072,
          3.8475079
        ]
      }
    },
    {
      "type": "Feature",
      "id": "node/5965086293",
      "properties": {
        "timestamp": "2019-07-01T19:43:45Z",
        "version": 5,
        "changeset": 71797560,
        "addr:city": "Oiapoque",
        "amenity": "dentist",
        "healthcare": "dentist",
        "name": "Dentista municipal, Unidade Básica de Saúde de Planalto",
        "operator": "Secretario Municipal de Saúde de Oiapoque",
        "id": "node/5965086293"
      },
      "geometry": {
        "type": "Point",
        "coordinates": [
          -51.8309374,
          3.8413946
        ]
      }
    }
  ]
}
