{
  "type": "FeatureCollection",
  "features": [
    {
      "type": "Feature",
      "id": "node/5809183750",
      "properties": {
        "timestamp": "2019-06-23T16:54:11Z",
        "version": 2,
        "changeset": 71536784,
        "addr:city": "Oiapoque",
        "amenity": "social_facility",
        "name": "DPAC-Fronteira",
        "operator": "ONG DPAC-Fronteira",
        "source": "local visit",
        "id": "node/5809183750"
      },
      "geometry": {
        "type": "Point",
        "coordinates": [
          -51.8299837,
          3.8460957
        ]
      }
    },
    {
      "type": "Feature",
      "id": "node/5923242520",
      "properties": {
        "timestamp": "2020-02-25T19:38:55Z",
        "version": 6,
        "changeset": 81470632,
        "addr:city": "Oiapoque",
        "amenity": "social_facility",
        "name": "Tratamento Fora de Domicilio de Oiapoque",
        "social_facility": "outreach",
        "id": "node/5923242520"
      },
      "geometry": {
        "type": "Point",
        "coordinates": [
          -51.8321568,
          3.8459255
        ]
      }
    },
    {
      "type": "Feature",
      "id": "node/6566256521",
      "properties": {
        "timestamp": "2024-12-19T19:45:23Z",
        "version": 4,
        "changeset": 160408305,
        "addr:city": "Oiapoque",
        "addr:street": "Rua Honório Caetano da Silva",
        "amenity": "social_facility",
        "description": "prevenção da malária",
        "name": "Centro Malakit",
        "operator": "ONG Dpac Fronteira",
        "id": "node/6566256521"
      },
      "geometry": {
        "type": "Point",
        "coordinates": [
          -51.8308295,
          3.8484464
        ]
      }
    }
  ]
}
