{
  "type": "FeatureCollection",
  "features": [
    {
      "type": "Feature",
      "id": "node/4883363121",
      "properties": {
        "timestamp": "2017-05-29T10:47:15Z",
        "version": 1,
        "changeset": 49069460,
        "addr:street": "rua c",
        "amenity": "pharmacy",
        "name": "Cms com representações santos med",
        "name:pt": "Cms com representações santos med",
        "id": "node/4883363121"
      },
      "geometry": {
        "type": "Point",
        "coordinates": [
          -43.210467,
          -12.1797519
        ]
      }
    }
  ]
}
