{
  "type": "FeatureCollection",
  "features": [
    {
      "type": "Feature",
      "id": "node/8630613140",
      "properties": {
        "timestamp": "2021-04-15T01:34:39Z",
        "version": 1,
        "changeset": 102957550,
        "amenity": "arts_centre",
        "name": "CTG Herdeiros da Tradição",
        "id": "node/8630613140"
      },
      "geometry": {
        "type": "Point",
        "coordinates": [
          -54.2104909,
          -29.7067732
        ]
      }
    }
  ]
}
