{
  "type": "FeatureCollection",
  "features": [
    {
      "type": "Feature",
      "id": "node/1262201297",
      "properties": {
        "timestamp": "2021-08-18T01:36:50Z",
        "version": 2,
        "changeset": 109840382,
        "waterway": "waterfall",
        "id": "node/1262201297"
      },
      "geometry": {
        "type": "Point",
        "coordinates": [
          -49.7066415,
          -28.6284644
        ]
      }
    },
    {
      "type": "Feature",
      "id": "node/1262277263",
      "properties": {
        "timestamp": "2021-08-18T01:36:50Z",
        "version": 3,
        "changeset": 109840382,
        "waterway": "waterfall",
        "id": "node/1262277263"
      },
      "geometry": {
        "type": "Point",
        "coordinates": [
          -49.7952892,
          -28.6153463
        ]
      }
    },
    {
      "type": "Feature",
      "id": "node/3983299407",
      "properties": {
        "timestamp": "2019-07-27T22:55:14Z",
        "version": 3,
        "changeset": 72726545,
        "height": "120",
        "name": "Cachoeira do Gelo",
        "waterway": "waterfall",
        "id": "node/3983299407"
      },
      "geometry": {
        "type": "Point",
        "coordinates": [
          -49.8279302,
          -28.6659247
        ]
      }
    },
    {
      "type": "Feature",
      "id": "node/4401374801",
      "properties": {
        "timestamp": "2021-08-18T01:36:54Z",
        "version": 3,
        "changeset": 109840382,
        "waterway": "waterfall",
        "id": "node/4401374801"
      },
      "geometry": {
        "type": "Point",
        "coordinates": [
          -49.8273107,
          -28.6873576
        ]
      }
    },
    {
      "type": "Feature",
      "id": "node/8304582131",
      "properties": {
        "timestamp": "2021-01-08T22:59:36Z",
        "version": 1,
        "changeset": 97194161,
        "name": "Cachoeira do Bizungo",
        "waterway": "waterfall",
        "id": "node/8304582131"
      },
      "geometry": {
        "type": "Point",
        "coordinates": [
          -49.7722828,
          -28.7093715
        ]
      }
    },
    {
      "type": "Feature",
      "id": "node/9015725986",
      "properties": {
        "timestamp": "2021-08-18T01:36:36Z",
        "version": 1,
        "changeset": 109840369,
        "waterway": "waterfall",
        "id": "node/9015725986"
      },
      "geometry": {
        "type": "Point",
        "coordinates": [
          -49.7760627,
          -28.692068
        ]
      }
    }
  ]
}
