{
  "type": "FeatureCollection",
  "features": [
    {
      "type": "Feature",
      "id": "node/6218715358",
      "properties": {
        "timestamp": "2019-01-18T13:33:37Z",
        "version": 1,
        "changeset": 66427245,
        "addr:street": "Rui Barbosa",
        "name": "Secretaria Municipal de Meio Ambiente de Bacabal",
        "office": "government",
        "opening_hours": "Mo-Fr 08:00-14:00",
        "id": "node/6218715358"
      },
      "geometry": {
        "type": "Point",
        "coordinates": [
          -44.7813576,
          -4.2255473
        ]
      }
    }
  ]
}
