{
  "type": "FeatureCollection",
  "features": [
    {
      "type": "Feature",
      "id": "node/2927465558",
      "properties": {
        "timestamp": "2021-08-07T14:35:05Z",
        "version": 3,
        "changeset": 109313254,
        "addr:city": "São Pedro da Aldeia",
        "addr:housenumber": "19",
        "addr:street": "Rua Feliciano Sodré",
        "addr:suburb": "Centro",
        "amenity": "pharmacy",
        "healthcare": "pharmacy",
        "name": "Drogarias Pacheco",
        "id": "node/2927465558"
      },
      "geometry": {
        "type": "Point",
        "coordinates": [
          -42.1025358,
          -22.8375431
        ]
      }
    }
  ]
}
