{
  "type": "FeatureCollection",
  "features": [
    {
      "type": "Feature",
      "id": "node/11049828977",
      "properties": {
        "timestamp": "2023-07-16T19:26:55Z",
        "version": 1,
        "changeset": 138592665,
        "addr:city": "Teixeira de Freitas",
        "addr:housenumber": "143",
        "addr:postcode": "45995-048",
        "addr:street": "Rua Mauá",
        "addr:suburb": "Centro",
        "amenity": "arts_centre",
        "name": "Casa da Cultura de Teixeira de Freitas",
        "phone": "+55 73 3011-2724",
        "id": "node/11049828977"
      },
      "geometry": {
        "type": "Point",
        "coordinates": [
          -39.7476494,
          -17.5352096
        ]
      }
    }
  ]
}
