{
  "type": "FeatureCollection",
  "features": [
    {
      "type": "Feature",
      "id": "node/2722659051",
      "properties": {
        "timestamp": "2014-03-19T02:45:52Z",
        "version": 4,
        "changeset": 21185546,
        "name": "Cachoeira dos Frades",
        "natural": "bare_rock",
        "tourism": "yes",
        "waterway": "waterfall",
        "id": "node/2722659051"
      },
      "geometry": {
        "type": "Point",
        "coordinates": [
          -42.800618,
          -22.3390197
        ]
      }
    },
    {
      "type": "Feature",
      "id": "node/4582033993",
      "properties": {
        "timestamp": "2021-05-05T00:12:36Z",
        "version": 2,
        "changeset": 104150012,
        "waterway": "waterfall",
        "id": "node/4582033993"
      },
      "geometry": {
        "type": "Point",
        "coordinates": [
          -43.0136049,
          -22.4484167
        ]
      }
    },
    {
      "type": "Feature",
      "id": "node/4714144609",
      "properties": {
        "timestamp": "2024-07-11T15:44:38Z",
        "version": 2,
        "changeset": 153817706,
        "name": "Cascata Fischer",
        "waterway": "waterfall",
        "id": "node/4714144609"
      },
      "geometry": {
        "type": "Point",
        "coordinates": [
          -42.9541677,
          -22.3735653
        ]
      }
    },
    {
      "type": "Feature",
      "id": "node/9918062908",
      "properties": {
        "timestamp": "2022-07-29T00:04:51Z",
        "version": 1,
        "changeset": 124207154,
        "name": "Poço Dois Irmãos",
        "waterway": "waterfall",
        "id": "node/9918062908"
      },
      "geometry": {
        "type": "Point",
        "coordinates": [
          -42.9884942,
          -22.4486257
        ]
      }
    }
  ]
}
