{
  "type": "FeatureCollection",
  "features": [
    {
      "type": "Feature",
      "id": "node/7204331256",
      "properties": {
        "timestamp": "2021-08-04T01:51:04Z",
        "version": 2,
        "changeset": 109118384,
        "addr:housenumber": "631",
        "addr:street": "Avenida José Furtado de Macedo",
        "amenity": "hospital",
        "healthcare": "hospital",
        "id": "node/7204331256"
      },
      "geometry": {
        "type": "Point",
        "coordinates": [
          -38.4612575,
          -5.4591374
        ]
      }
    }
  ]
}
