{
  "type": "FeatureCollection",
  "features": [
    {
      "type": "Feature",
      "id": "node/10465863111",
      "properties": {
        "timestamp": "2023-01-13T01:38:45Z",
        "version": 3,
        "changeset": 131210302,
        "name": "Cachoeira Várzea Bonita",
        "waterway": "waterfall",
        "id": "node/10465863111"
      },
      "geometry": {
        "type": "Point",
        "coordinates": [
          -51.8479932,
          -28.1767073
        ]
      }
    }
  ]
}
