{
  "type": "FeatureCollection",
  "features": [
    {
      "type": "Feature",
      "id": "node/9693934297",
      "properties": {
        "timestamp": "2022-04-25T23:27:08Z",
        "version": 1,
        "changeset": 120186850,
        "name": "Flor de Mandacaru",
        "source": "survey",
        "tourism": "guest_house",
        "id": "node/9693934297"
      },
      "geometry": {
        "type": "Point",
        "coordinates": [
          -36.1389966,
          -7.4797694
        ]
      }
    }
  ]
}
