{
  "type": "FeatureCollection",
  "features": [
    {
      "type": "Feature",
      "id": "node/12112539727",
      "properties": {
        "timestamp": "2024-08-15T12:53:59Z",
        "version": 1,
        "changeset": 155281853,
        "amenity": "library",
        "name": "Biblioteca Universitária de Amargosa",
        "id": "node/12112539727"
      },
      "geometry": {
        "type": "Point",
        "coordinates": [
          -39.613424,
          -13.022776
        ]
      }
    }
  ]
}
