{
  "type": "FeatureCollection",
  "features": [
    {
      "type": "Feature",
      "id": "node/9053515590",
      "properties": {
        "timestamp": "2021-09-01T13:24:19Z",
        "version": 1,
        "changeset": 110568055,
        "addr:housenumber": "3",
        "addr:street": "Rua do Cruzeiro",
        "amenity": "pharmacy",
        "name": "Farmácia Palhano",
        "id": "node/9053515590"
      },
      "geometry": {
        "type": "Point",
        "coordinates": [
          -37.960186,
          -4.7444377
        ]
      }
    }
  ]
}
