{
  "type": "FeatureCollection",
  "features": [
    {
      "type": "Feature",
      "id": "node/10280577521",
      "properties": {
        "timestamp": "2022-12-22T15:29:05Z",
        "version": 1,
        "changeset": 130381581,
        "amenity": "social_facility",
        "name": "Abrigo de idosos sagrado coração de jesus",
        "social_facility": "nursing_home",
        "social_facility:for": "senior",
        "id": "node/10280577521"
      },
      "geometry": {
        "type": "Point",
        "coordinates": [
          -37.1189799,
          -9.1092667
        ]
      }
    }
  ]
}
