{
  "type": "FeatureCollection",
  "features": [
    {
      "type": "Feature",
      "id": "node/4154563091",
      "properties": {
        "timestamp": "2016-04-29T00:46:35Z",
        "version": 1,
        "changeset": 38970398,
        "amenity": "drinking_water",
        "name": "Parque das águas",
        "id": "node/4154563091"
      },
      "geometry": {
        "type": "Point",
        "coordinates": [
          -45.3504914,
          -21.9759024
        ]
      }
    }
  ]
}
