{
  "type": "FeatureCollection",
  "features": [
    {
      "type": "Feature",
      "id": "node/5506765423",
      "properties": {
        "timestamp": "2018-03-26T22:25:15Z",
        "version": 1,
        "changeset": 57550475,
        "name": "Hotel Papa Léguas",
        "tourism": "hotel",
        "id": "node/5506765423"
      },
      "geometry": {
        "type": "Point",
        "coordinates": [
          -38.5242916,
          -6.8967589
        ]
      }
    },
    {
      "type": "Feature",
      "id": "node/5514324224",
      "properties": {
        "timestamp": "2018-03-29T14:37:11Z",
        "version": 1,
        "changeset": 57635930,
        "name": "Mondrian Hotel",
        "tourism": "hotel",
        "id": "node/5514324224"
      },
      "geometry": {
        "type": "Point",
        "coordinates": [
          -38.5814798,
          -6.9217124
        ]
      }
    },
    {
      "type": "Feature",
      "id": "node/10839821705",
      "properties": {
        "timestamp": "2023-04-25T14:09:23Z",
        "version": 1,
        "changeset": 135345733,
        "name": "Gravatá Flat Hotel",
        "tourism": "hotel",
        "id": "node/10839821705"
      },
      "geometry": {
        "type": "Point",
        "coordinates": [
          -38.5605645,
          -6.8923474
        ]
      }
    }
  ]
}
