{
  "type": "FeatureCollection",
  "features": [
    {
      "type": "Feature",
      "id": "node/5932831650",
      "properties": {
        "timestamp": "2018-09-26T22:25:13Z",
        "version": 1,
        "changeset": 62960214,
        "amenity": "cinema",
        "name": "Cinevip.com",
        "id": "node/5932831650"
      },
      "geometry": {
        "type": "Point",
        "coordinates": [
          -54.6079622,
          -16.472105
        ]
      }
    }
  ]
}
