{
  "type": "FeatureCollection",
  "features": [
    {
      "type": "Feature",
      "id": "node/3361589459",
      "properties": {
        "timestamp": "2015-02-20T11:58:12Z",
        "version": 1,
        "changeset": 28975871,
        "addr:city": "Piratini",
        "addr:street": "Praça da República Rio-Grandense",
        "historic": "monument",
        "name": "Obelisco ao Centenário Farroupilha",
        "id": "node/3361589459"
      },
      "geometry": {
        "type": "Point",
        "coordinates": [
          -53.1039377,
          -31.448593
        ]
      }
    }
  ]
}
