{
  "type": "FeatureCollection",
  "features": [
    {
      "type": "Feature",
      "id": "node/5764337924",
      "properties": {
        "timestamp": "2018-07-17T17:31:39Z",
        "version": 3,
        "changeset": 60808497,
        "amenity": "social_facility",
        "name": "CRAS Insurreição",
        "id": "node/5764337924"
      },
      "geometry": {
        "type": "Point",
        "coordinates": [
          -35.6781077,
          -8.2123334
        ]
      }
    }
  ]
}
