{
  "type": "FeatureCollection",
  "features": [
    {
      "type": "Feature",
      "id": "node/5300819338",
      "properties": {
        "timestamp": "2019-09-24T18:07:56Z",
        "version": 2,
        "changeset": 74871804,
        "historic": "monument",
        "monument": "crist",
        "name": "Estátua do Cristo",
        "id": "node/5300819338"
      },
      "geometry": {
        "type": "Point",
        "coordinates": [
          -45.9082037,
          -21.6756534
        ]
      }
    },
    {
      "type": "Feature",
      "id": "node/5309536584",
      "properties": {
        "timestamp": "2019-09-09T14:10:04Z",
        "version": 2,
        "changeset": 74266086,
        "historic": "monument",
        "name": "CIC",
        "id": "node/5309536584"
      },
      "geometry": {
        "type": "Point",
        "coordinates": [
          -45.9216505,
          -21.6765275
        ]
      }
    },
    {
      "type": "Feature",
      "id": "node/5309536585",
      "properties": {
        "timestamp": "2017-12-29T02:25:24Z",
        "version": 1,
        "changeset": 54998719,
        "historic": "monument",
        "name": "Homenagem ao Cônego Walter Maria Pulcinelli",
        "id": "node/5309536585"
      },
      "geometry": {
        "type": "Point",
        "coordinates": [
          -45.9215003,
          -21.6763854
        ]
      }
    },
    {
      "type": "Feature",
      "id": "node/5309536586",
      "properties": {
        "timestamp": "2019-09-09T14:10:04Z",
        "version": 2,
        "changeset": 74266086,
        "historic": "monument",
        "id": "node/5309536586"
      },
      "geometry": {
        "type": "Point",
        "coordinates": [
          -45.922148,
          -21.6757903
        ]
      }
    }
  ]
}
