{
  "type": "FeatureCollection",
  "features": [
    {
      "type": "Feature",
      "id": "node/7527631934",
      "properties": {
        "timestamp": "2020-05-16T23:25:53Z",
        "version": 1,
        "changeset": 85319624,
        "name": "Pousada Paraíso",
        "tourism": "hotel",
        "id": "node/7527631934"
      },
      "geometry": {
        "type": "Point",
        "coordinates": [
          -45.534526,
          -23.2787348
        ]
      }
    }
  ]
}
