{
  "type": "FeatureCollection",
  "features": [
    {
      "type": "Feature",
      "id": "node/8410113070",
      "properties": {
        "timestamp": "2021-02-09T22:05:54Z",
        "version": 1,
        "changeset": 99001841,
        "addr:housenumber": "300",
        "addr:postcode": "36424-000",
        "addr:street": "Rua João Costa",
        "government": "register_office",
        "name": "Cartório de Registro Civil",
        "office": "government",
        "id": "node/8410113070"
      },
      "geometry": {
        "type": "Point",
        "coordinates": [
          -43.8738458,
          -20.7408317
        ]
      }
    }
  ]
}
