{
  "type": "FeatureCollection",
  "features": [
    {
      "type": "Feature",
      "id": "node/3958093417",
      "properties": {
        "timestamp": "2022-07-25T00:37:17Z",
        "version": 5,
        "changeset": 124027853,
        "addr:housenumber": "141",
        "addr:street": "Rua Blumenau",
        "addr:suburb": "Centro",
        "contact:email": "reservas@timbopark.com.br",
        "contact:phone": "+55 47 3281-0700;+55 47 99293-6795",
        "contact:website": "http://www.timbopark.com.br/",
        "name": "Timbó Park Hotel",
        "tourism": "hotel",
        "id": "node/3958093417"
      },
      "geometry": {
        "type": "Point",
        "coordinates": [
          -49.2742999,
          -26.8293194
        ]
      }
    }
  ]
}
