{
  "type": "FeatureCollection",
  "features": [
    {
      "type": "Feature",
      "id": "node/3705257149",
      "properties": {
        "timestamp": "2022-10-11T19:29:49Z",
        "version": 5,
        "changeset": 127377625,
        "government": "legislative",
        "name": "Câmara de Vereadores de Santa Terezinha do Progresso",
        "office": "government",
        "id": "node/3705257149"
      },
      "geometry": {
        "type": "Point",
        "coordinates": [
          -53.1979089,
          -26.6195336
        ]
      }
    },
    {
      "type": "Feature",
      "id": "node/3705281438",
      "properties": {
        "timestamp": "2017-04-07T21:49:56Z",
        "version": 2,
        "changeset": 47553657,
        "name": "Centro Municipal da Agricultura",
        "office": "government",
        "id": "node/3705281438"
      },
      "geometry": {
        "type": "Point",
        "coordinates": [
          -53.1996305,
          -26.6190793
        ]
      }
    }
  ]
}
