{
  "type": "FeatureCollection",
  "features": [
    {
      "type": "Feature",
      "id": "node/3708709255",
      "properties": {
        "timestamp": "2021-04-16T18:36:19Z",
        "version": 2,
        "changeset": 103075689,
        "amenity": "library",
        "name": "Biblioteca Pública Municipal de Santa Terezinha do Progresso",
        "id": "node/3708709255"
      },
      "geometry": {
        "type": "Point",
        "coordinates": [
          -53.1995712,
          -26.6193773
        ]
      }
    }
  ]
}
