{
  "type": "FeatureCollection",
  "features": [
    {
      "type": "Feature",
      "id": "node/3708708671",
      "properties": {
        "timestamp": "2015-08-22T17:35:29Z",
        "version": 2,
        "changeset": 33508379,
        "amenity": "social_facility",
        "building": "yes",
        "name": "CRAS",
        "id": "node/3708708671"
      },
      "geometry": {
        "type": "Point",
        "coordinates": [
          -53.2026933,
          -26.6199
        ]
      }
    }
  ]
}
