{
  "type": "FeatureCollection",
  "features": [
    {
      "type": "Feature",
      "id": "node/5380534679",
      "properties": {
        "timestamp": "2018-03-22T23:48:09Z",
        "version": 2,
        "changeset": 57441022,
        "addr:city": "Videira",
        "addr:postcode": "89560-000",
        "addr:suburb": "Centro",
        "amenity": "cinema",
        "name": "Cinema Grupo Cine",
        "id": "node/5380534679"
      },
      "geometry": {
        "type": "Point",
        "coordinates": [
          -51.1537886,
          -27.0051965
        ]
      }
    }
  ]
}
