{
  "type": "FeatureCollection",
  "features": [
    {
      "type": "Feature",
      "id": "node/4976248422",
      "properties": {
        "timestamp": "2023-04-28T01:44:25Z",
        "version": 4,
        "changeset": 135447990,
        "amenity": "dentist",
        "healthcare": "dentist",
        "name": "Odonto Logia",
        "name:pt": "Odonto Logia",
        "id": "node/4976248422"
      },
      "geometry": {
        "type": "Point",
        "coordinates": [
          -37.8188823,
          -7.5377854
        ]
      }
    }
  ]
}
