{
  "type": "FeatureCollection",
  "features": [
    {
      "type": "Feature",
      "id": "node/10882058496",
      "properties": {
        "timestamp": "2023-05-09T22:29:12Z",
        "version": 1,
        "changeset": 135913437,
        "access": "yes",
        "historic": "monument",
        "inscription": "Homenagem a passagem da Coluna Prestes por Carnaíba em 1926.",
        "name": "Monumento Resistência",
        "id": "node/10882058496"
      },
      "geometry": {
        "type": "Point",
        "coordinates": [
          -37.7933489,
          -7.8030112
        ]
      }
    }
  ]
}
