{
  "type": "FeatureCollection",
  "features": [
    {
      "type": "Feature",
      "id": "node/4750794062",
      "properties": {
        "timestamp": "2025-01-08T04:47:31Z",
        "version": 2,
        "changeset": 161119207,
        "amenity": "community_centre",
        "name": "Sociedade Amigos do Bairro do Bom Jardim e Campo Verde",
        "id": "node/4750794062"
      },
      "geometry": {
        "type": "Point",
        "coordinates": [
          -46.018274,
          -22.7859956
        ]
      }
    }
  ]
}
