{
  "type": "FeatureCollection",
  "features": [
    {
      "type": "Feature",
      "id": "node/4750794062",
      "properties": {
        "timestamp": "2017-03-23T11:44:29Z",
        "version": 1,
        "changeset": 47094873,
        "amenity": "community_centre",
        "name": "Sociedade Amigos do Bairro do Bom Jardim e Campo Verde",
        "id": "node/4750794062"
      },
      "geometry": {
        "type": "Point",
        "coordinates": [
          -46.0182338,
          -22.7860117
        ]
      }
    }
  ]
}
