{
  "type": "FeatureCollection",
  "features": [
    {
      "type": "Feature",
      "id": "node/4635264963",
      "properties": {
        "timestamp": "2017-01-26T18:17:37Z",
        "version": 1,
        "changeset": 45522533,
        "addr:city": "Conceição das Alagoas",
        "addr:housenumber": "633",
        "addr:street": "Rua Doze de Outubro",
        "addr:suburb": "Centro",
        "amenity": "nursing_home",
        "name": "Lar do Idoso Sociedade São Vicente de Paulo",
        "phone": "+55 34 3321 1202",
        "id": "node/4635264963"
      },
      "geometry": {
        "type": "Point",
        "coordinates": [
          -48.3876407,
          -19.9107719
        ]
      }
    }
  ]
}
