{
  "type": "FeatureCollection",
  "features": [
    {
      "type": "Feature",
      "id": "node/3999139410",
      "properties": {
        "timestamp": "2016-02-10T13:37:09Z",
        "version": 1,
        "changeset": 37124622,
        "addr:city": "Bom Jesus do Norte",
        "addr:postcode": "29460-000",
        "addr:street": "Avenida Luciano Fraga",
        "addr:suburb": "Vista Alegre",
        "alt_name": "Centro de Referência de Assistência Social",
        "amenity": "social_facility",
        "contact:phone": "(28) 3562-2053",
        "name": "CRAS - Bom Jesus do Norte",
        "social_facility": "outreach",
        "source": "IJSN",
        "id": "node/3999139410"
      },
      "geometry": {
        "type": "Point",
        "coordinates": [
          -41.6659947,
          -21.1194201
        ]
      }
    },
    {
      "type": "Feature",
      "id": "node/10003307452",
      "properties": {
        "timestamp": "2022-09-06T02:46:38Z",
        "version": 1,
        "changeset": 125836065,
        "addr:city": "Bom Jesus do Norte",
        "addr:postcode": "29460-000",
        "addr:street": "Rua Anizio Pereira da Silva",
        "addr:suburb": "Vista Alegre",
        "amenity": "social_facility",
        "name": "Lar dos Idosos Padre Gabriel",
        "operator": "Associação Lar dos Idosos Padre Gabriel",
        "operator:type": "private",
        "phone": "+55 28 3562 1513",
        "social_facility": "group_home",
        "social_facility:for": "senior",
        "wheelchair": "yes",
        "id": "node/10003307452"
      },
      "geometry": {
        "type": "Point",
        "coordinates": [
          -41.664724,
          -21.120438
        ]
      }
    }
  ]
}
