{
  "type": "FeatureCollection",
  "features": [
    {
      "type": "Feature",
      "id": "node/5788496662",
      "properties": {
        "timestamp": "2018-07-27T03:19:10Z",
        "version": 1,
        "changeset": 61105755,
        "amenity": "cinema",
        "contact:phone": "+55 47 3035-8654",
        "name": "Cine Gracher",
        "id": "node/5788496662"
      },
      "geometry": {
        "type": "Point",
        "coordinates": [
          -49.2229342,
          -26.8709025
        ]
      }
    }
  ]
}
