{
  "type": "FeatureCollection",
  "features": [
    {
      "type": "Feature",
      "id": "node/3774567670",
      "properties": {
        "timestamp": "2019-03-29T23:46:49Z",
        "version": 3,
        "changeset": 68682712,
        "addr:city": "Itacoatiara",
        "addr:housenumber": "259",
        "addr:postcode": "69100-143",
        "addr:street": "Rua Floriano Peixoto",
        "addr:suburb": "Colonia",
        "name": "Christian Hotel",
        "smoking": "no",
        "tourism": "hotel",
        "id": "node/3774567670"
      },
      "geometry": {
        "type": "Point",
        "coordinates": [
          -58.4498804,
          -3.1447735
        ]
      }
    },
    {
      "type": "Feature",
      "id": "node/6340612885",
      "properties": {
        "timestamp": "2019-03-15T21:06:39Z",
        "version": 1,
        "changeset": 68189628,
        "name": "Pousada",
        "tourism": "hotel",
        "id": "node/6340612885"
      },
      "geometry": {
        "type": "Point",
        "coordinates": [
          -58.7173217,
          -3.1248741
        ]
      }
    },
    {
      "type": "Feature",
      "id": "node/6366409049",
      "properties": {
        "timestamp": "2019-03-28T00:39:57Z",
        "version": 1,
        "changeset": 68607898,
        "name": "Regine's Hotel",
        "tourism": "hotel",
        "id": "node/6366409049"
      },
      "geometry": {
        "type": "Point",
        "coordinates": [
          -58.4465196,
          -3.1419884
        ]
      }
    },
    {
      "type": "Feature",
      "id": "node/6371268014",
      "properties": {
        "timestamp": "2019-03-29T23:46:48Z",
        "version": 1,
        "changeset": 68682712,
        "name": "Serpa Hotel",
        "tourism": "hotel",
        "id": "node/6371268014"
      },
      "geometry": {
        "type": "Point",
        "coordinates": [
          -58.4500298,
          -3.1450035
        ]
      }
    }
  ]
}
