{
  "type": "FeatureCollection",
  "features": [
    {
      "type": "Feature",
      "id": "node/3332942819",
      "properties": {
        "timestamp": "2015-02-05T22:34:42Z",
        "version": 2,
        "changeset": 28641329,
        "amenity": "cinema",
        "name": "Cine Teatro Matão",
        "id": "node/3332942819"
      },
      "geometry": {
        "type": "Point",
        "coordinates": [
          -48.3662333,
          -21.6015485
        ]
      }
    }
  ]
}
