{
  "type": "FeatureCollection",
  "features": [
    {
      "type": "Feature",
      "id": "node/5809225955",
      "properties": {
        "timestamp": "2022-09-09T21:34:51Z",
        "version": 3,
        "changeset": 125996968,
        "addr:street": "Rua Pinheiro Machado",
        "amenity": "social_facility",
        "name": "CAPS",
        "id": "node/5809225955"
      },
      "geometry": {
        "type": "Point",
        "coordinates": [
          -51.0165978,
          -26.7827904
        ]
      }
    }
  ]
}
