{
  "type": "FeatureCollection",
  "features": [
    {
      "type": "Feature",
      "id": "node/5577506034",
      "properties": {
        "timestamp": "2018-04-25T01:33:53Z",
        "version": 1,
        "changeset": 58393358,
        "amenity": "hospital",
        "healthcare": "hospital",
        "name": "Hospital e Matenidade Geraldo Lacerda Botelho",
        "id": "node/5577506034"
      },
      "geometry": {
        "type": "Point",
        "coordinates": [
          -39.2763654,
          -7.0399113
        ]
      }
    }
  ]
}
