{
  "type": "FeatureCollection",
  "features": [
    {
      "type": "Feature",
      "id": "node/6379855787",
      "properties": {
        "timestamp": "2019-04-03T00:38:00Z",
        "version": 1,
        "changeset": 68817992,
        "amenity": "pharmacy",
        "dispensing": "yes",
        "healthcare": "pharmacy",
        "name": "farmacia madre paulina",
        "id": "node/6379855787"
      },
      "geometry": {
        "type": "Point",
        "coordinates": [
          -39.2832218,
          -7.0414133
        ]
      }
    }
  ]
}
