{
  "type": "FeatureCollection",
  "features": [
    {
      "type": "Feature",
      "id": "node/4711635656",
      "properties": {
        "timestamp": "2024-08-19T01:40:03Z",
        "version": 3,
        "changeset": 155439212,
        "name": "Cascata Perau da Nega",
        "natural": "cliff",
        "tourism": "attraction",
        "waterway": "waterfall",
        "id": "node/4711635656"
      },
      "geometry": {
        "type": "Point",
        "coordinates": [
          -52.443038,
          -29.3379671
        ]
      }
    },
    {
      "type": "Feature",
      "id": "node/4711635717",
      "properties": {
        "timestamp": "2024-08-19T01:40:03Z",
        "version": 3,
        "changeset": 155439212,
        "name": "Cascata Fischer",
        "source": "Bing",
        "tourism": "attraction",
        "waterway": "waterfall",
        "id": "node/4711635717"
      },
      "geometry": {
        "type": "Point",
        "coordinates": [
          -52.4467339,
          -29.3532141
        ]
      }
    },
    {
      "type": "Feature",
      "id": "node/4711638904",
      "properties": {
        "timestamp": "2024-08-19T01:40:03Z",
        "version": 4,
        "changeset": 155439212,
        "name": "Cascata Gamelão",
        "source": "Bing",
        "tourism": "attraction",
        "waterway": "waterfall",
        "id": "node/4711638904"
      },
      "geometry": {
        "type": "Point",
        "coordinates": [
          -52.4482301,
          -29.3012334
        ]
      }
    },
    {
      "type": "Feature",
      "id": "node/8694885598",
      "properties": {
        "timestamp": "2023-04-04T18:42:58Z",
        "version": 2,
        "changeset": 134509023,
        "name": "Cascata da Trovão",
        "waterway": "waterfall",
        "id": "node/8694885598"
      },
      "geometry": {
        "type": "Point",
        "coordinates": [
          -52.2948042,
          -29.2892752
        ]
      }
    },
    {
      "type": "Feature",
      "id": "node/11533911177",
      "properties": {
        "timestamp": "2024-01-20T13:22:09Z",
        "version": 1,
        "changeset": 146478844,
        "waterway": "waterfall",
        "id": "node/11533911177"
      },
      "geometry": {
        "type": "Point",
        "coordinates": [
          -52.2974444,
          -29.3485556
        ]
      }
    }
  ]
}
