{
  "type": "FeatureCollection",
  "features": [
    {
      "type": "Feature",
      "id": "node/4711635656",
      "properties": {
        "timestamp": "2017-12-24T19:05:34Z",
        "version": 2,
        "changeset": 54893750,
        "name": "Cascata Perau da Nega",
        "natural": "cliff",
        "tourism": "attraction",
        "waterway": "waterfall",
        "id": "node/4711635656"
      },
      "geometry": {
        "type": "Point",
        "coordinates": [
          -52.4429736,
          -29.3380478
        ]
      }
    },
    {
      "type": "Feature",
      "id": "node/4711635717",
      "properties": {
        "timestamp": "2017-12-24T19:29:47Z",
        "version": 2,
        "changeset": 54894218,
        "name": "Cascata Fischer",
        "source": "Bing",
        "tourism": "attraction",
        "waterway": "waterfall",
        "id": "node/4711635717"
      },
      "geometry": {
        "type": "Point",
        "coordinates": [
          -52.4466132,
          -29.3533801
        ]
      }
    },
    {
      "type": "Feature",
      "id": "node/4711638904",
      "properties": {
        "timestamp": "2020-06-05T14:32:06Z",
        "version": 3,
        "changeset": 86249660,
        "name": "Cascata Gamelão",
        "source": "Bing",
        "tourism": "attraction",
        "waterway": "waterfall",
        "id": "node/4711638904"
      },
      "geometry": {
        "type": "Point",
        "coordinates": [
          -52.4481621,
          -29.3014343
        ]
      }
    },
    {
      "type": "Feature",
      "id": "node/8694885598",
      "properties": {
        "timestamp": "2023-04-04T18:42:58Z",
        "version": 2,
        "changeset": 134509023,
        "name": "Cascata da Trovão",
        "waterway": "waterfall",
        "id": "node/8694885598"
      },
      "geometry": {
        "type": "Point",
        "coordinates": [
          -52.2948042,
          -29.2892752
        ]
      }
    },
    {
      "type": "Feature",
      "id": "node/11533911177",
      "properties": {
        "timestamp": "2024-01-20T13:22:09Z",
        "version": 1,
        "changeset": 146478844,
        "waterway": "waterfall",
        "id": "node/11533911177"
      },
      "geometry": {
        "type": "Point",
        "coordinates": [
          -52.2974444,
          -29.3485556
        ]
      }
    }
  ]
}
