{
  "type": "FeatureCollection",
  "features": [
    {
      "type": "Feature",
      "id": "node/7946397629",
      "properties": {
        "timestamp": "2023-12-27T19:59:54Z",
        "version": 2,
        "changeset": 145590661,
        "access": "yes",
        "historic": "monument",
        "name": "Monumento das Bençãos",
        "id": "node/7946397629"
      },
      "geometry": {
        "type": "Point",
        "coordinates": [
          -49.121008,
          -16.6805937
        ]
      }
    }
  ]
}
