{
  "type": "FeatureCollection",
  "features": [
    {
      "type": "Feature",
      "id": "node/7946397629",
      "properties": {
        "timestamp": "2020-09-27T00:06:46Z",
        "version": 1,
        "changeset": 91566326,
        "historic": "monument",
        "name": "Monumento das Bençãos",
        "id": "node/7946397629"
      },
      "geometry": {
        "type": "Point",
        "coordinates": [
          -49.1210074,
          -16.6806302
        ]
      }
    }
  ]
}
