{
  "type": "FeatureCollection",
  "features": [
    {
      "type": "Feature",
      "id": "node/2626923468",
      "properties": {
        "timestamp": "2014-04-20T13:35:10Z",
        "version": 2,
        "changeset": 21815886,
        "amenity": "pharmacy",
        "name": "ROSAFARMA",
        "operator": "Douglas e Kelly",
        "id": "node/2626923468"
      },
      "geometry": {
        "type": "Point",
        "coordinates": [
          -48.9321569,
          -20.0175102
        ]
      }
    },
    {
      "type": "Feature",
      "id": "node/2626953597",
      "properties": {
        "timestamp": "2014-01-18T12:34:01Z",
        "version": 1,
        "changeset": 20065343,
        "amenity": "pharmacy",
        "name": "Americana",
        "id": "node/2626953597"
      },
      "geometry": {
        "type": "Point",
        "coordinates": [
          -48.9379397,
          -20.0244988
        ]
      }
    }
  ]
}
