{
  "type": "FeatureCollection",
  "features": [
    {
      "type": "Feature",
      "id": "node/8439547214",
      "properties": {
        "timestamp": "2021-02-20T00:19:40Z",
        "version": 1,
        "changeset": 99622159,
        "amenity": "clinic",
        "healthcare": "clinic",
        "name": "Posto de Saúde",
        "operator": "SUS",
        "operator:type": "public",
        "id": "node/8439547214"
      },
      "geometry": {
        "type": "Point",
        "coordinates": [
          -47.7701865,
          -21.0213971
        ]
      }
    }
  ]
}
