{
  "type": "FeatureCollection",
  "features": [
    {
      "type": "Feature",
      "id": "node/7968572985",
      "properties": {
        "timestamp": "2020-10-03T11:45:51Z",
        "version": 1,
        "changeset": 91899381,
        "amenity": "pharmacy",
        "name": "Farmacia Santo Angelo",
        "opening_hours": "24/7",
        "id": "node/7968572985"
      },
      "geometry": {
        "type": "Point",
        "coordinates": [
          -56.2692305,
          -11.3073476
        ]
      }
    }
  ]
}
