{
  "type": "FeatureCollection",
  "features": [
    {
      "type": "Feature",
      "id": "node/12716943081",
      "properties": {
        "timestamp": "2025-03-31T19:26:34Z",
        "version": 1,
        "changeset": 164345793,
        "addr:city": "Nossa Senhora de Lourdes",
        "addr:postcode": "49890-000",
        "addr:street": "Avenida Senador Leite Neto",
        "addr:suburb": "Centro",
        "amenity": "library",
        "name": "Biblioteca Municipal Professora Lindinalva Rodrigues de Oliveira",
        "operator": "Município de Nossa Senhora de Lourdes",
        "id": "node/12716943081"
      },
      "geometry": {
        "type": "Point",
        "coordinates": [
          -37.0568824,
          -10.0784672
        ]
      }
    }
  ]
}
