{
  "type": "FeatureCollection",
  "features": [
    {
      "type": "Feature",
      "id": "node/8732559376",
      "properties": {
        "timestamp": "2021-05-17T10:03:38Z",
        "version": 2,
        "changeset": 104816155,
        "addr:city": "Nossa Senhora de Lourdes",
        "name": "Cachoeira Poção de Pedras",
        "waterway": "waterfall",
        "id": "node/8732559376"
      },
      "geometry": {
        "type": "Point",
        "coordinates": [
          -37.0080285,
          -10.0808677
        ]
      }
    }
  ]
}
