{
  "type": "FeatureCollection",
  "features": [
    {
      "type": "Feature",
      "id": "node/5278568960",
      "properties": {
        "timestamp": "2017-12-11T22:22:49Z",
        "version": 1,
        "changeset": 54551879,
        "historic": "monument",
        "name": "Cristo Redentor",
        "id": "node/5278568960"
      },
      "geometry": {
        "type": "Point",
        "coordinates": [
          -37.9450981,
          -11.80454
        ]
      }
    }
  ]
}
