{
  "type": "FeatureCollection",
  "features": [
    {
      "type": "Feature",
      "id": "node/6176656009",
      "properties": {
        "timestamp": "2021-10-18T14:45:04Z",
        "version": 3,
        "changeset": 112656341,
        "access": "private",
        "amenity": "community_centre",
        "community_centre": "events_venue",
        "description": "Espaço de aluguel para festas",
        "name": "Espaço Yellow Bee",
        "id": "node/6176656009"
      },
      "geometry": {
        "type": "Point",
        "coordinates": [
          -52.8597476,
          -26.3528777
        ]
      }
    },
    {
      "type": "Feature",
      "id": "node/6176966894",
      "properties": {
        "timestamp": "2021-10-18T14:45:04Z",
        "version": 2,
        "changeset": 112656341,
        "addr:city": "Vitorino",
        "addr:postcode": "85520-000",
        "addr:suburb": "Araucária",
        "amenity": "community_centre",
        "name": "Associação Vila Maria",
        "id": "node/6176966894"
      },
      "geometry": {
        "type": "Point",
        "coordinates": [
          -52.8722114,
          -26.352155
        ]
      }
    },
    {
      "type": "Feature",
      "id": "node/8685658217",
      "properties": {
        "timestamp": "2021-04-30T20:06:02Z",
        "version": 1,
        "changeset": 103933731,
        "amenity": "community_centre",
        "name": "São Braz - Vitorino",
        "id": "node/8685658217"
      },
      "geometry": {
        "type": "Point",
        "coordinates": [
          -52.8643405,
          -26.2995127
        ]
      }
    }
  ]
}
