{
  "type": "FeatureCollection",
  "features": [
    {
      "type": "Feature",
      "id": "node/8636271435",
      "properties": {
        "timestamp": "2022-08-28T23:37:58Z",
        "version": 2,
        "changeset": 125498238,
        "amenity": "library",
        "fixme": "verificar localização",
        "name": "Biblioteca Pública Municipal Gilberto Santos Dumont",
        "id": "node/8636271435"
      },
      "geometry": {
        "type": "Point",
        "coordinates": [
          -51.660659,
          -27.069462
        ]
      }
    }
  ]
}
