{
  "type": "FeatureCollection",
  "features": [
    {
      "type": "Feature",
      "id": "node/1341272385",
      "properties": {
        "timestamp": "2011-06-27T16:05:35Z",
        "version": 1,
        "changeset": 8563526,
        "amenity": "school",
        "name": "Escola Municipal Monsenhor Afonso Ligório Rosa",
        "id": "node/1341272385"
      },
      "geometry": {
        "type": "Point",
        "coordinates": [
          -46.0217504,
          -22.6300787
        ]
      }
    }
  ]
}
