{
  "type": "FeatureCollection",
  "features": [
    {
      "type": "Feature",
      "id": "node/5129130374",
      "properties": {
        "timestamp": "2017-09-25T18:37:04Z",
        "version": 1,
        "changeset": 52363981,
        "historic": "monument",
        "name": "Cristo Redentor",
        "id": "node/5129130374"
      },
      "geometry": {
        "type": "Point",
        "coordinates": [
          -48.8116094,
          -20.797377
        ]
      }
    }
  ]
}
