{
  "type": "FeatureCollection",
  "features": [
    {
      "type": "Feature",
      "id": "node/2673618371",
      "properties": {
        "timestamp": "2014-02-15T21:56:15Z",
        "version": 1,
        "changeset": 20585765,
        "amenity": "hospital",
        "name": "Posto de Saude",
        "id": "node/2673618371"
      },
      "geometry": {
        "type": "Point",
        "coordinates": [
          -35.4267883,
          -6.7813091
        ]
      }
    }
  ]
}
