{
  "type": "FeatureCollection",
  "features": [
    {
      "type": "Feature",
      "id": "node/8636242001",
      "properties": {
        "timestamp": "2021-04-16T18:19:44Z",
        "version": 1,
        "changeset": 103075689,
        "amenity": "library",
        "name": "Biblioteca Pública Municipal Domingos Pascoal Cegalla",
        "id": "node/8636242001"
      },
      "geometry": {
        "type": "Point",
        "coordinates": [
          -49.734078,
          -27.223547
        ]
      }
    }
  ]
}
