{
  "type": "FeatureCollection",
  "features": [
    {
      "type": "Feature",
      "id": "node/6380826037",
      "properties": {
        "timestamp": "2019-04-03T13:05:13Z",
        "version": 1,
        "changeset": 68837925,
        "description": "Monumento de um índio (representando os nativos) segurando um barco (representando os colonizadores).",
        "historic": "monument",
        "inscription": "Monumento em homenagem aos 500 anos do Brasil.",
        "name": "Brasil 500 Anos",
        "id": "node/6380826037"
      },
      "geometry": {
        "type": "Point",
        "coordinates": [
          -57.1784147,
          -15.0649422
        ]
      }
    },
    {
      "type": "Feature",
      "id": "node/6380838067",
      "properties": {
        "timestamp": "2019-04-03T13:11:19Z",
        "version": 1,
        "changeset": 68838205,
        "historic": "monument",
        "inscription": "Monumento em homenagem aos festivais de pesca de Barra do Bugres.",
        "name": "Fest Bugres",
        "id": "node/6380838067"
      },
      "geometry": {
        "type": "Point",
        "coordinates": [
          -57.1793186,
          -15.0650868
        ]
      }
    }
  ]
}
