{
  "type": "FeatureCollection",
  "features": [
    {
      "type": "Feature",
      "id": "node/6380056634",
      "properties": {
        "timestamp": "2019-04-03T04:24:51Z",
        "version": 1,
        "changeset": 68821953,
        "historic": "memorial",
        "inscription": "Jubileu 50 anos",
        "memorial": "yes",
        "name": "Memorial do Jubileu",
        "id": "node/6380056634"
      },
      "geometry": {
        "type": "Point",
        "coordinates": [
          -50.6974303,
          -20.3597642
        ]
      }
    },
    {
      "type": "Feature",
      "id": "node/6380056896",
      "properties": {
        "timestamp": "2019-04-03T04:24:52Z",
        "version": 1,
        "changeset": 68821953,
        "historic": "memorial",
        "memorial": "statue",
        "name": "Estatua dos Mineradores",
        "id": "node/6380056896"
      },
      "geometry": {
        "type": "Point",
        "coordinates": [
          -50.6945413,
          -20.3622693
        ]
      }
    }
  ]
}
