{
  "type": "FeatureCollection",
  "features": [
    {
      "type": "Feature",
      "id": "node/10082804417",
      "properties": {
        "timestamp": "2022-11-18T21:02:57Z",
        "version": 4,
        "changeset": 129102087,
        "addr:housenumber": "402-488",
        "addr:postcode": "76520-000",
        "addr:street": "Avenida da Tribos",
        "internet_access": "wlan",
        "name": "Dormitório H-I",
        "opening_hours": "24/7",
        "phone": "+55 62 9 9927 2997",
        "tourism": "hotel",
        "id": "node/10082804417"
      },
      "geometry": {
        "type": "Point",
        "coordinates": [
          -50.3341812,
          -14.0972813
        ]
      }
    },
    {
      "type": "Feature",
      "id": "node/10083038117",
      "properties": {
        "timestamp": "2022-10-08T03:21:16Z",
        "version": 2,
        "changeset": 127180588,
        "addr:housenumber": "1379",
        "addr:postcode": "76520-000",
        "addr:street": "Avenida Tancredo Neves",
        "internet_access": "wlan",
        "name": "Palace Hotel",
        "opening_hours": "24/7",
        "phone": "+55 62 3385-3233",
        "tourism": "hotel",
        "id": "node/10083038117"
      },
      "geometry": {
        "type": "Point",
        "coordinates": [
          -50.3379472,
          -14.0999161
        ]
      }
    }
  ]
}
