{
  "type": "FeatureCollection",
  "features": [
    {
      "type": "Feature",
      "id": "node/8175324904",
      "properties": {
        "timestamp": "2020-11-29T01:19:01Z",
        "version": 1,
        "changeset": 94964228,
        "historic": "memorial",
        "memorial": "statue",
        "id": "node/8175324904"
      },
      "geometry": {
        "type": "Point",
        "coordinates": [
          -45.4330158,
          -20.4575368
        ]
      }
    },
    {
      "type": "Feature",
      "id": "node/9460337634",
      "properties": {
        "timestamp": "2023-02-26T12:14:35Z",
        "version": 3,
        "changeset": 133039940,
        "historic": "memorial",
        "inscription": "https://www.mgquilombo.com.br/artigos/bens-quilombolas-materias-e-imateriais/morro-das-balas-formiga-mg/",
        "material": "wood",
        "name": "Cruzeiro do Rei Ambrósio",
        "id": "node/9460337634"
      },
      "geometry": {
        "type": "Point",
        "coordinates": [
          -45.4409388,
          -20.4025929
        ]
      }
    }
  ]
}
