{
  "type": "FeatureCollection",
  "features": [
    {
      "type": "Feature",
      "id": "node/10777913386",
      "properties": {
        "timestamp": "2023-04-01T13:30:35Z",
        "version": 1,
        "changeset": 134381344,
        "name": "Salto Rio Guarani",
        "waterway": "waterfall",
        "id": "node/10777913386"
      },
      "geometry": {
        "type": "Point",
        "coordinates": [
          -53.1149731,
          -25.4040801
        ]
      }
    }
  ]
}
