{
  "type": "FeatureCollection",
  "features": [
    {
      "type": "Feature",
      "id": "node/5257846486",
      "properties": {
        "timestamp": "2017-12-05T14:27:09Z",
        "version": 2,
        "changeset": 54366828,
        "addr:city": "Sumé",
        "addr:postcode": "58540000",
        "addr:suburb": "Carro Quebrado",
        "description": "Açude de Abastecimento de Sumé, também usado para pesca.",
        "name": "Açude Público de Sumé",
        "surface": "Açude_de_Sumé",
        "waterway": "dam",
        "id": "node/5257846486"
      },
      "geometry": {
        "type": "Point",
        "coordinates": [
          -36.906527,
          -7.6700707
        ]
      }
    }
  ]
}
