{
  "type": "FeatureCollection",
  "features": [
    {
      "type": "Feature",
      "id": "node/5299939318",
      "properties": {
        "timestamp": "2017-12-22T21:49:28Z",
        "version": 1,
        "changeset": 54851231,
        "addr:city": "Cabeceiras",
        "addr:postcode": "73870-000",
        "addr:street": "Rua Martins de Godói",
        "addr:suburb": "Centro",
        "amenity": "clinic",
        "healthcare": "clinic",
        "name": "Posto de Saúde",
        "opening_hours": "Mo-Sa 08:00-18:00",
        "id": "node/5299939318"
      },
      "geometry": {
        "type": "Point",
        "coordinates": [
          -46.9283625,
          -15.8003553
        ]
      }
    }
  ]
}
