{
  "type": "FeatureCollection",
  "features": [
    {
      "type": "Feature",
      "id": "node/5363534636",
      "properties": {
        "timestamp": "2018-01-26T13:45:55Z",
        "version": 1,
        "changeset": 55772254,
        "amenity": "college",
        "internet_access": "yes",
        "name": "Elite Cursos Profissionalizantes",
        "id": "node/5363534636"
      },
      "geometry": {
        "type": "Point",
        "coordinates": [
          -47.1833097,
          -1.1963358
        ]
      }
    }
  ]
}
