{
  "type": "FeatureCollection",
  "features": [
    {
      "type": "Feature",
      "id": "node/10706816256",
      "properties": {
        "timestamp": "2023-03-05T22:14:56Z",
        "version": 2,
        "changeset": 133342427,
        "description": "Agroturismo e permacultura",
        "name": "Sítio Encanto verde",
        "operator": "Acolhida na colônia",
        "tourism": "guest_house",
        "website": "https://acolhida.com.br/destinos/santa-catarina/serra-geral/santa-rosa-de-lima/encanto-verde/",
        "id": "node/10706816256"
      },
      "geometry": {
        "type": "Point",
        "coordinates": [
          -49.1055032,
          -28.0232052
        ]
      }
    }
  ]
}
