{
  "type": "FeatureCollection",
  "features": [
    {
      "type": "Feature",
      "id": "node/7248185520",
      "properties": {
        "timestamp": "2023-10-25T16:28:32Z",
        "version": 3,
        "changeset": 143124551,
        "addr:city": "São Luiz Gonzaga",
        "addr:housenumber": "1734",
        "addr:postcode": "97800-000",
        "addr:street": "Rua São João",
        "addr:suburb": "Centro",
        "amenity": "cinema",
        "name": "Cine Lux",
        "phone": "+55 55 99961-6326",
        "id": "node/7248185520"
      },
      "geometry": {
        "type": "Point",
        "coordinates": [
          -54.9614944,
          -28.4076519
        ]
      }
    }
  ]
}
