{
  "type": "FeatureCollection",
  "features": [
    {
      "type": "Feature",
      "id": "node/7529119111",
      "properties": {
        "timestamp": "2024-12-14T02:40:51Z",
        "version": 3,
        "changeset": 160267136,
        "addr:housenumber": "1662",
        "addr:postcode": "97800-000",
        "addr:street": "Rua São João",
        "amenity": "pharmacy",
        "name": "Farmácias São João",
        "opening_hours": "Mo-Sa 12:00-00:00",
        "phone": "+55 55 3352-1898",
        "id": "node/7529119111"
      },
      "geometry": {
        "type": "Point",
        "coordinates": [
          -54.9606972,
          -28.4039249
        ]
      }
    },
    {
      "type": "Feature",
      "id": "node/7529689676",
      "properties": {
        "timestamp": "2024-12-14T02:40:51Z",
        "version": 3,
        "changeset": 160267136,
        "addr:postcode": "97800-000",
        "amenity": "pharmacy",
        "name": "Edifarma",
        "phone": "+55 55 3352-2100",
        "id": "node/7529689676"
      },
      "geometry": {
        "type": "Point",
        "coordinates": [
          -54.9581337,
          -28.4072571
        ]
      }
    }
  ]
}
