{
  "type": "FeatureCollection",
  "features": [
    {
      "type": "Feature",
      "id": "node/7529119111",
      "properties": {
        "timestamp": "2021-06-13T16:28:01Z",
        "version": 2,
        "changeset": 106289421,
        "addr:housenumber": "1662",
        "addr:street": "R. São João, 1662 - Centro, São Luiz Gonzaga - RS, 97800-000",
        "amenity": "pharmacy",
        "name": "Farmácias São João",
        "opening_hours": "Mo-Sa 12:00-00:00",
        "phone": "+55 55 3352-1898",
        "id": "node/7529119111"
      },
      "geometry": {
        "type": "Point",
        "coordinates": [
          -54.9606972,
          -28.4039249
        ]
      }
    },
    {
      "type": "Feature",
      "id": "node/7529689676",
      "properties": {
        "timestamp": "2021-06-13T15:05:16Z",
        "version": 2,
        "changeset": 106286788,
        "addr:street": "Centro, São Luiz Gonzaga - RS, 97800-000",
        "amenity": "pharmacy",
        "name": "Edifarma",
        "phone": "+55 55 3352-2100",
        "id": "node/7529689676"
      },
      "geometry": {
        "type": "Point",
        "coordinates": [
          -54.9581337,
          -28.4072571
        ]
      }
    }
  ]
}
