{
  "type": "FeatureCollection",
  "features": [
    {
      "type": "Feature",
      "id": "node/9778101072",
      "properties": {
        "timestamp": "2022-05-28T22:44:00Z",
        "version": 1,
        "changeset": 121634880,
        "amenity": "clinic",
        "name": "UBS",
        "id": "node/9778101072"
      },
      "geometry": {
        "type": "Point",
        "coordinates": [
          -47.8129776,
          -14.1772767
        ]
      }
    }
  ]
}
