{
  "type": "FeatureCollection",
  "features": [
    {
      "type": "Feature",
      "id": "node/2705018556",
      "properties": {
        "timestamp": "2014-03-07T01:19:21Z",
        "version": 1,
        "changeset": 20961703,
        "amenity": "school",
        "name": "Escola Vila Verde",
        "id": "node/2705018556"
      },
      "geometry": {
        "type": "Point",
        "coordinates": [
          -47.5207449,
          -14.1320431
        ]
      }
    },
    {
      "type": "Feature",
      "id": "node/2706345366",
      "properties": {
        "timestamp": "2014-03-08T01:32:48Z",
        "version": 1,
        "changeset": 20980677,
        "amenity": "school",
        "name": "Escola Municipal Zeca de Faria",
        "id": "node/2706345366"
      },
      "geometry": {
        "type": "Point",
        "coordinates": [
          -47.5256646,
          -14.1363846
        ]
      }
    },
    {
      "type": "Feature",
      "id": "node/4713888630",
      "properties": {
        "timestamp": "2023-11-28T20:31:16Z",
        "version": 4,
        "changeset": 144564187,
        "amenity": "school",
        "esperanto": "yes",
        "fixme": "corrigir posição / ĝustigi la posicion",
        "language:eo": "yes",
        "name": "Bona Espero",
        "official_name": "Fazenda Escola Bona Espero",
        "place": "farm",
        "source": "IBGE Setores Rurais",
        "website": "https://www.bona-espero.de/",
        "wikidata": "Q201017",
        "wikimedia_commons": "Category:Bona Espero",
        "wikipedia": "eo:Bona Espero",
        "id": "node/4713888630"
      },
      "geometry": {
        "type": "Point",
        "coordinates": [
          -47.6176061,
          -14.1354221
        ]
      }
    }
  ]
}
