{
  "type": "FeatureCollection",
  "features": [
    {
      "type": "Feature",
      "id": "node/6458825631",
      "properties": {
        "timestamp": "2019-05-08T15:28:03Z",
        "version": 1,
        "changeset": 70034334,
        "name": "Câmara de Vereadores de União da Serra",
        "office": "government",
        "id": "node/6458825631"
      },
      "geometry": {
        "type": "Point",
        "coordinates": [
          -52.0155467,
          -28.7506364
        ]
      }
    }
  ]
}
