{
  "type": "FeatureCollection",
  "features": [
    {
      "type": "Feature",
      "id": "node/12620588922",
      "properties": {
        "timestamp": "2025-02-26T13:20:25Z",
        "version": 1,
        "changeset": 162971594,
        "addr:city": "Santa Brígida",
        "addr:housenumber": "262",
        "addr:postcode": "48570-000",
        "addr:street": "Rua Mãe Ana",
        "addr:suburb": "Centro",
        "amenity": "social_facility",
        "name": "Salão da Sociedade São Vicente de Paulo",
        "operator": "Sociedade São Vicente de Paulo",
        "operator:type": "religious",
        "id": "node/12620588922"
      },
      "geometry": {
        "type": "Point",
        "coordinates": [
          -38.1292123,
          -9.7361254
        ]
      }
    }
  ]
}
