{
  "type": "FeatureCollection",
  "features": [
    {
      "type": "Feature",
      "id": "node/6338021886",
      "properties": {
        "timestamp": "2019-03-14T15:25:08Z",
        "version": 1,
        "changeset": 68140871,
        "name": "Hotel California 18",
        "tourism": "hotel",
        "id": "node/6338021886"
      },
      "geometry": {
        "type": "Point",
        "coordinates": [
          -37.6607125,
          -11.3818001
        ]
      }
    }
  ]
}
