{
  "type": "FeatureCollection",
  "features": [
    {
      "type": "Feature",
      "id": "node/6612366516",
      "properties": {
        "timestamp": "2019-07-13T23:30:07Z",
        "version": 1,
        "changeset": 72220818,
        "historic": "memorial",
        "name": "SENZALA DO SINHO EDUARDO",
        "id": "node/6612366516"
      },
      "geometry": {
        "type": "Point",
        "coordinates": [
          -53.5131323,
          -15.8629136
        ]
      }
    },
    {
      "type": "Feature",
      "id": "node/6612366525",
      "properties": {
        "timestamp": "2019-07-13T23:30:07Z",
        "version": 1,
        "changeset": 72220818,
        "historic": "memorial",
        "id": "node/6612366525"
      },
      "geometry": {
        "type": "Point",
        "coordinates": [
          -53.5130559,
          -15.8631329
        ]
      }
    },
    {
      "type": "Feature",
      "id": "node/6612368817",
      "properties": {
        "timestamp": "2019-07-13T23:30:07Z",
        "version": 1,
        "changeset": 72220818,
        "historic": "memorial",
        "memorial": "plaque",
        "name": "PLACA METALICA HOMENAGEM",
        "id": "node/6612368817"
      },
      "geometry": {
        "type": "Point",
        "coordinates": [
          -53.5139994,
          -15.8626767
        ]
      }
    }
  ]
}
