{
  "type": "FeatureCollection",
  "features": [
    {
      "type": "Feature",
      "id": "node/2552685310",
      "properties": {
        "timestamp": "2013-11-26T15:41:17Z",
        "version": 1,
        "changeset": 19128874,
        "amenity": "pharmacy",
        "name": "Farmácia do Trabalhador",
        "id": "node/2552685310"
      },
      "geometry": {
        "type": "Point",
        "coordinates": [
          -48.6900998,
          -1.5196823
        ]
      }
    }
  ]
}
