{
  "type": "FeatureCollection",
  "features": [
    {
      "type": "Feature",
      "id": "node/5241140432",
      "properties": {
        "timestamp": "2017-11-23T14:20:22Z",
        "version": 2,
        "changeset": 54027480,
        "addr:city": "Pentecoste",
        "addr:postcode": "62640000",
        "addr:street": "Rua Padre Sinval Facundo",
        "amenity": "clinic",
        "healthcare": "clinic",
        "name": "UPA - Unidade de Pronto Atendimento",
        "opening_hours": "24/7",
        "id": "node/5241140432"
      },
      "geometry": {
        "type": "Point",
        "coordinates": [
          -39.2576407,
          -3.7892939
        ]
      }
    }
  ]
}
