{
  "type": "FeatureCollection",
  "features": [
    {
      "type": "Feature",
      "id": "node/5310669200",
      "properties": {
        "timestamp": "2017-12-29T19:07:09Z",
        "version": 1,
        "changeset": 55017392,
        "historic": "monument",
        "name": "Busto de Antonio Francio",
        "id": "node/5310669200"
      },
      "geometry": {
        "type": "Point",
        "coordinates": [
          -53.4745564,
          -25.9170014
        ]
      }
    }
  ]
}
