{
  "type": "FeatureCollection",
  "features": [
    {
      "type": "Feature",
      "id": "node/4968811300",
      "properties": {
        "timestamp": "2019-09-07T12:57:14Z",
        "version": 2,
        "changeset": 74205123,
        "amenity": "dentist",
        "healthcare": "dentist",
        "name": "Clínica Drª Celina Suzuki Kanno",
        "id": "node/4968811300"
      },
      "geometry": {
        "type": "Point",
        "coordinates": [
          -49.7968904,
          -21.6226404
        ]
      }
    }
  ]
}
