{
  "type": "FeatureCollection",
  "features": [
    {
      "type": "Feature",
      "id": "node/4968602845",
      "properties": {
        "timestamp": "2019-09-07T12:57:14Z",
        "version": 2,
        "changeset": 74205123,
        "amenity": "pharmacy",
        "healthcare": "pharmacy",
        "name": "Farmeika",
        "id": "node/4968602845"
      },
      "geometry": {
        "type": "Point",
        "coordinates": [
          -49.797173,
          -21.6236959
        ]
      }
    },
    {
      "type": "Feature",
      "id": "node/4968602846",
      "properties": {
        "timestamp": "2019-09-07T12:57:14Z",
        "version": 2,
        "changeset": 74205123,
        "amenity": "pharmacy",
        "healthcare": "pharmacy",
        "name": "Farmafácil",
        "id": "node/4968602846"
      },
      "geometry": {
        "type": "Point",
        "coordinates": [
          -49.7970231,
          -21.6228429
        ]
      }
    }
  ]
}
