{
  "type": "FeatureCollection",
  "features": [
    {
      "type": "Feature",
      "id": "node/9429063431",
      "properties": {
        "timestamp": "2022-01-19T02:55:44Z",
        "version": 2,
        "changeset": 116322012,
        "addr:city": "Barbacena",
        "addr:housenumber": "200 B",
        "addr:postcode": "36202284",
        "addr:street": "Avenida Coronel José Maximo",
        "addr:suburb": "São Sebastião",
        "amenity": "university",
        "name": "Universidade do Estado de Minas Gerais - Unidade Barbacena",
        "short_name": "UEMG Barbacena",
        "id": "node/9429063431"
      },
      "geometry": {
        "type": "Point",
        "coordinates": [
          -43.7739653,
          -21.2163307
        ]
      }
    }
  ]
}
