{
  "type": "FeatureCollection",
  "features": [
    {
      "type": "Feature",
      "id": "node/5633462560",
      "properties": {
        "timestamp": "2018-09-05T13:13:34Z",
        "version": 2,
        "changeset": 62311447,
        "addr:street": "Rua Vereador Francisco Freire Araújo",
        "amenity": "hospital",
        "healthcare": "hospital",
        "name": "CAE",
        "operator": "Prefeitura Municipal",
        "id": "node/5633462560"
      },
      "geometry": {
        "type": "Point",
        "coordinates": [
          -36.993207,
          -6.7700125
        ]
      }
    },
    {
      "type": "Feature",
      "id": "node/5633462561",
      "properties": {
        "timestamp": "2018-09-05T13:13:33Z",
        "version": 2,
        "changeset": 62311447,
        "addr:street": "Rua Isabel Leopoldina Bittencourt",
        "amenity": "hospital",
        "healthcare": "hospital",
        "name": "UMS Balbina Maria da Conceição",
        "operator": "Prefeitura Municipal",
        "id": "node/5633462561"
      },
      "geometry": {
        "type": "Point",
        "coordinates": [
          -36.9896458,
          -6.7711895
        ]
      }
    }
  ]
}
