{
  "type": "FeatureCollection",
  "features": [
    {
      "type": "Feature",
      "id": "node/9563384708",
      "properties": {
        "timestamp": "2022-03-08T19:39:10Z",
        "version": 1,
        "changeset": 118250190,
        "addr:city": "Viçosa",
        "addr:street": "Rua José Vilela",
        "addr:suburb": "Centro",
        "government": "social_security",
        "name": "Instituto Nacional do Seguro Social - INSS",
        "office": "government",
        "opening_hours": "Mo-Fr 07:00-17:00",
        "operator": "Instituto Nacional do Seguro Social",
        "operator:short": "INSS",
        "operator:wikidata": "Q10302614",
        "operator:wikipedia": "pt:Instituto Nacional do Seguro Social",
        "id": "node/9563384708"
      },
      "geometry": {
        "type": "Point",
        "coordinates": [
          -36.2465276,
          -9.3714947
        ]
      }
    }
  ]
}
