{
  "type": "FeatureCollection",
  "features": [
    {
      "type": "Feature",
      "id": "node/5390213422",
      "properties": {
        "timestamp": "2018-02-05T15:47:49Z",
        "version": 1,
        "changeset": 56088810,
        "amenity": "college",
        "name": "Colégio COOPPED",
        "id": "node/5390213422"
      },
      "geometry": {
        "type": "Point",
        "coordinates": [
          -43.6942977,
          -20.5219373
        ]
      }
    }
  ]
}
