{
  "type": "FeatureCollection",
  "features": [
    {
      "type": "Feature",
      "id": "node/3651269875",
      "properties": {
        "timestamp": "2015-07-14T20:30:31Z",
        "version": 1,
        "changeset": 32637614,
        "addr:city": "Eugênio de Castro",
        "amenity": "clinic",
        "emergency": "no",
        "name": "Posto de Saúde",
        "source": "Bing;IBGE",
        "id": "node/3651269875"
      },
      "geometry": {
        "type": "Point",
        "coordinates": [
          -54.1499342,
          -28.5283087
        ]
      }
    }
  ]
}
