{
  "type": "FeatureCollection",
  "features": [
    {
      "type": "Feature",
      "id": "node/10059324217",
      "properties": {
        "timestamp": "2022-09-28T17:57:56Z",
        "version": 1,
        "changeset": 126750886,
        "amenity": "clinic",
        "name": "Policlínica",
        "id": "node/10059324217"
      },
      "geometry": {
        "type": "Point",
        "coordinates": [
          -39.3133028,
          -7.298163
        ]
      }
    }
  ]
}
