{
  "type": "FeatureCollection",
  "features": [
    {
      "type": "Feature",
      "id": "node/12175244480",
      "properties": {
        "timestamp": "2024-09-13T17:37:11Z",
        "version": 1,
        "changeset": 156583015,
        "addr:housenumber": "128",
        "addr:street": "Rua Coronel Machado",
        "addr:suburb": "Centro",
        "amenity": "veterinary",
        "id": "node/12175244480"
      },
      "geometry": {
        "type": "Point",
        "coordinates": [
          -45.4670479,
          -22.2422011
        ]
      }
    }
  ]
}
