{
  "type": "FeatureCollection",
  "features": [
    {
      "type": "Feature",
      "id": "node/12175244480",
      "properties": {
        "timestamp": "2024-09-13T17:37:11Z",
        "version": 1,
        "changeset": 156583015,
        "addr:housenumber": "128",
        "addr:street": "Rua Coronel Machado",
        "addr:suburb": "Centro",
        "amenity": "veterinary",
        "id": "node/12175244480"
      },
      "geometry": {
        "type": "Point",
        "coordinates": [
          -45.4670479,
          -22.2422011
        ]
      }
    },
    {
      "type": "Feature",
      "id": "node/12187423107",
      "properties": {
        "timestamp": "2024-09-20T03:05:45Z",
        "version": 1,
        "changeset": 156846873,
        "addr:housenumber": "55",
        "addr:street": "Rua Casemiro Osório",
        "addr:suburb": "Centro",
        "amenity": "veterinary",
        "name": "Veterinaria Siqueira",
        "id": "node/12187423107"
      },
      "geometry": {
        "type": "Point",
        "coordinates": [
          -45.467002,
          -22.2445556
        ]
      }
    }
  ]
}
