{
  "type": "FeatureCollection",
  "features": [
    {
      "type": "Feature",
      "id": "node/5931296287",
      "properties": {
        "timestamp": "2018-09-26T11:46:43Z",
        "version": 1,
        "changeset": 62943910,
        "name": "Bicicletaria do Rafa",
        "shop": "bicycle",
        "id": "node/5931296287"
      },
      "geometry": {
        "type": "Point",
        "coordinates": [
          -46.8175903,
          -11.6271129
        ]
      }
    }
  ]
}
