{
  "type": "FeatureCollection",
  "features": [
    {
      "type": "Feature",
      "id": "node/12181125166",
      "properties": {
        "timestamp": "2024-09-16T22:56:43Z",
        "version": 1,
        "changeset": 156708244,
        "addr:housenumber": "601",
        "addr:street": "Avenida Joaquim Pompeu de Toledo",
        "addr:suburb": "Vila Estádio",
        "amenity": "cinema",
        "name": "Cine Araújo",
        "id": "node/12181125166"
      },
      "geometry": {
        "type": "Point",
        "coordinates": [
          -50.4357233,
          -21.2220838
        ]
      }
    }
  ]
}
