{
  "type": "FeatureCollection",
  "features": [
    {
      "type": "Feature",
      "id": "node/4117872790",
      "properties": {
        "timestamp": "2016-04-13T02:16:57Z",
        "version": 1,
        "changeset": 38514400,
        "amenity": "hospital",
        "name": "Hospital Universitário",
        "id": "node/4117872790"
      },
      "geometry": {
        "type": "Point",
        "coordinates": [
          -44.9205685,
          -20.9478381
        ]
      }
    }
  ]
}
