{
  "type": "FeatureCollection",
  "features": [
    {
      "type": "Feature",
      "id": "node/4117872800",
      "properties": {
        "timestamp": "2016-08-11T16:31:45Z",
        "version": 2,
        "changeset": 41392656,
        "amenity": "school",
        "name": "E. E. Newton Ferreira de Paiva",
        "id": "node/4117872800"
      },
      "geometry": {
        "type": "Point",
        "coordinates": [
          -44.9176449,
          -20.9443274
        ]
      }
    },
    {
      "type": "Feature",
      "id": "node/4330055676",
      "properties": {
        "timestamp": "2023-04-13T16:42:34Z",
        "version": 2,
        "changeset": 134870780,
        "amenity": "school",
        "name": "E. E. Doutor Cícero Ferreira",
        "id": "node/4330055676"
      },
      "geometry": {
        "type": "Point",
        "coordinates": [
          -44.9173232,
          -20.9467307
        ]
      }
    },
    {
      "type": "Feature",
      "id": "node/10769054654",
      "properties": {
        "timestamp": "2023-03-28T16:25:39Z",
        "version": 1,
        "changeset": 134227639,
        "addr:city": "Santo Antonio do Amparo",
        "addr:housenumber": "80",
        "addr:postcode": "37262000",
        "addr:street": "Rua Lavras",
        "addr:suburb": "Afranio Aguiar Paiva",
        "amenity": "school",
        "name": "Escola Municipal \"Dr. Geraldo Carrara\"",
        "id": "node/10769054654"
      },
      "geometry": {
        "type": "Point",
        "coordinates": [
          -44.9107207,
          -20.9427632
        ]
      }
    }
  ]
}
