{
  "type": "FeatureCollection",
  "features": [
    {
      "type": "Feature",
      "id": "node/5108434890",
      "properties": {
        "timestamp": "2017-09-15T21:38:56Z",
        "version": 1,
        "changeset": 52082304,
        "amenity": "library",
        "name": "Biblioteca Cidadão Armando Schiavinato",
        "id": "node/5108434890"
      },
      "geometry": {
        "type": "Point",
        "coordinates": [
          -51.8232434,
          -23.1973044
        ]
      }
    }
  ]
}
