{
  "type": "FeatureCollection",
  "features": [
    {
      "type": "Feature",
      "id": "node/5600460821",
      "properties": {
        "timestamp": "2018-05-06T16:45:45Z",
        "version": 1,
        "changeset": 58734777,
        "amenity": "library",
        "name": "Biblioteca Municipal",
        "id": "node/5600460821"
      },
      "geometry": {
        "type": "Point",
        "coordinates": [
          -40.557685,
          -3.3154565
        ]
      }
    }
  ]
}
