{
  "type": "FeatureCollection",
  "features": [
    {
      "type": "Feature",
      "id": "node/8848473443",
      "properties": {
        "timestamp": "2021-09-18T16:15:37Z",
        "version": 2,
        "changeset": 111381847,
        "name": "Cachoeira de Angeli",
        "waterway": "waterfall",
        "id": "node/8848473443"
      },
      "geometry": {
        "type": "Point",
        "coordinates": [
          -40.421175,
          -19.3489861
        ]
      }
    }
  ]
}
