{
  "type": "FeatureCollection",
  "features": [
    {
      "type": "Feature",
      "id": "node/4103694172",
      "properties": {
        "timestamp": "2017-04-04T13:25:30Z",
        "version": 2,
        "changeset": 47442672,
        "amenity": "community_centre",
        "name": "Centro Comunitário",
        "id": "node/4103694172"
      },
      "geometry": {
        "type": "Point",
        "coordinates": [
          -51.1795204,
          0.8612488
        ]
      }
    }
  ]
}
