{
  "type": "FeatureCollection",
  "features": [
    {
      "type": "Feature",
      "id": "node/4153950112",
      "properties": {
        "timestamp": "2017-11-20T02:02:25Z",
        "version": 2,
        "changeset": 53937021,
        "name": "Açude Público",
        "waterway": "dam",
        "id": "node/4153950112"
      },
      "geometry": {
        "type": "Point",
        "coordinates": [
          -40.8358569,
          -4.7452131
        ]
      }
    }
  ]
}
