{
  "type": "FeatureCollection",
  "features": [
    {
      "type": "Feature",
      "id": "node/6379839034",
      "properties": {
        "timestamp": "2019-04-03T00:19:41Z",
        "version": 1,
        "changeset": 68817697,
        "addr:street": "Rua Antônio Edvar Soares Torres",
        "amenity": "hospital",
        "emergency": "yes",
        "healthcare": "hospital",
        "healthcare:speciality": "general",
        "name": "francisco mourão lima",
        "id": "node/6379839034"
      },
      "geometry": {
        "type": "Point",
        "coordinates": [
          -40.8297968,
          -4.7489605
        ]
      }
    }
  ]
}
