{
  "type": "FeatureCollection",
  "features": [
    {
      "type": "Feature",
      "id": "node/6379839035",
      "properties": {
        "timestamp": "2019-04-03T00:19:41Z",
        "version": 1,
        "changeset": 68817697,
        "addr:street": "Rua Pinto Bastos",
        "amenity": "school",
        "name": "Escola FRANCISCO MOURÃO LIMA",
        "id": "node/6379839035"
      },
      "geometry": {
        "type": "Point",
        "coordinates": [
          -40.8303425,
          -4.7499746
        ]
      }
    },
    {
      "type": "Feature",
      "id": "node/6379840185",
      "properties": {
        "timestamp": "2020-02-25T02:02:09Z",
        "version": 2,
        "changeset": 81429070,
        "addr:street": "Rua Patriolino Alves Gomes",
        "amenity": "school",
        "name": "ESCOLINHA ARCO IRIS",
        "id": "node/6379840185"
      },
      "geometry": {
        "type": "Point",
        "coordinates": [
          -40.8312021,
          -4.7555293
        ]
      }
    }
  ]
}
