{
  "type": "FeatureCollection",
  "features": [
    {
      "type": "Feature",
      "id": "node/6904081984",
      "properties": {
        "timestamp": "2019-10-22T00:03:12Z",
        "version": 1,
        "changeset": 76021405,
        "amenity": "pharmacy",
        "dispensing": "yes",
        "healthcare": "pharmacy",
        "name": "drogaria do Anísio",
        "id": "node/6904081984"
      },
      "geometry": {
        "type": "Point",
        "coordinates": [
          -42.1432094,
          -20.6032752
        ]
      }
    }
  ]
}
