{
  "type": "FeatureCollection",
  "features": [
    {
      "type": "Feature",
      "id": "node/9508454808",
      "properties": {
        "timestamp": "2022-08-23T03:25:46Z",
        "version": 2,
        "changeset": 125250131,
        "name": "Cachoeira dos Ferreiras",
        "waterway": "waterfall",
        "id": "node/9508454808"
      },
      "geometry": {
        "type": "Point",
        "coordinates": [
          -42.1751137,
          -20.5992805
        ]
      }
    },
    {
      "type": "Feature",
      "id": "node/11943602853",
      "properties": {
        "timestamp": "2024-05-30T01:31:21Z",
        "version": 1,
        "changeset": 152011843,
        "waterway": "waterfall",
        "id": "node/11943602853"
      },
      "geometry": {
        "type": "Point",
        "coordinates": [
          -42.1865603,
          -20.638223
        ]
      }
    }
  ]
}
