{
  "type": "FeatureCollection",
  "features": [
    {
      "type": "Feature",
      "id": "node/6218472157",
      "properties": {
        "timestamp": "2019-01-18T11:38:33Z",
        "version": 1,
        "changeset": 66423639,
        "amenity": "pharmacy",
        "dispensing": "yes",
        "healthcare": "pharmacy",
        "name": "Kobayashi",
        "id": "node/6218472157"
      },
      "geometry": {
        "type": "Point",
        "coordinates": [
          -46.0391265,
          -23.5730534
        ]
      }
    },
    {
      "type": "Feature",
      "id": "node/11957258428",
      "properties": {
        "timestamp": "2024-06-05T03:25:12Z",
        "version": 1,
        "changeset": 152268198,
        "addr:city": "Biritiba Mirim",
        "addr:housenumber": "171",
        "addr:postcode": "08940-000",
        "addr:street": "Av. Jair Leme",
        "addr:suburb": "Jardim Lorena",
        "amenity": "pharmacy",
        "dispensing": "yes",
        "healthcare": "pharmacy",
        "name": "Drogaria Yoneda",
        "id": "node/11957258428"
      },
      "geometry": {
        "type": "Point",
        "coordinates": [
          -46.0401361,
          -23.5676722
        ]
      }
    }
  ]
}
