{
  "type": "FeatureCollection",
  "features": [
    {
      "type": "Feature",
      "id": "node/6218472157",
      "properties": {
        "timestamp": "2019-01-18T11:38:33Z",
        "version": 1,
        "changeset": 66423639,
        "amenity": "pharmacy",
        "dispensing": "yes",
        "healthcare": "pharmacy",
        "name": "Kobayashi",
        "id": "node/6218472157"
      },
      "geometry": {
        "type": "Point",
        "coordinates": [
          -46.0391265,
          -23.5730534
        ]
      }
    }
  ]
}
