{
  "type": "FeatureCollection",
  "features": [
    {
      "type": "Feature",
      "id": "node/12513087506",
      "properties": {
        "timestamp": "2025-01-18T22:42:10Z",
        "version": 1,
        "changeset": 161508077,
        "amenity": "clinic",
        "healthcare": "clinic",
        "name": "POSTO DE SAÚDE FRANCELINO GREGÓRIO",
        "operator": "DSEI",
        "operator:type": "public",
        "id": "node/12513087506"
      },
      "geometry": {
        "type": "Point",
        "coordinates": [
          -57.0714465,
          -3.2848256
        ]
      }
    }
  ]
}
