{
  "type": "FeatureCollection",
  "features": [
    {
      "type": "Feature",
      "id": "node/4063300183",
      "properties": {
        "timestamp": "2016-03-16T11:43:43Z",
        "version": 1,
        "changeset": 37869577,
        "amenity": "library",
        "name": "Farol da Educação",
        "id": "node/4063300183"
      },
      "geometry": {
        "type": "Point",
        "coordinates": [
          -45.3421086,
          -3.6069909
        ]
      }
    }
  ]
}
