{
  "type": "FeatureCollection",
  "features": [
    {
      "type": "Feature",
      "id": "node/5010156130",
      "properties": {
        "timestamp": "2021-08-24T21:50:29Z",
        "version": 4,
        "changeset": 110195272,
        "addr:city": "Esteio",
        "addr:housenumber": "900",
        "addr:street": "Rua Padre Felipe",
        "addr:suburb": "Centro",
        "amenity": "arts_centre",
        "name": "Casa de Cultura Lufredina Araújo Gaya",
        "id": "node/5010156130"
      },
      "geometry": {
        "type": "Point",
        "coordinates": [
          -51.1668915,
          -29.8499364
        ]
      }
    }
  ]
}
