{
  "type": "FeatureCollection",
  "features": [
    {
      "type": "Feature",
      "id": "node/9040840886",
      "properties": {
        "timestamp": "2021-08-27T13:03:17Z",
        "version": 1,
        "changeset": 110341838,
        "addr:city": "Esteio",
        "addr:street": "Avenida Padre Claret",
        "addr:suburb": "Centro",
        "amenity": "clinic",
        "healthcare": "clinic",
        "name": "Ponto de Vacinação",
        "id": "node/9040840886"
      },
      "geometry": {
        "type": "Point",
        "coordinates": [
          -51.1679486,
          -29.8485864
        ]
      }
    },
    {
      "type": "Feature",
      "id": "node/10003176817",
      "properties": {
        "timestamp": "2022-09-05T23:15:37Z",
        "version": 1,
        "changeset": 125833897,
        "amenity": "clinic",
        "healthcare": "clinic",
        "name": "UBS Juan Pio Germano",
        "id": "node/10003176817"
      },
      "geometry": {
        "type": "Point",
        "coordinates": [
          -51.1792326,
          -29.8595327
        ]
      }
    }
  ]
}
