{
  "type": "FeatureCollection",
  "features": [
    {
      "type": "Feature",
      "id": "node/8492036336",
      "properties": {
        "timestamp": "2022-12-11T04:28:22Z",
        "version": 3,
        "changeset": 129952088,
        "height": "15",
        "name": "Cascata Santa Manuela",
        "waterway": "waterfall",
        "width": "204",
        "id": "node/8492036336"
      },
      "geometry": {
        "type": "Point",
        "coordinates": [
          -52.4678713,
          -26.7610396
        ]
      }
    }
  ]
}
