{
  "type": "FeatureCollection",
  "features": [
    {
      "type": "Feature",
      "id": "node/5393902554",
      "properties": {
        "timestamp": "2019-05-07T13:13:29Z",
        "version": 2,
        "changeset": 69977471,
        "addr:city": "Santo Amaro",
        "addr:postcode": "44200000",
        "addr:street": "Rua Doutor Biao",
        "addr:suburb": "Centro",
        "building": "yes",
        "name": "Galeria de Arte-Caetano Veloso",
        "tourism": "gallery",
        "id": "node/5393902554"
      },
      "geometry": {
        "type": "Point",
        "coordinates": [
          -38.7099452,
          -12.5471313
        ]
      }
    }
  ]
}
