{
  "type": "FeatureCollection",
  "features": [
    {
      "type": "Feature",
      "id": "node/9767935115",
      "properties": {
        "timestamp": "2022-05-24T19:19:09Z",
        "version": 1,
        "changeset": 121441158,
        "historic": "monument",
        "name": "Monumento à Bíblia",
        "id": "node/9767935115"
      },
      "geometry": {
        "type": "Point",
        "coordinates": [
          -49.0992705,
          -23.4118444
        ]
      }
    }
  ]
}
