{
  "type": "FeatureCollection",
  "features": [
    {
      "type": "Feature",
      "id": "node/11153475860",
      "properties": {
        "timestamp": "2023-08-29T15:47:32Z",
        "version": 1,
        "changeset": 140548831,
        "addr:city": "Araçuai",
        "addr:housenumber": "776",
        "addr:postcode": "39600-000",
        "addr:street": "Rua Clemente Santana",
        "addr:suburb": "vila magnolia",
        "amenity": "pharmacy",
        "dispensing": "yes",
        "drive_through": "no",
        "healthcare": "pharmacy",
        "name": "Farmacia Viva Mais",
        "opening_hours": "seg-dom 07h-21h",
        "id": "node/11153475860"
      },
      "geometry": {
        "type": "Point",
        "coordinates": [
          -42.0583454,
          -16.8469322
        ]
      }
    }
  ]
}
