{
  "type": "FeatureCollection",
  "features": [
    {
      "type": "Feature",
      "id": "node/4088480426",
      "properties": {
        "timestamp": "2016-03-31T15:15:10Z",
        "version": 1,
        "changeset": 38200364,
        "amenity": "hospital",
        "name": "Posto de Saúde Santo Antônio",
        "id": "node/4088480426"
      },
      "geometry": {
        "type": "Point",
        "coordinates": [
          -44.6553848,
          -21.2991074
        ]
      }
    }
  ]
}
