{
  "type": "FeatureCollection",
  "features": [
    {
      "type": "Feature",
      "id": "node/4088466224",
      "properties": {
        "timestamp": "2016-03-31T15:10:47Z",
        "version": 1,
        "changeset": 38200245,
        "amenity": "pharmacy",
        "name": "Farmácia Minas Farma",
        "id": "node/4088466224"
      },
      "geometry": {
        "type": "Point",
        "coordinates": [
          -44.6585518,
          -21.2978574
        ]
      }
    }
  ]
}
