{
  "type": "FeatureCollection",
  "features": [
    {
      "type": "Feature",
      "id": "node/898411025",
      "properties": {
        "timestamp": "2016-07-27T01:20:17Z",
        "version": 3,
        "changeset": 41051486,
        "historic": "monument",
        "name": "Cristo de São Luiz do Purunã",
        "id": "node/898411025"
      },
      "geometry": {
        "type": "Point",
        "coordinates": [
          -49.6389357,
          -25.4726285
        ]
      }
    }
  ]
}
