{
  "type": "FeatureCollection",
  "features": [
    {
      "type": "Feature",
      "id": "node/7285890611",
      "properties": {
        "timestamp": "2020-03-11T20:10:22Z",
        "version": 1,
        "changeset": 82077827,
        "name": "Hotel Central",
        "tourism": "hotel",
        "id": "node/7285890611"
      },
      "geometry": {
        "type": "Point",
        "coordinates": [
          -45.7600415,
          -21.2375874
        ]
      }
    }
  ]
}
