{
  "type": "FeatureCollection",
  "features": [
    {
      "type": "Feature",
      "id": "node/9143278417",
      "properties": {
        "timestamp": "2021-10-03T22:03:52Z",
        "version": 1,
        "changeset": 112050426,
        "addr:housenumber": "205",
        "addr:postcode": "69970-000",
        "addr:street": "Rua Doutor Sansão Gomes",
        "internet_access": "wlan",
        "name": "Hotel Estrela",
        "phone": "+556834622651",
        "tourism": "hotel",
        "id": "node/9143278417"
      },
      "geometry": {
        "type": "Point",
        "coordinates": [
          -70.7622575,
          -8.1596647
        ]
      }
    }
  ]
}
