{
  "type": "FeatureCollection",
  "features": [
    {
      "type": "Feature",
      "id": "node/2601152769",
      "properties": {
        "timestamp": "2014-10-10T13:03:09Z",
        "version": 2,
        "changeset": 25982646,
        "addr:city": "Rio de Contas",
        "addr:postcode": "46170-970",
        "addr:suburb": "Centro",
        "amenity": "pharmacy",
        "dispensing": "yes",
        "name": "Farmácia Guimarães",
        "wheelchair": "yes",
        "id": "node/2601152769"
      },
      "geometry": {
        "type": "Point",
        "coordinates": [
          -41.8134809,
          -13.5812642
        ]
      }
    },
    {
      "type": "Feature",
      "id": "node/2601152773",
      "properties": {
        "timestamp": "2014-10-10T13:03:09Z",
        "version": 2,
        "changeset": 25982646,
        "addr:city": "Rio de Contas",
        "addr:postcode": "46170-970",
        "addr:suburb": "Centro",
        "amenity": "pharmacy",
        "dispensing": "yes",
        "name": "Farmácia Rio de Contas",
        "wheelchair": "no",
        "id": "node/2601152773"
      },
      "geometry": {
        "type": "Point",
        "coordinates": [
          -41.8135103,
          -13.5813983
        ]
      }
    },
    {
      "type": "Feature",
      "id": "node/2601370907",
      "properties": {
        "timestamp": "2022-10-21T19:58:30Z",
        "version": 2,
        "changeset": 127900855,
        "amenity": "pharmacy",
        "dispensing": "yes",
        "healthcare": "pharmacy",
        "name": "Farmácia Riocontense",
        "phone": "+55 77 34752394",
        "wheelchair": "no",
        "id": "node/2601370907"
      },
      "geometry": {
        "type": "Point",
        "coordinates": [
          -41.8124044,
          -13.5802511
        ]
      }
    }
  ]
}
