{
  "type": "FeatureCollection",
  "features": [
    {
      "type": "Feature",
      "id": "node/2360854887",
      "properties": {
        "timestamp": "2023-08-02T18:15:29Z",
        "version": 10,
        "changeset": 139359256,
        "addr:city": "Livramento de Nossa Senhora",
        "addr:postcode": "46140-000",
        "addr:street": "BA-148",
        "name": "Cachoeira Véu de Noiva",
        "source": "IBGE",
        "tourism": "attraction",
        "waterway": "waterfall",
        "id": "node/2360854887"
      },
      "geometry": {
        "type": "Point",
        "coordinates": [
          -41.818872,
          -13.6124154
        ]
      }
    },
    {
      "type": "Feature",
      "id": "node/8462481831",
      "properties": {
        "timestamp": "2024-09-24T23:11:53Z",
        "version": 2,
        "changeset": 157059445,
        "name": "Cachoeira dos Frios",
        "waterway": "waterfall",
        "id": "node/8462481831"
      },
      "geometry": {
        "type": "Point",
        "coordinates": [
          -41.9043177,
          -13.3257929
        ]
      }
    }
  ]
}
