{
  "type": "FeatureCollection",
  "features": [
    {
      "type": "Feature",
      "id": "node/9841724464",
      "properties": {
        "timestamp": "2022-06-23T14:39:21Z",
        "version": 2,
        "changeset": 122763378,
        "name": "Cachoeira Nossa Senhora do Carmo",
        "waterway": "waterfall",
        "id": "node/9841724464"
      },
      "geometry": {
        "type": "Point",
        "coordinates": [
          -49.2160141,
          -24.7839829
        ]
      }
    }
  ]
}
