{
  "type": "FeatureCollection",
  "features": [
    {
      "type": "Feature",
      "id": "node/3925692852",
      "properties": {
        "timestamp": "2016-01-03T17:14:18Z",
        "version": 1,
        "changeset": 36342843,
        "amenity": "hospital",
        "name": "Hospital Municipal",
        "source": "IBGE",
        "id": "node/3925692852"
      },
      "geometry": {
        "type": "Point",
        "coordinates": [
          -45.7895035,
          -19.5204474
        ]
      }
    }
  ]
}
