{
  "type": "FeatureCollection",
  "features": [
    {
      "type": "Feature",
      "id": "node/7236296285",
      "properties": {
        "timestamp": "2020-02-23T07:09:29Z",
        "version": 1,
        "changeset": 81360389,
        "name": "Departamento de Fiscalização Tributária e Posturas do Município",
        "office": "government",
        "id": "node/7236296285"
      },
      "geometry": {
        "type": "Point",
        "coordinates": [
          -48.2630515,
          -15.9473721
        ]
      }
    }
  ]
}
