{
  "type": "FeatureCollection",
  "features": [
    {
      "type": "Feature",
      "id": "node/7602591791",
      "properties": {
        "timestamp": "2020-06-08T11:16:28Z",
        "version": 1,
        "changeset": 86351449,
        "amenity": "pharmacy",
        "name": "Feitosa Farma",
        "id": "node/7602591791"
      },
      "geometry": {
        "type": "Point",
        "coordinates": [
          -38.7798144,
          -7.1754368
        ]
      }
    }
  ]
}
