{
  "type": "FeatureCollection",
  "features": [
    {
      "type": "Feature",
      "id": "node/8936611441",
      "properties": {
        "timestamp": "2021-07-21T04:33:32Z",
        "version": 2,
        "changeset": 108345942,
        "amenity": "dentist",
        "name": "Consultório Odontológico Dr. Samuel Santana",
        "id": "node/8936611441"
      },
      "geometry": {
        "type": "Point",
        "coordinates": [
          -41.1615323,
          -11.5480577
        ]
      }
    }
  ]
}
