{
  "type": "FeatureCollection",
  "features": [
    {
      "type": "Feature",
      "id": "node/5134071995",
      "properties": {
        "timestamp": "2017-09-27T23:32:46Z",
        "version": 1,
        "changeset": 52428170,
        "access": "private",
        "amenity": "bicycle_parking",
        "bicycle_parking": "wall_loops",
        "capacity": "14",
        "covered": "no",
        "fee": "no",
        "lit": "yes",
        "operator": "Escola Estadual Presidente Kennedy",
        "supervised": "no",
        "id": "node/5134071995"
      },
      "geometry": {
        "type": "Point",
        "coordinates": [
          -51.101657,
          -29.9558801
        ]
      }
    },
    {
      "type": "Feature",
      "id": "node/5134262132",
      "properties": {
        "timestamp": "2017-09-28T03:41:32Z",
        "version": 1,
        "changeset": 52430449,
        "access": "customers",
        "amenity": "bicycle_parking",
        "bicycle_parking": "wall_loops",
        "capacity": "5",
        "covered": "no",
        "fee": "no",
        "lit": "yes",
        "opening_hours": "Mo-Sa 08:00-21:30; Su 08:00-20:30",
        "operator": "Asun",
        "supervised": "yes",
        "website": "http://www.asun.com.br/",
        "id": "node/5134262132"
      },
      "geometry": {
        "type": "Point",
        "coordinates": [
          -51.1037146,
          -29.9532836
        ]
      }
    },
    {
      "type": "Feature",
      "id": "node/5134262135",
      "properties": {
        "timestamp": "2023-11-06T12:28:50Z",
        "version": 3,
        "changeset": 143691505,
        "access": "customers",
        "amenity": "bicycle_parking",
        "bicycle_parking": "wall_loops",
        "capacity": "8",
        "covered": "no",
        "fee": "no",
        "lit": "yes",
        "opening_hours": "Mo-Fr 10:00-15:00",
        "operator": "Caixa Econômica Federal",
        "supervised": "yes",
        "website": "https://www.caixa.gov.br/",
        "id": "node/5134262135"
      },
      "geometry": {
        "type": "Point",
        "coordinates": [
          -51.103,
          -29.953316
        ]
      }
    },
    {
      "type": "Feature",
      "id": "node/5134262152",
      "properties": {
        "timestamp": "2019-09-30T03:27:19Z",
        "version": 4,
        "changeset": 75076765,
        "access": "customers",
        "amenity": "bicycle_parking",
        "bicycle_parking": "wall_loops",
        "capacity": "2",
        "covered": "no",
        "fee": "no",
        "lit": "yes",
        "opening_hours": "Mo-Sa 08:00-21:00",
        "operator": "Farmácias Associadas",
        "supervised": "no",
        "website": "https://www.farmaciasassociadas.com.br/",
        "id": "node/5134262152"
      },
      "geometry": {
        "type": "Point",
        "coordinates": [
          -51.0944215,
          -29.9542459
        ]
      }
    }
  ]
}
