{
  "type": "FeatureCollection",
  "features": [
    {
      "type": "Feature",
      "id": "node/4727830259",
      "properties": {
        "timestamp": "2021-11-29T19:01:53Z",
        "version": 5,
        "changeset": 114373579,
        "addr:city": "Cachoeirinha",
        "addr:housenumber": "2165",
        "addr:postcode": "94910-003",
        "addr:street": "Avenida General Flores da Cunha",
        "addr:suburb": "Vila Cachoeirinha",
        "amenity": "doctors",
        "healthcare": "doctor",
        "name": "J.J. Serviços Médicos",
        "phone": "+55 51 3441-2004",
        "id": "node/4727830259"
      },
      "geometry": {
        "type": "Point",
        "coordinates": [
          -51.0926442,
          -29.947602
        ]
      }
    }
  ]
}
