{
  "type": "FeatureCollection",
  "features": [
    {
      "type": "Feature",
      "id": "node/4636406312",
      "properties": {
        "timestamp": "2017-01-29T14:08:54Z",
        "version": 2,
        "changeset": 45621266,
        "name": "Paradouro Batistella",
        "tourism": "hotel",
        "id": "node/4636406312"
      },
      "geometry": {
        "type": "Point",
        "coordinates": [
          -49.2321763,
          -27.6924437
        ]
      }
    },
    {
      "type": "Feature",
      "id": "node/6239562149",
      "properties": {
        "timestamp": "2022-05-17T01:38:23Z",
        "version": 2,
        "changeset": 121074415,
        "addr:housenumber": "Alfredo Wagner SC Brasil",
        "addr:street": "Rod. Br 282 - Trevo - Alfredo Wagner/SC",
        "description": "contato@hotelkretzer.com.br",
        "name": "Hotel & Churrascaria Kretzer",
        "phone": "+554832761292",
        "tourism": "hotel",
        "website": "https://www.hotelkretzer.com.br/",
        "id": "node/6239562149"
      },
      "geometry": {
        "type": "Point",
        "coordinates": [
          -49.3310844,
          -27.6950606
        ]
      }
    },
    {
      "type": "Feature",
      "id": "node/12525272406",
      "properties": {
        "timestamp": "2025-01-23T02:16:48Z",
        "version": 1,
        "changeset": 161658205,
        "addr:housenumber": "109",
        "addr:street": "Rua do Comércio",
        "name": "Park Potel",
        "phone": "+5548988266242",
        "tourism": "hotel",
        "id": "node/12525272406"
      },
      "geometry": {
        "type": "Point",
        "coordinates": [
          -49.334719,
          -27.6987922
        ]
      }
    }
  ]
}
