{
  "type": "FeatureCollection",
  "features": [
    {
      "type": "Feature",
      "id": "node/2797716506",
      "properties": {
        "timestamp": "2023-01-22T20:14:32Z",
        "version": 2,
        "changeset": 131580232,
        "amenity": "doctors",
        "healthcare": "doctor",
        "name": "Posto de Saude",
        "id": "node/2797716506"
      },
      "geometry": {
        "type": "Point",
        "coordinates": [
          -40.6028821,
          -20.7952002
        ]
      }
    }
  ]
}
