{
  "type": "FeatureCollection",
  "features": [
    {
      "type": "Feature",
      "id": "node/3225049293",
      "properties": {
        "timestamp": "2015-02-22T13:23:27Z",
        "version": 2,
        "changeset": 29020764,
        "amenity": "community_centre",
        "name": "Sindicato dos Produtores Rurais de Itueta",
        "id": "node/3225049293"
      },
      "geometry": {
        "type": "Point",
        "coordinates": [
          -41.2246603,
          -19.393758
        ]
      }
    },
    {
      "type": "Feature",
      "id": "node/3225049294",
      "properties": {
        "timestamp": "2015-02-22T13:23:27Z",
        "version": 2,
        "changeset": 29020764,
        "amenity": "community_centre",
        "name": "Sindicato dos Trabalhadores Rurais de Itueta",
        "id": "node/3225049294"
      },
      "geometry": {
        "type": "Point",
        "coordinates": [
          -41.2246199,
          -19.3933742
        ]
      }
    },
    {
      "type": "Feature",
      "id": "node/6693697790",
      "properties": {
        "timestamp": "2019-08-08T01:17:28Z",
        "version": 1,
        "changeset": 73132172,
        "amenity": "community_centre",
        "name": "Centro Comunitário de Itueta",
        "id": "node/6693697790"
      },
      "geometry": {
        "type": "Point",
        "coordinates": [
          -41.2241046,
          -19.3921982
        ]
      }
    }
  ]
}
