{
  "type": "FeatureCollection",
  "features": [
    {
      "type": "Feature",
      "id": "node/4230996863",
      "properties": {
        "timestamp": "2016-06-07T22:38:32Z",
        "version": 1,
        "changeset": 39873176,
        "historic": "monument",
        "name": "Cristo Redentor",
        "id": "node/4230996863"
      },
      "geometry": {
        "type": "Point",
        "coordinates": [
          -61.7790516,
          -11.8857153
        ]
      }
    }
  ]
}
