{
  "type": "FeatureCollection",
  "features": [
    {
      "type": "Feature",
      "id": "node/2969258081",
      "properties": {
        "timestamp": "2020-07-14T21:29:59Z",
        "version": 2,
        "changeset": 87997867,
        "amenity": "clinic",
        "healthcare": "clinic",
        "name": "UBS Aida Barroncas",
        "id": "node/2969258081"
      },
      "geometry": {
        "type": "Point",
        "coordinates": [
          -60.017486,
          -2.0473953
        ]
      }
    },
    {
      "type": "Feature",
      "id": "node/6405344883",
      "properties": {
        "timestamp": "2020-01-14T21:55:53Z",
        "version": 2,
        "changeset": 79583749,
        "amenity": "clinic",
        "healthcare": "clinic",
        "id": "node/6405344883"
      },
      "geometry": {
        "type": "Point",
        "coordinates": [
          -60.0116117,
          -2.0498782
        ]
      }
    }
  ]
}
