{
  "type": "FeatureCollection",
  "features": [
    {
      "type": "Feature",
      "id": "node/2368052068",
      "properties": {
        "timestamp": "2019-07-15T22:17:27Z",
        "version": 3,
        "changeset": 72282939,
        "historic": "monument",
        "name": "Índio",
        "id": "node/2368052068"
      },
      "geometry": {
        "type": "Point",
        "coordinates": [
          -60.0285055,
          -2.043261
        ]
      }
    }
  ]
}
