{
  "type": "FeatureCollection",
  "features": [
    {
      "type": "Feature",
      "id": "node/10555453050",
      "properties": {
        "timestamp": "2023-01-18T18:27:15Z",
        "version": 2,
        "changeset": 131433755,
        "amenity": "pharmacy",
        "healthcare": "pharmacy",
        "name": "Bemol Farma",
        "id": "node/10555453050"
      },
      "geometry": {
        "type": "Point",
        "coordinates": [
          -60.0248927,
          -2.0504962
        ]
      }
    }
  ]
}
