{
  "type": "FeatureCollection",
  "features": [
    {
      "type": "Feature",
      "id": "node/12013003622",
      "properties": {
        "timestamp": "2024-06-26T18:37:07Z",
        "version": 1,
        "changeset": 153216269,
        "addr:housenumber": "25",
        "addr:street": "Avenida dos Imigrantes",
        "amenity": "dentist",
        "healthcare": "dentist",
        "name": "Clínica Odontológica Thamiris",
        "id": "node/12013003622"
      },
      "geometry": {
        "type": "Point",
        "coordinates": [
          -45.4263939,
          -21.5564932
        ]
      }
    },
    {
      "type": "Feature",
      "id": "node/12013003655",
      "properties": {
        "timestamp": "2024-06-26T18:37:07Z",
        "version": 1,
        "changeset": 153216269,
        "addr:housenumber": "44",
        "addr:street": "Avenida Miguel Alves",
        "amenity": "dentist",
        "healthcare": "dentist",
        "name": "Odontologia e Nutrição",
        "id": "node/12013003655"
      },
      "geometry": {
        "type": "Point",
        "coordinates": [
          -45.4273864,
          -21.5572095
        ]
      }
    }
  ]
}
