{
  "type": "FeatureCollection",
  "features": [
    {
      "type": "Feature",
      "id": "node/12010152402",
      "properties": {
        "timestamp": "2024-06-25T19:22:58Z",
        "version": 1,
        "changeset": 153172146,
        "amenity": "pharmacy",
        "healthcare": "pharmacy",
        "name": "Drogaria do Alex",
        "id": "node/12010152402"
      },
      "geometry": {
        "type": "Point",
        "coordinates": [
          -45.4239025,
          -21.5545128
        ]
      }
    },
    {
      "type": "Feature",
      "id": "node/12010152415",
      "properties": {
        "timestamp": "2024-06-25T19:22:58Z",
        "version": 1,
        "changeset": 153172146,
        "addr:housenumber": "430",
        "addr:street": "Avenida dos Imigrantes",
        "amenity": "pharmacy",
        "healthcare": "pharmacy",
        "name": "Drogaria americana",
        "id": "node/12010152415"
      },
      "geometry": {
        "type": "Point",
        "coordinates": [
          -45.4239118,
          -21.5539671
        ]
      }
    },
    {
      "type": "Feature",
      "id": "node/12013003645",
      "properties": {
        "timestamp": "2024-06-26T18:37:07Z",
        "version": 1,
        "changeset": 153216269,
        "addr:housenumber": "384",
        "addr:street": "Rua Milton Costa",
        "amenity": "pharmacy",
        "healthcare": "pharmacy",
        "name": "Drogaria americana",
        "id": "node/12013003645"
      },
      "geometry": {
        "type": "Point",
        "coordinates": [
          -45.4271015,
          -21.5566244
        ]
      }
    }
  ]
}
