{
  "type": "FeatureCollection",
  "features": [
    {
      "type": "Feature",
      "id": "node/8626422724",
      "properties": {
        "timestamp": "2022-12-20T02:32:17Z",
        "version": 2,
        "changeset": 130269433,
        "amenity": "hospital",
        "healthcare": "hospital",
        "name": "Hospital Nossa Senhora dos Navegantes",
        "id": "node/8626422724"
      },
      "geometry": {
        "type": "Point",
        "coordinates": [
          -48.6561268,
          -26.8880374
        ]
      }
    }
  ]
}
