{
  "type": "FeatureCollection",
  "features": [
    {
      "type": "Feature",
      "id": "node/3762749674",
      "properties": {
        "timestamp": "2020-06-27T14:42:45Z",
        "version": 2,
        "changeset": 87228282,
        "amenity": "kindergarten",
        "name": "Creche Municipal Ângela Maria",
        "id": "node/3762749674"
      },
      "geometry": {
        "type": "Point",
        "coordinates": [
          -37.3557582,
          -4.7103928
        ]
      }
    }
  ]
}
