{
  "type": "FeatureCollection",
  "features": [
    {
      "type": "Feature",
      "id": "node/9040875786",
      "properties": {
        "timestamp": "2021-10-17T20:01:43Z",
        "version": 2,
        "changeset": 112625683,
        "government": "legislative",
        "name": "Câmara de Vereadores de Faxinal dos Guedes",
        "office": "government",
        "id": "node/9040875786"
      },
      "geometry": {
        "type": "Point",
        "coordinates": [
          -52.2570451,
          -26.8542093
        ]
      }
    },
    {
      "type": "Feature",
      "id": "node/9040888677",
      "properties": {
        "timestamp": "2021-08-27T13:25:19Z",
        "version": 1,
        "changeset": 110342946,
        "government": "education",
        "name": "Secretaria de Educação",
        "office": "government",
        "id": "node/9040888677"
      },
      "geometry": {
        "type": "Point",
        "coordinates": [
          -52.2598037,
          -26.8546783
        ]
      }
    }
  ]
}
