{
  "type": "FeatureCollection",
  "features": [
    {
      "type": "Feature",
      "id": "node/9040888575",
      "properties": {
        "timestamp": "2021-08-27T13:25:19Z",
        "version": 1,
        "changeset": 110342946,
        "name": "Hotel & Restaurante Moinho de Vento",
        "stars": "3",
        "tourism": "hotel",
        "id": "node/9040888575"
      },
      "geometry": {
        "type": "Point",
        "coordinates": [
          -52.2591171,
          -26.8558317
        ]
      }
    }
  ]
}
