{
  "type": "FeatureCollection",
  "features": [
    {
      "type": "Feature",
      "id": "node/9045329722",
      "properties": {
        "timestamp": "2021-08-29T14:11:44Z",
        "version": 1,
        "changeset": 110414498,
        "amenity": "library",
        "name": "Biblioteca Municipal",
        "id": "node/9045329722"
      },
      "geometry": {
        "type": "Point",
        "coordinates": [
          -52.2641167,
          -26.8556295
        ]
      }
    }
  ]
}
