{
  "type": "FeatureCollection",
  "features": [
    {
      "type": "Feature",
      "id": "node/1770602061",
      "properties": {
        "timestamp": "2012-05-30T17:17:58Z",
        "version": 1,
        "changeset": 11750421,
        "amenity": "kindergarten",
        "name": "Creche Municipal",
        "id": "node/1770602061"
      },
      "geometry": {
        "type": "Point",
        "coordinates": [
          -43.3170073,
          -22.7939482
        ]
      }
    },
    {
      "type": "Feature",
      "id": "node/2440676143",
      "properties": {
        "timestamp": "2013-08-31T18:43:51Z",
        "version": 1,
        "changeset": 17607863,
        "amenity": "kindergarten",
        "id": "node/2440676143"
      },
      "geometry": {
        "type": "Point",
        "coordinates": [
          -43.2955693,
          -22.7875175
        ]
      }
    }
  ]
}
