{
  "type": "FeatureCollection",
  "features": [
    {
      "type": "Feature",
      "id": "node/9573099817",
      "properties": {
        "timestamp": "2022-03-12T16:23:51Z",
        "version": 1,
        "changeset": 118404180,
        "addr:street": "Avenida José do Patrocínio",
        "amenity": "pharmacy",
        "name": "Farmácia Prista",
        "id": "node/9573099817"
      },
      "geometry": {
        "type": "Point",
        "coordinates": [
          -39.5790072,
          -3.4996919
        ]
      }
    }
  ]
}
