{
  "type": "FeatureCollection",
  "features": [
    {
      "type": "Feature",
      "id": "node/9077671240",
      "properties": {
        "timestamp": "2021-09-09T19:43:57Z",
        "version": 1,
        "changeset": 110992600,
        "historic": "monument",
        "name": "Cristo Redentor",
        "id": "node/9077671240"
      },
      "geometry": {
        "type": "Point",
        "coordinates": [
          -52.1580695,
          -28.5303039
        ]
      }
    }
  ]
}
