{
  "type": "FeatureCollection",
  "features": [
    {
      "type": "Feature",
      "id": "node/12387017094",
      "properties": {
        "timestamp": "2024-12-03T14:58:09Z",
        "version": 3,
        "changeset": 159884884,
        "addr:city": "Ametista do Sul",
        "addr:housenumber": "686",
        "addr:postcode": "98465-000",
        "addr:street": "Estada Planalto",
        "contact:facebook": "complexobelvederemina",
        "contact:instagram": "belvederemina",
        "contact:whatsapp": "+55 55 99937 6882",
        "email": "contato@beldeveremina.com.ar",
        "name": "Belveder Mina",
        "phone": "+55 55 99937 6882",
        "tourism": "hotel",
        "website": "https://beldeveremina.com.br",
        "id": "node/12387017094"
      },
      "geometry": {
        "type": "Point",
        "coordinates": [
          -53.17284,
          -27.364538
        ]
      }
    },
    {
      "type": "Feature",
      "id": "node/12644443361",
      "properties": {
        "timestamp": "2025-03-08T02:09:19Z",
        "version": 1,
        "changeset": 163348887,
        "name": "Hotel Ametista",
        "tourism": "hotel",
        "id": "node/12644443361"
      },
      "geometry": {
        "type": "Point",
        "coordinates": [
          -53.1879633,
          -27.3587251
        ]
      }
    }
  ]
}
