{
  "type": "FeatureCollection",
  "features": [
    {
      "type": "Feature",
      "id": "node/4216198055",
      "properties": {
        "timestamp": "2016-05-30T20:52:08Z",
        "version": 1,
        "changeset": 39675306,
        "addr:city": "Santa Fé",
        "amenity": "clinic",
        "emergency": "no",
        "name": "Posto de Saúde de Santa Fé",
        "id": "node/4216198055"
      },
      "geometry": {
        "type": "Point",
        "coordinates": [
          -35.3456238,
          -6.2402501
        ]
      }
    }
  ]
}
