{
  "type": "FeatureCollection",
  "features": [
    {
      "type": "Feature",
      "id": "node/8560785682",
      "properties": {
        "timestamp": "2021-03-25T14:42:19Z",
        "version": 1,
        "changeset": 101727066,
        "name": "hotel da Lina",
        "tourism": "hotel",
        "id": "node/8560785682"
      },
      "geometry": {
        "type": "Point",
        "coordinates": [
          -47.7709426,
          -1.6780527
        ]
      }
    }
  ]
}
