{
  "type": "FeatureCollection",
  "features": [
    {
      "type": "Feature",
      "id": "node/2103186527",
      "properties": {
        "timestamp": "2023-04-24T05:46:15Z",
        "version": 3,
        "changeset": 135285149,
        "addr:city": "Palmitinho",
        "addr:housenumber": "320",
        "addr:postcode": "98430-000",
        "addr:street": "Rua Carlos Gomes",
        "addr:suburb": "Centro",
        "amenity": "hospital",
        "healthcare": "hospital",
        "name": "Hospital Santa Terezinha",
        "phone": "+55 55 3791 1150",
        "ref:CNES": "2228580",
        "ref:vatin": "BR87664793000121",
        "id": "node/2103186527"
      },
      "geometry": {
        "type": "Point",
        "coordinates": [
          -53.5566017,
          -27.3565563
        ]
      }
    }
  ]
}
