{
  "type": "FeatureCollection",
  "features": [
    {
      "type": "Feature",
      "id": "node/4681991989",
      "properties": {
        "timestamp": "2017-02-28T10:57:57Z",
        "version": 2,
        "changeset": 46464499,
        "amenity": "social_facility",
        "name": "Posto de Saúde da Família",
        "id": "node/4681991989"
      },
      "geometry": {
        "type": "Point",
        "coordinates": [
          -39.258702,
          -17.737794
        ]
      }
    }
  ]
}
