{
  "type": "FeatureCollection",
  "features": [
    {
      "type": "Feature",
      "id": "node/12165384256",
      "properties": {
        "timestamp": "2024-09-09T11:50:12Z",
        "version": 2,
        "changeset": 156390796,
        "amenity": "hospital",
        "healthcare": "hospital",
        "healthcare:speciality": "general",
        "name": "Unidade Basica de Saude",
        "id": "node/12165384256"
      },
      "geometry": {
        "type": "Point",
        "coordinates": [
          -43.6011875,
          -15.5964828
        ]
      }
    }
  ]
}
