{
  "type": "FeatureCollection",
  "features": [
    {
      "type": "Feature",
      "id": "node/11756752571",
      "properties": {
        "timestamp": "2024-03-23T22:08:15Z",
        "version": 1,
        "changeset": 149068855,
        "name": "Sousa Center",
        "tourism": "gallery",
        "id": "node/11756752571"
      },
      "geometry": {
        "type": "Point",
        "coordinates": [
          -36.6320978,
          -5.1150061
        ]
      }
    }
  ]
}
