{
  "type": "FeatureCollection",
  "features": [
    {
      "type": "Feature",
      "id": "node/11756752569",
      "properties": {
        "timestamp": "2025-03-08T20:00:47Z",
        "version": 8,
        "changeset": 163377780,
        "addr:city": "Macau",
        "addr:housenumber": "83",
        "addr:postcode": "59500000",
        "addr:street": "Rua São José",
        "addr:suburb": "Centro",
        "air_conditioning": "yes",
        "brand": "Maria Bonita",
        "contact:instagram": "pousada_mariabonita",
        "email": "maria-bonita.service761@passinbox.com",
        "internet_access": "wlan",
        "internet_access:fee": "no",
        "name": "Pousada Maria Bonita",
        "name:en": "Maria Bonita Inn",
        "name:es": "Posada/Pensión María Bonita",
        "payment:cash": "yes",
        "payment:credit_cards": "yes",
        "payment:debit_cards": "yes",
        "payment:lightning": "yes",
        "phone": "84988152426",
        "rooms": "3",
        "tourism": "hotel",
        "id": "node/11756752569"
      },
      "geometry": {
        "type": "Point",
        "coordinates": [
          -36.6351023,
          -5.1157429
        ]
      }
    },
    {
      "type": "Feature",
      "id": "node/12607170451",
      "properties": {
        "timestamp": "2025-03-09T02:38:37Z",
        "version": 5,
        "changeset": 163385298,
        "addr:city": "Macau",
        "addr:housenumber": "84a",
        "addr:postcode": "59500000",
        "addr:street": "Rua Amaro Cavalcante",
        "addr:suburb": "Centro",
        "air_conditioning": "yes",
        "brand": "Maria Bonita Macau",
        "check_date:currency:XBT": "2025-03-09",
        "currency:BRL": "yes",
        "currency:XBT": "yes",
        "description": "Pousada no centro de Macau, procurar 84988152426 para mais informações.",
        "email": "maria-bonita.service761@passinbox.com",
        "internet_access": "yes",
        "internet_access:fee": "no",
        "mobile": "5584988152426",
        "name": "Pousada Maria Bonita Macau",
        "payment:bitcoin": "yes",
        "payment:cash": "yes",
        "payment:credit_cards": "yes",
        "payment:debit_cards": "yes",
        "payment:lightning": "yes",
        "phone": "84988152426",
        "rooms": "8",
        "tourism": "hotel",
        "website": "https://www.instagram.com/pousada_mariabonita?igsh=MWwxeWpucHE4ejhvag==",
        "id": "node/12607170451"
      },
      "geometry": {
        "type": "Point",
        "coordinates": [
          -36.6320796,
          -5.1150507
        ]
      }
    }
  ]
}
