{
  "type": "FeatureCollection",
  "features": [
    {
      "type": "Feature",
      "id": "node/11756752569",
      "properties": {
        "timestamp": "2024-03-23T22:42:36Z",
        "version": 4,
        "changeset": 149069767,
        "addr:housenumber": "83",
        "addr:postcode": "59500000",
        "addr:street": "Rua São José",
        "contact:instagram": "pousada_mariabonita",
        "internet_access": "wlan",
        "name": "Pousada Maria Bonita",
        "name:en": "Maria Bonita Inn",
        "name:es": "Posada/Pensión María Bonita",
        "opening_hours": "Mo-Su 07:00-22:00",
        "tourism": "hotel",
        "id": "node/11756752569"
      },
      "geometry": {
        "type": "Point",
        "coordinates": [
          -36.6351023,
          -5.1157429
        ]
      }
    }
  ]
}
