{
  "type": "FeatureCollection",
  "features": [
    {
      "type": "Feature",
      "id": "node/4336429145",
      "properties": {
        "timestamp": "2022-06-12T07:46:54Z",
        "version": 8,
        "changeset": 122269051,
        "addr:city": "Matinhos",
        "addr:door": "Sobreloja 04",
        "addr:housenumber": "517",
        "addr:postcode": "83260-000",
        "addr:street": "Rua Apucarana",
        "addr:suburb": "Caiobá",
        "description": "Representante de Tubos e Conexões em PEAD e PPR marca TopFusion, Perfis em PVC Wood para portas da marca Unicomper, Indústria de Plásticos Siplas,",
        "ele": "7",
        "name": "Hernández Representações",
        "office": "government",
        "phone": "+55 41 9987-0074",
        "id": "node/4336429145"
      },
      "geometry": {
        "type": "Point",
        "coordinates": [
          -48.5438048,
          -25.8360179
        ]
      }
    },
    {
      "type": "Feature",
      "id": "node/4379994839",
      "properties": {
        "timestamp": "2024-07-04T00:21:07Z",
        "version": 3,
        "changeset": 153523431,
        "government": "register_office",
        "office": "government",
        "id": "node/4379994839"
      },
      "geometry": {
        "type": "Point",
        "coordinates": [
          -48.5344876,
          -25.817309
        ]
      }
    }
  ]
}
