{
  "type": "FeatureCollection",
  "features": [
    {
      "type": "Feature",
      "id": "node/12136533795",
      "properties": {
        "timestamp": "2024-09-27T23:58:13Z",
        "version": 2,
        "changeset": 157191695,
        "addr:city": "Divinópolis",
        "addr:postcode": "35501-250",
        "addr:street": "Rua Muriaé",
        "addr:suburb": "Catalão",
        "amenity": "kindergarten",
        "name": "Escola Infantil Carinha de Anjo",
        "phone": "037 3212-3521",
        "id": "node/12136533795"
      },
      "geometry": {
        "type": "Point",
        "coordinates": [
          -44.9071711,
          -20.1695217
        ]
      }
    }
  ]
}
