{
  "type": "FeatureCollection",
  "features": [
    {
      "type": "Feature",
      "id": "node/12136533795",
      "properties": {
        "timestamp": "2024-08-25T21:25:26Z",
        "version": 1,
        "changeset": 155756351,
        "addr:city": "Divinópolis-MG",
        "addr:postcode": "35501-250",
        "addr:street": "Rua Muriaé",
        "addr:suburb": "Catalão",
        "amenity": "kindergarten",
        "name": "Escola Infantil Carinha de Anjo",
        "phone": "037 3212-3521",
        "id": "node/12136533795"
      },
      "geometry": {
        "type": "Point",
        "coordinates": [
          -44.9071711,
          -20.1695217
        ]
      }
    }
  ]
}
