{
  "type": "FeatureCollection",
  "features": [
    {
      "type": "Feature",
      "id": "node/3326898430",
      "properties": {
        "timestamp": "2015-02-02T13:47:33Z",
        "version": 1,
        "changeset": 28566556,
        "amenity": "hospital",
        "name": "RS. ZAINAB",
        "operator": "14075006",
        "id": "node/3326898430"
      },
      "geometry": {
        "type": "Point",
        "coordinates": [
          -49.7531226,
          -14.7175301
        ]
      }
    }
  ]
}
