{
  "type": "FeatureCollection",
  "features": [
    {
      "type": "Feature",
      "id": "node/11510935070",
      "properties": {
        "timestamp": "2024-01-12T14:04:52Z",
        "version": 1,
        "changeset": 146182573,
        "amenity": "clinic",
        "name": "UBS",
        "id": "node/11510935070"
      },
      "geometry": {
        "type": "Point",
        "coordinates": [
          -38.3570265,
          -6.63166
        ]
      }
    }
  ]
}
