{
  "type": "FeatureCollection",
  "features": [
    {
      "type": "Feature",
      "id": "node/9964819541",
      "properties": {
        "timestamp": "2023-05-02T18:23:25Z",
        "version": 2,
        "changeset": 135628470,
        "historic": "monument",
        "name": "Letreiro Monte Sião",
        "tourism": "attraction",
        "id": "node/9964819541"
      },
      "geometry": {
        "type": "Point",
        "coordinates": [
          -46.5768915,
          -22.4422304
        ]
      }
    },
    {
      "type": "Feature",
      "id": "node/9966453955",
      "properties": {
        "timestamp": "2023-05-02T18:25:38Z",
        "version": 2,
        "changeset": 135628556,
        "historic": "monument",
        "name": "Letreiro Monte Sião",
        "tourism": "attraction",
        "id": "node/9966453955"
      },
      "geometry": {
        "type": "Point",
        "coordinates": [
          -46.5752734,
          -22.4344738
        ]
      }
    }
  ]
}
