{
  "type": "FeatureCollection",
  "features": [
    {
      "type": "Feature",
      "id": "node/12392805805",
      "properties": {
        "timestamp": "2024-12-03T01:40:45Z",
        "version": 1,
        "changeset": 159863753,
        "amenity": "social_facility",
        "name": "CREAS",
        "id": "node/12392805805"
      },
      "geometry": {
        "type": "Point",
        "coordinates": [
          -52.7804254,
          -29.6765138
        ]
      }
    }
  ]
}
