{
  "type": "FeatureCollection",
  "features": [
    {
      "type": "Feature",
      "id": "node/6142931423",
      "properties": {
        "timestamp": "2018-12-17T15:39:38Z",
        "version": 1,
        "changeset": 65553885,
        "name": "Cascata da Ferradura",
        "waterway": "waterfall",
        "id": "node/6142931423"
      },
      "geometry": {
        "type": "Point",
        "coordinates": [
          -52.9344732,
          -29.5452965
        ]
      }
    }
  ]
}
