{
  "type": "FeatureCollection",
  "features": [
    {
      "type": "Feature",
      "id": "node/7005944360",
      "properties": {
        "timestamp": "2019-11-24T11:37:46Z",
        "version": 1,
        "changeset": 77479796,
        "amenity": "library",
        "name": "Biblioteca Municipal",
        "id": "node/7005944360"
      },
      "geometry": {
        "type": "Point",
        "coordinates": [
          -61.9052474,
          -11.1679192
        ]
      }
    }
  ]
}
