{
  "type": "FeatureCollection",
  "features": [
    {
      "type": "Feature",
      "id": "node/1866525022",
      "properties": {
        "timestamp": "2021-05-10T04:51:56Z",
        "version": 5,
        "changeset": 104420406,
        "amenity": "hospital",
        "emergency": "yes",
        "healthcare": "hospital",
        "name": "Hospital Bom Jesus",
        "source": "knowledge",
        "id": "node/1866525022"
      },
      "geometry": {
        "type": "Point",
        "coordinates": [
          -51.6721935,
          -24.2409018
        ]
      }
    },
    {
      "type": "Feature",
      "id": "node/1866573548",
      "properties": {
        "timestamp": "2021-05-10T04:51:56Z",
        "version": 3,
        "changeset": 104420406,
        "amenity": "hospital",
        "emergency": "yes",
        "healthcare": "hospital",
        "name": "Hospital e Maternidade Ivaiporã",
        "source": "knowledge",
        "id": "node/1866573548"
      },
      "geometry": {
        "type": "Point",
        "coordinates": [
          -51.6743162,
          -24.2491642
        ]
      }
    }
  ]
}
