{
  "type": "FeatureCollection",
  "features": [
    {
      "type": "Feature",
      "id": "node/12400836581",
      "properties": {
        "timestamp": "2024-12-06T19:11:31Z",
        "version": 1,
        "changeset": 160006283,
        "addr:city": "Comendador Levy Gasparian",
        "addr:housenumber": "311",
        "addr:postcode": "25870-000",
        "addr:street": "Estrada União Indústria",
        "addr:suburb": "Grotão",
        "amenity": "hospital",
        "emergency": "yes",
        "healthcare": "hospital",
        "healthcare:speciality": "general",
        "name": "Policlínica Doutor Altino Alves Moreira",
        "operator": "Município de Comendador Levy Gasparin",
        "operator:type": "public",
        "id": "node/12400836581"
      },
      "geometry": {
        "type": "Point",
        "coordinates": [
          -43.2046541,
          -22.0376083
        ]
      }
    }
  ]
}
