{
  "type": "FeatureCollection",
  "features": [
    {
      "type": "Feature",
      "id": "node/3924479218",
      "properties": {
        "timestamp": "2021-01-07T10:51:18Z",
        "version": 2,
        "changeset": 97103512,
        "historic": "monument",
        "name": "Cristo",
        "id": "node/3924479218"
      },
      "geometry": {
        "type": "Point",
        "coordinates": [
          -44.9150435,
          -21.5235524
        ]
      }
    },
    {
      "type": "Feature",
      "id": "node/8477148627",
      "properties": {
        "timestamp": "2021-03-01T21:04:19Z",
        "version": 1,
        "changeset": 100230531,
        "historic": "monument",
        "id": "node/8477148627"
      },
      "geometry": {
        "type": "Point",
        "coordinates": [
          -44.9030246,
          -21.5134798
        ]
      }
    }
  ]
}
