{
  "type": "FeatureCollection",
  "features": [
    {
      "type": "Feature",
      "id": "node/4528328150",
      "properties": {
        "timestamp": "2016-11-29T13:03:16Z",
        "version": 1,
        "changeset": 44033887,
        "amenity": "doctors",
        "healthcare": "psychotherapist",
        "name": "Nayana Cataldo",
        "phone": "+5524981430506",
        "id": "node/4528328150"
      },
      "geometry": {
        "type": "Point",
        "coordinates": [
          -44.7149599,
          -23.2183102
        ]
      }
    }
  ]
}
