{
  "type": "FeatureCollection",
  "features": [
    {
      "type": "Feature",
      "id": "node/4528325431",
      "properties": {
        "timestamp": "2016-11-29T13:23:23Z",
        "version": 2,
        "changeset": 44034281,
        "addr:housenumber": "50",
        "addr:street": "Largo do Rozario",
        "craft": "painter",
        "name": "Atelier Márcio Franco",
        "tourism": "gallery",
        "id": "node/4528325431"
      },
      "geometry": {
        "type": "Point",
        "coordinates": [
          -44.7143993,
          -23.2187579
        ]
      }
    },
    {
      "type": "Feature",
      "id": "node/4528328090",
      "properties": {
        "timestamp": "2016-11-29T13:03:14Z",
        "version": 1,
        "changeset": 44033887,
        "name": "Galeria Colobri",
        "shop": "art",
        "tourism": "gallery",
        "id": "node/4528328090"
      },
      "geometry": {
        "type": "Point",
        "coordinates": [
          -44.7145258,
          -23.2194273
        ]
      }
    },
    {
      "type": "Feature",
      "id": "node/4528328128",
      "properties": {
        "timestamp": "2021-11-27T19:02:04Z",
        "version": 3,
        "changeset": 114304372,
        "addr:street": "Largo do Rozario",
        "name": "Imagenação",
        "office": "government",
        "tourism": "gallery",
        "id": "node/4528328128"
      },
      "geometry": {
        "type": "Point",
        "coordinates": [
          -44.7145524,
          -23.2187646
        ]
      }
    },
    {
      "type": "Feature",
      "id": "node/4528328187",
      "properties": {
        "timestamp": "2016-11-29T13:03:17Z",
        "version": 1,
        "changeset": 44033887,
        "name": "Renata Rosa",
        "shop": "art",
        "tourism": "gallery",
        "id": "node/4528328187"
      },
      "geometry": {
        "type": "Point",
        "coordinates": [
          -44.7131253,
          -23.2188568
        ]
      }
    }
  ]
}
