{
  "type": "FeatureCollection",
  "features": [
    {
      "type": "Feature",
      "id": "node/4528325448",
      "properties": {
        "timestamp": "2023-02-01T15:06:46Z",
        "version": 3,
        "changeset": 131967314,
        "addr:city": "Paraty",
        "addr:housenumber": "74",
        "addr:street": "Rua José Vieira Ramos",
        "alt_name": "Centro de Referência Especializado de Assistência Social",
        "amenity": "social_facility",
        "name": "CREAS",
        "social_facility": "outreach",
        "social_facility:for": "underprivileged;abused;victim",
        "id": "node/4528325448"
      },
      "geometry": {
        "type": "Point",
        "coordinates": [
          -44.7160385,
          -23.2202438
        ]
      }
    }
  ]
}
