{
  "type": "FeatureCollection",
  "features": [
    {
      "type": "Feature",
      "id": "node/2001287107",
      "properties": {
        "timestamp": "2012-11-07T13:51:06Z",
        "version": 1,
        "changeset": 13785599,
        "addr:housenumber": "411",
        "addr:street": "Avenida Governador Roberto Silveira",
        "name": "Melo's Cicle",
        "phone": "+55-21-26688296",
        "shop": "bicycle",
        "website": "http://www.meloscicles.com.br",
        "id": "node/2001287107"
      },
      "geometry": {
        "type": "Point",
        "coordinates": [
          -43.455139,
          -22.7545369
        ]
      }
    },
    {
      "type": "Feature",
      "id": "node/3159584993",
      "properties": {
        "timestamp": "2022-07-23T07:00:05Z",
        "version": 5,
        "changeset": 123963815,
        "addr:city": "Nova Iguaçu",
        "addr:housenumber": "207",
        "addr:street": "Rua Lafaiete Pimenta",
        "addr:suburb": "Comendador Soares",
        "name": "Shopping das Bicicletas",
        "opening_hours": "Mo-Sa 08:00-18:00",
        "payment:credit_cards": "yes",
        "payment:debit_cards": "yes",
        "phone": "+55 21 3102-8377",
        "shop": "bicycle",
        "website": "http://shoppingdasbicicletas.com/",
        "id": "node/3159584993"
      },
      "geometry": {
        "type": "Point",
        "coordinates": [
          -43.4878972,
          -22.7452337
        ]
      }
    },
    {
      "type": "Feature",
      "id": "node/3159605297",
      "properties": {
        "timestamp": "2022-07-23T06:59:21Z",
        "version": 4,
        "changeset": 123963815,
        "addr:suburb": "Comendador Soares",
        "name": "Renata's Bikes",
        "opening_hours:signed": "no",
        "payment:credit_cards": "yes",
        "payment:debit_cards": "yes",
        "shop": "bicycle",
        "id": "node/3159605297"
      },
      "geometry": {
        "type": "Point",
        "coordinates": [
          -43.4894623,
          -22.7445362
        ]
      }
    },
    {
      "type": "Feature",
      "id": "node/3163657301",
      "properties": {
        "timestamp": "2014-11-02T21:03:53Z",
        "version": 1,
        "changeset": 26513213,
        "name": "Cicle Bike",
        "shop": "bicycle",
        "id": "node/3163657301"
      },
      "geometry": {
        "type": "Point",
        "coordinates": [
          -43.524147,
          -22.71991
        ]
      }
    }
  ]
}
