{
  "type": "FeatureCollection",
  "features": [
    {
      "type": "Feature",
      "id": "node/6367417760",
      "properties": {
        "timestamp": "2021-08-18T00:33:04Z",
        "version": 5,
        "changeset": 109837639,
        "addr:city": "Nova Iguaçu",
        "addr:housenumber": "19",
        "addr:postcode": "26277-350",
        "addr:street": "Rua Leonel Gouveia",
        "addr:suburb": "Comendador Soares",
        "amenity": "dentist",
        "healthcare": "dentist",
        "healthcare:speciality": "dentist",
        "name": "Consultório dentista",
        "opening_hours": "Mo-Fr 08:00-18:00",
        "operator": "Dr. Danielle Lucas",
        "wheelchair": "no",
        "id": "node/6367417760"
      },
      "geometry": {
        "type": "Point",
        "coordinates": [
          -43.4884767,
          -22.7450863
        ]
      }
    },
    {
      "type": "Feature",
      "id": "node/6367501697",
      "properties": {
        "timestamp": "2021-08-18T00:27:42Z",
        "version": 5,
        "changeset": 109837639,
        "addr:city": "Nova Iguaçu",
        "addr:housenumber": "12",
        "addr:postcode": "26277-350",
        "addr:street": "Rua Leonel Gouveia",
        "addr:suburb": "Comendador Soares",
        "amenity": "dentist",
        "healthcare": "dentist",
        "healthcare:speciality": "dentist",
        "name": "Consultorio Dentario",
        "opening_hours": "Mo-Fr 08:00-18:00",
        "operator": "Dr. Diana",
        "phone": "+55 21 31027649",
        "wheelchair": "no",
        "id": "node/6367501697"
      },
      "geometry": {
        "type": "Point",
        "coordinates": [
          -43.4886466,
          -22.7450147
        ]
      }
    }
  ]
}
