{
  "type": "FeatureCollection",
  "features": [
    {
      "type": "Feature",
      "id": "node/10315031115",
      "properties": {
        "timestamp": "2023-01-08T16:19:39Z",
        "version": 1,
        "changeset": 131021825,
        "addr:postcode": "48415-000",
        "addr:street": "Avenida Nossa Senhora de Fátima",
        "amenity": "hospital",
        "healthcare": "hospital",
        "name": "Hospital Municipal",
        "id": "node/10315031115"
      },
      "geometry": {
        "type": "Point",
        "coordinates": [
          -38.2185806,
          -10.5967283
        ]
      }
    }
  ]
}
