{
  "type": "FeatureCollection",
  "features": [
    {
      "type": "Feature",
      "id": "node/7644955185",
      "properties": {
        "timestamp": "2020-06-23T03:57:55Z",
        "version": 1,
        "changeset": 87006888,
        "alt_name": "Cachoeira do Itupocu",
        "name": "Cachoeira do Itapocu",
        "note": "'name' segue a grafia do ribeirão da margem esquerda, e 'alt_name' segue a grafia original no mapa do CGG-SP 1888.",
        "source:name": "Comissão Geographica e Geologica Provincia de São Paulo 1888: Planta do Rio Tietê. Folha 2.",
        "waterway": "waterfall",
        "id": "node/7644955185"
      },
      "geometry": {
        "type": "Point",
        "coordinates": [
          -47.4159515,
          -23.1655989
        ]
      }
    }
  ]
}
