{
  "type": "FeatureCollection",
  "features": [
    {
      "type": "Feature",
      "id": "node/11378596787",
      "properties": {
        "timestamp": "2023-11-26T22:42:17Z",
        "version": 1,
        "changeset": 144487706,
        "amenity": "university",
        "name": "IFSC Câmpus São Carlos",
        "id": "node/11378596787"
      },
      "geometry": {
        "type": "Point",
        "coordinates": [
          -53.0133924,
          -27.0921502
        ]
      }
    }
  ]
}
