{
  "type": "FeatureCollection",
  "features": [
    {
      "type": "Feature",
      "id": "node/1611135974",
      "properties": {
        "timestamp": "2018-07-19T18:00:40Z",
        "version": 7,
        "changeset": 60880048,
        "name": "INSS - Previdência Social",
        "office": "government",
        "id": "node/1611135974"
      },
      "geometry": {
        "type": "Point",
        "coordinates": [
          -42.2203368,
          -14.4996044
        ]
      }
    },
    {
      "type": "Feature",
      "id": "node/9716727147",
      "properties": {
        "timestamp": "2022-05-04T23:26:31Z",
        "version": 1,
        "changeset": 120563959,
        "addr:city": "Caculé",
        "addr:street": "Praça Coração de Jesus",
        "addr:suburb": "Centro",
        "government": "healthcare",
        "name": "Secretaria Municipal de Saúde",
        "office": "government",
        "id": "node/9716727147"
      },
      "geometry": {
        "type": "Point",
        "coordinates": [
          -42.2223083,
          -14.5040686
        ]
      }
    },
    {
      "type": "Feature",
      "id": "node/9741279153",
      "properties": {
        "timestamp": "2022-05-15T14:00:25Z",
        "version": 1,
        "changeset": 121013846,
        "government": "yes",
        "name": "Departamento de Esportes",
        "office": "government",
        "id": "node/9741279153"
      },
      "geometry": {
        "type": "Point",
        "coordinates": [
          -42.2249715,
          -14.5052802
        ]
      }
    },
    {
      "type": "Feature",
      "id": "node/9812281084",
      "properties": {
        "timestamp": "2022-06-12T13:30:11Z",
        "version": 1,
        "changeset": 122281270,
        "alt_name": "Retran Caculé",
        "government": "transportation",
        "name": "Detran",
        "office": "government",
        "id": "node/9812281084"
      },
      "geometry": {
        "type": "Point",
        "coordinates": [
          -42.2232364,
          -14.5060108
        ]
      }
    }
  ]
}
