{
  "type": "FeatureCollection",
  "features": [
    {
      "type": "Feature",
      "id": "node/530312171",
      "properties": {
        "timestamp": "2009-10-14T03:14:34Z",
        "version": 1,
        "changeset": 2841609,
        "amenity": "school",
        "name": "Instituto Estadual de Educação Madre Tereza",
        "id": "node/530312171"
      },
      "geometry": {
        "type": "Point",
        "coordinates": [
          -53.4029214,
          -27.4784301
        ]
      }
    },
    {
      "type": "Feature",
      "id": "node/707497724",
      "properties": {
        "timestamp": "2010-07-13T19:27:57Z",
        "version": 3,
        "changeset": 5211229,
        "addr:street": "Rua Alfredo Westphalen",
        "amenity": "school",
        "name": "Escola Estadual de 1° Grau Alfredo Westphalen",
        "id": "node/707497724"
      },
      "geometry": {
        "type": "Point",
        "coordinates": [
          -53.399515,
          -27.484123
        ]
      }
    },
    {
      "type": "Feature",
      "id": "node/992782043",
      "properties": {
        "timestamp": "2010-11-17T15:25:59Z",
        "version": 1,
        "changeset": 6393546,
        "amenity": "school",
        "name": "E.M.1° Grau Ministro Tarso Dutra",
        "id": "node/992782043"
      },
      "geometry": {
        "type": "Point",
        "coordinates": [
          -53.3471808,
          -27.4210214
        ]
      }
    },
    {
      "type": "Feature",
      "id": "node/9071996679",
      "properties": {
        "timestamp": "2021-09-07T21:35:56Z",
        "version": 1,
        "changeset": 110880446,
        "amenity": "school",
        "name": "Escola de Ensino Fundamental Ada Hemieleski",
        "id": "node/9071996679"
      },
      "geometry": {
        "type": "Point",
        "coordinates": [
          -53.4052306,
          -27.4739105
        ]
      }
    }
  ]
}
