{
  "type": "FeatureCollection",
  "features": [
    {
      "type": "Feature",
      "id": "node/5910111186",
      "properties": {
        "timestamp": "2018-09-16T17:11:11Z",
        "version": 1,
        "changeset": 62641190,
        "name": "Miluquinho Bicicletas",
        "shop": "bicycle",
        "id": "node/5910111186"
      },
      "geometry": {
        "type": "Point",
        "coordinates": [
          -57.0799717,
          -29.7659387
        ]
      }
    }
  ]
}
