{
  "type": "FeatureCollection",
  "features": [
    {
      "type": "Feature",
      "id": "node/9839054481",
      "properties": {
        "timestamp": "2022-06-22T15:29:26Z",
        "version": 1,
        "changeset": 122717376,
        "addr:city": "Uruguaiana",
        "addr:housenumber": "1438",
        "addr:postcode": "97501-570",
        "addr:street": "Rua Quinze de Novembro",
        "addr:suburb": "Centro",
        "amenity": "cinema",
        "name": "Cineprime",
        "website": "https://cineprimeuruguaiana.com.br/cine/",
        "id": "node/9839054481"
      },
      "geometry": {
        "type": "Point",
        "coordinates": [
          -57.0882464,
          -29.752273
        ]
      }
    }
  ]
}
