{
  "type": "FeatureCollection",
  "features": [
    {
      "type": "Feature",
      "id": "node/3992362105",
      "properties": {
        "timestamp": "2016-02-06T17:45:28Z",
        "version": 1,
        "changeset": 37045456,
        "addr:city": "Guanambi",
        "addr:housenumber": "44",
        "addr:street": "Rua Maria Regina Cardoso",
        "amenity": "doctors",
        "name": "Dra. Márcia Stela C. Bonfim Pediatra",
        "id": "node/3992362105"
      },
      "geometry": {
        "type": "Point",
        "coordinates": [
          -42.7812739,
          -14.2269245
        ]
      }
    },
    {
      "type": "Feature",
      "id": "node/6060804726",
      "properties": {
        "timestamp": "2019-06-16T14:13:24Z",
        "version": 2,
        "changeset": 71302224,
        "addr:city": "Guanambi",
        "addr:postcode": "46430-000",
        "addr:street": "Rua 13 de Maio",
        "addr:suburb": "São Francisco",
        "amenity": "doctors",
        "email": "karilenefernandes.dermato@gmail.com",
        "healthcare": "doctor",
        "healthcare:speciality": "dermatology",
        "is_in": "Hospital Policlinica; São Francisco; Guanambi; Bahia; Brasil",
        "name": "Karilena Fernandes Dermatologista",
        "phone": "+55 77 3451 1404",
        "id": "node/6060804726"
      },
      "geometry": {
        "type": "Point",
        "coordinates": [
          -42.7769264,
          -14.2198911
        ]
      }
    },
    {
      "type": "Feature",
      "id": "node/9029202675",
      "properties": {
        "timestamp": "2021-08-23T16:20:14Z",
        "version": 1,
        "changeset": 110126369,
        "addr:city": "Guanambi",
        "addr:housenumber": "25",
        "addr:postcode": "46430-000",
        "addr:street": "Rua Alto da Boa Vista",
        "addr:suburb": "Centro",
        "amenity": "doctors",
        "healthcare": "doctor",
        "healthcare:speciality": "cardiology",
        "name": "Dra. Barbara Fagundes Cardiologista",
        "id": "node/9029202675"
      },
      "geometry": {
        "type": "Point",
        "coordinates": [
          -42.7830852,
          -14.223429
        ]
      }
    }
  ]
}
