{
  "type": "FeatureCollection",
  "features": [
    {
      "type": "Feature",
      "id": "node/2825622056",
      "properties": {
        "timestamp": "2014-04-30T02:22:09Z",
        "version": 1,
        "changeset": 22034867,
        "addr:hamlet": "Sítio Bom Jardim",
        "addr:postcode": "57300000",
        "addr:street": "Sítio Flexeira",
        "amenity": "community_centre",
        "name": "Sede da Comunidade",
        "id": "node/2825622056"
      },
      "geometry": {
        "type": "Point",
        "coordinates": [
          -36.604083,
          -9.792648
        ]
      }
    }
  ]
}
