{
  "type": "FeatureCollection",
  "features": [
    {
      "type": "Feature",
      "id": "node/6863454400",
      "properties": {
        "timestamp": "2019-10-09T12:27:13Z",
        "version": 1,
        "changeset": 75460141,
        "amenity": "arts_centre",
        "name": "DTG Gaudérios do Vale (Departamento Tradicionalista Gaúcho)",
        "id": "node/6863454400"
      },
      "geometry": {
        "type": "Point",
        "coordinates": [
          -51.1535829,
          -29.7413591
        ]
      }
    }
  ]
}
