{
  "type": "FeatureCollection",
  "features": [
    {
      "type": "Feature",
      "id": "node/6912358891",
      "properties": {
        "timestamp": "2019-10-24T12:28:44Z",
        "version": 1,
        "changeset": 76151798,
        "amenity": "nursing_home",
        "name": "Entrada fazenda Canaã",
        "id": "node/6912358891"
      },
      "geometry": {
        "type": "Point",
        "coordinates": [
          -56.8175089,
          -21.9742798
        ]
      }
    }
  ]
}
