{
  "type": "FeatureCollection",
  "features": [
    {
      "type": "Feature",
      "id": "node/4039373092",
      "properties": {
        "timestamp": "2022-03-22T02:04:15Z",
        "version": 2,
        "changeset": 118758472,
        "amenity": "dentist",
        "healthcare": "dentist",
        "name": "Felipe Viek",
        "id": "node/4039373092"
      },
      "geometry": {
        "type": "Point",
        "coordinates": [
          -48.4992176,
          -27.198956
        ]
      }
    }
  ]
}
