{
  "type": "FeatureCollection",
  "features": [
    {
      "type": "Feature",
      "id": "node/12484253971",
      "properties": {
        "timestamp": "2025-01-08T11:45:52Z",
        "version": 1,
        "changeset": 161130362,
        "amenity": "hospital",
        "healthcare": "hospital",
        "name": "UPA 24 Horas - Bombas",
        "id": "node/12484253971"
      },
      "geometry": {
        "type": "Point",
        "coordinates": [
          -48.5065731,
          -27.1508811
        ]
      }
    }
  ]
}
