{
  "type": "FeatureCollection",
  "features": [
    {
      "type": "Feature",
      "id": "node/4009700470",
      "properties": {
        "timestamp": "2016-02-16T17:03:38Z",
        "version": 1,
        "changeset": 37250178,
        "amenity": "community_centre",
        "name": "Centro de Bairro Lagoinha",
        "id": "node/4009700470"
      },
      "geometry": {
        "type": "Point",
        "coordinates": [
          -48.261061,
          -18.9280053
        ]
      }
    },
    {
      "type": "Feature",
      "id": "node/4009702504",
      "properties": {
        "timestamp": "2016-02-16T17:03:40Z",
        "version": 1,
        "changeset": 37250178,
        "amenity": "community_centre",
        "name": "UAI",
        "id": "node/4009702504"
      },
      "geometry": {
        "type": "Point",
        "coordinates": [
          -48.2704525,
          -18.9154932
        ]
      }
    },
    {
      "type": "Feature",
      "id": "node/4011704470",
      "properties": {
        "timestamp": "2016-02-17T20:32:54Z",
        "version": 1,
        "changeset": 37275346,
        "amenity": "community_centre",
        "name": "Centro de Tecelágem",
        "id": "node/4011704470"
      },
      "geometry": {
        "type": "Point",
        "coordinates": [
          -48.2824469,
          -18.9326787
        ]
      }
    }
  ]
}
