{
  "type": "FeatureCollection",
  "features": [
    {
      "type": "Feature",
      "id": "node/9724544217",
      "properties": {
        "timestamp": "2022-05-08T11:26:10Z",
        "version": 1,
        "changeset": 120698536,
        "amenity": "community_centre",
        "name": "Esterqueira geração de energia",
        "id": "node/9724544217"
      },
      "geometry": {
        "type": "Point",
        "coordinates": [
          -53.3822734,
          -26.1663491
        ]
      }
    }
  ]
}
