{
  "type": "FeatureCollection",
  "features": [
    {
      "type": "Feature",
      "id": "node/3605077287",
      "properties": {
        "timestamp": "2015-06-19T12:09:10Z",
        "version": 1,
        "changeset": 32073627,
        "amenity": "school",
        "id": "node/3605077287"
      },
      "geometry": {
        "type": "Point",
        "coordinates": [
          -49.0994521,
          -3.8376849
        ]
      }
    },
    {
      "type": "Feature",
      "id": "node/3605086429",
      "properties": {
        "timestamp": "2015-06-19T12:09:11Z",
        "version": 1,
        "changeset": 32073627,
        "amenity": "school",
        "id": "node/3605086429"
      },
      "geometry": {
        "type": "Point",
        "coordinates": [
          -49.0995283,
          -3.8369901
        ]
      }
    },
    {
      "type": "Feature",
      "id": "node/3605086430",
      "properties": {
        "timestamp": "2015-06-19T12:09:11Z",
        "version": 1,
        "changeset": 32073627,
        "amenity": "school",
        "id": "node/3605086430"
      },
      "geometry": {
        "type": "Point",
        "coordinates": [
          -49.1001184,
          -3.8378037
        ]
      }
    },
    {
      "type": "Feature",
      "id": "node/3605086446",
      "properties": {
        "timestamp": "2015-09-28T03:39:57Z",
        "version": 2,
        "changeset": 34295705,
        "amenity": "school",
        "id": "node/3605086446"
      },
      "geometry": {
        "type": "Point",
        "coordinates": [
          -49.1026702,
          -3.8485894
        ]
      }
    },
    {
      "type": "Feature",
      "id": "node/3605086602",
      "properties": {
        "timestamp": "2015-06-19T12:09:12Z",
        "version": 1,
        "changeset": 32073627,
        "amenity": "school",
        "id": "node/3605086602"
      },
      "geometry": {
        "type": "Point",
        "coordinates": [
          -49.100338,
          -3.8457404
        ]
      }
    },
    {
      "type": "Feature",
      "id": "node/4556840989",
      "properties": {
        "timestamp": "2016-12-16T09:02:37Z",
        "version": 1,
        "changeset": 44441753,
        "amenity": "school",
        "name": "Conselhos de Goianésia",
        "id": "node/4556840989"
      },
      "geometry": {
        "type": "Point",
        "coordinates": [
          -49.105968,
          -3.8478286
        ]
      }
    },
    {
      "type": "Feature",
      "id": "node/11396029331",
      "properties": {
        "timestamp": "2023-12-05T13:08:50Z",
        "version": 1,
        "changeset": 144791491,
        "amenity": "school",
        "name": "EMEF MANOEL SILVA",
        "id": "node/11396029331"
      },
      "geometry": {
        "type": "Point",
        "coordinates": [
          -48.9224352,
          -3.9550535
        ]
      }
    }
  ]
}
