{
  "type": "FeatureCollection",
  "features": [
    {
      "type": "Feature",
      "id": "node/2038894026",
      "properties": {
        "timestamp": "2012-11-28T20:25:31Z",
        "version": 1,
        "changeset": 14078489,
        "name": "Hotel Lago Dourado",
        "tourism": "hotel",
        "id": "node/2038894026"
      },
      "geometry": {
        "type": "Point",
        "coordinates": [
          -53.0687984,
          -25.7570684
        ]
      }
    },
    {
      "type": "Feature",
      "id": "node/2123271647",
      "properties": {
        "timestamp": "2013-01-22T01:32:44Z",
        "version": 1,
        "changeset": 14740584,
        "name": "Dois Vizinhos Palace Hotel",
        "tourism": "hotel",
        "id": "node/2123271647"
      },
      "geometry": {
        "type": "Point",
        "coordinates": [
          -53.0565774,
          -25.745332
        ]
      }
    },
    {
      "type": "Feature",
      "id": "node/2123271660",
      "properties": {
        "timestamp": "2013-01-22T01:32:44Z",
        "version": 1,
        "changeset": 14740584,
        "name": "Hotel Requinte",
        "tourism": "hotel",
        "id": "node/2123271660"
      },
      "geometry": {
        "type": "Point",
        "coordinates": [
          -53.0567859,
          -25.7441268
        ]
      }
    }
  ]
}
