{
  "type": "FeatureCollection",
  "features": [
    {
      "type": "Feature",
      "id": "node/2825544724",
      "properties": {
        "timestamp": "2018-01-27T16:28:54Z",
        "version": 2,
        "changeset": 55808190,
        "historic": "monument",
        "name": "Cristo Redentor",
        "tourism": "attraction",
        "id": "node/2825544724"
      },
      "geometry": {
        "type": "Point",
        "coordinates": [
          -52.2600038,
          -15.8721519
        ]
      }
    }
  ]
}
