{
  "type": "FeatureCollection",
  "features": [
    {
      "type": "Feature",
      "id": "node/12385616026",
      "properties": {
        "timestamp": "2024-11-30T04:05:35Z",
        "version": 1,
        "changeset": 159762491,
        "amenity": "pharmacy",
        "healthcare": "pharmacy",
        "name": "Farmácia Torres",
        "id": "node/12385616026"
      },
      "geometry": {
        "type": "Point",
        "coordinates": [
          -40.5376642,
          -4.9439632
        ]
      }
    },
    {
      "type": "Feature",
      "id": "node/12385619282",
      "properties": {
        "timestamp": "2024-11-30T04:24:46Z",
        "version": 1,
        "changeset": 159762722,
        "amenity": "pharmacy",
        "healthcare": "pharmacy",
        "name": "Farma Sampaio",
        "id": "node/12385619282"
      },
      "geometry": {
        "type": "Point",
        "coordinates": [
          -40.5375107,
          -4.944009
        ]
      }
    },
    {
      "type": "Feature",
      "id": "node/12385619283",
      "properties": {
        "timestamp": "2024-11-30T04:24:46Z",
        "version": 1,
        "changeset": 159762722,
        "amenity": "pharmacy",
        "healthcare": "pharmacy",
        "name": "Farmácia Melhor Farma",
        "id": "node/12385619283"
      },
      "geometry": {
        "type": "Point",
        "coordinates": [
          -40.5375798,
          -4.9441226
        ]
      }
    }
  ]
}
