{
  "type": "FeatureCollection",
  "features": [
    {
      "type": "Feature",
      "id": "node/7718915597",
      "properties": {
        "timestamp": "2020-07-16T02:23:52Z",
        "version": 1,
        "changeset": 88056049,
        "access": "yes",
        "historic": "monument",
        "inscription": "Praça São Pedro",
        "name": "Praça São Pedro",
        "id": "node/7718915597"
      },
      "geometry": {
        "type": "Point",
        "coordinates": [
          -52.6261625,
          -31.5947267
        ]
      }
    },
    {
      "type": "Feature",
      "id": "node/7718915963",
      "properties": {
        "timestamp": "2020-07-16T02:23:52Z",
        "version": 1,
        "changeset": 88056049,
        "historic": "monument",
        "name": "Roda",
        "id": "node/7718915963"
      },
      "geometry": {
        "type": "Point",
        "coordinates": [
          -52.6403214,
          -31.5899112
        ]
      }
    }
  ]
}
