{
  "type": "FeatureCollection",
  "features": [
    {
      "type": "Feature",
      "id": "node/5857198561",
      "properties": {
        "timestamp": "2023-05-02T19:42:56Z",
        "version": 2,
        "changeset": 135631108,
        "addr:city": "Trindade do Sul",
        "addr:housenumber": "82",
        "addr:postcode": "99615-000",
        "addr:street": "Rua Cabiuna",
        "addr:suburb": "Centro",
        "amenity": "hospital",
        "healthcare": "hospital",
        "name": "Aspiazu Filhas Cia Ltda",
        "ref:CNES": "2235366",
        "ref:vatin": "BR97441307000160",
        "id": "node/5857198561"
      },
      "geometry": {
        "type": "Point",
        "coordinates": [
          -52.8871599,
          -27.5220087
        ]
      }
    }
  ]
}
