{
  "type": "FeatureCollection",
  "features": [
    {
      "type": "Feature",
      "id": "node/5985295042",
      "properties": {
        "timestamp": "2024-12-10T19:24:17Z",
        "version": 2,
        "changeset": 160141591,
        "addr:city": "Francisco Beltrao",
        "addr:postcode": "85601971",
        "addr:street": "Linha Santa Bárbara",
        "addr:suburb": "Rural",
        "amenity": "library",
        "email": "debib-fb@utfpr.edu.br",
        "internet_access": "wlan",
        "internet_access:fee": "no",
        "internet_access:ssid": "UTFPR_Web",
        "name": "Biblioteca da UTFPR",
        "nohousenumber": "yes",
        "opening_hours": "Mo-Su 08:00-22:00",
        "id": "node/5985295042"
      },
      "geometry": {
        "type": "Point",
        "coordinates": [
          -53.0914878,
          -26.0835243
        ]
      }
    }
  ]
}
