{
  "type": "FeatureCollection",
  "features": [
    {
      "type": "Feature",
      "id": "node/2379536484",
      "properties": {
        "timestamp": "2013-07-09T21:18:27Z",
        "version": 1,
        "changeset": 16892740,
        "amenity": "hospital",
        "name": "Hospital Municipal",
        "id": "node/2379536484"
      },
      "geometry": {
        "type": "Point",
        "coordinates": [
          -41.9856666,
          -11.2914476
        ]
      }
    }
  ]
}
