{
  "type": "FeatureCollection",
  "features": [
    {
      "type": "Feature",
      "id": "node/2697149063",
      "properties": {
        "timestamp": "2020-06-19T13:14:38Z",
        "version": 2,
        "changeset": 86879283,
        "building": "civic",
        "name": "Cartório Elias Farias",
        "office": "government",
        "id": "node/2697149063"
      },
      "geometry": {
        "type": "Point",
        "coordinates": [
          -35.9988979,
          -7.5233742
        ]
      }
    }
  ]
}
