{
  "type": "FeatureCollection",
  "features": [
    {
      "type": "Feature",
      "id": "node/5314090782",
      "properties": {
        "timestamp": "2017-12-31T21:51:25Z",
        "version": 1,
        "changeset": 55066561,
        "historic": "monument",
        "id": "node/5314090782"
      },
      "geometry": {
        "type": "Point",
        "coordinates": [
          -46.3278971,
          -22.3174087
        ]
      }
    },
    {
      "type": "Feature",
      "id": "node/9884561643",
      "properties": {
        "timestamp": "2022-07-13T08:22:07Z",
        "version": 1,
        "changeset": 123551292,
        "historic": "monument",
        "name": "Monumento ao Romeiro",
        "id": "node/9884561643"
      },
      "geometry": {
        "type": "Point",
        "coordinates": [
          -46.3322184,
          -22.3168135
        ]
      }
    }
  ]
}
