{
  "type": "FeatureCollection",
  "features": [
    {
      "type": "Feature",
      "id": "node/11015181338",
      "properties": {
        "timestamp": "2023-06-30T04:56:23Z",
        "version": 1,
        "changeset": 137940983,
        "addr:city": "Inconfidentes",
        "addr:housenumber": "178",
        "addr:postcode": "37576-000",
        "addr:street": "Rua Sargento Mor Toledo Pizza",
        "addr:suburb": "Centro",
        "amenity": "social_facility",
        "contact:phone": "0800 726 0101",
        "name": "CRAS Inconfidentes",
        "id": "node/11015181338"
      },
      "geometry": {
        "type": "Point",
        "coordinates": [
          -46.3306085,
          -22.3169392
        ]
      }
    }
  ]
}
