{
  "type": "FeatureCollection",
  "features": [
    {
      "type": "Feature",
      "id": "node/2115182806",
      "properties": {
        "timestamp": "2013-01-17T04:07:29Z",
        "version": 1,
        "changeset": 14679801,
        "amenity": "hospital",
        "name": "Santa Casa de Sengés",
        "id": "node/2115182806"
      },
      "geometry": {
        "type": "Point",
        "coordinates": [
          -49.4697428,
          -24.1138913
        ]
      }
    }
  ]
}
