{
  "type": "FeatureCollection",
  "features": [
    {
      "type": "Feature",
      "id": "node/4062388809",
      "properties": {
        "timestamp": "2016-03-15T21:47:18Z",
        "version": 1,
        "changeset": 37857356,
        "amenity": "school",
        "name": "Escola Estadual Erasmo Braga",
        "id": "node/4062388809"
      },
      "geometry": {
        "type": "Point",
        "coordinates": [
          -49.4622822,
          -24.1142965
        ]
      }
    }
  ]
}
