{
  "type": "FeatureCollection",
  "features": [
    {
      "type": "Feature",
      "id": "node/3819493395",
      "properties": {
        "timestamp": "2018-01-02T22:22:14Z",
        "version": 3,
        "changeset": 55113667,
        "addr:street": "BR 381",
        "name": "Hotel Primavera",
        "tourism": "hotel",
        "id": "node/3819493395"
      },
      "geometry": {
        "type": "Point",
        "coordinates": [
          -43.3477148,
          -19.8364108
        ]
      }
    }
  ]
}
