{
  "type": "FeatureCollection",
  "features": [
    {
      "type": "Feature",
      "id": "node/10855353905",
      "properties": {
        "timestamp": "2023-04-29T03:30:16Z",
        "version": 1,
        "changeset": 135489725,
        "amenity": "hospital",
        "name": "Pólo Base São Pedro",
        "id": "node/10855353905"
      },
      "geometry": {
        "type": "Point",
        "coordinates": [
          -65.737949,
          -7.9168153
        ]
      }
    }
  ]
}
