{
  "type": "FeatureCollection",
  "features": [
    {
      "type": "Feature",
      "id": "node/2062357745",
      "properties": {
        "timestamp": "2017-03-18T01:22:12Z",
        "version": 5,
        "changeset": 46945563,
        "addr:city": "Santos",
        "addr:housenumber": "4",
        "addr:street": "Rua Prefeito Antenor Bué",
        "addr:suburb": "Aparecida",
        "name": "Ciclomania",
        "phone": "+55 13 3238-7949",
        "shop": "bicycle",
        "id": "node/2062357745"
      },
      "geometry": {
        "type": "Point",
        "coordinates": [
          -46.3081825,
          -23.9720796
        ]
      }
    },
    {
      "type": "Feature",
      "id": "node/11160055281",
      "properties": {
        "timestamp": "2023-09-01T02:15:59Z",
        "version": 1,
        "changeset": 140658659,
        "addr:city": "Santos",
        "addr:housenumber": "128",
        "addr:street": "Rua Oswaldo Cochrane",
        "addr:suburb": "Embaré",
        "name": "Greco Bike",
        "phone": "+55 13 3321 9196",
        "shop": "bicycle",
        "id": "node/11160055281"
      },
      "geometry": {
        "type": "Point",
        "coordinates": [
          -46.3149557,
          -23.9728953
        ]
      }
    }
  ]
}
