{
  "type": "FeatureCollection",
  "features": [
    {
      "type": "Feature",
      "id": "node/12587702148",
      "properties": {
        "timestamp": "2025-02-14T14:50:57Z",
        "version": 1,
        "changeset": 162506292,
        "addr:city": "Camboriú",
        "addr:housenumber": "497",
        "addr:postcode": "88340206",
        "addr:street": "Avenida José Francisco Bernardes",
        "addr:suburb": "Centro",
        "amenity": "dentist",
        "currency:XBT": "yes",
        "email": "lealptais@gmail.com",
        "healthcare": "dentist",
        "healthcare:speciality": "implantes_dentários;cirurgia_ortognática;sisos;dtm;orthodontics;aparelho_fixo;aparelho_invisivel;clinico_geral;endodontia;harmonização",
        "name": "Leal Clinic Odontologia",
        "opening_hours": "Mo-Sa 08:00-18:00",
        "payment:bitcoin": "yes",
        "payment:lightning": "yes",
        "phone": "+5547996312283",
        "website": "https://lealclinic.com.br",
        "id": "node/12587702148"
      },
      "geometry": {
        "type": "Point",
        "coordinates": [
          -48.6549104,
          -27.0269637
        ]
      }
    }
  ]
}
