{
  "type": "FeatureCollection",
  "features": [
    {
      "type": "Feature",
      "id": "node/2555820548",
      "properties": {
        "timestamp": "2013-11-28T16:45:57Z",
        "version": 1,
        "changeset": 19163529,
        "name": "Cachoeira Utiariti",
        "waterway": "waterfall",
        "id": "node/2555820548"
      },
      "geometry": {
        "type": "Point",
        "coordinates": [
          -58.2781852,
          -13.0258213
        ]
      }
    },
    {
      "type": "Feature",
      "id": "node/4579791696",
      "properties": {
        "timestamp": "2020-06-05T14:32:06Z",
        "version": 3,
        "changeset": 86249660,
        "name": "Balneário do Pubi",
        "waterway": "waterfall",
        "id": "node/4579791696"
      },
      "geometry": {
        "type": "Point",
        "coordinates": [
          -58.407227,
          -13.560883
        ]
      }
    },
    {
      "type": "Feature",
      "id": "node/5637597650",
      "properties": {
        "timestamp": "2018-05-23T13:59:36Z",
        "version": 1,
        "changeset": 59212603,
        "waterway": "waterfall",
        "id": "node/5637597650"
      },
      "geometry": {
        "type": "Point",
        "coordinates": [
          -58.5979816,
          -13.3991903
        ]
      }
    }
  ]
}
