{
  "type": "FeatureCollection",
  "features": [
    {
      "type": "Feature",
      "id": "node/9349901023",
      "properties": {
        "timestamp": "2022-10-22T14:21:42Z",
        "version": 3,
        "changeset": 127924460,
        "amenity": "community_centre",
        "name": "Área de Lazer Green Ville",
        "id": "node/9349901023"
      },
      "geometry": {
        "type": "Point",
        "coordinates": [
          -47.7116285,
          -21.5542847
        ]
      }
    }
  ]
}
