{
  "type": "FeatureCollection",
  "features": [
    {
      "type": "Feature",
      "id": "node/9049000091",
      "properties": {
        "timestamp": "2022-05-23T17:47:38Z",
        "version": 2,
        "changeset": 121382969,
        "addr:city": "Dracena",
        "addr:housenumber": "1564",
        "addr:postcode": "17900000",
        "addr:street": "Rua São Paulo",
        "addr:suburb": "Centro",
        "alt_name": "crosp;CROSP;crosp dracena;CROSP Dracena",
        "government": "administrative",
        "name": "Conselho Regional de Odontologia do Estado de São Paulo- Seccional Dracena",
        "office": "government",
        "phone": "+55 18 38230949",
        "website": "https://www.crosp.org.br/",
        "id": "node/9049000091"
      },
      "geometry": {
        "type": "Point",
        "coordinates": [
          -51.5378061,
          -21.4825278
        ]
      }
    },
    {
      "type": "Feature",
      "id": "node/10822667649",
      "properties": {
        "timestamp": "2023-04-18T19:32:41Z",
        "version": 1,
        "changeset": 135074286,
        "addr:city": "Dracena",
        "addr:housenumber": "411",
        "addr:postcode": "17900000",
        "addr:street": "Rua Duque de Caxias",
        "addr:suburb": "Centro",
        "government": "register_office",
        "name": "Tabelião de Notas e de Protesto",
        "office": "government",
        "phone": "55-18.3821.3307",
        "id": "node/10822667649"
      },
      "geometry": {
        "type": "Point",
        "coordinates": [
          -51.5329947,
          -21.4853024
        ]
      }
    }
  ]
}
