{
  "type": "FeatureCollection",
  "features": [
    {
      "type": "Feature",
      "id": "node/12571055102",
      "properties": {
        "timestamp": "2025-02-09T13:52:56Z",
        "version": 1,
        "changeset": 162315405,
        "addr:housenumber": "0",
        "addr:postcode": "68567000",
        "addr:street": "Avenida José Martins de Resende",
        "amenity": "school",
        "name": "Colégio estadual casa de tábua",
        "id": "node/12571055102"
      },
      "geometry": {
        "type": "Point",
        "coordinates": [
          -50.470152,
          -8.7849342
        ]
      }
    }
  ]
}
