{
  "type": "FeatureCollection",
  "features": [
    {
      "type": "Feature",
      "id": "node/8887509132",
      "properties": {
        "timestamp": "2021-07-02T11:24:10Z",
        "version": 1,
        "changeset": 107307737,
        "addr:city": "Cotia - SP",
        "addr:housenumber": "35",
        "addr:postcode": "06710-700",
        "addr:street": "Rua Adib Auada - Sala 110c",
        "addr:suburb": "Jardim Lambreta",
        "amenity": "dentist",
        "healthcare": "dentist",
        "healthcare:speciality": "Dentista",
        "name": "Prime Care - Odontologia e Saúde Integrada",
        "id": "node/8887509132"
      },
      "geometry": {
        "type": "Point",
        "coordinates": [
          -46.8286311,
          -23.5912646
        ]
      }
    }
  ]
}
