{
  "type": "FeatureCollection",
  "features": [
    {
      "type": "Feature",
      "id": "node/9552413924",
      "properties": {
        "timestamp": "2022-03-03T17:47:36Z",
        "version": 1,
        "changeset": 118064924,
        "addr:street": "Avenida Fernando Nobre",
        "addr:suburb": "Parque Rincão",
        "amenity": "veterinary",
        "contact:mobile": "+55 11 98480 2890",
        "name": "Clinica Veterinária e Pet Shop",
        "phone": "+55 11 4551 4516",
        "id": "node/9552413924"
      },
      "geometry": {
        "type": "Point",
        "coordinates": [
          -46.8809185,
          -23.5870224
        ]
      }
    }
  ]
}
