{
  "type": "FeatureCollection",
  "features": [
    {
      "type": "Feature",
      "id": "node/3832569319",
      "properties": {
        "timestamp": "2015-11-12T13:36:04Z",
        "version": 1,
        "changeset": 35261275,
        "amenity": "library",
        "name": "Biblioteca Pública",
        "id": "node/3832569319"
      },
      "geometry": {
        "type": "Point",
        "coordinates": [
          -36.858787,
          -10.7379559
        ]
      }
    }
  ]
}
