{
  "type": "FeatureCollection",
  "features": [
    {
      "type": "Feature",
      "id": "node/5425952014",
      "properties": {
        "timestamp": "2022-01-18T17:30:19Z",
        "version": 4,
        "changeset": 116308823,
        "addr:city": "Petrolina",
        "addr:housenumber": "356",
        "addr:postcode": "56304-340",
        "addr:street": "Rua Castro Alves",
        "addr:suburb": "Centro",
        "amenity": "dentist",
        "healthcare": "dentist",
        "name": "Clin Odontologia Integrada",
        "id": "node/5425952014"
      },
      "geometry": {
        "type": "Point",
        "coordinates": [
          -40.5037122,
          -9.3942345
        ]
      }
    }
  ]
}
