{
  "type": "FeatureCollection",
  "features": [
    {
      "type": "Feature",
      "id": "node/12579157239",
      "properties": {
        "timestamp": "2025-02-11T15:24:32Z",
        "version": 1,
        "changeset": 162395748,
        "addr:street": "Rua Ipiranga",
        "amenity": "health_post",
        "name": "UBS Maria Iraci Lobato Rocha",
        "id": "node/12579157239"
      },
      "geometry": {
        "type": "Point",
        "coordinates": [
          -45.1591316,
          -10.4368113
        ]
      }
    }
  ]
}
