{
  "type": "FeatureCollection",
  "features": [
    {
      "type": "Feature",
      "id": "node/5029708922",
      "properties": {
        "timestamp": "2024-09-08T11:33:44Z",
        "version": 2,
        "changeset": 156347268,
        "amenity": "hospital",
        "healthcare": "hospital",
        "name": "Hospital Municipal de Fonte Boa",
        "name:pt": "Hospital Municipal de Fonte Boa",
        "id": "node/5029708922"
      },
      "geometry": {
        "type": "Point",
        "coordinates": [
          -66.0979716,
          -2.5182433
        ]
      }
    }
  ]
}
