{
  "type": "FeatureCollection",
  "features": [
    {
      "type": "Feature",
      "id": "node/5029708922",
      "properties": {
        "timestamp": "2017-08-12T00:44:17Z",
        "version": 1,
        "changeset": 51047566,
        "amenity": "hospital",
        "name": "Hospital Municipal de Fonte Boa",
        "name:pt": "Hospital Municipal de Fonte Boa",
        "id": "node/5029708922"
      },
      "geometry": {
        "type": "Point",
        "coordinates": [
          -66.0979716,
          -2.5182433
        ]
      }
    }
  ]
}
