{
  "type": "FeatureCollection",
  "features": [
    {
      "type": "Feature",
      "id": "node/6506968286",
      "properties": {
        "timestamp": "2019-05-28T19:01:32Z",
        "version": 1,
        "changeset": 70708391,
        "amenity": "pharmacy",
        "name": "Pague menos",
        "name:en": "Drugstore",
        "id": "node/6506968286"
      },
      "geometry": {
        "type": "Point",
        "coordinates": [
          -38.8313401,
          -3.556121
        ]
      }
    }
  ]
}
