{
  "type": "FeatureCollection",
  "features": [
    {
      "type": "Feature",
      "id": "node/6182525821",
      "properties": {
        "timestamp": "2023-10-13T18:42:30Z",
        "version": 3,
        "changeset": 142535767,
        "addr:housenumber": "481",
        "addr:street": "Avenida Dona Beatriz Braga",
        "addr:suburb": "Pecém",
        "amenity": "university",
        "contact:phone": "0800 006 1717",
        "name": "UniAteneu - Pecém",
        "website": "https://uniateneu.edu.br/",
        "id": "node/6182525821"
      },
      "geometry": {
        "type": "Point",
        "coordinates": [
          -38.8359984,
          -3.5537934
        ]
      }
    }
  ]
}
