{
  "type": "FeatureCollection",
  "features": [
    {
      "type": "Feature",
      "id": "node/8038552122",
      "properties": {
        "timestamp": "2020-10-23T01:29:22Z",
        "version": 2,
        "changeset": 92923444,
        "amenity": "clinic",
        "healthcare": "clinic",
        "name": "Posto de Saúde Figueirinha",
        "id": "node/8038552122"
      },
      "geometry": {
        "type": "Point",
        "coordinates": [
          -50.0478112,
          -29.7847537
        ]
      }
    }
  ]
}
