{
  "type": "FeatureCollection",
  "features": [
    {
      "type": "Feature",
      "id": "node/8039440115",
      "properties": {
        "timestamp": "2023-05-18T22:51:28Z",
        "version": 4,
        "changeset": 136275689,
        "addr:housenumber": "2001",
        "addr:postcode": "95588-000",
        "addr:street": "Rua Elias João Medeiros",
        "addr:suburb": "Santorini",
        "amenity": "hospital",
        "healthcare": "hospital",
        "name": "Hospital Lifeplus Litoral Norte",
        "ref:CNES": "958077",
        "ref:vatin": "BR43239279000173",
        "id": "node/8039440115"
      },
      "geometry": {
        "type": "Point",
        "coordinates": [
          -50.0546442,
          -29.8011263
        ]
      }
    }
  ]
}
