{
  "type": "FeatureCollection",
  "features": [
    {
      "type": "Feature",
      "id": "node/5775129549",
      "properties": {
        "timestamp": "2018-07-21T14:45:50Z",
        "version": 1,
        "changeset": 60932428,
        "amenity": "community_centre",
        "community_centre": "club_home",
        "name": "CTG Estrela Serrana",
        "source": "IBGE",
        "id": "node/5775129549"
      },
      "geometry": {
        "type": "Point",
        "coordinates": [
          -50.790385,
          -29.3438684
        ]
      }
    },
    {
      "type": "Feature",
      "id": "node/7637005625",
      "properties": {
        "timestamp": "2020-06-20T01:54:55Z",
        "version": 1,
        "changeset": 86898218,
        "amenity": "community_centre",
        "id": "node/7637005625"
      },
      "geometry": {
        "type": "Point",
        "coordinates": [
          -50.8125346,
          -29.3499381
        ]
      }
    }
  ]
}
