{
  "type": "FeatureCollection",
  "features": [
    {
      "type": "Feature",
      "id": "node/1614840492",
      "properties": {
        "timestamp": "2017-04-12T00:28:08Z",
        "version": 2,
        "changeset": 47678743,
        "name": "Poço",
        "waterway": "waterfall",
        "id": "node/1614840492"
      },
      "geometry": {
        "type": "Point",
        "coordinates": [
          -50.8342152,
          -29.3974883
        ]
      }
    },
    {
      "type": "Feature",
      "id": "node/1614840496",
      "properties": {
        "timestamp": "2017-04-12T00:28:08Z",
        "version": 2,
        "changeset": 47678743,
        "name": "Usina",
        "waterway": "waterfall",
        "id": "node/1614840496"
      },
      "geometry": {
        "type": "Point",
        "coordinates": [
          -50.8336761,
          -29.3973925
        ]
      }
    },
    {
      "type": "Feature",
      "id": "node/4760874121",
      "properties": {
        "timestamp": "2017-03-29T00:19:07Z",
        "version": 1,
        "changeset": 47245451,
        "name": "Cascata do Arroio Caçador",
        "waterway": "waterfall",
        "id": "node/4760874121"
      },
      "geometry": {
        "type": "Point",
        "coordinates": [
          -50.8425674,
          -29.2654344
        ]
      }
    },
    {
      "type": "Feature",
      "id": "node/6239087211",
      "properties": {
        "timestamp": "2019-01-27T04:42:21Z",
        "version": 1,
        "changeset": 66669065,
        "fixme": "Confirmar existência de queda d'água neste local",
        "waterway": "waterfall",
        "id": "node/6239087211"
      },
      "geometry": {
        "type": "Point",
        "coordinates": [
          -50.7224125,
          -29.3946035
        ]
      }
    }
  ]
}
