{
  "type": "FeatureCollection",
  "features": [
    {
      "type": "Feature",
      "id": "node/5228998908",
      "properties": {
        "timestamp": "2017-11-14T20:56:14Z",
        "version": 1,
        "changeset": 53783320,
        "name": "Cachoeira Cujubim",
        "waterway": "waterfall",
        "id": "node/5228998908"
      },
      "geometry": {
        "type": "Point",
        "coordinates": [
          -62.2827438,
          1.7526281
        ]
      }
    },
    {
      "type": "Feature",
      "id": "node/5228998909",
      "properties": {
        "timestamp": "2017-11-14T20:56:14Z",
        "version": 1,
        "changeset": 53783320,
        "name": "Cachoeira do Uruçu",
        "waterway": "waterfall",
        "id": "node/5228998909"
      },
      "geometry": {
        "type": "Point",
        "coordinates": [
          -62.3624078,
          1.6134145
        ]
      }
    }
  ]
}
