{
  "type": "FeatureCollection",
  "features": [
    {
      "type": "Feature",
      "id": "node/3479223516",
      "properties": {
        "timestamp": "2015-11-10T19:36:32Z",
        "version": 2,
        "changeset": 35224610,
        "name": "Cachoeira do Cubatão",
        "waterway": "waterfall",
        "id": "node/3479223516"
      },
      "geometry": {
        "type": "Point",
        "coordinates": [
          -45.1761012,
          -22.4120741
        ]
      }
    }
  ]
}
