{
  "type": "FeatureCollection",
  "features": [
    {
      "type": "Feature",
      "id": "node/6723691964",
      "properties": {
        "timestamp": "2024-12-07T21:30:42Z",
        "version": 2,
        "changeset": 160040301,
        "addr:city": "Cotiporã",
        "addr:postcode": "95335-000",
        "addr:street": "Estrada Linha Brasil",
        "addr:suburb": "N Sra do Caravaggio",
        "brand": "Pousada Piccolo Refugio",
        "name": "Edaci Paludo",
        "nohousenumber": "yes",
        "tourism": "hotel",
        "id": "node/6723691964"
      },
      "geometry": {
        "type": "Point",
        "coordinates": [
          -51.7045287,
          -29.0090488
        ]
      }
    },
    {
      "type": "Feature",
      "id": "node/6735283929",
      "properties": {
        "timestamp": "2019-08-22T12:22:44Z",
        "version": 1,
        "changeset": 73621703,
        "addr:city": "Cotiporã",
        "addr:housenumber": "514",
        "addr:postcode": "95335-000",
        "addr:street": "Rua Souza Lobo",
        "addr:suburb": "Centro",
        "brand": "Roseli Maria Gomes",
        "name": "Hotel Dal Molin",
        "tourism": "hotel",
        "id": "node/6735283929"
      },
      "geometry": {
        "type": "Point",
        "coordinates": [
          -51.696147,
          -28.9930964
        ]
      }
    }
  ]
}
