{
  "type": "FeatureCollection",
  "features": [
    {
      "type": "Feature",
      "id": "node/6735283929",
      "properties": {
        "timestamp": "2019-08-22T12:22:44Z",
        "version": 1,
        "changeset": 73621703,
        "addr:city": "Cotiporã",
        "addr:housenumber": "514",
        "addr:postcode": "95335-000",
        "addr:street": "Rua Souza Lobo",
        "addr:suburb": "Centro",
        "brand": "Roseli Maria Gomes",
        "name": "Hotel Dal Molin",
        "tourism": "hotel",
        "id": "node/6735283929"
      },
      "geometry": {
        "type": "Point",
        "coordinates": [
          -51.696147,
          -28.9930964
        ]
      }
    }
  ]
}
