{
  "type": "FeatureCollection",
  "features": [
    {
      "type": "Feature",
      "id": "node/10700164468",
      "properties": {
        "timestamp": "2023-10-18T05:09:22Z",
        "version": 2,
        "changeset": 142741927,
        "addr:city": "Ubaíra",
        "addr:housenumber": "BA-550",
        "addr:postcode": "45310000",
        "addr:street": "Fazenda Três Lagoas",
        "email": "contato@tehanatural.com.br",
        "internet_access": "wlan",
        "name": "Pousada Teha",
        "note": "Nosso objetivo é proporcionar uma experiência marcante de hospedagem e alimentação com foco no contato com a natureza, produção caseira e simplicidade",
        "phone": "+55 71 992650442",
        "rooms": "13",
        "tourism": "hotel",
        "website": "https://tehanatural.com.br/",
        "id": "node/10700164468"
      },
      "geometry": {
        "type": "Point",
        "coordinates": [
          -39.7004993,
          -13.3451211
        ]
      }
    }
  ]
}
