{
  "type": "FeatureCollection",
  "features": [
    {
      "type": "Feature",
      "id": "node/4315586290",
      "properties": {
        "timestamp": "2016-07-22T12:03:44Z",
        "version": 1,
        "changeset": 40948870,
        "historic": "monument",
        "name": "CD PONTO RURAL",
        "id": "node/4315586290"
      },
      "geometry": {
        "type": "Point",
        "coordinates": [
          -51.2353106,
          -23.2920731
        ]
      }
    }
  ]
}
