{
  "type": "FeatureCollection",
  "features": [
    {
      "type": "Feature",
      "id": "node/4713525912",
      "properties": {
        "timestamp": "2019-05-22T22:04:34Z",
        "version": 2,
        "changeset": 70532020,
        "name": "Cachoeira do Ancião",
        "waterway": "waterfall",
        "id": "node/4713525912"
      },
      "geometry": {
        "type": "Point",
        "coordinates": [
          -42.9567451,
          -22.2297185
        ]
      }
    }
  ]
}
