{
  "type": "FeatureCollection",
  "features": [
    {
      "type": "Feature",
      "id": "node/3622463600",
      "properties": {
        "timestamp": "2015-06-27T20:35:55Z",
        "version": 1,
        "changeset": 32250991,
        "amenity": "social_facility",
        "name": "Assistência Social",
        "id": "node/3622463600"
      },
      "geometry": {
        "type": "Point",
        "coordinates": [
          -53.1776834,
          -29.7330164
        ]
      }
    }
  ]
}
