{
  "type": "FeatureCollection",
  "features": [
    {
      "type": "Feature",
      "id": "node/4808552249",
      "properties": {
        "timestamp": "2018-09-04T18:12:05Z",
        "version": 2,
        "changeset": 62287880,
        "amenity": "school",
        "name": "Escola Estadual de Ensino Fundamental Santa Isabel",
        "source": "IBGE",
        "id": "node/4808552249"
      },
      "geometry": {
        "type": "Point",
        "coordinates": [
          -52.5977706,
          -32.1171309
        ]
      }
    },
    {
      "type": "Feature",
      "id": "node/4808552260",
      "properties": {
        "timestamp": "2017-04-21T22:31:54Z",
        "version": 1,
        "changeset": 48017961,
        "amenity": "school",
        "name": "Escola Municipal Silvina Gonçalves",
        "operator": "Secretaria Municipal da Educação",
        "source": "IBGE",
        "id": "node/4808552260"
      },
      "geometry": {
        "type": "Point",
        "coordinates": [
          -53.0933028,
          -32.2255689
        ]
      }
    }
  ]
}
