{
  "type": "FeatureCollection",
  "features": [
    {
      "type": "Feature",
      "id": "node/11328141201",
      "properties": {
        "timestamp": "2023-11-05T20:27:25Z",
        "version": 1,
        "changeset": 143665163,
        "addr:city": "Aquidauana",
        "addr:housenumber": "398",
        "addr:postcode": "79200000",
        "addr:street": "Rua Augusto Mascarenhas",
        "addr:suburb": "Centro",
        "amenity": "dentist",
        "healthcare": "dentist",
        "healthcare:speciality": "orthodontics",
        "name": "Dra. Camila Moroto",
        "opening_hours": "Mo-Fr 10:00-19:00",
        "id": "node/11328141201"
      },
      "geometry": {
        "type": "Point",
        "coordinates": [
          -55.7945007,
          -20.4780322
        ]
      }
    }
  ]
}
