{
  "type": "FeatureCollection",
  "features": [
    {
      "type": "Feature",
      "id": "node/7894856882",
      "properties": {
        "timestamp": "2020-09-10T19:49:08Z",
        "version": 1,
        "changeset": 90720218,
        "addr:city": "Manacapuru-AM",
        "addr:housenumber": "1321",
        "addr:postcode": "69400-000",
        "addr:street": "Avenida Eduardo Ribeiro",
        "addr:suburb": "Centro",
        "government": "register_office",
        "name": "Cartório 2º Ofício",
        "office": "government",
        "id": "node/7894856882"
      },
      "geometry": {
        "type": "Point",
        "coordinates": [
          -60.6193069,
          -3.3033793
        ]
      }
    },
    {
      "type": "Feature",
      "id": "node/7894896507",
      "properties": {
        "timestamp": "2020-09-10T19:52:04Z",
        "version": 1,
        "changeset": 90720316,
        "addr:city": "Manacapuru-AM",
        "addr:housenumber": "1161",
        "addr:postcode": "69400-000",
        "addr:street": "Avenida Getúlio Vargas",
        "addr:suburb": "Centro",
        "name": "Câmara Municipal de Manacapuru",
        "office": "government",
        "id": "node/7894896507"
      },
      "geometry": {
        "type": "Point",
        "coordinates": [
          -60.6197444,
          -3.3031839
        ]
      }
    },
    {
      "type": "Feature",
      "id": "node/7913383256",
      "properties": {
        "timestamp": "2022-10-18T22:21:03Z",
        "version": 2,
        "changeset": 127749447,
        "addr:city": "Manacapuru",
        "addr:postcode": "69400000",
        "addr:street": "Avenida Eduardo Ribeiro",
        "addr:suburb": "Centro",
        "government": "social_security",
        "name": "Agência Da Previdência Social (INSS)",
        "office": "government",
        "operator": "Instituto Nacional do Seguro Social",
        "operator:short": "INSS",
        "operator:wikidata": "Q10302614",
        "id": "node/7913383256"
      },
      "geometry": {
        "type": "Point",
        "coordinates": [
          -60.6252759,
          -3.2998047
        ]
      }
    }
  ]
}
