{
  "type": "FeatureCollection",
  "features": [
    {
      "type": "Feature",
      "id": "node/12138912894",
      "properties": {
        "timestamp": "2024-08-27T01:14:22Z",
        "version": 1,
        "changeset": 155807112,
        "addr:housenumber": "157",
        "addr:street": "Av Nove de Julho",
        "name": "Hotel Tupi",
        "phone": "018 99739-7778",
        "tourism": "hotel",
        "id": "node/12138912894"
      },
      "geometry": {
        "type": "Point",
        "coordinates": [
          -51.577928,
          -21.3920713
        ]
      }
    }
  ]
}
