{
  "type": "FeatureCollection",
  "features": [
    {
      "type": "Feature",
      "id": "node/5046838825",
      "properties": {
        "timestamp": "2017-08-20T20:20:59Z",
        "version": 1,
        "changeset": 51285751,
        "amenity": "library",
        "name": "Biblioteca Municipal Pedro Meneses Sobrinho",
        "name:pt": "Biblioteca Municipal Pedro Meneses Sobrinho",
        "id": "node/5046838825"
      },
      "geometry": {
        "type": "Point",
        "coordinates": [
          -37.5104327,
          -7.3852377
        ]
      }
    }
  ]
}
