{
  "type": "FeatureCollection",
  "features": [
    {
      "type": "Feature",
      "id": "node/5046838722",
      "properties": {
        "timestamp": "2021-02-20T21:15:55Z",
        "version": 2,
        "changeset": 99660429,
        "amenity": "pharmacy",
        "healthcare": "pharmacy",
        "name": "Mega Pharma",
        "name:pt": "Mega Pharma",
        "id": "node/5046838722"
      },
      "geometry": {
        "type": "Point",
        "coordinates": [
          -37.5113949,
          -7.3885321
        ]
      }
    }
  ]
}
