{
  "type": "FeatureCollection",
  "features": [
    {
      "type": "Feature",
      "id": "node/4456875889",
      "properties": {
        "timestamp": "2021-08-03T20:12:35Z",
        "version": 3,
        "changeset": 109112240,
        "amenity": "clinic",
        "healthcare": "clinic",
        "name": "Lotus spa urbano",
        "name:pt": "Lotus spa urbano",
        "id": "node/4456875889"
      },
      "geometry": {
        "type": "Point",
        "coordinates": [
          -39.0740518,
          -13.3721846
        ]
      }
    },
    {
      "type": "Feature",
      "id": "node/6718398885",
      "properties": {
        "timestamp": "2019-08-17T13:37:55Z",
        "version": 1,
        "changeset": 73443084,
        "amenity": "clinic",
        "name": "Policlínica Regional de Saúde do Baixo Sul",
        "id": "node/6718398885"
      },
      "geometry": {
        "type": "Point",
        "coordinates": [
          -39.0659288,
          -13.3686151
        ]
      }
    }
  ]
}
