{
  "type": "FeatureCollection",
  "features": [
    {
      "type": "Feature",
      "id": "node/3467988571",
      "properties": {
        "timestamp": "2015-04-20T17:28:18Z",
        "version": 1,
        "changeset": 30359528,
        "name": "Prefeitura Municipal",
        "office": "government",
        "id": "node/3467988571"
      },
      "geometry": {
        "type": "Point",
        "coordinates": [
          -39.0714965,
          -13.3707073
        ]
      }
    },
    {
      "type": "Feature",
      "id": "node/3468000170",
      "properties": {
        "timestamp": "2015-04-20T17:34:19Z",
        "version": 1,
        "changeset": 30359655,
        "office": "government",
        "id": "node/3468000170"
      },
      "geometry": {
        "type": "Point",
        "coordinates": [
          -39.0714106,
          -13.3703942
        ]
      }
    }
  ]
}
