{
  "type": "FeatureCollection",
  "features": [
    {
      "type": "Feature",
      "id": "node/4637528692",
      "properties": {
        "timestamp": "2017-01-27T14:02:41Z",
        "version": 1,
        "changeset": 45559892,
        "amenity": "library",
        "name": "Entrada pra Agapito",
        "name:pt": "Entrada pra Agapito",
        "id": "node/4637528692"
      },
      "geometry": {
        "type": "Point",
        "coordinates": [
          -39.1742957,
          -13.4967729
        ]
      }
    }
  ]
}
