{
  "type": "FeatureCollection",
  "features": [
    {
      "type": "Feature",
      "id": "node/11077280452",
      "properties": {
        "timestamp": "2023-07-30T16:54:24Z",
        "version": 1,
        "changeset": 139218142,
        "name": "Cachoeira da Laje",
        "waterway": "waterfall",
        "id": "node/11077280452"
      },
      "geometry": {
        "type": "Point",
        "coordinates": [
          -42.4583945,
          -20.6469437
        ]
      }
    },
    {
      "type": "Feature",
      "id": "node/11077330329",
      "properties": {
        "timestamp": "2023-07-30T17:30:58Z",
        "version": 1,
        "changeset": 139219548,
        "waterway": "waterfall",
        "id": "node/11077330329"
      },
      "geometry": {
        "type": "Point",
        "coordinates": [
          -42.4505583,
          -20.6582837
        ]
      }
    }
  ]
}
