{
  "type": "FeatureCollection",
  "features": [
    {
      "type": "Feature",
      "id": "node/7055676996",
      "properties": {
        "timestamp": "2019-12-13T22:58:16Z",
        "version": 1,
        "changeset": 78395307,
        "addr:city": "Pedro Osório",
        "addr:postcode": "96360-000",
        "addr:street": "Avenida Tiradentes",
        "addr:suburb": "Jaime Pons",
        "amenity": "clinic",
        "healthcare": "clinic",
        "healthcare:speciality": "general",
        "operator": "municipal",
        "id": "node/7055676996"
      },
      "geometry": {
        "type": "Point",
        "coordinates": [
          -52.8358194,
          -31.8679291
        ]
      }
    }
  ]
}
