{
  "type": "FeatureCollection",
  "features": [
    {
      "type": "Feature",
      "id": "node/5174662870",
      "properties": {
        "timestamp": "2017-10-18T13:02:46Z",
        "version": 1,
        "changeset": 53039116,
        "historic": "monument",
        "id": "node/5174662870"
      },
      "geometry": {
        "type": "Point",
        "coordinates": [
          -52.8218791,
          -31.8620689
        ]
      }
    },
    {
      "type": "Feature",
      "id": "node/5174695656",
      "properties": {
        "timestamp": "2017-10-18T13:27:24Z",
        "version": 1,
        "changeset": 53039729,
        "historic": "monument",
        "name": "MTG",
        "id": "node/5174695656"
      },
      "geometry": {
        "type": "Point",
        "coordinates": [
          -52.8209083,
          -31.8623606
        ]
      }
    }
  ]
}
