{
  "type": "FeatureCollection",
  "features": [
    {
      "type": "Feature",
      "id": "node/12445777797",
      "properties": {
        "timestamp": "2024-12-23T22:38:49Z",
        "version": 1,
        "changeset": 160556382,
        "historic": "monument",
        "name": "Monumento Bíblia Sagrada",
        "id": "node/12445777797"
      },
      "geometry": {
        "type": "Point",
        "coordinates": [
          -40.3551628,
          -20.3324773
        ]
      }
    }
  ]
}
