{
  "type": "FeatureCollection",
  "features": [
    {
      "type": "Feature",
      "id": "node/6867227957",
      "properties": {
        "timestamp": "2021-03-07T05:52:02Z",
        "version": 2,
        "changeset": 100561292,
        "historic": "monument",
        "inscription": "Monumento que representa o nascimento das tartarugas marinhas no ES",
        "name": "Nascimento da tartaruga marinha",
        "id": "node/6867227957"
      },
      "geometry": {
        "type": "Point",
        "coordinates": [
          -40.4002579,
          -20.3432852
        ]
      }
    }
  ]
}
