{
  "type": "FeatureCollection",
  "features": [
    {
      "type": "Feature",
      "id": "node/12569767909",
      "properties": {
        "timestamp": "2025-02-08T23:42:01Z",
        "version": 1,
        "changeset": 162298116,
        "amenity": "pharmacy",
        "name": "São Lucas",
        "id": "node/12569767909"
      },
      "geometry": {
        "type": "Point",
        "coordinates": [
          -39.4749083,
          -14.8084038
        ]
      }
    }
  ]
}
