{
  "type": "FeatureCollection",
  "features": [
    {
      "type": "Feature",
      "id": "node/4475037131",
      "properties": {
        "timestamp": "2016-11-01T13:01:22Z",
        "version": 1,
        "changeset": 43325401,
        "amenity": "arts_centre",
        "name": "Centro Cultural Gustavo Fischer",
        "id": "node/4475037131"
      },
      "geometry": {
        "type": "Point",
        "coordinates": [
          -53.955546,
          -24.4648546
        ]
      }
    }
  ]
}
