{
  "type": "FeatureCollection",
  "features": [
    {
      "type": "Feature",
      "id": "node/1970487337",
      "properties": {
        "timestamp": "2021-04-03T20:04:26Z",
        "version": 2,
        "changeset": 102249740,
        "amenity": "hospital",
        "healthcare": "hospital",
        "name": "Hospital Lar Belém",
        "id": "node/1970487337"
      },
      "geometry": {
        "type": "Point",
        "coordinates": [
          -53.9518042,
          -24.4659467
        ]
      }
    }
  ]
}
