{
  "type": "FeatureCollection",
  "features": [
    {
      "type": "Feature",
      "id": "node/4475037138",
      "properties": {
        "timestamp": "2016-11-01T13:01:22Z",
        "version": 1,
        "changeset": 43325401,
        "name": "Nicole Hotel",
        "tourism": "hotel",
        "id": "node/4475037138"
      },
      "geometry": {
        "type": "Point",
        "coordinates": [
          -53.9536985,
          -24.4678505
        ]
      }
    }
  ]
}
