{
  "type": "FeatureCollection",
  "features": [
    {
      "type": "Feature",
      "id": "node/2454638028",
      "properties": {
        "timestamp": "2013-09-11T19:53:34Z",
        "version": 1,
        "changeset": 17789235,
        "amenity": "college",
        "name": "Escola Carneiro do Vale",
        "id": "node/2454638028"
      },
      "geometry": {
        "type": "Point",
        "coordinates": [
          -38.2179149,
          -8.979416
        ]
      }
    },
    {
      "type": "Feature",
      "id": "node/2455506369",
      "properties": {
        "timestamp": "2013-09-12T13:06:21Z",
        "version": 1,
        "changeset": 17799328,
        "amenity": "college",
        "name": "CFEPP Cursos Profissionalizantes",
        "id": "node/2455506369"
      },
      "geometry": {
        "type": "Point",
        "coordinates": [
          -38.2179206,
          -8.9794262
        ]
      }
    }
  ]
}
