{
  "type": "FeatureCollection",
  "features": [
    {
      "type": "Feature",
      "id": "node/12085902171",
      "properties": {
        "timestamp": "2024-07-31T19:14:14Z",
        "version": 1,
        "changeset": 154665015,
        "addr:city": "Piracaia",
        "addr:housenumber": "197",
        "addr:postcode": "12970-000",
        "addr:street": "Rua Sebastião de Almeida Barros",
        "addr:suburb": "Centro",
        "amenity": "school",
        "grades": "1-12",
        "name": "Integrado de Piracaia EIFM Colégio",
        "id": "node/12085902171"
      },
      "geometry": {
        "type": "Point",
        "coordinates": [
          -46.3560906,
          -23.0537187
        ]
      }
    },
    {
      "type": "Feature",
      "id": "node/12085902173",
      "properties": {
        "timestamp": "2024-07-31T19:14:14Z",
        "version": 1,
        "changeset": 154665015,
        "addr:city": "Piracaia",
        "addr:housenumber": "140",
        "addr:postcode": "12970-000",
        "addr:street": "Rua Guilherme Léo",
        "addr:suburb": "Centro",
        "amenity": "school",
        "name": "EMEF Santo Antonio da Cachoeira",
        "phone": "+55 (11) 40366446",
        "id": "node/12085902173"
      },
      "geometry": {
        "type": "Point",
        "coordinates": [
          -46.3614556,
          -23.0524379
        ]
      }
    },
    {
      "type": "Feature",
      "id": "node/12085902177",
      "properties": {
        "timestamp": "2024-07-31T19:14:14Z",
        "version": 1,
        "changeset": 154665015,
        "addr:city": "Piracaia",
        "addr:housenumber": "100",
        "addr:postcode": "12970-000",
        "addr:street": "Avenida Doutor Cândido Rodrigues",
        "addr:suburb": "Centro",
        "amenity": "school",
        "name": "EMEF Coronel Thomaz Goncalves da Rocha Cunha",
        "phone": "+55 11 40363774",
        "id": "node/12085902177"
      },
      "geometry": {
        "type": "Point",
        "coordinates": [
          -46.3561866,
          -23.0552994
        ]
      }
    }
  ]
}
