{
  "type": "FeatureCollection",
  "features": [
    {
      "type": "Feature",
      "id": "node/5750244247",
      "properties": {
        "timestamp": "2018-07-09T21:34:14Z",
        "version": 1,
        "changeset": 60553377,
        "name": "Cachoeira Arapongas",
        "waterway": "waterfall",
        "id": "node/5750244247"
      },
      "geometry": {
        "type": "Point",
        "coordinates": [
          -48.7289867,
          -24.5174362
        ]
      }
    }
  ]
}
