{
  "type": "FeatureCollection",
  "features": [
    {
      "type": "Feature",
      "id": "node/1880372357",
      "properties": {
        "timestamp": "2021-08-12T19:31:23Z",
        "version": 5,
        "changeset": 109591222,
        "amenity": "cinema",
        "brand": "Cinepolis",
        "brand:wikidata": "Q5686673",
        "brand:wikipedia": "en:Cinépolis",
        "name": "Cinepolis",
        "id": "node/1880372357"
      },
      "geometry": {
        "type": "Point",
        "coordinates": [
          -51.0809405,
          -0.0090501
        ]
      }
    },
    {
      "type": "Feature",
      "id": "node/10572116539",
      "properties": {
        "timestamp": "2023-01-21T04:52:26Z",
        "version": 1,
        "changeset": 131530285,
        "amenity": "cinema",
        "name": "Moviecom",
        "id": "node/10572116539"
      },
      "geometry": {
        "type": "Point",
        "coordinates": [
          -51.063456,
          0.0312004
        ]
      }
    },
    {
      "type": "Feature",
      "id": "node/12128994007",
      "properties": {
        "timestamp": "2024-08-23T04:58:00Z",
        "version": 1,
        "changeset": 155633599,
        "amenity": "cinema",
        "name": "Movieland",
        "id": "node/12128994007"
      },
      "geometry": {
        "type": "Point",
        "coordinates": [
          -51.0526312,
          0.0372699
        ]
      }
    }
  ]
}
