{
  "type": "FeatureCollection",
  "features": [
    {
      "type": "Feature",
      "id": "node/10923414472",
      "properties": {
        "timestamp": "2023-05-24T04:48:57Z",
        "version": 1,
        "changeset": 136479876,
        "amenity": "veterinary",
        "name": "Veterinária São Lázaro",
        "id": "node/10923414472"
      },
      "geometry": {
        "type": "Point",
        "coordinates": [
          -51.0633457,
          0.0357793
        ]
      }
    }
  ]
}
