{
  "type": "FeatureCollection",
  "features": [
    {
      "type": "Feature",
      "id": "node/8626365977",
      "properties": {
        "timestamp": "2021-10-18T18:02:53Z",
        "version": 2,
        "changeset": 112664274,
        "amenity": "hospital",
        "healthcare": "hospital",
        "name": "Sociedade Hospitalar Beneficente de Modelo",
        "id": "node/8626365977"
      },
      "geometry": {
        "type": "Point",
        "coordinates": [
          -53.0592782,
          -26.7729821
        ]
      }
    }
  ]
}
