{
  "type": "FeatureCollection",
  "features": [
    {
      "type": "Feature",
      "id": "node/3165849665",
      "properties": {
        "timestamp": "2016-11-27T16:43:23Z",
        "version": 3,
        "changeset": 43987164,
        "amenity": "community_centre",
        "name": "Centro de Pacificação Social",
        "short_name": "CPS",
        "website": "https://cpstjgo.wordpress.com/",
        "id": "node/3165849665"
      },
      "geometry": {
        "type": "Point",
        "coordinates": [
          -49.1442562,
          -13.4431518
        ]
      }
    }
  ]
}
