{
  "type": "FeatureCollection",
  "features": [
    {
      "type": "Feature",
      "id": "node/6631156558",
      "properties": {
        "timestamp": "2019-07-19T11:33:51Z",
        "version": 1,
        "changeset": 72426685,
        "amenity": "clinic",
        "healthcare": "optometrist",
        "healthcare:speciality": "ophthalmology",
        "name": "Centro Especializado em Oftalmologia",
        "id": "node/6631156558"
      },
      "geometry": {
        "type": "Point",
        "coordinates": [
          -52.559031,
          -17.5643943
        ]
      }
    },
    {
      "type": "Feature",
      "id": "node/9426615656",
      "properties": {
        "timestamp": "2022-01-17T21:05:24Z",
        "version": 1,
        "changeset": 116271896,
        "amenity": "clinic",
        "healthcare": "clinic",
        "name": "Unidade de Saúde Doutor Ermínio Parralego",
        "id": "node/9426615656"
      },
      "geometry": {
        "type": "Point",
        "coordinates": [
          -52.5500381,
          -17.5456901
        ]
      }
    }
  ]
}
