{
  "type": "FeatureCollection",
  "features": [
    {
      "type": "Feature",
      "id": "node/4453597108",
      "properties": {
        "timestamp": "2016-10-18T15:58:06Z",
        "version": 1,
        "changeset": 42987318,
        "waterway": "waterfall",
        "id": "node/4453597108"
      },
      "geometry": {
        "type": "Point",
        "coordinates": [
          -53.1342314,
          -17.8764246
        ]
      }
    },
    {
      "type": "Feature",
      "id": "node/4453763718",
      "properties": {
        "timestamp": "2016-10-18T18:25:58Z",
        "version": 2,
        "changeset": 42991298,
        "waterway": "waterfall",
        "id": "node/4453763718"
      },
      "geometry": {
        "type": "Point",
        "coordinates": [
          -53.1373179,
          -17.8532995
        ]
      }
    },
    {
      "type": "Feature",
      "id": "node/5533922472",
      "properties": {
        "timestamp": "2020-06-05T14:32:06Z",
        "version": 2,
        "changeset": 86249660,
        "name": "Sucuri",
        "waterway": "waterfall",
        "id": "node/5533922472"
      },
      "geometry": {
        "type": "Point",
        "coordinates": [
          -52.664068,
          -17.5357458
        ]
      }
    },
    {
      "type": "Feature",
      "id": "node/5540514221",
      "properties": {
        "timestamp": "2018-04-09T14:48:26Z",
        "version": 1,
        "changeset": 57943288,
        "waterway": "waterfall",
        "id": "node/5540514221"
      },
      "geometry": {
        "type": "Point",
        "coordinates": [
          -52.666879,
          -17.5438199
        ]
      }
    },
    {
      "type": "Feature",
      "id": "node/5546501476",
      "properties": {
        "timestamp": "2020-06-05T14:32:06Z",
        "version": 2,
        "changeset": 86249660,
        "name": "Rio Verde",
        "waterway": "waterfall",
        "id": "node/5546501476"
      },
      "geometry": {
        "type": "Point",
        "coordinates": [
          -52.6756107,
          -17.4495462
        ]
      }
    }
  ]
}
