{
  "type": "FeatureCollection",
  "features": [
    {
      "type": "Feature",
      "id": "node/10800153069",
      "properties": {
        "timestamp": "2023-04-10T20:11:18Z",
        "version": 1,
        "changeset": 134747680,
        "addr:city": "Água Boa",
        "addr:housenumber": "159",
        "addr:postcode": "39790-000",
        "addr:street": "Rua Treze de Maio",
        "addr:suburb": "Centro",
        "amenity": "pharmacy",
        "dispensing": "yes",
        "healthcare": "pharmacy",
        "name": "Drogaria Enifarma",
        "phone": "+55 33 3515 1693",
        "source": "microsoft/BuildingFootprints",
        "id": "node/10800153069"
      },
      "geometry": {
        "type": "Point",
        "coordinates": [
          -42.3924598,
          -17.9916892
        ]
      }
    }
  ]
}
