{
  "type": "FeatureCollection",
  "features": [
    {
      "type": "Feature",
      "id": "node/9767143473",
      "properties": {
        "timestamp": "2023-01-17T21:33:29Z",
        "version": 3,
        "changeset": 131397186,
        "addr:city": "Realeza",
        "addr:postcode": "85770000",
        "addr:street": "Avenida Bruno Zuttion",
        "addr:suburb": "Centro",
        "amenity": "pharmacy",
        "contact:instagram": "https://www.instagram.com/farmacia_farmaanjos/",
        "dispensing": "yes",
        "healthcare": "pharmacy",
        "name": "Farmácia - Farma Anjos",
        "phone": "+55 46 3543-1976",
        "id": "node/9767143473"
      },
      "geometry": {
        "type": "Point",
        "coordinates": [
          -53.5340196,
          -25.7697855
        ]
      }
    }
  ]
}
