{
  "type": "FeatureCollection",
  "features": [
    {
      "type": "Feature",
      "id": "node/6117344693",
      "properties": {
        "timestamp": "2018-12-05T02:03:28Z",
        "version": 1,
        "changeset": 65179831,
        "addr:city": "PERDIZES",
        "addr:housenumber": "65",
        "addr:postcode": "38170-000",
        "addr:street": "Rua Prefeito Terêncio Pereira Vale",
        "addr:suburb": "ALVORADA I",
        "government": "education",
        "name": "SECRETARIA DE EDUCAÇÃO",
        "office": "government",
        "id": "node/6117344693"
      },
      "geometry": {
        "type": "Point",
        "coordinates": [
          -47.2870236,
          -19.3534266
        ]
      }
    }
  ]
}
