{
  "type": "FeatureCollection",
  "features": [
    {
      "type": "Feature",
      "id": "node/5012466167",
      "properties": {
        "timestamp": "2017-08-03T16:43:41Z",
        "version": 1,
        "changeset": 50814069,
        "amenity": "hospital",
        "name": "São Vicente de Paula",
        "id": "node/5012466167"
      },
      "geometry": {
        "type": "Point",
        "coordinates": [
          -44.9369537,
          -21.9772399
        ]
      }
    }
  ]
}
