{
  "type": "FeatureCollection",
  "features": [
    {
      "type": "Feature",
      "id": "node/2440343173",
      "properties": {
        "timestamp": "2023-05-22T22:47:57Z",
        "version": 2,
        "changeset": 136432380,
        "addr:housenumber": "284",
        "addr:postcode": "39650-000",
        "addr:street": "Avenida Israel Pinheiro",
        "addr:suburb": "Saudade",
        "amenity": "hospital",
        "email": "hospital@fhnhbj.com.br",
        "emergency": "yes",
        "healthcare": "hospital",
        "name": "Hospital Doutor Badaro Junior",
        "phone": "+55 33 3764 1202",
        "ref:CNES": "2134268",
        "ref:vatin": "BR21248752000146",
        "id": "node/2440343173"
      },
      "geometry": {
        "type": "Point",
        "coordinates": [
          -42.5829906,
          -17.2213786
        ]
      }
    }
  ]
}
