{
  "type": "FeatureCollection",
  "features": [
    {
      "type": "Feature",
      "id": "node/2440343173",
      "properties": {
        "timestamp": "2024-12-24T02:23:20Z",
        "version": 4,
        "changeset": 160560369,
        "addr:city": "Minas Novas",
        "addr:housenumber": "284",
        "addr:postcode": "39650-000",
        "addr:street": "Avenida Israel Pinheiro",
        "addr:suburb": "Padre Emiliano",
        "amenity": "hospital",
        "email": "hospital@fhnhbj.com.br",
        "emergency": "yes",
        "healthcare": "hospital",
        "healthcare:speciality": "general",
        "name": "Hospital Doutor Badaró Júnior",
        "operator": "Fundação Minas Novas",
        "operator:type": "government",
        "phone": "+55 33 3764 1202",
        "ref:CNES": "2134268",
        "ref:vatin": "BR21248752000146",
        "id": "node/2440343173"
      },
      "geometry": {
        "type": "Point",
        "coordinates": [
          -42.5830482,
          -17.2212318
        ]
      }
    }
  ]
}
