{
  "type": "FeatureCollection",
  "features": [
    {
      "type": "Feature",
      "id": "node/11284535519",
      "properties": {
        "timestamp": "2023-10-23T19:32:13Z",
        "version": 1,
        "changeset": 143032873,
        "addr:city": "Alecrim",
        "addr:country": "BR",
        "addr:housenumber": "474",
        "addr:state": "Rio Grande do Sul",
        "addr:street": "Rua Vereador Adelmi Colossi",
        "addr:suburb": "Centro",
        "amenity": "clinic",
        "contact:phone": "+55 55 3546-1300",
        "name": "UBS Alecrim",
        "official_name": "Unidade Básica de Saúde Alecrim",
        "opening_hours": "Mo-Fr 07:00-19:00",
        "postal_code": "95980-000",
        "ref:CNES": "2249839",
        "id": "node/11284535519"
      },
      "geometry": {
        "type": "Point",
        "coordinates": [
          -54.7638752,
          -27.6564953
        ]
      }
    }
  ]
}
