{
  "type": "FeatureCollection",
  "features": [
    {
      "type": "Feature",
      "id": "node/2681579043",
      "properties": {
        "timestamp": "2023-12-04T18:18:43Z",
        "version": 3,
        "changeset": 144765345,
        "addr:city": "Guadalupe",
        "addr:postcode": "64840-000",
        "addr:street": "Rua Presidente Getúlio Vargas",
        "name": "Hotel Porto Seguro",
        "operator": "Eunice Pereira Lima",
        "tourism": "hotel",
        "id": "node/2681579043"
      },
      "geometry": {
        "type": "Point",
        "coordinates": [
          -43.5679314,
          -6.7875973
        ]
      }
    }
  ]
}
