{
  "type": "FeatureCollection",
  "features": [
    {
      "type": "Feature",
      "id": "node/5148099205",
      "properties": {
        "timestamp": "2018-09-09T05:51:43Z",
        "version": 2,
        "changeset": 62416374,
        "historic": "monument",
        "name": "Cristo de Macaúbas",
        "id": "node/5148099205"
      },
      "geometry": {
        "type": "Point",
        "coordinates": [
          -42.692785,
          -13.011153
        ]
      }
    }
  ]
}
