{
  "type": "FeatureCollection",
  "features": [
    {
      "type": "Feature",
      "id": "node/9108630180",
      "properties": {
        "timestamp": "2021-09-20T19:31:33Z",
        "version": 1,
        "changeset": 111464001,
        "addr:city": "Imbituba",
        "addr:housenumber": "601",
        "addr:postcode": "88780-000",
        "addr:street": "Avenida Doutor João Rimsa",
        "addr:suburb": "Centro",
        "amenity": "doctors",
        "healthcare": "doctor",
        "healthcare:speciality": "nutrition",
        "name": "Nutricionista Samanta Beseke",
        "id": "node/9108630180"
      },
      "geometry": {
        "type": "Point",
        "coordinates": [
          -48.6660295,
          -28.2405281
        ]
      }
    }
  ]
}
