{
  "type": "FeatureCollection",
  "features": [
    {
      "type": "Feature",
      "id": "node/5282361568",
      "properties": {
        "timestamp": "2017-12-13T16:46:12Z",
        "version": 1,
        "changeset": 54601716,
        "amenity": "school",
        "name": "EMEF Duque de Caxias",
        "id": "node/5282361568"
      },
      "geometry": {
        "type": "Point",
        "coordinates": [
          -51.6784744,
          -29.3479371
        ]
      }
    },
    {
      "type": "Feature",
      "id": "node/5282361570",
      "properties": {
        "timestamp": "2017-12-13T16:46:12Z",
        "version": 1,
        "changeset": 54601716,
        "amenity": "school",
        "id": "node/5282361570"
      },
      "geometry": {
        "type": "Point",
        "coordinates": [
          -51.6764564,
          -29.3509258
        ]
      }
    },
    {
      "type": "Feature",
      "id": "node/12229574990",
      "properties": {
        "timestamp": "2024-10-06T13:48:16Z",
        "version": 2,
        "changeset": 157541240,
        "amenity": "school",
        "name": "EEEM Marcelino Champagnat",
        "id": "node/12229574990"
      },
      "geometry": {
        "type": "Point",
        "coordinates": [
          -51.64489,
          -29.3125858
        ]
      }
    }
  ]
}
