{
  "type": "FeatureCollection",
  "features": [
    {
      "type": "Feature",
      "id": "node/2753115612",
      "properties": {
        "timestamp": "2022-05-02T13:30:59Z",
        "version": 2,
        "changeset": 120461711,
        "amenity": "pharmacy",
        "dispensing": "no",
        "healthcare": "pharmacy",
        "name": "Farmácia Sto. Antônio",
        "opening_hours": "24/7",
        "id": "node/2753115612"
      },
      "geometry": {
        "type": "Point",
        "coordinates": [
          -40.3118276,
          -12.5279331
        ]
      }
    },
    {
      "type": "Feature",
      "id": "node/6593422587",
      "properties": {
        "timestamp": "2019-07-06T16:29:51Z",
        "version": 1,
        "changeset": 71963179,
        "amenity": "pharmacy",
        "dispensing": "yes",
        "healthcare": "pharmacy",
        "name": "Pague Menos",
        "id": "node/6593422587"
      },
      "geometry": {
        "type": "Point",
        "coordinates": [
          -40.3097002,
          -12.5298261
        ]
      }
    }
  ]
}
