{
  "type": "FeatureCollection",
  "features": [
    {
      "type": "Feature",
      "id": "node/12523020702",
      "properties": {
        "timestamp": "2025-01-23T18:41:55Z",
        "version": 3,
        "changeset": 161685424,
        "amenity": "kindergarten",
        "name": "CENTRO EDUCACIONAL TERESINHA LAURENTINO",
        "id": "node/12523020702"
      },
      "geometry": {
        "type": "Point",
        "coordinates": [
          -42.2543091,
          -8.3632282
        ]
      }
    }
  ]
}
