{
  "type": "FeatureCollection",
  "features": [
    {
      "type": "Feature",
      "id": "node/12523020588",
      "properties": {
        "timestamp": "2025-01-22T16:47:02Z",
        "version": 2,
        "changeset": 161645506,
        "amenity": "kindergarten",
        "gpxicon": "icon-1.png",
        "name": "Creche Proinfância Tia Heloína",
        "id": "node/12523020588"
      },
      "geometry": {
        "type": "Point",
        "coordinates": [
          -42.2518772,
          -8.3639241
        ]
      }
    },
    {
      "type": "Feature",
      "id": "node/12523020702",
      "properties": {
        "timestamp": "2025-01-22T16:47:02Z",
        "version": 2,
        "changeset": 161645506,
        "amenity": "kindergarten",
        "gpxicon": "icon-1.png",
        "name": "CENTRO EDUCACIONAL TERESINHA LAURENTINO",
        "id": "node/12523020702"
      },
      "geometry": {
        "type": "Point",
        "coordinates": [
          -42.2543091,
          -8.3632282
        ]
      }
    }
  ]
}
