{
  "type": "FeatureCollection",
  "features": [
    {
      "type": "Feature",
      "id": "node/12163526803",
      "properties": {
        "timestamp": "2024-09-08T13:41:33Z",
        "version": 1,
        "changeset": 156352442,
        "access": "yes",
        "historic": "monument",
        "inscription": "Letreiro São João do Piauí",
        "name": "Letreiro São João do Piauí",
        "id": "node/12163526803"
      },
      "geometry": {
        "type": "Point",
        "coordinates": [
          -42.2395896,
          -8.3696067
        ]
      }
    }
  ]
}
