{
  "type": "FeatureCollection",
  "features": [
    {
      "type": "Feature",
      "id": "node/5600556627",
      "properties": {
        "timestamp": "2018-05-06T17:42:47Z",
        "version": 1,
        "changeset": 58736201,
        "addr:city": "Marco",
        "addr:street": "Rua Rios",
        "amenity": "pharmacy",
        "dispensing": "yes",
        "healthcare": "pharmacy",
        "id": "node/5600556627"
      },
      "geometry": {
        "type": "Point",
        "coordinates": [
          -40.1501963,
          -3.1214014
        ]
      }
    }
  ]
}
