{
  "type": "FeatureCollection",
  "features": [
    {
      "type": "Feature",
      "id": "node/4910825021",
      "properties": {
        "timestamp": "2017-06-12T13:10:42Z",
        "version": 1,
        "changeset": 49468751,
        "amenity": "pharmacy",
        "name": "Farmácia Santo Cristo",
        "name:en": "Santo Cristo Pharmacy",
        "name:pt": "Farmácia Santo Cristo",
        "opening_hours": "Mo-Su 09:00-22:00",
        "phone": "+55 82 3296 1176",
        "id": "node/4910825021"
      },
      "geometry": {
        "type": "Point",
        "coordinates": [
          -35.2219595,
          -9.0136656
        ]
      }
    },
    {
      "type": "Feature",
      "id": "node/7114544885",
      "properties": {
        "timestamp": "2020-01-07T13:48:55Z",
        "version": 1,
        "changeset": 79296332,
        "amenity": "pharmacy",
        "name": "Deus é Fiel",
        "id": "node/7114544885"
      },
      "geometry": {
        "type": "Point",
        "coordinates": [
          -35.2181179,
          -9.0076768
        ]
      }
    },
    {
      "type": "Feature",
      "id": "node/12069798497",
      "properties": {
        "timestamp": "2024-07-23T12:26:49Z",
        "version": 1,
        "changeset": 154304994,
        "amenity": "pharmacy",
        "healthcare": "pharmacy",
        "name": "Farmácia Santo Cristo",
        "id": "node/12069798497"
      },
      "geometry": {
        "type": "Point",
        "coordinates": [
          -35.1625017,
          -8.9270973
        ]
      }
    }
  ]
}
