{
  "type": "FeatureCollection",
  "features": [
    {
      "type": "Feature",
      "id": "node/7704122902",
      "properties": {
        "timestamp": "2020-07-11T04:17:58Z",
        "version": 1,
        "changeset": 87842248,
        "addr:city": "Rurópolis",
        "addr:postcode": "68165000",
        "addr:street": "Rodovia Transamazônica",
        "amenity": "university",
        "name": "Faculdade Fael - Polo Rurópolis",
        "website": "https://fael.edu.br/",
        "id": "node/7704122902"
      },
      "geometry": {
        "type": "Point",
        "coordinates": [
          -54.9094859,
          -4.0926449
        ]
      }
    }
  ]
}
