{
  "type": "FeatureCollection",
  "features": [
    {
      "type": "Feature",
      "id": "node/5237184421",
      "properties": {
        "timestamp": "2017-11-18T23:10:00Z",
        "version": 1,
        "changeset": 53913059,
        "amenity": "school",
        "name": "Escola Municipal São João Evangelista",
        "id": "node/5237184421"
      },
      "geometry": {
        "type": "Point",
        "coordinates": [
          -46.3214975,
          -13.631446
        ]
      }
    }
  ]
}
