{
  "type": "FeatureCollection",
  "features": [
    {
      "type": "Feature",
      "id": "node/3504086323",
      "properties": {
        "timestamp": "2015-05-07T23:51:25Z",
        "version": 1,
        "changeset": 30888329,
        "artwork_type": "statue",
        "historic": "memorial",
        "name": "400 Anos da Redução Jesuítica de Santo Inácio",
        "tourism": "artwork",
        "id": "node/3504086323"
      },
      "geometry": {
        "type": "Point",
        "coordinates": [
          -51.7880877,
          -22.6938697
        ]
      }
    },
    {
      "type": "Feature",
      "id": "node/3504090177",
      "properties": {
        "timestamp": "2015-05-07T23:59:12Z",
        "version": 1,
        "changeset": 30888397,
        "historic": "memorial",
        "name": "Ciclovia",
        "id": "node/3504090177"
      },
      "geometry": {
        "type": "Point",
        "coordinates": [
          -51.7828723,
          -22.6898429
        ]
      }
    }
  ]
}
