{
  "type": "FeatureCollection",
  "features": [
    {
      "type": "Feature",
      "id": "node/2473862969",
      "properties": {
        "timestamp": "2013-09-27T17:07:30Z",
        "version": 1,
        "changeset": 18065160,
        "addr:city": "Nova Olímpia",
        "addr:postcode": "78370000",
        "addr:street": "Rua Pedro Pedrossian",
        "amenity": "pharmacy",
        "name": "Farmácia Ouro Verde",
        "id": "node/2473862969"
      },
      "geometry": {
        "type": "Point",
        "coordinates": [
          -57.2851626,
          -14.7780251
        ]
      }
    },
    {
      "type": "Feature",
      "id": "node/3529407764",
      "properties": {
        "timestamp": "2015-05-19T23:16:24Z",
        "version": 1,
        "changeset": 31301251,
        "addr:street": "Avenida Governador Carlos Gomes Bezerra",
        "addr:suburb": "Jardim Ouro Verde",
        "amenity": "pharmacy",
        "name": "Farmacia Popular",
        "id": "node/3529407764"
      },
      "geometry": {
        "type": "Point",
        "coordinates": [
          -57.285487,
          -14.7795719
        ]
      }
    }
  ]
}
