{
  "type": "FeatureCollection",
  "features": [
    {
      "type": "Feature",
      "id": "node/8695437712",
      "properties": {
        "timestamp": "2021-05-04T14:43:50Z",
        "version": 2,
        "changeset": 104131415,
        "name": "Cachoeira da Onça",
        "waterway": "waterfall",
        "id": "node/8695437712"
      },
      "geometry": {
        "type": "Point",
        "coordinates": [
          -40.5404973,
          -19.0444289
        ]
      }
    }
  ]
}
