{
  "type": "FeatureCollection",
  "features": [
    {
      "type": "Feature",
      "id": "node/8939550343",
      "properties": {
        "timestamp": "2021-07-21T18:44:35Z",
        "version": 1,
        "changeset": 108381780,
        "addr:housenumber": "70",
        "addr:street": "Rua São Paulo",
        "addr:suburb": "Centro",
        "amenity": "dentist",
        "contact:mobile": "+55 11 96922 0321",
        "healthcare": "dentist",
        "name": "Odonto Mile",
        "operator": "Doutora Ketliny Dias  Sampaio",
        "phone": "+55 11 4566 4664",
        "ref": "CROSP-121776",
        "id": "node/8939550343"
      },
      "geometry": {
        "type": "Point",
        "coordinates": [
          -46.849956,
          -23.7137016
        ]
      }
    },
    {
      "type": "Feature",
      "id": "node/8957693377",
      "properties": {
        "timestamp": "2021-07-28T16:03:49Z",
        "version": 1,
        "changeset": 108768744,
        "addr:street": "Avenida Quinze de Novembro",
        "addr:suburb": "Centro",
        "amenity": "dentist",
        "contact:mobile": "+55 11 96604 6422",
        "healthcare": "dentist",
        "name": "Nascimento odontologia Especealizada",
        "phone": "+55 11 4566 0066",
        "id": "node/8957693377"
      },
      "geometry": {
        "type": "Point",
        "coordinates": [
          -46.8494399,
          -23.7106969
        ]
      }
    }
  ]
}
