{
  "type": "FeatureCollection",
  "features": [
    {
      "type": "Feature",
      "id": "node/7133165797",
      "properties": {
        "timestamp": "2020-01-15T13:20:06Z",
        "version": 1,
        "changeset": 79608499,
        "addr:city": "Muqui",
        "addr:postcode": "29480000",
        "addr:street": "Pratinha",
        "name": "Pousada Esperança",
        "tourism": "hotel",
        "id": "node/7133165797"
      },
      "geometry": {
        "type": "Point",
        "coordinates": [
          -41.3186097,
          -20.9256626
        ]
      }
    }
  ]
}
