{
  "type": "FeatureCollection",
  "features": [
    {
      "type": "Feature",
      "id": "node/5840650833",
      "properties": {
        "timestamp": "2018-08-19T00:05:59Z",
        "version": 1,
        "changeset": 61782447,
        "name": "Pousada Maristela",
        "tourism": "hotel",
        "id": "node/5840650833"
      },
      "geometry": {
        "type": "Point",
        "coordinates": [
          -45.6191362,
          -22.9345105
        ]
      }
    }
  ]
}
