{
  "type": "FeatureCollection",
  "features": [
    {
      "type": "Feature",
      "id": "node/7243576985",
      "properties": {
        "timestamp": "2020-02-25T21:56:25Z",
        "version": 1,
        "changeset": 81473834,
        "amenity": "pharmacy",
        "name": "Drogaria Topázio",
        "id": "node/7243576985"
      },
      "geometry": {
        "type": "Point",
        "coordinates": [
          -36.0206495,
          -6.2237708
        ]
      }
    }
  ]
}
