{
  "type": "FeatureCollection",
  "features": [
    {
      "type": "Feature",
      "id": "node/1721362647",
      "properties": {
        "timestamp": "2012-04-18T01:58:46Z",
        "version": 1,
        "changeset": 11339543,
        "name": "Hotel Coroados",
        "tourism": "hotel",
        "id": "node/1721362647"
      },
      "geometry": {
        "type": "Point",
        "coordinates": [
          -51.6087269,
          -28.7859079
        ]
      }
    },
    {
      "type": "Feature",
      "id": "node/1721379598",
      "properties": {
        "timestamp": "2012-04-18T02:20:54Z",
        "version": 1,
        "changeset": 11339543,
        "name": "Pousada",
        "tourism": "hotel",
        "id": "node/1721379598"
      },
      "geometry": {
        "type": "Point",
        "coordinates": [
          -51.6083193,
          -28.7924239
        ]
      }
    },
    {
      "type": "Feature",
      "id": "node/1957711265",
      "properties": {
        "timestamp": "2013-09-02T19:08:41Z",
        "version": 2,
        "changeset": 17641665,
        "addr:housename": "Hotel Vilaggio",
        "name": "Vilaggio",
        "tourism": "hotel",
        "id": "node/1957711265"
      },
      "geometry": {
        "type": "Point",
        "coordinates": [
          -51.6089918,
          -28.8000187
        ]
      }
    },
    {
      "type": "Feature",
      "id": "node/2443376204",
      "properties": {
        "timestamp": "2013-09-02T19:07:18Z",
        "version": 2,
        "changeset": 17641638,
        "addr:city": "Nova Prata",
        "addr:housename": "Hotel Condall",
        "addr:housenumber": "925",
        "addr:street": "Rua Flores Da Cunha",
        "name": "Hotel Condall",
        "tourism": "hotel",
        "id": "node/2443376204"
      },
      "geometry": {
        "type": "Point",
        "coordinates": [
          -51.6087002,
          -28.7852106
        ]
      }
    }
  ]
}
