{
  "type": "FeatureCollection",
  "features": [
    {
      "type": "Feature",
      "id": "node/1528679872",
      "properties": {
        "timestamp": "2011-12-02T18:10:51Z",
        "version": 1,
        "changeset": 10018822,
        "name": "Cristalino Jungle Lodge",
        "tourism": "guest_house",
        "id": "node/1528679872"
      },
      "geometry": {
        "type": "Point",
        "coordinates": [
          -55.9312473,
          -9.5976997
        ]
      }
    }
  ]
}
