{
  "type": "FeatureCollection",
  "features": [
    {
      "type": "Feature",
      "id": "node/10577815329",
      "properties": {
        "timestamp": "2023-01-23T23:14:22Z",
        "version": 1,
        "changeset": 131627920,
        "amenity": "pharmacy",
        "healthcare": "pharmacy",
        "name": "Posto de Medicamentos Andrade",
        "id": "node/10577815329"
      },
      "geometry": {
        "type": "Point",
        "coordinates": [
          -37.6350203,
          -10.5572327
        ]
      }
    },
    {
      "type": "Feature",
      "id": "node/10577854712",
      "properties": {
        "timestamp": "2023-01-23T23:31:36Z",
        "version": 1,
        "changeset": 131628223,
        "amenity": "pharmacy",
        "healthcare": "pharmacy",
        "name": "Farmácia Valadares",
        "id": "node/10577854712"
      },
      "geometry": {
        "type": "Point",
        "coordinates": [
          -37.5362374,
          -10.550453
        ]
      }
    },
    {
      "type": "Feature",
      "id": "node/11458650172",
      "properties": {
        "timestamp": "2023-12-27T03:36:46Z",
        "version": 1,
        "changeset": 145556530,
        "amenity": "pharmacy",
        "healthcare": "pharmacy",
        "id": "node/11458650172"
      },
      "geometry": {
        "type": "Point",
        "coordinates": [
          -37.5347785,
          -10.550616
        ]
      }
    }
  ]
}
