{
  "type": "FeatureCollection",
  "features": [
    {
      "type": "Feature",
      "id": "node/9923201109",
      "properties": {
        "timestamp": "2022-08-10T17:37:56Z",
        "version": 2,
        "changeset": 124742218,
        "amenity": "cinema",
        "level": "3",
        "name": "Cinemagic",
        "id": "node/9923201109"
      },
      "geometry": {
        "type": "Point",
        "coordinates": [
          -42.3410789,
          -22.8784707
        ]
      }
    }
  ]
}
