{
  "type": "FeatureCollection",
  "features": [
    {
      "type": "Feature",
      "id": "node/11173193552",
      "properties": {
        "timestamp": "2023-09-07T12:18:07Z",
        "version": 2,
        "changeset": 140938364,
        "addr:city": "Santa Cruz Cabrália",
        "addr:postcode": "45807-000",
        "addr:street": "Rua Porto Alegre",
        "addr:suburb": "Campinho",
        "amenity": "social_facility",
        "name": "Centro de Referência em Assistência Social",
        "operator": "Município de Santa Cruz Cabrália",
        "operator:type": "public",
        "social_facility": "outreach",
        "social_facility:for": "community",
        "id": "node/11173193552"
      },
      "geometry": {
        "type": "Point",
        "coordinates": [
          -39.0337667,
          -16.2802582
        ]
      }
    }
  ]
}
