{
  "type": "FeatureCollection",
  "features": [
    {
      "type": "Feature",
      "id": "node/2916658669",
      "properties": {
        "timestamp": "2016-09-27T13:50:18Z",
        "version": 2,
        "changeset": 42470987,
        "addr:city": "Paraí",
        "addr:housenumber": "112",
        "addr:postcode": "95360-000",
        "addr:street": "Rua Ernesto Mattiello",
        "name": "Hotel - Pousada do Campo",
        "smoking": "outside",
        "tourism": "hotel",
        "id": "node/2916658669"
      },
      "geometry": {
        "type": "Point",
        "coordinates": [
          -51.791055,
          -28.5936005
        ]
      }
    }
  ]
}
