{
  "type": "FeatureCollection",
  "features": [
    {
      "type": "Feature",
      "id": "node/5014054754",
      "properties": {
        "timestamp": "2017-08-04T11:57:43Z",
        "version": 1,
        "changeset": 50836741,
        "amenity": "library",
        "name": "Biblioteca Municipal",
        "id": "node/5014054754"
      },
      "geometry": {
        "type": "Point",
        "coordinates": [
          -44.9723157,
          -22.195134
        ]
      }
    }
  ]
}
