{
  "type": "FeatureCollection",
  "features": [
    {
      "type": "Feature",
      "id": "node/5014062463",
      "properties": {
        "timestamp": "2017-08-04T11:48:16Z",
        "version": 1,
        "changeset": 50836409,
        "amenity": "pharmacy",
        "name": "Drogaria Tradição",
        "operator": "Rede Inova",
        "id": "node/5014062463"
      },
      "geometry": {
        "type": "Point",
        "coordinates": [
          -44.9735044,
          -22.1970617
        ]
      }
    },
    {
      "type": "Feature",
      "id": "node/5014134024",
      "properties": {
        "timestamp": "2017-08-04T12:06:59Z",
        "version": 1,
        "changeset": 50837032,
        "amenity": "pharmacy",
        "name": "Drogarede",
        "id": "node/5014134024"
      },
      "geometry": {
        "type": "Point",
        "coordinates": [
          -44.9734825,
          -22.1981943
        ]
      }
    },
    {
      "type": "Feature",
      "id": "node/5014180354",
      "properties": {
        "timestamp": "2017-08-04T12:22:11Z",
        "version": 1,
        "changeset": 50837513,
        "amenity": "pharmacy",
        "name": "Drogaria Santa Rita",
        "id": "node/5014180354"
      },
      "geometry": {
        "type": "Point",
        "coordinates": [
          -44.9345249,
          -22.2508311
        ]
      }
    }
  ]
}
