{
  "type": "FeatureCollection",
  "features": [
    {
      "type": "Feature",
      "id": "node/4576182133",
      "properties": {
        "timestamp": "2017-01-10T23:20:00Z",
        "version": 2,
        "changeset": 45064863,
        "name": "Pousada Pontal da Barra",
        "tourism": "guest_house",
        "id": "node/4576182133"
      },
      "geometry": {
        "type": "Point",
        "coordinates": [
          -39.1898799,
          -17.5512104
        ]
      }
    }
  ]
}
