{
  "type": "FeatureCollection",
  "features": [
    {
      "type": "Feature",
      "id": "node/3476488223",
      "properties": {
        "timestamp": "2023-04-28T18:47:35Z",
        "version": 2,
        "changeset": 135480782,
        "historic": "monument",
        "name": "Cristo Redentor de Itupeva",
        "tourism": "attraction",
        "id": "node/3476488223"
      },
      "geometry": {
        "type": "Point",
        "coordinates": [
          -47.0612823,
          -23.1514288
        ]
      }
    },
    {
      "type": "Feature",
      "id": "node/3479081328",
      "properties": {
        "timestamp": "2015-04-26T15:29:06Z",
        "version": 1,
        "changeset": 30506702,
        "historic": "monument",
        "name": "Gruta do Quilombo",
        "id": "node/3479081328"
      },
      "geometry": {
        "type": "Point",
        "coordinates": [
          -47.1174059,
          -23.1119359
        ]
      }
    }
  ]
}
