{
  "type": "FeatureCollection",
  "features": [
    {
      "type": "Feature",
      "id": "node/4301381635",
      "properties": {
        "timestamp": "2019-10-05T18:42:07Z",
        "version": 2,
        "changeset": 75325522,
        "historic": "memorial",
        "material": "metal",
        "memorial": "war_memorial",
        "name": "Soldados da FEB",
        "id": "node/4301381635"
      },
      "geometry": {
        "type": "Point",
        "coordinates": [
          -46.5574758,
          -23.6942723
        ]
      }
    },
    {
      "type": "Feature",
      "id": "node/6699309889",
      "properties": {
        "timestamp": "2022-08-03T23:18:50Z",
        "version": 2,
        "changeset": 124456083,
        "historic": "memorial",
        "inscription": "Árvore dos Carvoeiros",
        "name": "Árvore dos Carvoeiros",
        "id": "node/6699309889"
      },
      "geometry": {
        "type": "Point",
        "coordinates": [
          -46.5455538,
          -23.7321586
        ]
      }
    },
    {
      "type": "Feature",
      "id": "node/10252237116",
      "properties": {
        "timestamp": "2022-12-18T19:28:10Z",
        "version": 2,
        "changeset": 130221886,
        "description": "Placa de inauguração da restauração do Caminho do Mar.",
        "direction": "248",
        "historic": "memorial",
        "image": "File:Estrada Velha de Santos 07.jpg",
        "material": "metal",
        "memorial": "plaque",
        "name": "Restauração do Caminho do Mar",
        "start_date": "1979-07-09",
        "id": "node/10252237116"
      },
      "geometry": {
        "type": "Point",
        "coordinates": [
          -46.465217,
          -23.8599515
        ]
      }
    }
  ]
}
