{
  "type": "FeatureCollection",
  "features": [
    {
      "type": "Feature",
      "id": "node/3491299278",
      "properties": {
        "timestamp": "2019-07-07T03:56:52Z",
        "version": 2,
        "changeset": 71972900,
        "IJSN:tipoUnidad": "Hospital Geral",
        "addr:city": "Rio Bananal",
        "addr:housenumber": "500",
        "addr:place": "São Sebastião",
        "addr:postcode": "29920-000",
        "addr:street": "Rua João Cipriano",
        "amenity": "hospital",
        "contact:phone": "(27) 3265-1101",
        "healthcare": "hospital",
        "name": "Hospital e Maternidade Alfredo Pinto Santana",
        "id": "node/3491299278"
      },
      "geometry": {
        "type": "Point",
        "coordinates": [
          -40.3229178,
          -19.2728742
        ]
      }
    }
  ]
}
