{
  "type": "FeatureCollection",
  "features": [
    {
      "type": "Feature",
      "id": "node/4599901883",
      "properties": {
        "timestamp": "2017-01-10T14:54:59Z",
        "version": 1,
        "changeset": 45052796,
        "amenity": "school",
        "name": "Escola Guedes de Miranda",
        "id": "node/4599901883"
      },
      "geometry": {
        "type": "Point",
        "coordinates": [
          -35.3975274,
          -9.0577595
        ]
      }
    }
  ]
}
