{
  "type": "FeatureCollection",
  "features": [
    {
      "type": "Feature",
      "id": "node/5602439999",
      "properties": {
        "timestamp": "2018-05-07T14:43:42Z",
        "version": 1,
        "changeset": 58760902,
        "addr:city": "Paranaíba",
        "addr:housenumber": "1195",
        "addr:postcode": "79500000",
        "addr:street": "Rua Maria Candida Freitas",
        "addr:suburb": "santa lucia",
        "email": "hotelsul@hotmail.com",
        "internet_access": "wlan",
        "internet_access:fee": "no",
        "name": "Hotel Sul",
        "rooms": "37",
        "smoking": "separated",
        "stars": "5",
        "tourism": "hotel",
        "website": "facebook( hotelsul)",
        "id": "node/5602439999"
      },
      "geometry": {
        "type": "Point",
        "coordinates": [
          -51.1926698,
          -19.6696434
        ]
      }
    }
  ]
}
