{
  "type": "FeatureCollection",
  "features": [
    {
      "type": "Feature",
      "id": "node/4380554392",
      "properties": {
        "timestamp": "2016-09-02T13:41:36Z",
        "version": 1,
        "changeset": 41869488,
        "name": "Hotel Fortaleza",
        "name:pt": "Hotel Fortaleza",
        "tourism": "hotel",
        "id": "node/4380554392"
      },
      "geometry": {
        "type": "Point",
        "coordinates": [
          -63.5692064,
          -12.0574458
        ]
      }
    },
    {
      "type": "Feature",
      "id": "node/6695470685",
      "properties": {
        "timestamp": "2019-08-08T17:35:25Z",
        "version": 1,
        "changeset": 73165301,
        "internet_access": "wlan",
        "name": "Hotel bela vista",
        "name:en": "Bela vista hotel",
        "tourism": "hotel",
        "id": "node/6695470685"
      },
      "geometry": {
        "type": "Point",
        "coordinates": [
          -63.5646402,
          -12.0608818
        ]
      }
    }
  ]
}
