{
  "type": "FeatureCollection",
  "features": [
    {
      "type": "Feature",
      "id": "node/5353068784",
      "properties": {
        "timestamp": "2018-01-21T18:22:47Z",
        "version": 1,
        "changeset": 55634614,
        "historic": "memorial",
        "memorial": "war_memorial",
        "name": "Marco da Guerra do Contestado",
        "id": "node/5353068784"
      },
      "geometry": {
        "type": "Point",
        "coordinates": [
          -50.7843823,
          -26.7910991
        ]
      }
    }
  ]
}
