{
  "type": "FeatureCollection",
  "features": [
    {
      "type": "Feature",
      "id": "node/2310537861",
      "properties": {
        "timestamp": "2014-01-25T00:54:08Z",
        "version": 2,
        "changeset": 20186962,
        "addr:housename": "Avenida Visconde do Rio Grande",
        "amenity": "veterinary",
        "name": "Agropecuária Rissa",
        "id": "node/2310537861"
      },
      "geometry": {
        "type": "Point",
        "coordinates": [
          -51.3035642,
          -30.2970154
        ]
      }
    }
  ]
}
