{
  "type": "FeatureCollection",
  "features": [
    {
      "type": "Feature",
      "id": "node/10212456530",
      "properties": {
        "timestamp": "2022-11-23T17:16:37Z",
        "version": 1,
        "changeset": 129290761,
        "addr:city": "Marilac",
        "addr:housenumber": "350",
        "addr:postcode": "35115-000",
        "addr:street": "Rua Rio de Janeiro",
        "addr:suburb": "Centro",
        "name": "Hotel e Restaurante Tropical",
        "operator": "Hotel e Restaurante Tropical Limitada",
        "phone": "+55 33 3292 1103",
        "tourism": "hotel",
        "id": "node/10212456530"
      },
      "geometry": {
        "type": "Point",
        "coordinates": [
          -42.082809,
          -18.5068002
        ]
      }
    }
  ]
}
