{
  "type": "FeatureCollection",
  "features": [
    {
      "type": "Feature",
      "id": "node/2306405887",
      "properties": {
        "timestamp": "2013-05-16T13:10:53Z",
        "version": 1,
        "changeset": 16153082,
        "name": "Bicicletaria Duas Rodas",
        "shop": "bicycle",
        "id": "node/2306405887"
      },
      "geometry": {
        "type": "Point",
        "coordinates": [
          -45.7772671,
          -22.3561316
        ]
      }
    }
  ]
}
