{
  "type": "FeatureCollection",
  "features": [
    {
      "type": "Feature",
      "id": "node/10053431276",
      "properties": {
        "timestamp": "2022-09-26T10:58:40Z",
        "version": 1,
        "changeset": 126650286,
        "addr:city": "Serro",
        "addr:postcode": "39150-000",
        "addr:street": "Praça Doutor Andrade",
        "addr:suburb": "Centro",
        "government": "administrative",
        "name": "Secretaria Municipal de Cultura, Turismo e Patrimônio",
        "office": "government",
        "id": "node/10053431276"
      },
      "geometry": {
        "type": "Point",
        "coordinates": [
          -43.3812082,
          -18.6040686
        ]
      }
    },
    {
      "type": "Feature",
      "id": "node/10056891243",
      "properties": {
        "timestamp": "2022-09-27T18:54:29Z",
        "version": 1,
        "changeset": 126710323,
        "addr:city": "Serro",
        "addr:postcode": "39150-000",
        "addr:street": "Rua Fernando Vasconcelos",
        "addr:suburb": "Centro",
        "government": "register_office",
        "name": "Cartório do Primeiro Ofício da Comarca de Serro",
        "office": "government",
        "id": "node/10056891243"
      },
      "geometry": {
        "type": "Point",
        "coordinates": [
          -43.3832166,
          -18.6051081
        ]
      }
    }
  ]
}
