{
  "type": "FeatureCollection",
  "features": [
    {
      "type": "Feature",
      "id": "node/6598704516",
      "properties": {
        "timestamp": "2019-07-09T10:58:14Z",
        "version": 1,
        "changeset": 72049517,
        "amenity": "clinic",
        "healthcare": "clinic",
        "name": "Unidade de Saúde da Família Maria Ferreira de Amaral",
        "id": "node/6598704516"
      },
      "geometry": {
        "type": "Point",
        "coordinates": [
          -44.2762935,
          -12.223284
        ]
      }
    }
  ]
}
