{
  "type": "FeatureCollection",
  "features": [
    {
      "type": "Feature",
      "id": "node/4203420310",
      "properties": {
        "timestamp": "2019-04-19T15:43:46Z",
        "version": 3,
        "changeset": 69380117,
        "amenity": "hospital",
        "name": "Hospital Cônego Monte Raso",
        "id": "node/4203420310"
      },
      "geometry": {
        "type": "Point",
        "coordinates": [
          -44.8896123,
          -21.9628114
        ]
      }
    }
  ]
}
