{
  "type": "FeatureCollection",
  "features": [
    {
      "type": "Feature",
      "id": "node/5302742575",
      "properties": {
        "timestamp": "2019-04-14T02:54:38Z",
        "version": 2,
        "changeset": 69191995,
        "amenity": "college",
        "name": "InfoWay",
        "id": "node/5302742575"
      },
      "geometry": {
        "type": "Point",
        "coordinates": [
          -35.5911024,
          -8.685724
        ]
      }
    },
    {
      "type": "Feature",
      "id": "node/6381904584",
      "properties": {
        "timestamp": "2019-04-03T20:24:18Z",
        "version": 1,
        "changeset": 68857008,
        "amenity": "college",
        "name": "ETE Palmares",
        "id": "node/6381904584"
      },
      "geometry": {
        "type": "Point",
        "coordinates": [
          -35.5775503,
          -8.6817769
        ]
      }
    }
  ]
}
