{
  "type": "FeatureCollection",
  "features": [
    {
      "type": "Feature",
      "id": "node/5302742589",
      "properties": {
        "timestamp": "2017-12-25T02:38:27Z",
        "version": 1,
        "changeset": 54899140,
        "amenity": "pharmacy",
        "healthcare": "pharmacy",
        "name": "Farmacia Permanente",
        "id": "node/5302742589"
      },
      "geometry": {
        "type": "Point",
        "coordinates": [
          -35.5911031,
          -8.6857242
        ]
      }
    }
  ]
}
