{
  "type": "FeatureCollection",
  "features": [
    {
      "type": "Feature",
      "id": "node/8907643944",
      "properties": {
        "timestamp": "2021-07-09T15:52:09Z",
        "version": 1,
        "changeset": 107714478,
        "waterway": "waterfall",
        "id": "node/8907643944"
      },
      "geometry": {
        "type": "Point",
        "coordinates": [
          -35.5553715,
          -8.6422824
        ]
      }
    },
    {
      "type": "Feature",
      "id": "node/11328403789",
      "properties": {
        "timestamp": "2023-11-05T23:54:51Z",
        "version": 1,
        "changeset": 143671867,
        "image": "https://lh3.googleusercontent.com/p/AF1QipNWqwqV_5jwFmX1E4TSQxWbBDAmqzH-_6GtlkkY=w1080-h608-p-no-v0",
        "name": "Cachoeira Paraíso",
        "opening_hours": "Mo-Sa 09:00-16:00; Su 08:00-16:00",
        "phone": "+5581996142978",
        "tourism": "viewpoint",
        "url": "https://www.instagram.com/cachoeiraparaisobonitope/",
        "waterfall": "water_fall",
        "waterway": "waterfall",
        "website": "https://cachoeiraparaiso.negocio.site/",
        "id": "node/11328403789"
      },
      "geometry": {
        "type": "Point",
        "coordinates": [
          -35.6994885,
          -8.5645236
        ]
      }
    }
  ]
}
