{
  "type": "FeatureCollection",
  "features": [
    {
      "type": "Feature",
      "id": "node/5998964660",
      "properties": {
        "timestamp": "2018-10-19T20:27:48Z",
        "version": 1,
        "changeset": 63690317,
        "name": "Pousada Todo Dia",
        "tourism": "hotel",
        "id": "node/5998964660"
      },
      "geometry": {
        "type": "Point",
        "coordinates": [
          -36.6321145,
          -9.536044
        ]
      }
    }
  ]
}
