{
  "type": "FeatureCollection",
  "features": [
    {
      "type": "Feature",
      "id": "node/10550743063",
      "properties": {
        "timestamp": "2023-01-13T17:39:46Z",
        "version": 2,
        "changeset": 131239432,
        "amenity": "social_facility",
        "name": "SerraVille Clínica Geriátrica",
        "social_facility": "group_home",
        "social_facility:for": "senior",
        "id": "node/10550743063"
      },
      "geometry": {
        "type": "Point",
        "coordinates": [
          -51.0773163,
          -29.5768395
        ]
      }
    }
  ]
}
