{
  "type": "FeatureCollection",
  "features": [
    {
      "type": "Feature",
      "id": "node/8155907617",
      "properties": {
        "timestamp": "2020-11-23T20:37:04Z",
        "version": 1,
        "changeset": 94661002,
        "amenity": "pharmacy",
        "name": "Farmacia Nossa Senhora Aparecids",
        "id": "node/8155907617"
      },
      "geometry": {
        "type": "Point",
        "coordinates": [
          -40.4570824,
          -7.2854104
        ]
      }
    }
  ]
}
