{
  "type": "FeatureCollection",
  "features": [
    {
      "type": "Feature",
      "id": "node/2324964254",
      "properties": {
        "timestamp": "2013-05-30T00:57:05Z",
        "version": 1,
        "changeset": 16345646,
        "amenity": "hospital",
        "name": "Hospital São Paulo",
        "id": "node/2324964254"
      },
      "geometry": {
        "type": "Point",
        "coordinates": [
          -51.5213193,
          -28.2099507
        ]
      }
    }
  ]
}
