{
  "type": "FeatureCollection",
  "features": [
    {
      "type": "Feature",
      "id": "node/9979829547",
      "properties": {
        "timestamp": "2022-08-29T09:46:28Z",
        "version": 2,
        "changeset": 125514295,
        "addr:city": "Tombos",
        "addr:housenumber": "333",
        "addr:postcode": "36844-000",
        "addr:street": "Avenida Imaculada Conceição",
        "addr:suburb": "Quebra Copos",
        "amenity": "library",
        "name": "Biblioteca Municipal Fernando Picardi",
        "operator": "Município de Tombos",
        "operator:type": "public",
        "id": "node/9979829547"
      },
      "geometry": {
        "type": "Point",
        "coordinates": [
          -42.0264055,
          -20.9136339
        ]
      }
    }
  ]
}
