{
  "type": "FeatureCollection",
  "features": [
    {
      "type": "Feature",
      "id": "node/3666142179",
      "properties": {
        "timestamp": "2021-04-13T14:15:58Z",
        "version": 4,
        "changeset": 102871311,
        "amenity": "dentist",
        "healthcare": "dentist",
        "name": "Odontocare",
        "phone": "+55-77-3261.1054",
        "id": "node/3666142179"
      },
      "geometry": {
        "type": "Point",
        "coordinates": [
          -40.2476753,
          -15.2454946
        ]
      }
    }
  ]
}
