{
  "type": "FeatureCollection",
  "features": [
    {
      "type": "Feature",
      "id": "node/1336170021",
      "properties": {
        "timestamp": "2012-01-21T13:57:30Z",
        "version": 3,
        "changeset": 10455641,
        "historic": "memorial",
        "id": "node/1336170021"
      },
      "geometry": {
        "type": "Point",
        "coordinates": [
          -40.2509794,
          -15.2476319
        ]
      }
    },
    {
      "type": "Feature",
      "id": "node/2263844024",
      "properties": {
        "timestamp": "2013-04-12T02:08:40Z",
        "version": 1,
        "changeset": 15696349,
        "historic": "memorial",
        "name": "Monumento dos perseguidos pela ditadura",
        "id": "node/2263844024"
      },
      "geometry": {
        "type": "Point",
        "coordinates": [
          -40.2467565,
          -15.2487243
        ]
      }
    },
    {
      "type": "Feature",
      "id": "node/3689690291",
      "properties": {
        "timestamp": "2015-08-10T14:58:12Z",
        "version": 1,
        "changeset": 33242253,
        "historic": "memorial",
        "id": "node/3689690291"
      },
      "geometry": {
        "type": "Point",
        "coordinates": [
          -40.2468361,
          -15.2458113
        ]
      }
    },
    {
      "type": "Feature",
      "id": "node/7914173385",
      "properties": {
        "timestamp": "2020-09-16T19:58:36Z",
        "version": 1,
        "changeset": 91005520,
        "historic": "memorial",
        "name": "6",
        "id": "node/7914173385"
      },
      "geometry": {
        "type": "Point",
        "coordinates": [
          -40.2038294,
          -15.3115281
        ]
      }
    }
  ]
}
