{
  "type": "FeatureCollection",
  "features": [
    {
      "type": "Feature",
      "id": "node/3645269738",
      "properties": {
        "timestamp": "2015-07-11T00:24:39Z",
        "version": 1,
        "changeset": 32556174,
        "historic": "monument",
        "name": "Monumento da Bìblia",
        "id": "node/3645269738"
      },
      "geometry": {
        "type": "Point",
        "coordinates": [
          -40.2451435,
          -15.2467621
        ]
      }
    }
  ]
}
