{
  "type": "FeatureCollection",
  "features": [
    {
      "type": "Feature",
      "id": "node/8636271460",
      "properties": {
        "timestamp": "2022-09-10T13:50:25Z",
        "version": 2,
        "changeset": 126016732,
        "amenity": "library",
        "fixme": "verificar localização",
        "name": "Biblioteca Pública Municipal João XXIII",
        "id": "node/8636271460"
      },
      "geometry": {
        "type": "Point",
        "coordinates": [
          -52.7193252,
          -26.728483
        ]
      }
    }
  ]
}
