{
  "type": "FeatureCollection",
  "features": [
    {
      "type": "Feature",
      "id": "node/6278442988",
      "properties": {
        "timestamp": "2022-12-07T10:41:02Z",
        "version": 3,
        "changeset": 129816065,
        "amenity": "pharmacy",
        "healthcare": "pharmacy",
        "name": "1649 F F comercio",
        "id": "node/6278442988"
      },
      "geometry": {
        "type": "Point",
        "coordinates": [
          -39.2758836,
          -14.8072727
        ]
      }
    },
    {
      "type": "Feature",
      "id": "node/8607006638",
      "properties": {
        "timestamp": "2021-04-08T14:13:14Z",
        "version": 1,
        "changeset": 102571268,
        "amenity": "pharmacy",
        "dispensing": "yes",
        "healthcare": "pharmacy",
        "id": "node/8607006638"
      },
      "geometry": {
        "type": "Point",
        "coordinates": [
          -39.2743642,
          -14.7874897
        ]
      }
    },
    {
      "type": "Feature",
      "id": "node/10255319508",
      "properties": {
        "timestamp": "2022-12-12T10:39:14Z",
        "version": 1,
        "changeset": 129993813,
        "addr:city": "Itabuna",
        "addr:housenumber": "1451",
        "addr:postcode": "45600-006",
        "addr:street": "Rua Dalila Paganelli",
        "addr:suburb": "Centro",
        "amenity": "pharmacy",
        "brand": "Drogasil",
        "brand:wikidata": "Q5308185",
        "healthcare": "pharmacy",
        "name": "Drogasil",
        "operator": "Raia Drogasil S/A",
        "wheelchair": "yes",
        "id": "node/10255319508"
      },
      "geometry": {
        "type": "Point",
        "coordinates": [
          -39.277914,
          -14.7972609
        ]
      }
    }
  ]
}
