{
  "type": "FeatureCollection",
  "features": [
    {
      "type": "Feature",
      "id": "node/11196875187",
      "properties": {
        "timestamp": "2023-09-17T02:33:25Z",
        "version": 1,
        "changeset": 141363984,
        "addr:city": "Nova Viçosa",
        "addr:district": "Posto da Mata",
        "addr:housenumber": "118 a",
        "addr:postcode": "45928-000",
        "addr:street": "Rua Mucuri",
        "addr:suburb": "Centro",
        "amenity": "social_facility",
        "name": "Centro de Referência Especializado de Assistência Social Ivonilde Rodrigues da Silva",
        "operator": "Município de Nova Viçosa",
        "operator:type": "public",
        "id": "node/11196875187"
      },
      "geometry": {
        "type": "Point",
        "coordinates": [
          -39.8583034,
          -17.890677
        ]
      }
    }
  ]
}
