{
  "type": "FeatureCollection",
  "features": [
    {
      "type": "Feature",
      "id": "node/9718173553",
      "properties": {
        "timestamp": "2022-05-05T13:38:07Z",
        "version": 1,
        "changeset": 120589958,
        "amenity": "clinic",
        "healthcare": "clinic",
        "id": "node/9718173553"
      },
      "geometry": {
        "type": "Point",
        "coordinates": [
          -42.9311557,
          -18.7694452
        ]
      }
    },
    {
      "type": "Feature",
      "id": "node/10059445123",
      "properties": {
        "timestamp": "2022-09-28T19:11:17Z",
        "version": 1,
        "changeset": 126752884,
        "addr:city": "Guanhães",
        "addr:housenumber": "110",
        "addr:postcode": "39740-000",
        "addr:street": "Rua Adelina Coelho Leão",
        "amenity": "clinic",
        "healthcare": "clinic",
        "healthcare:speciality": "general",
        "name": "Equipe de Saúde da Família Alvorada",
        "id": "node/10059445123"
      },
      "geometry": {
        "type": "Point",
        "coordinates": [
          -42.9298806,
          -18.7722895
        ]
      }
    }
  ]
}
