{
  "type": "FeatureCollection",
  "features": [
    {
      "type": "Feature",
      "id": "node/1865621635",
      "properties": {
        "timestamp": "2022-10-01T11:39:57Z",
        "version": 2,
        "changeset": 126856633,
        "name": "Cachoeira Escura",
        "waterway": "waterfall",
        "id": "node/1865621635"
      },
      "geometry": {
        "type": "Point",
        "coordinates": [
          -42.8077125,
          -19.0695407
        ]
      }
    },
    {
      "type": "Feature",
      "id": "node/4348080815",
      "properties": {
        "timestamp": "2022-10-10T13:37:56Z",
        "version": 2,
        "changeset": 127304819,
        "name": "Cachoeira da Fumaça",
        "waterway": "waterfall",
        "id": "node/4348080815"
      },
      "geometry": {
        "type": "Point",
        "coordinates": [
          -42.6839248,
          -18.8957402
        ]
      }
    },
    {
      "type": "Feature",
      "id": "node/4351598201",
      "properties": {
        "timestamp": "2022-10-04T19:33:39Z",
        "version": 3,
        "changeset": 127013090,
        "name": "Cachoeira da Usina",
        "waterway": "waterfall",
        "id": "node/4351598201"
      },
      "geometry": {
        "type": "Point",
        "coordinates": [
          -42.8220351,
          -18.790483
        ]
      }
    },
    {
      "type": "Feature",
      "id": "node/4351598417",
      "properties": {
        "timestamp": "2018-12-05T11:16:00Z",
        "version": 2,
        "changeset": 65197651,
        "waterway": "waterfall",
        "id": "node/4351598417"
      },
      "geometry": {
        "type": "Point",
        "coordinates": [
          -42.8292017,
          -18.7710402
        ]
      }
    }
  ]
}
