{
  "type": "FeatureCollection",
  "features": [
    {
      "type": "Feature",
      "id": "node/4201212665",
      "properties": {
        "timestamp": "2021-02-16T21:15:48Z",
        "version": 2,
        "changeset": 99405929,
        "amenity": "pharmacy",
        "brand": "Master Farma",
        "healthcare": "pharmacy",
        "name": "Farmácia Avenida",
        "id": "node/4201212665"
      },
      "geometry": {
        "type": "Point",
        "coordinates": [
          -49.9427117,
          -28.2915515
        ]
      }
    },
    {
      "type": "Feature",
      "id": "node/9787144391",
      "properties": {
        "timestamp": "2022-06-01T02:57:22Z",
        "version": 1,
        "changeset": 121790233,
        "amenity": "pharmacy",
        "dispensing": "yes",
        "healthcare": "pharmacy",
        "name": "Líder Farma",
        "id": "node/9787144391"
      },
      "geometry": {
        "type": "Point",
        "coordinates": [
          -49.9327125,
          -28.2926846
        ]
      }
    }
  ]
}
