{
  "type": "FeatureCollection",
  "features": [
    {
      "type": "Feature",
      "id": "node/4984813924",
      "properties": {
        "timestamp": "2017-07-21T12:13:24Z",
        "version": 1,
        "changeset": 50457022,
        "name": "CBM",
        "name:pt": "CBM",
        "shop": "bicycle",
        "id": "node/4984813924"
      },
      "geometry": {
        "type": "Point",
        "coordinates": [
          -50.4547348,
          -18.4481779
        ]
      }
    }
  ]
}
