{
  "type": "FeatureCollection",
  "features": [
    {
      "type": "Feature",
      "id": "node/4983904029",
      "properties": {
        "timestamp": "2023-05-11T23:28:58Z",
        "version": 3,
        "changeset": 135996758,
        "addr:city": "Quirinópolis",
        "addr:housenumber": "286",
        "addr:postcode": "75860-000",
        "addr:street": "Avenida Rui Barbosa",
        "addr:suburb": "Centro",
        "amenity": "hospital",
        "healthcare": "hospital",
        "name": "Hospital Municipal Antônio Martins da Costa",
        "id": "node/4983904029"
      },
      "geometry": {
        "type": "Point",
        "coordinates": [
          -50.4459185,
          -18.4525632
        ]
      }
    },
    {
      "type": "Feature",
      "id": "node/4983946326",
      "properties": {
        "timestamp": "2020-03-08T03:21:15Z",
        "version": 2,
        "changeset": 81913966,
        "amenity": "hospital",
        "healthcare": "hospital",
        "name": "Hospital Nossa Sra D'Abadia",
        "name:pt": "Hospital Nossa Sra D'Abadia",
        "id": "node/4983946326"
      },
      "geometry": {
        "type": "Point",
        "coordinates": [
          -50.4531994,
          -18.4466961
        ]
      }
    },
    {
      "type": "Feature",
      "id": "node/4983960823",
      "properties": {
        "timestamp": "2017-07-21T00:18:52Z",
        "version": 1,
        "changeset": 50444719,
        "amenity": "hospital",
        "name": "Hospital Quirinópolis",
        "name:pt": "Hospital Quirinópolis",
        "id": "node/4983960823"
      },
      "geometry": {
        "type": "Point",
        "coordinates": [
          -50.4527764,
          -18.4455915
        ]
      }
    },
    {
      "type": "Feature",
      "id": "node/4984013421",
      "properties": {
        "timestamp": "2023-05-11T23:28:58Z",
        "version": 2,
        "changeset": 135996758,
        "addr:postcode": "75860-000",
        "addr:street": "Avenida Lázaro Xavier",
        "addr:suburb": "Centro",
        "amenity": "hospital",
        "fax": "+55 62 651 2132",
        "healthcare": "hospital",
        "name": "São Francisco",
        "name:pt": "São Francisco",
        "phone": "+55 62 651 1451",
        "ref:CNES": "2340593",
        "ref:vatin": "BR37173123013708",
        "id": "node/4984013421"
      },
      "geometry": {
        "type": "Point",
        "coordinates": [
          -50.4573035,
          -18.4462218
        ]
      }
    }
  ]
}
