{
  "type": "FeatureCollection",
  "features": [
    {
      "type": "Feature",
      "id": "node/10554569633",
      "properties": {
        "timestamp": "2023-01-14T14:15:23Z",
        "version": 1,
        "changeset": 131266592,
        "addr:city": "Pedro Canário",
        "addr:postcode": "29970-000",
        "addr:street": "Avenida Alberto dos Reis Castro",
        "addr:suburb": "Novo Horizonte",
        "amenity": "clinic",
        "healthcare": "clinic",
        "healthcare:speciality": "general",
        "name": "Unidade de Saúde Central",
        "operator": "Município de Pedro Canário",
        "operator:type": "public",
        "phone": "+55 27 3764 0815",
        "id": "node/10554569633"
      },
      "geometry": {
        "type": "Point",
        "coordinates": [
          -39.9596307,
          -18.2959491
        ]
      }
    }
  ]
}
