{
  "type": "FeatureCollection",
  "features": [
    {
      "type": "Feature",
      "id": "node/9074878899",
      "properties": {
        "timestamp": "2021-09-08T22:15:00Z",
        "version": 1,
        "changeset": 110940299,
        "amenity": "arts_centre",
        "name": "CTG Alvorada dos Pampas",
        "id": "node/9074878899"
      },
      "geometry": {
        "type": "Point",
        "coordinates": [
          -51.4571865,
          -27.6743429
        ]
      }
    }
  ]
}
