{
  "type": "FeatureCollection",
  "features": [
    {
      "type": "Feature",
      "id": "node/5986226447",
      "properties": {
        "timestamp": "2023-04-25T05:23:58Z",
        "version": 4,
        "changeset": 135326460,
        "addr:postcode": "95370-000",
        "addr:suburb": "Centro",
        "amenity": "hospital",
        "healthcare": "hospital",
        "name": "Hospital São Valentim",
        "phone": "+55 54 356 1333",
        "ref:CNES": "2246856",
        "ref:vatin": "BR88534748000115",
        "id": "node/5986226447"
      },
      "geometry": {
        "type": "Point",
        "coordinates": [
          -51.4623118,
          -27.6725791
        ]
      }
    }
  ]
}
