{
  "type": "FeatureCollection",
  "features": [
    {
      "type": "Feature",
      "id": "node/4438433091",
      "properties": {
        "timestamp": "2019-07-15T17:44:30Z",
        "version": 4,
        "changeset": 72275605,
        "addr:city": "Ibiraiaras",
        "addr:housenumber": "431",
        "addr:postcode": "95305-000",
        "addr:street": "Rua Antonio Fabris",
        "internet_access": "yes",
        "name": "Hotel e Restaurante Perinotto",
        "tourism": "hotel",
        "id": "node/4438433091"
      },
      "geometry": {
        "type": "Point",
        "coordinates": [
          -51.6361681,
          -28.3731197
        ]
      }
    },
    {
      "type": "Feature",
      "id": "node/4438433491",
      "properties": {
        "timestamp": "2018-09-01T02:16:18Z",
        "version": 3,
        "changeset": 62188470,
        "name": "Migliavacca",
        "tourism": "hotel",
        "id": "node/4438433491"
      },
      "geometry": {
        "type": "Point",
        "coordinates": [
          -51.635303,
          -28.3690966
        ]
      }
    }
  ]
}
