{
  "type": "FeatureCollection",
  "features": [
    {
      "type": "Feature",
      "id": "node/4873182021",
      "properties": {
        "timestamp": "2018-09-01T02:16:18Z",
        "version": 3,
        "changeset": 62188470,
        "amenity": "pharmacy",
        "name": "Agafarma",
        "id": "node/4873182021"
      },
      "geometry": {
        "type": "Point",
        "coordinates": [
          -51.635692,
          -28.3693648
        ]
      }
    },
    {
      "type": "Feature",
      "id": "node/5872533139",
      "properties": {
        "timestamp": "2018-09-01T02:16:17Z",
        "version": 1,
        "changeset": 62188470,
        "amenity": "pharmacy",
        "dispensing": "yes",
        "healthcare": "pharmacy",
        "id": "node/5872533139"
      },
      "geometry": {
        "type": "Point",
        "coordinates": [
          -51.6366688,
          -28.3691395
        ]
      }
    }
  ]
}
