{
  "type": "FeatureCollection",
  "features": [
    {
      "type": "Feature",
      "id": "node/10632958358",
      "properties": {
        "timestamp": "2023-02-09T16:27:19Z",
        "version": 3,
        "changeset": 132316328,
        "historic": "memorial",
        "memorial": "obelisk",
        "name": "Theodor Koelle",
        "subject:wikidata": "Q114340945",
        "id": "node/10632958358"
      },
      "geometry": {
        "type": "Point",
        "coordinates": [
          -47.5650593,
          -22.4044831
        ]
      }
    }
  ]
}
