{
  "type": "FeatureCollection",
  "features": [
    {
      "type": "Feature",
      "id": "node/2051400995",
      "properties": {
        "timestamp": "2017-03-04T13:53:47Z",
        "version": 3,
        "changeset": 46573005,
        "amenity": "library",
        "name": "Biblioteca Municipal",
        "wheelchair": "no",
        "id": "node/2051400995"
      },
      "geometry": {
        "type": "Point",
        "coordinates": [
          -38.969857,
          -12.6065493
        ]
      }
    }
  ]
}
