{
  "type": "FeatureCollection",
  "features": [
    {
      "type": "Feature",
      "id": "node/4982773323",
      "properties": {
        "timestamp": "2019-07-05T19:42:25Z",
        "version": 2,
        "changeset": 71943695,
        "name": "Ipú",
        "name:en": "Ipú",
        "name:pt": "Ipú",
        "seasonal": "yes",
        "waterway": "waterfall",
        "id": "node/4982773323"
      },
      "geometry": {
        "type": "Point",
        "coordinates": [
          -40.4913264,
          -3.4926679
        ]
      }
    }
  ]
}
