{
  "type": "FeatureCollection",
  "features": [
    {
      "type": "Feature",
      "id": "node/5697911015",
      "properties": {
        "timestamp": "2018-06-18T01:03:30Z",
        "version": 1,
        "changeset": 59926556,
        "amenity": "hospital",
        "healthcare": "hospital",
        "name": "Hospital de Miraí",
        "id": "node/5697911015"
      },
      "geometry": {
        "type": "Point",
        "coordinates": [
          -42.6139032,
          -21.1990367
        ]
      }
    }
  ]
}
