{
  "type": "FeatureCollection",
  "features": [
    {
      "type": "Feature",
      "id": "node/5697911015",
      "properties": {
        "timestamp": "2024-06-24T10:58:47Z",
        "version": 2,
        "changeset": 153106649,
        "addr:city": "Miraí",
        "addr:housenumber": "57",
        "addr:postcode": "36790-000",
        "addr:street": "Rua Ataulfo Alves",
        "addr:suburb": "Centro",
        "amenity": "hospital",
        "emergency": "yes",
        "healthcare": "hospital",
        "healthcare:speciality": "general",
        "name": "Casa de Caridade São Vicente de Paulo",
        "phone": "+ 55 32 3426 1362",
        "id": "node/5697911015"
      },
      "geometry": {
        "type": "Point",
        "coordinates": [
          -42.6138753,
          -21.1989607
        ]
      }
    }
  ]
}
