{
  "type": "FeatureCollection",
  "features": [
    {
      "type": "Feature",
      "id": "node/12111164499",
      "properties": {
        "timestamp": "2024-08-15T04:17:34Z",
        "version": 2,
        "changeset": 155265716,
        "amenity": "library",
        "name": "Biblioteca Pública Municipal Professora Leonidia Avelino Moraes",
        "wikidata": "Q88516450",
        "id": "node/12111164499"
      },
      "geometry": {
        "type": "Point",
        "coordinates": [
          -57.6862016,
          -16.0661317
        ]
      }
    }
  ]
}
