{
  "type": "FeatureCollection",
  "features": [
    {
      "type": "Feature",
      "id": "node/1844788316",
      "properties": {
        "timestamp": "2016-08-10T12:33:06Z",
        "version": 2,
        "changeset": 41366521,
        "amenity": "school",
        "name": "EMEF Governador Mario Covas",
        "id": "node/1844788316"
      },
      "geometry": {
        "type": "Point",
        "coordinates": [
          -49.7191365,
          -22.0804014
        ]
      }
    }
  ]
}
