{
  "type": "FeatureCollection",
  "features": [
    {
      "type": "Feature",
      "id": "node/3999140709",
      "properties": {
        "timestamp": "2016-02-10T13:37:27Z",
        "version": 1,
        "changeset": 37124622,
        "addr:city": "Viana",
        "addr:postcode": "29135-000",
        "addr:street": "Avenida Rio de Janeiro",
        "addr:suburb": "Areinha",
        "alt_name": "Centro de Referência de Assistência Social",
        "amenity": "social_facility",
        "contact:phone": "(27) 3354-1466",
        "name": "CRAS I - Vale do Sol",
        "social_facility": "outreach",
        "source": "IJSN",
        "id": "node/3999140709"
      },
      "geometry": {
        "type": "Point",
        "coordinates": [
          -40.4244886,
          -20.3776536
        ]
      }
    },
    {
      "type": "Feature",
      "id": "node/3999140710",
      "properties": {
        "timestamp": "2016-02-10T13:37:28Z",
        "version": 1,
        "changeset": 37124622,
        "addr:city": "Viana",
        "addr:housenumber": "25",
        "addr:postcode": "29135-000",
        "addr:street": "Rua Colatina",
        "addr:suburb": "Marcílio de Noronha",
        "alt_name": "Centro de Referência de Assistência Social",
        "amenity": "social_facility",
        "contact:phone": "(27) 3396-2818",
        "name": "CRAS II - Marcílio de Noronha",
        "social_facility": "outreach",
        "source": "IJSN",
        "id": "node/3999140710"
      },
      "geometry": {
        "type": "Point",
        "coordinates": [
          -40.4224614,
          -20.3493245
        ]
      }
    },
    {
      "type": "Feature",
      "id": "node/3999140712",
      "properties": {
        "timestamp": "2016-02-10T13:37:28Z",
        "version": 1,
        "changeset": 37124622,
        "addr:city": "Viana",
        "addr:postcode": "29135-983",
        "addr:street": "Rua Vesúvio",
        "addr:suburb": "Nova Bethânia",
        "alt_name": "Centro de Referência de Assistência Social",
        "amenity": "social_facility",
        "contact:phone": "(27) 3226-4263",
        "name": "CRAS IV - Nova Bethânia",
        "social_facility": "outreach",
        "source": "IJSN",
        "id": "node/3999140712"
      },
      "geometry": {
        "type": "Point",
        "coordinates": [
          -40.4141114,
          -20.369486
        ]
      }
    }
  ]
}
