{
  "type": "FeatureCollection",
  "features": [
    {
      "type": "Feature",
      "id": "node/3658781458",
      "properties": {
        "timestamp": "2022-03-09T16:18:32Z",
        "version": 6,
        "changeset": 118285455,
        "addr:postcode": "89295-000",
        "addr:street": "Rua Jorge Zipperer",
        "amenity": "library",
        "email": "bibliotecarn@bol.com.br",
        "name": "Biblioteca Pública Municipal Doutor Helládio Olsen Veiga",
        "phone": "+55 47 3644 4090",
        "website": "http://bibliotecapublicarn.blogspot.com",
        "id": "node/3658781458"
      },
      "geometry": {
        "type": "Point",
        "coordinates": [
          -49.5180925,
          -26.2549573
        ]
      }
    }
  ]
}
