{
  "type": "FeatureCollection",
  "features": [
    {
      "type": "Feature",
      "id": "node/3658781458",
      "properties": {
        "timestamp": "2024-04-21T13:32:14Z",
        "version": 7,
        "changeset": 150302689,
        "addr:postcode": "89295-000",
        "addr:street": "Rua Jorge Zipperer",
        "addr:suburb": "Centro",
        "amenity": "library",
        "contact:facebook": "https://www.facebook.com/BibliotecaRioNegrinho/",
        "email": "bibliotecarn@bol.com.br",
        "name": "Biblioteca Pública Municipal Doutor Helládio Olsen Veiga",
        "opening_hours": "Mo-Fr 07:30-11:30, 13:00-17:00; PH off",
        "phone": "+55 47 3644 4090",
        "website": "https://www.pensa-b.com.br/bibliotecarionegrinho/servlet/hmih001",
        "id": "node/3658781458"
      },
      "geometry": {
        "type": "Point",
        "coordinates": [
          -49.5180925,
          -26.2549573
        ]
      }
    }
  ]
}
