{
  "type": "FeatureCollection",
  "features": [
    {
      "type": "Feature",
      "id": "node/10185752438",
      "properties": {
        "timestamp": "2022-11-15T12:05:57Z",
        "version": 1,
        "changeset": 128937673,
        "addr:city": "Coluna",
        "addr:housenumber": "99",
        "addr:postcode": "39770-000",
        "addr:street": "Rua São João Evangelista",
        "addr:suburb": "Centro",
        "amenity": "hospital",
        "healthcare": "hospital",
        "healthcare:speciality": "general",
        "name": "Hospital Agostinha Alcantara de Aguiar",
        "operator": "Município de Coluna",
        "operator:type": "public",
        "phone": "+55 33 3435 1311",
        "id": "node/10185752438"
      },
      "geometry": {
        "type": "Point",
        "coordinates": [
          -42.8374461,
          -18.2385752
        ]
      }
    }
  ]
}
