{
  "type": "FeatureCollection",
  "features": [
    {
      "type": "Feature",
      "id": "node/10188273606",
      "properties": {
        "timestamp": "2022-11-16T10:59:49Z",
        "version": 1,
        "changeset": 128984314,
        "addr:city": "Coluna",
        "addr:housenumber": "550",
        "addr:postcode": "39770-000",
        "addr:street": "Rua Francisco Sousa Ferreira",
        "addr:suburb": "Centro",
        "amenity": "social_facility",
        "name": "Centro de Assistência e Referência Social de Coluna",
        "operator": "Município de Coluna",
        "operator:type": "public",
        "id": "node/10188273606"
      },
      "geometry": {
        "type": "Point",
        "coordinates": [
          -42.8414989,
          -18.2298705
        ]
      }
    },
    {
      "type": "Feature",
      "id": "node/10188273607",
      "properties": {
        "timestamp": "2022-11-16T10:59:49Z",
        "version": 1,
        "changeset": 128984314,
        "addr:city": "Coluna",
        "addr:housenumber": "349",
        "addr:postcode": "39770-000",
        "addr:street": "Rua Francisco Sousa Ferreira",
        "addr:suburb": "Centro",
        "amenity": "social_facility",
        "name": "Asilo São Vicente de Paulo",
        "operator": "Abrigo São Vicente de Paulo",
        "operator:type": "private",
        "social_facility": "day_care",
        "social_facility:for": "senior",
        "id": "node/10188273607"
      },
      "geometry": {
        "type": "Point",
        "coordinates": [
          -42.8416331,
          -18.2300482
        ]
      }
    }
  ]
}
