{
  "type": "FeatureCollection",
  "features": [
    {
      "type": "Feature",
      "id": "node/12050045475",
      "properties": {
        "timestamp": "2024-07-12T20:18:15Z",
        "version": 1,
        "changeset": 153871025,
        "government": "education",
        "name": "Secretaria Municipal de Educação",
        "office": "government",
        "source": "survey",
        "id": "node/12050045475"
      },
      "geometry": {
        "type": "Point",
        "coordinates": [
          -36.730069,
          -7.0755605
        ]
      }
    },
    {
      "type": "Feature",
      "id": "node/12050045476",
      "properties": {
        "timestamp": "2024-07-12T20:18:15Z",
        "version": 1,
        "changeset": 153871025,
        "government": "healthcare",
        "name": "Secretaria Municipal de Saúde",
        "office": "government",
        "source": "survey",
        "id": "node/12050045476"
      },
      "geometry": {
        "type": "Point",
        "coordinates": [
          -36.7323281,
          -7.0749463
        ]
      }
    }
  ]
}
