{
  "type": "FeatureCollection",
  "features": [
    {
      "type": "Feature",
      "id": "node/12388231820",
      "properties": {
        "timestamp": "2024-12-01T14:39:00Z",
        "version": 1,
        "changeset": 159808683,
        "IBGE:COD_UNICO_ENDERECO": "43247676",
        "addr:housenumber": "32",
        "addr:postcode": "25850-000",
        "addr:street": "Rua Chile",
        "addr:suburb": "Parque Morone",
        "building": "yes",
        "name": "Pousada Vô Deco",
        "tourism": "guest_house",
        "id": "node/12388231820"
      },
      "geometry": {
        "type": "Point",
        "coordinates": [
          -43.2865995,
          -22.146973
        ]
      }
    }
  ]
}
