{
  "type": "FeatureCollection",
  "features": [
    {
      "type": "Feature",
      "id": "node/6762729046",
      "properties": {
        "timestamp": "2019-08-31T23:25:29Z",
        "version": 1,
        "changeset": 73960021,
        "name": "Câmara de Vereadores",
        "office": "government",
        "id": "node/6762729046"
      },
      "geometry": {
        "type": "Point",
        "coordinates": [
          -52.6231349,
          -18.8026713
        ]
      }
    }
  ]
}
