{
  "type": "FeatureCollection",
  "features": [
    {
      "type": "Feature",
      "id": "node/10250414415",
      "properties": {
        "timestamp": "2022-12-10T09:54:46Z",
        "version": 1,
        "changeset": 129927835,
        "amenity": "hospital",
        "contact:phone": "+55 11 4597-1233",
        "healthcare": "hospital",
        "name": "Hospital Municipal De Nazaré Paulista",
        "id": "node/10250414415"
      },
      "geometry": {
        "type": "Point",
        "coordinates": [
          -46.3941988,
          -23.1609731
        ]
      }
    }
  ]
}
