{
  "type": "FeatureCollection",
  "features": [
    {
      "type": "Feature",
      "id": "node/5310628224",
      "properties": {
        "timestamp": "2017-12-29T18:29:41Z",
        "version": 1,
        "changeset": 55016572,
        "name": "Casa de Neiguinho",
        "tourism": "guest_house",
        "id": "node/5310628224"
      },
      "geometry": {
        "type": "Point",
        "coordinates": [
          -39.0099557,
          -13.0331322
        ]
      }
    }
  ]
}
