{
  "type": "FeatureCollection",
  "features": [
    {
      "type": "Feature",
      "id": "node/2256065130",
      "properties": {
        "timestamp": "2022-07-28T19:07:19Z",
        "version": 5,
        "changeset": 124199960,
        "name": "Hotel Ágatha",
        "tourism": "hotel",
        "id": "node/2256065130"
      },
      "geometry": {
        "type": "Point",
        "coordinates": [
          -42.7317128,
          -17.2858974
        ]
      }
    },
    {
      "type": "Feature",
      "id": "node/11431884369",
      "properties": {
        "timestamp": "2023-12-19T10:53:56Z",
        "version": 1,
        "changeset": 145286272,
        "name": "Hotel e Clube Lago Irapé",
        "tourism": "hotel",
        "id": "node/11431884369"
      },
      "geometry": {
        "type": "Point",
        "coordinates": [
          -42.8110874,
          -17.0258513
        ]
      }
    }
  ]
}
