{
  "type": "FeatureCollection",
  "features": [
    {
      "type": "Feature",
      "id": "node/2256065130",
      "properties": {
        "timestamp": "2022-07-28T19:07:19Z",
        "version": 5,
        "changeset": 124199960,
        "name": "Hotel Ágatha",
        "tourism": "hotel",
        "id": "node/2256065130"
      },
      "geometry": {
        "type": "Point",
        "coordinates": [
          -42.7317128,
          -17.2858974
        ]
      }
    }
  ]
}
