{
  "type": "FeatureCollection",
  "features": [
    {
      "type": "Feature",
      "id": "node/7017845443",
      "properties": {
        "timestamp": "2019-11-28T18:35:02Z",
        "version": 1,
        "changeset": 77695799,
        "amenity": "hospital",
        "healthcare": "hospital",
        "name": "Hospital Doutor Otto Alencar",
        "id": "node/7017845443"
      },
      "geometry": {
        "type": "Point",
        "coordinates": [
          -44.6960501,
          -12.007849
        ]
      }
    }
  ]
}
