{
  "type": "FeatureCollection",
  "features": [
    {
      "type": "Feature",
      "id": "node/1617113637",
      "properties": {
        "timestamp": "2020-05-05T23:20:58Z",
        "version": 3,
        "changeset": 84721115,
        "amenity": "school",
        "historic:railway": "station",
        "id": "node/1617113637"
      },
      "geometry": {
        "type": "Point",
        "coordinates": [
          -52.298122,
          -28.1254205
        ]
      }
    },
    {
      "type": "Feature",
      "id": "node/5443965220",
      "properties": {
        "timestamp": "2020-05-06T10:28:47Z",
        "version": 2,
        "changeset": 84753142,
        "amenity": "school",
        "name": "Escola Estadual Ensino Médio Visconde de Araguaia",
        "id": "node/5443965220"
      },
      "geometry": {
        "type": "Point",
        "coordinates": [
          -52.2974867,
          -28.1274275
        ]
      }
    },
    {
      "type": "Feature",
      "id": "node/7487536703",
      "properties": {
        "timestamp": "2020-05-05T23:20:58Z",
        "version": 1,
        "changeset": 84721115,
        "amenity": "school",
        "name": "Escola Municipal Ensino Fundamental Pantaleão Thomaz",
        "id": "node/7487536703"
      },
      "geometry": {
        "type": "Point",
        "coordinates": [
          -52.2997997,
          -28.1247154
        ]
      }
    }
  ]
}
