{
  "type": "FeatureCollection",
  "features": [
    {
      "type": "Feature",
      "id": "node/8883995906",
      "properties": {
        "timestamp": "2021-07-01T22:37:04Z",
        "version": 1,
        "changeset": 107281753,
        "addr:housename": "Centro Democrático Benjamin José Copetti",
        "addr:housenumber": "45",
        "addr:postcode": "97185-000",
        "addr:street": "Rua Itaara",
        "alt_name": "Câmara de Vereadores de Itaara",
        "contact:phone": "+55 55 3227-1443;+55 55 99613-5713",
        "contact:website": "https://www.itaara.rs.leg.br",
        "government": "legislative",
        "name": "Câmara Municipal de Itaara",
        "office": "government",
        "opening_hours": "Mo-Fr 08:00-12:00",
        "source": "LM 1206/2011",
        "id": "node/8883995906"
      },
      "geometry": {
        "type": "Point",
        "coordinates": [
          -53.7621023,
          -29.6096005
        ]
      }
    }
  ]
}
