{
  "type": "FeatureCollection",
  "features": [
    {
      "type": "Feature",
      "id": "node/9629736433",
      "properties": {
        "timestamp": "2022-04-01T18:07:06Z",
        "version": 1,
        "changeset": 119212817,
        "name": "Cachoeira Véu da Noiva",
        "waterway": "waterfall",
        "id": "node/9629736433"
      },
      "geometry": {
        "type": "Point",
        "coordinates": [
          -42.9548317,
          -16.5955286
        ]
      }
    }
  ]
}
