{
  "type": "FeatureCollection",
  "features": [
    {
      "type": "Feature",
      "id": "node/12246762498",
      "properties": {
        "timestamp": "2024-10-12T18:27:25Z",
        "version": 1,
        "changeset": 157808547,
        "name": "BEL BIKE",
        "shop": "bicycle",
        "id": "node/12246762498"
      },
      "geometry": {
        "type": "Point",
        "coordinates": [
          -44.1500862,
          -2.5362101
        ]
      }
    }
  ]
}
