{
  "type": "FeatureCollection",
  "features": [
    {
      "type": "Feature",
      "id": "node/4424408243",
      "properties": {
        "timestamp": "2021-01-25T01:57:26Z",
        "version": 2,
        "changeset": 98080935,
        "brand": "Holiday Inn Express",
        "brand:wikidata": "Q5880423",
        "brand:wikipedia": "en:Holiday Inn Express",
        "name": "Holiday Inn Express",
        "tourism": "hotel",
        "id": "node/4424408243"
      },
      "geometry": {
        "type": "Point",
        "coordinates": [
          -48.4281061,
          -1.4020069
        ]
      }
    },
    {
      "type": "Feature",
      "id": "node/4726169990",
      "properties": {
        "timestamp": "2017-03-09T15:36:11Z",
        "version": 1,
        "changeset": 46712776,
        "name": "Casa tia",
        "name:pt": "Casa tia",
        "tourism": "hotel",
        "id": "node/4726169990"
      },
      "geometry": {
        "type": "Point",
        "coordinates": [
          -48.4299652,
          -1.3874064
        ]
      }
    },
    {
      "type": "Feature",
      "id": "node/5256914809",
      "properties": {
        "timestamp": "2017-12-01T02:29:04Z",
        "version": 1,
        "changeset": 54221798,
        "tourism": "hotel",
        "id": "node/5256914809"
      },
      "geometry": {
        "type": "Point",
        "coordinates": [
          -48.4147463,
          -1.3749249
        ]
      }
    }
  ]
}
