{
  "type": "FeatureCollection",
  "features": [
    {
      "type": "Feature",
      "id": "node/5189048621",
      "properties": {
        "timestamp": "2018-10-30T03:20:16Z",
        "version": 2,
        "changeset": 63997522,
        "addr:postcode": "55330-000",
        "addr:street": "Rua Cleto Campelo",
        "amenity": "hospital",
        "name": "Hospital Monsenhor Alfredo Dâmaso",
        "id": "node/5189048621"
      },
      "geometry": {
        "type": "Point",
        "coordinates": [
          -36.6869701,
          -9.1645301
        ]
      }
    }
  ]
}
