{
  "type": "FeatureCollection",
  "features": [
    {
      "type": "Feature",
      "id": "node/4355868228",
      "properties": {
        "timestamp": "2016-08-18T14:39:52Z",
        "version": 1,
        "changeset": 41535425,
        "name": "Condomínio Residencial Sonho Real",
        "tourism": "hotel",
        "id": "node/4355868228"
      },
      "geometry": {
        "type": "Point",
        "coordinates": [
          -47.6052471,
          -15.4363707
        ]
      }
    }
  ]
}
