{
  "type": "FeatureCollection",
  "features": [
    {
      "type": "Feature",
      "id": "node/5434198085",
      "properties": {
        "timestamp": "2018-12-17T15:21:59Z",
        "version": 2,
        "changeset": 65553452,
        "name": "Cascata Cantinho Colonial",
        "tourism": "attraction",
        "waterway": "waterfall",
        "id": "node/5434198085"
      },
      "geometry": {
        "type": "Point",
        "coordinates": [
          -52.5067413,
          -29.6772544
        ]
      }
    }
  ]
}
