{
  "type": "FeatureCollection",
  "features": [
    {
      "type": "Feature",
      "id": "node/4758085178",
      "properties": {
        "timestamp": "2017-03-27T14:51:38Z",
        "version": 1,
        "changeset": 47203612,
        "amenity": "school",
        "name": "Escola Municipal Siegfried Heuser",
        "id": "node/4758085178"
      },
      "geometry": {
        "type": "Point",
        "coordinates": [
          -53.213329,
          -29.0957184
        ]
      }
    },
    {
      "type": "Feature",
      "id": "node/4758085192",
      "properties": {
        "timestamp": "2020-05-09T16:29:32Z",
        "version": 3,
        "changeset": 84944341,
        "amenity": "school",
        "name": "Escola Miguel Calmon",
        "id": "node/4758085192"
      },
      "geometry": {
        "type": "Point",
        "coordinates": [
          -53.2275117,
          -29.0901479
        ]
      }
    },
    {
      "type": "Feature",
      "id": "node/4758630004",
      "properties": {
        "timestamp": "2022-09-07T20:57:33Z",
        "version": 3,
        "changeset": 125917911,
        "addr:street": "Rua Alberto Pasqualini",
        "amenity": "school",
        "name": "EEEM Castelo Branco",
        "id": "node/4758630004"
      },
      "geometry": {
        "type": "Point",
        "coordinates": [
          -53.212705,
          -29.0885046
        ]
      }
    },
    {
      "type": "Feature",
      "id": "node/7522982321",
      "properties": {
        "timestamp": "2020-05-15T14:03:39Z",
        "version": 1,
        "changeset": 85265983,
        "amenity": "school",
        "id": "node/7522982321"
      },
      "geometry": {
        "type": "Point",
        "coordinates": [
          -53.2130636,
          -29.1004013
        ]
      }
    },
    {
      "type": "Feature",
      "id": "node/7522982322",
      "properties": {
        "timestamp": "2020-05-15T14:03:39Z",
        "version": 1,
        "changeset": 85265983,
        "amenity": "school",
        "id": "node/7522982322"
      },
      "geometry": {
        "type": "Point",
        "coordinates": [
          -53.2254504,
          -29.0944062
        ]
      }
    }
  ]
}
