{
  "type": "FeatureCollection",
  "features": [
    {
      "type": "Feature",
      "id": "node/10102992069",
      "properties": {
        "timestamp": "2022-10-15T13:58:32Z",
        "version": 2,
        "changeset": 127572545,
        "description": "Waterfall and rocky formations inside indigenous reserve. Free access upon asking locals.",
        "name": "Saltinho do Jacuí",
        "waterway": "waterfall",
        "id": "node/10102992069"
      },
      "geometry": {
        "type": "Point",
        "coordinates": [
          -53.2259203,
          -29.0548941
        ]
      }
    }
  ]
}
