{
  "type": "FeatureCollection",
  "features": [
    {
      "type": "Feature",
      "id": "node/3382422767",
      "properties": {
        "timestamp": "2015-03-04T07:43:18Z",
        "version": 2,
        "changeset": 29238022,
        "addr:city": "Curaçá",
        "addr:postcode": "48930-000",
        "addr:street": "Avenida Dr. Euvaldo Torres de Aquino",
        "addr:suburb": "Centro",
        "amenity": "hospital",
        "emergency": "yes",
        "name": "Hospital Municipal Doutor Antonio Carlos Magalhães",
        "id": "node/3382422767"
      },
      "geometry": {
        "type": "Point",
        "coordinates": [
          -39.9055745,
          -8.9920734
        ]
      }
    }
  ]
}
