{
  "type": "FeatureCollection",
  "features": [
    {
      "type": "Feature",
      "id": "node/6533179001",
      "properties": {
        "timestamp": "2024-02-03T01:51:46Z",
        "version": 2,
        "changeset": 147006026,
        "historic": "monument",
        "name": "Monumento ao Caminhoneiro",
        "id": "node/6533179001"
      },
      "geometry": {
        "type": "Point",
        "coordinates": [
          -38.964313,
          -12.2597532
        ]
      }
    },
    {
      "type": "Feature",
      "id": "node/6533179002",
      "properties": {
        "timestamp": "2019-06-08T01:24:04Z",
        "version": 1,
        "changeset": 71041606,
        "historic": "monument",
        "name": "Monumento a Maria Quitéria",
        "id": "node/6533179002"
      },
      "geometry": {
        "type": "Point",
        "coordinates": [
          -38.9546554,
          -12.2555767
        ]
      }
    },
    {
      "type": "Feature",
      "id": "node/6566191877",
      "properties": {
        "timestamp": "2019-06-23T15:37:48Z",
        "version": 1,
        "changeset": 71535074,
        "historic": "monument",
        "name": "Monumento ao Tropeiro",
        "id": "node/6566191877"
      },
      "geometry": {
        "type": "Point",
        "coordinates": [
          -38.9696793,
          -12.2530838
        ]
      }
    }
  ]
}
