{
  "type": "FeatureCollection",
  "features": [
    {
      "type": "Feature",
      "id": "node/7702361623",
      "properties": {
        "timestamp": "2020-07-10T12:30:15Z",
        "version": 1,
        "changeset": 87817509,
        "amenity": "drinking_water",
        "name": "Bebedouro Público",
        "id": "node/7702361623"
      },
      "geometry": {
        "type": "Point",
        "coordinates": [
          -54.0573525,
          -24.5576024
        ]
      }
    }
  ]
}
