{
  "type": "FeatureCollection",
  "features": [
    {
      "type": "Feature",
      "id": "node/4819790421",
      "properties": {
        "timestamp": "2017-04-27T08:47:05Z",
        "version": 1,
        "changeset": 48187275,
        "addr:street": "Rua E",
        "amenity": "community_centre",
        "name": "Sebrae",
        "name:pt": "Sebrae",
        "id": "node/4819790421"
      },
      "geometry": {
        "type": "Point",
        "coordinates": [
          -49.9110519,
          -6.0649393
        ]
      }
    }
  ]
}
