{
  "type": "FeatureCollection",
  "features": [
    {
      "type": "Feature",
      "id": "node/4176720361",
      "properties": {
        "timestamp": "2016-05-10T16:00:06Z",
        "version": 1,
        "changeset": 39221609,
        "historic": "monument",
        "id": "node/4176720361"
      },
      "geometry": {
        "type": "Point",
        "coordinates": [
          -35.6321286,
          -6.7524572
        ]
      }
    },
    {
      "type": "Feature",
      "id": "node/4176720362",
      "properties": {
        "timestamp": "2016-05-10T16:00:06Z",
        "version": 1,
        "changeset": 39221609,
        "historic": "monument",
        "name": "Marco comemorativo dos 100 anos da Independência do Brasil",
        "id": "node/4176720362"
      },
      "geometry": {
        "type": "Point",
        "coordinates": [
          -35.6326713,
          -6.7544219
        ]
      }
    }
  ]
}
