{
  "type": "FeatureCollection",
  "features": [
    {
      "type": "Feature",
      "id": "node/6990834975",
      "properties": {
        "timestamp": "2019-11-23T17:48:01Z",
        "version": 2,
        "changeset": 77465108,
        "description": "Inundada pela Represa. O local de implantação da barragem, sendo escolhido a Cachoeira próxima à foz do Rio Borrachudo, 22 km a jusante das Três Marias, que em virtude da divulgação dada aos trabalhos iniciais, consagrou-se com o nome de Três Marias",
        "name": "Cachoeira Comprida",
        "old_name": "Cachoeira das Três Marias",
        "source": "IBGE",
        "waterway": "waterfall",
        "id": "node/6990834975"
      },
      "geometry": {
        "type": "Point",
        "coordinates": [
          -45.2905472,
          -18.3391582
        ]
      }
    }
  ]
}
