{
  "type": "FeatureCollection",
  "features": [
    {
      "type": "Feature",
      "id": "node/10681899589",
      "properties": {
        "timestamp": "2023-02-20T22:29:26Z",
        "version": 1,
        "changeset": 132811008,
        "amenity": "library",
        "name": "Biblioteca da Fortaleza",
        "operator": "IPHAN",
        "id": "node/10681899589"
      },
      "geometry": {
        "type": "Point",
        "coordinates": [
          -48.3116559,
          -25.5109115
        ]
      }
    },
    {
      "type": "Feature",
      "id": "node/11117828254",
      "properties": {
        "timestamp": "2023-08-15T23:48:57Z",
        "version": 1,
        "changeset": 139938944,
        "amenity": "library",
        "name": "Biblioteca Mun. de Paranaguá",
        "id": "node/11117828254"
      },
      "geometry": {
        "type": "Point",
        "coordinates": [
          -48.5084106,
          -25.5215696
        ]
      }
    }
  ]
}
