{
  "type": "FeatureCollection",
  "features": [
    {
      "type": "Feature",
      "id": "node/2644895130",
      "properties": {
        "timestamp": "2023-09-24T20:11:20Z",
        "version": 5,
        "changeset": 141698321,
        "historic": "monument",
        "name": "Monumento Natural dos Costões Rochosos",
        "wikimedia_commons": "File:Costoes rochosos 2.jpg",
        "id": "node/2644895130"
      },
      "geometry": {
        "type": "Point",
        "coordinates": [
          -41.9227398,
          -22.5285672
        ]
      }
    }
  ]
}
