{
  "type": "FeatureCollection",
  "features": [
    {
      "type": "Feature",
      "id": "node/3603992180",
      "properties": {
        "timestamp": "2023-08-06T22:47:04Z",
        "version": 6,
        "changeset": 139534949,
        "addr:city": "Meridiano",
        "addr:housenumber": "2070",
        "addr:postcode": "15625-000",
        "addr:street": "Rua Sete de Setembro",
        "addr:suburb": "Centro",
        "amenity": "clinic",
        "healthcare": "clinic",
        "healthcare:speciality": "general;gynaecology;paediatrics",
        "name": "Unidade Básica de Saúde de Meridiano",
        "opening_hours": "Mo-Fr 07:00-21:00; Sa,Su,PH off",
        "operator:ref:vatin": "BR45116092000108",
        "phone": "+55 17 3475 1144",
        "ref": "CNES-2028557",
        "ref:CNES": "2028557",
        "short_name": "UBS de Meridiano",
        "id": "node/3603992180"
      },
      "geometry": {
        "type": "Point",
        "coordinates": [
          -50.1762547,
          -20.3568356
        ]
      }
    }
  ]
}
