{
  "type": "FeatureCollection",
  "features": [
    {
      "type": "Feature",
      "id": "node/3406118508",
      "properties": {
        "timestamp": "2016-02-25T20:00:25Z",
        "version": 2,
        "changeset": 37445557,
        "waterway": "waterfall",
        "id": "node/3406118508"
      },
      "geometry": {
        "type": "Point",
        "coordinates": [
          -48.9898824,
          -26.8258672
        ]
      }
    },
    {
      "type": "Feature",
      "id": "node/6409595706",
      "properties": {
        "timestamp": "2020-05-29T14:58:47Z",
        "version": 2,
        "changeset": 85952996,
        "height": "30",
        "intermittent": "no",
        "name": "Cachoeira Alananda",
        "waterway": "waterfall",
        "width": "10",
        "id": "node/6409595706"
      },
      "geometry": {
        "type": "Point",
        "coordinates": [
          -49.0359575,
          -27.033689
        ]
      }
    },
    {
      "type": "Feature",
      "id": "node/7278292918",
      "properties": {
        "timestamp": "2020-03-08T21:41:27Z",
        "version": 1,
        "changeset": 81934232,
        "waterway": "waterfall",
        "id": "node/7278292918"
      },
      "geometry": {
        "type": "Point",
        "coordinates": [
          -48.9937465,
          -26.9782654
        ]
      }
    },
    {
      "type": "Feature",
      "id": "node/8695378571",
      "properties": {
        "timestamp": "2021-05-04T00:09:58Z",
        "version": 1,
        "changeset": 104083592,
        "waterway": "waterfall",
        "id": "node/8695378571"
      },
      "geometry": {
        "type": "Point",
        "coordinates": [
          -48.9735237,
          -26.8485019
        ]
      }
    },
    {
      "type": "Feature",
      "id": "node/11608712501",
      "properties": {
        "timestamp": "2024-02-10T22:34:44Z",
        "version": 2,
        "changeset": 147310544,
        "waterway": "waterfall",
        "id": "node/11608712501"
      },
      "geometry": {
        "type": "Point",
        "coordinates": [
          -49.004616,
          -27.0002663
        ]
      }
    },
    {
      "type": "Feature",
      "id": "node/12013053672",
      "properties": {
        "timestamp": "2024-06-26T19:01:52Z",
        "version": 1,
        "changeset": 153217145,
        "waterway": "waterfall",
        "id": "node/12013053672"
      },
      "geometry": {
        "type": "Point",
        "coordinates": [
          -48.9869911,
          -26.8358419
        ]
      }
    }
  ]
}
