{
  "type": "FeatureCollection",
  "features": [
    {
      "type": "Feature",
      "id": "node/4714022229",
      "properties": {
        "timestamp": "2024-02-06T23:47:03Z",
        "version": 2,
        "changeset": 147155638,
        "contact:instagram": "cascata_salto_rio_pardinho",
        "name": "Cascata Salto Rio Pardinho",
        "source": "osm notes",
        "waterway": "waterfall",
        "id": "node/4714022229"
      },
      "geometry": {
        "type": "Point",
        "coordinates": [
          -52.5148362,
          -29.4965845
        ]
      }
    },
    {
      "type": "Feature",
      "id": "node/5581397029",
      "properties": {
        "timestamp": "2023-04-04T15:30:31Z",
        "version": 2,
        "changeset": 134501622,
        "waterway": "waterfall",
        "id": "node/5581397029"
      },
      "geometry": {
        "type": "Point",
        "coordinates": [
          -52.6815784,
          -29.3160908
        ]
      }
    },
    {
      "type": "Feature",
      "id": "node/5581398092",
      "properties": {
        "timestamp": "2023-04-04T01:12:07Z",
        "version": 2,
        "changeset": 134475073,
        "name": "Cascata Salto do Rio Pardinho",
        "waterway": "waterfall",
        "id": "node/5581398092"
      },
      "geometry": {
        "type": "Point",
        "coordinates": [
          -52.5426829,
          -29.3820232
        ]
      }
    },
    {
      "type": "Feature",
      "id": "node/10784650200",
      "properties": {
        "timestamp": "2023-04-04T15:30:31Z",
        "version": 1,
        "changeset": 134501622,
        "waterway": "waterfall",
        "id": "node/10784650200"
      },
      "geometry": {
        "type": "Point",
        "coordinates": [
          -52.6865566,
          -29.3309825
        ]
      }
    }
  ]
}
