{
  "type": "FeatureCollection",
  "features": [
    {
      "type": "Feature",
      "id": "node/4986895855",
      "properties": {
        "timestamp": "2017-07-22T16:13:34Z",
        "version": 1,
        "changeset": 50484472,
        "addr:postcode": "37170-000",
        "addr:street": "Rua Presidente Getúlio Vargas",
        "amenity": "cinema",
        "name": "Cine Coral",
        "id": "node/4986895855"
      },
      "geometry": {
        "type": "Point",
        "coordinates": [
          -45.5638543,
          -21.09151
        ]
      }
    }
  ]
}
