{
  "type": "FeatureCollection",
  "features": [
    {
      "type": "Feature",
      "id": "node/6980263897",
      "properties": {
        "timestamp": "2019-11-15T16:43:25Z",
        "version": 1,
        "changeset": 77138632,
        "historic": "monument",
        "name": "Monumento à Batalha da Ilha do Fanfa",
        "id": "node/6980263897"
      },
      "geometry": {
        "type": "Point",
        "coordinates": [
          -51.5493315,
          -29.9142025
        ]
      }
    }
  ]
}
