{
  "type": "FeatureCollection",
  "features": [
    {
      "type": "Feature",
      "id": "node/4594329629",
      "properties": {
        "timestamp": "2017-01-07T13:24:31Z",
        "version": 1,
        "changeset": 44978641,
        "amenity": "clinic",
        "name": "Posto de Saúde",
        "id": "node/4594329629"
      },
      "geometry": {
        "type": "Point",
        "coordinates": [
          -43.6922885,
          -19.6597165
        ]
      }
    }
  ]
}
