{
  "type": "FeatureCollection",
  "features": [
    {
      "type": "Feature",
      "id": "node/8626428201",
      "properties": {
        "timestamp": "2023-03-10T00:14:47Z",
        "version": 2,
        "changeset": 133498824,
        "amenity": "hospital",
        "healthcare": "hospital",
        "name": "Hospital São Lucas",
        "id": "node/8626428201"
      },
      "geometry": {
        "type": "Point",
        "coordinates": [
          -50.3351817,
          -26.3669963
        ]
      }
    }
  ]
}
