{
  "type": "FeatureCollection",
  "features": [
    {
      "type": "Feature",
      "id": "node/6003681889",
      "properties": {
        "timestamp": "2021-08-19T11:41:13Z",
        "version": 2,
        "changeset": 109929096,
        "amenity": "pharmacy",
        "healthcare": "pharmacy",
        "id": "node/6003681889"
      },
      "geometry": {
        "type": "Point",
        "coordinates": [
          -55.1687052,
          -15.5494826
        ]
      }
    },
    {
      "type": "Feature",
      "id": "node/6003681891",
      "properties": {
        "timestamp": "2021-08-19T11:41:13Z",
        "version": 2,
        "changeset": 109929096,
        "amenity": "pharmacy",
        "healthcare": "pharmacy",
        "name": "Drogaria Popular",
        "name:en": "Drogaria Popular 24h",
        "name:pt": "Drogaria Popular 24h",
        "opening_hours": "24/7",
        "id": "node/6003681891"
      },
      "geometry": {
        "type": "Point",
        "coordinates": [
          -55.1680332,
          -15.5506751
        ]
      }
    },
    {
      "type": "Feature",
      "id": "node/6003682085",
      "properties": {
        "timestamp": "2021-08-19T11:41:13Z",
        "version": 2,
        "changeset": 109929096,
        "amenity": "pharmacy",
        "healthcare": "pharmacy",
        "id": "node/6003682085"
      },
      "geometry": {
        "type": "Point",
        "coordinates": [
          -55.168992,
          -15.5496557
        ]
      }
    }
  ]
}
