{
  "type": "FeatureCollection",
  "features": [
    {
      "type": "Feature",
      "id": "node/10573000899",
      "properties": {
        "timestamp": "2023-01-21T16:59:47Z",
        "version": 1,
        "changeset": 131547813,
        "amenity": "pharmacy",
        "healthcare": "pharmacy",
        "name": "Drogaria Magnus",
        "id": "node/10573000899"
      },
      "geometry": {
        "type": "Point",
        "coordinates": [
          -49.8338932,
          -29.1955132
        ]
      }
    }
  ]
}
