{
  "type": "FeatureCollection",
  "features": [
    {
      "type": "Feature",
      "id": "node/6381108289",
      "properties": {
        "timestamp": "2019-04-03T15:22:09Z",
        "version": 1,
        "changeset": 68844134,
        "name": "Kabana",
        "restaurant": "yes",
        "tourism": "hotel",
        "id": "node/6381108289"
      },
      "geometry": {
        "type": "Point",
        "coordinates": [
          -46.9067367,
          -17.9864689
        ]
      }
    }
  ]
}
