{
  "type": "FeatureCollection",
  "features": [
    {
      "type": "Feature",
      "id": "node/6381176827",
      "properties": {
        "timestamp": "2019-04-03T16:00:01Z",
        "version": 1,
        "changeset": 68845792,
        "historic": "monument",
        "name": "Cruz Vazada",
        "natural": "earth",
        "id": "node/6381176827"
      },
      "geometry": {
        "type": "Point",
        "coordinates": [
          -46.9040073,
          -17.9959705
        ]
      }
    },
    {
      "type": "Feature",
      "id": "node/6385695016",
      "properties": {
        "timestamp": "2019-04-05T13:53:03Z",
        "version": 1,
        "changeset": 68922814,
        "historic": "monument",
        "id": "node/6385695016"
      },
      "geometry": {
        "type": "Point",
        "coordinates": [
          -46.8986584,
          -17.9892946
        ]
      }
    }
  ]
}
