{
  "type": "FeatureCollection",
  "features": [
    {
      "type": "Feature",
      "id": "node/9758232474",
      "properties": {
        "timestamp": "2022-05-20T20:18:56Z",
        "version": 1,
        "changeset": 121259776,
        "access": "yes",
        "amenity": "library",
        "name": "Biblioteca Pública Municipal Albertina Ramos de Araújo",
        "operator": "Prefeitura Municipal de São José",
        "operator:type": "public",
        "start_date": "1877",
        "id": "node/9758232474"
      },
      "geometry": {
        "type": "Point",
        "coordinates": [
          -48.6278379,
          -27.6154654
        ]
      }
    }
  ]
}
