{
  "type": "FeatureCollection",
  "features": [
    {
      "type": "Feature",
      "id": "node/2071792410",
      "properties": {
        "timestamp": "2022-05-20T20:18:56Z",
        "version": 3,
        "changeset": 121259776,
        "historic": "monument",
        "name": "250 anos de São José",
        "id": "node/2071792410"
      },
      "geometry": {
        "type": "Point",
        "coordinates": [
          -48.6269957,
          -27.6162604
        ]
      }
    },
    {
      "type": "Feature",
      "id": "node/5739583799",
      "properties": {
        "timestamp": "2018-12-24T21:01:08Z",
        "version": 2,
        "changeset": 65750084,
        "historic": "monument",
        "name": "Fundação de São José",
        "id": "node/5739583799"
      },
      "geometry": {
        "type": "Point",
        "coordinates": [
          -48.6274322,
          -27.6158801
        ]
      }
    }
  ]
}
