{
  "type": "FeatureCollection",
  "features": [
    {
      "type": "Feature",
      "id": "node/11397179277",
      "properties": {
        "timestamp": "2023-12-10T05:25:46Z",
        "version": 2,
        "changeset": 144954658,
        "addr:city": "São José",
        "addr:housenumber": "668",
        "addr:postcode": "88101-090",
        "addr:street": "Rua Adhemar da Silva",
        "addr:suburb": "Kobrasol",
        "amenity": "veterinary",
        "name": "Hospital Veterinário Santa Vida",
        "opening_hours": "24/7",
        "phone": "+55 48 3034 7477",
        "website": "https://hvsantavida.com.br/",
        "id": "node/11397179277"
      },
      "geometry": {
        "type": "Point",
        "coordinates": [
          -48.61301,
          -27.5958378
        ]
      }
    }
  ]
}
