{
  "type": "FeatureCollection",
  "features": [
    {
      "type": "Feature",
      "id": "node/6723581844",
      "properties": {
        "timestamp": "2023-04-14T13:26:43Z",
        "version": 2,
        "changeset": 134903067,
        "name": "Bike Trip - Pinhais",
        "shop": "bicycle",
        "id": "node/6723581844"
      },
      "geometry": {
        "type": "Point",
        "coordinates": [
          -49.1806676,
          -25.4404085
        ]
      }
    },
    {
      "type": "Feature",
      "id": "node/6812855486",
      "properties": {
        "timestamp": "2019-10-28T16:11:14Z",
        "version": 2,
        "changeset": 76306843,
        "name": "KF Bikes",
        "shop": "bicycle",
        "id": "node/6812855486"
      },
      "geometry": {
        "type": "Point",
        "coordinates": [
          -49.1756073,
          -25.4345722
        ]
      }
    },
    {
      "type": "Feature",
      "id": "node/9554682505",
      "properties": {
        "timestamp": "2022-07-30T12:42:55Z",
        "version": 2,
        "changeset": 124266519,
        "addr:city": "Jardim Amélia - Pinhais",
        "addr:housenumber": "364",
        "addr:postcode": "83330-200",
        "addr:street": "Rua Humberto de Alencar Castelo Branco",
        "addr:suburb": "Vila Amelia",
        "name": "Bicicletaria Pedal Cilada",
        "opening_hours": "Mo-Sa 08:00-18:00",
        "operator": "Alex Fediuk",
        "phone": "+55 41 9 9580 0882",
        "service:bicycle:repair": "yes",
        "service:bicycle:sales": "yes",
        "shop": "bicycle",
        "id": "node/9554682505"
      },
      "geometry": {
        "type": "Point",
        "coordinates": [
          -49.1621873,
          -25.4339049
        ]
      }
    },
    {
      "type": "Feature",
      "id": "node/12431224296",
      "properties": {
        "timestamp": "2025-01-22T16:31:16Z",
        "version": 4,
        "changeset": 161644945,
        "addr:street": "Rua Etiópia",
        "contact:phone": "+55 41 99985-6522",
        "name": "JV Bikes",
        "shop": "bicycle",
        "id": "node/12431224296"
      },
      "geometry": {
        "type": "Point",
        "coordinates": [
          -49.1780933,
          -25.4309204
        ]
      }
    }
  ]
}
