{
  "type": "FeatureCollection",
  "features": [
    {
      "type": "Feature",
      "id": "node/5371457428",
      "properties": {
        "timestamp": "2018-01-30T01:04:32Z",
        "version": 1,
        "changeset": 55877730,
        "historic": "memorial",
        "memorial": "bust",
        "name": "Argigas",
        "id": "node/5371457428"
      },
      "geometry": {
        "type": "Point",
        "coordinates": [
          -48.6229603,
          -27.0026879
        ]
      }
    }
  ]
}
