{
  "type": "FeatureCollection",
  "features": [
    {
      "type": "Feature",
      "id": "node/6883887586",
      "properties": {
        "timestamp": "2019-10-16T00:28:25Z",
        "version": 1,
        "changeset": 75747831,
        "amenity": "arts_centre",
        "name": "Centro Cultural Eduardo Cabral",
        "id": "node/6883887586"
      },
      "geometry": {
        "type": "Point",
        "coordinates": [
          -62.9227338,
          -0.9788791
        ]
      }
    }
  ]
}
