{
  "type": "FeatureCollection",
  "features": [
    {
      "type": "Feature",
      "id": "node/12750869982",
      "properties": {
        "timestamp": "2025-04-13T01:55:53Z",
        "version": 1,
        "changeset": 164877075,
        "addr:city": "Uauá",
        "addr:housenumber": "1173",
        "addr:postcode": "48950-000",
        "addr:street": "Avenida Pedro Ribeiro",
        "addr:suburb": "Centro",
        "government": "agriculture",
        "name": "Agência de Defesa Agropecuária da Bahia - Adab",
        "office": "government",
        "phone": "+55 74 99808 1321",
        "website": "http://www.adab.ba.gov.br/institucional/",
        "id": "node/12750869982"
      },
      "geometry": {
        "type": "Point",
        "coordinates": [
          -39.4819726,
          -9.8399698
        ]
      }
    }
  ]
}
