{
  "type": "FeatureCollection",
  "features": [
    {
      "type": "Feature",
      "id": "node/2978426204",
      "properties": {
        "timestamp": "2014-07-25T02:54:35Z",
        "version": 1,
        "changeset": 24341277,
        "name": "Cachoeira do Cavalo Queimado",
        "waterway": "waterfall",
        "id": "node/2978426204"
      },
      "geometry": {
        "type": "Point",
        "coordinates": [
          -46.8584025,
          -11.4033779
        ]
      }
    }
  ]
}
