{
  "type": "FeatureCollection",
  "features": [
    {
      "type": "Feature",
      "id": "node/8971242097",
      "properties": {
        "timestamp": "2021-08-01T03:11:29Z",
        "version": 1,
        "changeset": 108961224,
        "amenity": "dentist",
        "healthcare": "dentist",
        "level": "0",
        "name": "SJ Odontologia Especializada",
        "id": "node/8971242097"
      },
      "geometry": {
        "type": "Point",
        "coordinates": [
          -48.8274539,
          -26.9005875
        ]
      }
    }
  ]
}
