{
  "type": "FeatureCollection",
  "features": [
    {
      "type": "Feature",
      "id": "node/4943190810",
      "properties": {
        "timestamp": "2022-03-04T21:55:51Z",
        "version": 3,
        "changeset": 118109092,
        "addr:housenumber": "300",
        "addr:street": "Avenida Ricardo Paulino Maes",
        "amenity": "pharmacy",
        "name": "Farmácia Santo André",
        "id": "node/4943190810"
      },
      "geometry": {
        "type": "Point",
        "coordinates": [
          -48.8309978,
          -26.9030342
        ]
      }
    },
    {
      "type": "Feature",
      "id": "node/9203450092",
      "properties": {
        "timestamp": "2021-10-26T22:21:42Z",
        "version": 1,
        "changeset": 113012542,
        "addr:housenumber": "413",
        "addr:street": "Rua Guilherme João Brockveld",
        "amenity": "pharmacy",
        "dispensing": "yes",
        "healthcare": "pharmacy",
        "name": "Popular Farma",
        "id": "node/9203450092"
      },
      "geometry": {
        "type": "Point",
        "coordinates": [
          -48.8170972,
          -26.9117632
        ]
      }
    }
  ]
}
