{
  "type": "FeatureCollection",
  "features": [
    {
      "type": "Feature",
      "id": "node/2854145694",
      "properties": {
        "timestamp": "2018-06-19T22:42:13Z",
        "version": 2,
        "changeset": 59992644,
        "government": "legislative",
        "name": "Câmara Municipal",
        "office": "government",
        "id": "node/2854145694"
      },
      "geometry": {
        "type": "Point",
        "coordinates": [
          -36.2964834,
          -9.256873
        ]
      }
    }
  ]
}
