{
  "type": "FeatureCollection",
  "features": [
    {
      "type": "Feature",
      "id": "node/4376330926",
      "properties": {
        "timestamp": "2020-05-08T15:13:50Z",
        "version": 3,
        "changeset": 84902361,
        "height": "100",
        "name": "Cachoeira Alta",
        "waterway": "waterfall",
        "id": "node/4376330926"
      },
      "geometry": {
        "type": "Point",
        "coordinates": [
          -41.0852593,
          -20.7002146
        ]
      }
    },
    {
      "type": "Feature",
      "id": "node/7439214814",
      "properties": {
        "timestamp": "2022-03-24T14:30:14Z",
        "version": 2,
        "changeset": 118867525,
        "waterway": "waterfall",
        "id": "node/7439214814"
      },
      "geometry": {
        "type": "Point",
        "coordinates": [
          -41.0025797,
          -20.4548273
        ]
      }
    },
    {
      "type": "Feature",
      "id": "node/7450388786",
      "properties": {
        "timestamp": "2022-03-21T11:52:03Z",
        "version": 2,
        "changeset": 118732548,
        "height": "12",
        "name": "Cachoeira do Caiado",
        "waterway": "waterfall",
        "id": "node/7450388786"
      },
      "geometry": {
        "type": "Point",
        "coordinates": [
          -40.9593301,
          -20.6501219
        ]
      }
    },
    {
      "type": "Feature",
      "id": "node/7463579276",
      "properties": {
        "timestamp": "2020-09-27T13:36:12Z",
        "version": 2,
        "changeset": 91583933,
        "name": "Cachoeira do Elói",
        "waterway": "waterfall",
        "id": "node/7463579276"
      },
      "geometry": {
        "type": "Point",
        "coordinates": [
          -41.0135439,
          -20.7389833
        ]
      }
    },
    {
      "type": "Feature",
      "id": "node/7463601406",
      "properties": {
        "timestamp": "2020-06-29T15:56:27Z",
        "version": 2,
        "changeset": 87302877,
        "name": "Cachoeira de Concórdia",
        "waterway": "waterfall",
        "id": "node/7463601406"
      },
      "geometry": {
        "type": "Point",
        "coordinates": [
          -40.9865471,
          -20.7728028
        ]
      }
    }
  ]
}
