{
  "type": "FeatureCollection",
  "features": [
    {
      "type": "Feature",
      "id": "node/11012701349",
      "properties": {
        "timestamp": "2023-06-28T16:54:06Z",
        "version": 1,
        "changeset": 137887355,
        "amenity": "clinic",
        "healthcare": "clinic",
        "name": "Posto de Saúde Municipal",
        "id": "node/11012701349"
      },
      "geometry": {
        "type": "Point",
        "coordinates": [
          -50.3998534,
          -29.7618081
        ]
      }
    }
  ]
}
