{
  "type": "FeatureCollection",
  "features": [
    {
      "type": "Feature",
      "id": "node/6162528391",
      "properties": {
        "timestamp": "2018-12-26T03:26:57Z",
        "version": 3,
        "changeset": 65773054,
        "addr:city": "Caraá",
        "addr:housenumber": "190",
        "addr:postcode": "95515-000",
        "addr:street": "Avenida Arno Von Saltiel",
        "addr:suburb": "Centro",
        "name": "Câmara de Vereadores",
        "office": "government",
        "website": "http://www.cmcaraa.rs.gov.br/",
        "id": "node/6162528391"
      },
      "geometry": {
        "type": "Point",
        "coordinates": [
          -50.4281449,
          -29.7877414
        ]
      }
    }
  ]
}
