{
  "type": "FeatureCollection",
  "features": [
    {
      "type": "Feature",
      "id": "node/4997316722",
      "properties": {
        "timestamp": "2017-07-27T14:17:29Z",
        "version": 1,
        "changeset": 50621624,
        "amenity": "school",
        "name": "Colégio Estadual Prof. Joaquim Adrega de Moura",
        "name:pt": "Colégio Estadual Prof. Joaquim Adrega de Moura",
        "id": "node/4997316722"
      },
      "geometry": {
        "type": "Point",
        "coordinates": [
          -49.7555528,
          -23.2020149
        ]
      }
    },
    {
      "type": "Feature",
      "id": "node/4997345122",
      "properties": {
        "timestamp": "2017-07-27T14:17:30Z",
        "version": 1,
        "changeset": 50621624,
        "amenity": "school",
        "name": "Escola Estadual Dr João da Rocha Chueiri",
        "name:pt": "Escola Estadual Dr João da Rocha Chueiri",
        "id": "node/4997345122"
      },
      "geometry": {
        "type": "Point",
        "coordinates": [
          -49.7535847,
          -23.2000328
        ]
      }
    },
    {
      "type": "Feature",
      "id": "node/4997351522",
      "properties": {
        "timestamp": "2017-07-27T14:17:32Z",
        "version": 1,
        "changeset": 50621624,
        "amenity": "school",
        "name": "Escola Municipal Correia de Freitas",
        "name:pt": "Escola Municipal Correia de Freitas",
        "id": "node/4997351522"
      },
      "geometry": {
        "type": "Point",
        "coordinates": [
          -49.7546789,
          -23.1993177
        ]
      }
    }
  ]
}
