{
  "type": "FeatureCollection",
  "features": [
    {
      "type": "Feature",
      "id": "node/5250517938",
      "properties": {
        "timestamp": "2017-11-27T15:32:31Z",
        "version": 1,
        "changeset": 54124797,
        "name": "Cascata Véu de Noiva",
        "tourism": "attraction",
        "waterway": "waterfall",
        "id": "node/5250517938"
      },
      "geometry": {
        "type": "Point",
        "coordinates": [
          -49.7534163,
          -23.1117084
        ]
      }
    }
  ]
}
