{
  "type": "FeatureCollection",
  "features": [
    {
      "type": "Feature",
      "id": "node/3688714433",
      "properties": {
        "timestamp": "2018-12-01T18:20:02Z",
        "version": 2,
        "changeset": 65079036,
        "name": "Cachoeira de Macambira",
        "waterway": "waterfall",
        "id": "node/3688714433"
      },
      "geometry": {
        "type": "Point",
        "coordinates": [
          -37.5896023,
          -10.6858457
        ]
      }
    }
  ]
}
