{
  "type": "FeatureCollection",
  "features": [
    {
      "type": "Feature",
      "id": "node/10121444017",
      "properties": {
        "timestamp": "2022-10-22T16:39:27Z",
        "version": 1,
        "changeset": 127930164,
        "addr:street": "Rua Tertuliano de Souza",
        "amenity": "hospital",
        "name": "USF Bonfim de Ipirá",
        "opening_hours": "Su-Th 08:00-16:00",
        "id": "node/10121444017"
      },
      "geometry": {
        "type": "Point",
        "coordinates": [
          -39.7477529,
          -11.9319123
        ]
      }
    }
  ]
}
