{
  "type": "FeatureCollection",
  "features": [
    {
      "type": "Feature",
      "id": "node/3813793873",
      "properties": {
        "timestamp": "2017-03-04T21:07:06Z",
        "version": 2,
        "changeset": 46582326,
        "amenity": "school",
        "name": "Escola Municipal Jonival Lucas",
        "id": "node/3813793873"
      },
      "geometry": {
        "type": "Point",
        "coordinates": [
          -39.4607878,
          -13.0471064
        ]
      }
    }
  ]
}
