{
  "type": "FeatureCollection",
  "features": [
    {
      "type": "Feature",
      "id": "node/6835827757",
      "properties": {
        "timestamp": "2022-08-19T16:18:23Z",
        "version": 4,
        "changeset": 125115960,
        "historic": "memorial",
        "memorial": "statue",
        "name": "Cônego Amílcar Gabriel",
        "id": "node/6835827757"
      },
      "geometry": {
        "type": "Point",
        "coordinates": [
          -49.4980134,
          -28.6371993
        ]
      }
    },
    {
      "type": "Feature",
      "id": "node/8814786774",
      "properties": {
        "timestamp": "2022-08-19T16:18:23Z",
        "version": 2,
        "changeset": 125115960,
        "historic": "memorial",
        "memorial": "statue",
        "name": "Monumento ao Imigrante",
        "id": "node/8814786774"
      },
      "geometry": {
        "type": "Point",
        "coordinates": [
          -49.4967398,
          -28.6423959
        ]
      }
    }
  ]
}
