{
  "type": "FeatureCollection",
  "features": [
    {
      "type": "Feature",
      "id": "node/10050939836",
      "properties": {
        "timestamp": "2022-09-25T13:05:04Z",
        "version": 1,
        "changeset": 126614758,
        "addr:street": "Alameda Ieda Rosa",
        "contact:phone": "+55 79 3281 1645",
        "email": "1pjlaranjeiras@mpse.mp.br",
        "government": "public_service",
        "name": "1ª Promotoria de Justiça de Laranjeiras",
        "office": "government",
        "phone": "+55 79 3281 5900",
        "source": "https://www.tjse.jus.br/portaldamulher/ministerio-publico/item/701-laranjeiras",
        "id": "node/10050939836"
      },
      "geometry": {
        "type": "Point",
        "coordinates": [
          -37.1656129,
          -10.7977783
        ]
      }
    }
  ]
}
