{
  "type": "FeatureCollection",
  "features": [
    {
      "type": "Feature",
      "id": "node/3908512388",
      "properties": {
        "timestamp": "2023-07-09T21:08:08Z",
        "version": 2,
        "changeset": 138311857,
        "addr:city": "Bonito",
        "addr:street": "Rua Tancredo Neves",
        "addr:suburb": "Centro",
        "amenity": "hospital",
        "emergency": "yes",
        "healthcare": "hospital",
        "name": "Maternidade Deputado José Carlos Araujo",
        "operator": "Secretaria de Saúde",
        "operator:type": "public",
        "id": "node/3908512388"
      },
      "geometry": {
        "type": "Point",
        "coordinates": [
          -41.2632823,
          -11.9697306
        ]
      }
    }
  ]
}
