{
  "type": "FeatureCollection",
  "features": [
    {
      "type": "Feature",
      "id": "node/10793271051",
      "properties": {
        "timestamp": "2023-04-07T16:43:24Z",
        "version": 1,
        "changeset": 134624794,
        "name": "Cachoeira da Soltinha",
        "waterway": "waterfall",
        "id": "node/10793271051"
      },
      "geometry": {
        "type": "Point",
        "coordinates": [
          -41.2230199,
          -12.0204593
        ]
      }
    }
  ]
}
