{
  "type": "FeatureCollection",
  "features": [
    {
      "type": "Feature",
      "id": "node/10212572864",
      "properties": {
        "timestamp": "2022-11-23T18:09:53Z",
        "version": 1,
        "changeset": 129292671,
        "amenity": "doctors",
        "healthcare": "doctor",
        "name": "Consultório espiritual ( Dona Neném )",
        "id": "node/10212572864"
      },
      "geometry": {
        "type": "Point",
        "coordinates": [
          -41.5297635,
          -8.0828166
        ]
      }
    }
  ]
}
