{
  "type": "FeatureCollection",
  "features": [
    {
      "type": "Feature",
      "id": "node/8626367657",
      "properties": {
        "timestamp": "2023-04-02T23:45:18Z",
        "version": 4,
        "changeset": 134432682,
        "alt_name": "SA005",
        "amenity": "clinic",
        "healthcare": "clinic",
        "name": "Posto de Saúde Serra Alta",
        "id": "node/8626367657"
      },
      "geometry": {
        "type": "Point",
        "coordinates": [
          -53.0447499,
          -26.7287029
        ]
      }
    }
  ]
}
