{
  "type": "FeatureCollection",
  "features": [
    {
      "type": "Feature",
      "id": "node/9672306032",
      "properties": {
        "timestamp": "2022-04-17T19:26:08Z",
        "version": 2,
        "changeset": 119829200,
        "name": "Pousadsa Magia da Sereia",
        "tourism": "hotel",
        "id": "node/9672306032"
      },
      "geometry": {
        "type": "Point",
        "coordinates": [
          -49.5729392,
          -29.1547275
        ]
      }
    },
    {
      "type": "Feature",
      "id": "node/9672713345",
      "properties": {
        "timestamp": "2022-04-17T22:47:56Z",
        "version": 2,
        "changeset": 119833301,
        "name": "Pousada Caxias",
        "tourism": "hotel",
        "id": "node/9672713345"
      },
      "geometry": {
        "type": "Point",
        "coordinates": [
          -49.5778498,
          -29.1575782
        ]
      }
    },
    {
      "type": "Feature",
      "id": "node/9696448442",
      "properties": {
        "timestamp": "2022-04-27T02:09:26Z",
        "version": 1,
        "changeset": 120235882,
        "name": "Pousada Rock Point",
        "tourism": "hotel",
        "id": "node/9696448442"
      },
      "geometry": {
        "type": "Point",
        "coordinates": [
          -49.5831721,
          -29.1515195
        ]
      }
    }
  ]
}
