{
  "type": "FeatureCollection",
  "features": [
    {
      "type": "Feature",
      "id": "node/3678380312",
      "properties": {
        "timestamp": "2018-06-19T22:42:16Z",
        "version": 2,
        "changeset": 59992644,
        "government": "legislative",
        "name": "Câmara Municipal",
        "office": "government",
        "source": "IBGE mapa de setores urbanos",
        "id": "node/3678380312"
      },
      "geometry": {
        "type": "Point",
        "coordinates": [
          -42.4845802,
          -13.5501558
        ]
      }
    },
    {
      "type": "Feature",
      "id": "node/3678380314",
      "properties": {
        "timestamp": "2015-08-03T05:29:40Z",
        "version": 1,
        "changeset": 33060534,
        "addr:city": "Tanque novo",
        "name": "Secretaria de Educação",
        "office": "government",
        "source": "IBGE mapa de setores urbanos",
        "id": "node/3678380314"
      },
      "geometry": {
        "type": "Point",
        "coordinates": [
          -42.486744,
          -13.548507
        ]
      }
    },
    {
      "type": "Feature",
      "id": "node/3678380318",
      "properties": {
        "timestamp": "2015-08-03T05:29:41Z",
        "version": 1,
        "changeset": 33060534,
        "addr:city": "Tanque Novo",
        "addr:street": "Avenida Antônio Carlos Magalhães",
        "name": "Secretaria Municipal de Saúde",
        "office": "government",
        "source": "IBGE mapa de setores urbanos",
        "id": "node/3678380318"
      },
      "geometry": {
        "type": "Point",
        "coordinates": [
          -42.4917711,
          -13.5484774
        ]
      }
    },
    {
      "type": "Feature",
      "id": "node/3678380319",
      "properties": {
        "timestamp": "2021-04-24T14:43:22Z",
        "version": 2,
        "changeset": 103539914,
        "addr:city": "Tanque Novo",
        "addr:street": "Rua dos Viana",
        "name": "Conselho Tutelar",
        "office": "government",
        "source": "IBGE mapa de setores urbanos",
        "id": "node/3678380319"
      },
      "geometry": {
        "type": "Point",
        "coordinates": [
          -42.4916304,
          -13.5482217
        ]
      }
    }
  ]
}
