{
  "type": "FeatureCollection",
  "features": [
    {
      "type": "Feature",
      "id": "node/3675837869",
      "properties": {
        "timestamp": "2015-08-01T05:00:56Z",
        "version": 1,
        "changeset": 33023838,
        "name": "Restaurante e Pousada Boi na Brasa",
        "tourism": "hotel",
        "id": "node/3675837869"
      },
      "geometry": {
        "type": "Point",
        "coordinates": [
          -42.4876611,
          -13.5525073
        ]
      }
    }
  ]
}
