{
  "type": "FeatureCollection",
  "features": [
    {
      "type": "Feature",
      "id": "node/5198177323",
      "properties": {
        "timestamp": "2017-10-29T13:53:49Z",
        "version": 1,
        "changeset": 53342624,
        "name": "Pousada São Francisco",
        "tourism": "guest_house",
        "id": "node/5198177323"
      },
      "geometry": {
        "type": "Point",
        "coordinates": [
          -36.7128183,
          -6.9945733
        ]
      }
    }
  ]
}
