{
  "type": "FeatureCollection",
  "features": [
    {
      "type": "Feature",
      "id": "node/3219255289",
      "properties": {
        "timestamp": "2014-12-04T19:16:13Z",
        "version": 1,
        "changeset": 27243552,
        "amenity": "clinic",
        "name": "PSF",
        "id": "node/3219255289"
      },
      "geometry": {
        "type": "Point",
        "coordinates": [
          -36.1048854,
          -9.7898874
        ]
      }
    }
  ]
}
