{
  "type": "FeatureCollection",
  "features": [
    {
      "type": "Feature",
      "id": "node/8290532617",
      "properties": {
        "timestamp": "2021-01-05T11:43:50Z",
        "version": 2,
        "changeset": 96976451,
        "historic": "monument",
        "name": "Samaúma Gingante",
        "name:en": "Giant Samauma Tree",
        "id": "node/8290532617"
      },
      "geometry": {
        "type": "Point",
        "coordinates": [
          -55.0133928,
          -2.8262878
        ]
      }
    }
  ]
}
