{
  "type": "FeatureCollection",
  "features": [
    {
      "type": "Feature",
      "id": "node/5607639522",
      "properties": {
        "timestamp": "2021-02-20T21:15:55Z",
        "version": 2,
        "changeset": 99660429,
        "amenity": "pharmacy",
        "healthcare": "pharmacy",
        "name": "Santa Luzia",
        "id": "node/5607639522"
      },
      "geometry": {
        "type": "Point",
        "coordinates": [
          -38.0705389,
          -7.4275723
        ]
      }
    }
  ]
}
