{
  "type": "FeatureCollection",
  "features": [
    {
      "type": "Feature",
      "id": "node/8636263043",
      "properties": {
        "timestamp": "2021-04-16T18:22:30Z",
        "version": 1,
        "changeset": 103075689,
        "amenity": "library",
        "name": "Biblioteca Pública Municipal de Caibi",
        "id": "node/8636263043"
      },
      "geometry": {
        "type": "Point",
        "coordinates": [
          -53.249953,
          -27.076525
        ]
      }
    }
  ]
}
