{
  "type": "FeatureCollection",
  "features": [
    {
      "type": "Feature",
      "id": "node/3163953624",
      "properties": {
        "timestamp": "2016-09-12T01:57:04Z",
        "version": 2,
        "changeset": 42090312,
        "addr:city": "Caibi",
        "addr:postcode": "89888-000",
        "addr:street": "Rua Independência",
        "addr:suburb": "Centro",
        "amenity": "school",
        "name": "Escola Dom Pedro II",
        "id": "node/3163953624"
      },
      "geometry": {
        "type": "Point",
        "coordinates": [
          -53.2458633,
          -27.0736567
        ]
      }
    },
    {
      "type": "Feature",
      "id": "node/3163970446",
      "properties": {
        "timestamp": "2017-04-09T13:00:20Z",
        "version": 3,
        "changeset": 47592512,
        "addr:postcode": "89888-000",
        "addr:suburb": "Natal",
        "amenity": "school",
        "name": "Escola Reunida Municipal Pedro Ivo Campos",
        "id": "node/3163970446"
      },
      "geometry": {
        "type": "Point",
        "coordinates": [
          -53.25523,
          -27.0739472
        ]
      }
    },
    {
      "type": "Feature",
      "id": "node/3164454879",
      "properties": {
        "timestamp": "2016-09-12T01:57:04Z",
        "version": 3,
        "changeset": 42090312,
        "addr:city": "Caibi",
        "addr:postcode": "89888-000",
        "addr:suburb": "Linha Planaltina",
        "alt_name": "Escola de Educação Básica Humberto de Alencar Castelo Branco",
        "amenity": "school",
        "name": "Escola Humberto de Alencar Castelo Branco",
        "short_name": "EEB Humberto de Alencar Castelo Branco",
        "id": "node/3164454879"
      },
      "geometry": {
        "type": "Point",
        "coordinates": [
          -53.2121194,
          -26.9642566
        ]
      }
    }
  ]
}
