{
  "type": "FeatureCollection",
  "features": [
    {
      "type": "Feature",
      "id": "node/369876451",
      "properties": {
        "timestamp": "2022-01-17T16:26:11Z",
        "version": 3,
        "changeset": 116261809,
        "amenity": "pharmacy",
        "dispensing": "no",
        "healthcare": "pharmacy",
        "id": "node/369876451"
      },
      "geometry": {
        "type": "Point",
        "coordinates": [
          -43.4155267,
          -20.3769515
        ]
      }
    },
    {
      "type": "Feature",
      "id": "node/2069874640",
      "properties": {
        "timestamp": "2022-01-18T14:32:35Z",
        "version": 2,
        "changeset": 116301798,
        "amenity": "pharmacy",
        "healthcare": "pharmacy",
        "name": "Drogaria Passagem de Mariana",
        "id": "node/2069874640"
      },
      "geometry": {
        "type": "Point",
        "coordinates": [
          -43.4444406,
          -20.3943405
        ]
      }
    },
    {
      "type": "Feature",
      "id": "node/4221189588",
      "properties": {
        "timestamp": "2018-07-17T09:14:49Z",
        "version": 2,
        "changeset": 60791175,
        "amenity": "pharmacy",
        "id": "node/4221189588"
      },
      "geometry": {
        "type": "Point",
        "coordinates": [
          -43.4217273,
          -20.3809294
        ]
      }
    },
    {
      "type": "Feature",
      "id": "node/4221189689",
      "properties": {
        "timestamp": "2016-06-02T08:49:01Z",
        "version": 1,
        "changeset": 39728701,
        "amenity": "pharmacy",
        "id": "node/4221189689"
      },
      "geometry": {
        "type": "Point",
        "coordinates": [
          -43.4173674,
          -20.3769642
        ]
      }
    },
    {
      "type": "Feature",
      "id": "node/4221189690",
      "properties": {
        "timestamp": "2016-06-02T08:49:01Z",
        "version": 1,
        "changeset": 39728701,
        "amenity": "pharmacy",
        "id": "node/4221189690"
      },
      "geometry": {
        "type": "Point",
        "coordinates": [
          -43.416479,
          -20.3774187
        ]
      }
    }
  ]
}
