{
  "type": "FeatureCollection",
  "features": [
    {
      "type": "Feature",
      "id": "node/9149792082",
      "properties": {
        "timestamp": "2021-10-05T18:48:31Z",
        "version": 1,
        "changeset": 112136594,
        "amenity": "community_centre",
        "name": "Centro Comunitário de Vereda Funda",
        "id": "node/9149792082"
      },
      "geometry": {
        "type": "Point",
        "coordinates": [
          -42.4835156,
          -15.9265146
        ]
      }
    }
  ]
}
