{
  "type": "FeatureCollection",
  "features": [
    {
      "type": "Feature",
      "id": "node/12323748484",
      "properties": {
        "timestamp": "2024-11-08T14:18:01Z",
        "version": 2,
        "changeset": 158897791,
        "IBGE:COD_UNICO_ENDERECO": "223870637",
        "addr:city": "Rio Pardo de Minas",
        "addr:housenumber": "163",
        "addr:postcode": "39530-000",
        "addr:street": "Praça Benedito Valadares",
        "addr:suburb": "Centro",
        "amenity": "social_facility",
        "brand:wikidata": "Q16494876",
        "brand:wikipedia": "pt:Associação_de_Pais_e_Amigos_dos_Excepcionais",
        "name": "Associação de Pais e Amigos dos Excepcionais",
        "official_name": "Associação de Pais e Amigos dos Excepcionais",
        "operator": "Associação de Pais e Amigos dos Excepcionais",
        "operator:type": "community",
        "operator:wikidata": "Q16494876",
        "short_name": "APAE",
        "id": "node/12323748484"
      },
      "geometry": {
        "type": "Point",
        "coordinates": [
          -42.5382498,
          -15.6113092
        ]
      }
    }
  ]
}
