{
  "type": "FeatureCollection",
  "features": [
    {
      "type": "Feature",
      "id": "node/4673702303",
      "properties": {
        "timestamp": "2017-02-07T23:53:58Z",
        "version": 1,
        "changeset": 45901467,
        "amenity": "social_facility",
        "social_facility": "group_home",
        "social_facility:for": "senior",
        "id": "node/4673702303"
      },
      "geometry": {
        "type": "Point",
        "coordinates": [
          -48.5184765,
          -16.7491732
        ]
      }
    }
  ]
}
