{
  "type": "FeatureCollection",
  "features": [
    {
      "type": "Feature",
      "id": "node/7988403963",
      "properties": {
        "timestamp": "2020-10-08T13:51:22Z",
        "version": 1,
        "changeset": 92179729,
        "amenity": "arts_centre",
        "name": "CTG Amigos da Tradição",
        "id": "node/7988403963"
      },
      "geometry": {
        "type": "Point",
        "coordinates": [
          -50.9781685,
          -29.5032924
        ]
      }
    }
  ]
}
