{
  "type": "FeatureCollection",
  "features": [
    {
      "type": "Feature",
      "id": "node/3740534535",
      "properties": {
        "timestamp": "2019-08-05T13:04:23Z",
        "version": 2,
        "changeset": 73023101,
        "addr:city": "Paranaiguara",
        "addr:housenumber": "27",
        "addr:postcode": "75880-000",
        "addr:street": "Avenida Prefeito Elias Miguel Salomão",
        "addr:suburb": "Centro",
        "amenity": "school",
        "name": "Escola Estadual Belmiro Soares",
        "website": "https://www.escol.as/264144-colegio-estadual-belmiro-soares",
        "id": "node/3740534535"
      },
      "geometry": {
        "type": "Point",
        "coordinates": [
          -50.6579712,
          -18.9113328
        ]
      }
    },
    {
      "type": "Feature",
      "id": "node/6689962002",
      "properties": {
        "timestamp": "2019-08-07T01:41:19Z",
        "version": 1,
        "changeset": 73088881,
        "addr:city": "Paranaiguara",
        "addr:postcode": "75880-000",
        "addr:street": "Rua Sete A",
        "addr:suburb": "Centro",
        "amenity": "school",
        "denomination": "none",
        "email": "escola.emob@hotmail.com",
        "internet_access": "yes",
        "name": "Escola Municipal Oscar Bernardes",
        "phone": "+55 64 36550126",
        "religion": "none",
        "website": "https://www.melhorescola.com.br/escola/publica/educandario-municipal-oscar-bernardes",
        "id": "node/6689962002"
      },
      "geometry": {
        "type": "Point",
        "coordinates": [
          -50.6522688,
          -18.9135451
        ]
      }
    }
  ]
}
