{
  "type": "FeatureCollection",
  "features": [
    {
      "type": "Feature",
      "id": "node/10221379815",
      "properties": {
        "timestamp": "2022-11-27T13:23:41Z",
        "version": 1,
        "changeset": 129434683,
        "addr:city": "Caparaó",
        "addr:housenumber": "320",
        "addr:postcode": "36834-000",
        "addr:street": "Rua Agenor Pinheiro",
        "addr:suburb": "Centro",
        "guest_house": "guest_house",
        "name": "Pousada da Conquista",
        "operator": "Claudio da Silva Reis",
        "tourism": "guest_house",
        "id": "node/10221379815"
      },
      "geometry": {
        "type": "Point",
        "coordinates": [
          -41.9067813,
          -20.5215741
        ]
      }
    }
  ]
}
