{
  "type": "FeatureCollection",
  "features": [
    {
      "type": "Feature",
      "id": "node/5236587021",
      "properties": {
        "timestamp": "2023-07-19T02:24:15Z",
        "version": 2,
        "changeset": 138693402,
        "name": "Hotel e Restaurante Rio Fortuna",
        "tourism": "hotel",
        "id": "node/5236587021"
      },
      "geometry": {
        "type": "Point",
        "coordinates": [
          -49.1155484,
          -28.1412031
        ]
      }
    }
  ]
}
