{
  "type": "FeatureCollection",
  "features": [
    {
      "type": "Feature",
      "id": "node/1836080707",
      "properties": {
        "timestamp": "2012-07-24T02:11:20Z",
        "version": 1,
        "changeset": 12459052,
        "name": "Grande Hotel",
        "tourism": "hotel",
        "id": "node/1836080707"
      },
      "geometry": {
        "type": "Point",
        "coordinates": [
          -48.499841,
          -21.4091162
        ]
      }
    },
    {
      "type": "Feature",
      "id": "node/1836080708",
      "properties": {
        "timestamp": "2012-07-24T02:11:20Z",
        "version": 1,
        "changeset": 12459052,
        "name": "Hotel Central",
        "tourism": "hotel",
        "id": "node/1836080708"
      },
      "geometry": {
        "type": "Point",
        "coordinates": [
          -48.4999912,
          -21.408407
        ]
      }
    },
    {
      "type": "Feature",
      "id": "node/1836080728",
      "properties": {
        "timestamp": "2014-09-17T19:20:03Z",
        "version": 2,
        "changeset": 25505625,
        "name": "Avenida Park Hotel",
        "tourism": "hotel",
        "id": "node/1836080728"
      },
      "geometry": {
        "type": "Point",
        "coordinates": [
          -48.5016703,
          -21.4127121
        ]
      }
    }
  ]
}
