{
  "type": "FeatureCollection",
  "features": [
    {
      "type": "Feature",
      "id": "node/3045515420",
      "properties": {
        "timestamp": "2021-06-15T05:43:14Z",
        "version": 4,
        "changeset": 106371617,
        "historic": "monument",
        "name": "Portal de São Luiz do Purunã",
        "id": "node/3045515420"
      },
      "geometry": {
        "type": "Point",
        "coordinates": [
          -49.7041108,
          -25.4735776
        ]
      }
    }
  ]
}
