{
  "type": "FeatureCollection",
  "features": [
    {
      "type": "Feature",
      "id": "node/2705368883",
      "properties": {
        "timestamp": "2023-07-07T19:05:41Z",
        "version": 2,
        "changeset": 138241126,
        "addr:city": "Uruaçu",
        "addr:housenumber": "14",
        "addr:postcode": "76400-000",
        "addr:street": "Avenida Tocantins",
        "name": "Acepeças",
        "phone": "+55 62 3357-1102",
        "shop": "bicycle",
        "id": "node/2705368883"
      },
      "geometry": {
        "type": "Point",
        "coordinates": [
          -49.1491677,
          -14.5245856
        ]
      }
    }
  ]
}
