{
  "type": "FeatureCollection",
  "features": [
    {
      "type": "Feature",
      "id": "node/9283967069",
      "properties": {
        "timestamp": "2021-11-25T20:09:12Z",
        "version": 1,
        "changeset": 114236910,
        "amenity": "pharmacy",
        "name": "Jai Farma",
        "id": "node/9283967069"
      },
      "geometry": {
        "type": "Point",
        "coordinates": [
          -41.1394386,
          -7.3588901
        ]
      }
    },
    {
      "type": "Feature",
      "id": "node/9283975480",
      "properties": {
        "timestamp": "2021-11-25T19:59:28Z",
        "version": 1,
        "changeset": 114236669,
        "amenity": "pharmacy",
        "name": "Fharma Vida",
        "id": "node/9283975480"
      },
      "geometry": {
        "type": "Point",
        "coordinates": [
          -41.1386795,
          -7.35919
        ]
      }
    },
    {
      "type": "Feature",
      "id": "node/9283975481",
      "properties": {
        "timestamp": "2021-11-25T20:02:00Z",
        "version": 1,
        "changeset": 114236734,
        "amenity": "pharmacy",
        "name": "Farmácia São Bento",
        "id": "node/9283975481"
      },
      "geometry": {
        "type": "Point",
        "coordinates": [
          -41.139019,
          -7.3589802
        ]
      }
    },
    {
      "type": "Feature",
      "id": "node/9283986249",
      "properties": {
        "timestamp": "2021-11-25T20:03:00Z",
        "version": 1,
        "changeset": 114236759,
        "amenity": "pharmacy",
        "name": "Drogaria Macêdo",
        "id": "node/9283986249"
      },
      "geometry": {
        "type": "Point",
        "coordinates": [
          -41.1390305,
          -7.3593102
        ]
      }
    }
  ]
}
