{
  "type": "FeatureCollection",
  "features": [
    {
      "type": "Feature",
      "id": "node/11341460169",
      "properties": {
        "timestamp": "2023-11-11T15:26:37Z",
        "version": 2,
        "changeset": 143904334,
        "amenity": "community_centre",
        "name": "Aldeia Indígena Xerente Salto",
        "id": "node/11341460169"
      },
      "geometry": {
        "type": "Point",
        "coordinates": [
          -48.3512725,
          -9.4854661
        ]
      }
    }
  ]
}
