{
  "type": "FeatureCollection",
  "features": [
    {
      "type": "Feature",
      "id": "node/11341460169",
      "properties": {
        "timestamp": "2023-11-11T15:26:37Z",
        "version": 2,
        "changeset": 143904334,
        "amenity": "community_centre",
        "name": "Aldeia Indígena Xerente Salto",
        "id": "node/11341460169"
      },
      "geometry": {
        "type": "Point",
        "coordinates": [
          -48.3512725,
          -9.4854661
        ]
      }
    },
    {
      "type": "Feature",
      "id": "node/11422480070",
      "properties": {
        "timestamp": "2023-12-16T10:04:48Z",
        "version": 1,
        "changeset": 145178378,
        "amenity": "community_centre",
        "name": "Cizinha",
        "id": "node/11422480070"
      },
      "geometry": {
        "type": "Point",
        "coordinates": [
          -48.3515056,
          -9.4839566
        ]
      }
    }
  ]
}
