{
  "type": "FeatureCollection",
  "features": [
    {
      "type": "Feature",
      "id": "node/9776053804",
      "properties": {
        "timestamp": "2022-05-27T22:52:37Z",
        "version": 1,
        "changeset": 121595869,
        "amenity": "kindergarten",
        "name": "EMEI Jovino Zambonato",
        "id": "node/9776053804"
      },
      "geometry": {
        "type": "Point",
        "coordinates": [
          -54.84962,
          -29.1710389
        ]
      }
    }
  ]
}
