{
  "type": "FeatureCollection",
  "features": [
    {
      "type": "Feature",
      "id": "node/297841970",
      "properties": {
        "timestamp": "2020-04-13T14:05:52Z",
        "version": 4,
        "changeset": 83481644,
        "name": "Cachoeira da Fumaça",
        "waterway": "waterfall",
        "id": "node/297841970"
      },
      "geometry": {
        "type": "Point",
        "coordinates": [
          -41.7255815,
          -21.0666828
        ]
      }
    }
  ]
}
