{
  "type": "FeatureCollection",
  "features": [
    {
      "type": "Feature",
      "id": "node/5891925901",
      "properties": {
        "timestamp": "2018-09-08T02:01:07Z",
        "version": 1,
        "changeset": 62391947,
        "name": "Emater",
        "office": "government",
        "source": "IBGE",
        "id": "node/5891925901"
      },
      "geometry": {
        "type": "Point",
        "coordinates": [
          -51.408315,
          -28.9911371
        ]
      }
    }
  ]
}
