{
  "type": "FeatureCollection",
  "features": [
    {
      "type": "Feature",
      "id": "node/4136648892",
      "properties": {
        "timestamp": "2021-10-23T20:45:25Z",
        "version": 2,
        "changeset": 112887290,
        "access": "yes",
        "addr:place": "Praça Rio Branco",
        "amenity": "toilets",
        "female": "yes",
        "male": "yes",
        "id": "node/4136648892"
      },
      "geometry": {
        "type": "Point",
        "coordinates": [
          -48.6416441,
          -20.9074012
        ]
      }
    }
  ]
}
