{
  "type": "FeatureCollection",
  "features": [
    {
      "type": "Feature",
      "id": "node/9895128917",
      "properties": {
        "timestamp": "2022-07-18T12:00:54Z",
        "version": 1,
        "changeset": 123761044,
        "name": "Comunidade Tauari",
        "opening_hours": "24/7",
        "tourism": "guest_house",
        "id": "node/9895128917"
      },
      "geometry": {
        "type": "Point",
        "coordinates": [
          -65.4424625,
          -0.7660266
        ]
      }
    }
  ]
}
