{
  "type": "FeatureCollection",
  "features": [
    {
      "type": "Feature",
      "id": "node/4116070589",
      "properties": {
        "timestamp": "2017-11-18T21:42:53Z",
        "version": 5,
        "changeset": 53911923,
        "addr:postcode": "69740-000",
        "addr:street": "Rua Duque de Caxias",
        "internet_access": "wlan",
        "name": "Hotel Ayuana",
        "opening_hours": "24/7",
        "tourism": "hotel",
        "id": "node/4116070589"
      },
      "geometry": {
        "type": "Point",
        "coordinates": [
          -65.0194728,
          -0.4161117
        ]
      }
    },
    {
      "type": "Feature",
      "id": "node/4131962589",
      "properties": {
        "timestamp": "2021-08-18T00:10:45Z",
        "version": 2,
        "changeset": 109838770,
        "internet_access": "wlan",
        "name": "Hotel Maikon",
        "phone": "+55 97 3441 1045",
        "tourism": "hotel",
        "id": "node/4131962589"
      },
      "geometry": {
        "type": "Point",
        "coordinates": [
          -65.0200545,
          -0.4144089
        ]
      }
    },
    {
      "type": "Feature",
      "id": "node/4137513990",
      "properties": {
        "timestamp": "2017-09-04T00:37:34Z",
        "version": 3,
        "changeset": 51704994,
        "internet_access": "wlan",
        "name": "Hotel Britânico",
        "opening_hours": "24/7",
        "tourism": "hotel",
        "id": "node/4137513990"
      },
      "geometry": {
        "type": "Point",
        "coordinates": [
          -65.0209607,
          -0.4156891
        ]
      }
    }
  ]
}
