{
  "type": "FeatureCollection",
  "features": [
    {
      "type": "Feature",
      "id": "node/5239403121",
      "properties": {
        "timestamp": "2017-11-20T12:49:35Z",
        "version": 1,
        "changeset": 53948525,
        "amenity": "library",
        "name": "Biblioteca do PERP",
        "name:en": "PERP library",
        "id": "node/5239403121"
      },
      "geometry": {
        "type": "Point",
        "coordinates": [
          -43.3452056,
          -18.1180395
        ]
      }
    }
  ]
}
