{
  "type": "FeatureCollection",
  "features": [
    {
      "type": "Feature",
      "id": "node/12729341804",
      "properties": {
        "timestamp": "2025-04-04T16:26:21Z",
        "version": 1,
        "changeset": 164518583,
        "addr:city": "Águas de Lindóia",
        "addr:housenumber": "1230",
        "addr:street": "Avenida das Nações Unidas",
        "addr:suburb": "Centro",
        "amenity": "social_facility",
        "name": "Centro de Convivência do Idoso \"Ignês Brolezi David\"",
        "social_facility": "social_club",
        "id": "node/12729341804"
      },
      "geometry": {
        "type": "Point",
        "coordinates": [
          -46.6361891,
          -22.4798563
        ]
      }
    }
  ]
}
