{
  "type": "FeatureCollection",
  "features": [
    {
      "type": "Feature",
      "id": "node/9118092713",
      "properties": {
        "timestamp": "2021-09-23T18:42:41Z",
        "version": 1,
        "changeset": 111613399,
        "name": "Secretária Municipal de Saude",
        "office": "government",
        "id": "node/9118092713"
      },
      "geometry": {
        "type": "Point",
        "coordinates": [
          -44.6451642,
          -5.2599795
        ]
      }
    }
  ]
}
