{
  "type": "FeatureCollection",
  "features": [
    {
      "type": "Feature",
      "id": "node/7391412436",
      "properties": {
        "timestamp": "2023-03-30T02:37:58Z",
        "version": 2,
        "changeset": 134284606,
        "amenity": "clinic",
        "healthcare": "clinic",
        "name": "Posto de Saúde Panorama",
        "opening_hours": "Mo-Fr 07:30-17:00",
        "id": "node/7391412436"
      },
      "geometry": {
        "type": "Point",
        "coordinates": [
          -54.2510535,
          -25.3551826
        ]
      }
    }
  ]
}
