{
  "type": "FeatureCollection",
  "features": [
    {
      "type": "Feature",
      "id": "node/8626387720",
      "properties": {
        "timestamp": "2021-04-13T15:56:52Z",
        "version": 1,
        "changeset": 102875428,
        "amenity": "hospital",
        "name": "Hospital São Roque",
        "id": "node/8626387720"
      },
      "geometry": {
        "type": "Point",
        "coordinates": [
          -51.3393928,
          -26.933622
        ]
      }
    }
  ]
}
