{
  "type": "FeatureCollection",
  "features": [
    {
      "type": "Feature",
      "id": "node/7264746637",
      "properties": {
        "timestamp": "2020-03-04T20:58:07Z",
        "version": 1,
        "changeset": 81792549,
        "amenity": "community_centre",
        "name": "ACM Vila Feliz",
        "id": "node/7264746637"
      },
      "geometry": {
        "type": "Point",
        "coordinates": [
          -51.1598551,
          -29.8064963
        ]
      }
    },
    {
      "type": "Feature",
      "id": "node/10003239269",
      "properties": {
        "timestamp": "2022-09-06T00:36:59Z",
        "version": 1,
        "changeset": 125834873,
        "amenity": "community_centre",
        "id": "node/10003239269"
      },
      "geometry": {
        "type": "Point",
        "coordinates": [
          -51.1647728,
          -29.810429
        ]
      }
    },
    {
      "type": "Feature",
      "id": "node/10003286572",
      "properties": {
        "timestamp": "2022-09-06T01:45:13Z",
        "version": 1,
        "changeset": 125835505,
        "amenity": "community_centre",
        "name": "Associação Amigos da Vila Cohab",
        "id": "node/10003286572"
      },
      "geometry": {
        "type": "Point",
        "coordinates": [
          -51.1593962,
          -29.8135814
        ]
      }
    }
  ]
}
