{
  "type": "FeatureCollection",
  "features": [
    {
      "type": "Feature",
      "id": "node/1126562424",
      "properties": {
        "timestamp": "2011-01-29T18:32:31Z",
        "version": 1,
        "changeset": 7125505,
        "amenity": "veterinary",
        "name": "Clínica Veterinária do Vale",
        "id": "node/1126562424"
      },
      "geometry": {
        "type": "Point",
        "coordinates": [
          -51.1648559,
          -29.7944959
        ]
      }
    }
  ]
}
