{
  "type": "FeatureCollection",
  "features": [
    {
      "type": "Feature",
      "id": "node/11981564777",
      "properties": {
        "timestamp": "2024-06-14T18:55:10Z",
        "version": 1,
        "changeset": 152694327,
        "addr:city": "Vespasiano",
        "addr:postcode": "33200000",
        "addr:street": "Avenida Existente",
        "addr:suburb": "Morro Alto",
        "amenity": "pharmacy",
        "contact:phone": "+55 31 3621-6031",
        "dispensing": "yes",
        "healthcare": "pharmacy",
        "name": "Drogaria Morro Alto - Multi Farma",
        "id": "node/11981564777"
      },
      "geometry": {
        "type": "Point",
        "coordinates": [
          -43.955542,
          -19.7683095
        ]
      }
    },
    {
      "type": "Feature",
      "id": "node/11981564781",
      "properties": {
        "timestamp": "2024-06-14T18:55:10Z",
        "version": 1,
        "changeset": 152694327,
        "addr:city": "Vespasiano",
        "addr:housenumber": "1084",
        "addr:postcode": "33200000",
        "addr:street": "Avenida Existente",
        "addr:suburb": "Morro Alto",
        "amenity": "pharmacy",
        "healthcare": "pharmacy",
        "name": "Drogaria Oliveira",
        "id": "node/11981564781"
      },
      "geometry": {
        "type": "Point",
        "coordinates": [
          -43.9554106,
          -19.7682746
        ]
      }
    }
  ]
}
