{
  "type": "FeatureCollection",
  "features": [
    {
      "type": "Feature",
      "id": "node/4676748153",
      "properties": {
        "timestamp": "2018-09-14T23:05:24Z",
        "version": 2,
        "changeset": 62598048,
        "description": "Programa de Recuperação de Nascentes e Trilhas da Serra da Calçada.",
        "historic": "memorial",
        "inscription": "\"PRAÇA ANDRÉ ABELHA\nPrograma de recuperação de nascentes e trilhas sa Serra da Calçada\"",
        "name": "Praça André Abelha",
        "start_date": "01/09/2018",
        "id": "node/4676748153"
      },
      "geometry": {
        "type": "Point",
        "coordinates": [
          -43.989316,
          -20.1042608
        ]
      }
    }
  ]
}
