{
  "type": "FeatureCollection",
  "features": [
    {
      "type": "Feature",
      "id": "node/8636271317",
      "properties": {
        "timestamp": "2021-04-16T18:17:16Z",
        "version": 1,
        "changeset": 103075689,
        "amenity": "library",
        "name": "Biblioteca Pública Municipal Doutor Nereu Ramos",
        "id": "node/8636271317"
      },
      "geometry": {
        "type": "Point",
        "coordinates": [
          -49.026319,
          -28.619055
        ]
      }
    }
  ]
}
