{
  "type": "FeatureCollection",
  "features": [
    {
      "type": "Feature",
      "id": "node/6444187495",
      "properties": {
        "timestamp": "2019-05-02T23:32:36Z",
        "version": 1,
        "changeset": 69823052,
        "addr:city": "Cacimba de Dentro",
        "addr:postcode": "58230-000",
        "amenity": "dentist",
        "healthcare": "dentist",
        "name": "Dra Vânia Badu Olegário",
        "id": "node/6444187495"
      },
      "geometry": {
        "type": "Point",
        "coordinates": [
          -35.7927026,
          -6.6426343
        ]
      }
    }
  ]
}
