{
  "type": "FeatureCollection",
  "features": [
    {
      "type": "Feature",
      "id": "node/5447263820",
      "properties": {
        "timestamp": "2018-03-02T07:00:30Z",
        "version": 1,
        "changeset": 56809468,
        "historic": "memorial",
        "name": "Estátua de São Jorge",
        "id": "node/5447263820"
      },
      "geometry": {
        "type": "Point",
        "coordinates": [
          -47.1334363,
          -23.5274323
        ]
      }
    }
  ]
}
