{
  "type": "FeatureCollection",
  "features": [
    {
      "type": "Feature",
      "id": "node/7824219407",
      "properties": {
        "timestamp": "2020-08-18T20:02:51Z",
        "version": 1,
        "changeset": 89594216,
        "amenity": "dentist",
        "healthcare": "dentist",
        "name": "Alex Brito",
        "id": "node/7824219407"
      },
      "geometry": {
        "type": "Point",
        "coordinates": [
          -42.7140665,
          -13.7721233
        ]
      }
    }
  ]
}
