{
  "type": "FeatureCollection",
  "features": [
    {
      "type": "Feature",
      "id": "node/10718005476",
      "properties": {
        "timestamp": "2023-03-07T00:35:58Z",
        "version": 1,
        "changeset": 133383991,
        "government": "social_security",
        "name": "INSS",
        "office": "government",
        "operator": "Instituto Nacional do Seguro Social",
        "operator:short": "INSS",
        "operator:wikidata": "Q10302614",
        "id": "node/10718005476"
      },
      "geometry": {
        "type": "Point",
        "coordinates": [
          -40.5945247,
          -11.427838
        ]
      }
    }
  ]
}
