{
  "type": "FeatureCollection",
  "features": [
    {
      "type": "Feature",
      "id": "node/6721834525",
      "properties": {
        "timestamp": "2019-08-18T21:14:11Z",
        "version": 1,
        "changeset": 73473883,
        "amenity": "library",
        "name": "Biblioteca da Indústria do Conhecimento do Sesi",
        "id": "node/6721834525"
      },
      "geometry": {
        "type": "Point",
        "coordinates": [
          -54.3743076,
          -21.4558242
        ]
      }
    }
  ]
}
