{
  "type": "FeatureCollection",
  "features": [
    {
      "type": "Feature",
      "id": "node/7211373791",
      "properties": {
        "timestamp": "2021-06-12T18:16:03Z",
        "version": 2,
        "changeset": 106262031,
        "addr:city": "Arvorezinha",
        "addr:housenumber": "645",
        "addr:postcode": "95995-000",
        "addr:street": "Rua Agromate",
        "addr:suburb": "Centro",
        "government": "legislative",
        "name": "Câmara Municipal de Vereadores de Arvorezinha",
        "office": "government",
        "id": "node/7211373791"
      },
      "geometry": {
        "type": "Point",
        "coordinates": [
          -52.1801231,
          -28.8775281
        ]
      }
    }
  ]
}
