{
  "type": "FeatureCollection",
  "features": [
    {
      "type": "Feature",
      "id": "node/11527751838",
      "properties": {
        "timestamp": "2024-01-18T11:47:05Z",
        "version": 1,
        "changeset": 146401562,
        "amenity": "pharmacy",
        "healthcare": "pharmacy",
        "name": "Drogaria Popular",
        "id": "node/11527751838"
      },
      "geometry": {
        "type": "Point",
        "coordinates": [
          -50.3712276,
          -16.5218489
        ]
      }
    }
  ]
}
