{
  "type": "FeatureCollection",
  "features": [
    {
      "type": "Feature",
      "id": "node/3663050525",
      "properties": {
        "timestamp": "2015-07-23T12:48:55Z",
        "version": 1,
        "changeset": 32824996,
        "name": "Corredeiras de Santa Rosa",
        "place": "locality",
        "source": "IBGE",
        "waterway": "waterfall",
        "id": "node/3663050525"
      },
      "geometry": {
        "type": "Point",
        "coordinates": [
          -58.0958505,
          -10.618622
        ]
      }
    }
  ]
}
