{
  "type": "FeatureCollection",
  "features": [
    {
      "type": "Feature",
      "id": "node/3491299266",
      "properties": {
        "timestamp": "2019-07-07T03:56:52Z",
        "version": 2,
        "changeset": 71972900,
        "IJSN:tipoUnidad": "Hospital Geral",
        "addr:city": "Iconha",
        "addr:housenumber": "40",
        "addr:place": "Centro",
        "addr:postcode": "29280-000",
        "addr:street": "Rua Alvim Serrão",
        "amenity": "hospital",
        "contact:phone": "(28) 3537-1225",
        "healthcare": "hospital",
        "name": "Hospital Maternidade Danilo Monteiro de Castro",
        "id": "node/3491299266"
      },
      "geometry": {
        "type": "Point",
        "coordinates": [
          -40.8131018,
          -20.7915778
        ]
      }
    }
  ]
}
