{
  "type": "FeatureCollection",
  "features": [
    {
      "type": "Feature",
      "id": "node/7942197817",
      "properties": {
        "timestamp": "2020-09-25T12:31:17Z",
        "version": 1,
        "changeset": 91509987,
        "access": "yes",
        "historic": "monument",
        "name": "Cruzeiro Serra Nova Esperança",
        "id": "node/7942197817"
      },
      "geometry": {
        "type": "Point",
        "coordinates": [
          -40.9011253,
          -20.7694829
        ]
      }
    }
  ]
}
