{
  "type": "FeatureCollection",
  "features": [
    {
      "type": "Feature",
      "id": "node/311695113",
      "properties": {
        "timestamp": "2020-07-21T22:37:17Z",
        "version": 4,
        "changeset": 88314740,
        "waterway": "waterfall",
        "id": "node/311695113"
      },
      "geometry": {
        "type": "Point",
        "coordinates": [
          -40.8248167,
          -20.7850366
        ]
      }
    },
    {
      "type": "Feature",
      "id": "node/2841052099",
      "properties": {
        "timestamp": "2020-07-21T22:37:17Z",
        "version": 2,
        "changeset": 88314740,
        "waterway": "waterfall",
        "id": "node/2841052099"
      },
      "geometry": {
        "type": "Point",
        "coordinates": [
          -40.8245818,
          -20.785271
        ]
      }
    },
    {
      "type": "Feature",
      "id": "node/7741980128",
      "properties": {
        "timestamp": "2020-10-01T17:18:28Z",
        "version": 2,
        "changeset": 91839069,
        "name": "Cachoeira da Matinha",
        "waterway": "waterfall",
        "id": "node/7741980128"
      },
      "geometry": {
        "type": "Point",
        "coordinates": [
          -40.8914493,
          -20.7562208
        ]
      }
    },
    {
      "type": "Feature",
      "id": "node/7741984797",
      "properties": {
        "timestamp": "2020-10-01T17:22:09Z",
        "version": 2,
        "changeset": 91839219,
        "name": "Primeira Cachoeira de Nova Esperança",
        "waterway": "waterfall",
        "id": "node/7741984797"
      },
      "geometry": {
        "type": "Point",
        "coordinates": [
          -40.8938619,
          -20.7448299
        ]
      }
    },
    {
      "type": "Feature",
      "id": "node/7741984803",
      "properties": {
        "timestamp": "2020-10-01T17:22:09Z",
        "version": 2,
        "changeset": 91839219,
        "waterway": "waterfall",
        "id": "node/7741984803"
      },
      "geometry": {
        "type": "Point",
        "coordinates": [
          -40.8937745,
          -20.745283
        ]
      }
    }
  ]
}
