{
  "type": "FeatureCollection",
  "features": [
    {
      "type": "Feature",
      "id": "node/7002937083",
      "properties": {
        "timestamp": "2019-11-22T19:15:46Z",
        "version": 1,
        "changeset": 77442704,
        "addr:city": "Camapuã",
        "addr:street": "Avenida Alvino Antônio Martins",
        "amenity": "clinic",
        "healthcare": "clinic",
        "name": "ESF I - Bairro Alto",
        "opening_hours": "Mo-Fr 08:00-17:00",
        "wheelchair": "yes",
        "id": "node/7002937083"
      },
      "geometry": {
        "type": "Point",
        "coordinates": [
          -54.0435965,
          -19.5174496
        ]
      }
    }
  ]
}
