{
  "type": "FeatureCollection",
  "features": [
    {
      "type": "Feature",
      "id": "node/5159841622",
      "properties": {
        "timestamp": "2017-10-10T21:54:00Z",
        "version": 1,
        "changeset": 52807468,
        "amenity": "pharmacy",
        "name": "Drogaria Bonfim",
        "id": "node/5159841622"
      },
      "geometry": {
        "type": "Point",
        "coordinates": [
          -54.04266,
          -19.5371836
        ]
      }
    }
  ]
}
