{
  "type": "FeatureCollection",
  "features": [
    {
      "type": "Feature",
      "id": "node/11247857097",
      "properties": {
        "timestamp": "2023-10-08T11:32:11Z",
        "version": 1,
        "changeset": 142300759,
        "addr:city": "Camacan",
        "addr:postcode": "45880-000",
        "addr:street": "Rua Bela Vista",
        "addr:suburb": "Centro",
        "amenity": "clinic",
        "healthcare": "clinic",
        "healthcare:speciality": "general",
        "name": "Unidade Básica de Saúde da Família Doutor Manoel Rodrigues",
        "operator": "Município de Camacan",
        "operator:type": "public",
        "id": "node/11247857097"
      },
      "geometry": {
        "type": "Point",
        "coordinates": [
          -39.4971304,
          -15.4227812
        ]
      }
    }
  ]
}
