{
  "type": "FeatureCollection",
  "features": [
    {
      "type": "Feature",
      "id": "node/4770407227",
      "properties": {
        "timestamp": "2019-12-20T13:01:42Z",
        "version": 4,
        "changeset": 78684028,
        "addr:city": "Uraí",
        "addr:housenumber": "983",
        "addr:postcode": "86280-000",
        "addr:street": "Rua Rio de Janeiro",
        "addr:suburb": "Centro",
        "amenity": "doctors",
        "healthcare": "doctor",
        "healthcare:speciality": "general",
        "name": "Consultório Médico Osnir Borghi",
        "opening_hours": "Mo-Sa 08:00-18:00",
        "wheelchair": "yes",
        "id": "node/4770407227"
      },
      "geometry": {
        "type": "Point",
        "coordinates": [
          -50.7924336,
          -23.2040327
        ]
      }
    }
  ]
}
