{
  "type": "FeatureCollection",
  "features": [
    {
      "type": "Feature",
      "id": "node/5519452824",
      "properties": {
        "timestamp": "2018-03-31T22:44:37Z",
        "version": 1,
        "changeset": 57700654,
        "addr:city": "Uraí",
        "addr:postcode": "86280-000",
        "addr:street": "Rua Professora Ana Dias de Souza",
        "addr:suburb": "Centro",
        "amenity": "hospital",
        "healthcare": "hospital",
        "name": "Santa Casa",
        "id": "node/5519452824"
      },
      "geometry": {
        "type": "Point",
        "coordinates": [
          -50.7930616,
          -23.1980219
        ]
      }
    }
  ]
}
