{
  "type": "FeatureCollection",
  "features": [
    {
      "type": "Feature",
      "id": "node/2766061317",
      "properties": {
        "timestamp": "2022-07-17T23:11:46Z",
        "version": 2,
        "changeset": 123737690,
        "addr:city": "Piedade de Ponte Nova",
        "addr:postcode": "35382-000",
        "amenity": "pharmacy",
        "healthcare": "pharmacy",
        "id": "node/2766061317"
      },
      "geometry": {
        "type": "Point",
        "coordinates": [
          -42.7339118,
          -20.2452773
        ]
      }
    }
  ]
}
