{
  "type": "FeatureCollection",
  "features": [
    {
      "type": "Feature",
      "id": "node/4789041236",
      "properties": {
        "timestamp": "2017-05-14T00:00:37Z",
        "version": 2,
        "changeset": 48662109,
        "government": "legislative",
        "name": "Câmara de Vereadores",
        "office": "government",
        "source": "IBGE",
        "id": "node/4789041236"
      },
      "geometry": {
        "type": "Point",
        "coordinates": [
          -53.5864404,
          -31.7326248
        ]
      }
    }
  ]
}
