{
  "type": "FeatureCollection",
  "features": [
    {
      "type": "Feature",
      "id": "node/11396058826",
      "properties": {
        "timestamp": "2023-12-05T13:20:20Z",
        "version": 1,
        "changeset": 144791808,
        "addr:city": "Palmópolis",
        "addr:postcode": "39945-000",
        "addr:street": "Praça Joaquim Almirante de Oliveira",
        "addr:suburb": "Planalto",
        "amenity": "clinic",
        "healthcare": "clinic",
        "healthcare:speciality": "general",
        "name": "Unidade Básica de Saúde Professora Eutalia Dias Neves",
        "operator": "Município de Palmópolis",
        "operator:type": "public",
        "phone": "+55 33 3744 9110",
        "id": "node/11396058826"
      },
      "geometry": {
        "type": "Point",
        "coordinates": [
          -40.4226837,
          -16.7426826
        ]
      }
    },
    {
      "type": "Feature",
      "id": "node/11396058827",
      "properties": {
        "timestamp": "2023-12-05T13:20:20Z",
        "version": 1,
        "changeset": 144791808,
        "addr:city": "Dois de Abril",
        "addr:district": "Dois de Abril",
        "addr:postcode": "39945-000",
        "addr:street": "Rua Fortunato Pereira",
        "addr:suburb": "Centro",
        "amenity": "clinic",
        "healthcare": "clinic",
        "healthcare:speciality": "general",
        "name": "Unidade Básica de Saúde Modesta Ferreira da Cruz",
        "operator": "Município de Palmópolis",
        "operator:type": "public",
        "id": "node/11396058827"
      },
      "geometry": {
        "type": "Point",
        "coordinates": [
          -40.317283,
          -16.8426725
        ]
      }
    }
  ]
}
