{
  "type": "FeatureCollection",
  "features": [
    {
      "type": "Feature",
      "id": "node/9643387484",
      "properties": {
        "timestamp": "2022-04-05T14:17:55Z",
        "version": 1,
        "changeset": 119346733,
        "addr:housenumber": "682",
        "addr:postcode": "08674-010",
        "addr:street": "Rua Benjamin Constant",
        "addr:suburb": "Centro",
        "amenity": "library",
        "email": "biblioteca@suzano.sp.gov.br",
        "name": "Biblioteca Pública Professora Maria Eliza de Azevedo Cintra",
        "operator": "Secretaria Municipal de Cultura",
        "operator:type": "government",
        "phone": "+55 11 4759 2304",
        "id": "node/9643387484"
      },
      "geometry": {
        "type": "Point",
        "coordinates": [
          -46.3116847,
          -23.5401379
        ]
      }
    },
    {
      "type": "Feature",
      "id": "node/9671314610",
      "properties": {
        "timestamp": "2022-04-17T02:54:27Z",
        "version": 1,
        "changeset": 119802838,
        "amenity": "library",
        "id": "node/9671314610"
      },
      "geometry": {
        "type": "Point",
        "coordinates": [
          -46.2922247,
          -23.5533154
        ]
      }
    }
  ]
}
