{
  "type": "FeatureCollection",
  "features": [
    {
      "type": "Feature",
      "id": "node/4829773495",
      "properties": {
        "timestamp": "2017-05-02T01:57:53Z",
        "version": 1,
        "changeset": 48321492,
        "name": "Cachoeira do Lageado",
        "waterway": "waterfall",
        "id": "node/4829773495"
      },
      "geometry": {
        "type": "Point",
        "coordinates": [
          -45.6605676,
          -22.7908604
        ]
      }
    }
  ]
}
