{
  "type": "FeatureCollection",
  "features": [
    {
      "type": "Feature",
      "id": "node/8402018079",
      "properties": {
        "timestamp": "2021-02-07T14:03:48Z",
        "version": 3,
        "changeset": 98851000,
        "name": "Cascata do Canudo",
        "natural": "cliff",
        "source": "Bing",
        "waterway": "waterfall",
        "id": "node/8402018079"
      },
      "geometry": {
        "type": "Point",
        "coordinates": [
          -52.1673296,
          -29.1492768
        ]
      }
    }
  ]
}
