{
  "type": "FeatureCollection",
  "features": [
    {
      "type": "Feature",
      "id": "node/796129477",
      "properties": {
        "timestamp": "2022-03-08T19:39:10Z",
        "version": 3,
        "changeset": 118250190,
        "addr:street": "Avenida Vaz de Castro",
        "government": "social_security",
        "name": "Instituto Nacional do Seguro Social - INSS",
        "office": "government",
        "opening_hours": "Mo-Fr 07:00-17:00",
        "operator": "Instituto Nacional do Seguro Social",
        "operator:short": "INSS",
        "operator:wikidata": "Q10302614",
        "operator:wikipedia": "pt:Instituto Nacional do Seguro Social",
        "id": "node/796129477"
      },
      "geometry": {
        "type": "Point",
        "coordinates": [
          -35.8561387,
          -9.4857202
        ]
      }
    }
  ]
}
