{
  "type": "FeatureCollection",
  "features": [
    {
      "type": "Feature",
      "id": "node/9406850279",
      "properties": {
        "timestamp": "2022-01-10T08:21:20Z",
        "version": 1,
        "changeset": 115970911,
        "amenity": "health_post",
        "name": "Posto de Saúde Pinheiro",
        "id": "node/9406850279"
      },
      "geometry": {
        "type": "Point",
        "coordinates": [
          -41.5428009,
          -7.9616699
        ]
      }
    }
  ]
}
