{
  "type": "FeatureCollection",
  "features": [
    {
      "type": "Feature",
      "id": "node/3350774723",
      "properties": {
        "timestamp": "2022-09-26T17:20:51Z",
        "version": 3,
        "changeset": 126665399,
        "name": "Empresa Baiana de Defesa Agropecuária",
        "office": "government",
        "short_name": "EBDA",
        "id": "node/3350774723"
      },
      "geometry": {
        "type": "Point",
        "coordinates": [
          -43.4119744,
          -13.2637558
        ]
      }
    }
  ]
}
