{
  "type": "FeatureCollection",
  "features": [
    {
      "type": "Feature",
      "id": "node/8234223911",
      "properties": {
        "timestamp": "2021-08-12T00:00:05Z",
        "version": 2,
        "changeset": 109540849,
        "addr:housenumber": "570",
        "addr:street": "Rua Padre Vicente",
        "amenity": "community_centre",
        "name": "Rádio Comunitária Styllus FM 104,9",
        "phone": "+55 88 9 9791 0800",
        "id": "node/8234223911"
      },
      "geometry": {
        "type": "Point",
        "coordinates": [
          -38.1035614,
          -5.1520624
        ]
      }
    }
  ]
}
