{
  "type": "FeatureCollection",
  "features": [
    {
      "type": "Feature",
      "id": "node/10155087240",
      "properties": {
        "timestamp": "2022-11-18T20:54:48Z",
        "version": 2,
        "changeset": 129101821,
        "addr:housenumber": "2699",
        "addr:street": "Rua Padre Custódio",
        "amenity": "dentist",
        "healthcare": "dentist",
        "name": "Dra. Ivaneide Cardoao odontologia",
        "phone": "+55 88 9 9717 3584",
        "id": "node/10155087240"
      },
      "geometry": {
        "type": "Point",
        "coordinates": [
          -38.0979385,
          -5.1428127
        ]
      }
    }
  ]
}
