{
  "type": "FeatureCollection",
  "features": [
    {
      "type": "Feature",
      "id": "node/6784058278",
      "properties": {
        "timestamp": "2019-09-10T01:46:23Z",
        "version": 1,
        "changeset": 74285508,
        "amenity": "hospital",
        "healthcare": "hospital",
        "name": "Hospital Municipal Iomar Meireles",
        "id": "node/6784058278"
      },
      "geometry": {
        "type": "Point",
        "coordinates": [
          -39.1011028,
          -13.5337342
        ]
      }
    }
  ]
}
