{
  "type": "FeatureCollection",
  "features": [
    {
      "type": "Feature",
      "id": "node/11327870340",
      "properties": {
        "timestamp": "2023-11-05T17:41:10Z",
        "version": 1,
        "changeset": 143660055,
        "amenity": "pharmacy",
        "name": "Farmácia Vida",
        "id": "node/11327870340"
      },
      "geometry": {
        "type": "Point",
        "coordinates": [
          -39.0981756,
          -13.5377176
        ]
      }
    }
  ]
}
