{
  "type": "FeatureCollection",
  "features": [
    {
      "type": "Feature",
      "id": "node/6222103793",
      "properties": {
        "timestamp": "2024-12-21T00:41:48Z",
        "version": 3,
        "changeset": 160454620,
        "name": "Cachoeirinha",
        "waterway": "waterfall",
        "id": "node/6222103793"
      },
      "geometry": {
        "type": "Point",
        "coordinates": [
          -53.4303206,
          -26.8651931
        ]
      }
    }
  ]
}
