{
  "type": "FeatureCollection",
  "features": [
    {
      "type": "Feature",
      "id": "node/6222103793",
      "properties": {
        "timestamp": "2019-01-20T00:28:01Z",
        "version": 2,
        "changeset": 66466318,
        "name": "Cachoeirinha",
        "waterway": "waterfall",
        "id": "node/6222103793"
      },
      "geometry": {
        "type": "Point",
        "coordinates": [
          -53.4304453,
          -26.8652242
        ]
      }
    },
    {
      "type": "Feature",
      "id": "node/6222123979",
      "properties": {
        "timestamp": "2019-01-20T00:28:00Z",
        "version": 1,
        "changeset": 66466318,
        "waterway": "waterfall",
        "id": "node/6222123979"
      },
      "geometry": {
        "type": "Point",
        "coordinates": [
          -53.4304043,
          -26.8650323
        ]
      }
    }
  ]
}
