{
  "type": "FeatureCollection",
  "features": [
    {
      "type": "Feature",
      "id": "node/2376480725",
      "properties": {
        "timestamp": "2020-06-22T07:35:40Z",
        "version": 3,
        "changeset": 86964179,
        "name": "Cachoeira Grande",
        "waterway": "waterfall",
        "id": "node/2376480725"
      },
      "geometry": {
        "type": "Point",
        "coordinates": [
          -45.2377725,
          -18.1365025
        ]
      }
    },
    {
      "type": "Feature",
      "id": "node/6990834790",
      "properties": {
        "timestamp": "2019-11-19T19:57:01Z",
        "version": 1,
        "changeset": 77290011,
        "name": "Corredeira dos Caldeirões",
        "source": "IBGE",
        "waterway": "waterfall",
        "id": "node/6990834790"
      },
      "geometry": {
        "type": "Point",
        "coordinates": [
          -45.184348,
          -18.1073671
        ]
      }
    }
  ]
}
