{
  "type": "FeatureCollection",
  "features": [
    {
      "type": "Feature",
      "id": "node/5404519151",
      "properties": {
        "timestamp": "2022-02-24T16:04:54Z",
        "version": 3,
        "changeset": 117818205,
        "name": "Cachoeira Gameleira",
        "waterway": "waterfall",
        "id": "node/5404519151"
      },
      "geometry": {
        "type": "Point",
        "coordinates": [
          -40.9066005,
          -3.8390728
        ]
      }
    },
    {
      "type": "Feature",
      "id": "node/5404519168",
      "properties": {
        "timestamp": "2022-02-24T16:04:54Z",
        "version": 4,
        "changeset": 117818205,
        "name": "Cachoeira Cafundó",
        "waterway": "waterfall",
        "id": "node/5404519168"
      },
      "geometry": {
        "type": "Point",
        "coordinates": [
          -40.9095159,
          -3.8369096
        ]
      }
    },
    {
      "type": "Feature",
      "id": "node/5404519622",
      "properties": {
        "timestamp": "2019-12-23T21:08:21Z",
        "version": 2,
        "changeset": 78789801,
        "name": "Cachoeira Gavião",
        "waterway": "waterfall",
        "id": "node/5404519622"
      },
      "geometry": {
        "type": "Point",
        "coordinates": [
          -40.9088106,
          -3.8329318
        ]
      }
    },
    {
      "type": "Feature",
      "id": "node/6654232365",
      "properties": {
        "timestamp": "2021-07-21T21:00:39Z",
        "version": 2,
        "changeset": 108386780,
        "name": "Cachoeira do Boi Morto",
        "waterway": "waterfall",
        "id": "node/6654232365"
      },
      "geometry": {
        "type": "Point",
        "coordinates": [
          -41.0141527,
          -3.8811615
        ]
      }
    }
  ]
}
