{
  "type": "FeatureCollection",
  "features": [
    {
      "type": "Feature",
      "id": "node/9258737130",
      "properties": {
        "timestamp": "2022-03-10T01:28:34Z",
        "version": 2,
        "changeset": 118299934,
        "addr:city": "Valença do Piauí",
        "addr:housenumber": "251",
        "addr:street": "Avenida Joaquim Manoel",
        "description": "Cartório da 18ª e 89ª zona eleitoral",
        "government": "yes",
        "name": "Justiça Eleitoral - Tribunal Regional Eleitoral do Piauí",
        "office": "government",
        "id": "node/9258737130"
      },
      "geometry": {
        "type": "Point",
        "coordinates": [
          -41.737362,
          -6.4065564
        ]
      }
    },
    {
      "type": "Feature",
      "id": "node/9258737208",
      "properties": {
        "timestamp": "2022-02-03T17:38:29Z",
        "version": 2,
        "changeset": 116974204,
        "addr:city": "Valença do Piauí",
        "addr:postcode": "64300-000",
        "addr:street": "Rua Eurípedes Martins",
        "addr:suburb": "Centro",
        "government": "yes",
        "name": "Secretaria Municipal de Educação",
        "office": "government",
        "id": "node/9258737208"
      },
      "geometry": {
        "type": "Point",
        "coordinates": [
          -41.735367,
          -6.4070411
        ]
      }
    },
    {
      "type": "Feature",
      "id": "node/10934523979",
      "properties": {
        "timestamp": "2023-05-28T17:28:47Z",
        "version": 1,
        "changeset": 136665662,
        "addr:housenumber": "164",
        "addr:street": "Rua Areolino de Abreu",
        "description": "Registro Civil, Registro de Imóveis, Protestos de títulos, Tabelionato de notas, Anexos",
        "name": "2° Cartorio",
        "office": "government",
        "id": "node/10934523979"
      },
      "geometry": {
        "type": "Point",
        "coordinates": [
          -41.7406274,
          -6.4042945
        ]
      }
    }
  ]
}
