{
  "type": "FeatureCollection",
  "features": [
    {
      "type": "Feature",
      "id": "node/2149863640",
      "properties": {
        "timestamp": "2020-08-17T22:25:05Z",
        "version": 4,
        "changeset": 89540164,
        "historic": "monument",
        "name": "Santuário Santo Antônio",
        "id": "node/2149863640"
      },
      "geometry": {
        "type": "Point",
        "coordinates": [
          -53.9045489,
          -30.8140456
        ]
      }
    },
    {
      "type": "Feature",
      "id": "node/6428928528",
      "properties": {
        "timestamp": "2019-04-25T17:49:39Z",
        "version": 1,
        "changeset": 69575390,
        "historic": "monument",
        "name": "L",
        "id": "node/6428928528"
      },
      "geometry": {
        "type": "Point",
        "coordinates": [
          -53.8920275,
          -30.8115476
        ]
      }
    }
  ]
}
