{
  "type": "FeatureCollection",
  "features": [
    {
      "type": "Feature",
      "id": "node/12146663547",
      "properties": {
        "timestamp": "2024-08-30T18:57:21Z",
        "version": 1,
        "changeset": 155988079,
        "amenity": "social_facility",
        "social_facility": "group_home",
        "social_facility:for": "senior",
        "id": "node/12146663547"
      },
      "geometry": {
        "type": "Point",
        "coordinates": [
          -50.7754605,
          -29.5149709
        ]
      }
    }
  ]
}
