{
  "type": "FeatureCollection",
  "features": [
    {
      "type": "Feature",
      "id": "node/5315260736",
      "properties": {
        "timestamp": "2018-01-01T19:57:07Z",
        "version": 1,
        "changeset": 55084797,
        "shop": "bicycle",
        "id": "node/5315260736"
      },
      "geometry": {
        "type": "Point",
        "coordinates": [
          -51.534467,
          -23.1090118
        ]
      }
    }
  ]
}
