{
  "type": "FeatureCollection",
  "features": [
    {
      "type": "Feature",
      "id": "node/4611812290",
      "properties": {
        "timestamp": "2017-10-15T22:47:44Z",
        "version": 2,
        "changeset": 52968398,
        "amenity": "clinic",
        "name": "Oftalmoclinica",
        "id": "node/4611812290"
      },
      "geometry": {
        "type": "Point",
        "coordinates": [
          -53.3181565,
          -27.9005917
        ]
      }
    },
    {
      "type": "Feature",
      "id": "node/5764783298",
      "properties": {
        "timestamp": "2020-04-04T18:10:54Z",
        "version": 2,
        "changeset": 83079457,
        "amenity": "clinic",
        "healthcare": "clinic",
        "source": "IBGE",
        "id": "node/5764783298"
      },
      "geometry": {
        "type": "Point",
        "coordinates": [
          -53.2959706,
          -27.8948697
        ]
      }
    },
    {
      "type": "Feature",
      "id": "node/5764783339",
      "properties": {
        "timestamp": "2018-07-17T01:40:45Z",
        "version": 1,
        "changeset": 60779488,
        "amenity": "clinic",
        "source": "IBGE",
        "id": "node/5764783339"
      },
      "geometry": {
        "type": "Point",
        "coordinates": [
          -53.3104813,
          -27.9014383
        ]
      }
    },
    {
      "type": "Feature",
      "id": "node/10593935336",
      "properties": {
        "timestamp": "2023-01-30T11:31:50Z",
        "version": 1,
        "changeset": 131876327,
        "addr:city": "Palmeira das Missões",
        "addr:postcode": "98300000",
        "addr:street": "Rua Santa Maria",
        "addr:suburb": "Vista Alegre",
        "amenity": "clinic",
        "healthcare": "clinic",
        "name": "Posto de Saúde",
        "wheelchair": "yes",
        "id": "node/10593935336"
      },
      "geometry": {
        "type": "Point",
        "coordinates": [
          -53.3183437,
          -27.9140453
        ]
      }
    }
  ]
}
