{
  "type": "FeatureCollection",
  "features": [
    {
      "type": "Feature",
      "id": "node/12481636395",
      "properties": {
        "timestamp": "2025-01-08T01:16:34Z",
        "version": 2,
        "changeset": 161116362,
        "addr:city": "Taiobeiras",
        "addr:housenumber": "448",
        "addr:postcode": "39550-000",
        "addr:street": "Rua Santa Rita de Cássia",
        "addr:suburb": "Centro",
        "amenity": "social_facility",
        "name": "Assosciação de Pais e Amigos dos Excepcionais de Taiobeiras",
        "operator": "Associação de Pais e Amigos dos Excepcionais",
        "operator:type": "ngo",
        "operator:wikidata": "Q16494876",
        "id": "node/12481636395"
      },
      "geometry": {
        "type": "Point",
        "coordinates": [
          -42.2325244,
          -15.8094009
        ]
      }
    }
  ]
}
