{
  "type": "FeatureCollection",
  "features": [
    {
      "type": "Feature",
      "id": "node/3816383115",
      "properties": {
        "timestamp": "2018-09-02T03:32:49Z",
        "version": 2,
        "changeset": 62210376,
        "amenity": "library",
        "name": "Biblioteca Municipal de Palmeiras",
        "id": "node/3816383115"
      },
      "geometry": {
        "type": "Point",
        "coordinates": [
          -41.5776243,
          -12.5150017
        ]
      }
    }
  ]
}
