{
  "type": "FeatureCollection",
  "features": [
    {
      "type": "Feature",
      "id": "node/3816383115",
      "properties": {
        "timestamp": "2018-09-02T03:32:49Z",
        "version": 2,
        "changeset": 62210376,
        "amenity": "library",
        "name": "Biblioteca Municipal de Palmeiras",
        "id": "node/3816383115"
      },
      "geometry": {
        "type": "Point",
        "coordinates": [
          -41.5776243,
          -12.5150017
        ]
      }
    },
    {
      "type": "Feature",
      "id": "node/12688602760",
      "properties": {
        "timestamp": "2025-03-21T20:27:17Z",
        "version": 1,
        "changeset": 163923422,
        "amenity": "library",
        "id": "node/12688602760"
      },
      "geometry": {
        "type": "Point",
        "coordinates": [
          -41.4950409,
          -12.450823
        ]
      }
    }
  ]
}
