{
  "type": "FeatureCollection",
  "features": [
    {
      "type": "Feature",
      "id": "node/4209887389",
      "properties": {
        "timestamp": "2016-10-12T14:42:53Z",
        "version": 2,
        "changeset": 42831929,
        "amenity": "school",
        "name": "Centro universitário",
        "id": "node/4209887389"
      },
      "geometry": {
        "type": "Point",
        "coordinates": [
          -47.5006334,
          -2.5571442
        ]
      }
    },
    {
      "type": "Feature",
      "id": "node/4209887489",
      "properties": {
        "timestamp": "2016-10-12T14:42:53Z",
        "version": 2,
        "changeset": 42831929,
        "amenity": "school",
        "name": "E.i.r.de Fárias",
        "id": "node/4209887489"
      },
      "geometry": {
        "type": "Point",
        "coordinates": [
          -47.4993802,
          -2.5584653
        ]
      }
    },
    {
      "type": "Feature",
      "id": "node/4648772989",
      "properties": {
        "timestamp": "2017-01-31T16:32:23Z",
        "version": 1,
        "changeset": 45690178,
        "amenity": "school",
        "name": "escola Adélia carvalho sodré",
        "name:pt": "escola Adélia carvalho sodré",
        "id": "node/4648772989"
      },
      "geometry": {
        "type": "Point",
        "coordinates": [
          -47.4974112,
          -2.5571381
        ]
      }
    }
  ]
}
