{
  "type": "FeatureCollection",
  "features": [
    {
      "type": "Feature",
      "id": "node/6434231089",
      "properties": {
        "timestamp": "2019-04-28T16:43:57Z",
        "version": 1,
        "changeset": 69668790,
        "amenity": "veterinary",
        "name": "HCI Veterinária",
        "id": "node/6434231089"
      },
      "geometry": {
        "type": "Point",
        "coordinates": [
          -38.6237503,
          -5.8890429
        ]
      }
    }
  ]
}
