{
  "type": "FeatureCollection",
  "features": [
    {
      "type": "Feature",
      "id": "node/9578392417",
      "properties": {
        "timestamp": "2022-09-29T22:13:24Z",
        "version": 2,
        "changeset": 126799964,
        "name:pt": "Cachoeira do Poço Encantado",
        "waterway": "waterfall",
        "id": "node/9578392417"
      },
      "geometry": {
        "type": "Point",
        "coordinates": [
          -47.1092503,
          -10.2460096
        ]
      }
    }
  ]
}
