{
  "type": "FeatureCollection",
  "features": [
    {
      "type": "Feature",
      "id": "node/6506371026",
      "properties": {
        "timestamp": "2023-02-15T19:17:57Z",
        "version": 2,
        "changeset": 132597546,
        "access": "permissive",
        "historic": "monument",
        "name": "Cruz Missionária",
        "id": "node/6506371026"
      },
      "geometry": {
        "type": "Point",
        "coordinates": [
          -38.2743982,
          -5.2722737
        ]
      }
    }
  ]
}
