{
  "type": "FeatureCollection",
  "features": [
    {
      "type": "Feature",
      "id": "node/5391464811",
      "properties": {
        "timestamp": "2018-02-06T02:54:41Z",
        "version": 1,
        "changeset": 56103359,
        "historic": "monument",
        "name": "Cruz Central",
        "id": "node/5391464811"
      },
      "geometry": {
        "type": "Point",
        "coordinates": [
          -37.8007952,
          -5.6678973
        ]
      }
    }
  ]
}
