{
  "type": "FeatureCollection",
  "features": [
    {
      "type": "Feature",
      "id": "node/5750420357",
      "properties": {
        "timestamp": "2018-07-10T00:41:02Z",
        "version": 1,
        "changeset": 60555918,
        "amenity": "college",
        "name": "SENAI",
        "source": "IBGE",
        "id": "node/5750420357"
      },
      "geometry": {
        "type": "Point",
        "coordinates": [
          -51.5245968,
          -29.2492521
        ]
      }
    }
  ]
}
