{
  "type": "FeatureCollection",
  "features": [
    {
      "type": "Feature",
      "id": "node/5750420354",
      "properties": {
        "timestamp": "2022-11-22T14:59:13Z",
        "version": 3,
        "changeset": 129243875,
        "amenity": "social_facility",
        "name": "Centro de Referência de Assitência Social",
        "short_name": "CRAS",
        "social_facility": "day_care",
        "social_facility:for": "underprivileged",
        "source": "IBGE",
        "id": "node/5750420354"
      },
      "geometry": {
        "type": "Point",
        "coordinates": [
          -51.5320204,
          -29.2548231
        ]
      }
    }
  ]
}
