{
  "type": "FeatureCollection",
  "features": [
    {
      "type": "Feature",
      "id": "node/4970904221",
      "properties": {
        "timestamp": "2017-07-14T17:18:25Z",
        "version": 1,
        "changeset": 50289557,
        "amenity": "community_centre",
        "internet_access": "wlan",
        "name": "CID Córrego do Meio",
        "name:pt": "CID Córrego do Meio",
        "id": "node/4970904221"
      },
      "geometry": {
        "type": "Point",
        "coordinates": [
          -55.1765815,
          -20.8711429
        ]
      }
    }
  ]
}
