{
  "type": "FeatureCollection",
  "features": [
    {
      "type": "Feature",
      "id": "node/9938065939",
      "properties": {
        "timestamp": "2022-08-07T21:03:02Z",
        "version": 1,
        "changeset": 124613481,
        "name": "Pousada Villa do Sossego",
        "tourism": "hotel",
        "id": "node/9938065939"
      },
      "geometry": {
        "type": "Point",
        "coordinates": [
          -46.6538626,
          -22.517267
        ]
      }
    },
    {
      "type": "Feature",
      "id": "node/10858085324",
      "properties": {
        "timestamp": "2023-04-30T15:18:02Z",
        "version": 1,
        "changeset": 135541434,
        "name": "Hotel Santiago 33",
        "tourism": "hotel",
        "id": "node/10858085324"
      },
      "geometry": {
        "type": "Point",
        "coordinates": [
          -46.6470552,
          -22.5234774
        ]
      }
    },
    {
      "type": "Feature",
      "id": "node/11079184121",
      "properties": {
        "timestamp": "2023-07-31T18:01:41Z",
        "version": 1,
        "changeset": 139265849,
        "name": "Pousada Pé da Serra - Lindóia SP",
        "tourism": "hotel",
        "id": "node/11079184121"
      },
      "geometry": {
        "type": "Point",
        "coordinates": [
          -46.6425049,
          -22.517956
        ]
      }
    }
  ]
}
