{
  "type": "FeatureCollection",
  "features": [
    {
      "type": "Feature",
      "id": "node/8596343510",
      "properties": {
        "timestamp": "2021-04-07T23:02:33Z",
        "version": 3,
        "changeset": 102509653,
        "name": "Cachoeira de Santa Ana",
        "waterway": "waterfall",
        "id": "node/8596343510"
      },
      "geometry": {
        "type": "Point",
        "coordinates": [
          -40.9481493,
          -18.9308848
        ]
      }
    },
    {
      "type": "Feature",
      "id": "node/8596367958",
      "properties": {
        "timestamp": "2021-04-06T09:50:23Z",
        "version": 2,
        "changeset": 102395235,
        "waterway": "waterfall",
        "id": "node/8596367958"
      },
      "geometry": {
        "type": "Point",
        "coordinates": [
          -40.9593071,
          -18.9361364
        ]
      }
    }
  ]
}
