{
  "type": "FeatureCollection",
  "features": [
    {
      "type": "Feature",
      "id": "node/6237876104",
      "properties": {
        "timestamp": "2019-01-26T12:30:30Z",
        "version": 1,
        "changeset": 66654344,
        "amenity": "toilets",
        "name": "Banheiro",
        "id": "node/6237876104"
      },
      "geometry": {
        "type": "Point",
        "coordinates": [
          -54.9222681,
          -28.7146006
        ]
      }
    },
    {
      "type": "Feature",
      "id": "node/7155485652",
      "properties": {
        "timestamp": "2020-01-24T05:11:46Z",
        "version": 1,
        "changeset": 80008495,
        "amenity": "toilets",
        "name": "Sanitàrio Pùblico",
        "id": "node/7155485652"
      },
      "geometry": {
        "type": "Point",
        "coordinates": [
          -54.9116192,
          -28.7299356
        ]
      }
    }
  ]
}
