{
  "type": "FeatureCollection",
  "features": [
    {
      "type": "Feature",
      "id": "node/6629046611",
      "properties": {
        "timestamp": "2019-07-18T16:35:08Z",
        "version": 1,
        "changeset": 72398997,
        "name": "Novo Hotel",
        "tourism": "hotel",
        "id": "node/6629046611"
      },
      "geometry": {
        "type": "Point",
        "coordinates": [
          -42.9444871,
          -8.1107144
        ]
      }
    }
  ]
}
