{
  "type": "FeatureCollection",
  "features": [
    {
      "type": "Feature",
      "id": "node/12104360402",
      "properties": {
        "timestamp": "2024-08-11T14:28:32Z",
        "version": 1,
        "changeset": 155105617,
        "amenity": "social_facility",
        "name": "Agência da Previdência Social - INSS",
        "id": "node/12104360402"
      },
      "geometry": {
        "type": "Point",
        "coordinates": [
          -42.9475365,
          -8.1089039
        ]
      }
    }
  ]
}
