{
  "type": "FeatureCollection",
  "features": [
    {
      "type": "Feature",
      "id": "node/3882246023",
      "properties": {
        "timestamp": "2023-04-18T20:09:17Z",
        "version": 5,
        "changeset": 135075630,
        "addr:city": "Vila Velha",
        "addr:country": "BR",
        "addr:housename": "Shopping Vila Velha",
        "addr:housenumber": "2418",
        "addr:place": "Shopping Vila Velha",
        "addr:postcode": "29100-022",
        "addr:state": "ES",
        "addr:street": "Avenida Luciano das Neves",
        "addr:suburb": "Divino Espirito Santo",
        "air_conditioning": "yes",
        "amenity": "cinema",
        "level": "2",
        "name": "Cinemark",
        "not:brand:wikidata": "Q707530",
        "operator": "Cinemark",
        "wheelchair": "yes",
        "id": "node/3882246023"
      },
      "geometry": {
        "type": "Point",
        "coordinates": [
          -40.2984561,
          -20.3508637
        ]
      }
    }
  ]
}
