{
  "type": "FeatureCollection",
  "features": [
    {
      "type": "Feature",
      "id": "node/5094748767",
      "properties": {
        "timestamp": "2021-05-17T19:27:42Z",
        "version": 2,
        "changeset": 104845590,
        "name": "Secretaria Municipal de Saúde",
        "office": "government",
        "id": "node/5094748767"
      },
      "geometry": {
        "type": "Point",
        "coordinates": [
          -51.1937057,
          -22.9941371
        ]
      }
    }
  ]
}
