{
  "type": "FeatureCollection",
  "features": [
    {
      "type": "Feature",
      "id": "node/8636188396",
      "properties": {
        "timestamp": "2021-04-16T18:20:03Z",
        "version": 1,
        "changeset": 103075689,
        "amenity": "library",
        "name": "Biblioteca Pública Municipal Cruz e Sousa",
        "id": "node/8636188396"
      },
      "geometry": {
        "type": "Point",
        "coordinates": [
          -49.261381,
          -26.19617
        ]
      }
    }
  ]
}
