{
  "type": "FeatureCollection",
  "features": [
    {
      "type": "Feature",
      "id": "node/2912152416",
      "properties": {
        "timestamp": "2023-02-24T19:34:14Z",
        "version": 7,
        "changeset": 132981953,
        "height": "60",
        "name": "Cascata Paraíso da Serra",
        "source": "http://www.campoalegre.sc.gov.br/turismo/item/detalhe/9990",
        "tourism": "attraction",
        "waterway": "waterfall",
        "id": "node/2912152416"
      },
      "geometry": {
        "type": "Point",
        "coordinates": [
          -49.256862,
          -26.1995325
        ]
      }
    },
    {
      "type": "Feature",
      "id": "node/2962027258",
      "properties": {
        "timestamp": "2020-10-24T22:28:26Z",
        "version": 4,
        "changeset": 93001853,
        "description": "Cachoeira",
        "name": "Salto do Engenho",
        "waterway": "waterfall",
        "id": "node/2962027258"
      },
      "geometry": {
        "type": "Point",
        "coordinates": [
          -49.2934008,
          -26.1413316
        ]
      }
    },
    {
      "type": "Feature",
      "id": "node/2962027510",
      "properties": {
        "timestamp": "2014-07-14T01:24:58Z",
        "version": 1,
        "changeset": 24131421,
        "waterway": "waterfall",
        "id": "node/2962027510"
      },
      "geometry": {
        "type": "Point",
        "coordinates": [
          -49.305151,
          -26.1484633
        ]
      }
    },
    {
      "type": "Feature",
      "id": "node/4785222535",
      "properties": {
        "timestamp": "2017-04-09T22:44:43Z",
        "version": 1,
        "changeset": 47605616,
        "name": "Cascatinha",
        "tourism": "attraction",
        "waterway": "waterfall",
        "id": "node/4785222535"
      },
      "geometry": {
        "type": "Point",
        "coordinates": [
          -49.263868,
          -26.1954069
        ]
      }
    }
  ]
}
