{
  "type": "FeatureCollection",
  "features": [
    {
      "type": "Feature",
      "id": "node/12358992367",
      "properties": {
        "timestamp": "2024-11-20T18:11:06Z",
        "version": 1,
        "changeset": 159378801,
        "addr:street": "Avenida Inocêncio Seráfico",
        "amenity": "veterinary",
        "mobile": "+55 11 94044 9617",
        "name": "Cães e Gatos Centro Veterinário",
        "opening_hours": "Mo-Su,PH 08:00-20:00",
        "phone": "+55 11 4184 7890",
        "id": "node/12358992367"
      },
      "geometry": {
        "type": "Point",
        "coordinates": [
          -46.8355733,
          -23.5267221
        ]
      }
    }
  ]
}
