{
  "type": "FeatureCollection",
  "features": [
    {
      "type": "Feature",
      "id": "node/4307558831",
      "properties": {
        "timestamp": "2016-07-17T16:24:32Z",
        "version": 1,
        "changeset": 40801592,
        "historic": "monument",
        "name": "Estátua de Padre Cícero",
        "id": "node/4307558831"
      },
      "geometry": {
        "type": "Point",
        "coordinates": [
          -39.0535058,
          -7.3648973
        ]
      }
    }
  ]
}
