{
  "type": "FeatureCollection",
  "features": [
    {
      "type": "Feature",
      "id": "node/4567860601",
      "properties": {
        "timestamp": "2017-07-05T00:07:29Z",
        "version": 2,
        "changeset": 50046678,
        "amenity": "drinking_water",
        "name": "Caixa d'agua",
        "id": "node/4567860601"
      },
      "geometry": {
        "type": "Point",
        "coordinates": [
          -50.2383523,
          -30.2468782
        ]
      }
    }
  ]
}
