{
  "type": "FeatureCollection",
  "features": [
    {
      "type": "Feature",
      "id": "node/6496473848",
      "properties": {
        "timestamp": "2023-03-23T23:23:33Z",
        "version": 8,
        "changeset": 134043634,
        "amenity": "drinking_water",
        "description": "Bica d'água",
        "name": "Fonte Caxambu",
        "id": "node/6496473848"
      },
      "geometry": {
        "type": "Point",
        "coordinates": [
          -51.1803849,
          -27.5670778
        ]
      }
    }
  ]
}
