{
  "type": "FeatureCollection",
  "features": [
    {
      "type": "Feature",
      "id": "node/12010777540",
      "properties": {
        "timestamp": "2024-06-26T00:11:27Z",
        "version": 1,
        "changeset": 153179266,
        "addr:city": "Muriaé",
        "addr:housenumber": "50",
        "addr:postcode": "36880-000",
        "addr:street": "Rua Presidente Artur Bernardes",
        "addr:suburb": "Centro",
        "amenity": "library",
        "name": "Biblioteca Municipal",
        "id": "node/12010777540"
      },
      "geometry": {
        "type": "Point",
        "coordinates": [
          -42.3675935,
          -21.1307913
        ]
      }
    }
  ]
}
