{
  "type": "FeatureCollection",
  "features": [
    {
      "type": "Feature",
      "id": "node/6003249055",
      "properties": {
        "timestamp": "2018-10-21T17:54:51Z",
        "version": 1,
        "changeset": 63734205,
        "historic": "monument",
        "name": "Obelico",
        "id": "node/6003249055"
      },
      "geometry": {
        "type": "Point",
        "coordinates": [
          -42.3545055,
          -21.1302682
        ]
      }
    }
  ]
}
