{
  "type": "FeatureCollection",
  "features": [
    {
      "type": "Feature",
      "id": "node/8636271461",
      "properties": {
        "timestamp": "2021-04-16T18:21:25Z",
        "version": 1,
        "changeset": 103075689,
        "amenity": "library",
        "name": "Biblioteca Pública Municipal Dom Jaime de Barros Câmara",
        "id": "node/8636271461"
      },
      "geometry": {
        "type": "Point",
        "coordinates": [
          -52.9027304,
          -26.9023482
        ]
      }
    }
  ]
}
