{
  "type": "FeatureCollection",
  "features": [
    {
      "type": "Feature",
      "id": "node/3629924237",
      "properties": {
        "timestamp": "2015-07-01T21:19:21Z",
        "version": 1,
        "changeset": 32341706,
        "amenity": "toilets",
        "name": "Banheiro Público",
        "id": "node/3629924237"
      },
      "geometry": {
        "type": "Point",
        "coordinates": [
          -49.6499016,
          -20.6261028
        ]
      }
    }
  ]
}
