{
  "type": "FeatureCollection",
  "features": [
    {
      "type": "Feature",
      "id": "node/6167345238",
      "properties": {
        "timestamp": "2018-12-28T03:06:02Z",
        "version": 1,
        "changeset": 65829955,
        "amenity": "school",
        "name": "EMEF Carlos Gomes",
        "id": "node/6167345238"
      },
      "geometry": {
        "type": "Point",
        "coordinates": [
          -51.5019204,
          -29.3752492
        ]
      }
    },
    {
      "type": "Feature",
      "id": "node/6167355711",
      "properties": {
        "timestamp": "2018-12-28T03:18:36Z",
        "version": 1,
        "changeset": 65830128,
        "amenity": "school",
        "name": "Escola de Ensino Fundamental Senhor do Bom Fim",
        "id": "node/6167355711"
      },
      "geometry": {
        "type": "Point",
        "coordinates": [
          -51.5664192,
          -29.3877998
        ]
      }
    }
  ]
}
