{
  "type": "FeatureCollection",
  "features": [
    {
      "type": "Feature",
      "id": "node/8572213880",
      "properties": {
        "timestamp": "2021-03-29T16:16:57Z",
        "version": 1,
        "changeset": 101928636,
        "addr:city": "Ituiutaba",
        "addr:housenumber": "302",
        "addr:postcode": "38307044",
        "addr:street": "Rua Fernando Vilela de Andrade",
        "addr:suburb": "Platina",
        "name": "Centro de Arte e Cultura Palhaça Marieta",
        "opening_hours": "Mo-Fr 09:00-17:00",
        "opening_hours:covid19": "closed",
        "tourism": "gallery",
        "id": "node/8572213880"
      },
      "geometry": {
        "type": "Point",
        "coordinates": [
          -49.4735763,
          -18.9763663
        ]
      }
    }
  ]
}
