{
  "type": "FeatureCollection",
  "features": [
    {
      "type": "Feature",
      "id": "node/5375761270",
      "properties": {
        "timestamp": "2018-01-31T16:52:05Z",
        "version": 1,
        "changeset": 55939096,
        "addr:postcode": "38300-076",
        "addr:street": "Praça Cônego Ângelo",
        "historic": "monument",
        "inscription": "“Ao Moacir Franco, orgulho de Ituiutaba, o reconhecimento, a gratidão, o carinho e a homenagem dos seus conterrâneos. Ituiutaba,16 de setembro de 1972\".",
        "name": "Estatua Moacir Franco",
        "id": "node/5375761270"
      },
      "geometry": {
        "type": "Point",
        "coordinates": [
          -49.4641175,
          -18.969814
        ]
      }
    },
    {
      "type": "Feature",
      "id": "node/5375761271",
      "properties": {
        "timestamp": "2018-01-31T16:52:05Z",
        "version": 1,
        "changeset": 55939096,
        "addr:city": "Ituiutaba",
        "addr:postcode": "38300-076",
        "addr:street": "Praça Cônego Ângelo",
        "addr:suburb": "Centro",
        "description": "Mosaíco presente na praça Cônego Ângelo",
        "historic": "monument",
        "name": "Mosaíco",
        "id": "node/5375761271"
      },
      "geometry": {
        "type": "Point",
        "coordinates": [
          -49.4638874,
          -18.9706364
        ]
      }
    }
  ]
}
