{
  "type": "FeatureCollection",
  "features": [
    {
      "type": "Feature",
      "id": "node/5644364222",
      "properties": {
        "timestamp": "2018-05-26T18:24:28Z",
        "version": 1,
        "changeset": 59299218,
        "addr:housenumber": "234",
        "addr:street": "Rua Edmundo Bischoff",
        "contact:phone": "+55 55 3261-1848;+55 55 3261-1293;+55 55 99614-1453",
        "contact:website": "https://www.restingaseca.rs.leg.br/",
        "government": "legislative",
        "name": "Câmara de Vereadores Restinga Sêca",
        "office": "government",
        "opening_hours": "Mo-Fr 08:00-12:00, 13:00-17:00",
        "id": "node/5644364222"
      },
      "geometry": {
        "type": "Point",
        "coordinates": [
          -53.3712623,
          -29.8136929
        ]
      }
    }
  ]
}
