{
  "type": "FeatureCollection",
  "features": [
    {
      "type": "Feature",
      "id": "node/6796853685",
      "properties": {
        "timestamp": "2019-09-15T13:03:54Z",
        "version": 1,
        "changeset": 74496240,
        "name": "Hotel tres meninos",
        "tourism": "hotel",
        "id": "node/6796853685"
      },
      "geometry": {
        "type": "Point",
        "coordinates": [
          -47.1744355,
          -24.2911561
        ]
      }
    },
    {
      "type": "Feature",
      "id": "node/6797067786",
      "properties": {
        "timestamp": "2019-09-15T16:00:40Z",
        "version": 1,
        "changeset": 74500019,
        "name": "Hotel Thamy",
        "tourism": "hotel",
        "id": "node/6797067786"
      },
      "geometry": {
        "type": "Point",
        "coordinates": [
          -47.1761259,
          -24.2899451
        ]
      }
    }
  ]
}
