{
  "type": "FeatureCollection",
  "features": [
    {
      "type": "Feature",
      "id": "node/2148101829",
      "properties": {
        "timestamp": "2013-02-09T19:02:22Z",
        "version": 1,
        "changeset": 14971311,
        "name": "Pousada Beira Rio",
        "tourism": "hotel",
        "id": "node/2148101829"
      },
      "geometry": {
        "type": "Point",
        "coordinates": [
          -43.7481912,
          -19.7935246
        ]
      }
    },
    {
      "type": "Feature",
      "id": "node/3770917052",
      "properties": {
        "timestamp": "2015-10-03T19:21:24Z",
        "version": 1,
        "changeset": 34413599,
        "name": "Hotel Solar Corte Real",
        "tourism": "hotel",
        "id": "node/3770917052"
      },
      "geometry": {
        "type": "Point",
        "coordinates": [
          -43.8122005,
          -19.8906599
        ]
      }
    }
  ]
}
