{
  "type": "FeatureCollection",
  "features": [
    {
      "type": "Feature",
      "id": "node/6468695682",
      "properties": {
        "timestamp": "2023-05-02T20:47:32Z",
        "version": 2,
        "changeset": 135633156,
        "addr:city": "São José do Ouro",
        "addr:housenumber": "801",
        "addr:postcode": "99870-000",
        "addr:street": "Avenida Marechal Floriano",
        "addr:suburb": "Centro",
        "amenity": "hospital",
        "email": "araucaria@araucaria.org.br",
        "healthcare": "hospital",
        "name": "Hospital São José",
        "phone": "+55 54 3352 4750",
        "ref:CNES": "2246791",
        "ref:vatin": "BR96704333000413",
        "id": "node/6468695682"
      },
      "geometry": {
        "type": "Point",
        "coordinates": [
          -51.6018113,
          -27.7725526
        ]
      }
    }
  ]
}
