{
  "type": "FeatureCollection",
  "features": [
    {
      "type": "Feature",
      "id": "node/3231853440",
      "properties": {
        "timestamp": "2018-03-12T21:24:34Z",
        "version": 4,
        "changeset": 57125161,
        "building": "office",
        "government": "social_security",
        "name": "Institudo de Previdência do Estado de Santa Catarina",
        "office": "government",
        "short_name": "Iprev",
        "id": "node/3231853440"
      },
      "geometry": {
        "type": "Point",
        "coordinates": [
          -49.6001524,
          -27.4238127
        ]
      }
    }
  ]
}
