{
  "type": "FeatureCollection",
  "features": [
    {
      "type": "Feature",
      "id": "node/3786061857",
      "properties": {
        "timestamp": "2015-10-14T12:24:04Z",
        "version": 1,
        "changeset": 34632037,
        "name": "Pousada",
        "tourism": "hotel",
        "id": "node/3786061857"
      },
      "geometry": {
        "type": "Point",
        "coordinates": [
          -44.4174714,
          -18.7516232
        ]
      }
    },
    {
      "type": "Feature",
      "id": "node/4559368392",
      "properties": {
        "timestamp": "2016-12-18T03:18:35Z",
        "version": 1,
        "changeset": 44482681,
        "addr:postcode": "35790-000",
        "addr:street": "Avenida Dom Pedro II, 165 - Centro",
        "name": "Hotel Bandeirante",
        "phone": "+55 38 3721-3099",
        "tourism": "hotel",
        "id": "node/4559368392"
      },
      "geometry": {
        "type": "Point",
        "coordinates": [
          -44.4285247,
          -18.7515085
        ]
      }
    }
  ]
}
