{
  "type": "FeatureCollection",
  "features": [
    {
      "type": "Feature",
      "id": "node/10870694398",
      "properties": {
        "timestamp": "2023-09-10T14:15:34Z",
        "version": 3,
        "changeset": 141065334,
        "addr:city": "Limeira do Oeste",
        "addr:housenumber": "236",
        "addr:postcode": "38295-000",
        "addr:street": "Avenida Minas Gerais",
        "addr:suburb": "Jardim Bela Vista",
        "mobile": "+55 34 99884 2748",
        "name": "Morais Bike, Cantinho Doce",
        "opening_hours": "Mo-Sa 08:00-18:00; PH off",
        "payment:cash": "yes",
        "payment:credit_cards": "yes",
        "payment:debit_cards": "yes",
        "service:bicycle:pump": "yes",
        "shop": "bicycle",
        "website": "https://www.instagram.com/cantinho_doce_muriell/?igshid=j15t9egy30ih",
        "id": "node/10870694398"
      },
      "geometry": {
        "type": "Point",
        "coordinates": [
          -50.5832416,
          -19.5510475
        ]
      }
    },
    {
      "type": "Feature",
      "id": "node/10962603368",
      "properties": {
        "timestamp": "2023-06-08T00:09:44Z",
        "version": 1,
        "changeset": 137075036,
        "addr:city": "Limeira do Oeste",
        "addr:housenumber": "977",
        "addr:postcode": "38295000",
        "addr:street": "Rua São Paulo",
        "addr:suburb": "Centro",
        "name": "Bicicletaria do Verdura",
        "opening_hours": "Mo-Su 09:00-17:00",
        "operator": "Verdura",
        "payment:cash": "yes",
        "phone": "+55 34 99693-0269",
        "shop": "bicycle",
        "id": "node/10962603368"
      },
      "geometry": {
        "type": "Point",
        "coordinates": [
          -50.5770662,
          -19.551429
        ]
      }
    },
    {
      "type": "Feature",
      "id": "node/10992902670",
      "properties": {
        "timestamp": "2023-06-20T22:16:44Z",
        "version": 1,
        "changeset": 137580846,
        "addr:city": "Limeira do Oeste",
        "addr:postcode": "38295000",
        "addr:street": "Avenida da Saudade",
        "addr:suburb": "Centro",
        "name": "MB Motos e Bicicletas",
        "opening_hours": "Mo-Su 09:00-17:00+",
        "operator": "Alcione Fernandes",
        "payment:cash": "yes",
        "phone": "+55 34 99996-2532",
        "shop": "bicycle",
        "id": "node/10992902670"
      },
      "geometry": {
        "type": "Point",
        "coordinates": [
          -50.5769668,
          -19.5521472
        ]
      }
    },
    {
      "type": "Feature",
      "id": "node/11020000558",
      "properties": {
        "timestamp": "2023-07-02T13:09:01Z",
        "version": 1,
        "changeset": 138023174,
        "addr:city": "Limeira do Oeste",
        "addr:housenumber": "764",
        "addr:postcode": "38295000",
        "addr:street": "Rua Canadá",
        "addr:suburb": "São João",
        "name": "Bicicletaria do Irmão",
        "opening_hours": "Mo-Su 08:00-17:00",
        "payment:cash": "yes",
        "payment:credit_cards": "yes",
        "phone": "+55 34 99997-0615",
        "service:bicycle:repair": "yes",
        "shop": "bicycle",
        "id": "node/11020000558"
      },
      "geometry": {
        "type": "Point",
        "coordinates": [
          -50.5830223,
          -19.549299
        ]
      }
    }
  ]
}
