{
  "type": "FeatureCollection",
  "features": [
    {
      "type": "Feature",
      "id": "node/2493342350",
      "properties": {
        "timestamp": "2013-10-12T03:22:00Z",
        "version": 1,
        "changeset": 18307841,
        "waterway": "waterfall",
        "id": "node/2493342350"
      },
      "geometry": {
        "type": "Point",
        "coordinates": [
          -50.6932349,
          -19.2176328
        ]
      }
    },
    {
      "type": "Feature",
      "id": "node/2493342379",
      "properties": {
        "timestamp": "2013-10-12T03:22:00Z",
        "version": 1,
        "changeset": 18307841,
        "waterway": "waterfall",
        "id": "node/2493342379"
      },
      "geometry": {
        "type": "Point",
        "coordinates": [
          -50.693435,
          -19.2180213
        ]
      }
    },
    {
      "type": "Feature",
      "id": "node/2493342383",
      "properties": {
        "timestamp": "2023-05-03T15:01:05Z",
        "version": 2,
        "changeset": 135664973,
        "name": "Cachoeira do Salto de São Domingos 3",
        "waterway": "waterfall",
        "id": "node/2493342383"
      },
      "geometry": {
        "type": "Point",
        "coordinates": [
          -50.6885482,
          -19.2181146
        ]
      }
    },
    {
      "type": "Feature",
      "id": "node/2493342441",
      "properties": {
        "timestamp": "2023-05-03T15:01:05Z",
        "version": 2,
        "changeset": 135664973,
        "name": "Cachoeira do Salto de São Domingos 2",
        "waterway": "waterfall",
        "id": "node/2493342441"
      },
      "geometry": {
        "type": "Point",
        "coordinates": [
          -50.686959,
          -19.2192374
        ]
      }
    },
    {
      "type": "Feature",
      "id": "node/2493342469",
      "properties": {
        "timestamp": "2023-05-03T15:01:05Z",
        "version": 2,
        "changeset": 135664973,
        "name": "Cachoeira do Salto de São Domingos 1",
        "waterway": "waterfall",
        "id": "node/2493342469"
      },
      "geometry": {
        "type": "Point",
        "coordinates": [
          -50.6858152,
          -19.2195047
        ]
      }
    }
  ]
}
