{
  "type": "FeatureCollection",
  "features": [
    {
      "type": "Feature",
      "id": "node/10095698689",
      "properties": {
        "timestamp": "2022-10-12T16:06:54Z",
        "version": 1,
        "changeset": 127425012,
        "amenity": "doctors",
        "healthcare": "doctor",
        "name": "Policlínica de Taperoá",
        "source": "survey",
        "id": "node/10095698689"
      },
      "geometry": {
        "type": "Point",
        "coordinates": [
          -36.825911,
          -7.2052342
        ]
      }
    }
  ]
}
