{
  "type": "FeatureCollection",
  "features": [
    {
      "type": "Feature",
      "id": "node/5335470821",
      "properties": {
        "timestamp": "2020-03-26T23:09:17Z",
        "version": 2,
        "changeset": 82685773,
        "name": "Mãe Joaninha",
        "tourism": "guest_house",
        "id": "node/5335470821"
      },
      "geometry": {
        "type": "Point",
        "coordinates": [
          -36.8239316,
          -7.205677
        ]
      }
    },
    {
      "type": "Feature",
      "id": "node/5595416523",
      "properties": {
        "timestamp": "2022-03-19T18:35:59Z",
        "version": 2,
        "changeset": 118675663,
        "name": "Pousada Leão",
        "tourism": "guest_house",
        "id": "node/5595416523"
      },
      "geometry": {
        "type": "Point",
        "coordinates": [
          -36.8228918,
          -7.1956326
        ]
      }
    },
    {
      "type": "Feature",
      "id": "node/9472884334",
      "properties": {
        "timestamp": "2022-02-03T23:46:36Z",
        "version": 1,
        "changeset": 116983961,
        "source": "survey",
        "tourism": "guest_house",
        "id": "node/9472884334"
      },
      "geometry": {
        "type": "Point",
        "coordinates": [
          -36.8248898,
          -7.212383
        ]
      }
    },
    {
      "type": "Feature",
      "id": "node/9579233634",
      "properties": {
        "timestamp": "2022-03-14T20:57:09Z",
        "version": 1,
        "changeset": 118485993,
        "name": "Pousada de Edjane",
        "source": "survey",
        "tourism": "guest_house",
        "id": "node/9579233634"
      },
      "geometry": {
        "type": "Point",
        "coordinates": [
          -36.8254101,
          -7.212103
        ]
      }
    },
    {
      "type": "Feature",
      "id": "node/11136563505",
      "properties": {
        "timestamp": "2023-08-22T15:53:46Z",
        "version": 1,
        "changeset": 140235946,
        "name": "Wind Pousada",
        "tourism": "guest_house",
        "id": "node/11136563505"
      },
      "geometry": {
        "type": "Point",
        "coordinates": [
          -36.8249928,
          -7.2130554
        ]
      }
    }
  ]
}
