{
  "type": "FeatureCollection",
  "features": [
    {
      "type": "Feature",
      "id": "node/12492057161",
      "properties": {
        "timestamp": "2025-01-11T10:53:32Z",
        "version": 1,
        "changeset": 161234347,
        "addr:city": "Berizal",
        "addr:housenumber": "812",
        "addr:postcode": "39555-000",
        "addr:street": "Rua Santa Cruz",
        "addr:suburb": "Planalto",
        "amenity": "clinic",
        "healthcare": "clinic",
        "healthcare:speciality": "general",
        "name": "Centro Municipal de Saúde Manoel Alves do Nascimento",
        "operator": "Município de Berizal",
        "operator:type": "public",
        "id": "node/12492057161"
      },
      "geometry": {
        "type": "Point",
        "coordinates": [
          -41.7373929,
          -15.6076412
        ]
      }
    }
  ]
}
