{
  "type": "FeatureCollection",
  "features": [
    {
      "type": "Feature",
      "id": "node/6612061997",
      "properties": {
        "timestamp": "2019-07-13T18:22:25Z",
        "version": 1,
        "changeset": 72215889,
        "access": "yes",
        "amenity": "bicycle_parking",
        "name": "praca dito bike",
        "id": "node/6612061997"
      },
      "geometry": {
        "type": "Point",
        "coordinates": [
          -54.3358394,
          -15.5218306
        ]
      }
    }
  ]
}
