{
  "type": "FeatureCollection",
  "features": [
    {
      "type": "Feature",
      "id": "node/4649967010",
      "properties": {
        "timestamp": "2023-04-24T05:46:15Z",
        "version": 3,
        "changeset": 135285149,
        "addr:housenumber": "105",
        "addr:postcode": "98570-000",
        "addr:street": "Rua Hermógenes Pahins",
        "addr:suburb": "Centro",
        "amenity": "hospital",
        "email": "hospitalcamponovo@hotmail.com",
        "fax": "+55 55 3528 1414",
        "healthcare": "hospital",
        "name": "Associacao Hospitalar de Caridade de Campo Novo",
        "phone": "+55 55 3528 1200",
        "ref:CNES": "2261154",
        "ref:vatin": "BR90167107000111",
        "id": "node/4649967010"
      },
      "geometry": {
        "type": "Point",
        "coordinates": [
          -53.8072397,
          -27.6840251
        ]
      }
    }
  ]
}
