{
  "type": "FeatureCollection",
  "features": [
    {
      "type": "Feature",
      "id": "node/4545001512",
      "properties": {
        "timestamp": "2016-12-08T15:10:44Z",
        "version": 1,
        "changeset": 44260086,
        "tourism": "guest_house",
        "id": "node/4545001512"
      },
      "geometry": {
        "type": "Point",
        "coordinates": [
          -43.0279456,
          -22.8125388
        ]
      }
    },
    {
      "type": "Feature",
      "id": "node/4953689021",
      "properties": {
        "timestamp": "2017-07-05T21:59:39Z",
        "version": 1,
        "changeset": 50069724,
        "name": "Casa",
        "name:pt": "Casa",
        "tourism": "guest_house",
        "id": "node/4953689021"
      },
      "geometry": {
        "type": "Point",
        "coordinates": [
          -43.0032239,
          -22.7970911
        ]
      }
    }
  ]
}
