{
  "type": "FeatureCollection",
  "features": [
    {
      "type": "Feature",
      "id": "node/3491745297",
      "properties": {
        "timestamp": "2022-02-27T19:24:08Z",
        "version": 3,
        "changeset": 117919604,
        "name": "Cachoeira dos Pretos",
        "tourism": "attraction",
        "waterway": "waterfall",
        "id": "node/3491745297"
      },
      "geometry": {
        "type": "Point",
        "coordinates": [
          -46.1703264,
          -22.9677528
        ]
      }
    },
    {
      "type": "Feature",
      "id": "node/10959447191",
      "properties": {
        "timestamp": "2023-12-04T01:05:15Z",
        "version": 2,
        "changeset": 144736848,
        "height": "1170",
        "name": "Hiponina",
        "waterway": "waterfall",
        "id": "node/10959447191"
      },
      "geometry": {
        "type": "Point",
        "coordinates": [
          -46.1142232,
          -22.9657394
        ]
      }
    },
    {
      "type": "Feature",
      "id": "node/12496785623",
      "properties": {
        "timestamp": "2025-01-12T20:25:12Z",
        "version": 1,
        "changeset": 161286617,
        "waterway": "waterfall",
        "id": "node/12496785623"
      },
      "geometry": {
        "type": "Point",
        "coordinates": [
          -46.0598749,
          -22.9161096
        ]
      }
    },
    {
      "type": "Feature",
      "id": "node/12496786413",
      "properties": {
        "timestamp": "2025-01-12T20:25:12Z",
        "version": 1,
        "changeset": 161286617,
        "waterway": "waterfall",
        "id": "node/12496786413"
      },
      "geometry": {
        "type": "Point",
        "coordinates": [
          -46.0612321,
          -22.9185109
        ]
      }
    },
    {
      "type": "Feature",
      "id": "node/12496786536",
      "properties": {
        "timestamp": "2025-01-12T20:25:12Z",
        "version": 1,
        "changeset": 161286617,
        "waterway": "waterfall",
        "id": "node/12496786536"
      },
      "geometry": {
        "type": "Point",
        "coordinates": [
          -46.0685813,
          -22.9052142
        ]
      }
    }
  ]
}
