{
  "type": "FeatureCollection",
  "features": [
    {
      "type": "Feature",
      "id": "node/3949084482",
      "properties": {
        "timestamp": "2016-01-15T23:50:36Z",
        "version": 1,
        "changeset": 36606579,
        "amenity": "hospital",
        "name": "Centro de Saúde",
        "id": "node/3949084482"
      },
      "geometry": {
        "type": "Point",
        "coordinates": [
          -39.4285803,
          -3.9425315
        ]
      }
    }
  ]
}
