{
  "type": "FeatureCollection",
  "features": [
    {
      "type": "Feature",
      "id": "node/4286923698",
      "properties": {
        "timestamp": "2021-07-01T18:24:06Z",
        "version": 4,
        "changeset": 107274521,
        "addr:housenumber": "600",
        "addr:postcode": "69345-000",
        "addr:street": "Rua Parima",
        "amenity": "dentist",
        "email": "flaviogaldinomoura@hotmail.com",
        "healthcare": "dentist",
        "name": "Consultório Odontologico Doutor Flávio Moura",
        "opening_hours": "24/7",
        "phone": "+5595991246456",
        "id": "node/4286923698"
      },
      "geometry": {
        "type": "Point",
        "coordinates": [
          -61.1457216,
          4.476612
        ]
      }
    }
  ]
}
