{
  "type": "FeatureCollection",
  "features": [
    {
      "type": "Feature",
      "id": "node/8636267132",
      "properties": {
        "timestamp": "2021-04-16T18:17:48Z",
        "version": 1,
        "changeset": 103075689,
        "amenity": "library",
        "name": "Biblioteca Pública Municipal de Anitápolis",
        "id": "node/8636267132"
      },
      "geometry": {
        "type": "Point",
        "coordinates": [
          -49.1301825,
          -27.9034432
        ]
      }
    }
  ]
}
