{
  "type": "FeatureCollection",
  "features": [
    {
      "type": "Feature",
      "id": "node/5575518036",
      "properties": {
        "timestamp": "2023-02-10T03:57:50Z",
        "version": 4,
        "changeset": 132337606,
        "description": "Monumento comemorativo a 50 anos de existência do Lions Clube de Itaperuna.",
        "historic": "monument",
        "inscription": "Cinquentenário do Lions Clube de Itaperuna 1960-2010",
        "name": "Monumento Lions Clube",
        "id": "node/5575518036"
      },
      "geometry": {
        "type": "Point",
        "coordinates": [
          -41.9060391,
          -21.2001773
        ]
      }
    },
    {
      "type": "Feature",
      "id": "node/5577533799",
      "properties": {
        "timestamp": "2024-05-03T10:01:57Z",
        "version": 5,
        "changeset": 150828526,
        "description": "Estátua dedicada à Cláudio Cerqueira Bastos, o (já falecido) famoso ex-prefeito da cidade de Itaperuna.",
        "historic": "monument",
        "name": "Estátua de Cláudio Cerqueira Bastos",
        "id": "node/5577533799"
      },
      "geometry": {
        "type": "Point",
        "coordinates": [
          -41.8921505,
          -21.2054339
        ]
      }
    },
    {
      "type": "Feature",
      "id": "node/5581696156",
      "properties": {
        "timestamp": "2018-04-27T04:00:08Z",
        "version": 1,
        "changeset": 58463102,
        "description": "A estátua, inaugurada em 1966, possui 20 metros de altura.",
        "historic": "monument",
        "name": "Monumento ao Cristo Redentor",
        "phone": "22 3824 6297",
        "tourism": "attraction",
        "website": "http://mapadecultura.rj.gov.br/manchete/monumento-ao-cristo-redentor-2",
        "id": "node/5581696156"
      },
      "geometry": {
        "type": "Point",
        "coordinates": [
          -41.8819005,
          -21.2010917
        ]
      }
    }
  ]
}
