{
  "type": "FeatureCollection",
  "features": [
    {
      "type": "Feature",
      "id": "node/8626335412",
      "properties": {
        "timestamp": "2021-04-13T16:00:38Z",
        "version": 1,
        "changeset": 102875428,
        "amenity": "hospital",
        "name": "Hospital São Donato Içara",
        "id": "node/8626335412"
      },
      "geometry": {
        "type": "Point",
        "coordinates": [
          -49.301251,
          -28.7172074
        ]
      }
    }
  ]
}
