{
  "type": "FeatureCollection",
  "features": [
    {
      "type": "Feature",
      "id": "node/8636271321",
      "properties": {
        "timestamp": "2021-04-16T18:17:16Z",
        "version": 1,
        "changeset": 103075689,
        "amenity": "library",
        "name": "Biblioteca Pública Municipal Cruz e Sousa",
        "id": "node/8636271321"
      },
      "geometry": {
        "type": "Point",
        "coordinates": [
          -49.3092121,
          -28.713702
        ]
      }
    }
  ]
}
