{
  "type": "FeatureCollection",
  "features": [
    {
      "type": "Feature",
      "id": "node/12530028266",
      "properties": {
        "timestamp": "2025-01-24T20:03:19Z",
        "version": 1,
        "changeset": 161726496,
        "amenity": "library",
        "name": "Biblioteca e Anexo I",
        "id": "node/12530028266"
      },
      "geometry": {
        "type": "Point",
        "coordinates": [
          -40.5375161,
          -11.1833289
        ]
      }
    }
  ]
}
