{
  "type": "FeatureCollection",
  "features": [
    {
      "type": "Feature",
      "id": "node/12331354746",
      "properties": {
        "timestamp": "2025-03-13T21:19:19Z",
        "version": 2,
        "changeset": 163588765,
        "addr:city": "Areal",
        "addr:housenumber": "200",
        "addr:postcode": "25845-000",
        "addr:street": "Rua Manoel Fernandes",
        "addr:suburb": "Centro",
        "name": "Louros Bike",
        "opening_hours": "Mo-Sa 08:00-18:00",
        "payment:app": "yes",
        "payment:cash": "yes",
        "payment:pix": "yes",
        "phone": "024 98833-2870",
        "service:bicycle:cleaning": "yes",
        "service:bicycle:mtb": "yes",
        "service:bicycle:pump": "yes",
        "service:bicycle:repair": "yes",
        "service:bicycle:service": "yes",
        "service:bicycle:tools": "yes",
        "shop": "bicycle",
        "stroller": "no",
        "wheelchair": "no",
        "id": "node/12331354746"
      },
      "geometry": {
        "type": "Point",
        "coordinates": [
          -43.1014216,
          -22.233949
        ]
      }
    },
    {
      "type": "Feature",
      "id": "node/12660913069",
      "properties": {
        "timestamp": "2025-03-13T21:19:19Z",
        "version": 1,
        "changeset": 163588765,
        "addr:city": "Areal",
        "addr:housenumber": "549",
        "addr:postcode": "25845-000",
        "addr:street": "Praça Presidente Castelo Branco",
        "addr:suburb": "Centro",
        "level": "0",
        "name": "JF BIKESHOP",
        "payment:cash": "yes",
        "payment:credit_cards": "yes",
        "payment:debit_cards": "yes",
        "payment:pix": "yes",
        "phone": "024 99225-6166",
        "ref:vatin": "34.057.252/0001-79",
        "service:bicycle:repair": "yes",
        "service:bicycle:sales": "yes",
        "service:bicycle:tools": "yes",
        "shop": "bicycle",
        "wheelchair": "yes",
        "id": "node/12660913069"
      },
      "geometry": {
        "type": "Point",
        "coordinates": [
          -43.1021445,
          -22.2359627
        ]
      }
    }
  ]
}
