{
  "type": "FeatureCollection",
  "features": [
    {
      "type": "Feature",
      "id": "node/12331354746",
      "properties": {
        "timestamp": "2024-11-11T17:11:11Z",
        "version": 1,
        "changeset": 159018101,
        "addr:city": "Areal",
        "addr:housenumber": "200",
        "addr:postcode": "25845-000",
        "addr:street": "Rua Manoel Fernandes",
        "addr:suburb": "Centro",
        "name": "Louros Bike",
        "opening_hours": "Mo-Sa 08:00-18:00",
        "payment:app": "yes",
        "payment:cash": "yes",
        "payment:pix": "yes",
        "phone": "24 98833-2870",
        "service:bicycle:cleaning": "yes",
        "service:bicycle:mtb": "yes",
        "service:bicycle:pump": "yes",
        "service:bicycle:repair": "yes",
        "service:bicycle:service": "yes",
        "service:bicycle:tools": "yes",
        "shop": "bicycle",
        "stroller": "no",
        "wheelchair": "no",
        "id": "node/12331354746"
      },
      "geometry": {
        "type": "Point",
        "coordinates": [
          -43.1014216,
          -22.233949
        ]
      }
    }
  ]
}
