{
  "type": "FeatureCollection",
  "features": [
    {
      "type": "Feature",
      "id": "node/5181958279",
      "properties": {
        "timestamp": "2024-12-07T20:35:45Z",
        "version": 2,
        "changeset": 160039017,
        "government": "register_office",
        "name": "Cartório Oficio Único de Areal",
        "office": "government",
        "id": "node/5181958279"
      },
      "geometry": {
        "type": "Point",
        "coordinates": [
          -43.1020894,
          -22.2350832
        ]
      }
    }
  ]
}
