{
  "type": "FeatureCollection",
  "features": [
    {
      "type": "Feature",
      "id": "node/4616827940",
      "properties": {
        "timestamp": "2017-01-18T19:56:20Z",
        "version": 1,
        "changeset": 45280010,
        "name": "Hotel Cidade Nova",
        "tourism": "hotel",
        "id": "node/4616827940"
      },
      "geometry": {
        "type": "Point",
        "coordinates": [
          -52.3729485,
          -30.18811
        ]
      }
    }
  ]
}
