{
  "type": "FeatureCollection",
  "features": [
    {
      "type": "Feature",
      "id": "node/3613508250",
      "properties": {
        "timestamp": "2015-06-23T20:52:53Z",
        "version": 1,
        "changeset": 32170786,
        "addr:city": "Nova Granada",
        "addr:street": "Rua José Barone Mercadante",
        "amenity": "library",
        "name": "Biblioteca Municipal",
        "id": "node/3613508250"
      },
      "geometry": {
        "type": "Point",
        "coordinates": [
          -49.3153448,
          -20.5331656
        ]
      }
    }
  ]
}
