{
  "type": "FeatureCollection",
  "features": [
    {
      "type": "Feature",
      "id": "node/7179748687",
      "properties": {
        "timestamp": "2020-02-02T20:43:08Z",
        "version": 1,
        "changeset": 80446206,
        "addr:housenumber": "442",
        "addr:street": "Avenida Bento Munhoz da Rocha Neto",
        "name": "Antares",
        "tourism": "hotel",
        "id": "node/7179748687"
      },
      "geometry": {
        "type": "Point",
        "coordinates": [
          -51.989191,
          -26.4943563
        ]
      }
    }
  ]
}
