{
  "type": "FeatureCollection",
  "features": [
    {
      "type": "Feature",
      "id": "node/2748273597",
      "properties": {
        "timestamp": "2014-03-27T23:59:16Z",
        "version": 2,
        "changeset": 21355702,
        "amenity": "arts_centre",
        "name": "Sociedade Caravel de Esporte, Recreação e Cultura",
        "id": "node/2748273597"
      },
      "geometry": {
        "type": "Point",
        "coordinates": [
          -53.5204144,
          -29.6668981
        ]
      }
    },
    {
      "type": "Feature",
      "id": "node/2748722755",
      "properties": {
        "timestamp": "2014-03-27T23:59:14Z",
        "version": 1,
        "changeset": 21355702,
        "addr:postcode": "97235-000",
        "amenity": "arts_centre",
        "name": "Sociedade Agrícola, Cultural e Esportiva Vale Veneto",
        "short_name": "SACE Vale Vêneto",
        "id": "node/2748722755"
      },
      "geometry": {
        "type": "Point",
        "coordinates": [
          -53.5281768,
          -29.6539612
        ]
      }
    }
  ]
}
