{
  "type": "FeatureCollection",
  "features": [
    {
      "type": "Feature",
      "id": "node/3999139453",
      "properties": {
        "timestamp": "2016-02-10T13:37:17Z",
        "version": 1,
        "changeset": 37124622,
        "addr:city": "Montanha",
        "addr:postcode": "29890-000",
        "addr:street": "Rua Conceição da Barra",
        "addr:suburb": "Decão",
        "alt_name": "Centro de Referência de Assistência Social",
        "amenity": "social_facility",
        "contact:phone": "(27) 3754-1373/3754-2269",
        "name": "CRAS - Montanha",
        "social_facility": "outreach",
        "source": "IJSN",
        "id": "node/3999139453"
      },
      "geometry": {
        "type": "Point",
        "coordinates": [
          -40.3680392,
          -18.1311223
        ]
      }
    },
    {
      "type": "Feature",
      "id": "node/9396503514",
      "properties": {
        "timestamp": "2023-01-15T14:16:39Z",
        "version": 2,
        "changeset": 131299990,
        "addr:city": "Montanha",
        "addr:postcode": "29890-000",
        "addr:street": "Rua Anchieta",
        "addr:suburb": "Centro",
        "amenity": "social_facility",
        "name": "Apae - Associação de Pais e Amigos dos Excepcionais",
        "operator": "Associação de Pais e Amigos dos Excepcionais",
        "operator:type": "private",
        "social_facility": "assisted_living",
        "id": "node/9396503514"
      },
      "geometry": {
        "type": "Point",
        "coordinates": [
          -40.3619204,
          -18.125759
        ]
      }
    }
  ]
}
