{
  "type": "FeatureCollection",
  "features": [
    {
      "type": "Feature",
      "id": "node/4960995082",
      "properties": {
        "timestamp": "2017-08-01T11:49:43Z",
        "version": 2,
        "changeset": 50750708,
        "amenity": "drinking_water",
        "name": "Chafariz",
        "id": "node/4960995082"
      },
      "geometry": {
        "type": "Point",
        "coordinates": [
          -47.2229359,
          -23.0855681
        ]
      }
    },
    {
      "type": "Feature",
      "id": "node/4961794495",
      "properties": {
        "timestamp": "2017-07-10T12:35:57Z",
        "version": 1,
        "changeset": 50175461,
        "amenity": "drinking_water",
        "name": "Bica",
        "id": "node/4961794495"
      },
      "geometry": {
        "type": "Point",
        "coordinates": [
          -47.2342614,
          -23.1156594
        ]
      }
    }
  ]
}
