{
  "type": "FeatureCollection",
  "features": [
    {
      "type": "Feature",
      "id": "node/5283841374",
      "properties": {
        "timestamp": "2017-12-14T12:14:39Z",
        "version": 1,
        "changeset": 54622676,
        "addr:city": "Tanguá",
        "addr:postcode": "24890000",
        "addr:street": "Avenida Prefeito João Batista Caffaro",
        "addr:suburb": "Vila Cortes",
        "amenity": "pharmacy",
        "healthcare": "pharmacy",
        "name": "Farma Cortes",
        "id": "node/5283841374"
      },
      "geometry": {
        "type": "Point",
        "coordinates": [
          -42.7169175,
          -22.726811
        ]
      }
    }
  ]
}
