{
  "type": "FeatureCollection",
  "features": [
    {
      "type": "Feature",
      "id": "node/3552697715",
      "properties": {
        "timestamp": "2018-07-21T21:00:02Z",
        "version": 2,
        "changeset": 60939469,
        "contact:website": "http://www.campodozinco.com.br/",
        "name": "Pousada Campo do Zinco",
        "tourism": "guest_house",
        "id": "node/3552697715"
      },
      "geometry": {
        "type": "Point",
        "coordinates": [
          -49.4886568,
          -26.902853
        ]
      }
    }
  ]
}
