{
  "type": "FeatureCollection",
  "features": [
    {
      "type": "Feature",
      "id": "node/7518860375",
      "properties": {
        "timestamp": "2022-09-16T22:58:57Z",
        "version": 2,
        "changeset": 126280544,
        "historic": "monument",
        "name": "Sesquicentenário de Itajaí",
        "id": "node/7518860375"
      },
      "geometry": {
        "type": "Point",
        "coordinates": [
          -48.6504489,
          -26.9193221
        ]
      }
    }
  ]
}
