{
  "type": "FeatureCollection",
  "features": [
    {
      "type": "Feature",
      "id": "node/7518860375",
      "properties": {
        "timestamp": "2022-09-16T22:58:57Z",
        "version": 2,
        "changeset": 126280544,
        "historic": "monument",
        "name": "Sesquicentenário de Itajaí",
        "id": "node/7518860375"
      },
      "geometry": {
        "type": "Point",
        "coordinates": [
          -48.6504489,
          -26.9193221
        ]
      }
    },
    {
      "type": "Feature",
      "id": "node/12461667207",
      "properties": {
        "timestamp": "2024-12-29T21:15:54Z",
        "version": 1,
        "changeset": 160768236,
        "historic": "monument",
        "name": "Monumento Lauro Muller",
        "id": "node/12461667207"
      },
      "geometry": {
        "type": "Point",
        "coordinates": [
          -48.6556708,
          -26.9048506
        ]
      }
    },
    {
      "type": "Feature",
      "id": "node/12461667208",
      "properties": {
        "timestamp": "2024-12-29T21:15:54Z",
        "version": 1,
        "changeset": 160768236,
        "historic": "monument",
        "name": "Monumento Marco Zero",
        "id": "node/12461667208"
      },
      "geometry": {
        "type": "Point",
        "coordinates": [
          -48.655286,
          -26.9046882
        ]
      }
    }
  ]
}
