{
  "type": "FeatureCollection",
  "features": [
    {
      "type": "Feature",
      "id": "node/12618199653",
      "properties": {
        "timestamp": "2025-02-25T13:30:29Z",
        "version": 1,
        "changeset": 162932471,
        "addr:city": "Araucária",
        "addr:housenumber": "97",
        "addr:postcode": "83702-185",
        "addr:street": "Avenida Archelau de Almeida Torres",
        "addr:suburb": "Centro",
        "amenity": "dentist",
        "currency:BRL": "yes",
        "currency:XBT": "yes",
        "description": "Clínica Odontológica especializada localizada no centro da cidade a mais de 20 anos. Drª Regina Célia de Oliveira (ortodontista), Drª Natasha Cristina de Oliveira da Silva ( Dentistica e endodontista) e Dr Kauan Marcel Oliveira da Silva (Implanto, prótese",
        "healthcare": "dentist",
        "mobile": "55 41 985248420",
        "name": "O.S. Odontologia",
        "opening_hours": "Mo-Fr 09:00-18:00",
        "operator": "@brP2Pcripto",
        "payment:coinos": "yes",
        "payment:cryptocurrencies": "yes",
        "payment:lightning": "yes",
        "payment:lightning_contactless": "yes",
        "payment:onchain": "yes",
        "id": "node/12618199653"
      },
      "geometry": {
        "type": "Point",
        "coordinates": [
          -49.4003814,
          -25.5891593
        ]
      }
    }
  ]
}
