{
  "type": "FeatureCollection",
  "features": [
    {
      "type": "Feature",
      "id": "node/3581005494",
      "properties": {
        "timestamp": "2018-05-27T00:05:13Z",
        "version": 3,
        "changeset": 59303857,
        "name": "Pousada Parintins",
        "tourism": "guest_house",
        "id": "node/3581005494"
      },
      "geometry": {
        "type": "Point",
        "coordinates": [
          -56.7289159,
          -2.6217469
        ]
      }
    }
  ]
}
