{
  "type": "FeatureCollection",
  "features": [
    {
      "type": "Feature",
      "id": "node/8828400510",
      "properties": {
        "timestamp": "2021-06-13T00:03:09Z",
        "version": 1,
        "changeset": 106268586,
        "government": "social_welfare",
        "name": "INSS",
        "office": "government",
        "id": "node/8828400510"
      },
      "geometry": {
        "type": "Point",
        "coordinates": [
          -39.6209952,
          -10.9814347
        ]
      }
    }
  ]
}
