{
  "type": "FeatureCollection",
  "features": [
    {
      "type": "Feature",
      "id": "node/11132232433",
      "properties": {
        "timestamp": "2023-08-20T15:18:44Z",
        "version": 1,
        "changeset": 140138727,
        "contact:facebook": "culturajoacaba",
        "name": "Casa da Cultura Rogério Sganzerla",
        "tourism": "gallery",
        "id": "node/11132232433"
      },
      "geometry": {
        "type": "Point",
        "coordinates": [
          -51.5060923,
          -27.172538
        ]
      }
    }
  ]
}
