{
  "type": "FeatureCollection",
  "features": [
    {
      "type": "Feature",
      "id": "node/11057340747",
      "properties": {
        "timestamp": "2023-07-20T20:12:29Z",
        "version": 2,
        "changeset": 138782731,
        "addr:city": "Joaçaba",
        "addr:door": "Sala t_02",
        "addr:housenumber": "537",
        "addr:postcode": "89600-000",
        "addr:street": "Rua Duque de Caxias",
        "addr:suburb": "Centro",
        "amenity": "veterinary",
        "emergency": "yes",
        "mobile": "+55 49 99838-1211",
        "name": "Vitalia - Medicina Felina",
        "operator": "Vitalia - Medicina Felina",
        "operator:type": "private",
        "id": "node/11057340747"
      },
      "geometry": {
        "type": "Point",
        "coordinates": [
          -51.5104358,
          -27.1739249
        ]
      }
    }
  ]
}
