{
  "type": "FeatureCollection",
  "features": [
    {
      "type": "Feature",
      "id": "node/8567721237",
      "properties": {
        "timestamp": "2021-03-27T19:25:40Z",
        "version": 1,
        "changeset": 101851285,
        "addr:city": "Matões",
        "addr:postcode": "65645-000",
        "addr:street": "Rodovia MA-262",
        "addr:suburb": "Residencial Nova Matões",
        "amenity": "university",
        "name": "IEMA - Instituto Estadual de Educação Ciência e Tecnologia do Maranhão",
        "phone": "+55 99 9 9985 0075",
        "id": "node/8567721237"
      },
      "geometry": {
        "type": "Point",
        "coordinates": [
          -43.1976588,
          -5.5438521
        ]
      }
    }
  ]
}
