{
  "type": "FeatureCollection",
  "features": [
    {
      "type": "Feature",
      "id": "node/4786872356",
      "properties": {
        "timestamp": "2017-04-10T18:36:23Z",
        "version": 1,
        "changeset": 47634767,
        "addr:city": "Jaguariúna",
        "addr:housenumber": "205",
        "addr:postcode": "13820000",
        "addr:street": "Rua Joaquim Pinto de Andrade",
        "addr:suburb": "Jardim Botânico",
        "amenity": "veterinary",
        "name": "Ohara Clínica Veterinária",
        "id": "node/4786872356"
      },
      "geometry": {
        "type": "Point",
        "coordinates": [
          -46.9839405,
          -22.7123241
        ]
      }
    },
    {
      "type": "Feature",
      "id": "node/10211823117",
      "properties": {
        "timestamp": "2022-11-23T11:59:12Z",
        "version": 2,
        "changeset": 129279161,
        "addr:housenumber": "136",
        "addr:street": "Rua Doutor João R Pires Bueno",
        "amenity": "veterinary",
        "name": "Centro Veterinário 7 Vidas",
        "opening_hours": "Mo-Fr 09:00-18:00; Sa 08:30-15:00",
        "phone": "+55 19 3837-1763",
        "id": "node/10211823117"
      },
      "geometry": {
        "type": "Point",
        "coordinates": [
          -47.0002334,
          -22.6974055
        ]
      }
    }
  ]
}
