{
  "type": "FeatureCollection",
  "features": [
    {
      "type": "Feature",
      "id": "node/9169326112",
      "properties": {
        "timestamp": "2021-10-13T10:18:24Z",
        "version": 1,
        "changeset": 112454882,
        "addr:city": "Mocajuba",
        "addr:street": "Comunidade Quilombola de Itabatinga - Vila São Pedro",
        "amenity": "community_centre",
        "name": "Salão Comunitário da Comunidade Crsitão São Pedro de Itabatinga",
        "operator": "Comunidade Cristã de Itabatinga - Igreja Católica",
        "operator:type": "comunidade",
        "id": "node/9169326112"
      },
      "geometry": {
        "type": "Point",
        "coordinates": [
          -49.6139285,
          -2.5370431
        ]
      }
    }
  ]
}
