{
  "type": "FeatureCollection",
  "features": [
    {
      "type": "Feature",
      "id": "node/10291002667",
      "properties": {
        "timestamp": "2022-12-28T09:36:13Z",
        "version": 1,
        "changeset": 130591050,
        "addr:street": "Rua Alfredo Rosa",
        "name": "Ops Hotel",
        "tourism": "hotel",
        "id": "node/10291002667"
      },
      "geometry": {
        "type": "Point",
        "coordinates": [
          -51.9474731,
          -18.2987825
        ]
      }
    }
  ]
}
