{
  "type": "FeatureCollection",
  "features": [
    {
      "type": "Feature",
      "id": "node/12451505131",
      "properties": {
        "timestamp": "2024-12-25T18:15:30Z",
        "version": 1,
        "changeset": 160613061,
        "name": "Cachoeira do Rafael",
        "waterway": "waterfall",
        "id": "node/12451505131"
      },
      "geometry": {
        "type": "Point",
        "coordinates": [
          -63.2478812,
          -10.416763
        ]
      }
    }
  ]
}
