{
  "type": "FeatureCollection",
  "features": [
    {
      "type": "Feature",
      "id": "node/4540483398",
      "properties": {
        "timestamp": "2023-07-17T16:32:47Z",
        "version": 3,
        "changeset": 138630058,
        "amenity": "cinema",
        "brand": "Cinemark",
        "brand:wikidata": "Q707530",
        "name": "Cinemark Camaçari",
        "website": "http://www.boulevardshoppingcamacari.com.br/cinema",
        "wikidata": "Q61417280",
        "id": "node/4540483398"
      },
      "geometry": {
        "type": "Point",
        "coordinates": [
          -38.3061023,
          -12.7116785
        ]
      }
    }
  ]
}
