{
  "type": "FeatureCollection",
  "features": [
    {
      "type": "Feature",
      "id": "node/10685067802",
      "properties": {
        "timestamp": "2023-06-04T15:57:37Z",
        "version": 2,
        "changeset": 136938667,
        "addr:city": "Sério",
        "addr:country": "BR",
        "addr:housenumber": "625",
        "addr:postcode": "95918-000",
        "addr:state": "Rio Grande do Sul",
        "addr:street": "Rua 30 de Novembro",
        "addr:suburb": "Centro",
        "check_date": "2023-06-01",
        "government": "legislative",
        "name": "Câmara de Vereadores de Sério",
        "office": "government",
        "opening_hours": "Mo-Th 07:45-11:30,13:30-17:00; Fr 08:00-11:00",
        "phone": "+55 (51) 3770-1139",
        "website": "https://www.camaradeserio.rs.gov.br/",
        "wheelchair": "yes",
        "id": "node/10685067802"
      },
      "geometry": {
        "type": "Point",
        "coordinates": [
          -52.2683412,
          -29.3870199
        ]
      }
    }
  ]
}
