{
  "type": "FeatureCollection",
  "features": [
    {
      "type": "Feature",
      "id": "node/5368792310",
      "properties": {
        "timestamp": "2023-06-04T15:57:37Z",
        "version": 5,
        "changeset": 136938667,
        "addr:floor": "2",
        "addr:housenumber": "871",
        "addr:street": "Rua 17 de Novembro",
        "check_date": "2023-06-01",
        "level": "1",
        "name": "Pousada Buona Notte",
        "phone": "+55 51 3770-1054",
        "tourism": "hotel",
        "id": "node/5368792310"
      },
      "geometry": {
        "type": "Point",
        "coordinates": [
          -52.2689718,
          -29.3864304
        ]
      }
    }
  ]
}
