{
  "type": "FeatureCollection",
  "features": [
    {
      "type": "Feature",
      "id": "node/10278572908",
      "properties": {
        "timestamp": "2022-12-21T18:09:54Z",
        "version": 1,
        "changeset": 130343899,
        "historic": "memorial",
        "memorial": "statue",
        "name": "Nossa Senhora da Boa Viagem",
        "id": "node/10278572908"
      },
      "geometry": {
        "type": "Point",
        "coordinates": [
          -52.2518193,
          -29.392969
        ]
      }
    }
  ]
}
