{
  "type": "FeatureCollection",
  "features": [
    {
      "type": "Feature",
      "id": "node/5368756226",
      "properties": {
        "timestamp": "2023-04-04T15:43:25Z",
        "version": 2,
        "changeset": 134502088,
        "description": "Cascata da Bugrinha",
        "name": "Cascata da Bugrinha",
        "waterway": "waterfall",
        "id": "node/5368756226"
      },
      "geometry": {
        "type": "Point",
        "coordinates": [
          -52.2758319,
          -29.3972418
        ]
      }
    },
    {
      "type": "Feature",
      "id": "node/10791028032",
      "properties": {
        "timestamp": "2023-04-11T15:32:08Z",
        "version": 2,
        "changeset": 134779771,
        "intermittent": "yes",
        "waterway": "waterfall",
        "id": "node/10791028032"
      },
      "geometry": {
        "type": "Point",
        "coordinates": [
          -52.294599,
          -29.386809
        ]
      }
    },
    {
      "type": "Feature",
      "id": "node/11400091078",
      "properties": {
        "timestamp": "2023-12-07T12:07:15Z",
        "version": 1,
        "changeset": 144864715,
        "waterway": "waterfall",
        "id": "node/11400091078"
      },
      "geometry": {
        "type": "Point",
        "coordinates": [
          -52.2235897,
          -29.4003346
        ]
      }
    },
    {
      "type": "Feature",
      "id": "node/11930842516",
      "properties": {
        "timestamp": "2024-05-24T14:38:03Z",
        "version": 1,
        "changeset": 151773642,
        "waterway": "waterfall",
        "id": "node/11930842516"
      },
      "geometry": {
        "type": "Point",
        "coordinates": [
          -52.2482568,
          -29.3750277
        ]
      }
    }
  ]
}
