{
  "type": "FeatureCollection",
  "features": [
    {
      "type": "Feature",
      "id": "node/2111179095",
      "properties": {
        "timestamp": "2019-02-02T15:07:42Z",
        "version": 3,
        "changeset": 66857699,
        "government": "legislative",
        "name": "Câmara Municipal de Águas de São Pedro",
        "office": "government",
        "id": "node/2111179095"
      },
      "geometry": {
        "type": "Point",
        "coordinates": [
          -47.8770544,
          -22.5986222
        ]
      }
    }
  ]
}
