{
  "type": "FeatureCollection",
  "features": [
    {
      "type": "Feature",
      "id": "node/9967918620",
      "properties": {
        "timestamp": "2022-08-21T14:04:20Z",
        "version": 1,
        "changeset": 125185133,
        "amenity": "university",
        "name": "Centro Universitário SENAC - Águas de São Pedro",
        "id": "node/9967918620"
      },
      "geometry": {
        "type": "Point",
        "coordinates": [
          -47.8835625,
          -22.5974356
        ]
      }
    }
  ]
}
