{
  "type": "FeatureCollection",
  "features": [
    {
      "type": "Feature",
      "id": "node/10220252860",
      "properties": {
        "timestamp": "2023-03-24T01:32:55Z",
        "version": 2,
        "changeset": 134045239,
        "historic": "memorial",
        "name": "Esqueleto de baleia-minke",
        "id": "node/10220252860"
      },
      "geometry": {
        "type": "Point",
        "coordinates": [
          -46.1092269,
          -23.8284163
        ]
      }
    }
  ]
}
