{
  "type": "FeatureCollection",
  "features": [
    {
      "type": "Feature",
      "id": "node/6934125288",
      "properties": {
        "timestamp": "2019-10-31T07:19:27Z",
        "version": 1,
        "changeset": 76431675,
        "addr:city": "Nova Santa Rita",
        "addr:postcode": "92480-000",
        "addr:street": "Avenida Santa Rita",
        "addr:suburb": "Centro",
        "name": "Marquinhos",
        "shop": "bicycle",
        "id": "node/6934125288"
      },
      "geometry": {
        "type": "Point",
        "coordinates": [
          -51.2740007,
          -29.8553968
        ]
      }
    }
  ]
}
