{
  "type": "FeatureCollection",
  "features": [
    {
      "type": "Feature",
      "id": "node/11942950547",
      "properties": {
        "timestamp": "2024-05-29T19:29:41Z",
        "version": 1,
        "changeset": 152004207,
        "addr:city": "Nova Santa Rita",
        "addr:housenumber": "177",
        "addr:postcode": "92480-000",
        "addr:street": "Rua Hélio Fraga de Moraes Sarmento",
        "amenity": "clinic",
        "healthcare": "clinic",
        "name": "Posto de Saúde Municipal",
        "source": "CNEFE 2022",
        "id": "node/11942950547"
      },
      "geometry": {
        "type": "Point",
        "coordinates": [
          -51.2755646,
          -29.856197
        ]
      }
    }
  ]
}
