{
  "type": "FeatureCollection",
  "features": [
    {
      "type": "Feature",
      "id": "node/5285687566",
      "properties": {
        "timestamp": "2017-12-15T11:09:58Z",
        "version": 1,
        "changeset": 54650114,
        "amenity": "clinic",
        "healthcare": "clinic",
        "name": "Posto de Saúde Alto do Jiquiri",
        "id": "node/5285687566"
      },
      "geometry": {
        "type": "Point",
        "coordinates": [
          -35.8548249,
          -8.1376059
        ]
      }
    }
  ]
}
