{
  "type": "FeatureCollection",
  "features": [
    {
      "type": "Feature",
      "id": "node/5285640694",
      "properties": {
        "timestamp": "2018-01-19T17:46:22Z",
        "version": 3,
        "changeset": 55584336,
        "addr:city": "Riacho das Almas",
        "addr:postcode": "55120-000",
        "addr:street": "Rua Coronel Joaquim Bezerra",
        "addr:suburb": "Centro",
        "government": "register_office",
        "name": "1º Cartorio de Riacho das Almas",
        "office": "government",
        "id": "node/5285640694"
      },
      "geometry": {
        "type": "Point",
        "coordinates": [
          -35.8570888,
          -8.1362703
        ]
      }
    },
    {
      "type": "Feature",
      "id": "node/5285713245",
      "properties": {
        "timestamp": "2018-10-30T03:20:19Z",
        "version": 2,
        "changeset": 63997522,
        "addr:city": "Riacho das Almas",
        "addr:postcode": "55120-000",
        "addr:street": "Rua Coronel Joaquim Bezerra",
        "name": "Secretaria Municipal de Esporte e Cultura",
        "office": "government",
        "id": "node/5285713245"
      },
      "geometry": {
        "type": "Point",
        "coordinates": [
          -35.855436,
          -8.1358117
        ]
      }
    },
    {
      "type": "Feature",
      "id": "node/5285717244",
      "properties": {
        "timestamp": "2018-01-19T17:46:21Z",
        "version": 3,
        "changeset": 55584336,
        "addr:city": "Riacho das Almas",
        "addr:postcode": "55120-000",
        "name": "Fórum",
        "office": "government",
        "id": "node/5285717244"
      },
      "geometry": {
        "type": "Point",
        "coordinates": [
          -35.8581306,
          -8.1356384
        ]
      }
    }
  ]
}
