{
  "type": "FeatureCollection",
  "features": [
    {
      "type": "Feature",
      "id": "node/6348098103",
      "properties": {
        "timestamp": "2022-03-08T19:39:10Z",
        "version": 2,
        "changeset": 118250190,
        "addr:street": "Rua Pedro Cavalcante",
        "addr:suburb": "Centro",
        "government": "social_security",
        "name": "Instituto Nacional do Seguro Social - INSS",
        "office": "government",
        "opening_hours": "Mo-Fr 07:30-17:30",
        "operator": "Instituto Nacional do Seguro Social",
        "operator:short": "INSS",
        "operator:wikidata": "Q10302614",
        "operator:wikipedia": "pt:Instituto Nacional do Seguro Social",
        "id": "node/6348098103"
      },
      "geometry": {
        "type": "Point",
        "coordinates": [
          -36.3515888,
          -9.9075727
        ]
      }
    }
  ]
}
