{
  "type": "FeatureCollection",
  "features": [
    {
      "type": "Feature",
      "id": "node/9491028698",
      "properties": {
        "timestamp": "2022-02-08T23:32:21Z",
        "version": 1,
        "changeset": 117180380,
        "addr:city": "Curralinhos",
        "addr:postcode": "64453-000",
        "addr:street": "Rua Manoel Pereira Lopes",
        "addr:suburb": "Centro",
        "amenity": "school",
        "name": "U E Menino Joao Pedro",
        "id": "node/9491028698"
      },
      "geometry": {
        "type": "Point",
        "coordinates": [
          -42.8317143,
          -5.6173552
        ]
      }
    },
    {
      "type": "Feature",
      "id": "node/9491029664",
      "properties": {
        "timestamp": "2022-02-08T23:31:33Z",
        "version": 1,
        "changeset": 117180363,
        "addr:city": "Curralinhos",
        "addr:postcode": "64453-000",
        "addr:street": "Avenida São Raimundo",
        "addr:suburb": "Centro",
        "amenity": "school",
        "name": "Unid Esc Jacob Gomes Barbosa",
        "id": "node/9491029664"
      },
      "geometry": {
        "type": "Point",
        "coordinates": [
          -42.833498,
          -5.6192557
        ]
      }
    }
  ]
}
