{
  "type": "FeatureCollection",
  "features": [
    {
      "type": "Feature",
      "id": "node/4825813031",
      "properties": {
        "timestamp": "2017-04-29T19:28:43Z",
        "version": 1,
        "changeset": 48264966,
        "name": "Pousada Planalto",
        "name:pt": "Pousada Planalto",
        "tourism": "hotel",
        "id": "node/4825813031"
      },
      "geometry": {
        "type": "Point",
        "coordinates": [
          -47.5373565,
          -10.7440488
        ]
      }
    },
    {
      "type": "Feature",
      "id": "node/4825830824",
      "properties": {
        "timestamp": "2017-04-29T19:28:44Z",
        "version": 1,
        "changeset": 48264966,
        "name": "Pousada Coelho",
        "name:pt": "Pousada Coelho",
        "tourism": "hotel",
        "id": "node/4825830824"
      },
      "geometry": {
        "type": "Point",
        "coordinates": [
          -47.5380068,
          -10.7443863
        ]
      }
    },
    {
      "type": "Feature",
      "id": "node/6760791385",
      "properties": {
        "timestamp": "2019-08-30T23:57:17Z",
        "version": 1,
        "changeset": 73940093,
        "name": "Pousads Beir",
        "tourism": "hotel",
        "id": "node/6760791385"
      },
      "geometry": {
        "type": "Point",
        "coordinates": [
          -47.5363434,
          -10.7408686
        ]
      }
    }
  ]
}
