{
  "type": "FeatureCollection",
  "features": [
    {
      "type": "Feature",
      "id": "node/4102072191",
      "properties": {
        "timestamp": "2016-09-04T21:42:12Z",
        "version": 2,
        "changeset": 41917552,
        "amenity": "doctors",
        "name": "Centro Médico",
        "source": "IBGE",
        "id": "node/4102072191"
      },
      "geometry": {
        "type": "Point",
        "coordinates": [
          -45.9255197,
          -22.2194658
        ]
      }
    },
    {
      "type": "Feature",
      "id": "node/11569221583",
      "properties": {
        "timestamp": "2024-01-30T13:37:37Z",
        "version": 1,
        "changeset": 146864468,
        "amenity": "doctors",
        "healthcare": "doctor",
        "name": "Medicina Integral",
        "id": "node/11569221583"
      },
      "geometry": {
        "type": "Point",
        "coordinates": [
          -45.9295644,
          -22.2226246
        ]
      }
    },
    {
      "type": "Feature",
      "id": "node/11575010362",
      "properties": {
        "timestamp": "2024-01-31T22:45:21Z",
        "version": 1,
        "changeset": 146924249,
        "amenity": "doctors",
        "healthcare": "doctor",
        "name": "Ofir Saúde",
        "id": "node/11575010362"
      },
      "geometry": {
        "type": "Point",
        "coordinates": [
          -45.928875,
          -22.2270787
        ]
      }
    },
    {
      "type": "Feature",
      "id": "node/11575072252",
      "properties": {
        "timestamp": "2024-01-31T22:45:24Z",
        "version": 1,
        "changeset": 146924249,
        "amenity": "doctors",
        "healthcare": "doctor",
        "name": "Clínica Kallás",
        "id": "node/11575072252"
      },
      "geometry": {
        "type": "Point",
        "coordinates": [
          -45.9306504,
          -22.2246981
        ]
      }
    }
  ]
}
