{
  "type": "FeatureCollection",
  "features": [
    {
      "type": "Feature",
      "id": "node/11123587818",
      "properties": {
        "timestamp": "2023-08-17T18:34:47Z",
        "version": 1,
        "changeset": 140026696,
        "addr:city": "Pouso Alegre",
        "addr:housenumber": "470",
        "addr:postcode": "37554-210",
        "addr:street": "Avenida Prefeito Tuany Toledo",
        "addr:suburb": "Fátima",
        "amenity": "kindergarten",
        "name": "Anglo Pouso Alegre Infantil",
        "preschool": "yes",
        "id": "node/11123587818"
      },
      "geometry": {
        "type": "Point",
        "coordinates": [
          -45.9168279,
          -22.2197942
        ]
      }
    },
    {
      "type": "Feature",
      "id": "node/11447154502",
      "properties": {
        "timestamp": "2023-12-23T20:15:21Z",
        "version": 1,
        "changeset": 145449185,
        "amenity": "kindergarten",
        "name": "Ciranda do Saber",
        "id": "node/11447154502"
      },
      "geometry": {
        "type": "Point",
        "coordinates": [
          -45.9343382,
          -22.2227803
        ]
      }
    }
  ]
}
