{
  "type": "FeatureCollection",
  "features": [
    {
      "type": "Feature",
      "id": "node/10908230197",
      "properties": {
        "timestamp": "2023-05-18T13:15:16Z",
        "version": 1,
        "changeset": 136254854,
        "amenity": "veterinary",
        "name": "Laboratório Veterinário HemoLab",
        "id": "node/10908230197"
      },
      "geometry": {
        "type": "Point",
        "coordinates": [
          -45.9460693,
          -22.2135429
        ]
      }
    }
  ]
}
