{
  "type": "FeatureCollection",
  "features": [
    {
      "type": "Feature",
      "id": "node/10908230197",
      "properties": {
        "timestamp": "2023-05-18T13:15:16Z",
        "version": 1,
        "changeset": 136254854,
        "amenity": "veterinary",
        "name": "Laboratório Veterinário HemoLab",
        "id": "node/10908230197"
      },
      "geometry": {
        "type": "Point",
        "coordinates": [
          -45.9460693,
          -22.2135429
        ]
      }
    },
    {
      "type": "Feature",
      "id": "node/11536744858",
      "properties": {
        "timestamp": "2024-01-21T13:00:01Z",
        "version": 1,
        "changeset": 146511767,
        "amenity": "veterinary",
        "name": "Mascote Center",
        "id": "node/11536744858"
      },
      "geometry": {
        "type": "Point",
        "coordinates": [
          -45.9328385,
          -22.2262309
        ]
      }
    }
  ]
}
