{
  "type": "FeatureCollection",
  "features": [
    {
      "type": "Feature",
      "id": "node/5009816525",
      "properties": {
        "timestamp": "2019-01-12T20:52:15Z",
        "version": 4,
        "changeset": 66260207,
        "addr:housenumber": "1542",
        "addr:street": "Avenida Felicíssimo Rodrigues Sobrinho",
        "contact:email": "parna.saojoaquim@icmbio.gov.br",
        "contact:phone": "+55 49 3278-4994",
        "description": "Autorização para entrada ao Morro da Igreja e Pedra Furada",
        "information": "office",
        "name": "Sede do Parque Nacional de São Joaquim",
        "office": "government",
        "operator": "ICMBio",
        "tourism": "information",
        "id": "node/5009816525"
      },
      "geometry": {
        "type": "Point",
        "coordinates": [
          -49.5821999,
          -27.9922564
        ]
      }
    }
  ]
}
