{
  "type": "FeatureCollection",
  "features": [
    {
      "type": "Feature",
      "id": "node/3983207639",
      "properties": {
        "timestamp": "2023-09-30T11:29:23Z",
        "version": 2,
        "changeset": 141947089,
        "addr:city": "Prado",
        "addr:postcode": "45980-000",
        "addr:street": "Avenida Itamaraju",
        "addr:suburb": "Centro",
        "amenity": "clinic",
        "healthcare": "clinic",
        "healthcare:speciality": "general;orthodontics",
        "name": "Unidade Básica de Saúde Um",
        "operator": "Município de Prado",
        "operator:type": "public",
        "source": "survey",
        "id": "node/3983207639"
      },
      "geometry": {
        "type": "Point",
        "coordinates": [
          -39.2257217,
          -17.3407098
        ]
      }
    }
  ]
}
