{
  "type": "FeatureCollection",
  "features": [
    {
      "type": "Feature",
      "id": "node/12604617802",
      "properties": {
        "timestamp": "2025-02-20T20:12:56Z",
        "version": 2,
        "changeset": 162755861,
        "addr:street": "Rua Recanto da Praia",
        "amenity": "dentist",
        "email": "paolardeo@gmail.com",
        "internet_access": "wlan",
        "name": "Padma Espaço Terapêutico",
        "phone": "5573999182829",
        "website": "http://www.instagram.com/corumbau.yoga",
        "id": "node/12604617802"
      },
      "geometry": {
        "type": "Point",
        "coordinates": [
          -39.1563035,
          -16.9288255
        ]
      }
    }
  ]
}
