{
  "type": "FeatureCollection",
  "features": [
    {
      "type": "Feature",
      "id": "node/8627215336",
      "properties": {
        "timestamp": "2022-11-22T10:44:36Z",
        "version": 2,
        "changeset": 129233187,
        "amenity": "community_centre",
        "building": "yes",
        "community_centre": "parish_hall",
        "name": "Salão Paroquial",
        "id": "node/8627215336"
      },
      "geometry": {
        "type": "Point",
        "coordinates": [
          -52.8594692,
          -26.8816028
        ]
      }
    }
  ]
}
