{
  "type": "FeatureCollection",
  "features": [
    {
      "type": "Feature",
      "id": "node/5311987827",
      "properties": {
        "timestamp": "2017-12-30T13:46:00Z",
        "version": 1,
        "changeset": 55034747,
        "addr:housenumber": "1780",
        "addr:street": "Avenida Gustavo Guedes",
        "amenity": "nursing_home",
        "name": "Caso do Amaro",
        "id": "node/5311987827"
      },
      "geometry": {
        "type": "Point",
        "coordinates": [
          -35.2006941,
          -5.8456905
        ]
      }
    },
    {
      "type": "Feature",
      "id": "node/10594247507",
      "properties": {
        "timestamp": "2023-01-30T14:14:28Z",
        "version": 1,
        "changeset": 131883016,
        "addr:housenumber": "1359",
        "addr:postcode": "59031630",
        "addr:street": "Rua São José",
        "amenity": "nursing_home",
        "name": "Casa de Lucas",
        "id": "node/10594247507"
      },
      "geometry": {
        "type": "Point",
        "coordinates": [
          -35.2106534,
          -5.8076785
        ]
      }
    }
  ]
}
