{
  "type": "FeatureCollection",
  "features": [
    {
      "type": "Feature",
      "id": "node/10004165067",
      "properties": {
        "timestamp": "2022-09-06T18:54:03Z",
        "version": 2,
        "changeset": 125871728,
        "government": "administrative",
        "name": "Secretaria de Infraestrutura e Transportes de Lindóia do Sul",
        "office": "government",
        "id": "node/10004165067"
      },
      "geometry": {
        "type": "Point",
        "coordinates": [
          -52.0651705,
          -27.0391421
        ]
      }
    }
  ]
}
