{
  "type": "FeatureCollection",
  "features": [
    {
      "type": "Feature",
      "id": "node/12168281594",
      "properties": {
        "timestamp": "2024-09-10T14:44:55Z",
        "version": 2,
        "changeset": 156444432,
        "amenity": "school",
        "name": "Escola Estadual Santa Maria Goretti",
        "id": "node/12168281594"
      },
      "geometry": {
        "type": "Point",
        "coordinates": [
          -47.5834641,
          -18.8847772
        ]
      }
    }
  ]
}
