{
  "type": "FeatureCollection",
  "features": [
    {
      "type": "Feature",
      "id": "node/6703408041",
      "properties": {
        "timestamp": "2019-08-12T14:38:20Z",
        "version": 1,
        "changeset": 73272005,
        "addr:city": "Piraju",
        "addr:housenumber": "662",
        "addr:postcode": "18800-000",
        "addr:state": "SP",
        "addr:street": "Rua Treze de Maio",
        "alt_name": "Centro Regional de Arqueologia Ambiental Mario Neme",
        "amenity": "university",
        "email": "mae@edu.usp.br",
        "name": "Casa da USP em Piraju",
        "operator": "Universidade de São Paulo",
        "phone": "+55 14 3351-6027",
        "website": "http://www.vmptbr.mae.usp.br/pesquisa/st/33/centro-regional-de-arqueologia-ambiental.html",
        "id": "node/6703408041"
      },
      "geometry": {
        "type": "Point",
        "coordinates": [
          -49.3859321,
          -23.1942328
        ]
      }
    },
    {
      "type": "Feature",
      "id": "node/11147295457",
      "properties": {
        "timestamp": "2023-08-27T00:02:35Z",
        "version": 1,
        "changeset": 140432816,
        "addr:city": "Piraju",
        "addr:housenumber": "100",
        "addr:street": "Rua Joaquim Franco da Silva",
        "amenity": "university",
        "name": "Faculdade Ibero Americana de São Paulo",
        "id": "node/11147295457"
      },
      "geometry": {
        "type": "Point",
        "coordinates": [
          -49.3917047,
          -23.1585681
        ]
      }
    }
  ]
}
