{
  "type": "FeatureCollection",
  "features": [
    {
      "type": "Feature",
      "id": "node/11147295457",
      "properties": {
        "timestamp": "2023-08-27T00:02:35Z",
        "version": 1,
        "changeset": 140432816,
        "addr:city": "Piraju",
        "addr:housenumber": "100",
        "addr:street": "Rua Joaquim Franco da Silva",
        "amenity": "university",
        "name": "Faculdade Ibero Americana de São Paulo",
        "id": "node/11147295457"
      },
      "geometry": {
        "type": "Point",
        "coordinates": [
          -49.3917047,
          -23.1585681
        ]
      }
    }
  ]
}
