{
  "type": "FeatureCollection",
  "features": [
    {
      "type": "Feature",
      "id": "node/6883306161",
      "properties": {
        "timestamp": "2019-10-15T19:48:33Z",
        "version": 1,
        "changeset": 75741985,
        "amenity": "veterinary",
        "name": "Clínica Veterinária Animal Life",
        "id": "node/6883306161"
      },
      "geometry": {
        "type": "Point",
        "coordinates": [
          -47.9525305,
          -16.1449332
        ]
      }
    }
  ]
}
