{
  "type": "FeatureCollection",
  "features": [
    {
      "type": "Feature",
      "id": "node/3071718622",
      "properties": {
        "timestamp": "2014-09-11T11:38:38Z",
        "version": 1,
        "changeset": 25366230,
        "historic": "monument",
        "name": "Monumento da Roda Verde - Inauguração da PR-151",
        "id": "node/3071718622"
      },
      "geometry": {
        "type": "Point",
        "coordinates": [
          -50.0994403,
          -24.9288208
        ]
      }
    }
  ]
}
