{
  "type": "FeatureCollection",
  "features": [
    {
      "type": "Feature",
      "id": "node/3684386501",
      "properties": {
        "timestamp": "2017-01-11T16:22:44Z",
        "version": 4,
        "changeset": 45080254,
        "name": "Cachoeira do Poção Rio Tamanduá",
        "tourism": "attraction",
        "waterway": "waterfall",
        "id": "node/3684386501"
      },
      "geometry": {
        "type": "Point",
        "coordinates": [
          -50.2214116,
          -24.8851402
        ]
      }
    },
    {
      "type": "Feature",
      "id": "node/4788680353",
      "properties": {
        "timestamp": "2017-04-11T17:26:05Z",
        "version": 1,
        "changeset": 47664280,
        "waterway": "waterfall",
        "id": "node/4788680353"
      },
      "geometry": {
        "type": "Point",
        "coordinates": [
          -50.2532332,
          -24.8330823
        ]
      }
    },
    {
      "type": "Feature",
      "id": "node/5331717994",
      "properties": {
        "timestamp": "2018-01-10T19:03:33Z",
        "version": 1,
        "changeset": 55331266,
        "name": "Cachoeira Maria Leme",
        "tourism": "attraction",
        "waterway": "waterfall",
        "id": "node/5331717994"
      },
      "geometry": {
        "type": "Point",
        "coordinates": [
          -50.2257451,
          -24.7671486
        ]
      }
    }
  ]
}
