{
  "type": "FeatureCollection",
  "features": [
    {
      "type": "Feature",
      "id": "node/6590131315",
      "properties": {
        "timestamp": "2019-07-05T02:02:22Z",
        "version": 1,
        "changeset": 71914510,
        "amenity": "college",
        "isced:level": "2;3",
        "name": "E. E. P. S. G. José Amaro Rodriguês",
        "operator:type": "public",
        "wheelchair": "yes",
        "id": "node/6590131315"
      },
      "geometry": {
        "type": "Point",
        "coordinates": [
          -47.1726778,
          -22.5759236
        ]
      }
    }
  ]
}
