{
  "type": "FeatureCollection",
  "features": [
    {
      "type": "Feature",
      "id": "node/4451774799",
      "properties": {
        "timestamp": "2016-10-17T12:23:32Z",
        "version": 1,
        "changeset": 42958549,
        "amenity": "school",
        "name": "Colégio Estadual Treze de junho",
        "name:pt": "Colégio Estadual Treze de junho",
        "id": "node/4451774799"
      },
      "geometry": {
        "type": "Point",
        "coordinates": [
          -39.3361587,
          -15.0786749
        ]
      }
    }
  ]
}
