{
  "type": "FeatureCollection",
  "features": [
    {
      "type": "Feature",
      "id": "node/6387972464",
      "properties": {
        "timestamp": "2019-04-06T23:01:55Z",
        "version": 2,
        "changeset": 68963962,
        "government": "legislative",
        "name": "Câmara dos Vereadores",
        "office": "government",
        "id": "node/6387972464"
      },
      "geometry": {
        "type": "Point",
        "coordinates": [
          -48.9305242,
          -23.0832866
        ]
      }
    }
  ]
}
