{
  "type": "FeatureCollection",
  "features": [
    {
      "type": "Feature",
      "id": "node/6495861036",
      "properties": {
        "timestamp": "2019-05-23T17:56:16Z",
        "version": 1,
        "changeset": 70561133,
        "historic": "monument",
        "name": "Letreiro da cidade",
        "id": "node/6495861036"
      },
      "geometry": {
        "type": "Point",
        "coordinates": [
          -38.9574139,
          -15.6745415
        ]
      }
    }
  ]
}
