{
  "type": "FeatureCollection",
  "features": [
    {
      "type": "Feature",
      "id": "node/6495861036",
      "properties": {
        "timestamp": "2019-05-23T17:56:16Z",
        "version": 1,
        "changeset": 70561133,
        "historic": "monument",
        "name": "Letreiro da cidade",
        "id": "node/6495861036"
      },
      "geometry": {
        "type": "Point",
        "coordinates": [
          -38.9574139,
          -15.6745415
        ]
      }
    },
    {
      "type": "Feature",
      "id": "node/10555555509",
      "properties": {
        "timestamp": "2023-01-14T23:39:47Z",
        "version": 1,
        "changeset": 131282627,
        "historic": "monument",
        "name": "Coreto de Canavieiras",
        "name:en": "Canavieira's Bandstand",
        "id": "node/10555555509"
      },
      "geometry": {
        "type": "Point",
        "coordinates": [
          -38.9457337,
          -15.6830175
        ]
      }
    }
  ]
}
