{
  "type": "FeatureCollection",
  "features": [
    {
      "type": "Feature",
      "id": "node/9895000647",
      "properties": {
        "timestamp": "2022-07-19T01:16:14Z",
        "version": 2,
        "changeset": 123783991,
        "addr:city": "Ataléia",
        "addr:housenumber": "82",
        "addr:postcode": "39850-000",
        "addr:street": "Rua Governador Valadares",
        "addr:suburb": "Centro",
        "email": "rosemiraguiar@yahoo.com.br",
        "guest_house": "agritourism",
        "mobile": "+55 33 98880 2519",
        "name": "Hotel Novo Mundo",
        "phone": "+55 33 3526 1214",
        "tourism": "guest_house",
        "id": "node/9895000647"
      },
      "geometry": {
        "type": "Point",
        "coordinates": [
          -41.1108823,
          -18.0435324
        ]
      }
    }
  ]
}
