{
  "type": "FeatureCollection",
  "features": [
    {
      "type": "Feature",
      "id": "node/4520442792",
      "properties": {
        "timestamp": "2016-11-25T11:31:15Z",
        "version": 1,
        "changeset": 43942177,
        "name": "Hotel Araújo",
        "name:pt": "Hotel Araújo",
        "tourism": "hotel",
        "id": "node/4520442792"
      },
      "geometry": {
        "type": "Point",
        "coordinates": [
          -47.5560131,
          -4.2934461
        ]
      }
    }
  ]
}
