{
  "type": "FeatureCollection",
  "features": [
    {
      "type": "Feature",
      "id": "node/6214997295",
      "properties": {
        "timestamp": "2019-01-17T00:51:02Z",
        "version": 1,
        "changeset": 66379487,
        "amenity": "clinic",
        "healthcare": "clinic",
        "name": "Posto de Saúde da Barra",
        "id": "node/6214997295"
      },
      "geometry": {
        "type": "Point",
        "coordinates": [
          -50.1244732,
          -29.9798915
        ]
      }
    },
    {
      "type": "Feature",
      "id": "node/7114430274",
      "properties": {
        "timestamp": "2020-01-07T12:31:24Z",
        "version": 1,
        "changeset": 79293678,
        "amenity": "clinic",
        "healthcare": "clinic",
        "name": "UBS Zona Sul",
        "id": "node/7114430274"
      },
      "geometry": {
        "type": "Point",
        "coordinates": [
          -50.159327,
          -30.0453061
        ]
      }
    }
  ]
}
