{
  "type": "FeatureCollection",
  "features": [
    {
      "type": "Feature",
      "id": "node/1141149250",
      "properties": {
        "timestamp": "2011-02-07T19:24:20Z",
        "version": 1,
        "changeset": 7219730,
        "name": "Salto Maciel",
        "waterway": "waterfall",
        "id": "node/1141149250"
      },
      "geometry": {
        "type": "Point",
        "coordinates": [
          -57.8031447,
          -14.6926981
        ]
      }
    },
    {
      "type": "Feature",
      "id": "node/1141149804",
      "properties": {
        "timestamp": "2011-02-07T19:24:40Z",
        "version": 1,
        "changeset": 7219730,
        "name": "Salto das Nuvens",
        "waterway": "waterfall",
        "id": "node/1141149804"
      },
      "geometry": {
        "type": "Point",
        "coordinates": [
          -57.7337911,
          -14.6079097
        ]
      }
    },
    {
      "type": "Feature",
      "id": "node/2479789151",
      "properties": {
        "timestamp": "2022-10-23T02:18:25Z",
        "version": 2,
        "changeset": 127941881,
        "name": "Cachoeira do Juba",
        "waterway": "waterfall",
        "id": "node/2479789151"
      },
      "geometry": {
        "type": "Point",
        "coordinates": [
          -57.7859155,
          -14.9452632
        ]
      }
    },
    {
      "type": "Feature",
      "id": "node/5345942546",
      "properties": {
        "timestamp": "2018-01-18T01:10:00Z",
        "version": 1,
        "changeset": 55536904,
        "waterway": "waterfall",
        "id": "node/5345942546"
      },
      "geometry": {
        "type": "Point",
        "coordinates": [
          -57.8091708,
          -14.9141799
        ]
      }
    },
    {
      "type": "Feature",
      "id": "node/5345942564",
      "properties": {
        "timestamp": "2018-01-18T01:10:00Z",
        "version": 1,
        "changeset": 55536904,
        "waterway": "waterfall",
        "id": "node/5345942564"
      },
      "geometry": {
        "type": "Point",
        "coordinates": [
          -57.7448648,
          -14.9723565
        ]
      }
    },
    {
      "type": "Feature",
      "id": "node/12107123953",
      "properties": {
        "timestamp": "2024-08-26T05:24:15Z",
        "version": 3,
        "changeset": 155763692,
        "height": "30",
        "intermittent": "yes",
        "name": "Cachoeira Tuin",
        "waterway": "waterfall",
        "width": "5",
        "id": "node/12107123953"
      },
      "geometry": {
        "type": "Point",
        "coordinates": [
          -57.2924179,
          -14.6814516
        ]
      }
    }
  ]
}
