{
  "type": "FeatureCollection",
  "features": [
    {
      "type": "Feature",
      "id": "node/6983054682",
      "properties": {
        "timestamp": "2019-11-16T17:00:55Z",
        "version": 1,
        "changeset": 77169970,
        "amenity": "clinic",
        "healthcare": "clinic",
        "name": "UBS Dieter Staudinger",
        "id": "node/6983054682"
      },
      "geometry": {
        "type": "Point",
        "coordinates": [
          -49.5224653,
          -27.0624557
        ]
      }
    }
  ]
}
