{
  "type": "FeatureCollection",
  "features": [
    {
      "type": "Feature",
      "id": "node/6658475086",
      "properties": {
        "timestamp": "2019-07-29T18:00:47Z",
        "version": 1,
        "changeset": 72781549,
        "amenity": "college",
        "name": "IFC Campus Ibirama",
        "id": "node/6658475086"
      },
      "geometry": {
        "type": "Point",
        "coordinates": [
          -49.5386757,
          -27.0492065
        ]
      }
    }
  ]
}
