{
  "type": "FeatureCollection",
  "features": [
    {
      "type": "Feature",
      "id": "node/2482224837",
      "properties": {
        "timestamp": "2019-09-23T20:34:16Z",
        "version": 2,
        "changeset": 74825903,
        "amenity": "arts_centre",
        "name": "CTG Querencia do Pau Ferro",
        "id": "node/2482224837"
      },
      "geometry": {
        "type": "Point",
        "coordinates": [
          -55.1513505,
          -29.0476685
        ]
      }
    }
  ]
}
