{
  "type": "FeatureCollection",
  "features": [
    {
      "type": "Feature",
      "id": "node/8290515683",
      "properties": {
        "timestamp": "2021-09-24T21:59:25Z",
        "version": 2,
        "changeset": 111668332,
        "historic": "memorial",
        "memorial": "stone",
        "name": "Pedra de Bauxita",
        "id": "node/8290515683"
      },
      "geometry": {
        "type": "Point",
        "coordinates": [
          -56.4844116,
          -2.102662
        ]
      }
    }
  ]
}
