{
  "type": "FeatureCollection",
  "features": [
    {
      "type": "Feature",
      "id": "node/9496480387",
      "properties": {
        "timestamp": "2022-02-10T21:07:44Z",
        "version": 1,
        "changeset": 117262421,
        "name": "Hotel Planeta",
        "tourism": "hotel",
        "id": "node/9496480387"
      },
      "geometry": {
        "type": "Point",
        "coordinates": [
          -48.0735374,
          -14.1534051
        ]
      }
    },
    {
      "type": "Feature",
      "id": "node/9496528224",
      "properties": {
        "timestamp": "2022-02-10T21:22:43Z",
        "version": 1,
        "changeset": 117263167,
        "tourism": "hotel",
        "id": "node/9496528224"
      },
      "geometry": {
        "type": "Point",
        "coordinates": [
          -48.0758941,
          -14.1510982
        ]
      }
    }
  ]
}
