{
  "type": "FeatureCollection",
  "features": [
    {
      "type": "Feature",
      "id": "node/7007106185",
      "properties": {
        "timestamp": "2019-11-25T00:37:01Z",
        "version": 1,
        "changeset": 77495856,
        "addr:street": "Bandeirantes da Beira-rio",
        "amenity": "community_centre",
        "name": "Albergue Noturno",
        "opening_hours": "Mo-Su 06:00-08:00, 12:00-14:00, 18:00-20:00",
        "id": "node/7007106185"
      },
      "geometry": {
        "type": "Point",
        "coordinates": [
          -61.1887122,
          -11.6820009
        ]
      }
    }
  ]
}
