{
  "type": "FeatureCollection",
  "features": [
    {
      "type": "Feature",
      "id": "node/8309097617",
      "properties": {
        "timestamp": "2021-11-13T13:12:03Z",
        "version": 2,
        "changeset": 113730144,
        "addr:city": "Biguaçu",
        "addr:housenumber": "79",
        "addr:postcode": "88160-000",
        "addr:street": "Rua Hermógenes Prazeres",
        "addr:suburb": "Centro",
        "government": "legislative",
        "name": "Câmara de Vereadores de Biguaçu",
        "office": "government",
        "phone": "+55 48 3243-4233",
        "id": "node/8309097617"
      },
      "geometry": {
        "type": "Point",
        "coordinates": [
          -48.6541283,
          -27.4966666
        ]
      }
    }
  ]
}
