{
  "type": "FeatureCollection",
  "features": [
    {
      "type": "Feature",
      "id": "node/12503264227",
      "properties": {
        "timestamp": "2025-01-15T01:12:30Z",
        "version": 1,
        "changeset": 161363817,
        "name": "Cachoeira de Oiticica",
        "waterway": "waterfall",
        "id": "node/12503264227"
      },
      "geometry": {
        "type": "Point",
        "coordinates": [
          -37.1229556,
          -6.1525553
        ]
      }
    }
  ]
}
