{
  "type": "FeatureCollection",
  "features": [
    {
      "type": "Feature",
      "id": "node/4806007614",
      "properties": {
        "timestamp": "2017-04-20T15:23:16Z",
        "version": 1,
        "changeset": 47975520,
        "amenity": "hospital",
        "name": "Unidade Mista de Saúde",
        "id": "node/4806007614"
      },
      "geometry": {
        "type": "Point",
        "coordinates": [
          -52.0065353,
          0.8993185
        ]
      }
    }
  ]
}
