{
  "type": "FeatureCollection",
  "features": [
    {
      "type": "Feature",
      "id": "node/4455901983",
      "properties": {
        "timestamp": "2017-09-21T23:24:46Z",
        "version": 4,
        "changeset": 52259866,
        "amenity": "community_centre",
        "name": "Clube 24 de Agosto",
        "id": "node/4455901983"
      },
      "geometry": {
        "type": "Point",
        "coordinates": [
          -53.371228,
          -32.5659275
        ]
      }
    },
    {
      "type": "Feature",
      "id": "node/5267089518",
      "properties": {
        "timestamp": "2017-12-06T01:48:54Z",
        "version": 1,
        "changeset": 54387562,
        "amenity": "community_centre",
        "id": "node/5267089518"
      },
      "geometry": {
        "type": "Point",
        "coordinates": [
          -53.3683067,
          -32.5669328
        ]
      }
    }
  ]
}
