{
  "type": "FeatureCollection",
  "features": [
    {
      "type": "Feature",
      "id": "node/6561623698",
      "properties": {
        "timestamp": "2019-06-20T19:47:13Z",
        "version": 1,
        "changeset": 71459231,
        "name": "C창mara Municipal de Cana찾",
        "office": "government",
        "id": "node/6561623698"
      },
      "geometry": {
        "type": "Point",
        "coordinates": [
          -42.6227232,
          -20.6843219
        ]
      }
    },
    {
      "type": "Feature",
      "id": "node/6561634113",
      "properties": {
        "timestamp": "2019-06-20T20:20:14Z",
        "version": 1,
        "changeset": 71460014,
        "government": "register_office",
        "name": "Cart처rio de Registro Civil e Notas de Cana찾 - MG",
        "office": "government",
        "id": "node/6561634113"
      },
      "geometry": {
        "type": "Point",
        "coordinates": [
          -42.6210425,
          -20.6850265
        ]
      }
    },
    {
      "type": "Feature",
      "id": "node/6561723223",
      "properties": {
        "timestamp": "2019-06-20T21:03:54Z",
        "version": 1,
        "changeset": 71461132,
        "name": "CRAS",
        "office": "government",
        "id": "node/6561723223"
      },
      "geometry": {
        "type": "Point",
        "coordinates": [
          -42.6111732,
          -20.6876965
        ]
      }
    }
  ]
}
