{
  "type": "FeatureCollection",
  "features": [
    {
      "type": "Feature",
      "id": "node/6561623697",
      "properties": {
        "timestamp": "2019-06-20T19:47:13Z",
        "version": 1,
        "changeset": 71459231,
        "amenity": "pharmacy",
        "dispensing": "yes",
        "healthcare": "pharmacy",
        "name": "Drogaria Municipal de Cannã",
        "id": "node/6561623697"
      },
      "geometry": {
        "type": "Point",
        "coordinates": [
          -42.6227688,
          -20.6845326
        ]
      }
    },
    {
      "type": "Feature",
      "id": "node/6561683426",
      "properties": {
        "timestamp": "2019-06-20T20:28:14Z",
        "version": 1,
        "changeset": 71460230,
        "amenity": "pharmacy",
        "dispensing": "yes",
        "healthcare": "pharmacy",
        "name": "Drogaria Sampaio",
        "id": "node/6561683426"
      },
      "geometry": {
        "type": "Point",
        "coordinates": [
          -42.6205084,
          -20.6852553
        ]
      }
    },
    {
      "type": "Feature",
      "id": "node/6561716896",
      "properties": {
        "timestamp": "2019-06-20T20:49:56Z",
        "version": 1,
        "changeset": 71460807,
        "amenity": "pharmacy",
        "dispensing": "yes",
        "healthcare": "pharmacy",
        "name": "Drogaria FarMelhor",
        "id": "node/6561716896"
      },
      "geometry": {
        "type": "Point",
        "coordinates": [
          -42.6183595,
          -20.6872847
        ]
      }
    },
    {
      "type": "Feature",
      "id": "node/6561723225",
      "properties": {
        "timestamp": "2019-06-20T21:03:54Z",
        "version": 1,
        "changeset": 71461132,
        "amenity": "pharmacy",
        "dispensing": "yes",
        "healthcare": "pharmacy",
        "name": "Drogaria Vitória",
        "id": "node/6561723225"
      },
      "geometry": {
        "type": "Point",
        "coordinates": [
          -42.6102767,
          -20.6883114
        ]
      }
    }
  ]
}
