{
  "type": "FeatureCollection",
  "features": [
    {
      "type": "Feature",
      "id": "node/5907386389",
      "properties": {
        "timestamp": "2021-09-16T08:15:50Z",
        "version": 2,
        "changeset": 111278009,
        "historic": "monument",
        "name": "O Menino da Porteira",
        "id": "node/5907386389"
      },
      "geometry": {
        "type": "Point",
        "coordinates": [
          -46.3726153,
          -22.2756276
        ]
      }
    }
  ]
}
