{
  "type": "FeatureCollection",
  "features": [
    {
      "type": "Feature",
      "id": "node/4794227015",
      "properties": {
        "timestamp": "2022-10-07T13:15:32Z",
        "version": 4,
        "changeset": 127152565,
        "addr:city": "Conceição do Mato Dentro",
        "addr:postcode": "35860-000",
        "addr:street": "Avenida Juscelino Kubitschek",
        "addr:suburb": "Centro",
        "amenity": "clinic",
        "healthcare": "clinic",
        "name": "Centro Municipal de Saúde",
        "source": "IBGE",
        "id": "node/4794227015"
      },
      "geometry": {
        "type": "Point",
        "coordinates": [
          -43.4262341,
          -19.031494
        ]
      }
    },
    {
      "type": "Feature",
      "id": "node/10080560591",
      "properties": {
        "timestamp": "2022-10-06T19:32:04Z",
        "version": 1,
        "changeset": 127116560,
        "addr:city": "Conceição do Mato Dentro",
        "addr:housenumber": "401",
        "addr:postcode": "35860-000",
        "addr:street": "Avenida Juscelino Kubitschek",
        "addr:suburb": "Centro",
        "amenity": "clinic",
        "healthcare": "clinic",
        "healthcare:speciality": "general",
        "name": "Centro de Promoção a Saúde Unimed",
        "operator": "Unimed",
        "operator:type": "private",
        "id": "node/10080560591"
      },
      "geometry": {
        "type": "Point",
        "coordinates": [
          -43.424941,
          -19.0340384
        ]
      }
    },
    {
      "type": "Feature",
      "id": "node/10081694561",
      "properties": {
        "timestamp": "2022-10-07T10:51:29Z",
        "version": 1,
        "changeset": 127145327,
        "addr:city": "Conceição do Mato Dentro",
        "addr:postcode": "35860-000",
        "addr:street": "Rua Professor Oscarino Ferreira Carneiro",
        "addr:suburb": "Alto da Boa Vista",
        "amenity": "clinic",
        "healthcare": "clinic",
        "healthcare:speciality": "general",
        "name": "Unidade Básica de Saúde Saudade",
        "id": "node/10081694561"
      },
      "geometry": {
        "type": "Point",
        "coordinates": [
          -43.4249818,
          -19.0422031
        ]
      }
    }
  ]
}
