{
  "type": "FeatureCollection",
  "features": [
    {
      "type": "Feature",
      "id": "node/4732226025",
      "properties": {
        "timestamp": "2017-03-13T13:31:36Z",
        "version": 1,
        "changeset": 46812862,
        "name": "Saltão do Rio Cotegipe",
        "tourism": "attraction",
        "waterway": "waterfall",
        "id": "node/4732226025"
      },
      "geometry": {
        "type": "Point",
        "coordinates": [
          -53.3364855,
          -25.7627963
        ]
      }
    }
  ]
}
