{
  "type": "FeatureCollection",
  "features": [
    {
      "type": "Feature",
      "id": "node/9136283692",
      "properties": {
        "timestamp": "2021-09-30T21:00:55Z",
        "version": 1,
        "changeset": 111935637,
        "addr:housenumber": "846",
        "addr:street": "Rua Professor Simão Hess",
        "amenity": "pharmacy",
        "building": "yes",
        "contact:website": "https://www.saojoaofarmacias.com.br/",
        "contact:whatsapp": "+55 54 99680-5029",
        "delivery": "yes",
        "dispensing": "yes",
        "healthcare": "pharmacy",
        "internet_access": "wlan",
        "internet_access:fee": "no",
        "name": "Farmácia São João",
        "opening_hours": "Mo-Sa 07:30-23:00; Su,PH 08:00-22:00",
        "wifi": "yes",
        "id": "node/9136283692"
      },
      "geometry": {
        "type": "Point",
        "coordinates": [
          -48.9080429,
          -26.7128219
        ]
      }
    },
    {
      "type": "Feature",
      "id": "node/11117042425",
      "properties": {
        "timestamp": "2023-08-15T15:42:06Z",
        "version": 1,
        "changeset": 139922003,
        "addr:city": "Luiz Alves",
        "addr:housenumber": "35",
        "addr:postcode": "89128-000",
        "addr:street": "Rua Erich Gielow",
        "addr:suburb": "Centro",
        "amenity": "pharmacy",
        "government": "healthcare",
        "healthcare": "pharmacy",
        "name": "Farmácia Básica",
        "operator": "Prefeitura Municipal de Luiz Alves",
        "operator:type": "government_facility-public",
        "phone": "+55 47 3377-8670",
        "id": "node/11117042425"
      },
      "geometry": {
        "type": "Point",
        "coordinates": [
          -48.9297609,
          -26.7230588
        ]
      }
    }
  ]
}
