{
  "type": "FeatureCollection",
  "features": [
    {
      "type": "Feature",
      "id": "node/3627067962",
      "properties": {
        "timestamp": "2020-01-14T22:33:25Z",
        "version": 2,
        "changeset": 79584670,
        "amenity": "pharmacy",
        "healthcare": "pharmacy",
        "id": "node/3627067962"
      },
      "geometry": {
        "type": "Point",
        "coordinates": [
          -50.9177333,
          -17.7944491
        ]
      }
    },
    {
      "type": "Feature",
      "id": "node/3627067964",
      "properties": {
        "timestamp": "2020-01-14T22:33:25Z",
        "version": 2,
        "changeset": 79584670,
        "amenity": "pharmacy",
        "healthcare": "pharmacy",
        "id": "node/3627067964"
      },
      "geometry": {
        "type": "Point",
        "coordinates": [
          -50.9179074,
          -17.7946004
        ]
      }
    },
    {
      "type": "Feature",
      "id": "node/10310838848",
      "properties": {
        "timestamp": "2023-01-06T12:58:33Z",
        "version": 1,
        "changeset": 130946602,
        "amenity": "pharmacy",
        "name": "Drogaria São Sebastião",
        "id": "node/10310838848"
      },
      "geometry": {
        "type": "Point",
        "coordinates": [
          -50.9258153,
          -17.7995843
        ]
      }
    },
    {
      "type": "Feature",
      "id": "node/10310857634",
      "properties": {
        "timestamp": "2023-01-06T13:09:05Z",
        "version": 1,
        "changeset": 130946991,
        "amenity": "pharmacy",
        "name": "Rede SanMar",
        "id": "node/10310857634"
      },
      "geometry": {
        "type": "Point",
        "coordinates": [
          -50.9286144,
          -17.7973803
        ]
      }
    }
  ]
}
