{
  "type": "FeatureCollection",
  "features": [
    {
      "type": "Feature",
      "id": "node/11255070037",
      "properties": {
        "timestamp": "2023-10-11T12:34:35Z",
        "version": 1,
        "changeset": 142434930,
        "amenity": "clinic",
        "name": "Policlínica Municipal",
        "id": "node/11255070037"
      },
      "geometry": {
        "type": "Point",
        "coordinates": [
          -36.7946087,
          -6.7750747
        ]
      }
    }
  ]
}
