{
  "type": "FeatureCollection",
  "features": [
    {
      "type": "Feature",
      "id": "node/742103581",
      "properties": {
        "timestamp": "2022-04-07T15:13:22Z",
        "version": 2,
        "changeset": 119434273,
        "name": "Cachoeira da Neve",
        "source": "Exército Brasileiro",
        "waterway": "waterfall",
        "id": "node/742103581"
      },
      "geometry": {
        "type": "Point",
        "coordinates": [
          -42.8342313,
          -16.5978444
        ]
      }
    },
    {
      "type": "Feature",
      "id": "node/9651669347",
      "properties": {
        "timestamp": "2022-04-08T14:47:28Z",
        "version": 2,
        "changeset": 119474414,
        "name": "Cachoeira da Fumaça",
        "waterway": "waterfall",
        "id": "node/9651669347"
      },
      "geometry": {
        "type": "Point",
        "coordinates": [
          -42.9060055,
          -16.597625
        ]
      }
    }
  ]
}
