{
  "type": "FeatureCollection",
  "features": [
    {
      "type": "Feature",
      "id": "node/9981303100",
      "properties": {
        "timestamp": "2022-08-27T09:43:30Z",
        "version": 1,
        "changeset": 125435775,
        "addr:city": "Guaçuí",
        "addr:housenumber": "58",
        "addr:postcode": "29560-000",
        "addr:street": "Rua Tereza Bolelli",
        "addr:suburb": "Quincas Machado",
        "amenity": "doctors",
        "healthcare": "doctor",
        "healthcare:speciality": "general;paediatrics",
        "name": "Centro Médico Caparaó",
        "operator": "Gilmar Polido Bodevan",
        "id": "node/9981303100"
      },
      "geometry": {
        "type": "Point",
        "coordinates": [
          -41.6765883,
          -20.7689047
        ]
      }
    }
  ]
}
