{
  "type": "FeatureCollection",
  "features": [
    {
      "type": "Feature",
      "id": "node/9180410114",
      "properties": {
        "timestamp": "2022-07-28T23:15:51Z",
        "version": 2,
        "changeset": 124206363,
        "amenity": "dentist",
        "contact:facebook": "https://www.facebook.com/odontomarcospasqualli/",
        "healthcare": "dentist",
        "name": "Consultório Odontológico Marcos Antonio Pasquali",
        "id": "node/9180410114"
      },
      "geometry": {
        "type": "Point",
        "coordinates": [
          -52.9856031,
          -26.8495959
        ]
      }
    }
  ]
}
