{
  "type": "FeatureCollection",
  "features": [
    {
      "type": "Feature",
      "id": "node/5625697971",
      "properties": {
        "timestamp": "2018-05-18T01:14:11Z",
        "version": 1,
        "changeset": 59065327,
        "alt_name": "Justiça Eleitoral",
        "government": "register_office",
        "name": "Cartório Eleitoral",
        "office": "government",
        "id": "node/5625697971"
      },
      "geometry": {
        "type": "Point",
        "coordinates": [
          -52.9883587,
          -26.8438581
        ]
      }
    },
    {
      "type": "Feature",
      "id": "node/6240191385",
      "properties": {
        "timestamp": "2021-02-05T18:10:26Z",
        "version": 2,
        "changeset": 98784481,
        "name": "Ev comunicação",
        "office": "government",
        "id": "node/6240191385"
      },
      "geometry": {
        "type": "Point",
        "coordinates": [
          -52.9836813,
          -26.8413914
        ]
      }
    }
  ]
}
