{
  "type": "FeatureCollection",
  "features": [
    {
      "type": "Feature",
      "id": "node/5779713164",
      "properties": {
        "timestamp": "2018-09-21T21:13:03Z",
        "version": 2,
        "changeset": 62810794,
        "amenity": "school",
        "name": "Escola Municipal São Francisco",
        "id": "node/5779713164"
      },
      "geometry": {
        "type": "Point",
        "coordinates": [
          -50.781545,
          -28.6857662
        ]
      }
    },
    {
      "type": "Feature",
      "id": "node/5921551059",
      "properties": {
        "timestamp": "2024-12-07T21:47:32Z",
        "version": 5,
        "changeset": 160040676,
        "addr:city": "Monte Alegre dos Campos",
        "addr:postcode": "95236-000",
        "addr:street": "Rua Professor Pedro Smiderle",
        "addr:suburb": "Distrito Capela da Luz",
        "amenity": "school",
        "name": "EMEF Luiz de Almeida Franca",
        "nohousenumber": "yes",
        "phone": "+55 54 3612-1056",
        "ref:INEP": "43163963",
        "id": "node/5921551059"
      },
      "geometry": {
        "type": "Point",
        "coordinates": [
          -50.8455855,
          -28.6196906
        ]
      }
    }
  ]
}
