{
  "type": "FeatureCollection",
  "features": [
    {
      "type": "Feature",
      "id": "node/5779713164",
      "properties": {
        "timestamp": "2018-09-21T21:13:03Z",
        "version": 2,
        "changeset": 62810794,
        "amenity": "school",
        "name": "Escola Municipal São Francisco",
        "id": "node/5779713164"
      },
      "geometry": {
        "type": "Point",
        "coordinates": [
          -50.781545,
          -28.6857662
        ]
      }
    }
  ]
}
