{
  "type": "FeatureCollection",
  "features": [
    {
      "type": "Feature",
      "id": "node/3761263691",
      "properties": {
        "timestamp": "2021-03-12T19:12:19Z",
        "version": 2,
        "changeset": 100927342,
        "amenity": "hospital",
        "healthcare": "hospital",
        "id": "node/3761263691"
      },
      "geometry": {
        "type": "Point",
        "coordinates": [
          -41.7390432,
          -17.6284563
        ]
      }
    },
    {
      "type": "Feature",
      "id": "node/8595549260",
      "properties": {
        "timestamp": "2023-05-25T06:02:34Z",
        "version": 2,
        "changeset": 136526217,
        "addr:city": "Ladainha",
        "addr:housenumber": "550",
        "addr:postcode": "39825-000",
        "addr:street": "Rua da Usina",
        "addr:suburb": "Centro",
        "amenity": "hospital",
        "ele": "1",
        "emergency": "yes",
        "healthcare": "hospital",
        "healthcare:speciality": "general",
        "name": "Hospital Municipal Dr Arthur Rausch",
        "operator": "Prefeitura Municipal de Ladainha",
        "operator:ref:vatin": "BR18404863000190",
        "operator:type": "government",
        "phone": "+55 33 3524 1290",
        "ref:CNES": "2797496",
        "wheelchair": "yes",
        "id": "node/8595549260"
      },
      "geometry": {
        "type": "Point",
        "coordinates": [
          -41.7434749,
          -17.6414766
        ]
      }
    }
  ]
}
