{
  "type": "FeatureCollection",
  "features": [
    {
      "type": "Feature",
      "id": "node/4607590891",
      "properties": {
        "timestamp": "2021-01-25T16:29:42Z",
        "version": 2,
        "changeset": 98134262,
        "addr:city": "São Miguel dos Milagres",
        "name": "Restaurante e Pousada da Dona Nice",
        "name:pt": "Restaurante e Pousada da Dona Nice",
        "phone": "+55 82 3295-1473",
        "tourism": "guest_house",
        "id": "node/4607590891"
      },
      "geometry": {
        "type": "Point",
        "coordinates": [
          -35.3749887,
          -9.2689805
        ]
      }
    },
    {
      "type": "Feature",
      "id": "node/8257504918",
      "properties": {
        "timestamp": "2021-01-25T16:31:18Z",
        "version": 2,
        "changeset": 98134336,
        "addr:street": "Rua Ana Marinho Braga",
        "internet_access": "wlan",
        "name": "Pousada Porto",
        "name:pt": "Pousada Porto Mar",
        "phone": "+55 82 9 9613-4556",
        "tourism": "guest_house",
        "id": "node/8257504918"
      },
      "geometry": {
        "type": "Point",
        "coordinates": [
          -35.3456095,
          -9.2397774
        ]
      }
    },
    {
      "type": "Feature",
      "id": "node/10301482027",
      "properties": {
        "timestamp": "2023-01-02T23:40:22Z",
        "version": 1,
        "changeset": 130806980,
        "addr:city": "São Miguel dos Milagres",
        "addr:district": "Praia Porto da Rua",
        "addr:state": "AL",
        "addr:street": "Sitio Alegria S/N",
        "guest_house": "agritourism",
        "internet_access": "yes",
        "internet_access:fee": "no",
        "name": "Pousada Corália",
        "tourism": "guest_house",
        "id": "node/10301482027"
      },
      "geometry": {
        "type": "Point",
        "coordinates": [
          -35.3530322,
          -9.2455933
        ]
      }
    }
  ]
}
