{
  "type": "FeatureCollection",
  "features": [
    {
      "type": "Feature",
      "id": "node/5640850821",
      "properties": {
        "timestamp": "2018-05-25T02:42:40Z",
        "version": 1,
        "changeset": 59257239,
        "amenity": "nursing_home",
        "name": "Casa",
        "id": "node/5640850821"
      },
      "geometry": {
        "type": "Point",
        "coordinates": [
          -51.0853983,
          -29.6648349
        ]
      }
    }
  ]
}
