{
  "type": "FeatureCollection",
  "features": [
    {
      "type": "Feature",
      "id": "node/2651028946",
      "properties": {
        "timestamp": "2017-06-18T19:36:29Z",
        "version": 5,
        "changeset": 49642450,
        "name": "Cachoeira Lorena",
        "waterway": "waterfall",
        "id": "node/2651028946"
      },
      "geometry": {
        "type": "Point",
        "coordinates": [
          -48.9978883,
          -27.0456211
        ]
      }
    },
    {
      "type": "Feature",
      "id": "node/2661758473",
      "properties": {
        "timestamp": "2020-03-27T22:47:07Z",
        "version": 6,
        "changeset": 82735832,
        "name": "Cachoeira Pedra Lisa",
        "waterway": "waterfall",
        "id": "node/2661758473"
      },
      "geometry": {
        "type": "Point",
        "coordinates": [
          -49.0415282,
          -27.0766603
        ]
      }
    },
    {
      "type": "Feature",
      "id": "node/7274804331",
      "properties": {
        "timestamp": "2020-03-16T17:55:27Z",
        "version": 2,
        "changeset": 82269145,
        "name": "Cachoeira do Jerônimo",
        "waterway": "waterfall",
        "id": "node/7274804331"
      },
      "geometry": {
        "type": "Point",
        "coordinates": [
          -49.0814577,
          -27.142414
        ]
      }
    }
  ]
}
