{
  "type": "FeatureCollection",
  "features": [
    {
      "type": "Feature",
      "id": "node/3677011426",
      "properties": {
        "timestamp": "2015-08-02T00:51:49Z",
        "version": 1,
        "changeset": 33040073,
        "name": "Privê do Atalaia",
        "tourism": "hotel",
        "id": "node/3677011426"
      },
      "geometry": {
        "type": "Point",
        "coordinates": [
          -47.3119257,
          -0.5956545
        ]
      }
    },
    {
      "type": "Feature",
      "id": "node/8148973042",
      "properties": {
        "timestamp": "2020-11-21T15:09:43Z",
        "version": 1,
        "changeset": 94548527,
        "name": "Hotel Salinópolis",
        "tourism": "hotel",
        "id": "node/8148973042"
      },
      "geometry": {
        "type": "Point",
        "coordinates": [
          -47.3586854,
          -0.6126024
        ]
      }
    }
  ]
}
