{
  "type": "FeatureCollection",
  "features": [
    {
      "type": "Feature",
      "id": "node/4958813824",
      "properties": {
        "timestamp": "2019-03-15T14:09:07Z",
        "version": 3,
        "changeset": 68176125,
        "amenity": "pharmacy",
        "drive_through": "no",
        "name": "Extrafarma",
        "id": "node/4958813824"
      },
      "geometry": {
        "type": "Point",
        "coordinates": [
          -47.3450566,
          -0.6240066
        ]
      }
    },
    {
      "type": "Feature",
      "id": "node/4958830722",
      "properties": {
        "timestamp": "2017-07-11T17:00:54Z",
        "version": 2,
        "changeset": 50206850,
        "amenity": "pharmacy",
        "name": "Big Ben Sal",
        "id": "node/4958830722"
      },
      "geometry": {
        "type": "Point",
        "coordinates": [
          -47.3451264,
          -0.6239482
        ]
      }
    }
  ]
}
