{
  "type": "FeatureCollection",
  "features": [
    {
      "type": "Feature",
      "id": "node/6835508707",
      "properties": {
        "timestamp": "2019-09-29T17:48:44Z",
        "version": 1,
        "changeset": 75068382,
        "amenity": "college",
        "internet_access": "yes",
        "name": "Casa Familiar Rural - Presidente Tancredo Neves",
        "operator": "CFR",
        "operator:type": "private",
        "website": "http://www.cfr.org.br/",
        "id": "node/6835508707"
      },
      "geometry": {
        "type": "Point",
        "coordinates": [
          -39.3720212,
          -13.3736251
        ]
      }
    }
  ]
}
