{
  "type": "FeatureCollection",
  "features": [
    {
      "type": "Feature",
      "id": "node/5023344621",
      "properties": {
        "timestamp": "2017-08-09T03:56:43Z",
        "version": 1,
        "changeset": 50959324,
        "amenity": "nursing_home",
        "name": "Enzo suelem",
        "name:pt": "Enzo suelem",
        "id": "node/5023344621"
      },
      "geometry": {
        "type": "Point",
        "coordinates": [
          -48.0976517,
          -15.9185718
        ]
      }
    }
  ]
}
