{
  "type": "FeatureCollection",
  "features": [
    {
      "type": "Feature",
      "id": "node/12014943988",
      "properties": {
        "timestamp": "2024-07-04T02:27:46Z",
        "version": 2,
        "changeset": 153524840,
        "name": "Cachoeiro do Alegre",
        "waterway": "waterfall",
        "id": "node/12014943988"
      },
      "geometry": {
        "type": "Point",
        "coordinates": [
          -42.4283749,
          -20.8296199
        ]
      }
    },
    {
      "type": "Feature",
      "id": "node/12014944584",
      "properties": {
        "timestamp": "2024-07-03T00:43:25Z",
        "version": 2,
        "changeset": 153480540,
        "waterway": "waterfall",
        "id": "node/12014944584"
      },
      "geometry": {
        "type": "Point",
        "coordinates": [
          -42.3815774,
          -20.8560239
        ]
      }
    },
    {
      "type": "Feature",
      "id": "node/12015480302",
      "properties": {
        "timestamp": "2024-07-03T00:43:25Z",
        "version": 2,
        "changeset": 153480540,
        "waterway": "waterfall",
        "id": "node/12015480302"
      },
      "geometry": {
        "type": "Point",
        "coordinates": [
          -42.3626733,
          -20.8229205
        ]
      }
    }
  ]
}
