{
  "type": "FeatureCollection",
  "features": [
    {
      "type": "Feature",
      "id": "node/3244613593",
      "properties": {
        "timestamp": "2014-12-20T15:04:26Z",
        "version": 1,
        "changeset": 27590277,
        "access": "public",
        "amenity": "clinic",
        "name": "PSF",
        "id": "node/3244613593"
      },
      "geometry": {
        "type": "Point",
        "coordinates": [
          -36.2135355,
          -9.6454965
        ]
      }
    },
    {
      "type": "Feature",
      "id": "node/3244634033",
      "properties": {
        "timestamp": "2014-12-20T15:19:51Z",
        "version": 1,
        "changeset": 27590601,
        "access": "public",
        "amenity": "clinic",
        "name": "PSF",
        "id": "node/3244634033"
      },
      "geometry": {
        "type": "Point",
        "coordinates": [
          -36.2105898,
          -9.6500139
        ]
      }
    }
  ]
}
