{
  "type": "FeatureCollection",
  "features": [
    {
      "type": "Feature",
      "id": "node/5292967893",
      "properties": {
        "timestamp": "2019-05-18T10:24:19Z",
        "version": 2,
        "changeset": 70383680,
        "amenity": "kindergarten",
        "isced:level": "0",
        "name": "Escolinha Betel",
        "opening_hours": "Mo-Fr 06:45-11:30,13:30-17:30; Sa 09:00-17:00; PH closed",
        "id": "node/5292967893"
      },
      "geometry": {
        "type": "Point",
        "coordinates": [
          -59.1341079,
          -3.6024783
        ]
      }
    }
  ]
}
