{
  "type": "FeatureCollection",
  "features": [
    {
      "type": "Feature",
      "id": "node/11598663354",
      "properties": {
        "timestamp": "2024-02-08T16:19:55Z",
        "version": 1,
        "changeset": 147224418,
        "name": "Cascata do Rio São marcos",
        "waterway": "waterfall",
        "id": "node/11598663354"
      },
      "geometry": {
        "type": "Point",
        "coordinates": [
          -51.0113213,
          -29.0174553
        ]
      }
    }
  ]
}
