{
  "type": "FeatureCollection",
  "features": [
    {
      "type": "Feature",
      "id": "node/7865019885",
      "properties": {
        "timestamp": "2022-02-24T00:28:28Z",
        "version": 2,
        "changeset": 117791943,
        "amenity": "pharmacy",
        "name": "Drogaria Macedo",
        "id": "node/7865019885"
      },
      "geometry": {
        "type": "Point",
        "coordinates": [
          -40.6605469,
          -7.4434264
        ]
      }
    }
  ]
}
