{
  "type": "FeatureCollection",
  "features": [
    {
      "type": "Feature",
      "id": "node/5187391058",
      "properties": {
        "timestamp": "2023-02-01T15:06:46Z",
        "version": 2,
        "changeset": 131967314,
        "addr:city": "Canaã dos Carajás",
        "addr:housenumber": "19",
        "addr:street": "Rua Muiracatiara",
        "alt_name": "Centro de Referência Especializado de Assistência Social",
        "amenity": "social_facility",
        "name": "CREAS Canaã dos Carajás",
        "social_facility": "outreach",
        "social_facility:for": "underprivileged;abused;victim",
        "id": "node/5187391058"
      },
      "geometry": {
        "type": "Point",
        "coordinates": [
          -49.8505947,
          -6.5395526
        ]
      }
    }
  ]
}
