{
  "type": "FeatureCollection",
  "features": [
    {
      "type": "Feature",
      "id": "node/7430001722",
      "properties": {
        "timestamp": "2020-04-21T12:49:39Z",
        "version": 1,
        "changeset": 83881994,
        "historic": "monument",
        "name": "Milho Gigante",
        "id": "node/7430001722"
      },
      "geometry": {
        "type": "Point",
        "coordinates": [
          -60.7439418,
          2.5656138
        ]
      }
    }
  ]
}
