{
  "type": "FeatureCollection",
  "features": [
    {
      "type": "Feature",
      "id": "node/9683893389",
      "properties": {
        "timestamp": "2022-04-21T21:28:20Z",
        "version": 1,
        "changeset": 120020528,
        "addr:city": "Aroazes",
        "addr:postcode": "64310-000",
        "addr:street": "Avenida Vinte e Sete de Fevereiro",
        "addr:suburb": "Centro",
        "amenity": "pharmacy",
        "dispensing": "yes",
        "healthcare": "pharmacy",
        "name": "Santa Cruz",
        "id": "node/9683893389"
      },
      "geometry": {
        "type": "Point",
        "coordinates": [
          -41.7884185,
          -6.1112354
        ]
      }
    }
  ]
}
