{
  "type": "FeatureCollection",
  "features": [
    {
      "type": "Feature",
      "id": "node/9152544161",
      "properties": {
        "timestamp": "2021-10-06T15:42:22Z",
        "version": 1,
        "changeset": 112176094,
        "addr:city": "Tacaimbó",
        "addr:housenumber": "41-A",
        "addr:postcode": "55140000",
        "addr:street": "Avenida Joao Clemente",
        "addr:suburb": "Centro",
        "amenity": "dentist",
        "healthcare": "dentist",
        "healthcare:speciality": "dentist;ortodontia;urgências;restaurações;canal;tratamento_de_gengiva;clareamento;prótese_dentária;estética_dental",
        "name": "DRA LARA MENDONÇA",
        "opening_hours": "Mo-Fr 09:00-17:00",
        "id": "node/9152544161"
      },
      "geometry": {
        "type": "Point",
        "coordinates": [
          -36.2901247,
          -8.3155463
        ]
      }
    }
  ]
}
