{
  "type": "FeatureCollection",
  "features": [
    {
      "type": "Feature",
      "id": "node/5285708085",
      "properties": {
        "timestamp": "2018-06-19T22:43:50Z",
        "version": 2,
        "changeset": 59992644,
        "addr:city": "Capela de Santana",
        "addr:postcode": "95745-000",
        "addr:street": "Avenida Coronel Orestes Lucas",
        "addr:suburb": "Vila Nova",
        "government": "legislative",
        "name": "Câmara dos Vereadores",
        "office": "government",
        "operator": "Poder Legislativo",
        "id": "node/5285708085"
      },
      "geometry": {
        "type": "Point",
        "coordinates": [
          -51.3213487,
          -29.6903484
        ]
      }
    }
  ]
}
