{
  "type": "FeatureCollection",
  "features": [
    {
      "type": "Feature",
      "id": "node/3651243920",
      "properties": {
        "timestamp": "2015-07-14T20:13:12Z",
        "version": 1,
        "changeset": 32637140,
        "amenity": "school",
        "name": "Escola João da Conceição",
        "id": "node/3651243920"
      },
      "geometry": {
        "type": "Point",
        "coordinates": [
          -54.1047002,
          -28.6423169
        ]
      }
    }
  ]
}
