{
  "type": "FeatureCollection",
  "features": [
    {
      "type": "Feature",
      "id": "node/4507345262",
      "properties": {
        "timestamp": "2021-05-20T14:11:22Z",
        "version": 3,
        "changeset": 105034220,
        "addr:city": "BRAGANÇA",
        "addr:postcode": "68600000",
        "addr:street": "Avenida Governador Mendonça Furtado",
        "addr:suburb": "VILA NOVA",
        "amenity": "college",
        "internet_access": "wlan",
        "name": "SENAI - CEP BRAGANÇA",
        "wheelchair": "limited",
        "id": "node/4507345262"
      },
      "geometry": {
        "type": "Point",
        "coordinates": [
          -46.7800569,
          -1.0649946
        ]
      }
    }
  ]
}
