{
  "type": "FeatureCollection",
  "features": [
    {
      "type": "Feature",
      "id": "node/6426697654",
      "properties": {
        "timestamp": "2019-04-24T20:27:23Z",
        "version": 1,
        "changeset": 69540692,
        "addr:city": "Leandro Ferreira",
        "addr:postcode": "35657000",
        "addr:street": "Rua Raul Ribeiro",
        "addr:suburb": "Centro",
        "name": "Divina Gula",
        "tourism": "hotel",
        "id": "node/6426697654"
      },
      "geometry": {
        "type": "Point",
        "coordinates": [
          -45.0238413,
          -19.715763
        ]
      }
    }
  ]
}
