{
  "type": "FeatureCollection",
  "features": [
    {
      "type": "Feature",
      "id": "node/3329093822",
      "properties": {
        "timestamp": "2024-01-28T19:01:38Z",
        "version": 3,
        "changeset": 146791695,
        "name": "Cachoeira de Ouricuri",
        "tourism": "attraction",
        "waterway": "waterfall",
        "id": "node/3329093822"
      },
      "geometry": {
        "type": "Point",
        "coordinates": [
          -35.5861901,
          -6.8914466
        ]
      }
    }
  ]
}
