{
  "type": "FeatureCollection",
  "features": [
    {
      "type": "Feature",
      "id": "node/3329093822",
      "properties": {
        "timestamp": "2019-07-01T01:06:26Z",
        "version": 2,
        "changeset": 71768048,
        "name": "Cachoeira de Ouricuri",
        "tourism": "attraction",
        "waterway": "waterfall",
        "id": "node/3329093822"
      },
      "geometry": {
        "type": "Point",
        "coordinates": [
          -35.5863028,
          -6.8914067
        ]
      }
    }
  ]
}
