{
  "type": "FeatureCollection",
  "features": [
    {
      "type": "Feature",
      "id": "node/8630612530",
      "properties": {
        "timestamp": "2021-04-15T01:31:02Z",
        "version": 1,
        "changeset": 102957506,
        "government": "public_service",
        "name": "Secretaria Municipal de Agricultura, Meio Ambiente e Desenvolvimento Industrial",
        "office": "government",
        "phone": "+55 54 32935636",
        "id": "node/8630612530"
      },
      "geometry": {
        "type": "Point",
        "coordinates": [
          -51.2828996,
          -28.8593075
        ]
      }
    }
  ]
}
