{
  "type": "FeatureCollection",
  "features": [
    {
      "type": "Feature",
      "id": "node/2095395764",
      "properties": {
        "timestamp": "2013-01-04T19:23:06Z",
        "version": 1,
        "changeset": 14529660,
        "name": "Hotel Pradense",
        "tourism": "hotel",
        "id": "node/2095395764"
      },
      "geometry": {
        "type": "Point",
        "coordinates": [
          -51.2861784,
          -28.8570596
        ]
      }
    },
    {
      "type": "Feature",
      "id": "node/10222649979",
      "properties": {
        "timestamp": "2022-11-28T01:17:40Z",
        "version": 1,
        "changeset": 129453852,
        "name": "Travel Inn Axten Antônio Prado",
        "tourism": "hotel",
        "id": "node/10222649979"
      },
      "geometry": {
        "type": "Point",
        "coordinates": [
          -51.2692562,
          -28.8571107
        ]
      }
    }
  ]
}
