{
  "type": "FeatureCollection",
  "features": [
    {
      "type": "Feature",
      "id": "node/6838587419",
      "properties": {
        "timestamp": "2019-09-30T19:36:39Z",
        "version": 2,
        "changeset": 75117874,
        "historic": "monument",
        "name": "Leão Alado",
        "id": "node/6838587419"
      },
      "geometry": {
        "type": "Point",
        "coordinates": [
          -51.2833274,
          -28.8575124
        ]
      }
    }
  ]
}
