{
  "type": "FeatureCollection",
  "features": [
    {
      "type": "Feature",
      "id": "node/6151716673",
      "properties": {
        "timestamp": "2018-12-24T01:55:51Z",
        "version": 2,
        "changeset": 65727971,
        "amenity": "pharmacy",
        "dispensing": "yes",
        "healthcare": "pharmacy",
        "name": "Farma & Cia",
        "id": "node/6151716673"
      },
      "geometry": {
        "type": "Point",
        "coordinates": [
          -51.4069213,
          0.7072415
        ]
      }
    },
    {
      "type": "Feature",
      "id": "node/6152725420",
      "properties": {
        "timestamp": "2018-12-22T00:56:38Z",
        "version": 1,
        "changeset": 65683687,
        "amenity": "pharmacy",
        "dispensing": "yes",
        "healthcare": "pharmacy",
        "name": "Farmacia Nacional",
        "id": "node/6152725420"
      },
      "geometry": {
        "type": "Point",
        "coordinates": [
          -51.4135761,
          0.7104655
        ]
      }
    }
  ]
}
