{
  "type": "FeatureCollection",
  "features": [
    {
      "type": "Feature",
      "id": "node/8297412318",
      "properties": {
        "timestamp": "2021-01-06T17:29:01Z",
        "version": 1,
        "changeset": 97063881,
        "addr:street": "Rua Arlindo Rocha",
        "name": "Casa da Tia Rozita",
        "tourism": "guest_house",
        "id": "node/8297412318"
      },
      "geometry": {
        "type": "Point",
        "coordinates": [
          -43.9539322,
          -7.6304398
        ]
      }
    }
  ]
}
