{
  "type": "FeatureCollection",
  "features": [
    {
      "type": "Feature",
      "id": "node/5728476833",
      "properties": {
        "timestamp": "2018-06-29T13:37:46Z",
        "version": 1,
        "changeset": 60279982,
        "amenity": "pharmacy",
        "dispensing": "yes",
        "healthcare": "pharmacy",
        "name": "Farmácia Santo Antônio",
        "id": "node/5728476833"
      },
      "geometry": {
        "type": "Point",
        "coordinates": [
          -51.3079975,
          -29.0285847
        ]
      }
    }
  ]
}
