{
  "type": "FeatureCollection",
  "features": [
    {
      "type": "Feature",
      "id": "node/8848976441",
      "properties": {
        "timestamp": "2023-08-19T11:56:02Z",
        "version": 2,
        "changeset": 140091839,
        "addr:city": "Sitiá",
        "addr:postcode": "63960000",
        "addr:street": "Avenida João Saraiva Rabelo",
        "addr:suburb": "Barra do Sitiá",
        "government": "register_office",
        "name": "Cartório Sitiá",
        "office": "government",
        "opening_hours": "Mo-Fr 08:00-17:00",
        "operator": "Cleânio Saraiva",
        "id": "node/8848976441"
      },
      "geometry": {
        "type": "Point",
        "coordinates": [
          -38.6562826,
          -5.1658621
        ]
      }
    }
  ]
}
