{
  "type": "FeatureCollection",
  "features": [
    {
      "type": "Feature",
      "id": "node/2301077764",
      "properties": {
        "timestamp": "2021-01-24T23:07:13Z",
        "version": 2,
        "changeset": 98078230,
        "amenity": "pharmacy",
        "healthcare": "pharmacy",
        "name": "Farmayelen",
        "id": "node/2301077764"
      },
      "geometry": {
        "type": "Point",
        "coordinates": [
          -47.5582568,
          -24.7108287
        ]
      }
    },
    {
      "type": "Feature",
      "id": "node/2702059014",
      "properties": {
        "timestamp": "2020-03-23T19:58:38Z",
        "version": 3,
        "changeset": 82539434,
        "amenity": "pharmacy",
        "healthcare": "pharmacy",
        "name": "Farmelhor",
        "id": "node/2702059014"
      },
      "geometry": {
        "type": "Point",
        "coordinates": [
          -47.5597562,
          -24.7037742
        ]
      }
    },
    {
      "type": "Feature",
      "id": "node/2702059015",
      "properties": {
        "timestamp": "2020-03-23T19:58:38Z",
        "version": 2,
        "changeset": 82539434,
        "amenity": "pharmacy",
        "healthcare": "pharmacy",
        "id": "node/2702059015"
      },
      "geometry": {
        "type": "Point",
        "coordinates": [
          -47.5596448,
          -24.7042536
        ]
      }
    },
    {
      "type": "Feature",
      "id": "node/2702060445",
      "properties": {
        "timestamp": "2020-03-23T19:58:38Z",
        "version": 3,
        "changeset": 82539434,
        "amenity": "pharmacy",
        "healthcare": "pharmacy",
        "id": "node/2702060445"
      },
      "geometry": {
        "type": "Point",
        "coordinates": [
          -47.5608268,
          -24.7022456
        ]
      }
    }
  ]
}
