{
  "type": "FeatureCollection",
  "features": [
    {
      "type": "Feature",
      "id": "node/4268817492",
      "properties": {
        "timestamp": "2016-06-27T22:39:49Z",
        "version": 1,
        "changeset": 40332606,
        "addr:street": "Rua Coronel Alcebíades de Miranda",
        "amenity": "dentist",
        "name": "odonto excelence",
        "id": "node/4268817492"
      },
      "geometry": {
        "type": "Point",
        "coordinates": [
          -50.1666743,
          -25.0559276
        ]
      }
    },
    {
      "type": "Feature",
      "id": "node/11573258546",
      "properties": {
        "timestamp": "2024-01-31T14:42:32Z",
        "version": 1,
        "changeset": 146908163,
        "addr:city": "Ponta Grossa",
        "addr:housenumber": "112",
        "addr:street": "Santana",
        "amenity": "dentist",
        "healthcare": "dentist",
        "name": "Clinica Prime odontologia",
        "opening_hours": "Mo-Fr 09:00-18:00",
        "id": "node/11573258546"
      },
      "geometry": {
        "type": "Point",
        "coordinates": [
          -50.1584976,
          -25.1023396
        ]
      }
    }
  ]
}
