{
  "type": "FeatureCollection",
  "features": [
    {
      "type": "Feature",
      "id": "node/4268817492",
      "properties": {
        "timestamp": "2016-06-27T22:39:49Z",
        "version": 1,
        "changeset": 40332606,
        "addr:street": "Rua Coronel Alcebíades de Miranda",
        "amenity": "dentist",
        "name": "odonto excelence",
        "id": "node/4268817492"
      },
      "geometry": {
        "type": "Point",
        "coordinates": [
          -50.1666743,
          -25.0559276
        ]
      }
    }
  ]
}
