{
  "type": "FeatureCollection",
  "features": [
    {
      "type": "Feature",
      "id": "node/4397887292",
      "properties": {
        "timestamp": "2016-09-12T18:14:46Z",
        "version": 1,
        "changeset": 42107193,
        "addr:housenumber": "604",
        "addr:postcode": "84050540",
        "addr:street": "Rua Euzébio da Motta",
        "internet_access": "wlan",
        "tourism": "guest_house",
        "id": "node/4397887292"
      },
      "geometry": {
        "type": "Point",
        "coordinates": [
          -50.1764492,
          -25.1035874
        ]
      }
    },
    {
      "type": "Feature",
      "id": "node/7276623985",
      "properties": {
        "timestamp": "2020-03-08T13:32:54Z",
        "version": 1,
        "changeset": 81923237,
        "name": "Pousada",
        "name:pt": "Pousada La Vierro",
        "tourism": "guest_house",
        "id": "node/7276623985"
      },
      "geometry": {
        "type": "Point",
        "coordinates": [
          -50.1394483,
          -25.1631914
        ]
      }
    }
  ]
}
