{
  "type": "FeatureCollection",
  "features": [
    {
      "type": "Feature",
      "id": "node/12652841959",
      "properties": {
        "timestamp": "2025-03-11T18:32:57Z",
        "version": 1,
        "changeset": 163497723,
        "addr:city": "Nossa Senhora da Glória",
        "addr:postcode": "49680-000",
        "addr:street": "Avenida Leste",
        "addr:suburb": "Brasília",
        "amenity": "clinic",
        "healthcare": "clinic",
        "healthcare:speciality": "general",
        "name": "Clínica de Saúde da Família Rosa Maria dos Santos Sbrinho",
        "operator": "Município de Nossa Senhora da Glória",
        "operator:type": "public",
        "id": "node/12652841959"
      },
      "geometry": {
        "type": "Point",
        "coordinates": [
          -37.4133205,
          -10.2149664
        ]
      }
    },
    {
      "type": "Feature",
      "id": "node/12652841991",
      "properties": {
        "timestamp": "2025-03-11T18:32:57Z",
        "version": 1,
        "changeset": 163497723,
        "addr:city": "Nossa Senhora da Glória",
        "addr:housenumber": "506",
        "addr:postcode": "49680-000",
        "addr:street": "Rua João Domingos Ribeiro",
        "addr:suburb": "Cohab",
        "amenity": "clinic",
        "healthcare": "clinic",
        "healthcare:speciality": "general",
        "name": "Centro de Testagem e Aconselhamento de Nossa Senhora da Glória",
        "operator": "Município de Nossa enhora da Glória",
        "operator:type": "public",
        "id": "node/12652841991"
      },
      "geometry": {
        "type": "Point",
        "coordinates": [
          -37.3983971,
          -10.2135494
        ]
      }
    }
  ]
}
