{
  "type": "FeatureCollection",
  "features": [
    {
      "type": "Feature",
      "id": "node/5950240626",
      "properties": {
        "timestamp": "2021-04-02T00:29:35Z",
        "version": 2,
        "changeset": 102152327,
        "amenity": "pharmacy",
        "healthcare": "pharmacy",
        "name": "Farmácia D Mais",
        "id": "node/5950240626"
      },
      "geometry": {
        "type": "Point",
        "coordinates": [
          -48.6341652,
          -27.2392919
        ]
      }
    }
  ]
}
