{
  "type": "FeatureCollection",
  "features": [
    {
      "type": "Feature",
      "id": "node/11183656013",
      "properties": {
        "timestamp": "2023-09-11T15:13:44Z",
        "version": 1,
        "changeset": 141118748,
        "addr:city": "Coronel Barros",
        "addr:housenumber": "281",
        "addr:postcode": "98735000",
        "addr:street": "Rua da Imigração",
        "addr:suburb": "Centro",
        "amenity": "pharmacy",
        "healthcare": "pharmacy",
        "name": "Farmavida",
        "opening_hours": "Mo-Sa 08:00-18:00",
        "operator": "Jaqueline Bussler Muller",
        "id": "node/11183656013"
      },
      "geometry": {
        "type": "Point",
        "coordinates": [
          -54.0711692,
          -28.3840335
        ]
      }
    }
  ]
}
