{
  "type": "FeatureCollection",
  "features": [
    {
      "type": "Feature",
      "id": "node/12175952824",
      "properties": {
        "timestamp": "2024-09-14T03:28:39Z",
        "version": 1,
        "changeset": 156595278,
        "access": "yes",
        "historic": "monument",
        "name": "Monumento aos Lanceiros Negros",
        "id": "node/12175952824"
      },
      "geometry": {
        "type": "Point",
        "coordinates": [
          -53.4916474,
          -30.5116137
        ]
      }
    }
  ]
}
