{
  "type": "FeatureCollection",
  "features": [
    {
      "type": "Feature",
      "id": "node/2054914729",
      "properties": {
        "timestamp": "2014-01-09T18:54:43Z",
        "version": 4,
        "changeset": 19905426,
        "addr:postcode": "48730-000",
        "addr:street": "Praça Porcina Rosa Carneiro",
        "historic": "monument",
        "name": "Fundação Bailon Lopes Carneiro",
        "id": "node/2054914729"
      },
      "geometry": {
        "type": "Point",
        "coordinates": [
          -39.2852933,
          -11.5621314
        ]
      }
    },
    {
      "type": "Feature",
      "id": "node/2067052196",
      "properties": {
        "timestamp": "2012-12-14T20:15:07Z",
        "version": 1,
        "changeset": 14274828,
        "historic": "monument",
        "name": "Congregação Cristã do Brasil",
        "id": "node/2067052196"
      },
      "geometry": {
        "type": "Point",
        "coordinates": [
          -39.2731079,
          -11.5722685
        ]
      }
    },
    {
      "type": "Feature",
      "id": "node/2067094514",
      "properties": {
        "timestamp": "2012-12-14T21:00:37Z",
        "version": 1,
        "changeset": 14274828,
        "historic": "monument",
        "name": "Igreja Assembléia de Deus Ministério Renascer",
        "id": "node/2067094514"
      },
      "geometry": {
        "type": "Point",
        "coordinates": [
          -39.2726895,
          -11.5729044
        ]
      }
    }
  ]
}
