{
  "type": "FeatureCollection",
  "features": [
    {
      "type": "Feature",
      "id": "node/2079075990",
      "properties": {
        "timestamp": "2012-12-22T20:39:21Z",
        "version": 1,
        "changeset": 14370622,
        "amenity": "veterinary",
        "name": "AWW BANTECO CASA DE METERIAL DE CONSTRUÇÃO E PRODUTOS VETERINARIOS",
        "id": "node/2079075990"
      },
      "geometry": {
        "type": "Point",
        "coordinates": [
          -39.1737673,
          -11.5956702
        ]
      }
    }
  ]
}
