{
  "type": "FeatureCollection",
  "features": [
    {
      "type": "Feature",
      "id": "node/6916272306",
      "properties": {
        "timestamp": "2022-05-28T21:22:09Z",
        "version": 2,
        "changeset": 121633239,
        "historic": "memorial",
        "memorial": "bust",
        "source": "survey",
        "tourism": "attraction",
        "id": "node/6916272306"
      },
      "geometry": {
        "type": "Point",
        "coordinates": [
          -36.9462054,
          -7.3755789
        ]
      }
    },
    {
      "type": "Feature",
      "id": "node/9991693017",
      "properties": {
        "timestamp": "2022-09-10T01:34:38Z",
        "version": 2,
        "changeset": 126000235,
        "historic": "memorial",
        "memorial": "cross",
        "name": "Alex",
        "source": "survey",
        "id": "node/9991693017"
      },
      "geometry": {
        "type": "Point",
        "coordinates": [
          -36.8934698,
          -7.359312
        ]
      }
    },
    {
      "type": "Feature",
      "id": "node/10004304699",
      "properties": {
        "timestamp": "2022-09-06T14:01:35Z",
        "version": 1,
        "changeset": 125860902,
        "historic": "memorial",
        "memorial": "cross",
        "source": "survey",
        "id": "node/10004304699"
      },
      "geometry": {
        "type": "Point",
        "coordinates": [
          -37.0322031,
          -7.337589
        ]
      }
    },
    {
      "type": "Feature",
      "id": "node/10004357459",
      "properties": {
        "timestamp": "2022-09-06T14:01:35Z",
        "version": 1,
        "changeset": 125860902,
        "historic": "memorial",
        "memorial": "cross",
        "source": "survey",
        "id": "node/10004357459"
      },
      "geometry": {
        "type": "Point",
        "coordinates": [
          -36.9712016,
          -7.3138456
        ]
      }
    },
    {
      "type": "Feature",
      "id": "node/10004357460",
      "properties": {
        "timestamp": "2022-09-06T14:01:35Z",
        "version": 1,
        "changeset": 125860902,
        "historic": "memorial",
        "memorial": "cross",
        "source": "survey",
        "id": "node/10004357460"
      },
      "geometry": {
        "type": "Point",
        "coordinates": [
          -36.9699758,
          -7.2937034
        ]
      }
    },
    {
      "type": "Feature",
      "id": "node/11403689335",
      "properties": {
        "timestamp": "2023-12-08T19:22:36Z",
        "version": 1,
        "changeset": 144915091,
        "historic": "memorial",
        "memorial": "cross",
        "source": "survey",
        "id": "node/11403689335"
      },
      "geometry": {
        "type": "Point",
        "coordinates": [
          -36.8999273,
          -7.3668906
        ]
      }
    },
    {
      "type": "Feature",
      "id": "node/12049931627",
      "properties": {
        "timestamp": "2024-07-12T18:53:01Z",
        "version": 1,
        "changeset": 153868412,
        "historic": "memorial",
        "memorial": "cross",
        "source": "survey",
        "id": "node/12049931627"
      },
      "geometry": {
        "type": "Point",
        "coordinates": [
          -36.8722254,
          -7.3396719
        ]
      }
    },
    {
      "type": "Feature",
      "id": "node/12049931628",
      "properties": {
        "timestamp": "2024-07-12T18:53:01Z",
        "version": 1,
        "changeset": 153868412,
        "historic": "memorial",
        "memorial": "cross",
        "source": "survey",
        "id": "node/12049931628"
      },
      "geometry": {
        "type": "Point",
        "coordinates": [
          -36.8339154,
          -7.3440107
        ]
      }
    },
    {
      "type": "Feature",
      "id": "node/12049931629",
      "properties": {
        "timestamp": "2024-07-12T18:53:01Z",
        "version": 1,
        "changeset": 153868412,
        "historic": "memorial",
        "memorial": "cross",
        "source": "survey",
        "id": "node/12049931629"
      },
      "geometry": {
        "type": "Point",
        "coordinates": [
          -36.923992,
          -7.3392436
        ]
      }
    }
  ]
}
