{
  "type": "FeatureCollection",
  "features": [
    {
      "type": "Feature",
      "id": "node/4090773239",
      "properties": {
        "timestamp": "2021-08-13T06:51:45Z",
        "version": 3,
        "changeset": 109608654,
        "waterway": "waterfall",
        "id": "node/4090773239"
      },
      "geometry": {
        "type": "Point",
        "coordinates": [
          -48.8438439,
          -28.1229449
        ]
      }
    },
    {
      "type": "Feature",
      "id": "node/4090773422",
      "properties": {
        "timestamp": "2021-08-13T06:51:45Z",
        "version": 2,
        "changeset": 109608654,
        "waterway": "waterfall",
        "id": "node/4090773422"
      },
      "geometry": {
        "type": "Point",
        "coordinates": [
          -48.8359852,
          -28.1248956
        ]
      }
    },
    {
      "type": "Feature",
      "id": "node/4326227201",
      "properties": {
        "timestamp": "2021-08-12T07:22:33Z",
        "version": 3,
        "changeset": 109553709,
        "name": "Cachoeira Salto Grande",
        "waterway": "waterfall",
        "id": "node/4326227201"
      },
      "geometry": {
        "type": "Point",
        "coordinates": [
          -48.8367906,
          -28.2545995
        ]
      }
    },
    {
      "type": "Feature",
      "id": "node/8181431479",
      "properties": {
        "timestamp": "2021-10-01T11:05:45Z",
        "version": 2,
        "changeset": 111958321,
        "waterway": "waterfall",
        "id": "node/8181431479"
      },
      "geometry": {
        "type": "Point",
        "coordinates": [
          -48.8350738,
          -28.1061829
        ]
      }
    },
    {
      "type": "Feature",
      "id": "node/8181431480",
      "properties": {
        "timestamp": "2021-10-01T11:05:45Z",
        "version": 2,
        "changeset": 111958321,
        "waterway": "waterfall",
        "id": "node/8181431480"
      },
      "geometry": {
        "type": "Point",
        "coordinates": [
          -48.8413529,
          -28.1006136
        ]
      }
    },
    {
      "type": "Feature",
      "id": "node/8181431481",
      "properties": {
        "timestamp": "2021-08-13T06:51:48Z",
        "version": 2,
        "changeset": 109608654,
        "waterway": "waterfall",
        "id": "node/8181431481"
      },
      "geometry": {
        "type": "Point",
        "coordinates": [
          -48.8458957,
          -28.1731286
        ]
      }
    },
    {
      "type": "Feature",
      "id": "node/8181431482",
      "properties": {
        "timestamp": "2020-12-01T00:44:36Z",
        "version": 1,
        "changeset": 95074040,
        "waterway": "waterfall",
        "id": "node/8181431482"
      },
      "geometry": {
        "type": "Point",
        "coordinates": [
          -48.853181,
          -28.1478335
        ]
      }
    },
    {
      "type": "Feature",
      "id": "node/8181431483",
      "properties": {
        "timestamp": "2021-08-13T06:51:48Z",
        "version": 2,
        "changeset": 109608654,
        "waterway": "waterfall",
        "id": "node/8181431483"
      },
      "geometry": {
        "type": "Point",
        "coordinates": [
          -48.857571,
          -28.1489441
        ]
      }
    },
    {
      "type": "Feature",
      "id": "node/8181431484",
      "properties": {
        "timestamp": "2021-08-13T06:51:48Z",
        "version": 2,
        "changeset": 109608654,
        "waterway": "waterfall",
        "id": "node/8181431484"
      },
      "geometry": {
        "type": "Point",
        "coordinates": [
          -48.836894,
          -28.1518113
        ]
      }
    },
    {
      "type": "Feature",
      "id": "node/8181431485",
      "properties": {
        "timestamp": "2021-08-13T06:51:48Z",
        "version": 2,
        "changeset": 109608654,
        "waterway": "waterfall",
        "id": "node/8181431485"
      },
      "geometry": {
        "type": "Point",
        "coordinates": [
          -48.8426804,
          -28.1510863
        ]
      }
    }
  ]
}
