{
  "type": "FeatureCollection",
  "features": [
    {
      "type": "Feature",
      "id": "node/8288160228",
      "properties": {
        "timestamp": "2022-10-15T21:02:25Z",
        "version": 2,
        "changeset": 127589322,
        "addr:housenumber": "1319",
        "addr:street": "Rua Luiz Pessoa da Silva Neto",
        "alt_name": "Câmara de Vereadores de Pinhal da Serra",
        "contact:email": "secretaria@cmps.rs.gov.br",
        "contact:phone": "+55 54 3698-4466",
        "contact:website": "https://www.cmps.rs.gov.br/",
        "government": "legislative",
        "name": "Câmara Municipal de Pinhal da Serra",
        "office": "government",
        "id": "node/8288160228"
      },
      "geometry": {
        "type": "Point",
        "coordinates": [
          -51.1710328,
          -27.8753662
        ]
      }
    }
  ]
}
