{
  "type": "FeatureCollection",
  "features": [
    {
      "type": "Feature",
      "id": "node/2665187938",
      "properties": {
        "timestamp": "2014-02-10T13:44:51Z",
        "version": 1,
        "changeset": 20485492,
        "historic": "memorial",
        "name": "Parque Estadual Mata dos Godoy",
        "id": "node/2665187938"
      },
      "geometry": {
        "type": "Point",
        "coordinates": [
          -51.2559057,
          -23.4418477
        ]
      }
    },
    {
      "type": "Feature",
      "id": "node/6475316460",
      "properties": {
        "timestamp": "2019-05-26T17:52:36Z",
        "version": 3,
        "changeset": 70638059,
        "description": "Monumento tipo placa de ferro",
        "historic": "memorial",
        "memorial": "plaque",
        "id": "node/6475316460"
      },
      "geometry": {
        "type": "Point",
        "coordinates": [
          -51.138132,
          -23.3418493
        ]
      }
    },
    {
      "type": "Feature",
      "id": "node/11176387351",
      "properties": {
        "timestamp": "2023-09-08T10:49:54Z",
        "version": 2,
        "changeset": 140981435,
        "artist:wikidata": "Q7288610",
        "artist_name": "Ram Vanji Sutar",
        "historic": "memorial",
        "material": "bronze",
        "memorial": "bust",
        "name": "Mahatma Gandhi",
        "start_date": "1999",
        "subject:wikidata": "Q1001",
        "subject:wikipedia": "pt:Mahatma Gandhi",
        "id": "node/11176387351"
      },
      "geometry": {
        "type": "Point",
        "coordinates": [
          -51.1979239,
          -23.3205825
        ]
      }
    }
  ]
}
