{
  "type": "FeatureCollection",
  "features": [
    {
      "type": "Feature",
      "id": "node/2033107457",
      "properties": {
        "timestamp": "2012-11-25T21:42:21Z",
        "version": 1,
        "changeset": 14037181,
        "amenity": "library",
        "name": "Biblioteca Municipal",
        "id": "node/2033107457"
      },
      "geometry": {
        "type": "Point",
        "coordinates": [
          -50.8741184,
          -21.7954712
        ]
      }
    }
  ]
}
