{
  "type": "FeatureCollection",
  "features": [
    {
      "type": "Feature",
      "id": "node/1754038836",
      "properties": {
        "timestamp": "2022-09-28T16:30:29Z",
        "version": 5,
        "changeset": 126748059,
        "amenity": "hospital",
        "emergency": "yes",
        "healthcare": "hospital",
        "name": "Hospital e Maternidade",
        "operator": "Sistema Único de Saúde",
        "operator:short": "SUS",
        "operator:wikidata": "Q7531056",
        "id": "node/1754038836"
      },
      "geometry": {
        "type": "Point",
        "coordinates": [
          -37.8210061,
          -4.6781873
        ]
      }
    },
    {
      "type": "Feature",
      "id": "node/1754044911",
      "properties": {
        "timestamp": "2012-05-15T17:29:24Z",
        "version": 1,
        "changeset": 11606497,
        "amenity": "hospital",
        "name": "Posto de Saúde da Família",
        "id": "node/1754044911"
      },
      "geometry": {
        "type": "Point",
        "coordinates": [
          -37.828615,
          -4.6776467
        ]
      }
    },
    {
      "type": "Feature",
      "id": "node/1754045402",
      "properties": {
        "timestamp": "2012-05-15T17:30:10Z",
        "version": 1,
        "changeset": 11606497,
        "amenity": "hospital",
        "name": "Posto de Saúde da Família São Francisco",
        "id": "node/1754045402"
      },
      "geometry": {
        "type": "Point",
        "coordinates": [
          -37.826158,
          -4.682341
        ]
      }
    },
    {
      "type": "Feature",
      "id": "node/1754350974",
      "properties": {
        "timestamp": "2012-05-15T22:16:20Z",
        "version": 1,
        "changeset": 11609346,
        "amenity": "hospital",
        "name": "PSF Alto Ferrão",
        "id": "node/1754350974"
      },
      "geometry": {
        "type": "Point",
        "coordinates": [
          -37.8074577,
          -4.7299233
        ]
      }
    },
    {
      "type": "Feature",
      "id": "node/1754512249",
      "properties": {
        "timestamp": "2012-05-16T04:41:09Z",
        "version": 1,
        "changeset": 11610750,
        "amenity": "hospital",
        "name": "Posto de Saúde da Família",
        "id": "node/1754512249"
      },
      "geometry": {
        "type": "Point",
        "coordinates": [
          -37.7797344,
          -4.7305007
        ]
      }
    }
  ]
}
