{
  "type": "FeatureCollection",
  "features": [
    {
      "type": "Feature",
      "id": "node/1754044341",
      "properties": {
        "timestamp": "2012-05-15T17:28:20Z",
        "version": 2,
        "changeset": 11606497,
        "amenity": "kindergarten",
        "name": "Creche CEI",
        "id": "node/1754044341"
      },
      "geometry": {
        "type": "Point",
        "coordinates": [
          -37.8253799,
          -4.6787214
        ]
      }
    },
    {
      "type": "Feature",
      "id": "node/1754511971",
      "properties": {
        "timestamp": "2012-05-16T04:38:42Z",
        "version": 1,
        "changeset": 11610750,
        "amenity": "kindergarten",
        "name": "Creche",
        "id": "node/1754511971"
      },
      "geometry": {
        "type": "Point",
        "coordinates": [
          -37.7787366,
          -4.7273625
        ]
      }
    }
  ]
}
