{
  "type": "FeatureCollection",
  "features": [
    {
      "type": "Feature",
      "id": "node/4957285805",
      "properties": {
        "timestamp": "2025-01-02T02:10:52Z",
        "version": 4,
        "changeset": 160891102,
        "addr:city": "Naviraí",
        "addr:housenumber": "912-A",
        "addr:postcode": "79950000",
        "addr:street": "Avenida Weimar Gonçalves Torres",
        "addr:suburb": "Centro",
        "amenity": "veterinary",
        "name": "Central Veterinária",
        "id": "node/4957285805"
      },
      "geometry": {
        "type": "Point",
        "coordinates": [
          -54.192528,
          -23.0647677
        ]
      }
    }
  ]
}
