{
  "type": "FeatureCollection",
  "features": [
    {
      "type": "Feature",
      "id": "node/4957285805",
      "properties": {
        "timestamp": "2022-07-18T05:53:47Z",
        "version": 3,
        "changeset": 123743900,
        "addr:city": "Naviraí",
        "addr:housenumber": "912-A",
        "addr:postcode": "79950000",
        "addr:street": "Avenida Weimar Goncalves Torres",
        "addr:suburb": "Centro",
        "amenity": "veterinary",
        "name": "Central Veterinária",
        "id": "node/4957285805"
      },
      "geometry": {
        "type": "Point",
        "coordinates": [
          -54.192528,
          -23.0647677
        ]
      }
    }
  ]
}
