{
  "type": "FeatureCollection",
  "features": [
    {
      "type": "Feature",
      "id": "node/3654792799",
      "properties": {
        "timestamp": "2015-07-16T20:20:18Z",
        "version": 1,
        "changeset": 32683842,
        "waterway": "waterfall",
        "id": "node/3654792799"
      },
      "geometry": {
        "type": "Point",
        "coordinates": [
          -41.8590717,
          -19.9037697
        ]
      }
    },
    {
      "type": "Feature",
      "id": "node/8736777895",
      "properties": {
        "timestamp": "2021-05-19T11:22:12Z",
        "version": 2,
        "changeset": 104956321,
        "name": "Cachoeira do Marreco",
        "waterway": "waterfall",
        "id": "node/8736777895"
      },
      "geometry": {
        "type": "Point",
        "coordinates": [
          -42.0105675,
          -19.9649237
        ]
      }
    },
    {
      "type": "Feature",
      "id": "node/8745615846",
      "properties": {
        "timestamp": "2021-05-19T11:22:12Z",
        "version": 1,
        "changeset": 104956321,
        "waterway": "waterfall",
        "id": "node/8745615846"
      },
      "geometry": {
        "type": "Point",
        "coordinates": [
          -42.0621819,
          -19.9870838
        ]
      }
    }
  ]
}
