{
  "type": "FeatureCollection",
  "features": [
    {
      "type": "Feature",
      "id": "node/3767234010",
      "properties": {
        "timestamp": "2015-10-01T12:34:09Z",
        "version": 1,
        "changeset": 34366967,
        "name": "Piscina dos Elefantes",
        "waterway": "dam",
        "id": "node/3767234010"
      },
      "geometry": {
        "type": "Point",
        "coordinates": [
          -48.7742621,
          -25.2310737
        ]
      }
    }
  ]
}
