{
  "type": "FeatureCollection",
  "features": [
    {
      "type": "Feature",
      "id": "node/6783945366",
      "properties": {
        "timestamp": "2019-09-09T23:07:41Z",
        "version": 1,
        "changeset": 74283621,
        "historic": "memorial",
        "material": "concrete",
        "memorial": "memorial",
        "name": "Memorial Frei Damião",
        "id": "node/6783945366"
      },
      "geometry": {
        "type": "Point",
        "coordinates": [
          -36.4195797,
          -9.3653301
        ]
      }
    }
  ]
}
