{
  "type": "FeatureCollection",
  "features": [
    {
      "type": "Feature",
      "id": "node/6143240022",
      "properties": {
        "timestamp": "2022-10-17T02:43:31Z",
        "version": 4,
        "changeset": 127644423,
        "intermittent": "no",
        "name": "Cachoeira dos Corvos",
        "waterway": "waterfall",
        "id": "node/6143240022"
      },
      "geometry": {
        "type": "Point",
        "coordinates": [
          -54.7644239,
          -29.3902359
        ]
      }
    },
    {
      "type": "Feature",
      "id": "node/6143240030",
      "properties": {
        "timestamp": "2022-10-17T02:43:31Z",
        "version": 3,
        "changeset": 127644423,
        "name": "Cascata Veu de Noiva",
        "waterway": "waterfall",
        "id": "node/6143240030"
      },
      "geometry": {
        "type": "Point",
        "coordinates": [
          -54.7676711,
          -29.3917871
        ]
      }
    }
  ]
}
