{
  "type": "FeatureCollection",
  "features": [
    {
      "type": "Feature",
      "id": "node/2347351782",
      "properties": {
        "timestamp": "2023-09-11T22:09:51Z",
        "version": 4,
        "changeset": 141135228,
        "height": "85",
        "name": "Cachoeira do Buracão",
        "tourism": "attraction",
        "waterway": "waterfall",
        "id": "node/2347351782"
      },
      "geometry": {
        "type": "Point",
        "coordinates": [
          -41.1454355,
          -13.3260723
        ]
      }
    },
    {
      "type": "Feature",
      "id": "node/11073499606",
      "properties": {
        "timestamp": "2023-10-14T23:55:35Z",
        "version": 2,
        "changeset": 142595531,
        "name": "Cachoeira do Rio Preto",
        "waterway": "waterfall",
        "id": "node/11073499606"
      },
      "geometry": {
        "type": "Point",
        "coordinates": [
          -41.2663677,
          -13.3832554
        ]
      }
    }
  ]
}
