{
  "type": "FeatureCollection",
  "features": [
    {
      "type": "Feature",
      "id": "node/1654321161",
      "properties": {
        "timestamp": "2013-06-26T01:23:21Z",
        "version": 2,
        "changeset": 16707228,
        "amenity": "kindergarten",
        "name": "Inflável Park",
        "id": "node/1654321161"
      },
      "geometry": {
        "type": "Point",
        "coordinates": [
          -51.0012447,
          -29.9503898
        ]
      }
    },
    {
      "type": "Feature",
      "id": "node/7133607711",
      "properties": {
        "timestamp": "2020-01-15T16:38:24Z",
        "version": 1,
        "changeset": 79614624,
        "amenity": "kindergarten",
        "name": "E.M.E.I Marechal Rondon",
        "id": "node/7133607711"
      },
      "geometry": {
        "type": "Point",
        "coordinates": [
          -51.0580752,
          -29.9051507
        ]
      }
    }
  ]
}
