{
  "type": "FeatureCollection",
  "features": [
    {
      "type": "Feature",
      "id": "node/5407650321",
      "properties": {
        "timestamp": "2018-03-02T19:09:32Z",
        "version": 2,
        "changeset": 56829864,
        "addr:housenumber": "67",
        "addr:postcode": "94055-420",
        "addr:street": "Rua Pinho",
        "amenity": "nursing_home",
        "name": "casa do Ar & Mar",
        "id": "node/5407650321"
      },
      "geometry": {
        "type": "Point",
        "coordinates": [
          -51.0316708,
          -29.9408991
        ]
      }
    }
  ]
}
