{
  "type": "FeatureCollection",
  "features": [
    {
      "type": "Feature",
      "id": "node/5932927129",
      "properties": {
        "timestamp": "2022-07-26T16:55:52Z",
        "version": 3,
        "changeset": 124105102,
        "description": "Pousada, Gastronomia e Lazer",
        "email": "mauroefernandes@hotmail.com",
        "internet_access:ssid": "Fazenda Fernandes",
        "name": "Fazenda Fernandes",
        "phone": "+55 48 9 9629 2646;+55 48 9 9999 2120",
        "rooms": "3",
        "tourism": "guest_house",
        "id": "node/5932927129"
      },
      "geometry": {
        "type": "Point",
        "coordinates": [
          -49.4807071,
          -28.5321794
        ]
      }
    }
  ]
}
