{
  "type": "FeatureCollection",
  "features": [
    {
      "type": "Feature",
      "id": "node/4031971783",
      "properties": {
        "timestamp": "2024-01-05T00:32:20Z",
        "version": 2,
        "changeset": 145901797,
        "addr:city": "Crisólita",
        "addr:housenumber": "99",
        "addr:postcode": "39885-000",
        "addr:street": "Rua Antônio José Gonçalves",
        "addr:suburb": "Centro",
        "amenity": "school",
        "name": "Escola Estadual Raul Ferreira Souto",
        "operator": "Secretaria de Estado da Educação de Minas Gerais",
        "operator:type": "public",
        "source": "IBGE",
        "id": "node/4031971783"
      },
      "geometry": {
        "type": "Point",
        "coordinates": [
          -40.910934,
          -17.2362872
        ]
      }
    },
    {
      "type": "Feature",
      "id": "node/11489429132",
      "properties": {
        "timestamp": "2024-01-05T00:32:20Z",
        "version": 1,
        "changeset": 145901797,
        "addr:city": "Crisólita",
        "addr:housenumber": "19",
        "addr:postcode": "39885-000",
        "addr:street": "Rua Antônio José Gonçalves",
        "addr:suburb": "Centro",
        "amenity": "school",
        "name": "Escola Municipal João Gonçalves da Rocha",
        "operator": "Município de Crisólita",
        "operator:type": "public",
        "id": "node/11489429132"
      },
      "geometry": {
        "type": "Point",
        "coordinates": [
          -40.9113852,
          -17.2369798
        ]
      }
    }
  ]
}
