{
  "type": "FeatureCollection",
  "features": [
    {
      "type": "Feature",
      "id": "node/4186519783",
      "properties": {
        "timestamp": "2023-12-31T11:34:51Z",
        "version": 2,
        "changeset": 145728905,
        "addr:city": "Joaíma",
        "addr:housenumber": "400",
        "addr:postcode": "39890-000",
        "addr:street": "Rua Brasília",
        "addr:suburb": "Centro",
        "amenity": "university",
        "email": "nucleo.joaima@unimontes.br",
        "name": "Campus Unimontes",
        "operator": "Universidade Estadual de Montes Claros",
        "operator:type": "public",
        "phone": "+55 33 3745 1599",
        "id": "node/4186519783"
      },
      "geometry": {
        "type": "Point",
        "coordinates": [
          -41.0281799,
          -16.6588626
        ]
      }
    }
  ]
}
