{
  "type": "FeatureCollection",
  "features": [
    {
      "type": "Feature",
      "id": "node/6166934028",
      "properties": {
        "timestamp": "2020-02-27T05:19:08Z",
        "version": 3,
        "changeset": 81530566,
        "amenity": "dentist",
        "healthcare": "dentist",
        "name": "Oral Live",
        "phone": "+55 55 3522-3280",
        "id": "node/6166934028"
      },
      "geometry": {
        "type": "Point",
        "coordinates": [
          -53.9290292,
          -27.4563857
        ]
      }
    },
    {
      "type": "Feature",
      "id": "node/6185130715",
      "properties": {
        "timestamp": "2019-01-07T01:13:28Z",
        "version": 2,
        "changeset": 66083707,
        "amenity": "dentist",
        "healthcare": "dentist",
        "name": "Marlise Beatriz Grolli",
        "phone": "+55 55 3522-1713",
        "id": "node/6185130715"
      },
      "geometry": {
        "type": "Point",
        "coordinates": [
          -53.9300895,
          -27.4562984
        ]
      }
    },
    {
      "type": "Feature",
      "id": "node/6351124302",
      "properties": {
        "timestamp": "2020-02-27T05:19:08Z",
        "version": 3,
        "changeset": 81530566,
        "amenity": "dentist",
        "healthcare": "dentist",
        "name": "Lucimári da Costa",
        "phone": "+55 55 98110-6105",
        "id": "node/6351124302"
      },
      "geometry": {
        "type": "Point",
        "coordinates": [
          -53.9320328,
          -27.4551832
        ]
      }
    }
  ]
}
