{
  "type": "FeatureCollection",
  "features": [
    {
      "type": "Feature",
      "id": "node/2493342295",
      "properties": {
        "timestamp": "2023-05-03T15:01:05Z",
        "version": 2,
        "changeset": 135664973,
        "addr:city": "Limeira do Oeste",
        "addr:postcode": "38295000",
        "addr:street": "Zona Rural",
        "name": "Cachoeira do Salto de São Domingos 4",
        "waterway": "waterfall",
        "id": "node/2493342295"
      },
      "geometry": {
        "type": "Point",
        "coordinates": [
          -50.6901337,
          -19.2167565
        ]
      }
    },
    {
      "type": "Feature",
      "id": "node/2493342661",
      "properties": {
        "timestamp": "2013-10-12T03:22:08Z",
        "version": 1,
        "changeset": 18307841,
        "waterway": "waterfall",
        "id": "node/2493342661"
      },
      "geometry": {
        "type": "Point",
        "coordinates": [
          -50.586993,
          -19.2263959
        ]
      }
    },
    {
      "type": "Feature",
      "id": "node/2493342698",
      "properties": {
        "timestamp": "2013-10-12T03:22:09Z",
        "version": 1,
        "changeset": 18307841,
        "waterway": "waterfall",
        "id": "node/2493342698"
      },
      "geometry": {
        "type": "Point",
        "coordinates": [
          -50.5871427,
          -19.227053
        ]
      }
    }
  ]
}
