{
  "type": "FeatureCollection",
  "features": [
    {
      "type": "Feature",
      "id": "node/6720148851",
      "properties": {
        "timestamp": "2019-08-18T01:56:17Z",
        "version": 1,
        "changeset": 73454417,
        "addr:postcode": "39373-000",
        "amenity": "clinic",
        "healthcare": "clinic",
        "id": "node/6720148851"
      },
      "geometry": {
        "type": "Point",
        "coordinates": [
          -44.224833,
          -16.1315262
        ]
      }
    }
  ]
}
