{
  "type": "FeatureCollection",
  "features": [
    {
      "type": "Feature",
      "id": "node/3796757054",
      "properties": {
        "timestamp": "2022-12-24T13:51:05Z",
        "version": 2,
        "changeset": 130457150,
        "amenity": "arts_centre",
        "name": "Centro Cultural Inúbia",
        "id": "node/3796757054"
      },
      "geometry": {
        "type": "Point",
        "coordinates": [
          -51.496616,
          -30.9125064
        ]
      }
    }
  ]
}
