{
  "type": "FeatureCollection",
  "features": [
    {
      "type": "Feature",
      "id": "node/9585575991",
      "properties": {
        "timestamp": "2022-03-28T10:47:12Z",
        "version": 3,
        "changeset": 119015850,
        "amenity": "dentist",
        "description": "Clínica Odontológica",
        "healthcare": "dentist",
        "name": "JK Clínica - Odontologia Especializada",
        "id": "node/9585575991"
      },
      "geometry": {
        "type": "Point",
        "coordinates": [
          -42.6587121,
          -14.7685628
        ]
      }
    }
  ]
}
