{
  "type": "FeatureCollection",
  "features": [
    {
      "type": "Feature",
      "id": "node/4989945555",
      "properties": {
        "timestamp": "2022-10-17T13:10:27Z",
        "version": 3,
        "changeset": 127672622,
        "amenity": "cinema",
        "name": "Cinemas Teresina",
        "website": "https://www.cinemasteresina.com.br",
        "id": "node/4989945555"
      },
      "geometry": {
        "type": "Point",
        "coordinates": [
          -42.7888479,
          -5.0850624
        ]
      }
    },
    {
      "type": "Feature",
      "id": "node/7327205913",
      "properties": {
        "timestamp": "2020-03-25T03:31:18Z",
        "version": 1,
        "changeset": 82595715,
        "amenity": "cinema",
        "brand": "Cinepolis",
        "brand:wikidata": "Q5686673",
        "brand:wikipedia": "en:Cinépolis",
        "name": "Cinepolis",
        "id": "node/7327205913"
      },
      "geometry": {
        "type": "Point",
        "coordinates": [
          -42.8020565,
          -5.0778076
        ]
      }
    }
  ]
}
