{
  "type": "FeatureCollection",
  "features": [
    {
      "type": "Feature",
      "id": "node/5136334921",
      "properties": {
        "timestamp": "2020-05-22T20:04:23Z",
        "version": 2,
        "changeset": 85629635,
        "addr:city": "Mirassol",
        "addr:housenumber": "1998",
        "addr:street": "Rua Campos Sales",
        "addr:suburb": "Centro",
        "amenity": "college",
        "name": "Senai",
        "phone": "+55 17 3243 8030",
        "id": "node/5136334921"
      },
      "geometry": {
        "type": "Point",
        "coordinates": [
          -49.5105797,
          -20.8197868
        ]
      }
    }
  ]
}
