{
  "type": "FeatureCollection",
  "features": [
    {
      "type": "Feature",
      "id": "node/10189230018",
      "properties": {
        "timestamp": "2022-11-16T17:29:13Z",
        "version": 1,
        "changeset": 129002972,
        "addr:city": "Rio Vermelho",
        "addr:housenumber": "65",
        "addr:postcode": "39170-000",
        "addr:street": "Avenida Aurelio Rodrigues Magalhães",
        "addr:suburb": "Centro",
        "amenity": "clinic",
        "healthcare": "clinic",
        "healthcare:speciality": "general",
        "name": "Centro de Saúde de Rio Vermelho",
        "operator": "Município de Rio Vermelho",
        "operator:type": "public",
        "phone": "+55 33 3436 1111",
        "id": "node/10189230018"
      },
      "geometry": {
        "type": "Point",
        "coordinates": [
          -43.0088167,
          -18.2925455
        ]
      }
    },
    {
      "type": "Feature",
      "id": "node/10189230181",
      "properties": {
        "timestamp": "2022-11-16T17:29:13Z",
        "version": 1,
        "changeset": 129002972,
        "addr:city": "Rio Vermelho",
        "addr:postcode": "39170-000",
        "amenity": "clinic",
        "healthcare": "clinic",
        "healthcare:speciality": "general",
        "name": "Unidade de Saúde da Família Ponte",
        "id": "node/10189230181"
      },
      "geometry": {
        "type": "Point",
        "coordinates": [
          -43.0037202,
          -18.289844
        ]
      }
    },
    {
      "type": "Feature",
      "id": "node/10189230184",
      "properties": {
        "timestamp": "2022-11-16T17:29:13Z",
        "version": 1,
        "changeset": 129002972,
        "addr:city": "Rio Vermelho",
        "addr:postcode": "39165-000",
        "addr:street": "Praça Sagrado Coração de Jesus",
        "addr:suburb": "Pedra Menina",
        "amenity": "clinic",
        "healthcare": "clinic",
        "healthcare:speciality": "general",
        "name": "Unidade de Saúde da Família de Pedra Menina",
        "operator": "Município de Rio Vermelho",
        "operator:type": "public",
        "id": "node/10189230184"
      },
      "geometry": {
        "type": "Point",
        "coordinates": [
          -43.1147189,
          -18.1150497
        ]
      }
    }
  ]
}
