{
  "type": "FeatureCollection",
  "features": [
    {
      "type": "Feature",
      "id": "node/2862007325",
      "properties": {
        "timestamp": "2014-05-16T12:32:29Z",
        "version": 1,
        "changeset": 22370473,
        "name": "Hotel Estrela",
        "tourism": "hotel",
        "id": "node/2862007325"
      },
      "geometry": {
        "type": "Point",
        "coordinates": [
          -43.3223057,
          -19.4159577
        ]
      }
    },
    {
      "type": "Feature",
      "id": "node/5667972405",
      "properties": {
        "timestamp": "2024-10-28T09:31:25Z",
        "version": 4,
        "changeset": 158446756,
        "addr:city": "Itambé do Mato Dentro",
        "addr:housenumber": "256",
        "addr:postcode": "35820-000",
        "addr:street": "Rua Nova Vista",
        "internet_access": "yes",
        "internet_access:fee": "no",
        "name": "Pousada Lá no Tererê",
        "phone": "+55 31 995914878",
        "rooms": "7",
        "stars": "5",
        "tourism": "hotel",
        "id": "node/5667972405"
      },
      "geometry": {
        "type": "Point",
        "coordinates": [
          -43.3939933,
          -19.4000409
        ]
      }
    },
    {
      "type": "Feature",
      "id": "node/5675472800",
      "properties": {
        "timestamp": "2018-06-08T13:30:20Z",
        "version": 1,
        "changeset": 59669650,
        "addr:street": "Rua do Rio Preto",
        "name": "Pousada Serra do Lobo",
        "tourism": "hotel",
        "id": "node/5675472800"
      },
      "geometry": {
        "type": "Point",
        "coordinates": [
          -43.3932456,
          -19.4017189
        ]
      }
    },
    {
      "type": "Feature",
      "id": "node/5675521050",
      "properties": {
        "timestamp": "2018-06-08T13:43:27Z",
        "version": 1,
        "changeset": 59669997,
        "addr:city": "Itambé do Mato Dentro",
        "addr:housenumber": "730",
        "addr:postcode": "35820-000",
        "addr:street": "Rua Prudente de Morais",
        "name": "Pousada Portal do Itambé",
        "tourism": "hotel",
        "id": "node/5675521050"
      },
      "geometry": {
        "type": "Point",
        "coordinates": [
          -43.3201959,
          -19.4243431
        ]
      }
    }
  ]
}
