{
  "type": "FeatureCollection",
  "features": [
    {
      "type": "Feature",
      "id": "node/5685066030",
      "properties": {
        "timestamp": "2018-06-12T12:49:08Z",
        "version": 2,
        "changeset": 59777519,
        "addr:city": "Itambé do Mato Dentro",
        "addr:housenumber": "80",
        "addr:postcode": "35820000",
        "addr:street": "Rua Principal",
        "addr:suburb": "Centro",
        "amenity": "pharmacy",
        "dispensing": "yes",
        "healthcare": "pharmacy",
        "name": "Drogaria Itambé",
        "phone": "+55 31 3836 5309",
        "id": "node/5685066030"
      },
      "geometry": {
        "type": "Point",
        "coordinates": [
          -43.3225359,
          -19.4144209
        ]
      }
    }
  ]
}
