{
  "type": "FeatureCollection",
  "features": [
    {
      "type": "Feature",
      "id": "node/4706945313",
      "properties": {
        "timestamp": "2017-09-07T18:50:59Z",
        "version": 2,
        "changeset": 51821610,
        "ele": "29.9",
        "historic": "monument",
        "name": "Estátua de Nossa Senhora do Prazeres",
        "id": "node/4706945313"
      },
      "geometry": {
        "type": "Point",
        "coordinates": [
          -38.6542869,
          -3.7352856
        ]
      }
    },
    {
      "type": "Feature",
      "id": "node/4707663832",
      "properties": {
        "timestamp": "2017-02-27T04:18:13Z",
        "version": 1,
        "changeset": 46431887,
        "historic": "monument",
        "name": "Santa Teresinha",
        "id": "node/4707663832"
      },
      "geometry": {
        "type": "Point",
        "coordinates": [
          -38.6502716,
          -3.739672
        ]
      }
    },
    {
      "type": "Feature",
      "id": "node/5655130243",
      "properties": {
        "timestamp": "2020-12-07T18:59:53Z",
        "version": 2,
        "changeset": 95441106,
        "historic": "monument",
        "name": "Santuário Santa Edwiges",
        "id": "node/5655130243"
      },
      "geometry": {
        "type": "Point",
        "coordinates": [
          -38.7617701,
          -3.6672442
        ]
      }
    }
  ]
}
