{
  "type": "FeatureCollection",
  "features": [
    {
      "type": "Feature",
      "id": "node/5879742287",
      "properties": {
        "timestamp": "2018-09-03T22:27:11Z",
        "version": 1,
        "changeset": 62260933,
        "addr:housenumber": "1671",
        "addr:postcode": "61648-105",
        "addr:street": "Rua Andira",
        "amenity": "nursing_home",
        "name": "Potira ll, Caucaia.",
        "id": "node/5879742287"
      },
      "geometry": {
        "type": "Point",
        "coordinates": [
          -38.6255232,
          -3.75472
        ]
      }
    }
  ]
}
