{
  "type": "FeatureCollection",
  "features": [
    {
      "type": "Feature",
      "id": "node/11804337321",
      "properties": {
        "timestamp": "2024-04-09T08:46:49Z",
        "version": 1,
        "changeset": 149765359,
        "historic": "monument",
        "name": "Casarão",
        "id": "node/11804337321"
      },
      "geometry": {
        "type": "Point",
        "coordinates": [
          -45.7190554,
          -22.5945161
        ]
      }
    }
  ]
}
