{
  "type": "FeatureCollection",
  "features": [
    {
      "type": "Feature",
      "id": "node/4993689521",
      "properties": {
        "timestamp": "2017-07-26T01:46:32Z",
        "version": 1,
        "changeset": 50573937,
        "amenity": "school",
        "name": "Escola São Judas Tadeu",
        "name:pt": "Escola São Judas Tadeu",
        "id": "node/4993689521"
      },
      "geometry": {
        "type": "Point",
        "coordinates": [
          -65.0178884,
          -11.8827905
        ]
      }
    }
  ]
}
