{
  "type": "FeatureCollection",
  "features": [
    {
      "type": "Feature",
      "id": "node/11795508213",
      "properties": {
        "timestamp": "2024-04-06T14:29:25Z",
        "version": 1,
        "changeset": 149657941,
        "amenity": "library",
        "id": "node/11795508213"
      },
      "geometry": {
        "type": "Point",
        "coordinates": [
          -41.5269459,
          -7.0529409
        ]
      }
    },
    {
      "type": "Feature",
      "id": "node/12532884287",
      "properties": {
        "timestamp": "2025-02-10T23:53:35Z",
        "version": 3,
        "changeset": 162371695,
        "amenity": "library",
        "name": "Bloco de Biologia e Nutrição/UFPI-Picos",
        "id": "node/12532884287"
      },
      "geometry": {
        "type": "Point",
        "coordinates": [
          -41.4345673,
          -7.0810965
        ]
      }
    },
    {
      "type": "Feature",
      "id": "node/12532884293",
      "properties": {
        "timestamp": "2025-02-10T23:53:35Z",
        "version": 3,
        "changeset": 162371695,
        "amenity": "library",
        "name": "Biblioteca José Albano de Macedo",
        "id": "node/12532884293"
      },
      "geometry": {
        "type": "Point",
        "coordinates": [
          -41.4353372,
          -7.0829327
        ]
      }
    }
  ]
}
