{
  "type": "FeatureCollection",
  "features": [
    {
      "type": "Feature",
      "id": "node/7056993544",
      "properties": {
        "timestamp": "2022-10-08T16:09:50Z",
        "version": 2,
        "changeset": 127210221,
        "government": "social_security",
        "name": "INSS",
        "office": "government",
        "operator": "Instituto Nacional do Seguro Social",
        "operator:short": "INSS",
        "operator:wikidata": "Q10302614",
        "id": "node/7056993544"
      },
      "geometry": {
        "type": "Point",
        "coordinates": [
          -48.9216412,
          -19.3033223
        ]
      }
    }
  ]
}
