{
  "type": "FeatureCollection",
  "features": [
    {
      "type": "Feature",
      "id": "node/7017720743",
      "properties": {
        "timestamp": "2022-04-10T14:17:25Z",
        "version": 3,
        "changeset": 119537600,
        "access": "yes",
        "ele": "738",
        "historic": "monument",
        "name": "Morrinho - Imagem de Nossa Senhora do Carmo",
        "natural": "peak",
        "id": "node/7017720743"
      },
      "geometry": {
        "type": "Point",
        "coordinates": [
          -48.9542579,
          -19.3036819
        ]
      }
    }
  ]
}
