{
  "type": "FeatureCollection",
  "features": [
    {
      "type": "Feature",
      "id": "node/1749704439",
      "properties": {
        "timestamp": "2012-05-12T14:18:15Z",
        "version": 1,
        "changeset": 11576596,
        "amenity": "college",
        "name": "Colégio Estadual Boa Vista",
        "id": "node/1749704439"
      },
      "geometry": {
        "type": "Point",
        "coordinates": [
          -49.3597164,
          -25.3764218
        ]
      }
    }
  ]
}
