{
  "type": "FeatureCollection",
  "features": [
    {
      "type": "Feature",
      "id": "node/4556251490",
      "properties": {
        "timestamp": "2018-01-27T02:37:26Z",
        "version": 3,
        "changeset": 55791976,
        "addr:housenumber": "1507",
        "addr:street": "Rua Venancio Aires",
        "amenity": "community_centre",
        "description": "Serviço Social do Comércio",
        "name": "SESC - Serviço Social do Comércio",
        "id": "node/4556251490"
      },
      "geometry": {
        "type": "Point",
        "coordinates": [
          -53.6067335,
          -28.6446677
        ]
      }
    },
    {
      "type": "Feature",
      "id": "node/5371368866",
      "properties": {
        "timestamp": "2018-11-06T04:04:00Z",
        "version": 2,
        "changeset": 64217573,
        "amenity": "community_centre",
        "name": "Consulado S. C. Internacional",
        "id": "node/5371368866"
      },
      "geometry": {
        "type": "Point",
        "coordinates": [
          -53.5895008,
          -28.6520659
        ]
      }
    }
  ]
}
