{
  "type": "FeatureCollection",
  "features": [
    {
      "type": "Feature",
      "id": "node/10688804605",
      "properties": {
        "timestamp": "2023-02-23T16:47:10Z",
        "version": 1,
        "changeset": 132935216,
        "addr:housenumber": "472",
        "addr:postcode": "13900-000",
        "addr:street": "Rua Quintino Bocaiúva",
        "amenity": "doctors",
        "email": "medtrans@yahoo.com.br",
        "name": "Medtrans Exames Detran",
        "name:pt": "MEDTRANS Exames Médicos Detran",
        "phone": "3807-6757",
        "id": "node/10688804605"
      },
      "geometry": {
        "type": "Point",
        "coordinates": [
          -46.7635201,
          -22.7041225
        ]
      }
    }
  ]
}
