{
  "type": "FeatureCollection",
  "features": [
    {
      "type": "Feature",
      "id": "node/6554121492",
      "properties": {
        "timestamp": "2019-06-17T22:45:29Z",
        "version": 1,
        "changeset": 71346177,
        "historic": "memorial",
        "memorial": "memorial",
        "name": "Marco da Praça Penha",
        "id": "node/6554121492"
      },
      "geometry": {
        "type": "Point",
        "coordinates": [
          -53.9131939,
          -28.4004443
        ]
      }
    }
  ]
}
