{
  "type": "FeatureCollection",
  "features": [
    {
      "type": "Feature",
      "id": "node/7270759093",
      "properties": {
        "timestamp": "2020-03-06T00:38:45Z",
        "version": 1,
        "changeset": 81843370,
        "historic": "memorial",
        "memorial": "bust",
        "name": "Santos Dumont",
        "id": "node/7270759093"
      },
      "geometry": {
        "type": "Point",
        "coordinates": [
          -34.9482568,
          -7.1456293
        ]
      }
    }
  ]
}
