{
  "type": "FeatureCollection",
  "features": [
    {
      "type": "Feature",
      "id": "node/9256106467",
      "properties": {
        "timestamp": "2021-11-16T10:49:38Z",
        "version": 1,
        "changeset": 113845739,
        "addr:city": "Bayeux",
        "addr:street": "Joao XXIII",
        "addr:suburb": "Sesi",
        "amenity": "school",
        "name": "Escola Cidadã Integral Irineu Pinto",
        "id": "node/9256106467"
      },
      "geometry": {
        "type": "Point",
        "coordinates": [
          -34.9163949,
          -7.1236754
        ]
      }
    }
  ]
}
