{
  "type": "FeatureCollection",
  "features": [
    {
      "type": "Feature",
      "id": "node/9931736317",
      "properties": {
        "timestamp": "2022-08-04T12:40:21Z",
        "version": 1,
        "changeset": 124479510,
        "addr:street": "Avenida Lindolfo Braga",
        "name": "Setor de combate às endemias",
        "office": "government",
        "id": "node/9931736317"
      },
      "geometry": {
        "type": "Point",
        "coordinates": [
          -39.9698469,
          -3.5707
        ]
      }
    }
  ]
}
