{
  "type": "FeatureCollection",
  "features": [
    {
      "type": "Feature",
      "id": "node/3600718769",
      "properties": {
        "timestamp": "2015-06-18T14:44:17Z",
        "version": 2,
        "changeset": 32052793,
        "addr:city": "Itaúna",
        "addr:housenumber": "270",
        "addr:street": "Praça Doutor Augusto Gonçalves",
        "name": "Hotel Ponto Chic",
        "tourism": "hotel",
        "id": "node/3600718769"
      },
      "geometry": {
        "type": "Point",
        "coordinates": [
          -44.5770229,
          -20.0741158
        ]
      }
    },
    {
      "type": "Feature",
      "id": "node/3600718770",
      "properties": {
        "timestamp": "2015-06-17T15:57:32Z",
        "version": 1,
        "changeset": 32032313,
        "name": "Grande Hotel Itaúna",
        "tourism": "hotel",
        "id": "node/3600718770"
      },
      "geometry": {
        "type": "Point",
        "coordinates": [
          -44.5784659,
          -20.0695911
        ]
      }
    }
  ]
}
