{
  "type": "FeatureCollection",
  "features": [
    {
      "type": "Feature",
      "id": "node/5485301805",
      "properties": {
        "timestamp": "2018-03-17T20:43:06Z",
        "version": 1,
        "changeset": 57275811,
        "name": "Secretaria FeIga",
        "office": "government",
        "id": "node/5485301805"
      },
      "geometry": {
        "type": "Point",
        "coordinates": [
          -47.6079558,
          -1.1284086
        ]
      }
    },
    {
      "type": "Feature",
      "id": "node/6603559356",
      "properties": {
        "timestamp": "2019-07-10T17:56:52Z",
        "version": 1,
        "changeset": 72105758,
        "addr:city": "Igarapé-Açu",
        "addr:street": "Avenida Barão do Rio Branco",
        "name": "Câmara Municipal de Igarapé-Açu",
        "office": "government",
        "id": "node/6603559356"
      },
      "geometry": {
        "type": "Point",
        "coordinates": [
          -47.6246085,
          -1.1275953
        ]
      }
    }
  ]
}
