{
  "type": "FeatureCollection",
  "features": [
    {
      "type": "Feature",
      "id": "node/7921736885",
      "properties": {
        "timestamp": "2020-09-19T02:14:54Z",
        "version": 2,
        "changeset": 91137878,
        "addr:housenumber": "476",
        "addr:street": "Rua Joāo Gama",
        "amenity": "pharmacy",
        "name": "Farmácia Morro Branco",
        "name:pt": "Farmácia Gama Morro Branco",
        "id": "node/7921736885"
      },
      "geometry": {
        "type": "Point",
        "coordinates": [
          -38.1138212,
          -4.1537234
        ]
      }
    },
    {
      "type": "Feature",
      "id": "node/8792001249",
      "properties": {
        "timestamp": "2021-06-02T13:20:46Z",
        "version": 1,
        "changeset": 105723096,
        "amenity": "pharmacy",
        "name": "Gama",
        "id": "node/8792001249"
      },
      "geometry": {
        "type": "Point",
        "coordinates": [
          -38.129795,
          -4.1821346
        ]
      }
    },
    {
      "type": "Feature",
      "id": "node/8798301035",
      "properties": {
        "timestamp": "2021-06-04T10:17:50Z",
        "version": 1,
        "changeset": 105831223,
        "addr:street": "Rua João Baltazar",
        "amenity": "pharmacy",
        "name": "Farmácia Beberibe",
        "opening_hours": "Mo-Sa 09:00-18:00",
        "id": "node/8798301035"
      },
      "geometry": {
        "type": "Point",
        "coordinates": [
          -38.1316922,
          -4.1813219
        ]
      }
    }
  ]
}
