{
  "type": "FeatureCollection",
  "features": [
    {
      "type": "Feature",
      "id": "node/10090285471",
      "properties": {
        "timestamp": "2022-10-10T18:05:39Z",
        "version": 1,
        "changeset": 127317509,
        "addr:city": "Divinolândia de Minas",
        "addr:housenumber": "189",
        "addr:postcode": "39735-000",
        "addr:street": "Rua Escrivã Conceição Carvalhais",
        "addr:suburb": "Centro",
        "government": "register_office",
        "name": "Cartório Andrade Silva",
        "office": "government",
        "operator": "Ofício do Registro Civil com Atribuição Notarial",
        "phone": "+55 33 98705 2962",
        "id": "node/10090285471"
      },
      "geometry": {
        "type": "Point",
        "coordinates": [
          -42.6176374,
          -18.8006798
        ]
      }
    },
    {
      "type": "Feature",
      "id": "node/10092062565",
      "properties": {
        "timestamp": "2022-10-11T12:25:21Z",
        "version": 1,
        "changeset": 127357269,
        "addr:city": "Divinolândia de Minas",
        "addr:housenumber": "326",
        "addr:postcode": "39735-000",
        "addr:street": "Rua São José",
        "addr:suburb": "Centro",
        "government": "administrative",
        "name": "Secretaria Municipal de Saúde",
        "office": "government",
        "id": "node/10092062565"
      },
      "geometry": {
        "type": "Point",
        "coordinates": [
          -42.6124781,
          -18.8001557
        ]
      }
    }
  ]
}
