{
  "type": "FeatureCollection",
  "features": [
    {
      "type": "Feature",
      "id": "node/1767520203",
      "properties": {
        "timestamp": "2018-09-09T19:24:50Z",
        "version": 2,
        "changeset": 62433022,
        "amenity": "clinic",
        "emergency": "no",
        "name": "UBS Dom Bosco",
        "id": "node/1767520203"
      },
      "geometry": {
        "type": "Point",
        "coordinates": [
          -44.3886098,
          -19.2772594
        ]
      }
    }
  ]
}
