{
  "type": "FeatureCollection",
  "features": [
    {
      "type": "Feature",
      "id": "node/5368080922",
      "properties": {
        "timestamp": "2018-01-28T13:56:47Z",
        "version": 1,
        "changeset": 55829734,
        "name": "Funil",
        "waterway": "waterfall",
        "id": "node/5368080922"
      },
      "geometry": {
        "type": "Point",
        "coordinates": [
          -44.3647497,
          -19.2469261
        ]
      }
    }
  ]
}
