{
  "type": "FeatureCollection",
  "features": [
    {
      "type": "Feature",
      "id": "node/2966394693",
      "properties": {
        "timestamp": "2022-08-02T10:50:39Z",
        "version": 3,
        "changeset": 124385658,
        "addr:city": "Itambacuri",
        "addr:housenumber": "1308",
        "addr:postcode": "39830-000",
        "addr:street": "Avenida Farmacêutico Joviano",
        "addr:suburb": "Várzea",
        "amenity": "hospital",
        "healthcare": "hospital",
        "healthcare:speciality": "general",
        "name": "Hospital São Vicente de Paula",
        "source": "IBGE",
        "id": "node/2966394693"
      },
      "geometry": {
        "type": "Point",
        "coordinates": [
          -41.6708667,
          -18.0387782
        ]
      }
    },
    {
      "type": "Feature",
      "id": "node/3766981788",
      "properties": {
        "timestamp": "2023-05-25T23:40:23Z",
        "version": 3,
        "changeset": 136562550,
        "addr:city": "Itambacuri",
        "addr:housenumber": "578",
        "addr:postcode": "39830-000",
        "addr:street": "Avenida Frei Arcângelo de Módica",
        "addr:suburb": "Centro",
        "amenity": "hospital",
        "healthcare": "hospital",
        "healthcare:speciality": "pediatric;general",
        "name": "Hospital Tristão da Cunha",
        "operator": "Associação Protetora da Infância de Itambacuri",
        "operator:type": "private",
        "phone": "+55 33 3511 3030",
        "ref:CNES": "2697548",
        "ref:vatin": "BR21163811000183",
        "id": "node/3766981788"
      },
      "geometry": {
        "type": "Point",
        "coordinates": [
          -41.676202,
          -18.032514
        ]
      }
    },
    {
      "type": "Feature",
      "id": "node/9926710847",
      "properties": {
        "timestamp": "2023-05-25T23:40:23Z",
        "version": 2,
        "changeset": 136562550,
        "addr:city": "Itambacuri",
        "addr:housenumber": "1308",
        "addr:postcode": "39830-000",
        "addr:street": "Avenida Farmacêutico Joviano",
        "addr:suburb": "Várzea",
        "amenity": "hospital",
        "email": "honosean@hotmail.com",
        "emergency": "yes",
        "healthcare": "hospital",
        "healthcare:speciality": "general",
        "name": "Hospital Nossa Senhora dos Anjos",
        "operator": "Associação Hospitalar Nossa Senhora dos Anjos",
        "operator:type": "private",
        "phone": "+55 33 3511 1366",
        "ref:CNES": "2185563",
        "ref:vatin": "BR26202168000173",
        "id": "node/9926710847"
      },
      "geometry": {
        "type": "Point",
        "coordinates": [
          -41.6713715,
          -18.0385063
        ]
      }
    }
  ]
}
