{
  "type": "FeatureCollection",
  "features": [
    {
      "type": "Feature",
      "id": "node/9926710852",
      "properties": {
        "timestamp": "2022-08-02T10:50:39Z",
        "version": 1,
        "changeset": 124385658,
        "addr:city": "Itambacuri",
        "addr:housenumber": "395",
        "addr:postcode": "39830-000",
        "addr:street": "Avenida Farmacêutico Joviano",
        "addr:suburb": "Centro",
        "amenity": "pharmacy",
        "dispensing": "yes",
        "healthcare": "pharmacy",
        "name": "Farmácia Esperança",
        "operator": "Consórcio Intermunicipal de Saúde Entre os Vales do Mucuri e Jequitinhonha",
        "id": "node/9926710852"
      },
      "geometry": {
        "type": "Point",
        "coordinates": [
          -41.6788538,
          -18.0346754
        ]
      }
    }
  ]
}
