{
  "type": "FeatureCollection",
  "features": [
    {
      "type": "Feature",
      "id": "node/10059871543",
      "properties": {
        "timestamp": "2022-09-29T00:07:31Z",
        "version": 1,
        "changeset": 126758767,
        "name": "Centro Cultural",
        "official_name": "Centro Cultural Amaury de Carvalho",
        "source": "survey",
        "tourism": "gallery",
        "id": "node/10059871543"
      },
      "geometry": {
        "type": "Point",
        "coordinates": [
          -37.2757282,
          -7.0295759
        ]
      }
    }
  ]
}
