{
  "type": "FeatureCollection",
  "features": [
    {
      "type": "Feature",
      "id": "node/12405866709",
      "properties": {
        "timestamp": "2024-12-09T01:51:37Z",
        "version": 1,
        "changeset": 160075486,
        "addr:city": "Cerquilho",
        "addr:housenumber": "430",
        "addr:postcode": "18526-036",
        "addr:street": "Avenida Corradi Segundo",
        "addr:suburb": "Centro",
        "amenity": "dentist",
        "contact:facebook": "https://www.facebook.com/grecchiodontologia",
        "email": "contato@grecchiodontologia.com.br",
        "healthcare": "dentist",
        "healthcare:speciality": "dental_oral_maxillo_facial_surgery;dentist",
        "image": "https://grecchiodontologia.com.br/img/estrutura/02_image_fachada_2.jpg",
        "mobile": "+55 15 99763-2507",
        "name": "Grecchi Odontologia",
        "opening_hours": "Mo-Fr 08:00-11:30; Mo-Fr 13:00-18:30",
        "payment:account_cards": "yes",
        "payment:cards": "yes",
        "payment:cash": "yes",
        "payment:coins": "yes",
        "payment:contactless": "yes",
        "payment:credit_cards": "yes",
        "payment:debit_cards": "yes",
        "payment:maestro": "yes",
        "payment:mastercard": "yes",
        "payment:mastercard_contactless": "yes",
        "payment:notes": "yes",
        "payment:pix": "yes",
        "payment:visa": "yes",
        "payment:visa_debit": "yes",
        "payment:visa_electron": "yes",
        "phone": "+55 15 3284-2507",
        "start_date": "2005",
        "website": "https://www.grecchiodontologia.com.br/",
        "wheelchair": "yes",
        "id": "node/12405866709"
      },
      "geometry": {
        "type": "Point",
        "coordinates": [
          -47.7471518,
          -23.165686
        ]
      }
    }
  ]
}
