{
  "type": "FeatureCollection",
  "features": [
    {
      "type": "Feature",
      "id": "node/8205967096",
      "properties": {
        "timestamp": "2020-12-08T20:28:57Z",
        "version": 2,
        "changeset": 95510122,
        "addr:city": "Monte alegre de goias",
        "addr:postcode": "73830000",
        "addr:street": "Avenida da Prata",
        "amenity": "pharmacy",
        "dispensing": "yes",
        "healthcare": "pharmacy",
        "name": "Drogaria Popular",
        "id": "node/8205967096"
      },
      "geometry": {
        "type": "Point",
        "coordinates": [
          -46.7857159,
          -13.3322336
        ]
      }
    }
  ]
}
