{
  "type": "FeatureCollection",
  "features": [
    {
      "type": "Feature",
      "id": "node/5293718321",
      "properties": {
        "timestamp": "2021-03-01T20:01:30Z",
        "version": 2,
        "changeset": 100228355,
        "amenity": "doctors",
        "healthcare": "doctor",
        "name": "UBS Absolon Leite da Nóbrega",
        "id": "node/5293718321"
      },
      "geometry": {
        "type": "Point",
        "coordinates": [
          -36.8477562,
          -7.1035582
        ]
      }
    }
  ]
}
