{
  "type": "FeatureCollection",
  "features": [
    {
      "type": "Feature",
      "id": "node/7112782470",
      "properties": {
        "timestamp": "2023-01-21T22:54:28Z",
        "version": 2,
        "changeset": 131555979,
        "name": "Pousada Ruaro",
        "rooms": "9",
        "tourism": "guest_house",
        "id": "node/7112782470"
      },
      "geometry": {
        "type": "Point",
        "coordinates": [
          -51.7358362,
          -27.169128
        ]
      }
    }
  ]
}
