{
  "type": "FeatureCollection",
  "features": [
    {
      "type": "Feature",
      "id": "node/12723336502",
      "properties": {
        "timestamp": "2025-04-02T13:16:14Z",
        "version": 1,
        "changeset": 164421128,
        "addr:housenumber": "4482",
        "addr:postcode": "49600-000",
        "addr:street": "Praça José Elício de Santana",
        "addr:suburb": "Campo Grande",
        "amenity": "clinic",
        "building": "yes",
        "healthcare": "yes",
        "name": "Unidade de Saúde",
        "id": "node/12723336502"
      },
      "geometry": {
        "type": "Point",
        "coordinates": [
          -37.1822298,
          -10.5690964
        ]
      }
    },
    {
      "type": "Feature",
      "id": "node/12723849166",
      "properties": {
        "timestamp": "2025-04-02T18:02:36Z",
        "version": 1,
        "changeset": 164433215,
        "addr:city": "Nossa Senhora das Dores",
        "addr:postcode": "49600-000",
        "addr:street": "Avenida Paulo Vasconcelos",
        "addr:suburb": "Centro",
        "amenity": "clinic",
        "healthcare": "clinic",
        "healthcare:speciality": "general",
        "name": "Clínica de Saúde da Família Maria Adalula da Costa",
        "operator": "Município de Nossa Senhora das Dores",
        "operator:type": "public",
        "id": "node/12723849166"
      },
      "geometry": {
        "type": "Point",
        "coordinates": [
          -37.1973089,
          -10.4990251
        ]
      }
    },
    {
      "type": "Feature",
      "id": "node/12724379602",
      "properties": {
        "timestamp": "2025-04-03T09:34:29Z",
        "version": 2,
        "changeset": 164455432,
        "addr:city": "Nossa Senhora das Dores",
        "addr:housenumber": "170",
        "addr:postcode": "49600-000",
        "addr:street": "Rua Zelia Batista dos Campos",
        "addr:suburb": "Centro",
        "amenity": "clinic",
        "healthcare": "clinic",
        "healthcare:speciality": "general",
        "name": "Centro de Saúde Doutor Milton Calumby Tourinho",
        "operator": "Município de Nossa Senhora das Dores",
        "operator:type": "public",
        "id": "node/12724379602"
      },
      "geometry": {
        "type": "Point",
        "coordinates": [
          -37.1923151,
          -10.4942335
        ]
      }
    },
    {
      "type": "Feature",
      "id": "node/12724379616",
      "properties": {
        "timestamp": "2025-04-02T21:37:34Z",
        "version": 1,
        "changeset": 164440629,
        "addr:city": "Nossa Senhora das Dores",
        "addr:housenumber": "147",
        "addr:postcode": "49600-000",
        "addr:street": "Rua Helena Feitosa de Lima",
        "addr:suburb": "Centro",
        "amenity": "clinic",
        "healthcare": "clinic",
        "healthcare:speciality": "general",
        "name": "Centro Municipal de Saúde",
        "operator": "Município de Nossa Senhora das Dores",
        "operator:type": "public",
        "id": "node/12724379616"
      },
      "geometry": {
        "type": "Point",
        "coordinates": [
          -37.1949129,
          -10.4920392
        ]
      }
    }
  ]
}
