{
  "type": "FeatureCollection",
  "features": [
    {
      "type": "Feature",
      "id": "node/9644692468",
      "properties": {
        "timestamp": "2022-04-18T01:31:12Z",
        "version": 2,
        "changeset": 119835098,
        "historic": "monument",
        "name": "Monumento Imigração Alemã",
        "id": "node/9644692468"
      },
      "geometry": {
        "type": "Point",
        "coordinates": [
          -54.8338902,
          -27.9928734
        ]
      }
    },
    {
      "type": "Feature",
      "id": "node/9644692469",
      "properties": {
        "timestamp": "2022-04-18T01:31:12Z",
        "version": 2,
        "changeset": 119835098,
        "historic": "monument",
        "name": "Monumento Imigração Russa",
        "id": "node/9644692469"
      },
      "geometry": {
        "type": "Point",
        "coordinates": [
          -54.8325162,
          -27.9900997
        ]
      }
    },
    {
      "type": "Feature",
      "id": "node/9644692470",
      "properties": {
        "timestamp": "2022-04-06T04:24:44Z",
        "version": 1,
        "changeset": 119367011,
        "historic": "monument",
        "name": "Cruz de Lorena",
        "id": "node/9644692470"
      },
      "geometry": {
        "type": "Point",
        "coordinates": [
          -54.8270237,
          -27.9980229
        ]
      }
    },
    {
      "type": "Feature",
      "id": "node/9644692471",
      "properties": {
        "timestamp": "2022-04-08T19:49:08Z",
        "version": 2,
        "changeset": 119483386,
        "historic": "monument",
        "name": "Monumento São Cristovão",
        "id": "node/9644692471"
      },
      "geometry": {
        "type": "Point",
        "coordinates": [
          -54.8320908,
          -27.9902968
        ]
      }
    },
    {
      "type": "Feature",
      "id": "node/9680746035",
      "properties": {
        "timestamp": "2022-04-20T17:51:18Z",
        "version": 1,
        "changeset": 119965720,
        "historic": "monument",
        "id": "node/9680746035"
      },
      "geometry": {
        "type": "Point",
        "coordinates": [
          -54.8440961,
          -27.9881024
        ]
      }
    }
  ]
}
