{
  "type": "FeatureCollection",
  "features": [
    {
      "type": "Feature",
      "id": "node/2672989566",
      "properties": {
        "timestamp": "2014-02-15T14:24:35Z",
        "version": 1,
        "changeset": 20577082,
        "amenity": "kindergarten",
        "name": "Creche Municipal",
        "id": "node/2672989566"
      },
      "geometry": {
        "type": "Point",
        "coordinates": [
          -35.4762573,
          -7.307456
        ]
      }
    }
  ]
}
