{
  "type": "FeatureCollection",
  "features": [
    {
      "type": "Feature",
      "id": "node/6384229238",
      "properties": {
        "timestamp": "2019-04-04T20:00:10Z",
        "version": 1,
        "changeset": 68897687,
        "addr:city": "Passa Sete",
        "addr:housenumber": "301",
        "addr:postcode": "96908-000",
        "addr:street": "Avenida Adolfo Emilio Karnopp",
        "addr:suburb": "cento",
        "amenity": "school",
        "name": "EEEM Cristo Rei",
        "operator": "Estado do Rio Grande do Sul",
        "id": "node/6384229238"
      },
      "geometry": {
        "type": "Point",
        "coordinates": [
          -52.9645524,
          -29.4487647
        ]
      }
    },
    {
      "type": "Feature",
      "id": "node/9815964458",
      "properties": {
        "timestamp": "2022-06-14T11:59:39Z",
        "version": 2,
        "changeset": 122370495,
        "amenity": "school",
        "name": "EMEF José Rech",
        "id": "node/9815964458"
      },
      "geometry": {
        "type": "Point",
        "coordinates": [
          -52.9306022,
          -29.5026349
        ]
      }
    }
  ]
}
