{
  "type": "FeatureCollection",
  "features": [
    {
      "type": "Feature",
      "id": "node/9290666626",
      "properties": {
        "timestamp": "2022-03-24T15:12:54Z",
        "version": 2,
        "changeset": 118869309,
        "addr:housenumber": "35",
        "addr:street": "Eua Capitão Manoel Rufino de Negreiros",
        "amenity": "university",
        "name": "FACI Ceará Faculdade",
        "phone": "+55 (88) 99711-1314",
        "id": "node/9290666626"
      },
      "geometry": {
        "type": "Point",
        "coordinates": [
          -38.3050613,
          -5.8088126
        ]
      }
    }
  ]
}
