{
  "type": "FeatureCollection",
  "features": [
    {
      "type": "Feature",
      "id": "node/12702933092",
      "properties": {
        "timestamp": "2025-03-26T15:28:56Z",
        "version": 1,
        "changeset": 164127213,
        "addr:city": "Viseu",
        "addr:postcode": "68620000",
        "addr:street": "Rua Nova I",
        "addr:suburb": "Centro",
        "government": "public_service",
        "level": "2",
        "name": "Assesoria de Comunicação - ASCOM VISEU/PA",
        "office": "government",
        "opening_hours": "24/7",
        "website": "viseu.pa.gov.br",
        "id": "node/12702933092"
      },
      "geometry": {
        "type": "Point",
        "coordinates": [
          -46.1384955,
          -1.2044774
        ]
      }
    }
  ]
}
