{
  "type": "FeatureCollection",
  "features": [
    {
      "type": "Feature",
      "id": "node/11534899619",
      "properties": {
        "timestamp": "2024-01-20T19:50:26Z",
        "version": 1,
        "changeset": 146491197,
        "amenity": "clinic",
        "healthcare": "clinic",
        "name": "Posto de Saúde 24 H",
        "id": "node/11534899619"
      },
      "geometry": {
        "type": "Point",
        "coordinates": [
          -51.1506111,
          -26.4742548
        ]
      }
    }
  ]
}
