{
  "type": "FeatureCollection",
  "features": [
    {
      "type": "Feature",
      "id": "node/12587609848",
      "properties": {
        "timestamp": "2025-02-14T13:39:15Z",
        "version": 1,
        "changeset": 162503851,
        "addr:city": "Jeremoabo",
        "addr:postcode": "48540-000",
        "addr:street": "Praça Coronel Antônio Lourenço de Carvalho",
        "addr:suburb": "Centro",
        "amenity": "library",
        "name": "Biblioteca Municipal Bento Nolasco",
        "operator": "Município de Jermoabo",
        "operator:type": "public",
        "id": "node/12587609848"
      },
      "geometry": {
        "type": "Point",
        "coordinates": [
          -38.3479434,
          -10.0740231
        ]
      }
    }
  ]
}
