{
  "type": "FeatureCollection",
  "features": [
    {
      "type": "Feature",
      "id": "node/12587609848",
      "properties": {
        "timestamp": "2025-02-14T13:39:15Z",
        "version": 1,
        "changeset": 162503851,
        "addr:city": "Jeremoabo",
        "addr:postcode": "48540-000",
        "addr:street": "Praça Coronel Antônio Lourenço de Carvalho",
        "addr:suburb": "Centro",
        "amenity": "library",
        "name": "Biblioteca Municipal Bento Nolasco",
        "operator": "Município de Jermoabo",
        "operator:type": "public",
        "id": "node/12587609848"
      },
      "geometry": {
        "type": "Point",
        "coordinates": [
          -38.3479434,
          -10.0740231
        ]
      }
    },
    {
      "type": "Feature",
      "id": "node/12600486342",
      "properties": {
        "timestamp": "2025-02-19T11:18:21Z",
        "version": 1,
        "changeset": 162696354,
        "IBGE:COD_UNICO_ENDERECO": "217444765",
        "addr:housenumber": "10",
        "addr:postcode": "48540-000",
        "addr:street": "Travessa Vicente de Paula Costa",
        "addr:suburb": "Centro",
        "amenity": "library",
        "building": "civic",
        "description": "CNEFE 2022 Biblioteca Municipal",
        "id": "node/12600486342"
      },
      "geometry": {
        "type": "Point",
        "coordinates": [
          -38.3478419,
          -10.0741176
        ]
      }
    }
  ]
}
