{
  "type": "FeatureCollection",
  "features": [
    {
      "type": "Feature",
      "id": "node/6283745590",
      "properties": {
        "timestamp": "2023-03-19T23:37:00Z",
        "version": 4,
        "changeset": 133877454,
        "amenity": "college",
        "name": "Escola de Gastronomia da UCS",
        "website": "https://www.ucs.br/site/escola-de-gastronomia/",
        "id": "node/6283745590"
      },
      "geometry": {
        "type": "Point",
        "coordinates": [
          -51.1763448,
          -29.0245875
        ]
      }
    }
  ]
}
