{
  "type": "FeatureCollection",
  "features": [
    {
      "type": "Feature",
      "id": "node/3846569481",
      "properties": {
        "timestamp": "2015-11-20T12:12:59Z",
        "version": 1,
        "changeset": 35459960,
        "addr:street": "Rua Afonso A. Feijó",
        "amenity": "school",
        "name": "Colégio Estadual José Amim Matte",
        "id": "node/3846569481"
      },
      "geometry": {
        "type": "Point",
        "coordinates": [
          -52.529169,
          -25.8578005
        ]
      }
    },
    {
      "type": "Feature",
      "id": "node/3846569482",
      "properties": {
        "timestamp": "2015-11-20T12:12:59Z",
        "version": 1,
        "changeset": 35459960,
        "amenity": "school",
        "name": "Escola Municipal Tasso Azevedo da Silveira",
        "id": "node/3846569482"
      },
      "geometry": {
        "type": "Point",
        "coordinates": [
          -52.5246558,
          -25.8584631
        ]
      }
    },
    {
      "type": "Feature",
      "id": "node/9024768184",
      "properties": {
        "timestamp": "2021-08-21T12:01:43Z",
        "version": 1,
        "changeset": 110025779,
        "amenity": "school",
        "name": "APAE",
        "id": "node/9024768184"
      },
      "geometry": {
        "type": "Point",
        "coordinates": [
          -52.5213138,
          -25.8529375
        ]
      }
    },
    {
      "type": "Feature",
      "id": "node/10264017327",
      "properties": {
        "timestamp": "2022-12-15T02:06:55Z",
        "version": 1,
        "changeset": 130094343,
        "amenity": "school",
        "id": "node/10264017327"
      },
      "geometry": {
        "type": "Point",
        "coordinates": [
          -52.5511053,
          -25.8516941
        ]
      }
    }
  ]
}
