{
  "type": "FeatureCollection",
  "features": [
    {
      "type": "Feature",
      "id": "node/11509125759",
      "properties": {
        "timestamp": "2024-01-11T18:34:58Z",
        "version": 1,
        "changeset": 146154342,
        "name": "Cachoeira do Encantado",
        "waterway": "waterfall",
        "id": "node/11509125759"
      },
      "geometry": {
        "type": "Point",
        "coordinates": [
          -37.3625782,
          -10.7335107
        ]
      }
    }
  ]
}
