{
  "type": "FeatureCollection",
  "features": [
    {
      "type": "Feature",
      "id": "node/9143467917",
      "properties": {
        "timestamp": "2021-10-04T01:42:10Z",
        "version": 1,
        "changeset": 112053221,
        "addr:housenumber": "672",
        "addr:postcode": "69960-000",
        "addr:street": "Avenida Placio de Castro",
        "email": "prefeitura@feijo.ac.gov.br",
        "name": "Prefe",
        "name:en": "Prefeitura Municipal de Feijó",
        "name:pt": "Prefeitura Municipal de Feijó",
        "office": "government",
        "phone": "+55 68 3463 2614",
        "website": "https://www.feijo.ac.gov.br/",
        "id": "node/9143467917"
      },
      "geometry": {
        "type": "Point",
        "coordinates": [
          -70.3545104,
          -8.1656328
        ]
      }
    }
  ]
}
