{
  "type": "FeatureCollection",
  "features": [
    {
      "type": "Feature",
      "id": "node/4471498897",
      "properties": {
        "timestamp": "2016-10-30T16:16:16Z",
        "version": 1,
        "changeset": 43286570,
        "amenity": "community_centre",
        "name": "Igreja Adventista",
        "id": "node/4471498897"
      },
      "geometry": {
        "type": "Point",
        "coordinates": [
          -47.3523115,
          -2.989875
        ]
      }
    }
  ]
}
