{
  "type": "FeatureCollection",
  "features": [
    {
      "type": "Feature",
      "id": "node/5817085181",
      "properties": {
        "timestamp": "2018-08-08T05:39:25Z",
        "version": 1,
        "changeset": 61454094,
        "historic": "monument",
        "name": "Homenagem aos Pioneiros do Café",
        "id": "node/5817085181"
      },
      "geometry": {
        "type": "Point",
        "coordinates": [
          -51.6448978,
          -23.6005524
        ]
      }
    },
    {
      "type": "Feature",
      "id": "node/5817085182",
      "properties": {
        "timestamp": "2018-08-08T05:39:25Z",
        "version": 1,
        "changeset": 61454094,
        "historic": "monument",
        "memorial": "statue",
        "name": "Busto de Paulo Pimentel",
        "id": "node/5817085182"
      },
      "geometry": {
        "type": "Point",
        "coordinates": [
          -51.6459956,
          -23.6002639
        ]
      }
    },
    {
      "type": "Feature",
      "id": "node/5817434192",
      "properties": {
        "timestamp": "2018-08-08T08:13:19Z",
        "version": 1,
        "changeset": 61458676,
        "historic": "monument",
        "monument": "historic",
        "name": "Muro entalhado pelo artista Eder Portalha",
        "id": "node/5817434192"
      },
      "geometry": {
        "type": "Point",
        "coordinates": [
          -51.6467164,
          -23.6076214
        ]
      }
    },
    {
      "type": "Feature",
      "id": "node/6926581713",
      "properties": {
        "timestamp": "2019-10-29T10:12:05Z",
        "version": 1,
        "changeset": 76335756,
        "historic": "monument",
        "id": "node/6926581713"
      },
      "geometry": {
        "type": "Point",
        "coordinates": [
          -51.6240066,
          -23.5959337
        ]
      }
    }
  ]
}
