{
  "type": "FeatureCollection",
  "features": [
    {
      "type": "Feature",
      "id": "node/4789012062",
      "properties": {
        "timestamp": "2017-10-19T13:26:02Z",
        "version": 4,
        "changeset": 53068902,
        "government": "legislative",
        "name": "Câmara de Vereadores de Cerrito",
        "office": "government",
        "source": "IBGE",
        "website": "http://www.cerrito.rs.leg.br/",
        "id": "node/4789012062"
      },
      "geometry": {
        "type": "Point",
        "coordinates": [
          -52.8110099,
          -31.8571428
        ]
      }
    }
  ]
}
