{
  "type": "FeatureCollection",
  "features": [
    {
      "type": "Feature",
      "id": "node/2423625703",
      "properties": {
        "timestamp": "2015-04-14T03:15:18Z",
        "version": 2,
        "changeset": 30202964,
        "amenity": "library",
        "name": "Biblioteca de Todo Mundo",
        "id": "node/2423625703"
      },
      "geometry": {
        "type": "Point",
        "coordinates": [
          -45.2531618,
          -21.6945236
        ]
      }
    },
    {
      "type": "Feature",
      "id": "node/8524393061",
      "properties": {
        "timestamp": "2024-09-30T09:12:14Z",
        "version": 6,
        "changeset": 157286992,
        "addr:city": "Três Corações",
        "addr:housenumber": "628",
        "addr:postcode": "37410-155",
        "addr:street": "Avenida Sete de Setembro",
        "addr:suburb": "Centro",
        "air_conditioning": "no",
        "amenity": "library",
        "internet_access": "no",
        "name": "Biblioteca Olavo Bilac",
        "opening_hours": "Mo-Fr 09:30-16:00; Sa,Su,PH off",
        "wheelchair": "limited",
        "wikidata": "Q105974249",
        "id": "node/8524393061"
      },
      "geometry": {
        "type": "Point",
        "coordinates": [
          -45.257025,
          -21.7025654
        ]
      }
    }
  ]
}
