{
  "type": "FeatureCollection",
  "features": [
    {
      "type": "Feature",
      "id": "node/4368876543",
      "properties": {
        "timestamp": "2016-08-27T03:28:37Z",
        "version": 1,
        "changeset": 41727187,
        "amenity": "social_facility",
        "name": "Conselho Tutelar",
        "office": "government",
        "operator": "Prefeitura de Três Corações",
        "id": "node/4368876543"
      },
      "geometry": {
        "type": "Point",
        "coordinates": [
          -45.2594517,
          -21.6943101
        ]
      }
    },
    {
      "type": "Feature",
      "id": "node/8213540036",
      "properties": {
        "timestamp": "2023-07-26T22:28:08Z",
        "version": 2,
        "changeset": 139060332,
        "addr:city": "Três Corações",
        "addr:housenumber": "57",
        "addr:postcode": "37410121",
        "addr:street": "Rua Coronel Alfredo Silva Junqueira",
        "addr:suburb": "Centro",
        "amenity": "social_facility",
        "check_date": "2023-07-26",
        "name": "Conselho Tutelar da Criança e do Adolescente",
        "operator": "Prefeitura Municipal de Três Corações",
        "operator:type": "community",
        "phone": "+55 35 98812-4091",
        "social_facility": "outreach",
        "social_facility:for": "child",
        "id": "node/8213540036"
      },
      "geometry": {
        "type": "Point",
        "coordinates": [
          -45.2570494,
          -21.6976233
        ]
      }
    }
  ]
}
