{
  "type": "FeatureCollection",
  "features": [
    {
      "type": "Feature",
      "id": "node/12351363246",
      "properties": {
        "timestamp": "2024-11-18T15:14:25Z",
        "version": 1,
        "changeset": 159287674,
        "addr:city": "Rio Grande",
        "addr:housenumber": "5",
        "addr:postcode": "96201-540",
        "addr:street": "Rua Paulo Leiria",
        "addr:suburb": "Parque Res. Salgado Filho",
        "amenity": "doctors",
        "healthcare": "doctor",
        "name": "ATAPIRG",
        "opening_hours": "Mo-Fr 08:00-17:00",
        "id": "node/12351363246"
      },
      "geometry": {
        "type": "Point",
        "coordinates": [
          -52.0949562,
          -32.0406892
        ]
      }
    }
  ]
}
