{
  "type": "FeatureCollection",
  "features": [
    {
      "type": "Feature",
      "id": "node/11793905868",
      "properties": {
        "timestamp": "2024-04-05T19:01:35Z",
        "version": 1,
        "changeset": 149629371,
        "addr:city": "Una",
        "addr:postcode": "45690-000",
        "addr:street": "Avenida Getúlio Vargas",
        "addr:suburb": "Centro",
        "amenity": "clinic",
        "healthcare": "clinic",
        "healthcare:speciality": "general",
        "name": "Unidade Básica de Saúde de Una",
        "id": "node/11793905868"
      },
      "geometry": {
        "type": "Point",
        "coordinates": [
          -39.0753285,
          -15.2932719
        ]
      }
    }
  ]
}
