{
  "type": "FeatureCollection",
  "features": [
    {
      "type": "Feature",
      "id": "node/10590394305",
      "properties": {
        "timestamp": "2023-01-29T02:33:34Z",
        "version": 1,
        "changeset": 131827948,
        "amenity": "nursing_home",
        "name": "inicio da estrada (sitio)",
        "id": "node/10590394305"
      },
      "geometry": {
        "type": "Point",
        "coordinates": [
          -44.9985546,
          -18.6572427
        ]
      }
    }
  ]
}
