{
  "type": "FeatureCollection",
  "features": [
    {
      "type": "Feature",
      "id": "node/6144554285",
      "properties": {
        "timestamp": "2018-12-18T08:43:42Z",
        "version": 1,
        "changeset": 65574008,
        "name": "NOVO HOTEL",
        "tourism": "hotel",
        "id": "node/6144554285"
      },
      "geometry": {
        "type": "Point",
        "coordinates": [
          -61.6587828,
          -3.7482618
        ]
      }
    }
  ]
}
