{
  "type": "FeatureCollection",
  "features": [
    {
      "type": "Feature",
      "id": "node/4467102214",
      "properties": {
        "timestamp": "2021-12-16T17:47:45Z",
        "version": 2,
        "changeset": 115019268,
        "name": "Cachoeira Licurí",
        "waterway": "waterfall",
        "id": "node/4467102214"
      },
      "geometry": {
        "type": "Point",
        "coordinates": [
          -41.2156753,
          -13.4284559
        ]
      }
    },
    {
      "type": "Feature",
      "id": "node/7124440089",
      "properties": {
        "timestamp": "2021-12-16T17:47:45Z",
        "version": 3,
        "changeset": 115019268,
        "name": "Cachoeira das Raízes",
        "name:en": "Roots falls",
        "waterway": "waterfall",
        "id": "node/7124440089"
      },
      "geometry": {
        "type": "Point",
        "coordinates": [
          -41.2111625,
          -13.4207074
        ]
      }
    }
  ]
}
