{
  "type": "FeatureCollection",
  "features": [
    {
      "type": "Feature",
      "id": "node/5788214770",
      "properties": {
        "timestamp": "2018-07-26T23:13:33Z",
        "version": 1,
        "changeset": 61103009,
        "name": "Pousada das Pirâmides",
        "tourism": "hotel",
        "id": "node/5788214770"
      },
      "geometry": {
        "type": "Point",
        "coordinates": [
          -49.4187202,
          -28.1326105
        ]
      }
    }
  ]
}
