{
  "type": "FeatureCollection",
  "features": [
    {
      "type": "Feature",
      "id": "node/5788214770",
      "properties": {
        "timestamp": "2024-01-09T12:36:16Z",
        "version": 2,
        "changeset": 146065199,
        "name": "Pousada das Pirâmides",
        "tourism": "hotel",
        "id": "node/5788214770"
      },
      "geometry": {
        "type": "Point",
        "coordinates": [
          -49.419262,
          -28.1327288
        ]
      }
    }
  ]
}
