{
  "type": "FeatureCollection",
  "features": [
    {
      "type": "Feature",
      "id": "node/2038240213",
      "properties": {
        "timestamp": "2015-11-10T02:31:11Z",
        "version": 2,
        "changeset": 35206274,
        "amenity": "arts_centre",
        "name": "Piquete Teófilo Vargas",
        "id": "node/2038240213"
      },
      "geometry": {
        "type": "Point",
        "coordinates": [
          -53.8508493,
          -29.5393135
        ]
      }
    },
    {
      "type": "Feature",
      "id": "node/4526740876",
      "properties": {
        "timestamp": "2019-03-18T18:56:58Z",
        "version": 2,
        "changeset": 68269458,
        "amenity": "arts_centre",
        "name": "CTG Galpão Alegre",
        "id": "node/4526740876"
      },
      "geometry": {
        "type": "Point",
        "coordinates": [
          -53.8546484,
          -29.5262926
        ]
      }
    }
  ]
}
