{
  "type": "FeatureCollection",
  "features": [
    {
      "type": "Feature",
      "id": "node/4606129724",
      "properties": {
        "timestamp": "2017-01-13T17:48:08Z",
        "version": 1,
        "changeset": 45141081,
        "amenity": "community_centre",
        "name": "Centro de Lazer do Trabalhador",
        "id": "node/4606129724"
      },
      "geometry": {
        "type": "Point",
        "coordinates": [
          -48.226035,
          -21.0149005
        ]
      }
    }
  ]
}
