{
  "type": "FeatureCollection",
  "features": [
    {
      "type": "Feature",
      "id": "node/5676229639",
      "properties": {
        "timestamp": "2018-06-08T19:26:45Z",
        "version": 1,
        "changeset": 59677041,
        "amenity": "kindergarten",
        "name": "EM Cantinho do Amor",
        "id": "node/5676229639"
      },
      "geometry": {
        "type": "Point",
        "coordinates": [
          -52.7430513,
          -28.5625635
        ]
      }
    }
  ]
}
