{
  "type": "FeatureCollection",
  "features": [
    {
      "type": "Feature",
      "id": "node/9174814438",
      "properties": {
        "timestamp": "2021-10-15T16:13:44Z",
        "version": 1,
        "changeset": 112549594,
        "addr:housenumber": "205",
        "addr:street": "Rua Progresso",
        "addr:suburb": "Centro",
        "amenity": "college",
        "name": "Instituto de Educação em Saúde",
        "phone": "+55 11 97172 4468",
        "id": "node/9174814438"
      },
      "geometry": {
        "type": "Point",
        "coordinates": [
          -46.7437205,
          -23.2820123
        ]
      }
    },
    {
      "type": "Feature",
      "id": "node/11005831689",
      "properties": {
        "timestamp": "2023-06-25T15:39:13Z",
        "version": 1,
        "changeset": 137757269,
        "addr:housenumber": "248",
        "addr:street": "Rua João Mendes Junior",
        "addr:suburb": "Jardim Professor Francisco Morato",
        "amenity": "college",
        "name": "Escola de Formação e Aprimoramento de Francisco Morato",
        "operator": "Secretaria Municipal de Educação",
        "operator:type": "government",
        "id": "node/11005831689"
      },
      "geometry": {
        "type": "Point",
        "coordinates": [
          -46.7458584,
          -23.2800864
        ]
      }
    }
  ]
}
