{
  "type": "FeatureCollection",
  "features": [
    {
      "type": "Feature",
      "id": "node/11002494063",
      "properties": {
        "timestamp": "2023-06-24T01:28:32Z",
        "version": 1,
        "changeset": 137706736,
        "addr:housenumber": "17",
        "addr:street": "Rua Alcantara Machado",
        "addr:suburb": "Centro",
        "amenity": "dentist",
        "contact:phone": "+55 11 4488 0656",
        "healthcare": "dentist",
        "healthcare:speciality": "orthodontics;general;implantodontia;periodontia;prótese_dentária",
        "name": "Odonto Company",
        "opening_hours": "Mo-Fr 09:00-19:30; Sa 09:00-15:30; Su,PH off",
        "phone": "+55 11 4488 0249",
        "website": "https://odontocompany.com/",
        "id": "node/11002494063"
      },
      "geometry": {
        "type": "Point",
        "coordinates": [
          -46.744689,
          -23.2804881
        ]
      }
    },
    {
      "type": "Feature",
      "id": "node/11018649734",
      "properties": {
        "timestamp": "2023-07-01T20:11:43Z",
        "version": 2,
        "changeset": 138004726,
        "addr:postcode": "07990-040",
        "addr:street": "Rua das Camélias",
        "addr:suburb": "Belém Capela",
        "amenity": "dentist",
        "healthcare": "dentist",
        "healthcare:speciality": "implante_dentário;orthodontics;general;prótese_dentária;odontopediatria;dentística",
        "name": "Odonto Company",
        "phone": "+55 11 4881 6350",
        "website": "https://odontocompany.com/",
        "id": "node/11018649734"
      },
      "geometry": {
        "type": "Point",
        "coordinates": [
          -46.7414356,
          -23.2768165
        ]
      }
    }
  ]
}
