{
  "type": "FeatureCollection",
  "features": [
    {
      "type": "Feature",
      "id": "node/11005831688",
      "properties": {
        "timestamp": "2023-06-25T15:39:13Z",
        "version": 1,
        "changeset": 137757269,
        "addr:housenumber": "248",
        "addr:street": "Rua João Mendes Júnior",
        "historic": "memorial",
        "memorial": "memorial",
        "name": "Memorial Francisco Morato",
        "opening_hours": "Mo-Fr 09:00-16:00; Sa,Su,PH off",
        "id": "node/11005831688"
      },
      "geometry": {
        "type": "Point",
        "coordinates": [
          -46.7459256,
          -23.2801085
        ]
      }
    }
  ]
}
