{
  "type": "FeatureCollection",
  "features": [
    {
      "type": "Feature",
      "id": "node/11002507800",
      "properties": {
        "timestamp": "2023-06-24T01:13:31Z",
        "version": 1,
        "changeset": 137706597,
        "addr:street": "Rua Vinte e Um de Março",
        "addr:suburb": "Centro",
        "amenity": "veterinary",
        "mobile": "+55 11 93931 4397",
        "name": "Hospital Veterinário Popular",
        "opening_hours": "24/7",
        "phone": "+55 11 4488 0691",
        "id": "node/11002507800"
      },
      "geometry": {
        "type": "Point",
        "coordinates": [
          -46.7448339,
          -23.2810868
        ]
      }
    },
    {
      "type": "Feature",
      "id": "node/11002507804",
      "properties": {
        "timestamp": "2023-06-24T01:13:31Z",
        "version": 1,
        "changeset": 137706597,
        "addr:housenumber": "49",
        "addr:street": "Rua Vinte e Um de Março",
        "addr:suburb": "Centro",
        "amenity": "veterinary",
        "contact:facebook": "https://www.facebook.com/tropicalvet/",
        "email": "administrativofranco@grupovettropical.com",
        "mobile": "+55 11 97361 2908",
        "name": "Hospital Veterinário Tropical",
        "opening_hours": "24/7",
        "id": "node/11002507804"
      },
      "geometry": {
        "type": "Point",
        "coordinates": [
          -46.7443243,
          -23.2810474
        ]
      }
    }
  ]
}
