{
  "type": "FeatureCollection",
  "features": [
    {
      "type": "Feature",
      "id": "node/5345598154",
      "properties": {
        "timestamp": "2023-11-26T16:07:42Z",
        "version": 2,
        "changeset": 144476855,
        "addr:city": "Queimados",
        "addr:street": "Avenida Tinguá",
        "amenity": "arts_centre",
        "name": "Palco da Praça dos Eucaliptos",
        "id": "node/5345598154"
      },
      "geometry": {
        "type": "Point",
        "coordinates": [
          -43.5585539,
          -22.7145399
        ]
      }
    }
  ]
}
