{
  "type": "FeatureCollection",
  "features": [
    {
      "type": "Feature",
      "id": "node/2524545389",
      "properties": {
        "timestamp": "2013-11-08T18:35:07Z",
        "version": 1,
        "changeset": 18787243,
        "addr:city": "Queimados",
        "addr:housenumber": "385",
        "addr:street": "Avenida Doutor Pedro Jorge",
        "name": "Romulo de Oliveira Machado",
        "shop": "bicycle",
        "source": "survey",
        "id": "node/2524545389"
      },
      "geometry": {
        "type": "Point",
        "coordinates": [
          -43.5557816,
          -22.7122174
        ]
      }
    },
    {
      "type": "Feature",
      "id": "node/2524559965",
      "properties": {
        "timestamp": "2013-11-08T18:48:57Z",
        "version": 1,
        "changeset": 18787478,
        "addr:city": "Queimados",
        "addr:housenumber": "17",
        "addr:street": "Travessa Marques",
        "name": "Leonaldo Bragante de Araujo Ciclo",
        "phone": "+55-21-26658453",
        "shop": "bicycle",
        "source": "survey",
        "id": "node/2524559965"
      },
      "geometry": {
        "type": "Point",
        "coordinates": [
          -43.5589396,
          -22.7154504
        ]
      }
    },
    {
      "type": "Feature",
      "id": "node/2960414640",
      "properties": {
        "timestamp": "2014-07-12T23:44:46Z",
        "version": 1,
        "changeset": 24110623,
        "addr:city": "Queimados",
        "addr:housenumber": "17",
        "addr:street": "Rua Doutor José Maria Coelho",
        "name": "Elida Bicicletas",
        "phone": "+55-21-27799600",
        "shop": "bicycle",
        "id": "node/2960414640"
      },
      "geometry": {
        "type": "Point",
        "coordinates": [
          -43.5564455,
          -22.7164961
        ]
      }
    },
    {
      "type": "Feature",
      "id": "node/3163676403",
      "properties": {
        "timestamp": "2014-11-02T21:14:25Z",
        "version": 1,
        "changeset": 26513411,
        "shop": "bicycle",
        "id": "node/3163676403"
      },
      "geometry": {
        "type": "Point",
        "coordinates": [
          -43.5587352,
          -22.7154874
        ]
      }
    }
  ]
}
