{
  "type": "FeatureCollection",
  "features": [
    {
      "type": "Feature",
      "id": "node/5352802009",
      "properties": {
        "timestamp": "2018-01-21T15:46:15Z",
        "version": 1,
        "changeset": 55630946,
        "amenity": "doctors",
        "healthcare": "doctor",
        "name": "Laboratório Emerson",
        "operator": "Privado",
        "id": "node/5352802009"
      },
      "geometry": {
        "type": "Point",
        "coordinates": [
          -43.5576709,
          -22.7185264
        ]
      }
    }
  ]
}
