{
  "type": "FeatureCollection",
  "features": [
    {
      "type": "Feature",
      "id": "node/5345598126",
      "properties": {
        "timestamp": "2018-01-17T19:59:48Z",
        "version": 1,
        "changeset": 55531628,
        "historic": "monument",
        "inscription": "Monumento Nossa Senhora da Conceição, a padroeira da Cidade",
        "name": "Monumento Nossa Senhora da Conceição",
        "id": "node/5345598126"
      },
      "geometry": {
        "type": "Point",
        "coordinates": [
          -43.5553207,
          -22.7167859
        ]
      }
    },
    {
      "type": "Feature",
      "id": "node/5349347957",
      "properties": {
        "timestamp": "2018-01-19T15:57:26Z",
        "version": 1,
        "changeset": 55581757,
        "historic": "monument",
        "name": "Monumento Maçon",
        "id": "node/5349347957"
      },
      "geometry": {
        "type": "Point",
        "coordinates": [
          -43.5569711,
          -22.7323948
        ]
      }
    },
    {
      "type": "Feature",
      "id": "node/5349347958",
      "properties": {
        "timestamp": "2018-01-19T15:57:26Z",
        "version": 1,
        "changeset": 55581757,
        "historic": "monument",
        "name": "Rotary Club",
        "id": "node/5349347958"
      },
      "geometry": {
        "type": "Point",
        "coordinates": [
          -43.5583169,
          -22.7299871
        ]
      }
    }
  ]
}
