{
  "type": "FeatureCollection",
  "features": [
    {
      "type": "Feature",
      "id": "node/10830911707",
      "properties": {
        "timestamp": "2023-04-26T13:06:39Z",
        "version": 2,
        "changeset": 135386298,
        "name": "Greick Bike",
        "service:bicycle:rental": "yes",
        "shop": "bicycle",
        "survey:date": "2023-04-21",
        "id": "node/10830911707"
      },
      "geometry": {
        "type": "Point",
        "coordinates": [
          -38.0048017,
          -12.5773601
        ]
      }
    }
  ]
}
