{
  "type": "FeatureCollection",
  "features": [
    {
      "type": "Feature",
      "id": "node/11470034969",
      "properties": {
        "timestamp": "2023-12-30T16:28:30Z",
        "version": 1,
        "changeset": 145704604,
        "amenity": "clinic",
        "name": "Especialidade Médicas Américo Montenegro",
        "id": "node/11470034969"
      },
      "geometry": {
        "type": "Point",
        "coordinates": [
          -47.4800137,
          -21.8601187
        ]
      }
    }
  ]
}
