{
  "type": "FeatureCollection",
  "features": [
    {
      "type": "Feature",
      "id": "node/10567958709",
      "properties": {
        "timestamp": "2023-01-19T14:16:49Z",
        "version": 1,
        "changeset": 131468882,
        "amenity": "community_centre",
        "name": "Sindicato laboral",
        "id": "node/10567958709"
      },
      "geometry": {
        "type": "Point",
        "coordinates": [
          -47.4819072,
          -21.8576459
        ]
      }
    }
  ]
}
