{
  "type": "FeatureCollection",
  "features": [
    {
      "type": "Feature",
      "id": "node/3714063588",
      "properties": {
        "timestamp": "2021-02-05T07:32:50Z",
        "version": 3,
        "changeset": 98748798,
        "access": "yes",
        "amenity": "clinic",
        "healthcare": "clinic",
        "name": "Posto de Saúde Municipal",
        "id": "node/3714063588"
      },
      "geometry": {
        "type": "Point",
        "coordinates": [
          -53.279507,
          -26.3480463
        ]
      }
    },
    {
      "type": "Feature",
      "id": "node/8626354432",
      "properties": {
        "timestamp": "2021-04-13T15:46:25Z",
        "version": 1,
        "changeset": 102875428,
        "amenity": "clinic",
        "id": "node/8626354432"
      },
      "geometry": {
        "type": "Point",
        "coordinates": [
          -53.3669927,
          -26.444264
        ]
      }
    }
  ]
}
