{
  "type": "FeatureCollection",
  "features": [
    {
      "type": "Feature",
      "id": "node/4298797319",
      "properties": {
        "timestamp": "2023-11-05T23:54:51Z",
        "version": 3,
        "changeset": 143671867,
        "name": "Cachoeira Veu da Noiva",
        "tourism": "viewpoint",
        "waterfall": "water_fall",
        "waterway": "waterfall",
        "id": "node/4298797319"
      },
      "geometry": {
        "type": "Point",
        "coordinates": [
          -35.712826,
          -8.5431216
        ]
      }
    }
  ]
}
