{
  "type": "FeatureCollection",
  "features": [
    {
      "type": "Feature",
      "id": "node/5294358076",
      "properties": {
        "timestamp": "2019-04-03T00:23:42Z",
        "version": 8,
        "changeset": 68817759,
        "historic": "memorial",
        "memorial": "statue",
        "name": "Homenagem a Agnaldo Timóteo",
        "id": "node/5294358076"
      },
      "geometry": {
        "type": "Point",
        "coordinates": [
          -42.1417805,
          -19.7885906
        ]
      }
    },
    {
      "type": "Feature",
      "id": "node/5294360043",
      "properties": {
        "timestamp": "2019-04-19T22:25:56Z",
        "version": 8,
        "changeset": 69390839,
        "historic": "memorial",
        "memorial": "statue",
        "name": "Getúlio Vargas",
        "id": "node/5294360043"
      },
      "geometry": {
        "type": "Point",
        "coordinates": [
          -42.1418847,
          -19.7881191
        ]
      }
    },
    {
      "type": "Feature",
      "id": "node/6807688591",
      "properties": {
        "timestamp": "2019-09-19T10:46:23Z",
        "version": 1,
        "changeset": 74665581,
        "historic": "memorial",
        "inscription": "Placa em Homenagem ao Major Etiene Arreguy na Antiga Rodoviaria que Hoje e o Centro Comercial Popular de Caratinga.",
        "memorial": "plaque",
        "name": "Placa em Homenagem ao Major Etiene Arreguy",
        "id": "node/6807688591"
      },
      "geometry": {
        "type": "Point",
        "coordinates": [
          -42.1406504,
          -19.7892634
        ]
      }
    }
  ]
}
