{
  "type": "FeatureCollection",
  "features": [
    {
      "type": "Feature",
      "id": "node/4151411492",
      "properties": {
        "timestamp": "2018-01-04T03:42:44Z",
        "version": 2,
        "changeset": 55146514,
        "name": "Pousada Lua Luana",
        "tourism": "guest_house",
        "id": "node/4151411492"
      },
      "geometry": {
        "type": "Point",
        "coordinates": [
          -45.2924535,
          -21.8871948
        ]
      }
    }
  ]
}
