{
  "type": "FeatureCollection",
  "features": [
    {
      "type": "Feature",
      "id": "node/6397702302",
      "properties": {
        "timestamp": "2020-03-22T04:31:23Z",
        "version": 2,
        "changeset": 82474444,
        "historic": "memorial",
        "name": "Rosa Magalhães",
        "id": "node/6397702302"
      },
      "geometry": {
        "type": "Point",
        "coordinates": [
          -44.212563,
          -13.3963503
        ]
      }
    }
  ]
}
