{
  "type": "FeatureCollection",
  "features": [
    {
      "type": "Feature",
      "id": "node/3500192998",
      "properties": {
        "timestamp": "2015-05-06T01:17:07Z",
        "version": 1,
        "changeset": 30827555,
        "name": "Cachoeira do Ano Bom",
        "waterway": "waterfall",
        "id": "node/3500192998"
      },
      "geometry": {
        "type": "Point",
        "coordinates": [
          -45.3817234,
          -22.3789834
        ]
      }
    },
    {
      "type": "Feature",
      "id": "node/11350052599",
      "properties": {
        "timestamp": "2023-11-15T00:58:02Z",
        "version": 1,
        "changeset": 144031732,
        "name": "Cachoeira da Estância",
        "waterway": "waterfall",
        "id": "node/11350052599"
      },
      "geometry": {
        "type": "Point",
        "coordinates": [
          -45.4258645,
          -22.4811508
        ]
      }
    }
  ]
}
