{
  "type": "FeatureCollection",
  "features": [
    {
      "type": "Feature",
      "id": "node/12070414205",
      "properties": {
        "timestamp": "2024-07-23T19:09:49Z",
        "version": 1,
        "changeset": 154320956,
        "addr:city": "Porto Feliz",
        "addr:housenumber": "185",
        "addr:postcode": "18540-000",
        "addr:street": "Rua Gabriel Antônio Carvalho",
        "amenity": "doctors",
        "healthcare": "doctor",
        "healthcare:speciality": "general;neurology;neurosurgery",
        "name": "MedVita Porto Feliz",
        "wheelchair": "yes",
        "id": "node/12070414205"
      },
      "geometry": {
        "type": "Point",
        "coordinates": [
          -47.5149941,
          -23.2146945
        ]
      }
    }
  ]
}
