{
  "type": "FeatureCollection",
  "features": [
    {
      "type": "Feature",
      "id": "node/4519725190",
      "properties": {
        "timestamp": "2016-11-24T22:55:10Z",
        "version": 1,
        "changeset": 43933564,
        "internet_access": "wlan",
        "name": "JN Hotel",
        "name:pt": "JN Hotel",
        "tourism": "hotel",
        "id": "node/4519725190"
      },
      "geometry": {
        "type": "Point",
        "coordinates": [
          -63.6164557,
          -10.5730102
        ]
      }
    }
  ]
}
