{
  "type": "FeatureCollection",
  "features": [
    {
      "type": "Feature",
      "id": "node/11491412853",
      "properties": {
        "timestamp": "2024-01-05T10:45:06Z",
        "version": 1,
        "changeset": 145916213,
        "addr:city": "Pavão",
        "addr:housenumber": "93",
        "addr:postcode": "39814-000",
        "amenity": "clinic",
        "healthcare": "clinic",
        "healthcare:speciality": "general",
        "name": "Centro Municipal de Saúde José Benedito de Almeida Santana",
        "operator": "Município de Pavão",
        "id": "node/11491412853"
      },
      "geometry": {
        "type": "Point",
        "coordinates": [
          -41.0023833,
          -17.4311354
        ]
      }
    }
  ]
}
