{
  "type": "FeatureCollection",
  "features": [
    {
      "type": "Feature",
      "id": "node/1416739577",
      "properties": {
        "timestamp": "2022-08-16T21:22:44Z",
        "version": 3,
        "changeset": 124991314,
        "access": "customers",
        "amenity": "drinking_water",
        "bottle": "yes",
        "check_date": "2022-08-14",
        "fee": "no",
        "id": "node/1416739577"
      },
      "geometry": {
        "type": "Point",
        "coordinates": [
          -41.3788875,
          -13.0026692
        ]
      }
    },
    {
      "type": "Feature",
      "id": "node/11537895676",
      "properties": {
        "timestamp": "2024-01-21T20:00:00Z",
        "version": 1,
        "changeset": 146526285,
        "amenity": "drinking_water",
        "name": "River",
        "id": "node/11537895676"
      },
      "geometry": {
        "type": "Point",
        "coordinates": [
          -41.469366,
          -12.7185266
        ]
      }
    },
    {
      "type": "Feature",
      "id": "node/11537895776",
      "properties": {
        "timestamp": "2024-01-21T19:59:58Z",
        "version": 1,
        "changeset": 146526285,
        "amenity": "drinking_water",
        "name": "River",
        "id": "node/11537895776"
      },
      "geometry": {
        "type": "Point",
        "coordinates": [
          -41.4524416,
          -12.7485284
        ]
      }
    },
    {
      "type": "Feature",
      "id": "node/11537895777",
      "properties": {
        "timestamp": "2024-01-21T19:59:59Z",
        "version": 1,
        "changeset": 146526285,
        "amenity": "drinking_water",
        "name": "River",
        "id": "node/11537895777"
      },
      "geometry": {
        "type": "Point",
        "coordinates": [
          -41.4614857,
          -12.7273949
        ]
      }
    }
  ]
}
