{
  "type": "FeatureCollection",
  "features": [
    {
      "type": "Feature",
      "id": "node/9406359415",
      "properties": {
        "timestamp": "2022-01-10T02:09:03Z",
        "version": 1,
        "changeset": 115962883,
        "addr:city": "Camaragibe",
        "addr:housenumber": "12A",
        "addr:street": "Avenida Doutor Belmino Correia",
        "addr:suburb": "Alberto Maia",
        "name": "Jss Bike",
        "shop": "bicycle",
        "id": "node/9406359415"
      },
      "geometry": {
        "type": "Point",
        "coordinates": [
          -35.0034287,
          -8.0214426
        ]
      }
    }
  ]
}
