{
  "type": "FeatureCollection",
  "features": [
    {
      "type": "Feature",
      "id": "node/4053973715",
      "properties": {
        "timestamp": "2016-03-11T04:12:22Z",
        "version": 1,
        "changeset": 37751212,
        "amenity": "hospital",
        "name": "Hospital Municipal São Sebastião",
        "id": "node/4053973715"
      },
      "geometry": {
        "type": "Point",
        "coordinates": [
          -42.2608409,
          -14.2596168
        ]
      }
    }
  ]
}
