{
  "type": "FeatureCollection",
  "features": [
    {
      "type": "Feature",
      "id": "node/6139769490",
      "properties": {
        "timestamp": "2020-11-29T16:52:06Z",
        "version": 2,
        "changeset": 94991113,
        "addr:city": "Ivoti",
        "amenity": "arts_centre",
        "name": "CTG Estância do Cotiporã",
        "id": "node/6139769490"
      },
      "geometry": {
        "type": "Point",
        "coordinates": [
          -51.1411825,
          -29.5842267
        ]
      }
    }
  ]
}
