{
  "type": "FeatureCollection",
  "features": [
    {
      "type": "Feature",
      "id": "node/4598957489",
      "properties": {
        "timestamp": "2017-01-10T02:51:04Z",
        "version": 2,
        "changeset": 45041175,
        "addr:housenumber": "414",
        "addr:street": "Rua São Borja",
        "name": "Casa de apoio para motoqueiros",
        "phone": "+55 51 98131-3032",
        "tourism": "guest_house",
        "id": "node/4598957489"
      },
      "geometry": {
        "type": "Point",
        "coordinates": [
          -51.1506336,
          -29.6066324
        ]
      }
    }
  ]
}
