{
  "type": "FeatureCollection",
  "features": [
    {
      "type": "Feature",
      "id": "node/11426647616",
      "properties": {
        "timestamp": "2023-12-17T18:26:04Z",
        "version": 1,
        "changeset": 145224986,
        "name": "Cachoeira do Pagão",
        "source": "Bing; survey",
        "waterway": "waterfall",
        "id": "node/11426647616"
      },
      "geometry": {
        "type": "Point",
        "coordinates": [
          -38.3853614,
          -7.2336039
        ]
      }
    },
    {
      "type": "Feature",
      "id": "node/11426647618",
      "properties": {
        "timestamp": "2023-12-17T18:26:04Z",
        "version": 1,
        "changeset": 145224986,
        "name": "Cachoeira das Piabas",
        "source": "Bing; survey",
        "waterway": "waterfall",
        "id": "node/11426647618"
      },
      "geometry": {
        "type": "Point",
        "coordinates": [
          -38.3555514,
          -7.2193893
        ]
      }
    },
    {
      "type": "Feature",
      "id": "node/11426647619",
      "properties": {
        "timestamp": "2023-12-17T18:26:04Z",
        "version": 1,
        "changeset": 145224986,
        "name": "Cachoeira da Santana",
        "source": "Bing; survey",
        "waterway": "waterfall",
        "id": "node/11426647619"
      },
      "geometry": {
        "type": "Point",
        "coordinates": [
          -38.3459276,
          -7.197907
        ]
      }
    },
    {
      "type": "Feature",
      "id": "node/11426647620",
      "properties": {
        "timestamp": "2023-12-17T18:26:04Z",
        "version": 1,
        "changeset": 145224986,
        "name": "Cachoeira da Espera",
        "source": "Bing; survey",
        "waterway": "waterfall",
        "id": "node/11426647620"
      },
      "geometry": {
        "type": "Point",
        "coordinates": [
          -38.3728999,
          -7.1897242
        ]
      }
    }
  ]
}
