{
  "type": "FeatureCollection",
  "features": [
    {
      "type": "Feature",
      "id": "node/12362660174",
      "properties": {
        "timestamp": "2024-11-21T19:43:01Z",
        "version": 1,
        "changeset": 159432376,
        "addr:city": "Ouro Verde",
        "addr:housenumber": "10",
        "addr:street": "Rua Pará",
        "addr:suburb": "Nova Esperança",
        "amenity": "college",
        "name": "SEBRAE AQUI",
        "operator": "SEBRAE",
        "operator:type": "government",
        "id": "node/12362660174"
      },
      "geometry": {
        "type": "Point",
        "coordinates": [
          -51.6958186,
          -21.4963134
        ]
      }
    }
  ]
}
