{
  "type": "FeatureCollection",
  "features": [
    {
      "type": "Feature",
      "id": "node/11102391078",
      "properties": {
        "timestamp": "2023-08-09T17:08:45Z",
        "version": 1,
        "changeset": 139670316,
        "amenity": "clinic",
        "name": "UBS Bandeira do Almada",
        "id": "node/11102391078"
      },
      "geometry": {
        "type": "Point",
        "coordinates": [
          -39.5077372,
          -14.6652008
        ]
      }
    },
    {
      "type": "Feature",
      "id": "node/11102402433",
      "properties": {
        "timestamp": "2023-08-09T17:08:45Z",
        "version": 1,
        "changeset": 139670316,
        "amenity": "clinic",
        "name": "UBS Sequeiro Grande",
        "id": "node/11102402433"
      },
      "geometry": {
        "type": "Point",
        "coordinates": [
          -39.4270375,
          -14.6882533
        ]
      }
    },
    {
      "type": "Feature",
      "id": "node/11102402463",
      "properties": {
        "timestamp": "2023-08-09T17:08:45Z",
        "version": 1,
        "changeset": 139670316,
        "amenity": "clinic",
        "name": "UBS Ruinha de São Cristóvão",
        "id": "node/11102402463"
      },
      "geometry": {
        "type": "Point",
        "coordinates": [
          -39.4132188,
          -14.6833067
        ]
      }
    }
  ]
}
