{
  "type": "FeatureCollection",
  "features": [
    {
      "type": "Feature",
      "id": "node/12134158390",
      "properties": {
        "timestamp": "2024-08-24T17:00:00Z",
        "version": 1,
        "changeset": 155706374,
        "amenity": "social_facility",
        "name": "CRAS Casa das Famílias",
        "id": "node/12134158390"
      },
      "geometry": {
        "type": "Point",
        "coordinates": [
          -44.9852038,
          -21.7208636
        ]
      }
    }
  ]
}
