{
  "type": "FeatureCollection",
  "features": [
    {
      "type": "Feature",
      "id": "node/1884584705",
      "properties": {
        "timestamp": "2012-08-26T22:42:08Z",
        "version": 1,
        "changeset": 12872982,
        "historic": "memorial",
        "name": "Praça do Forninho",
        "id": "node/1884584705"
      },
      "geometry": {
        "type": "Point",
        "coordinates": [
          -43.9730783,
          -21.1839359
        ]
      }
    },
    {
      "type": "Feature",
      "id": "node/6597054417",
      "properties": {
        "timestamp": "2019-07-08T16:31:49Z",
        "version": 1,
        "changeset": 72022039,
        "historic": "memorial",
        "material": "concrete",
        "name": "Obelisco da Emancipaçao",
        "id": "node/6597054417"
      },
      "geometry": {
        "type": "Point",
        "coordinates": [
          -43.9761922,
          -21.1865274
        ]
      }
    },
    {
      "type": "Feature",
      "id": "node/6597054418",
      "properties": {
        "timestamp": "2019-07-08T16:31:49Z",
        "version": 1,
        "changeset": 72022039,
        "historic": "memorial",
        "material": "concrete",
        "memorial": "statue",
        "name": "Conego Luiz Giarola Carlos",
        "id": "node/6597054418"
      },
      "geometry": {
        "type": "Point",
        "coordinates": [
          -43.976295,
          -21.1866993
        ]
      }
    },
    {
      "type": "Feature",
      "id": "node/6597107266",
      "properties": {
        "timestamp": "2021-11-18T06:48:04Z",
        "version": 6,
        "changeset": 113929461,
        "artwork_type": "statue",
        "building:material": "concrete",
        "historic": "memorial",
        "material": "bronze",
        "memorial": "statue",
        "name": "Estátua de Castelo Branco",
        "tourism": "artwork",
        "wikidata": "Q96247102",
        "wikimedia_commons": "File:Estatua Castelo Branco Barroso-MG.jpg",
        "id": "node/6597107266"
      },
      "geometry": {
        "type": "Point",
        "coordinates": [
          -43.9765473,
          -21.1879218
        ]
      }
    }
  ]
}
