{
  "type": "FeatureCollection",
  "features": [
    {
      "type": "Feature",
      "id": "node/1884584703",
      "properties": {
        "timestamp": "2019-07-08T16:40:08Z",
        "version": 3,
        "changeset": 72022391,
        "historic": "monument",
        "name": "Praça Sant'Ana",
        "id": "node/1884584703"
      },
      "geometry": {
        "type": "Point",
        "coordinates": [
          -43.9769567,
          -21.1876973
        ]
      }
    },
    {
      "type": "Feature",
      "id": "node/1884584707",
      "properties": {
        "timestamp": "2012-08-26T22:42:08Z",
        "version": 1,
        "changeset": 12872982,
        "historic": "monument",
        "name": "Praça do Cruzeiro",
        "id": "node/1884584707"
      },
      "geometry": {
        "type": "Point",
        "coordinates": [
          -43.9727349,
          -21.1877573
        ]
      }
    },
    {
      "type": "Feature",
      "id": "node/6597750446",
      "properties": {
        "timestamp": "2019-07-09T01:08:08Z",
        "version": 1,
        "changeset": 72033530,
        "historic": "monument",
        "id": "node/6597750446"
      },
      "geometry": {
        "type": "Point",
        "coordinates": [
          -43.9727906,
          -21.1754254
        ]
      }
    },
    {
      "type": "Feature",
      "id": "node/6597750447",
      "properties": {
        "timestamp": "2019-07-09T01:08:08Z",
        "version": 1,
        "changeset": 72033530,
        "historic": "monument",
        "id": "node/6597750447"
      },
      "geometry": {
        "type": "Point",
        "coordinates": [
          -43.9724702,
          -21.1754829
        ]
      }
    },
    {
      "type": "Feature",
      "id": "node/6597750448",
      "properties": {
        "timestamp": "2019-07-09T01:08:08Z",
        "version": 1,
        "changeset": 72033530,
        "historic": "monument",
        "id": "node/6597750448"
      },
      "geometry": {
        "type": "Point",
        "coordinates": [
          -43.9726304,
          -21.1754369
        ]
      }
    }
  ]
}
