{
  "type": "FeatureCollection",
  "features": [
    {
      "type": "Feature",
      "id": "node/1104140315",
      "properties": {
        "timestamp": "2023-08-12T21:08:14Z",
        "version": 3,
        "changeset": 139802728,
        "addr:city": "Governador Celso Ramos",
        "addr:housenumber": "104",
        "addr:postcode": "88190-000",
        "addr:street": "Servidão Elpídio Alves do Nascimento",
        "addr:suburb": "Ganchos de Fora",
        "name": "Ponta dos Ganchos",
        "tourism": "hotel",
        "website": "http://www.pontadosganchos.com/",
        "id": "node/1104140315"
      },
      "geometry": {
        "type": "Point",
        "coordinates": [
          -48.5511412,
          -27.305181
        ]
      }
    },
    {
      "type": "Feature",
      "id": "node/4830999691",
      "properties": {
        "timestamp": "2023-08-05T15:24:56Z",
        "version": 4,
        "changeset": 139484933,
        "addr:city": "Governador Celso Ramos",
        "addr:housenumber": "186",
        "addr:postcode": "88190-000",
        "addr:street": "Servidão João Domingos Pereira",
        "addr:suburb": "Costeira da Armação",
        "name": "Pousada Baía dos Golfinhos",
        "phone": "+55 48 98406-6130",
        "source:date": "2017-04-30",
        "tourism": "hotel",
        "id": "node/4830999691"
      },
      "geometry": {
        "type": "Point",
        "coordinates": [
          -48.5627174,
          -27.403589
        ]
      }
    },
    {
      "type": "Feature",
      "id": "node/5379587806",
      "properties": {
        "timestamp": "2023-08-09T21:03:31Z",
        "version": 3,
        "changeset": 139678207,
        "addr:city": "Governador Celso Ramos",
        "addr:housenumber": "80",
        "addr:postcode": "88190-000",
        "addr:street": "Rua dos Recantos",
        "addr:suburb": "Palmas",
        "name": "Hotel Águas de Palmas",
        "tourism": "hotel",
        "id": "node/5379587806"
      },
      "geometry": {
        "type": "Point",
        "coordinates": [
          -48.5369861,
          -27.3364998
        ]
      }
    }
  ]
}
