{
  "type": "FeatureCollection",
  "features": [
    {
      "type": "Feature",
      "id": "node/3808567862",
      "properties": {
        "timestamp": "2019-09-26T15:17:08Z",
        "version": 2,
        "changeset": 74969527,
        "addr:street": "BR 101",
        "name": "Pousada do Posto Vitória",
        "tourism": "guest_house",
        "id": "node/3808567862"
      },
      "geometry": {
        "type": "Point",
        "coordinates": [
          -39.5472412,
          -16.6021942
        ]
      }
    }
  ]
}
