{
  "type": "FeatureCollection",
  "features": [
    {
      "type": "Feature",
      "id": "node/5324148649",
      "properties": {
        "timestamp": "2018-01-06T17:57:29Z",
        "version": 1,
        "changeset": 55217752,
        "government": "public_service",
        "name": "Detran",
        "office": "government",
        "id": "node/5324148649"
      },
      "geometry": {
        "type": "Point",
        "coordinates": [
          -47.2154932,
          -22.8638337
        ]
      }
    }
  ]
}
