{
  "type": "FeatureCollection",
  "features": [
    {
      "type": "Feature",
      "id": "node/3537238647",
      "properties": {
        "timestamp": "2015-05-23T00:36:09Z",
        "version": 5,
        "changeset": 31387344,
        "addr:city": "Santana do Paraíso",
        "addr:street": "Avenida São Luiz",
        "amenity": "college",
        "name": "Sest Senat",
        "id": "node/3537238647"
      },
      "geometry": {
        "type": "Point",
        "coordinates": [
          -42.5241319,
          -19.4535265
        ]
      }
    }
  ]
}
