{
  "type": "FeatureCollection",
  "features": [
    {
      "type": "Feature",
      "id": "node/4522119592",
      "properties": {
        "timestamp": "2022-07-28T19:09:12Z",
        "version": 3,
        "changeset": 124200016,
        "addr:postcode": "35167-000",
        "addr:street": "MG 232",
        "name": "Pousada Veredas da Serra",
        "name:pt": "Pousada Veredas da Serra",
        "opening_hours": "Mo-Su 09:00-22:00",
        "phone": "+55 31 9 9645 6870",
        "tourism": "guest_house",
        "website": "https://www.facebook.com/Pousada-Veredas-da-Serra-318638141494170/",
        "id": "node/4522119592"
      },
      "geometry": {
        "type": "Point",
        "coordinates": [
          -42.5544893,
          -19.3234854
        ]
      }
    }
  ]
}
