{
  "type": "FeatureCollection",
  "features": [
    {
      "type": "Feature",
      "id": "node/7424033652",
      "properties": {
        "timestamp": "2020-12-10T20:43:58Z",
        "version": 2,
        "changeset": 95640750,
        "addr:city": "Caetité",
        "addr:postcode": "46400-000",
        "amenity": "college",
        "name": "Centro de Estudos Técnicos Criando Talentos",
        "operator:type": "private",
        "phone": "+55 77 3454-1255",
        "training": "tutoring",
        "id": "node/7424033652"
      },
      "geometry": {
        "type": "Point",
        "coordinates": [
          -42.4927937,
          -14.0666596
        ]
      }
    },
    {
      "type": "Feature",
      "id": "node/10015795459",
      "properties": {
        "timestamp": "2022-09-11T20:45:25Z",
        "version": 2,
        "changeset": 126064480,
        "addr:city": "Caetité",
        "addr:housenumber": "254",
        "addr:postcode": "46400-000",
        "addr:street": "Avenida Santana",
        "addr:suburb": "Centro",
        "amenity": "college",
        "contact:instagram": "https://www.instagram.com/humanizacte/",
        "contact:mobile": "+55 77 9 9238 0577;+55 77 9 8154 1164",
        "level": "1",
        "name": "Humaniza Escola Técnica",
        "id": "node/10015795459"
      },
      "geometry": {
        "type": "Point",
        "coordinates": [
          -42.4882456,
          -14.0689087
        ]
      }
    }
  ]
}
