{
  "type": "FeatureCollection",
  "features": [
    {
      "type": "Feature",
      "id": "node/4769724930",
      "properties": {
        "timestamp": "2017-04-01T16:07:55Z",
        "version": 1,
        "changeset": 47360118,
        "height": "6",
        "waterway": "waterfall",
        "id": "node/4769724930"
      },
      "geometry": {
        "type": "Point",
        "coordinates": [
          -42.493461,
          -14.0842556
        ]
      }
    },
    {
      "type": "Feature",
      "id": "node/5421687279",
      "properties": {
        "timestamp": "2018-02-19T04:59:30Z",
        "version": 1,
        "changeset": 56480085,
        "waterway": "waterfall",
        "id": "node/5421687279"
      },
      "geometry": {
        "type": "Point",
        "coordinates": [
          -42.4644537,
          -14.1490401
        ]
      }
    },
    {
      "type": "Feature",
      "id": "node/11903597756",
      "properties": {
        "timestamp": "2024-05-14T10:16:25Z",
        "version": 1,
        "changeset": 151305038,
        "name": "Cachoeira da Gameleira",
        "waterway": "waterfall",
        "id": "node/11903597756"
      },
      "geometry": {
        "type": "Point",
        "coordinates": [
          -42.6735437,
          -14.0486123
        ]
      }
    },
    {
      "type": "Feature",
      "id": "node/11903597757",
      "properties": {
        "timestamp": "2024-05-14T10:16:25Z",
        "version": 1,
        "changeset": 151305038,
        "name": "Cachoeira do Gado Bravo",
        "waterway": "waterfall",
        "id": "node/11903597757"
      },
      "geometry": {
        "type": "Point",
        "coordinates": [
          -42.6717368,
          -14.0475166
        ]
      }
    },
    {
      "type": "Feature",
      "id": "node/11903605971",
      "properties": {
        "timestamp": "2024-05-14T10:16:25Z",
        "version": 1,
        "changeset": 151305038,
        "name": "Cachoeira da Salinas",
        "waterway": "waterfall",
        "id": "node/11903605971"
      },
      "geometry": {
        "type": "Point",
        "coordinates": [
          -42.5415891,
          -14.0885851
        ]
      }
    },
    {
      "type": "Feature",
      "id": "node/11903606016",
      "properties": {
        "timestamp": "2024-05-14T10:16:25Z",
        "version": 1,
        "changeset": 151305038,
        "name": "Cachoeira do Capão de Tereza",
        "waterway": "waterfall",
        "id": "node/11903606016"
      },
      "geometry": {
        "type": "Point",
        "coordinates": [
          -42.4926699,
          -14.2051561
        ]
      }
    }
  ]
}
