{
  "type": "FeatureCollection",
  "features": [
    {
      "type": "Feature",
      "id": "node/5257765023",
      "properties": {
        "timestamp": "2017-12-01T14:35:12Z",
        "version": 1,
        "changeset": 54237865,
        "amenity": "cinema",
        "name": "Cinesystem",
        "id": "node/5257765023"
      },
      "geometry": {
        "type": "Point",
        "coordinates": [
          -42.9054016,
          -22.7681427
        ]
      }
    }
  ]
}
