{
  "type": "FeatureCollection",
  "features": [
    {
      "type": "Feature",
      "id": "node/5256965118",
      "properties": {
        "timestamp": "2017-12-04T12:28:48Z",
        "version": 4,
        "changeset": 54327695,
        "addr:city": "Itaboraí",
        "addr:housenumber": "49-141",
        "addr:postcode": "24800-041",
        "addr:street": "Praça Marechal Floriano Peixoto",
        "addr:suburb": "Centro",
        "description": "Joaquim Manuel de Macedo foi um médico, jornalista, político, professor, romancista, poeta, teatrólogo e memorialista brasileiro. É o patrono da cadeira nº 20 da Academia Brasileira de Letras.",
        "historic": "monument",
        "name": "Busto Joaquim Manoel de Macedo",
        "photo": "http://www.itaborai.rj.gov.br/wp-content/uploads/2015/06/DIVULGACAO2.jpg",
        "wikipedia": "pt:Joaquim Manuel de Macedo",
        "id": "node/5256965118"
      },
      "geometry": {
        "type": "Point",
        "coordinates": [
          -42.8590701,
          -22.7452462
        ]
      }
    },
    {
      "type": "Feature",
      "id": "node/5320468160",
      "properties": {
        "timestamp": "2018-01-04T16:14:04Z",
        "version": 1,
        "changeset": 55162303,
        "historic": "monument",
        "name": "Torre de Tijolos Dimattoni",
        "tower:type": "concrete",
        "id": "node/5320468160"
      },
      "geometry": {
        "type": "Point",
        "coordinates": [
          -42.8976402,
          -22.760644
        ]
      }
    },
    {
      "type": "Feature",
      "id": "node/6532289768",
      "properties": {
        "timestamp": "2019-06-07T15:57:00Z",
        "version": 1,
        "changeset": 71028444,
        "historic": "monument",
        "name": "Monumento",
        "id": "node/6532289768"
      },
      "geometry": {
        "type": "Point",
        "coordinates": [
          -42.8394526,
          -22.7386677
        ]
      }
    },
    {
      "type": "Feature",
      "id": "node/7346806495",
      "properties": {
        "timestamp": "2020-03-30T16:10:55Z",
        "version": 1,
        "changeset": 82833684,
        "historic": "monument",
        "name": "placa da revitalizaçao da praça",
        "id": "node/7346806495"
      },
      "geometry": {
        "type": "Point",
        "coordinates": [
          -42.8390775,
          -22.738428
        ]
      }
    }
  ]
}
