{
  "type": "FeatureCollection",
  "features": [
    {
      "type": "Feature",
      "id": "node/3518304250",
      "properties": {
        "timestamp": "2021-01-25T16:27:52Z",
        "version": 2,
        "changeset": 98134176,
        "contact:email": "hotelfazendadesatuba@hotmail.com",
        "contact:phone": "+55 82) 4141-2439",
        "contact:website": "http://www.hotelfazendasatuba.com.br/",
        "name": "Hotel Fazenda Satuba",
        "phone": "+55 82 4141-2442",
        "tourism": "hotel",
        "id": "node/3518304250"
      },
      "geometry": {
        "type": "Point",
        "coordinates": [
          -35.8606422,
          -9.5987477
        ]
      }
    }
  ]
}
