{
  "type": "FeatureCollection",
  "features": [
    {
      "type": "Feature",
      "id": "node/3065973544",
      "properties": {
        "timestamp": "2023-02-08T19:27:31Z",
        "version": 2,
        "changeset": 132272684,
        "addr:city": "Córrego Danta",
        "alt_name": "CRAS",
        "amenity": "social_facility",
        "name": "Centro de Referência de Assistência Social",
        "social_facility": "outreach",
        "social_facility:for": "underprivileged",
        "source": "survey",
        "id": "node/3065973544"
      },
      "geometry": {
        "type": "Point",
        "coordinates": [
          -45.9040255,
          -19.8276774
        ]
      }
    }
  ]
}
