{
  "type": "FeatureCollection",
  "features": [
    {
      "type": "Feature",
      "id": "node/703505756",
      "properties": {
        "timestamp": "2022-03-18T06:55:36Z",
        "version": 2,
        "changeset": 118619352,
        "waterway": "waterfall",
        "id": "node/703505756"
      },
      "geometry": {
        "type": "Point",
        "coordinates": [
          -51.1954021,
          -27.6495974
        ]
      }
    },
    {
      "type": "Feature",
      "id": "node/8220746417",
      "properties": {
        "timestamp": "2021-09-27T22:34:37Z",
        "version": 2,
        "changeset": 111791100,
        "name": "Furnas do Brechó",
        "waterway": "waterfall",
        "id": "node/8220746417"
      },
      "geometry": {
        "type": "Point",
        "coordinates": [
          -51.4342242,
          -27.6204266
        ]
      }
    }
  ]
}
