{
  "type": "FeatureCollection",
  "features": [
    {
      "type": "Feature",
      "id": "node/2673205636",
      "properties": {
        "timestamp": "2016-01-11T21:59:59Z",
        "version": 2,
        "changeset": 36514375,
        "addr:city": "Unaí",
        "addr:housenumber": "14",
        "addr:postcode": "38618-000",
        "addr:street": "Rua Fonseca Melo",
        "amenity": "community_centre",
        "name": "Associação Comunitária de Pedras",
        "id": "node/2673205636"
      },
      "geometry": {
        "type": "Point",
        "coordinates": [
          -46.4222666,
          -16.2014249
        ]
      }
    },
    {
      "type": "Feature",
      "id": "node/5268299221",
      "properties": {
        "timestamp": "2017-12-06T17:13:38Z",
        "version": 1,
        "changeset": 54407625,
        "amenity": "community_centre",
        "name": "Salão de Festas",
        "id": "node/5268299221"
      },
      "geometry": {
        "type": "Point",
        "coordinates": [
          -46.8846948,
          -16.3793205
        ]
      }
    }
  ]
}
