{
  "type": "FeatureCollection",
  "features": [
    {
      "type": "Feature",
      "id": "node/9621352317",
      "properties": {
        "timestamp": "2022-11-18T20:52:52Z",
        "version": 2,
        "changeset": 129101737,
        "addr:street": "Rodovia José Abílio Bruno",
        "amenity": "dentist",
        "healthcare": "dentist",
        "name": "Icaraí Saúde",
        "id": "node/9621352317"
      },
      "geometry": {
        "type": "Point",
        "coordinates": [
          -39.6530731,
          -3.0303771
        ]
      }
    },
    {
      "type": "Feature",
      "id": "node/10056309817",
      "properties": {
        "timestamp": "2022-11-18T20:52:52Z",
        "version": 2,
        "changeset": 129101737,
        "addr:street": "Rodovia José Abílio Bruno",
        "amenity": "dentist",
        "healthcare": "dentist",
        "name": "Clinica Integrada Dra. Michelle Silveira",
        "phone": "88981741618",
        "id": "node/10056309817"
      },
      "geometry": {
        "type": "Point",
        "coordinates": [
          -39.6517919,
          -3.0286774
        ]
      }
    },
    {
      "type": "Feature",
      "id": "node/10878553406",
      "properties": {
        "timestamp": "2023-09-16T01:11:57Z",
        "version": 2,
        "changeset": 141324318,
        "amenity": "dentist",
        "name": "Dr.Sorriso",
        "id": "node/10878553406"
      },
      "geometry": {
        "type": "Point",
        "coordinates": [
          -39.8323125,
          -3.361033
        ]
      }
    }
  ]
}
