{
  "type": "FeatureCollection",
  "features": [
    {
      "type": "Feature",
      "id": "node/11994586180",
      "properties": {
        "timestamp": "2024-06-20T14:06:48Z",
        "version": 1,
        "changeset": 152947846,
        "historic": "monument",
        "inscription": "NE PUTES QUOD ANIMAN TUAM LIBERES QUIA IN DOMO\nRECIS ES PRO CUNCTIS POPULIS",
        "name": "Monumento do Santo Cristo de Ervália",
        "id": "node/11994586180"
      },
      "geometry": {
        "type": "Point",
        "coordinates": [
          -42.6530992,
          -20.8384292
        ]
      }
    },
    {
      "type": "Feature",
      "id": "node/11994586189",
      "properties": {
        "timestamp": "2024-06-20T14:06:48Z",
        "version": 1,
        "changeset": 152947846,
        "historic": "monument",
        "name": "O Cristo Redentor",
        "id": "node/11994586189"
      },
      "geometry": {
        "type": "Point",
        "coordinates": [
          -42.653392,
          -20.8395522
        ]
      }
    }
  ]
}
