{
  "type": "FeatureCollection",
  "features": [
    {
      "type": "Feature",
      "id": "node/8636271444",
      "properties": {
        "timestamp": "2022-09-10T22:50:59Z",
        "version": 4,
        "changeset": 126031961,
        "air_conditioning": "no",
        "amenity": "library",
        "fixme": "verificar localização",
        "name": "Biblioteca Pública Municipal Dom Daniel Hostin",
        "wheelchair": "yes",
        "id": "node/8636271444"
      },
      "geometry": {
        "type": "Point",
        "coordinates": [
          -51.8917896,
          -27.0224675
        ]
      }
    }
  ]
}
