{
  "type": "FeatureCollection",
  "features": [
    {
      "type": "Feature",
      "id": "node/3469576413",
      "properties": {
        "timestamp": "2016-07-17T01:53:34Z",
        "version": 4,
        "changeset": 40790347,
        "amenity": "pharmacy",
        "id": "node/3469576413"
      },
      "geometry": {
        "type": "Point",
        "coordinates": [
          -47.9310243,
          -25.0080168
        ]
      }
    },
    {
      "type": "Feature",
      "id": "node/3469589054",
      "properties": {
        "timestamp": "2015-05-07T15:42:37Z",
        "version": 2,
        "changeset": 30876991,
        "amenity": "pharmacy",
        "name": "Laboratório Laborclin",
        "id": "node/3469589054"
      },
      "geometry": {
        "type": "Point",
        "coordinates": [
          -47.9296189,
          -25.0116822
        ]
      }
    },
    {
      "type": "Feature",
      "id": "node/3469590861",
      "properties": {
        "timestamp": "2016-07-17T01:53:34Z",
        "version": 5,
        "changeset": 40790347,
        "amenity": "pharmacy",
        "id": "node/3469590861"
      },
      "geometry": {
        "type": "Point",
        "coordinates": [
          -47.9300588,
          -25.0105447
        ]
      }
    }
  ]
}
