{
  "type": "FeatureCollection",
  "features": [
    {
      "type": "Feature",
      "id": "node/6672483711",
      "properties": {
        "timestamp": "2019-08-01T19:44:52Z",
        "version": 1,
        "changeset": 72912979,
        "amenity": "library",
        "name": "Biblioteca Pública",
        "id": "node/6672483711"
      },
      "geometry": {
        "type": "Point",
        "coordinates": [
          -40.1735602,
          -3.0555649
        ]
      }
    }
  ]
}
