{
  "type": "FeatureCollection",
  "features": [
    {
      "type": "Feature",
      "id": "node/5655024342",
      "properties": {
        "timestamp": "2018-06-01T01:37:48Z",
        "version": 1,
        "changeset": 59447212,
        "amenity": "cinema",
        "name": "Cinemaxs",
        "id": "node/5655024342"
      },
      "geometry": {
        "type": "Point",
        "coordinates": [
          -52.3749843,
          -24.0371989
        ]
      }
    }
  ]
}
