{
  "type": "FeatureCollection",
  "features": [
    {
      "type": "Feature",
      "id": "node/4943999429",
      "properties": {
        "timestamp": "2024-01-27T14:32:41Z",
        "version": 3,
        "changeset": 146746370,
        "amenity": "clinic",
        "healthcare": "clinic",
        "name": "Climed",
        "name:pt": "Climed",
        "id": "node/4943999429"
      },
      "geometry": {
        "type": "Point",
        "coordinates": [
          -37.2522223,
          -7.2177452
        ]
      }
    }
  ]
}
