{
  "type": "FeatureCollection",
  "features": [
    {
      "type": "Feature",
      "id": "node/4943999429",
      "properties": {
        "timestamp": "2021-02-23T04:36:01Z",
        "version": 2,
        "changeset": 99786804,
        "amenity": "clinic",
        "healthcare": "clinic",
        "name": "Climed",
        "name:pt": "Climed",
        "id": "node/4943999429"
      },
      "geometry": {
        "type": "Point",
        "coordinates": [
          -37.2522263,
          -7.2176787
        ]
      }
    }
  ]
}
