{
  "type": "FeatureCollection",
  "features": [
    {
      "type": "Feature",
      "id": "node/4993558525",
      "properties": {
        "timestamp": "2021-02-23T04:36:01Z",
        "version": 2,
        "changeset": 99786804,
        "amenity": "pharmacy",
        "healthcare": "pharmacy",
        "name": "Farmácia Santa Isabel",
        "name:pt": "Farmácia Santa Isabel",
        "id": "node/4993558525"
      },
      "geometry": {
        "type": "Point",
        "coordinates": [
          -37.2536879,
          -7.2252943
        ]
      }
    },
    {
      "type": "Feature",
      "id": "node/4993558529",
      "properties": {
        "timestamp": "2024-01-28T18:29:18Z",
        "version": 3,
        "changeset": 146790667,
        "amenity": "pharmacy",
        "healthcare": "pharmacy",
        "name": "Central",
        "name:pt": "Central",
        "id": "node/4993558529"
      },
      "geometry": {
        "type": "Point",
        "coordinates": [
          -37.2528397,
          -7.2217036
        ]
      }
    },
    {
      "type": "Feature",
      "id": "node/11560102617",
      "properties": {
        "timestamp": "2024-01-28T17:17:59Z",
        "version": 1,
        "changeset": 146787979,
        "amenity": "pharmacy",
        "healthcare": "pharmacy",
        "name": "Santa Maria Madalena",
        "source": "survey",
        "id": "node/11560102617"
      },
      "geometry": {
        "type": "Point",
        "coordinates": [
          -37.254355,
          -7.2216225
        ]
      }
    }
  ]
}
