{
  "type": "FeatureCollection",
  "features": [
    {
      "type": "Feature",
      "id": "node/4993558525",
      "properties": {
        "timestamp": "2021-02-23T04:36:01Z",
        "version": 2,
        "changeset": 99786804,
        "amenity": "pharmacy",
        "healthcare": "pharmacy",
        "name": "Farmácia Santa Isabel",
        "name:pt": "Farmácia Santa Isabel",
        "id": "node/4993558525"
      },
      "geometry": {
        "type": "Point",
        "coordinates": [
          -37.2536879,
          -7.2252943
        ]
      }
    },
    {
      "type": "Feature",
      "id": "node/4993558529",
      "properties": {
        "timestamp": "2021-02-23T04:36:01Z",
        "version": 2,
        "changeset": 99786804,
        "amenity": "pharmacy",
        "healthcare": "pharmacy",
        "name": "Central",
        "name:pt": "Central",
        "id": "node/4993558529"
      },
      "geometry": {
        "type": "Point",
        "coordinates": [
          -37.253014,
          -7.2216198
        ]
      }
    }
  ]
}
