{
  "type": "FeatureCollection",
  "features": [
    {
      "type": "Feature",
      "id": "node/4993558525",
      "properties": {
        "timestamp": "2024-01-30T23:36:12Z",
        "version": 3,
        "changeset": 146883072,
        "amenity": "pharmacy",
        "healthcare": "pharmacy",
        "name": "Farmácia Santa Isabel",
        "name:pt": "Farmácia Santa Isabel",
        "id": "node/4993558525"
      },
      "geometry": {
        "type": "Point",
        "coordinates": [
          -37.2536591,
          -7.2253069
        ]
      }
    },
    {
      "type": "Feature",
      "id": "node/4993558529",
      "properties": {
        "timestamp": "2024-01-28T18:29:18Z",
        "version": 3,
        "changeset": 146790667,
        "amenity": "pharmacy",
        "healthcare": "pharmacy",
        "name": "Central",
        "name:pt": "Central",
        "id": "node/4993558529"
      },
      "geometry": {
        "type": "Point",
        "coordinates": [
          -37.2528397,
          -7.2217036
        ]
      }
    },
    {
      "type": "Feature",
      "id": "node/11560102617",
      "properties": {
        "timestamp": "2024-01-28T17:17:59Z",
        "version": 1,
        "changeset": 146787979,
        "amenity": "pharmacy",
        "healthcare": "pharmacy",
        "name": "Santa Maria Madalena",
        "source": "survey",
        "id": "node/11560102617"
      },
      "geometry": {
        "type": "Point",
        "coordinates": [
          -37.254355,
          -7.2216225
        ]
      }
    },
    {
      "type": "Feature",
      "id": "node/11815110170",
      "properties": {
        "timestamp": "2024-04-13T18:16:18Z",
        "version": 1,
        "changeset": 149964163,
        "amenity": "pharmacy",
        "name": "Santo Antônio",
        "id": "node/11815110170"
      },
      "geometry": {
        "type": "Point",
        "coordinates": [
          -37.254488,
          -7.2225735
        ]
      }
    }
  ]
}
