{
  "type": "FeatureCollection",
  "features": [
    {
      "type": "Feature",
      "id": "node/5549163337",
      "properties": {
        "timestamp": "2018-04-12T23:54:01Z",
        "version": 1,
        "changeset": 58050242,
        "amenity": "clinic",
        "healthcare": "clinic",
        "name": "Centro Municipal de Saúde Manuel Morales",
        "id": "node/5549163337"
      },
      "geometry": {
        "type": "Point",
        "coordinates": [
          -48.3387212,
          -22.0413285
        ]
      }
    }
  ]
}
