{
  "type": "FeatureCollection",
  "features": [
    {
      "type": "Feature",
      "id": "node/3702161925",
      "properties": {
        "timestamp": "2015-08-18T01:57:23Z",
        "version": 1,
        "changeset": 33405743,
        "amenity": "library",
        "name": "Biblioteca Hermes Fontes",
        "id": "node/3702161925"
      },
      "geometry": {
        "type": "Point",
        "coordinates": [
          -37.6219296,
          -11.1472965
        ]
      }
    }
  ]
}
