{
  "type": "FeatureCollection",
  "features": [
    {
      "type": "Feature",
      "id": "node/4558012005",
      "properties": {
        "timestamp": "2017-03-25T21:49:31Z",
        "version": 2,
        "changeset": 47163508,
        "addr:street": "Rua Francisco Guerino",
        "amenity": "library",
        "fixme": "Corrigir a localização da biblioteca.",
        "name": "Professora Onice Bianchi",
        "official_name": "Biblioteca Pública Municipal Professora Onice Bianchi",
        "source:official_name": "LM 427/1998",
        "id": "node/4558012005"
      },
      "geometry": {
        "type": "Point",
        "coordinates": [
          -53.5850306,
          -29.642805
        ]
      }
    }
  ]
}
