{
  "type": "FeatureCollection",
  "features": [
    {
      "type": "Feature",
      "id": "node/3946828954",
      "properties": {
        "timestamp": "2016-02-06T17:27:30Z",
        "version": 2,
        "changeset": 37045079,
        "addr:housenumber": "17",
        "addr:street": "Praça Neuzice Barreto de Lima",
        "amenity": "pharmacy",
        "id": "node/3946828954"
      },
      "geometry": {
        "type": "Point",
        "coordinates": [
          -37.1927536,
          -10.6484286
        ]
      }
    },
    {
      "type": "Feature",
      "id": "node/3980270827",
      "properties": {
        "timestamp": "2016-01-31T18:30:05Z",
        "version": 1,
        "changeset": 36922523,
        "amenity": "pharmacy",
        "name": "Farmácia Popular",
        "id": "node/3980270827"
      },
      "geometry": {
        "type": "Point",
        "coordinates": [
          -37.1917954,
          -10.6479053
        ]
      }
    }
  ]
}
