{
  "type": "FeatureCollection",
  "features": [
    {
      "type": "Feature",
      "id": "node/11104628208",
      "properties": {
        "timestamp": "2023-08-10T11:57:16Z",
        "version": 1,
        "changeset": 139703342,
        "access": "yes",
        "historic": "monument",
        "name": "Monumento à Lenda de Encantado",
        "id": "node/11104628208"
      },
      "geometry": {
        "type": "Point",
        "coordinates": [
          -51.8876395,
          -29.234936
        ]
      }
    }
  ]
}
