{
  "type": "FeatureCollection",
  "features": [
    {
      "type": "Feature",
      "id": "node/11345240064",
      "properties": {
        "timestamp": "2023-11-12T22:09:53Z",
        "version": 1,
        "changeset": 143950040,
        "artist_name": "Vilam Loviška",
        "historic": "memorial",
        "inscription": "MONUMENTO COMEMORATIVO\nÀ VISTA\nGEN. MILAN RASTISLAV ŠTEFÁNIK\n(* 21.07.1880 + 04.05.1919)\nASTRÓNOMO, ESTADISTA E HERÓI\nDA NAÇÂO ESLOVACA.\nPOR OCASIÂO DA ECLIPSE SOLAR DE 1912\nPASSA QUATRO, 9 DE DEZEMBRO DE 1995",
        "material": "betón,_bronz",
        "memorial": "war_memorial",
        "name": "Gen. Milan R. Stefanik",
        "start_date": "1995-12-09",
        "website": "https://www.vets.cz/vpm/mista/obec/9761-passa-quatro/",
        "id": "node/11345240064"
      },
      "geometry": {
        "type": "Point",
        "coordinates": [
          -44.9671532,
          -22.3955151
        ]
      }
    }
  ]
}
