{
  "type": "FeatureCollection",
  "features": [
    {
      "type": "Feature",
      "id": "node/11345240064",
      "properties": {
        "timestamp": "2024-06-05T15:37:30Z",
        "version": 2,
        "changeset": 152294125,
        "artist_name": "Vilam Loviška",
        "historic": "memorial",
        "inscription": "MONUMENTO COMEMORATIVO\nÀ VISTA\nGEN. MILAN RASTISLAV ŠTEFÁNIK\n(* 21.07.1880 + 04.05.1919)\nASTRÓNOMO, ESTADISTA E HERÓI\nDA NAÇÂO ESLOVACA.\nPOR OCASIÂO DA ECLIPSE SOLAR DE 1912\nPASSA QUATRO, 9 DE DEZEMBRO DE 1995",
        "material": "concrete;bronze",
        "memorial": "bust",
        "name": "Gen. Milan Rastislav Štefánik",
        "start_date": "1995-12-09",
        "subject:wikidata": "Q319962",
        "subject:wikipedia": "sk:Milan Rastislav Štefánik",
        "url": "https://www.vets.cz/vpm/mista/obec/9761-passa-quatro/",
        "id": "node/11345240064"
      },
      "geometry": {
        "type": "Point",
        "coordinates": [
          -44.9671532,
          -22.3955151
        ]
      }
    }
  ]
}
