{
  "type": "FeatureCollection",
  "features": [
    {
      "type": "Feature",
      "id": "node/9974805163",
      "properties": {
        "timestamp": "2022-08-24T12:24:23Z",
        "version": 1,
        "changeset": 125313856,
        "addr:city": "Carangola",
        "addr:housenumber": "427",
        "addr:postcode": "36800-000",
        "addr:street": "Rua Pedro de Oliveira",
        "addr:suburb": "Centro",
        "email": "aps11025010@inss.gov.br",
        "government": "administrative",
        "name": "Agência da Previdência Social em Carangola",
        "office": "government",
        "phone": "+55 32 3741 2503",
        "id": "node/9974805163"
      },
      "geometry": {
        "type": "Point",
        "coordinates": [
          -42.033972,
          -20.7314754
        ]
      }
    },
    {
      "type": "Feature",
      "id": "node/9974840448",
      "properties": {
        "timestamp": "2022-08-24T12:54:44Z",
        "version": 1,
        "changeset": 125315365,
        "addr:city": "Carangola",
        "addr:housenumber": "15",
        "addr:postcode": "36800-000",
        "addr:street": "Rua Barão de São Francisco",
        "addr:suburb": "Centro",
        "government": "prosecutor",
        "name": "Promotoria de Justiça da Comarca de Carangola",
        "office": "government",
        "operator": "Ministério Público do Estado de Minas Gerais",
        "phone": "+55 32 3741 7003",
        "website": "https://www.mpmg.mp.br/portal/auxiliar/telefones-e-enderecos/detalhe/idunidade/340.shtml",
        "id": "node/9974840448"
      },
      "geometry": {
        "type": "Point",
        "coordinates": [
          -42.0283641,
          -20.7347422
        ]
      }
    }
  ]
}
