{
  "type": "FeatureCollection",
  "features": [
    {
      "type": "Feature",
      "id": "node/12380405872",
      "properties": {
        "timestamp": "2024-11-27T21:27:34Z",
        "version": 1,
        "changeset": 159678697,
        "amenity": "pharmacy",
        "healthcare": "pharmacy",
        "name": "Farmácia do Marcelo",
        "id": "node/12380405872"
      },
      "geometry": {
        "type": "Point",
        "coordinates": [
          -41.469035,
          -11.6944935
        ]
      }
    },
    {
      "type": "Feature",
      "id": "node/12380405884",
      "properties": {
        "timestamp": "2024-11-27T21:27:34Z",
        "version": 1,
        "changeset": 159678697,
        "amenity": "pharmacy",
        "healthcare": "pharmacy",
        "name": "Fármacia do Vaqueiro",
        "id": "node/12380405884"
      },
      "geometry": {
        "type": "Point",
        "coordinates": [
          -41.4679566,
          -11.6946708
        ]
      }
    }
  ]
}
