{
  "type": "FeatureCollection",
  "features": [
    {
      "type": "Feature",
      "id": "node/6093610583",
      "properties": {
        "timestamp": "2021-01-10T21:06:09Z",
        "version": 3,
        "changeset": 97264011,
        "addr:city": "Coremas",
        "addr:postcode": "58770-000",
        "addr:street": "Avenida Manoel Cavalcante",
        "addr:suburb": "Centro",
        "amenity": "dentist",
        "fax": "+55 83 9 9655-0777",
        "healthcare": "dentist",
        "name": "Odontoriso - Clínica Odontológica",
        "id": "node/6093610583"
      },
      "geometry": {
        "type": "Point",
        "coordinates": [
          -37.9452348,
          -7.0178891
        ]
      }
    }
  ]
}
