{
  "type": "FeatureCollection",
  "features": [
    {
      "type": "Feature",
      "id": "node/6582969879",
      "properties": {
        "timestamp": "2019-07-02T00:09:16Z",
        "version": 1,
        "changeset": 71803102,
        "addr:city": "Santa Rosa do Piauí",
        "addr:postcode": "64518000",
        "addr:street": "Rua Veríssimo Antônio da Silva",
        "addr:suburb": "Centro",
        "amenity": "hospital",
        "description": "Hospital público da Cidade",
        "healthcare": "hospital",
        "healthcare:speciality": "general",
        "name": "Hospital Dom Edilberto Dinkelborg",
        "id": "node/6582969879"
      },
      "geometry": {
        "type": "Point",
        "coordinates": [
          -42.2810547,
          -6.7975038
        ]
      }
    },
    {
      "type": "Feature",
      "id": "node/6584525514",
      "properties": {
        "timestamp": "2019-07-02T17:19:19Z",
        "version": 1,
        "changeset": 71830434,
        "amenity": "hospital",
        "healthcare": "hospital",
        "healthcare:speciality": "general",
        "name": "Posto de Saúde",
        "id": "node/6584525514"
      },
      "geometry": {
        "type": "Point",
        "coordinates": [
          -42.2770752,
          -6.8009228
        ]
      }
    },
    {
      "type": "Feature",
      "id": "node/6590076891",
      "properties": {
        "timestamp": "2019-07-05T00:19:39Z",
        "version": 1,
        "changeset": 71913319,
        "addr:city": "Santa Rosa do Piauí",
        "addr:postcode": "64518000",
        "addr:street": "Rua José Muniz",
        "addr:suburb": "Pé da Serra",
        "amenity": "hospital",
        "healthcare": "hospital",
        "healthcare:speciality": "general",
        "name": "Posto de Saúde Unidade 3",
        "id": "node/6590076891"
      },
      "geometry": {
        "type": "Point",
        "coordinates": [
          -42.2846022,
          -6.792162
        ]
      }
    }
  ]
}
