{
  "type": "FeatureCollection",
  "features": [
    {
      "type": "Feature",
      "id": "node/6380166771",
      "properties": {
        "timestamp": "2019-04-03T06:19:51Z",
        "version": 1,
        "changeset": 68824099,
        "addr:city": "Porto Franco",
        "addr:housenumber": "212",
        "addr:postcode": "65970000",
        "addr:street": "Travessa Carolina",
        "addr:suburb": "Centro",
        "government": "public_service",
        "name": "Secretaria de Assistência Social",
        "office": "government",
        "opening_hours": "Mo-Fr 08:00-17:00",
        "id": "node/6380166771"
      },
      "geometry": {
        "type": "Point",
        "coordinates": [
          -47.3938308,
          -6.3361762
        ]
      }
    }
  ]
}
