{
  "type": "FeatureCollection",
  "features": [
    {
      "type": "Feature",
      "id": "node/7143095586",
      "properties": {
        "timestamp": "2020-01-19T17:41:50Z",
        "version": 1,
        "changeset": 79760912,
        "name": "Mundico",
        "tourism": "guest_house",
        "id": "node/7143095586"
      },
      "geometry": {
        "type": "Point",
        "coordinates": [
          -44.4122706,
          -2.4033002
        ]
      }
    }
  ]
}
