{
  "type": "FeatureCollection",
  "features": [
    {
      "type": "Feature",
      "id": "node/4346736871",
      "properties": {
        "timestamp": "2016-09-27T14:37:00Z",
        "version": 2,
        "changeset": 42471889,
        "addr:city": "Lajeado",
        "addr:housenumber": "87",
        "addr:street": "Avenida Parque do Imigrante",
        "amenity": "nursing_home",
        "name": "Lar Santa Rita de Cássia",
        "phone": "+55 51 3279-5201",
        "id": "node/4346736871"
      },
      "geometry": {
        "type": "Point",
        "coordinates": [
          -51.9557068,
          -29.456119
        ]
      }
    }
  ]
}
