{
  "type": "FeatureCollection",
  "features": [
    {
      "type": "Feature",
      "id": "node/2938354736",
      "properties": {
        "timestamp": "2019-01-18T23:43:51Z",
        "version": 4,
        "changeset": 66442756,
        "addr:street": "Rodovia Engenheiro Félix Malburg",
        "building": "hotel",
        "name": "Hotel Formosa",
        "phone": "+55 49 3343-0052",
        "tourism": "hotel",
        "id": "node/2938354736"
      },
      "geometry": {
        "type": "Point",
        "coordinates": [
          -52.7970706,
          -26.6493282
        ]
      }
    }
  ]
}
