{
  "type": "FeatureCollection",
  "features": [
    {
      "type": "Feature",
      "id": "node/12542213520",
      "properties": {
        "timestamp": "2025-01-29T16:47:33Z",
        "version": 1,
        "changeset": 161905518,
        "amenity": "doctors",
        "healthcare": "doctor",
        "name": "Clínica Contri",
        "id": "node/12542213520"
      },
      "geometry": {
        "type": "Point",
        "coordinates": [
          -46.7407148,
          -22.1938173
        ]
      }
    }
  ]
}
