{
  "type": "FeatureCollection",
  "features": [
    {
      "type": "Feature",
      "id": "node/11196409537",
      "properties": {
        "timestamp": "2023-09-16T18:44:39Z",
        "version": 1,
        "changeset": 141355075,
        "addr:housenumber": "19",
        "addr:street": "Rua Felisbino Passos",
        "amenity": "nursing_home",
        "name": "Lar Rosa de Saron",
        "id": "node/11196409537"
      },
      "geometry": {
        "type": "Point",
        "coordinates": [
          -49.216385,
          -25.3862133
        ]
      }
    }
  ]
}
