{
  "type": "FeatureCollection",
  "features": [
    {
      "type": "Feature",
      "id": "node/3886691238",
      "properties": {
        "timestamp": "2015-12-10T21:28:27Z",
        "version": 1,
        "changeset": 35874134,
        "internet_access": "wlan",
        "name": "Veredas do Sertao",
        "tourism": "hotel",
        "id": "node/3886691238"
      },
      "geometry": {
        "type": "Point",
        "coordinates": [
          -39.2906806,
          -5.1955951
        ]
      }
    },
    {
      "type": "Feature",
      "id": "node/8511457256",
      "properties": {
        "timestamp": "2021-03-12T18:52:04Z",
        "version": 1,
        "changeset": 100926663,
        "name": "Pousada Quisertão",
        "tourism": "hotel",
        "id": "node/8511457256"
      },
      "geometry": {
        "type": "Point",
        "coordinates": [
          -39.2906565,
          -5.1918274
        ]
      }
    }
  ]
}
