{
  "type": "FeatureCollection",
  "features": [
    {
      "type": "Feature",
      "id": "node/6385430569",
      "properties": {
        "timestamp": "2019-04-05T11:17:14Z",
        "version": 1,
        "changeset": 68917551,
        "government": "register_office",
        "name": "Tabelionato",
        "office": "government",
        "opening_hours": "Mo-Fr 09:00-17:00",
        "id": "node/6385430569"
      },
      "geometry": {
        "type": "Point",
        "coordinates": [
          -48.7768316,
          -27.6864956
        ]
      }
    },
    {
      "type": "Feature",
      "id": "node/6386696708",
      "properties": {
        "timestamp": "2021-11-24T00:03:45Z",
        "version": 3,
        "changeset": 114160700,
        "addr:postcode": "88140-000",
        "addr:street": "Rua Prefeito José Kehrig",
        "addr:suburb": "Centro",
        "building": "yes",
        "building:levels": "6",
        "description": "Atendimentos ao público sobre tributos, fiscalização de obras, IGP para Carteira de Identidade, Departamento de Trânsito, SINE carteira de Trabalho, Junta Militar e Protocolo Geral",
        "government": "public_service",
        "name": "Prédio Pró-Cidadão",
        "office": "government",
        "id": "node/6386696708"
      },
      "geometry": {
        "type": "Point",
        "coordinates": [
          -48.7767849,
          -27.6865062
        ]
      }
    },
    {
      "type": "Feature",
      "id": "node/9286507853",
      "properties": {
        "timestamp": "2024-09-24T20:40:00Z",
        "version": 3,
        "changeset": 157056397,
        "addr:city": "Santo Amaro da Imperatriz",
        "addr:postcode": "88140-000",
        "addr:street": "Rua Clemente Thiago Diniz",
        "addr:suburb": "Centro",
        "government": "register_office",
        "name": "Ofício de Registro de Imóveis",
        "office": "government",
        "id": "node/9286507853"
      },
      "geometry": {
        "type": "Point",
        "coordinates": [
          -48.7753399,
          -27.6858932
        ]
      }
    },
    {
      "type": "Feature",
      "id": "node/10582463679",
      "properties": {
        "timestamp": "2023-01-25T19:12:46Z",
        "version": 1,
        "changeset": 131707904,
        "addr:city": "Santo Amaro da Imperatriz",
        "addr:housenumber": "30",
        "addr:postcode": "88140-000",
        "addr:street": "Rua Padre Isidro Duarte e Silva",
        "addr:suburb": "Centro",
        "government": "register_office",
        "name": "Cartório Athayde",
        "office": "government",
        "opening_hours": "Mo-Fr 09:00-18:00",
        "phone": "+55 48 3245-1581",
        "id": "node/10582463679"
      },
      "geometry": {
        "type": "Point",
        "coordinates": [
          -48.7775672,
          -27.6881389
        ]
      }
    }
  ]
}
