{
  "type": "FeatureCollection",
  "features": [
    {
      "type": "Feature",
      "id": "node/7641274992",
      "properties": {
        "timestamp": "2021-04-02T23:23:29Z",
        "version": 3,
        "changeset": 102219323,
        "name": "Cachoeirinha do Itaúnas",
        "waterway": "waterfall",
        "id": "node/7641274992"
      },
      "geometry": {
        "type": "Point",
        "coordinates": [
          -40.9116099,
          -18.8316821
        ]
      }
    },
    {
      "type": "Feature",
      "id": "node/7641302528",
      "properties": {
        "timestamp": "2021-04-01T10:31:57Z",
        "version": 2,
        "changeset": 102117536,
        "name": "Cachoeira de Itaúna",
        "waterway": "waterfall",
        "id": "node/7641302528"
      },
      "geometry": {
        "type": "Point",
        "coordinates": [
          -40.9333414,
          -18.8699884
        ]
      }
    },
    {
      "type": "Feature",
      "id": "node/8512333382",
      "properties": {
        "timestamp": "2021-04-02T23:23:29Z",
        "version": 2,
        "changeset": 102219323,
        "name": "Cachoeirinha do Denzol",
        "waterway": "waterfall",
        "id": "node/8512333382"
      },
      "geometry": {
        "type": "Point",
        "coordinates": [
          -40.7644246,
          -18.6248018
        ]
      }
    },
    {
      "type": "Feature",
      "id": "node/8512351314",
      "properties": {
        "timestamp": "2021-08-28T17:31:20Z",
        "version": 2,
        "changeset": 110389017,
        "name": "Cachoeira do Granito",
        "waterway": "waterfall",
        "id": "node/8512351314"
      },
      "geometry": {
        "type": "Point",
        "coordinates": [
          -40.8006334,
          -18.6942651
        ]
      }
    }
  ]
}
