{
  "type": "FeatureCollection",
  "features": [
    {
      "type": "Feature",
      "id": "node/10043367686",
      "properties": {
        "timestamp": "2022-09-22T14:46:08Z",
        "version": 2,
        "changeset": 126508635,
        "alt_name": "2º/2º/1ª/4ºBBM;SAT;Seção de Atividades Técnicas",
        "contact:phone": "+55 48 3403-1555",
        "contact:website": "https://www.cbm.sc.gov.br/",
        "government": "fire_service",
        "name": "Serviço de Segurança Contra Incêndio",
        "office": "government",
        "operator": "Corpo de Bombeiros Militar de Santa Catarina",
        "operator:short": "CBMSC",
        "operator:type": "public",
        "operator:wikidata": "Q768967",
        "owner": "Governo do Estado de Santa Catarina",
        "ownership": "state",
        "short_name": "SSCI",
        "id": "node/10043367686"
      },
      "geometry": {
        "type": "Point",
        "coordinates": [
          -49.422264,
          -28.5975438
        ]
      }
    }
  ]
}
