{
  "type": "FeatureCollection",
  "features": [
    {
      "type": "Feature",
      "id": "node/7199020574",
      "properties": {
        "timestamp": "2023-05-06T17:36:39Z",
        "version": 3,
        "changeset": 135786145,
        "addr:city": "Araputanga",
        "addr:housenumber": "228",
        "addr:postcode": "78260-000",
        "addr:street": "Rua Rui Barbosa",
        "addr:suburb": "Centro",
        "amenity": "hospital",
        "email": "mat.araputanga@sspnet.com.br",
        "fax": "+55 65 3261 1628",
        "healthcare": "hospital",
        "name": "Hospital Geral e Maternidade Araputanga",
        "phone": "+55 65 3261 1200",
        "ref:CNES": "2752611",
        "ref:vatin": "BR14961171000191",
        "id": "node/7199020574"
      },
      "geometry": {
        "type": "Point",
        "coordinates": [
          -58.3521636,
          -15.4677177
        ]
      }
    }
  ]
}
