{
  "type": "FeatureCollection",
  "features": [
    {
      "type": "Feature",
      "id": "node/12385539444",
      "properties": {
        "timestamp": "2025-03-07T20:31:30Z",
        "version": 2,
        "changeset": 163342806,
        "addr:city": "Serra Preta",
        "addr:postcode": "44660-000",
        "addr:street": "Avenida Doutor Liberalino Sales Gadelha",
        "addr:suburb": "Centro",
        "air_conditioning": "yes",
        "email": "sec.edu21@gmail.com",
        "government": "education",
        "internet_access": "yes",
        "name": "Secretaria Municipal de Educação, Cultura, Esporte e Lazer",
        "office": "government",
        "opening_hours": "Mo-Fr 08:00-12:00,14:00-17:00",
        "operator": "Prefeitura Municipal de Serra Preta",
        "phone": "+55 75 3697 2232",
        "smoking": "no",
        "wheelchair": "yes",
        "id": "node/12385539444"
      },
      "geometry": {
        "type": "Point",
        "coordinates": [
          -39.3313349,
          -12.1598562
        ]
      }
    }
  ]
}
