{
  "type": "FeatureCollection",
  "features": [
    {
      "type": "Feature",
      "id": "node/12292868636",
      "properties": {
        "timestamp": "2024-10-28T01:45:02Z",
        "version": 1,
        "changeset": 158436754,
        "addr:city": "Serra Preta",
        "addr:postcode": "44660-000",
        "addr:street": "Avenida Dr. Liberalino Sales Gadelha",
        "addr:suburb": "Centro",
        "air_conditioning": "yes",
        "email": "sec.edu21@gmail.com",
        "government": "education",
        "internet_access": "wlan",
        "name": "Secretaria Municipal de Educação",
        "office": "government",
        "opening_hours": "Mo-Fr 08:00-12:00,14:00-17:00",
        "operator": "Prefeitura Municipal de Serra Preta",
        "phone": "+55 75 3697 2232",
        "smoking": "no",
        "wheelchair": "yes",
        "id": "node/12292868636"
      },
      "geometry": {
        "type": "Point",
        "coordinates": [
          -39.3313327,
          -12.1598556
        ]
      }
    }
  ]
}
