{
  "type": "FeatureCollection",
  "features": [
    {
      "type": "Feature",
      "id": "node/4931445342",
      "properties": {
        "timestamp": "2017-06-22T19:43:06Z",
        "version": 1,
        "changeset": 49755609,
        "government": "register_office",
        "name": "Cartório de Registro de Imóveis",
        "office": "government",
        "id": "node/4931445342"
      },
      "geometry": {
        "type": "Point",
        "coordinates": [
          -43.2947755,
          -20.683075
        ]
      }
    },
    {
      "type": "Feature",
      "id": "node/4931559419",
      "properties": {
        "timestamp": "2017-06-22T21:31:33Z",
        "version": 1,
        "changeset": 49757518,
        "government": "register_office",
        "name": "Registro de Pessoas",
        "office": "government",
        "id": "node/4931559419"
      },
      "geometry": {
        "type": "Point",
        "coordinates": [
          -43.304913,
          -20.6798914
        ]
      }
    },
    {
      "type": "Feature",
      "id": "node/4931559420",
      "properties": {
        "timestamp": "2017-06-22T21:31:33Z",
        "version": 1,
        "changeset": 49757518,
        "government": "register_office",
        "name": "Registro de Notas",
        "office": "government",
        "id": "node/4931559420"
      },
      "geometry": {
        "type": "Point",
        "coordinates": [
          -43.301131,
          -20.6833922
        ]
      }
    }
  ]
}
