{
  "type": "FeatureCollection",
  "features": [
    {
      "type": "Feature",
      "id": "node/6214425186",
      "properties": {
        "timestamp": "2019-01-16T19:59:35Z",
        "version": 1,
        "changeset": 66374373,
        "amenity": "community_centre",
        "name": "Centro Comunitario Nostra Senhora da Fátima",
        "id": "node/6214425186"
      },
      "geometry": {
        "type": "Point",
        "coordinates": [
          -51.1367533,
          -1.1658795
        ]
      }
    },
    {
      "type": "Feature",
      "id": "node/6214425285",
      "properties": {
        "timestamp": "2019-01-16T19:59:33Z",
        "version": 1,
        "changeset": 66374373,
        "amenity": "community_centre",
        "name": "Centro comunitario",
        "name:pt": "Centro Comunitario Nostra Senhora de Fátima",
        "id": "node/6214425285"
      },
      "geometry": {
        "type": "Point",
        "coordinates": [
          -51.1362716,
          -1.1640258
        ]
      }
    }
  ]
}
