{
  "type": "FeatureCollection",
  "features": [
    {
      "type": "Feature",
      "id": "node/6524726472",
      "properties": {
        "timestamp": "2019-07-30T19:37:04Z",
        "version": 2,
        "changeset": 72827741,
        "historic": "monument",
        "name": "Monumento Bíblia",
        "id": "node/6524726472"
      },
      "geometry": {
        "type": "Point",
        "coordinates": [
          -39.4852738,
          -13.7447177
        ]
      }
    },
    {
      "type": "Feature",
      "id": "node/6524927662",
      "properties": {
        "timestamp": "2019-06-05T15:40:04Z",
        "version": 1,
        "changeset": 70959348,
        "historic": "monument",
        "name": "Busto de Manoel Libanio",
        "id": "node/6524927662"
      },
      "geometry": {
        "type": "Point",
        "coordinates": [
          -39.4890916,
          -13.7448695
        ]
      }
    },
    {
      "type": "Feature",
      "id": "node/6525034201",
      "properties": {
        "timestamp": "2019-07-30T23:30:53Z",
        "version": 2,
        "changeset": 72832706,
        "historic": "monument",
        "name": "Seja Bem Vindo a Gandu",
        "id": "node/6525034201"
      },
      "geometry": {
        "type": "Point",
        "coordinates": [
          -39.4841034,
          -13.7461065
        ]
      }
    }
  ]
}
