{
  "type": "FeatureCollection",
  "features": [
    {
      "type": "Feature",
      "id": "node/5051937321",
      "properties": {
        "timestamp": "2017-08-22T18:28:10Z",
        "version": 1,
        "changeset": 51351364,
        "historic": "memorial",
        "name": "Ramal de acesso: Porto Grande",
        "name:pt": "Ramal de acesso: Porto Grande",
        "id": "node/5051937321"
      },
      "geometry": {
        "type": "Point",
        "coordinates": [
          -50.8898405,
          0.6571508
        ]
      }
    },
    {
      "type": "Feature",
      "id": "node/5051937621",
      "properties": {
        "timestamp": "2017-08-22T18:28:12Z",
        "version": 1,
        "changeset": 51351364,
        "historic": "memorial",
        "name": "Ramal de acesso: Porto Grande",
        "name:pt": "Ramal de acesso: Porto Grande",
        "id": "node/5051937621"
      },
      "geometry": {
        "type": "Point",
        "coordinates": [
          -50.8495312,
          0.7149607
        ]
      }
    }
  ]
}
