{
  "type": "FeatureCollection",
  "features": [
    {
      "type": "Feature",
      "id": "node/3845368917",
      "properties": {
        "timestamp": "2020-12-12T14:26:31Z",
        "version": 2,
        "changeset": 95724032,
        "addr:housenumber": "381",
        "addr:street": "Avenida Doutor Soares de Oliveira",
        "amenity": "pharmacy",
        "brand": "Droga Raia",
        "brand:wikidata": "Q10357101",
        "brand:wikipedia": "pt:RaiaDrogasil",
        "dispensing": "yes",
        "drive_through": "no",
        "healthcare": "pharmacy",
        "name": "Droga Raia",
        "id": "node/3845368917"
      },
      "geometry": {
        "type": "Point",
        "coordinates": [
          -47.7840671,
          -20.3362037
        ]
      }
    },
    {
      "type": "Feature",
      "id": "node/3845368929",
      "properties": {
        "timestamp": "2015-11-19T19:53:58Z",
        "version": 1,
        "changeset": 35445329,
        "addr:street": "Praça Dez de Março",
        "amenity": "pharmacy",
        "name": "Pharmain",
        "id": "node/3845368929"
      },
      "geometry": {
        "type": "Point",
        "coordinates": [
          -47.778536,
          -20.3376224
        ]
      }
    },
    {
      "type": "Feature",
      "id": "node/3845368930",
      "properties": {
        "timestamp": "2015-11-19T19:53:58Z",
        "version": 1,
        "changeset": 35445329,
        "addr:housenumber": "50",
        "addr:street": "Avenida Doutor Soares de Oliveira",
        "amenity": "pharmacy",
        "name": "Drogaria Total",
        "id": "node/3845368930"
      },
      "geometry": {
        "type": "Point",
        "coordinates": [
          -47.7806764,
          -20.3365309
        ]
      }
    }
  ]
}
