{
  "type": "FeatureCollection",
  "features": [
    {
      "type": "Feature",
      "id": "node/1719296100",
      "properties": {
        "timestamp": "2021-01-25T18:07:32Z",
        "version": 4,
        "changeset": 98138266,
        "amenity": "clinic",
        "emergency": "yes",
        "healthcare": "clinic",
        "name": "Posto de Saúde Municipal",
        "id": "node/1719296100"
      },
      "geometry": {
        "type": "Point",
        "coordinates": [
          -49.9764578,
          -29.6837932
        ]
      }
    },
    {
      "type": "Feature",
      "id": "node/6382449324",
      "properties": {
        "timestamp": "2019-04-04T04:14:37Z",
        "version": 1,
        "changeset": 68865747,
        "amenity": "clinic",
        "healthcare": "clinic",
        "name": "ESF São Jorge",
        "id": "node/6382449324"
      },
      "geometry": {
        "type": "Point",
        "coordinates": [
          -50.0240303,
          -29.7475333
        ]
      }
    },
    {
      "type": "Feature",
      "id": "node/10600153764",
      "properties": {
        "timestamp": "2023-02-01T23:21:01Z",
        "version": 1,
        "changeset": 131981751,
        "amenity": "clinic",
        "healthcare": "clinic",
        "name": "ESF Capão Novo",
        "id": "node/10600153764"
      },
      "geometry": {
        "type": "Point",
        "coordinates": [
          -49.9848764,
          -29.6783744
        ]
      }
    },
    {
      "type": "Feature",
      "id": "node/11622239073",
      "properties": {
        "timestamp": "2024-02-14T11:11:14Z",
        "version": 1,
        "changeset": 147445908,
        "addr:street": "Rua da Brigada Militar",
        "amenity": "clinic",
        "healthcare": "clinic",
        "name": "ESF São Jorge",
        "id": "node/11622239073"
      },
      "geometry": {
        "type": "Point",
        "coordinates": [
          -50.0188766,
          -29.7533305
        ]
      }
    }
  ]
}
