{
  "type": "FeatureCollection",
  "features": [
    {
      "type": "Feature",
      "id": "node/8184322717",
      "properties": {
        "timestamp": "2020-12-01T14:24:32Z",
        "version": 1,
        "changeset": 95099532,
        "amenity": "pharmacy",
        "name": "Farmacia Santa Luzia",
        "id": "node/8184322717"
      },
      "geometry": {
        "type": "Point",
        "coordinates": [
          -39.3903809,
          -8.0794681
        ]
      }
    }
  ]
}
