{
  "type": "FeatureCollection",
  "features": [
    {
      "type": "Feature",
      "id": "node/2919154627",
      "properties": {
        "timestamp": "2014-09-21T10:29:39Z",
        "version": 2,
        "changeset": 25576329,
        "addr:city": "Ingá",
        "addr:street": "Rua Euclides Bacalhau",
        "amenity": "kindergarten",
        "name": "CEMES",
        "id": "node/2919154627"
      },
      "geometry": {
        "type": "Point",
        "coordinates": [
          -35.6062396,
          -7.2911501
        ]
      }
    }
  ]
}
