{
  "type": "FeatureCollection",
  "features": [
    {
      "type": "Feature",
      "id": "node/3144314133",
      "properties": {
        "timestamp": "2022-03-25T11:35:17Z",
        "version": 3,
        "changeset": 118905529,
        "amenity": "pharmacy",
        "healthcare": "pharmacy",
        "id": "node/3144314133"
      },
      "geometry": {
        "type": "Point",
        "coordinates": [
          -39.5748617,
          -4.8505151
        ]
      }
    },
    {
      "type": "Feature",
      "id": "node/3145611525",
      "properties": {
        "timestamp": "2015-05-21T22:18:28Z",
        "version": 2,
        "changeset": 31357258,
        "amenity": "pharmacy",
        "id": "node/3145611525"
      },
      "geometry": {
        "type": "Point",
        "coordinates": [
          -39.57308,
          -4.8505347
        ]
      }
    },
    {
      "type": "Feature",
      "id": "node/8333848717",
      "properties": {
        "timestamp": "2021-01-18T10:51:19Z",
        "version": 1,
        "changeset": 97692248,
        "amenity": "pharmacy",
        "name": "Drigaria Acesso Facil",
        "id": "node/8333848717"
      },
      "geometry": {
        "type": "Point",
        "coordinates": [
          -39.5761054,
          -4.8546315
        ]
      }
    }
  ]
}
