{
  "type": "FeatureCollection",
  "features": [
    {
      "type": "Feature",
      "id": "node/2583095213",
      "properties": {
        "timestamp": "2013-12-17T00:17:09Z",
        "version": 1,
        "changeset": 19491257,
        "waterway": "waterfall",
        "id": "node/2583095213"
      },
      "geometry": {
        "type": "Point",
        "coordinates": [
          -46.3347263,
          -22.8558428
        ]
      }
    },
    {
      "type": "Feature",
      "id": "node/2583095242",
      "properties": {
        "timestamp": "2017-04-23T19:40:48Z",
        "version": 2,
        "changeset": 48070193,
        "name": "Cachoeira do Rio Jaguari",
        "waterway": "waterfall",
        "id": "node/2583095242"
      },
      "geometry": {
        "type": "Point",
        "coordinates": [
          -46.3343886,
          -22.8560913
        ]
      }
    },
    {
      "type": "Feature",
      "id": "node/2583095421",
      "properties": {
        "timestamp": "2013-12-17T00:17:13Z",
        "version": 1,
        "changeset": 19491257,
        "waterway": "waterfall",
        "id": "node/2583095421"
      },
      "geometry": {
        "type": "Point",
        "coordinates": [
          -46.334293,
          -22.857158
        ]
      }
    },
    {
      "type": "Feature",
      "id": "node/2608169819",
      "properties": {
        "timestamp": "2024-06-03T17:47:19Z",
        "version": 2,
        "changeset": 152210914,
        "waterway": "waterfall",
        "id": "node/2608169819"
      },
      "geometry": {
        "type": "Point",
        "coordinates": [
          -46.3757105,
          -22.8721709
        ]
      }
    },
    {
      "type": "Feature",
      "id": "node/4812128366",
      "properties": {
        "timestamp": "2021-10-28T09:21:56Z",
        "version": 3,
        "changeset": 113072974,
        "name": "Cachoeira do Salto",
        "waterway": "waterfall",
        "id": "node/4812128366"
      },
      "geometry": {
        "type": "Point",
        "coordinates": [
          -46.2661221,
          -22.8461557
        ]
      }
    }
  ]
}
