{
  "type": "FeatureCollection",
  "features": [
    {
      "type": "Feature",
      "id": "node/4306887740",
      "properties": {
        "timestamp": "2024-11-05T09:47:27Z",
        "version": 2,
        "changeset": 158771882,
        "amenity": "veterinary",
        "name": "Santo Antônio",
        "id": "node/4306887740"
      },
      "geometry": {
        "type": "Point",
        "coordinates": [
          -47.9218426,
          -22.5001206
        ]
      }
    }
  ]
}
