{
  "type": "FeatureCollection",
  "features": [
    {
      "type": "Feature",
      "id": "node/12377528697",
      "properties": {
        "timestamp": "2024-11-27T04:08:18Z",
        "version": 1,
        "changeset": 159641495,
        "addr:city": "Caroebe",
        "addr:postcode": "69378-000",
        "addr:street": "Rua Paulino Gomes Costa",
        "amenity": "hospital",
        "healthcare": "hospital",
        "name": "Hospital de Caroebe",
        "id": "node/12377528697"
      },
      "geometry": {
        "type": "Point",
        "coordinates": [
          -59.6952154,
          0.8841573
        ]
      }
    }
  ]
}
