{
  "type": "FeatureCollection",
  "features": [
    {
      "type": "Feature",
      "id": "node/6287524944",
      "properties": {
        "timestamp": "2019-02-19T03:17:43Z",
        "version": 1,
        "changeset": 67337644,
        "access": "yes",
        "historic": "monument",
        "name": "Homenagem Tenente Portela",
        "id": "node/6287524944"
      },
      "geometry": {
        "type": "Point",
        "coordinates": [
          -53.7563298,
          -27.3716707
        ]
      }
    }
  ]
}
