{
  "type": "FeatureCollection",
  "features": [
    {
      "type": "Feature",
      "id": "node/6864929157",
      "properties": {
        "timestamp": "2019-10-09T20:18:08Z",
        "version": 1,
        "changeset": 75482069,
        "amenity": "arts_centre",
        "name": "CTG Tropeiros do Buricá",
        "id": "node/6864929157"
      },
      "geometry": {
        "type": "Point",
        "coordinates": [
          -54.2199101,
          -27.7940441
        ]
      }
    }
  ]
}
