{
  "type": "FeatureCollection",
  "features": [
    {
      "type": "Feature",
      "id": "node/5951671433",
      "properties": {
        "timestamp": "2018-10-03T14:23:15Z",
        "version": 1,
        "changeset": 63162319,
        "amenity": "university",
        "internet_access": "yes",
        "name": "Faculdade SETREM - Bacharelado em Efnfermagem",
        "id": "node/5951671433"
      },
      "geometry": {
        "type": "Point",
        "coordinates": [
          -54.2397676,
          -27.7811248
        ]
      }
    },
    {
      "type": "Feature",
      "id": "node/12010551522",
      "properties": {
        "timestamp": "2024-06-25T22:56:24Z",
        "version": 1,
        "changeset": 153178275,
        "addr:city": "Três de Maio",
        "addr:housenumber": "SN",
        "addr:postcode": "98910000",
        "addr:street": "Avenida Avaí esquina com a rua Osvaldo Cruz - Bloco B",
        "addr:suburb": "Centro",
        "amenity": "university",
        "name": "Polo Universitário Federal de Três de Maio - UAB",
        "opening_hours": "De segunda a sexta-feiras das 13h30min às 17h30min e das 18h às 22h.",
        "phone": "(55)35358877",
        "id": "node/12010551522"
      },
      "geometry": {
        "type": "Point",
        "coordinates": [
          -54.2369551,
          -27.7817736
        ]
      }
    }
  ]
}
