{
  "type": "FeatureCollection",
  "features": [
    {
      "type": "Feature",
      "id": "node/5951671433",
      "properties": {
        "timestamp": "2018-10-03T14:23:15Z",
        "version": 1,
        "changeset": 63162319,
        "amenity": "university",
        "internet_access": "yes",
        "name": "Faculdade SETREM - Bacharelado em Efnfermagem",
        "id": "node/5951671433"
      },
      "geometry": {
        "type": "Point",
        "coordinates": [
          -54.2397676,
          -27.7811248
        ]
      }
    }
  ]
}
