{
  "type": "FeatureCollection",
  "features": [
    {
      "type": "Feature",
      "id": "node/4865552875",
      "properties": {
        "timestamp": "2022-03-15T15:35:05Z",
        "version": 2,
        "changeset": 118516517,
        "name": "Conselho Tutelar",
        "office": "government",
        "id": "node/4865552875"
      },
      "geometry": {
        "type": "Point",
        "coordinates": [
          -38.655354,
          -6.8149212
        ]
      }
    }
  ]
}
