{
  "type": "FeatureCollection",
  "features": [
    {
      "type": "Feature",
      "id": "node/2258428440",
      "properties": {
        "timestamp": "2013-04-08T16:59:19Z",
        "version": 1,
        "changeset": 15656835,
        "amenity": "library",
        "name": "Biblioteca Municipal",
        "id": "node/2258428440"
      },
      "geometry": {
        "type": "Point",
        "coordinates": [
          -51.9911543,
          -23.6601069
        ]
      }
    }
  ]
}
