{
  "type": "FeatureCollection",
  "features": [
    {
      "type": "Feature",
      "id": "node/7256497785",
      "properties": {
        "timestamp": "2020-03-01T22:35:02Z",
        "version": 1,
        "changeset": 81655684,
        "internet_access": "wlan",
        "name": "Pousada Portal",
        "tourism": "guest_house",
        "id": "node/7256497785"
      },
      "geometry": {
        "type": "Point",
        "coordinates": [
          -41.2954908,
          -13.8206166
        ]
      }
    }
  ]
}
