{
  "type": "FeatureCollection",
  "features": [
    {
      "type": "Feature",
      "id": "node/1895639415",
      "properties": {
        "timestamp": "2020-09-02T12:17:31Z",
        "version": 2,
        "changeset": 90303945,
        "addr:street": "Alameda Itororó",
        "artwork_type": "sculpture",
        "historic": "monument",
        "name": "Cristo Redentor",
        "tourism": "artwork",
        "id": "node/1895639415"
      },
      "geometry": {
        "type": "Point",
        "coordinates": [
          -50.6416246,
          -21.2520557
        ]
      }
    }
  ]
}
