{
  "type": "FeatureCollection",
  "features": [
    {
      "type": "Feature",
      "id": "node/2607287367",
      "properties": {
        "timestamp": "2023-12-31T20:48:29Z",
        "version": 2,
        "changeset": 145746292,
        "historic": "memorial",
        "material": "stone",
        "memorial": "sculpture",
        "name": "Padre Antonio Sepp von Rechegg",
        "id": "node/2607287367"
      },
      "geometry": {
        "type": "Point",
        "coordinates": [
          -54.399638,
          -28.4567869
        ]
      }
    }
  ]
}
