{
  "type": "FeatureCollection",
  "features": [
    {
      "type": "Feature",
      "id": "node/7047931885",
      "properties": {
        "timestamp": "2021-08-04T01:34:57Z",
        "version": 2,
        "changeset": 109118198,
        "addr:street": "R. do Amparo, Sn - Cajueiro, Santo Antônio de Jesus - BA, 44570-330",
        "amenity": "college",
        "email": "ton_amparo@hotmail.com",
        "name": "CETEP - Centro Territorial De Educação Profissional Do Recôncavo",
        "opening_hours": "Mo-Fr 07:00-22:00",
        "phone": "+55 71 3115 1401",
        "website": "http://escolas.educacao.ba.gov.br/node/13197",
        "id": "node/7047931885"
      },
      "geometry": {
        "type": "Point",
        "coordinates": [
          -39.2729012,
          -12.9694002
        ]
      }
    }
  ]
}
