{
  "type": "FeatureCollection",
  "features": [
    {
      "type": "Feature",
      "id": "node/483643558",
      "properties": {
        "timestamp": "2014-12-19T11:08:12Z",
        "version": 2,
        "changeset": 27566962,
        "amenity": "library",
        "id": "node/483643558"
      },
      "geometry": {
        "type": "Point",
        "coordinates": [
          -48.4111719,
          -24.2665813
        ]
      }
    },
    {
      "type": "Feature",
      "id": "node/4878382713",
      "properties": {
        "timestamp": "2021-08-24T14:54:02Z",
        "version": 3,
        "changeset": 110179156,
        "amenity": "library",
        "description": "Foi inaugurada em 27 de janeiro de 2005, em parceria com a Secretaria do Estado e Cultura, através do Programa São Paulo: Um Estado de Leitores. Batizada com o nome de Paulino Ferreira Assunção em 04 de novembro do 2005.",
        "name": "Biblioteca Municipal",
        "id": "node/4878382713"
      },
      "geometry": {
        "type": "Point",
        "coordinates": [
          -48.3644445,
          -24.0991112
        ]
      }
    }
  ]
}
