{
  "type": "FeatureCollection",
  "features": [
    {
      "type": "Feature",
      "id": "node/7300290695",
      "properties": {
        "timestamp": "2020-03-16T21:05:10Z",
        "version": 1,
        "changeset": 82274280,
        "amenity": "clinic",
        "healthcare": "clinic",
        "name": "Clínica do Trabalhador",
        "id": "node/7300290695"
      },
      "geometry": {
        "type": "Point",
        "coordinates": [
          -42.7323818,
          -10.8222718
        ]
      }
    }
  ]
}
