{
  "type": "FeatureCollection",
  "features": [
    {
      "type": "Feature",
      "id": "node/2460553290",
      "properties": {
        "timestamp": "2021-03-16T15:24:11Z",
        "version": 2,
        "changeset": 101130174,
        "amenity": "hospital",
        "emergency": "yes",
        "healthcare": "hospital",
        "name": "Hospital Municipal",
        "id": "node/2460553290"
      },
      "geometry": {
        "type": "Point",
        "coordinates": [
          -54.3642769,
          -27.5071624
        ]
      }
    }
  ]
}
