{
  "type": "FeatureCollection",
  "features": [
    {
      "type": "Feature",
      "id": "node/3837674151",
      "properties": {
        "timestamp": "2020-02-27T17:32:41Z",
        "version": 3,
        "changeset": 81558164,
        "historic": "monument",
        "name": "Estátua Nossa Senhora de Fátima",
        "id": "node/3837674151"
      },
      "geometry": {
        "type": "Point",
        "coordinates": [
          -38.9878815,
          -4.2352637
        ]
      }
    }
  ]
}
