{
  "type": "FeatureCollection",
  "features": [
    {
      "type": "Feature",
      "id": "node/6746734545",
      "properties": {
        "timestamp": "2019-08-26T16:18:24Z",
        "version": 1,
        "changeset": 73761708,
        "name": "Cachoeira São Paulo",
        "waterway": "waterfall",
        "id": "node/6746734545"
      },
      "geometry": {
        "type": "Point",
        "coordinates": [
          -38.9034628,
          -4.2589105
        ]
      }
    },
    {
      "type": "Feature",
      "id": "node/6746735641",
      "properties": {
        "timestamp": "2019-08-26T16:18:24Z",
        "version": 1,
        "changeset": 73761708,
        "name": "Poço da Veada",
        "waterway": "waterfall",
        "id": "node/6746735641"
      },
      "geometry": {
        "type": "Point",
        "coordinates": [
          -38.9249918,
          -4.2475967
        ]
      }
    }
  ]
}
