{
  "type": "FeatureCollection",
  "features": [
    {
      "type": "Feature",
      "id": "node/4392343889",
      "properties": {
        "timestamp": "2016-09-08T16:53:04Z",
        "version": 1,
        "changeset": 42008048,
        "addr:housenumber": "84",
        "addr:street": "Rua Waldemar Alves Ferreira",
        "internet_access": "wlan",
        "name": "Minha casa",
        "name:pt": "Minha casa",
        "tourism": "guest_house",
        "id": "node/4392343889"
      },
      "geometry": {
        "type": "Point",
        "coordinates": [
          -49.2499613,
          -18.4158555
        ]
      }
    }
  ]
}
