{
  "type": "FeatureCollection",
  "features": [
    {
      "type": "Feature",
      "id": "node/5304005509",
      "properties": {
        "timestamp": "2017-12-26T02:38:17Z",
        "version": 1,
        "changeset": 54919392,
        "historic": "memorial",
        "memorial": "statue",
        "name": "Marechal Cunha Matos",
        "id": "node/5304005509"
      },
      "geometry": {
        "type": "Point",
        "coordinates": [
          -49.2139689,
          -18.4190645
        ]
      }
    }
  ]
}
