{
  "type": "FeatureCollection",
  "features": [
    {
      "type": "Feature",
      "id": "node/8381762497",
      "properties": {
        "timestamp": "2023-10-28T09:23:46Z",
        "version": 2,
        "changeset": 143250400,
        "amenity": "university",
        "name": "Universidade Aberta do Brasil",
        "website": "https://www.capes.gov.br/uab",
        "id": "node/8381762497"
      },
      "geometry": {
        "type": "Point",
        "coordinates": [
          -51.7273573,
          -30.0923984
        ]
      }
    }
  ]
}
