{
  "type": "FeatureCollection",
  "features": [
    {
      "type": "Feature",
      "id": "node/3404086764",
      "properties": {
        "timestamp": "2015-03-17T15:30:58Z",
        "version": 1,
        "changeset": 29543776,
        "addr:city": "Nova Palma",
        "addr:postcode": "97250-000",
        "addr:street": "Rua Raimundo Aléssio",
        "amenity": "doctors",
        "name": "Flávio Sumerval Benetti",
        "id": "node/3404086764"
      },
      "geometry": {
        "type": "Point",
        "coordinates": [
          -53.472391,
          -29.4715306
        ]
      }
    }
  ]
}
