{
  "type": "FeatureCollection",
  "features": [
    {
      "type": "Feature",
      "id": "node/3350146219",
      "properties": {
        "timestamp": "2021-01-18T17:27:11Z",
        "version": 3,
        "changeset": 97712669,
        "source": "survey",
        "tourism": "hotel",
        "id": "node/3350146219"
      },
      "geometry": {
        "type": "Point",
        "coordinates": [
          -43.4711321,
          -18.073794
        ]
      }
    },
    {
      "type": "Feature",
      "id": "node/11008690563",
      "properties": {
        "timestamp": "2023-11-14T17:18:03Z",
        "version": 2,
        "changeset": 144019372,
        "addr:city": "Couto de Magalhães de Minas",
        "addr:postcode": "39188-000",
        "addr:street": "RPPN Raiz, S/N",
        "addr:suburb": "Povoado do Alecrim",
        "email": "informacoes@pousadaraizparque.com",
        "internet_access": "yes",
        "internet_access:fee": "no",
        "name": "Pousada Raiz Parque",
        "phone": "+55 (31) 98470-3785",
        "rooms": "14",
        "tourism": "hotel",
        "website": "https://www.pousadaraizparque.com/",
        "id": "node/11008690563"
      },
      "geometry": {
        "type": "Point",
        "coordinates": [
          -43.3725092,
          -18.0938183
        ]
      }
    }
  ]
}
