{
  "type": "FeatureCollection",
  "features": [
    {
      "type": "Feature",
      "id": "node/4233849719",
      "properties": {
        "timestamp": "2023-10-20T10:42:10Z",
        "version": 2,
        "changeset": 142863887,
        "amenity": "clinic",
        "name": "Posto de Saúde de Carlos Gomes",
        "operator": "Prefeitura Municipal de Carlos Gomes",
        "operator:type": "public",
        "id": "node/4233849719"
      },
      "geometry": {
        "type": "Point",
        "coordinates": [
          -51.9154559,
          -27.7164057
        ]
      }
    }
  ]
}
