{
  "type": "FeatureCollection",
  "features": [
    {
      "type": "Feature",
      "id": "node/2034662779",
      "properties": {
        "timestamp": "2012-11-26T13:31:15Z",
        "version": 1,
        "changeset": 14044825,
        "building": "yes",
        "name": "EBDA - Empresa Baiana de Desenvolvimento Agrícola",
        "office": "government",
        "id": "node/2034662779"
      },
      "geometry": {
        "type": "Point",
        "coordinates": [
          -39.107128,
          -12.6684717
        ]
      }
    },
    {
      "type": "Feature",
      "id": "node/2939248884",
      "properties": {
        "timestamp": "2014-06-30T12:55:37Z",
        "version": 2,
        "changeset": 23346772,
        "name": "31ª DIRES",
        "office": "government",
        "id": "node/2939248884"
      },
      "geometry": {
        "type": "Point",
        "coordinates": [
          -39.1052878,
          -12.669419
        ]
      }
    }
  ]
}
