{
  "type": "FeatureCollection",
  "features": [
    {
      "type": "Feature",
      "id": "node/8018815793",
      "properties": {
        "timestamp": "2020-10-18T16:16:20Z",
        "version": 1,
        "changeset": 92662074,
        "name": "Pra Você",
        "tourism": "hotel",
        "id": "node/8018815793"
      },
      "geometry": {
        "type": "Point",
        "coordinates": [
          -48.2865922,
          -15.734646
        ]
      }
    }
  ]
}
