{
  "type": "FeatureCollection",
  "features": [
    {
      "type": "Feature",
      "id": "node/8636271439",
      "properties": {
        "timestamp": "2022-08-28T19:20:22Z",
        "version": 2,
        "changeset": 125491841,
        "amenity": "library",
        "fixme": "verificar localização",
        "name": "Biblioteca Pública Municipal de Erval Velho",
        "id": "node/8636271439"
      },
      "geometry": {
        "type": "Point",
        "coordinates": [
          -51.4421685,
          -27.2779759
        ]
      }
    }
  ]
}
