{
  "type": "FeatureCollection",
  "features": [
    {
      "type": "Feature",
      "id": "node/12533313851",
      "properties": {
        "timestamp": "2025-01-26T03:05:11Z",
        "version": 1,
        "changeset": 161767461,
        "addr:city": "São Lourenço",
        "addr:housenumber": "292",
        "addr:postcode": "37470-000",
        "addr:street": "Avenida Dom Pedro II",
        "addr:suburb": "Centro",
        "addr:unit": "701",
        "amenity": "clinic",
        "check_date": "2025-01-26",
        "contact:email": "contato@clinicalefosse.com.br",
        "contact:facebook": "https://www.facebook.com/clinicalefossefisio",
        "contact:instagram": "https://www.instagram.com/clinicalefosse",
        "currency:XBT": "yes",
        "description": "Clínica de Fisioterapia Bianca Lefosse especialista em Traumato-ortopedia, mestre em Ciências da Reabilitação, MBA em Inteligência artificial para negócios. Pioneirismo e modernidade em nível internacional Prática Baseada em Evidência Científica.",
        "healthcare": "clinic",
        "healthcare:speciality": "physiatry",
        "name": "Clínica Lefosse",
        "opening_hours": "Mo-Fr 08:00-20:00",
        "payment:lightning": "yes",
        "payment:lightning_contactless": "no",
        "payment:onchain": "no",
        "phone": "+55 35 98407 5387",
        "website": "https://www.clinicalefosse.com.br/",
        "id": "node/12533313851"
      },
      "geometry": {
        "type": "Point",
        "coordinates": [
          -45.0538366,
          -22.1155312
        ]
      }
    }
  ]
}
