{
  "type": "FeatureCollection",
  "features": [
    {
      "type": "Feature",
      "id": "node/4715731772",
      "properties": {
        "timestamp": "2017-03-03T21:33:54Z",
        "version": 1,
        "changeset": 46559616,
        "addr:street": "Rua José Ramalho",
        "amenity": "clinic",
        "id": "node/4715731772"
      },
      "geometry": {
        "type": "Point",
        "coordinates": [
          -53.8195216,
          -22.3019188
        ]
      }
    }
  ]
}
