{
  "type": "FeatureCollection",
  "features": [
    {
      "type": "Feature",
      "id": "node/4556931085",
      "properties": {
        "timestamp": "2017-01-08T20:48:14Z",
        "version": 2,
        "changeset": 45011578,
        "addr:city": "Ivinhema",
        "addr:country": "BR",
        "addr:state": "Mato Grosso do Sul",
        "addr:street": "Rua Antônio Baltazar Dias",
        "tourism": "hotel",
        "id": "node/4556931085"
      },
      "geometry": {
        "type": "Point",
        "coordinates": [
          -53.8197456,
          -22.3162467
        ]
      }
    }
  ]
}
