{
  "type": "FeatureCollection",
  "features": [
    {
      "type": "Feature",
      "id": "node/2303826902",
      "properties": {
        "timestamp": "2013-05-14T14:18:51Z",
        "version": 1,
        "changeset": 16126193,
        "amenity": "kindergarten",
        "name": "Creche Maria Egione",
        "id": "node/2303826902"
      },
      "geometry": {
        "type": "Point",
        "coordinates": [
          -37.5266362,
          -6.90451
        ]
      }
    },
    {
      "type": "Feature",
      "id": "node/2303826909",
      "properties": {
        "timestamp": "2013-05-14T14:18:51Z",
        "version": 1,
        "changeset": 16126193,
        "amenity": "kindergarten",
        "name": "Creche Salvelina Cavalcanti",
        "id": "node/2303826909"
      },
      "geometry": {
        "type": "Point",
        "coordinates": [
          -37.5292969,
          -6.9057508
        ]
      }
    },
    {
      "type": "Feature",
      "id": "node/2898422009",
      "properties": {
        "timestamp": "2015-12-09T00:05:37Z",
        "version": 3,
        "changeset": 35837211,
        "addr:city": "Malta",
        "addr:postcode": "58713000",
        "addr:street": "Rua Justino Fernandes",
        "amenity": "kindergarten",
        "name": "Maternal Mini Doutor",
        "wheelchair": "yes",
        "id": "node/2898422009"
      },
      "geometry": {
        "type": "Point",
        "coordinates": [
          -37.5219807,
          -6.9076335
        ]
      }
    }
  ]
}
