{
  "type": "FeatureCollection",
  "features": [
    {
      "type": "Feature",
      "id": "node/5598754532",
      "properties": {
        "timestamp": "2018-07-05T15:35:36Z",
        "version": 2,
        "changeset": 60440536,
        "name": "Hotel Katedral",
        "tourism": "hotel",
        "id": "node/5598754532"
      },
      "geometry": {
        "type": "Point",
        "coordinates": [
          -51.7456657,
          -28.6617363
        ]
      }
    },
    {
      "type": "Feature",
      "id": "node/5741668515",
      "properties": {
        "timestamp": "2018-07-05T15:35:36Z",
        "version": 1,
        "changeset": 60440536,
        "name": "Alvi Hotel",
        "tourism": "hotel",
        "id": "node/5741668515"
      },
      "geometry": {
        "type": "Point",
        "coordinates": [
          -51.7478877,
          -28.6602672
        ]
      }
    }
  ]
}
