{
  "type": "FeatureCollection",
  "features": [
    {
      "type": "Feature",
      "id": "node/8636271428",
      "properties": {
        "timestamp": "2022-09-04T16:25:50Z",
        "version": 2,
        "changeset": 125779562,
        "amenity": "library",
        "fixme": "verificar localização",
        "name": "Biblioteca Pública Municipal Professora Benavenute Flores de Souza",
        "id": "node/8636271428"
      },
      "geometry": {
        "type": "Point",
        "coordinates": [
          -48.6455338,
          -26.7715059
        ]
      }
    }
  ]
}
