{
  "type": "FeatureCollection",
  "features": [
    {
      "type": "Feature",
      "id": "node/2600698850",
      "properties": {
        "timestamp": "2021-03-31T18:41:43Z",
        "version": 2,
        "changeset": 102073939,
        "amenity": "pharmacy",
        "healthcare": "pharmacy",
        "id": "node/2600698850"
      },
      "geometry": {
        "type": "Point",
        "coordinates": [
          -48.6065279,
          -26.7911874
        ]
      }
    },
    {
      "type": "Feature",
      "id": "node/4158643758",
      "properties": {
        "timestamp": "2021-01-03T21:13:12Z",
        "version": 2,
        "changeset": 96864747,
        "amenity": "pharmacy",
        "healthcare": "pharmacy",
        "id": "node/4158643758"
      },
      "geometry": {
        "type": "Point",
        "coordinates": [
          -48.6155595,
          -26.8020999
        ]
      }
    },
    {
      "type": "Feature",
      "id": "node/5874120597",
      "properties": {
        "timestamp": "2022-09-04T16:25:50Z",
        "version": 3,
        "changeset": 125779562,
        "amenity": "pharmacy",
        "healthcare": "pharmacy",
        "name": "Farma Faita",
        "id": "node/5874120597"
      },
      "geometry": {
        "type": "Point",
        "coordinates": [
          -48.638932,
          -26.7790337
        ]
      }
    },
    {
      "type": "Feature",
      "id": "node/10716187376",
      "properties": {
        "timestamp": "2023-03-06T12:22:27Z",
        "version": 1,
        "changeset": 133360974,
        "amenity": "pharmacy",
        "healthcare": "pharmacy",
        "name": "Stylofarma",
        "id": "node/10716187376"
      },
      "geometry": {
        "type": "Point",
        "coordinates": [
          -48.6058296,
          -26.7923746
        ]
      }
    },
    {
      "type": "Feature",
      "id": "node/10728009294",
      "properties": {
        "timestamp": "2023-03-11T18:27:15Z",
        "version": 1,
        "changeset": 133563660,
        "amenity": "pharmacy",
        "healthcare": "pharmacy",
        "name": "Farma Faita",
        "id": "node/10728009294"
      },
      "geometry": {
        "type": "Point",
        "coordinates": [
          -48.6264952,
          -26.7913901
        ]
      }
    }
  ]
}
