{
  "type": "FeatureCollection",
  "features": [
    {
      "type": "Feature",
      "id": "node/3739819963",
      "properties": {
        "timestamp": "2024-03-26T14:57:17Z",
        "version": 4,
        "changeset": 149181995,
        "name": "Cachoeira da Praia Vermelha",
        "tourism": "attraction",
        "waterway": "waterfall",
        "id": "node/3739819963"
      },
      "geometry": {
        "type": "Point",
        "coordinates": [
          -48.6015326,
          -26.8123028
        ]
      }
    }
  ]
}
