{
  "type": "FeatureCollection",
  "features": [
    {
      "type": "Feature",
      "id": "node/3739819963",
      "properties": {
        "timestamp": "2023-01-18T16:48:31Z",
        "version": 3,
        "changeset": 131430902,
        "name": "Cachoeira da Praia Vermelha",
        "waterway": "waterfall",
        "id": "node/3739819963"
      },
      "geometry": {
        "type": "Point",
        "coordinates": [
          -48.6015326,
          -26.8123028
        ]
      }
    }
  ]
}
