{
  "type": "FeatureCollection",
  "features": [
    {
      "type": "Feature",
      "id": "node/3837243943",
      "properties": {
        "timestamp": "2020-10-30T23:41:24Z",
        "version": 2,
        "changeset": 93314656,
        "amenity": "hospital",
        "name": "Centro de Saúde",
        "id": "node/3837243943"
      },
      "geometry": {
        "type": "Point",
        "coordinates": [
          -42.522841,
          -13.3822246
        ]
      }
    }
  ]
}
