{
  "type": "FeatureCollection",
  "features": [
    {
      "type": "Feature",
      "id": "node/5955352816",
      "properties": {
        "timestamp": "2018-10-04T19:44:17Z",
        "version": 1,
        "changeset": 63207975,
        "historic": "memorial",
        "name": "Entrada do Parque de Exposições Da Festa do Produtor",
        "id": "node/5955352816"
      },
      "geometry": {
        "type": "Point",
        "coordinates": [
          -46.4065156,
          -18.7720149
        ]
      }
    }
  ]
}
