{
  "type": "FeatureCollection",
  "features": [
    {
      "type": "Feature",
      "id": "node/10723995405",
      "properties": {
        "timestamp": "2023-03-09T17:23:35Z",
        "version": 1,
        "changeset": 133487839,
        "amenity": "doctors",
        "name": "UBS I",
        "id": "node/10723995405"
      },
      "geometry": {
        "type": "Point",
        "coordinates": [
          -37.1562475,
          -7.128666
        ]
      }
    }
  ]
}
