{
  "type": "FeatureCollection",
  "features": [
    {
      "type": "Feature",
      "id": "node/12535166785",
      "properties": {
        "timestamp": "2025-01-26T23:25:53Z",
        "version": 1,
        "changeset": 161798769,
        "waterway": "waterfall",
        "id": "node/12535166785"
      },
      "geometry": {
        "type": "Point",
        "coordinates": [
          -46.99597,
          -23.4360834
        ]
      }
    },
    {
      "type": "Feature",
      "id": "node/12535166786",
      "properties": {
        "timestamp": "2025-01-26T23:25:53Z",
        "version": 1,
        "changeset": 161798769,
        "attraction": "yes",
        "name": "Cachoeira do Suru",
        "waterway": "waterfall",
        "id": "node/12535166786"
      },
      "geometry": {
        "type": "Point",
        "coordinates": [
          -46.9957584,
          -23.4367033
        ]
      }
    }
  ]
}
