{
  "type": "FeatureCollection",
  "features": [
    {
      "type": "Feature",
      "id": "node/5260559039",
      "properties": {
        "timestamp": "2017-12-02T18:39:40Z",
        "version": 1,
        "changeset": 54278273,
        "historic": "monument",
        "name": "Concha Acústica",
        "id": "node/5260559039"
      },
      "geometry": {
        "type": "Point",
        "coordinates": [
          -49.2380114,
          -22.8806726
        ]
      }
    }
  ]
}
