{
  "type": "FeatureCollection",
  "features": [
    {
      "type": "Feature",
      "id": "node/2507527308",
      "properties": {
        "timestamp": "2018-12-21T20:19:50Z",
        "version": 2,
        "changeset": 65679104,
        "name": "Cascata do Rio Turvo",
        "waterway": "waterfall",
        "id": "node/2507527308"
      },
      "geometry": {
        "type": "Point",
        "coordinates": [
          -53.6967739,
          -27.8681009
        ]
      }
    }
  ]
}
