{
  "type": "FeatureCollection",
  "features": [
    {
      "type": "Feature",
      "id": "node/8626390674",
      "properties": {
        "timestamp": "2021-04-13T16:04:00Z",
        "version": 1,
        "changeset": 102875428,
        "amenity": "clinic",
        "id": "node/8626390674"
      },
      "geometry": {
        "type": "Point",
        "coordinates": [
          -49.8217298,
          -27.7378098
        ]
      }
    },
    {
      "type": "Feature",
      "id": "node/8626390675",
      "properties": {
        "timestamp": "2025-03-12T20:45:30Z",
        "version": 2,
        "changeset": 163544815,
        "amenity": "clinic",
        "healthcare": "clinic",
        "name": "UBS Doraldina Setembrina de Liz",
        "id": "node/8626390675"
      },
      "geometry": {
        "type": "Point",
        "coordinates": [
          -49.8800593,
          -27.7851356
        ]
      }
    },
    {
      "type": "Feature",
      "id": "node/8626390677",
      "properties": {
        "timestamp": "2021-06-17T23:01:16Z",
        "version": 2,
        "changeset": 106555006,
        "amenity": "clinic",
        "healthcare": "clinic",
        "id": "node/8626390677"
      },
      "geometry": {
        "type": "Point",
        "coordinates": [
          -50.0332108,
          -27.7874442
        ]
      }
    },
    {
      "type": "Feature",
      "id": "node/8626390678",
      "properties": {
        "timestamp": "2021-04-13T16:04:00Z",
        "version": 1,
        "changeset": 102875428,
        "amenity": "clinic",
        "id": "node/8626390678"
      },
      "geometry": {
        "type": "Point",
        "coordinates": [
          -50.0142037,
          -27.724706
        ]
      }
    },
    {
      "type": "Feature",
      "id": "node/8626390679",
      "properties": {
        "timestamp": "2021-04-13T16:04:00Z",
        "version": 1,
        "changeset": 102875428,
        "amenity": "clinic",
        "id": "node/8626390679"
      },
      "geometry": {
        "type": "Point",
        "coordinates": [
          -49.8981484,
          -27.7409715
        ]
      }
    }
  ]
}
