{
  "type": "FeatureCollection",
  "features": [
    {
      "type": "Feature",
      "id": "node/9607748685",
      "properties": {
        "timestamp": "2024-12-27T16:53:40Z",
        "version": 3,
        "changeset": 160684713,
        "name": "Raudal Golondrinas",
        "waterway": "waterfall",
        "id": "node/9607748685"
      },
      "geometry": {
        "type": "Point",
        "coordinates": [
          -69.5594061,
          -0.8193012
        ]
      }
    }
  ]
}
