{
  "type": "FeatureCollection",
  "features": [
    {
      "type": "Feature",
      "id": "node/6384597340",
      "properties": {
        "timestamp": "2019-04-29T01:28:26Z",
        "version": 3,
        "changeset": 69677975,
        "access": "yes",
        "historic": "monument",
        "name": "Homenagem aos Pioneiros",
        "id": "node/6384597340"
      },
      "geometry": {
        "type": "Point",
        "coordinates": [
          -49.7976474,
          -27.1931916
        ]
      }
    }
  ]
}
