{
  "type": "FeatureCollection",
  "features": [
    {
      "type": "Feature",
      "id": "node/6455908986",
      "properties": {
        "timestamp": "2019-05-07T16:57:04Z",
        "version": 1,
        "changeset": 69989726,
        "addr:housenumber": "2300",
        "addr:postcode": "76803660",
        "addr:street": "Avenida Lauro Sodré",
        "amenity": "community_centre",
        "name": "Condomínio Reserva do Bosque",
        "opening_hours": "24/7",
        "id": "node/6455908986"
      },
      "geometry": {
        "type": "Point",
        "coordinates": [
          -63.9024553,
          -8.7444004
        ]
      }
    }
  ]
}
