{
  "type": "FeatureCollection",
  "features": [
    {
      "type": "Feature",
      "id": "node/5329778311",
      "properties": {
        "timestamp": "2020-04-19T14:06:41Z",
        "version": 2,
        "changeset": 83774168,
        "amenity": "pharmacy",
        "healthcare": "pharmacy",
        "name": "Drogaria Cavalcante",
        "id": "node/5329778311"
      },
      "geometry": {
        "type": "Point",
        "coordinates": [
          -38.6080919,
          -12.9625559
        ]
      }
    }
  ]
}
