{
  "type": "FeatureCollection",
  "features": [
    {
      "type": "Feature",
      "id": "node/5534834139",
      "properties": {
        "timestamp": "2021-02-20T21:15:55Z",
        "version": 2,
        "changeset": 99660429,
        "amenity": "pharmacy",
        "healthcare": "pharmacy",
        "name": "Nossa Senhora da Guia",
        "id": "node/5534834139"
      },
      "geometry": {
        "type": "Point",
        "coordinates": [
          -37.9883093,
          -7.3864512
        ]
      }
    }
  ]
}
