{
  "type": "FeatureCollection",
  "features": [
    {
      "type": "Feature",
      "id": "node/5431198680",
      "properties": {
        "timestamp": "2018-02-23T12:03:39Z",
        "version": 1,
        "changeset": 56607814,
        "amenity": "dentist",
        "healthcare": "dentist",
        "name": "Centro Odontológico",
        "operator": "Dr. Marcelo Santiago Ferreira",
        "id": "node/5431198680"
      },
      "geometry": {
        "type": "Point",
        "coordinates": [
          -51.9808086,
          -23.9181071
        ]
      }
    }
  ]
}
