{
  "type": "FeatureCollection",
  "features": [
    {
      "type": "Feature",
      "id": "node/4360761809",
      "properties": {
        "timestamp": "2016-08-21T23:14:44Z",
        "version": 1,
        "changeset": 41603436,
        "tourism": "guest_house",
        "id": "node/4360761809"
      },
      "geometry": {
        "type": "Point",
        "coordinates": [
          -40.1377297,
          -19.9373435
        ]
      }
    },
    {
      "type": "Feature",
      "id": "node/6291983892",
      "properties": {
        "timestamp": "2019-02-20T20:59:21Z",
        "version": 1,
        "changeset": 67407571,
        "tourism": "guest_house",
        "id": "node/6291983892"
      },
      "geometry": {
        "type": "Point",
        "coordinates": [
          -40.271016,
          -19.8262303
        ]
      }
    },
    {
      "type": "Feature",
      "id": "node/11340443369",
      "properties": {
        "timestamp": "2023-11-11T10:41:32Z",
        "version": 2,
        "changeset": 143893969,
        "addr:street": "Rua Padre José de Anchieta",
        "internet_access": "wlan",
        "name": "Pousada Costa do Sol",
        "tourism": "guest_house",
        "id": "node/11340443369"
      },
      "geometry": {
        "type": "Point",
        "coordinates": [
          -40.124382,
          -19.9306688
        ]
      }
    }
  ]
}
