{
  "type": "FeatureCollection",
  "features": [
    {
      "type": "Feature",
      "id": "node/7784326939",
      "properties": {
        "timestamp": "2020-08-04T13:51:25Z",
        "version": 1,
        "changeset": 88933000,
        "amenity": "school",
        "name": "EMEFNNM Pe. José de Anchieta",
        "id": "node/7784326939"
      },
      "geometry": {
        "type": "Point",
        "coordinates": [
          -38.6412452,
          -6.7170583
        ]
      }
    },
    {
      "type": "Feature",
      "id": "node/7784326940",
      "properties": {
        "timestamp": "2020-08-04T13:51:25Z",
        "version": 1,
        "changeset": 88933000,
        "amenity": "school",
        "id": "node/7784326940"
      },
      "geometry": {
        "type": "Point",
        "coordinates": [
          -38.6390297,
          -6.7178201
        ]
      }
    },
    {
      "type": "Feature",
      "id": "node/7784326941",
      "properties": {
        "timestamp": "2020-08-04T13:51:25Z",
        "version": 1,
        "changeset": 88933000,
        "amenity": "school",
        "name": "EEEFM Elaine Soares Brasileiro",
        "id": "node/7784326941"
      },
      "geometry": {
        "type": "Point",
        "coordinates": [
          -38.6411111,
          -6.7175804
        ]
      }
    }
  ]
}
