{
  "type": "FeatureCollection",
  "features": [
    {
      "type": "Feature",
      "id": "node/12451505134",
      "properties": {
        "timestamp": "2024-12-25T18:15:30Z",
        "version": 1,
        "changeset": 160613061,
        "name": "Cachoeira Jaturana",
        "waterway": "waterfall",
        "id": "node/12451505134"
      },
      "geometry": {
        "type": "Point",
        "coordinates": [
          -63.1932864,
          -10.5995484
        ]
      }
    }
  ]
}
