{
  "type": "FeatureCollection",
  "features": [
    {
      "type": "Feature",
      "id": "node/3725660330",
      "properties": {
        "timestamp": "2015-09-02T09:06:29Z",
        "version": 2,
        "changeset": 33746344,
        "addr:city": "Pato Branco",
        "amenity": "veterinary",
        "name": "Consultório Veterinário",
        "id": "node/3725660330"
      },
      "geometry": {
        "type": "Point",
        "coordinates": [
          -52.6716478,
          -26.2285009
        ]
      }
    }
  ]
}
