{
  "type": "FeatureCollection",
  "features": [
    {
      "type": "Feature",
      "id": "node/3504036358",
      "properties": {
        "timestamp": "2023-02-10T12:10:09Z",
        "version": 2,
        "changeset": 132355711,
        "historic": "memorial",
        "inscription": "Naciente del Río San Antonio",
        "marker": "yes",
        "material": "stone",
        "memorial": "obelisk",
        "name": "Marco de Frontera Argentina-Brasil",
        "id": "node/3504036358"
      },
      "geometry": {
        "type": "Point",
        "coordinates": [
          -53.7407575,
          -26.116903
        ]
      }
    }
  ]
}
