{
  "type": "FeatureCollection",
  "features": [
    {
      "type": "Feature",
      "id": "node/6574726585",
      "properties": {
        "timestamp": "2019-06-27T12:51:33Z",
        "version": 1,
        "changeset": 71671793,
        "amenity": "drinking_water",
        "name": "Torneira com filtro",
        "id": "node/6574726585"
      },
      "geometry": {
        "type": "Point",
        "coordinates": [
          -47.4513639,
          -13.8179888
        ]
      }
    },
    {
      "type": "Feature",
      "id": "node/10834262105",
      "properties": {
        "timestamp": "2023-04-23T17:33:07Z",
        "version": 1,
        "changeset": 135271360,
        "amenity": "drinking_water",
        "name": "Nascente",
        "id": "node/10834262105"
      },
      "geometry": {
        "type": "Point",
        "coordinates": [
          -47.450076,
          -13.8537391
        ]
      }
    }
  ]
}
