{
  "type": "FeatureCollection",
  "features": [
    {
      "type": "Feature",
      "id": "node/6770488092",
      "properties": {
        "timestamp": "2019-09-03T20:27:47Z",
        "version": 1,
        "changeset": 74057383,
        "amenity": "clinic",
        "healthcare": "clinic",
        "name": "Clinica do rim",
        "id": "node/6770488092"
      },
      "geometry": {
        "type": "Point",
        "coordinates": [
          -51.3531993,
          -23.3006789
        ]
      }
    }
  ]
}
