{
  "type": "FeatureCollection",
  "features": [
    {
      "type": "Feature",
      "id": "node/2934092668",
      "properties": {
        "timestamp": "2024-07-02T12:54:55Z",
        "version": 6,
        "changeset": 153455837,
        "historic": "memorial",
        "memorial": "statue",
        "name": "Estátua de Roland",
        "name:de": "Bremer Roland",
        "name:en": "Bremen Roland",
        "tourism": "attraction",
        "wheelchair": "yes",
        "wikidata": "Q10277571",
        "id": "node/2934092668"
      },
      "geometry": {
        "type": "Point",
        "coordinates": [
          -51.3697166,
          -23.3102645
        ]
      }
    }
  ]
}
