{
  "type": "FeatureCollection",
  "features": [
    {
      "type": "Feature",
      "id": "node/10945206069",
      "properties": {
        "timestamp": "2023-06-02T18:21:35Z",
        "version": 2,
        "changeset": 136879386,
        "addr:city": "Boa Vista do Buricá",
        "addr:country": "BR",
        "addr:housenumber": "895",
        "addr:state": "Rio Grande do Sul",
        "addr:street": "Avenida São José",
        "addr:suburb": "Centro",
        "amenity": "clinic",
        "contact:phone": "+55 55 3538-1270",
        "postal_code": "98918-000",
        "ref:CNES": "2249820",
        "id": "node/10945206069"
      },
      "geometry": {
        "type": "Point",
        "coordinates": [
          -54.1102597,
          -27.6700446
        ]
      }
    }
  ]
}
