{
  "type": "FeatureCollection",
  "features": [
    {
      "type": "Feature",
      "id": "node/2673618281",
      "properties": {
        "timestamp": "2018-06-19T22:42:10Z",
        "version": 2,
        "changeset": 59992644,
        "building": "civic",
        "government": "legislative",
        "name": "Câmara Municipal de Aracagi",
        "office": "government",
        "id": "node/2673618281"
      },
      "geometry": {
        "type": "Point",
        "coordinates": [
          -35.3868294,
          -6.8509059
        ]
      }
    },
    {
      "type": "Feature",
      "id": "node/2673618350",
      "properties": {
        "timestamp": "2014-02-15T21:56:15Z",
        "version": 1,
        "changeset": 20585765,
        "building": "civic",
        "name": "Mercado de Cima",
        "office": "government",
        "id": "node/2673618350"
      },
      "geometry": {
        "type": "Point",
        "coordinates": [
          -35.3296394,
          -6.9288869
        ]
      }
    }
  ]
}
