{
  "type": "FeatureCollection",
  "features": [
    {
      "type": "Feature",
      "id": "node/920881855",
      "properties": {
        "timestamp": "2017-08-26T00:13:47Z",
        "version": 2,
        "changeset": 51447651,
        "amenity": "hospital",
        "healthcare": "hospital",
        "name": "Hospital Doutor Paulo Fortes",
        "id": "node/920881855"
      },
      "geometry": {
        "type": "Point",
        "coordinates": [
          -50.3815916,
          -25.8754701
        ]
      }
    },
    {
      "type": "Feature",
      "id": "node/10824805836",
      "properties": {
        "timestamp": "2023-04-19T17:18:33Z",
        "version": 1,
        "changeset": 135113265,
        "amenity": "hospital",
        "emergency": "yes",
        "healthcare": "hospital",
        "name": "Unidade de Pronto Socorro",
        "id": "node/10824805836"
      },
      "geometry": {
        "type": "Point",
        "coordinates": [
          -50.3818932,
          -25.8755487
        ]
      }
    }
  ]
}
