{
  "type": "FeatureCollection",
  "features": [
    {
      "type": "Feature",
      "id": "node/2670811537",
      "properties": {
        "timestamp": "2014-02-13T22:55:32Z",
        "version": 1,
        "changeset": 20550158,
        "addr:city": "São Mateus do Sul",
        "addr:country": "BR",
        "addr:state": "PARANÁ",
        "addr:street": "Rua Ulisses Faria",
        "amenity": "pharmacy",
        "name": "Rodocentro",
        "id": "node/2670811537"
      },
      "geometry": {
        "type": "Point",
        "coordinates": [
          -50.389287,
          -25.86825
        ]
      }
    }
  ]
}
