{
  "type": "FeatureCollection",
  "features": [
    {
      "type": "Feature",
      "id": "node/4382390446",
      "properties": {
        "timestamp": "2016-09-03T16:34:42Z",
        "version": 1,
        "changeset": 41892166,
        "amenity": "hospital",
        "name": "Hospital Municipal De Farias Brito",
        "id": "node/4382390446"
      },
      "geometry": {
        "type": "Point",
        "coordinates": [
          -39.5689167,
          -6.9306319
        ]
      }
    }
  ]
}
