{
  "type": "FeatureCollection",
  "features": [
    {
      "type": "Feature",
      "id": "node/12586242160",
      "properties": {
        "timestamp": "2025-02-14T14:26:19Z",
        "version": 2,
        "changeset": 162505487,
        "amenity": "dentist",
        "gpxicon": "https://www.gstatic.com/mapspro/images/stock/503-wht-blank_maps.png",
        "healthcare": "dentist",
        "name": "Consultório Odontológico Dra Raimunda",
        "id": "node/12586242160"
      },
      "geometry": {
        "type": "Point",
        "coordinates": [
          -42.1322647,
          -7.0133927
        ]
      }
    }
  ]
}
