{
  "type": "FeatureCollection",
  "features": [
    {
      "type": "Feature",
      "id": "node/3430967888",
      "properties": {
        "timestamp": "2015-04-01T23:57:29Z",
        "version": 1,
        "changeset": 29918028,
        "amenity": "library",
        "name": "Biblioteca Pública",
        "id": "node/3430967888"
      },
      "geometry": {
        "type": "Point",
        "coordinates": [
          -36.8835385,
          -10.2088061
        ]
      }
    }
  ]
}
