{
  "type": "FeatureCollection",
  "features": [
    {
      "type": "Feature",
      "id": "node/11210954638",
      "properties": {
        "timestamp": "2023-09-22T20:08:00Z",
        "version": 1,
        "changeset": 141620310,
        "name": "Prefeitura Municipal de Graça",
        "office": "government",
        "id": "node/11210954638"
      },
      "geometry": {
        "type": "Point",
        "coordinates": [
          -40.752082,
          -4.045309
        ]
      }
    }
  ]
}
