{
  "type": "FeatureCollection",
  "features": [
    {
      "type": "Feature",
      "id": "node/12663188001",
      "properties": {
        "timestamp": "2025-03-14T17:53:53Z",
        "version": 1,
        "changeset": 163620758,
        "name": "Gralha Azul",
        "tourism": "hotel",
        "id": "node/12663188001"
      },
      "geometry": {
        "type": "Point",
        "coordinates": [
          -50.3858465,
          -27.3569777
        ]
      }
    }
  ]
}
