{
  "type": "FeatureCollection",
  "features": [
    {
      "type": "Feature",
      "id": "node/4633734432",
      "properties": {
        "timestamp": "2022-10-11T00:01:20Z",
        "version": 2,
        "changeset": 127328282,
        "name": "Hotel Scheibler",
        "tourism": "hotel",
        "id": "node/4633734432"
      },
      "geometry": {
        "type": "Point",
        "coordinates": [
          -53.0687483,
          -28.060578
        ]
      }
    }
  ]
}
