{
  "type": "FeatureCollection",
  "features": [
    {
      "type": "Feature",
      "id": "node/5735125294",
      "properties": {
        "timestamp": "2025-01-14T17:20:16Z",
        "version": 3,
        "changeset": 161353103,
        "addr:city": "Pedra Azul",
        "addr:housenumber": "369",
        "addr:postcode": "39970-000",
        "addr:street": "Avenida Doutor Álvaro Neves",
        "addr:suburb": "Centro",
        "amenity": "hospital",
        "emergency": "yes",
        "healthcare": "hospital",
        "healthcare:speciality": "general",
        "name": "Hospital Ester Faria de Almeida - Hefa",
        "id": "node/5735125294"
      },
      "geometry": {
        "type": "Point",
        "coordinates": [
          -41.2827917,
          -16.0081466
        ]
      }
    }
  ]
}
