{
  "type": "FeatureCollection",
  "features": [
    {
      "type": "Feature",
      "id": "node/5735125294",
      "properties": {
        "timestamp": "2018-07-02T21:47:02Z",
        "version": 1,
        "changeset": 60359807,
        "amenity": "hospital",
        "healthcare": "hospital",
        "name": "Hospital Ester Farias de Almeida",
        "id": "node/5735125294"
      },
      "geometry": {
        "type": "Point",
        "coordinates": [
          -41.2827917,
          -16.0081466
        ]
      }
    }
  ]
}
