{
  "type": "FeatureCollection",
  "features": [
    {
      "type": "Feature",
      "id": "node/10087013126",
      "properties": {
        "timestamp": "2022-10-09T13:36:37Z",
        "version": 1,
        "changeset": 127249287,
        "addr:city": "São Lourenço do Sul",
        "addr:housenumber": "608",
        "addr:postcode": "96170-000",
        "addr:street": "Rua Senador Pinheiro Machado",
        "addr:suburb": "Centro",
        "name": "Sul Bike",
        "shop": "bicycle",
        "id": "node/10087013126"
      },
      "geometry": {
        "type": "Point",
        "coordinates": [
          -51.9805627,
          -31.3633368
        ]
      }
    }
  ]
}
