{
  "type": "FeatureCollection",
  "features": [
    {
      "type": "Feature",
      "id": "node/3001430595",
      "properties": {
        "timestamp": "2020-09-23T01:11:57Z",
        "version": 3,
        "changeset": 91323521,
        "addr:city": "São Lourenço do Sul",
        "addr:housenumber": "241",
        "addr:postcode": "96170-000",
        "addr:street": "Rua Coronel Alfredo Born",
        "amenity": "pharmacy",
        "brand": "Panvel",
        "brand:wikidata": "Q10344254",
        "brand:wikipedia": "pt:Panvel",
        "healthcare": "pharmacy",
        "name": "Panvel",
        "source": "ibge",
        "id": "node/3001430595"
      },
      "geometry": {
        "type": "Point",
        "coordinates": [
          -51.9798607,
          -31.3660937
        ]
      }
    },
    {
      "type": "Feature",
      "id": "node/3009563537",
      "properties": {
        "timestamp": "2021-03-09T02:31:47Z",
        "version": 3,
        "changeset": 100668681,
        "addr:street": "Rua Coronel Alfredo Born",
        "amenity": "pharmacy",
        "healthcare": "pharmacy",
        "name": "Agafarma",
        "id": "node/3009563537"
      },
      "geometry": {
        "type": "Point",
        "coordinates": [
          -51.9801627,
          -31.3659819
        ]
      }
    },
    {
      "type": "Feature",
      "id": "node/3009563545",
      "properties": {
        "timestamp": "2020-07-10T17:26:39Z",
        "version": 2,
        "changeset": 87828035,
        "addr:city": "São Lourenço do Sul",
        "addr:housenumber": "452",
        "addr:postcode": "96170-000",
        "addr:street": "Rua Coronel Alfredo Born",
        "amenity": "pharmacy",
        "healthcare": "pharmacy",
        "name": "Mais Econômica",
        "id": "node/3009563545"
      },
      "geometry": {
        "type": "Point",
        "coordinates": [
          -51.9806064,
          -31.3651087
        ]
      }
    },
    {
      "type": "Feature",
      "id": "node/3009584719",
      "properties": {
        "timestamp": "2020-07-10T17:26:39Z",
        "version": 2,
        "changeset": 87828035,
        "addr:city": "São Lourenço do Sul",
        "addr:housenumber": "453",
        "addr:postcode": "96170-000",
        "addr:street": "Rua Coronel Alfredo Born",
        "amenity": "pharmacy",
        "healthcare": "pharmacy",
        "name": "FarmaRitter",
        "id": "node/3009584719"
      },
      "geometry": {
        "type": "Point",
        "coordinates": [
          -51.9804055,
          -31.3650612
        ]
      }
    }
  ]
}
