{
  "type": "FeatureCollection",
  "features": [
    {
      "type": "Feature",
      "id": "node/6455724895",
      "properties": {
        "timestamp": "2021-09-28T20:26:57Z",
        "version": 2,
        "changeset": 111836720,
        "addr:street": "Avenida Coronel Francisco Moreira",
        "name": "INSS Previdência Social",
        "office": "government",
        "id": "node/6455724895"
      },
      "geometry": {
        "type": "Point",
        "coordinates": [
          -42.5623777,
          -3.5002526
        ]
      }
    }
  ]
}
