{
  "type": "FeatureCollection",
  "features": [
    {
      "type": "Feature",
      "id": "node/6044048972",
      "properties": {
        "timestamp": "2022-07-17T23:20:33Z",
        "version": 3,
        "changeset": 123737787,
        "addr:postcode": "37466-000",
        "amenity": "arts_centre",
        "name": "Cine Teatro São José",
        "id": "node/6044048972"
      },
      "geometry": {
        "type": "Point",
        "coordinates": [
          -44.8704565,
          -22.2859445
        ]
      }
    }
  ]
}
