{
  "type": "FeatureCollection",
  "features": [
    {
      "type": "Feature",
      "id": "node/6044048249",
      "properties": {
        "timestamp": "2022-07-17T23:20:33Z",
        "version": 5,
        "changeset": 123737787,
        "addr:postcode": "37466-000",
        "amenity": "library",
        "internet_access": "yes",
        "name": "Casa da Cultura Liberato Torino",
        "id": "node/6044048249"
      },
      "geometry": {
        "type": "Point",
        "coordinates": [
          -44.8703116,
          -22.2858204
        ]
      }
    }
  ]
}
