{
  "type": "FeatureCollection",
  "features": [
    {
      "type": "Feature",
      "id": "node/4154615370",
      "properties": {
        "timestamp": "2016-04-29T02:35:15Z",
        "version": 1,
        "changeset": 38971208,
        "historic": "monument",
        "name": "Morro da Santa",
        "id": "node/4154615370"
      },
      "geometry": {
        "type": "Point",
        "coordinates": [
          -44.2290649,
          -21.0193791
        ]
      }
    }
  ]
}
