{
  "type": "FeatureCollection",
  "features": [
    {
      "type": "Feature",
      "id": "node/9577929237",
      "properties": {
        "timestamp": "2023-09-26T12:32:51Z",
        "version": 3,
        "changeset": 141772840,
        "name": "Cachoeira do Carteiro (parte alta)",
        "waterway": "waterfall",
        "id": "node/9577929237"
      },
      "geometry": {
        "type": "Point",
        "coordinates": [
          -44.168911,
          -21.0806933
        ]
      }
    },
    {
      "type": "Feature",
      "id": "node/9577931533",
      "properties": {
        "timestamp": "2023-09-26T12:32:51Z",
        "version": 2,
        "changeset": 141772840,
        "name": "Cachoeira do Carteiro (parte baixa)",
        "waterway": "waterfall",
        "id": "node/9577931533"
      },
      "geometry": {
        "type": "Point",
        "coordinates": [
          -44.1700416,
          -21.0798689
        ]
      }
    }
  ]
}
