{
  "type": "FeatureCollection",
  "features": [
    {
      "type": "Feature",
      "id": "node/12175957249",
      "properties": {
        "timestamp": "2024-09-14T02:51:31Z",
        "version": 1,
        "changeset": 156594824,
        "addr:city": "Campina Grande do Sul",
        "addr:housenumber": "1158",
        "addr:postcode": "83430000",
        "addr:street": "Rua Annibale Ferrarini",
        "amenity": "pharmacy",
        "healthcare": "pharmacy",
        "name": "Maxifarma",
        "id": "node/12175957249"
      },
      "geometry": {
        "type": "Point",
        "coordinates": [
          -49.114573,
          -25.3603326
        ]
      }
    }
  ]
}
