{
  "type": "FeatureCollection",
  "features": [
    {
      "type": "Feature",
      "id": "node/10785812842",
      "properties": {
        "timestamp": "2023-04-05T01:28:13Z",
        "version": 1,
        "changeset": 134518169,
        "addr:housenumber": "1567",
        "addr:street": "Rua Professor Duilio Calderari",
        "addr:suburb": "Jardim Paulista",
        "amenity": "social_facility",
        "name": "Centro de Referência de Assistência Social",
        "id": "node/10785812842"
      },
      "geometry": {
        "type": "Point",
        "coordinates": [
          -49.0975729,
          -25.3637352
        ]
      }
    }
  ]
}
