{
  "type": "FeatureCollection",
  "features": [
    {
      "type": "Feature",
      "id": "node/9503608903",
      "properties": {
        "timestamp": "2022-02-14T02:40:26Z",
        "version": 2,
        "changeset": 117374441,
        "addr:city": "Santa Teresa",
        "addr:postcode": "29650-000",
        "addr:street": "Rodovia Enrico Aurélio Hildebrando Ruschi",
        "addr:suburb": "Jardim da Montanha",
        "email": "aps07001190@inss.gov.br",
        "government": "social_services",
        "name": "Agência da Previdência Social de Santa Teresa - INSS",
        "office": "government",
        "phone": "+55 27 3259 1170",
        "id": "node/9503608903"
      },
      "geometry": {
        "type": "Point",
        "coordinates": [
          -40.5875077,
          -19.9404784
        ]
      }
    },
    {
      "type": "Feature",
      "id": "node/9503608906",
      "properties": {
        "timestamp": "2022-02-13T23:23:09Z",
        "version": 1,
        "changeset": 117372480,
        "addr:city": "Santa Teresa",
        "addr:housenumber": "358",
        "addr:postcode": "29650-000",
        "addr:street": "Avenida Maria Angélica Vervloet dos Santos",
        "addr:suburb": "Canaã",
        "government": "prosecutor",
        "name": "Promotoria de Justiça de Santa Teresa",
        "office": "government",
        "phone": "+55 27 3259 2121",
        "id": "node/9503608906"
      },
      "geometry": {
        "type": "Point",
        "coordinates": [
          -40.5969965,
          -19.9264505
        ]
      }
    },
    {
      "type": "Feature",
      "id": "node/9520732262",
      "properties": {
        "timestamp": "2022-02-20T01:12:01Z",
        "version": 1,
        "changeset": 117623662,
        "addr:city": "Santa Teresa",
        "addr:housenumber": "70",
        "addr:postcode": "29650-000",
        "addr:street": "Rua Jerônimo Vervloet",
        "addr:suburb": "Centro",
        "government": "register_office",
        "name": "Cartório de Primeiro Ofício de Santa Teresa",
        "office": "government",
        "id": "node/9520732262"
      },
      "geometry": {
        "type": "Point",
        "coordinates": [
          -40.6001007,
          -19.9326672
        ]
      }
    },
    {
      "type": "Feature",
      "id": "node/9520732263",
      "properties": {
        "timestamp": "2022-02-20T01:12:01Z",
        "version": 1,
        "changeset": 117623662,
        "addr:city": "Santa Teresa",
        "addr:housenumber": "89",
        "addr:postcode": "29650-000",
        "addr:street": "Avenida Getúlio Vargas",
        "addr:suburb": "Centro",
        "government": "register_office",
        "name": "Cartório de Protestos de Títulos e Tabelionato",
        "office": "government",
        "id": "node/9520732263"
      },
      "geometry": {
        "type": "Point",
        "coordinates": [
          -40.6006251,
          -19.9325941
        ]
      }
    }
  ]
}
