{
  "type": "FeatureCollection",
  "features": [
    {
      "type": "Feature",
      "id": "node/2411982147",
      "properties": {
        "timestamp": "2022-02-20T01:12:01Z",
        "version": 6,
        "changeset": 117623662,
        "IJSN:tipoUnidad": "Hospital Geral",
        "addr:city": "Santa Teresa",
        "addr:housenumber": "417",
        "addr:place": "Jardim da Montanha",
        "addr:postcode": "29650-000",
        "addr:street": "Avenida das Acácias",
        "addr:suburb": "Jardim da Montanha",
        "amenity": "hospital",
        "contact:phone": "+55 27 3259-1113",
        "emergency": "yes",
        "healthcare": "hospital",
        "name": "Hospital Madre Regina Protmann",
        "id": "node/2411982147"
      },
      "geometry": {
        "type": "Point",
        "coordinates": [
          -40.5924022,
          -19.9415588
        ]
      }
    }
  ]
}
