{
  "type": "FeatureCollection",
  "features": [
    {
      "type": "Feature",
      "id": "node/8338608150",
      "properties": {
        "timestamp": "2022-02-13T21:48:01Z",
        "version": 2,
        "changeset": 117370576,
        "addr:city": "Santa Teresa",
        "addr:housenumber": "165",
        "addr:postcode": "29650-000",
        "addr:street": "Avenida José Ruschi",
        "addr:suburb": "Centro",
        "amenity": "pharmacy",
        "dispensing": "yes",
        "healthcare": "pharmacy",
        "name": "Farmácia Bortolini",
        "id": "node/8338608150"
      },
      "geometry": {
        "type": "Point",
        "coordinates": [
          -40.5989079,
          -19.9354413
        ]
      }
    },
    {
      "type": "Feature",
      "id": "node/9474380873",
      "properties": {
        "timestamp": "2022-02-04T13:46:51Z",
        "version": 1,
        "changeset": 117007486,
        "addr:city": "Santa Teresa",
        "addr:housenumber": "276",
        "addr:postcode": "29650-000",
        "addr:street": "Rua do Comércio",
        "addr:suburb": "São João de Petrópolis",
        "amenity": "pharmacy",
        "dispensing": "yes",
        "healthcare": "pharmacy",
        "name": "Drogaria São João",
        "operator": "Drogaria Sao Joao De Petropolis Ltda",
        "id": "node/9474380873"
      },
      "geometry": {
        "type": "Point",
        "coordinates": [
          -40.6778039,
          -19.816247
        ]
      }
    },
    {
      "type": "Feature",
      "id": "node/9521212615",
      "properties": {
        "timestamp": "2022-02-20T09:08:27Z",
        "version": 1,
        "changeset": 117629715,
        "addr:city": "Santa Teresa",
        "addr:housenumber": "188",
        "addr:postcode": "29650-000",
        "addr:street": "Rua Coronel Bonfim Junior",
        "addr:suburb": "Centro",
        "amenity": "pharmacy",
        "healthcare": "pharmacy",
        "name": "Imafar",
        "phone": "+55 27 3259 3663",
        "id": "node/9521212615"
      },
      "geometry": {
        "type": "Point",
        "coordinates": [
          -40.602707,
          -19.9317044
        ]
      }
    }
  ]
}
