{
  "type": "FeatureCollection",
  "features": [
    {
      "type": "Feature",
      "id": "node/7600299774",
      "properties": {
        "timestamp": "2021-11-09T10:05:29Z",
        "version": 2,
        "changeset": 113558252,
        "waterway": "waterfall",
        "id": "node/7600299774"
      },
      "geometry": {
        "type": "Point",
        "coordinates": [
          -40.5277171,
          -19.9745806
        ]
      }
    },
    {
      "type": "Feature",
      "id": "node/9038342796",
      "properties": {
        "timestamp": "2022-02-12T20:20:38Z",
        "version": 3,
        "changeset": 117334892,
        "name": "Cachoeira do Zanotti",
        "waterway": "waterfall",
        "id": "node/9038342796"
      },
      "geometry": {
        "type": "Point",
        "coordinates": [
          -40.7434673,
          -19.921804
        ]
      }
    }
  ]
}
