{
  "type": "FeatureCollection",
  "features": [
    {
      "type": "Feature",
      "id": "node/9607523220",
      "properties": {
        "timestamp": "2022-03-25T22:02:48Z",
        "version": 1,
        "changeset": 118929411,
        "amenity": "clinic",
        "healthcare": "clinic",
        "name": "Posto de Saúde",
        "id": "node/9607523220"
      },
      "geometry": {
        "type": "Point",
        "coordinates": [
          -37.6628011,
          -11.1928054
        ]
      }
    }
  ]
}
