{
  "type": "FeatureCollection",
  "features": [
    {
      "type": "Feature",
      "id": "node/8346410417",
      "properties": {
        "timestamp": "2021-01-21T20:40:12Z",
        "version": 1,
        "changeset": 97926820,
        "amenity": "pharmacy",
        "name": "Farmacia Bia Esperança",
        "id": "node/8346410417"
      },
      "geometry": {
        "type": "Point",
        "coordinates": [
          -39.6275884,
          -5.7435159
        ]
      }
    }
  ]
}
