{
  "type": "FeatureCollection",
  "features": [
    {
      "type": "Feature",
      "id": "node/4537608189",
      "properties": {
        "timestamp": "2017-07-05T00:07:22Z",
        "version": 2,
        "changeset": 50046678,
        "amenity": "community_centre",
        "name": "chácara sol nascente",
        "id": "node/4537608189"
      },
      "geometry": {
        "type": "Point",
        "coordinates": [
          -51.6773082,
          -30.6711132
        ]
      }
    }
  ]
}
