{
  "type": "FeatureCollection",
  "features": [
    {
      "type": "Feature",
      "id": "node/6444866082",
      "properties": {
        "timestamp": "2019-05-03T09:03:31Z",
        "version": 1,
        "changeset": 69833735,
        "amenity": "drinking_water",
        "id": "node/6444866082"
      },
      "geometry": {
        "type": "Point",
        "coordinates": [
          -48.5076563,
          -27.5796663
        ]
      }
    },
    {
      "type": "Feature",
      "id": "node/10267149649",
      "properties": {
        "timestamp": "2022-12-16T12:53:42Z",
        "version": 2,
        "changeset": 130155278,
        "amenity": "drinking_water",
        "bottle": "yes",
        "id": "node/10267149649"
      },
      "geometry": {
        "type": "Point",
        "coordinates": [
          -48.5147434,
          -27.5990162
        ]
      }
    },
    {
      "type": "Feature",
      "id": "node/10734557663",
      "properties": {
        "timestamp": "2023-03-14T10:29:24Z",
        "version": 1,
        "changeset": 133660461,
        "amenity": "drinking_water",
        "bottle": "yes",
        "fee": "no",
        "id": "node/10734557663"
      },
      "geometry": {
        "type": "Point",
        "coordinates": [
          -48.5423698,
          -27.5931621
        ]
      }
    },
    {
      "type": "Feature",
      "id": "node/10734557678",
      "properties": {
        "timestamp": "2023-03-14T10:29:24Z",
        "version": 1,
        "changeset": 133660461,
        "amenity": "drinking_water",
        "bottle": "yes",
        "fee": "no",
        "wheelchair": "yes",
        "id": "node/10734557678"
      },
      "geometry": {
        "type": "Point",
        "coordinates": [
          -48.5425602,
          -27.5944079
        ]
      }
    },
    {
      "type": "Feature",
      "id": "node/10752932615",
      "properties": {
        "timestamp": "2023-03-22T10:40:36Z",
        "version": 1,
        "changeset": 133972451,
        "amenity": "drinking_water",
        "bottle": "yes",
        "fee": "no",
        "level": "1",
        "wheelchair": "yes",
        "id": "node/10752932615"
      },
      "geometry": {
        "type": "Point",
        "coordinates": [
          -48.5420583,
          -27.5943198
        ]
      }
    },
    {
      "type": "Feature",
      "id": "node/10781715743",
      "properties": {
        "timestamp": "2023-04-03T12:25:15Z",
        "version": 1,
        "changeset": 134452847,
        "addr:floor": "2",
        "amenity": "drinking_water",
        "bottle": "yes",
        "fee": "no",
        "wheelchair": "yes",
        "id": "node/10781715743"
      },
      "geometry": {
        "type": "Point",
        "coordinates": [
          -48.5421353,
          -27.5944586
        ]
      }
    }
  ]
}
