{
  "type": "FeatureCollection",
  "features": [
    {
      "type": "Feature",
      "id": "node/3815421468",
      "properties": {
        "timestamp": "2016-01-08T21:05:36Z",
        "version": 2,
        "changeset": 36453679,
        "name": "Cachoeira do Arcão",
        "waterway": "waterfall",
        "id": "node/3815421468"
      },
      "geometry": {
        "type": "Point",
        "coordinates": [
          -48.4359391,
          -24.28979
        ]
      }
    },
    {
      "type": "Feature",
      "id": "node/3934571730",
      "properties": {
        "timestamp": "2018-04-24T16:43:27Z",
        "version": 2,
        "changeset": 58380208,
        "name": "Cachoeira Bulha d'água 2",
        "waterway": "waterfall",
        "id": "node/3934571730"
      },
      "geometry": {
        "type": "Point",
        "coordinates": [
          -48.4987722,
          -24.3452164
        ]
      }
    },
    {
      "type": "Feature",
      "id": "node/3934571731",
      "properties": {
        "timestamp": "2018-04-24T16:43:12Z",
        "version": 2,
        "changeset": 58380200,
        "name": "Cachoeira Bulha d'água",
        "waterway": "waterfall",
        "id": "node/3934571731"
      },
      "geometry": {
        "type": "Point",
        "coordinates": [
          -48.501006,
          -24.3398807
        ]
      }
    },
    {
      "type": "Feature",
      "id": "node/7196220787",
      "properties": {
        "timestamp": "2024-04-10T15:40:08Z",
        "version": 2,
        "changeset": 149826616,
        "waterway": "waterfall",
        "id": "node/7196220787"
      },
      "geometry": {
        "type": "Point",
        "coordinates": [
          -48.6538543,
          -24.5710737
        ]
      }
    }
  ]
}
