{
  "type": "FeatureCollection",
  "features": [
    {
      "type": "Feature",
      "id": "node/11261019573",
      "properties": {
        "timestamp": "2023-10-15T16:19:44Z",
        "version": 2,
        "changeset": 142625372,
        "amenity": "clinic",
        "healthcare": "clinic",
        "name": "Posto de Saude",
        "id": "node/11261019573"
      },
      "geometry": {
        "type": "Point",
        "coordinates": [
          -39.9593381,
          -3.2829275
        ]
      }
    }
  ]
}
