{
  "type": "FeatureCollection",
  "features": [
    {
      "type": "Feature",
      "id": "node/11261019572",
      "properties": {
        "timestamp": "2023-10-15T16:19:44Z",
        "version": 2,
        "changeset": 142625372,
        "amenity": "school",
        "name": "EEIEF Antônio Ferreira Sales",
        "id": "node/11261019572"
      },
      "geometry": {
        "type": "Point",
        "coordinates": [
          -39.9593044,
          -3.2827048
        ]
      }
    }
  ]
}
