{
  "type": "FeatureCollection",
  "features": [
    {
      "type": "Feature",
      "id": "node/4816778621",
      "properties": {
        "timestamp": "2022-07-30T00:20:56Z",
        "version": 4,
        "changeset": 124251457,
        "addr:housenumber": "71",
        "addr:postcode": "85892000",
        "addr:street": "Avenida Curitiba",
        "email": "contato@hotelalvorada-pr.com.br",
        "internet_access": "wlan",
        "name": "Hotel Alvorada",
        "name:en": "Português",
        "name:pt": "Hotel alvorada",
        "phone": "+55 45 3268 2258",
        "tourism": "hotel",
        "website": "https://www.hotelalvorada-pr.com.br/",
        "id": "node/4816778621"
      },
      "geometry": {
        "type": "Point",
        "coordinates": [
          -54.3304467,
          -24.8606576
        ]
      }
    }
  ]
}
