{
  "type": "FeatureCollection",
  "features": [
    {
      "type": "Feature",
      "id": "node/2450719627",
      "properties": {
        "timestamp": "2013-09-08T17:04:41Z",
        "version": 1,
        "changeset": 17736435,
        "amenity": "drinking_water",
        "source": "local",
        "id": "node/2450719627"
      },
      "geometry": {
        "type": "Point",
        "coordinates": [
          -44.324398,
          -22.4162246
        ]
      }
    },
    {
      "type": "Feature",
      "id": "node/2470120482",
      "properties": {
        "timestamp": "2013-10-02T16:29:07Z",
        "version": 2,
        "changeset": 18146984,
        "amenity": "drinking_water",
        "name": "Pluviômetro ETA Bulhões",
        "id": "node/2470120482"
      },
      "geometry": {
        "type": "Point",
        "coordinates": [
          -44.3527553,
          -22.4701045
        ]
      }
    }
  ]
}
