{
  "type": "FeatureCollection",
  "features": [
    {
      "type": "Feature",
      "id": "node/2593136741",
      "properties": {
        "timestamp": "2014-01-03T16:25:31Z",
        "version": 3,
        "changeset": 19789757,
        "name": "Açude de João Alfredo",
        "waterway": "dam",
        "id": "node/2593136741"
      },
      "geometry": {
        "type": "Point",
        "coordinates": [
          -35.5974329,
          -7.8547369
        ]
      }
    }
  ]
}
