{
  "type": "FeatureCollection",
  "features": [
    {
      "type": "Feature",
      "id": "node/7745524802",
      "properties": {
        "timestamp": "2020-07-24T21:58:24Z",
        "version": 1,
        "changeset": 88478641,
        "historic": "memorial",
        "name": "Relógio das Flores",
        "id": "node/7745524802"
      },
      "geometry": {
        "type": "Point",
        "coordinates": [
          -45.2249307,
          -22.8388194
        ]
      }
    }
  ]
}
