{
  "type": "FeatureCollection",
  "features": [
    {
      "type": "Feature",
      "id": "node/5742330163",
      "properties": {
        "timestamp": "2018-07-05T23:55:53Z",
        "version": 1,
        "changeset": 60450251,
        "name": "Pousada Jucá",
        "tourism": "hotel",
        "id": "node/5742330163"
      },
      "geometry": {
        "type": "Point",
        "coordinates": [
          -39.6766302,
          -4.651199
        ]
      }
    }
  ]
}
