{
  "type": "FeatureCollection",
  "features": [
    {
      "type": "Feature",
      "id": "node/5846312770",
      "properties": {
        "timestamp": "2019-04-03T12:03:04Z",
        "version": 2,
        "changeset": 68835208,
        "historic": "monument",
        "landuse": "grass",
        "name": "Pórtico",
        "id": "node/5846312770"
      },
      "geometry": {
        "type": "Point",
        "coordinates": [
          -37.5606555,
          -5.7807781
        ]
      }
    },
    {
      "type": "Feature",
      "id": "node/7052137263",
      "properties": {
        "timestamp": "2019-12-12T13:51:23Z",
        "version": 1,
        "changeset": 78320940,
        "historic": "monument",
        "name": "Centenario de Caraúbas",
        "id": "node/7052137263"
      },
      "geometry": {
        "type": "Point",
        "coordinates": [
          -37.5582653,
          -5.793976
        ]
      }
    }
  ]
}
