{
  "type": "FeatureCollection",
  "features": [
    {
      "type": "Feature",
      "id": "node/10009675418",
      "properties": {
        "timestamp": "2022-09-08T18:04:56Z",
        "version": 1,
        "changeset": 125953299,
        "contact:instagram": "https://www.instagram.com/pousadatialourdinha/",
        "internet_access": "wlan",
        "name": "Pousada Tia Lourdinha",
        "phone": "+55 86 98814 7558;+55 98 99973 8402",
        "tourism": "hotel",
        "id": "node/10009675418"
      },
      "geometry": {
        "type": "Point",
        "coordinates": [
          -41.9095145,
          -2.875846
        ]
      }
    },
    {
      "type": "Feature",
      "id": "node/10271089109",
      "properties": {
        "timestamp": "2022-12-18T10:13:45Z",
        "version": 1,
        "changeset": 130207226,
        "name": "Casa de Caboclo",
        "tourism": "hotel",
        "id": "node/10271089109"
      },
      "geometry": {
        "type": "Point",
        "coordinates": [
          -41.8386532,
          -2.7633003
        ]
      }
    }
  ]
}
