{
  "type": "FeatureCollection",
  "features": [
    {
      "type": "Feature",
      "id": "node/8533587210",
      "properties": {
        "timestamp": "2022-12-21T12:17:57Z",
        "version": 2,
        "changeset": 130330532,
        "historic": "monument",
        "name": "Tocha Olímpica",
        "id": "node/8533587210"
      },
      "geometry": {
        "type": "Point",
        "coordinates": [
          -40.8491644,
          -2.8796798
        ]
      }
    },
    {
      "type": "Feature",
      "id": "node/8657424700",
      "properties": {
        "timestamp": "2021-04-25T02:51:58Z",
        "version": 2,
        "changeset": 103558401,
        "historic": "monument",
        "inscription": "Símbolo maçônico",
        "id": "node/8657424700"
      },
      "geometry": {
        "type": "Point",
        "coordinates": [
          -40.8548527,
          -2.9258011
        ]
      }
    }
  ]
}
