{
  "type": "FeatureCollection",
  "features": [
    {
      "type": "Feature",
      "id": "node/4546600257",
      "properties": {
        "timestamp": "2018-02-19T04:59:54Z",
        "version": 2,
        "changeset": 56480085,
        "name": "Cachoeira da Mandiroba",
        "waterway": "waterfall",
        "id": "node/4546600257"
      },
      "geometry": {
        "type": "Point",
        "coordinates": [
          -43.0093599,
          -14.3944849
        ]
      }
    },
    {
      "type": "Feature",
      "id": "node/5421685265",
      "properties": {
        "timestamp": "2018-02-19T04:58:56Z",
        "version": 1,
        "changeset": 56480085,
        "name": "Cachoeira do Brucunum",
        "waterway": "waterfall",
        "id": "node/5421685265"
      },
      "geometry": {
        "type": "Point",
        "coordinates": [
          -43.0648962,
          -14.349657
        ]
      }
    }
  ]
}
