{
  "type": "FeatureCollection",
  "features": [
    {
      "type": "Feature",
      "id": "node/4263654291",
      "properties": {
        "timestamp": "2020-05-14T05:09:10Z",
        "version": 3,
        "changeset": 85175352,
        "addr:street": "Avenida Siqueira Campos",
        "government": "customs",
        "name": "Receita Federal",
        "office": "government",
        "id": "node/4263654291"
      },
      "geometry": {
        "type": "Point",
        "coordinates": [
          -55.5150047,
          -1.918812
        ]
      }
    },
    {
      "type": "Feature",
      "id": "node/4270036917",
      "properties": {
        "timestamp": "2016-07-11T15:57:25Z",
        "version": 2,
        "changeset": 40654931,
        "name": "Demutran",
        "office": "government",
        "id": "node/4270036917"
      },
      "geometry": {
        "type": "Point",
        "coordinates": [
          -55.5169744,
          -1.9112035
        ]
      }
    }
  ]
}
