{
  "type": "FeatureCollection",
  "features": [
    {
      "type": "Feature",
      "id": "node/4715897311",
      "properties": {
        "timestamp": "2017-03-04T01:04:27Z",
        "version": 1,
        "changeset": 46562380,
        "waterway": "waterfall",
        "id": "node/4715897311"
      },
      "geometry": {
        "type": "Point",
        "coordinates": [
          -55.842261,
          -0.3174453
        ]
      }
    },
    {
      "type": "Feature",
      "id": "node/12498532913",
      "properties": {
        "timestamp": "2025-01-13T17:02:59Z",
        "version": 1,
        "changeset": 161317807,
        "name": "Cachoeira Jaramacarú",
        "waterway": "waterfall",
        "id": "node/12498532913"
      },
      "geometry": {
        "type": "Point",
        "coordinates": [
          -55.7124853,
          -1.1676671
        ]
      }
    }
  ]
}
