{
  "type": "FeatureCollection",
  "features": [
    {
      "type": "Feature",
      "id": "node/1682706978",
      "properties": {
        "timestamp": "2019-04-09T13:45:04Z",
        "version": 2,
        "changeset": 69046812,
        "name": "Pousada SESC MG",
        "tourism": "guest_house",
        "id": "node/1682706978"
      },
      "geometry": {
        "type": "Point",
        "coordinates": [
          -43.8687836,
          -16.7212234
        ]
      }
    }
  ]
}
