{
  "type": "FeatureCollection",
  "features": [
    {
      "type": "Feature",
      "id": "node/3491299272",
      "properties": {
        "timestamp": "2022-08-18T19:04:42Z",
        "version": 3,
        "changeset": 125076546,
        "IJSN:tipoUnidad": "Hospital Geral",
        "addr:city": "Santa Leopoldina",
        "addr:housenumber": "1000",
        "addr:place": "Centro",
        "addr:postcode": "29640-000",
        "addr:street": "Ladeira Vereadora Rosalina Ribeiro Nunes",
        "amenity": "hospital",
        "contact:phone": "(27) 3266-1131",
        "healthcare": "hospital",
        "name": "Hospital Nossa Senhora da Penha",
        "id": "node/3491299272"
      },
      "geometry": {
        "type": "Point",
        "coordinates": [
          -40.5267414,
          -20.0982248
        ]
      }
    }
  ]
}
