{
  "type": "FeatureCollection",
  "features": [
    {
      "type": "Feature",
      "id": "node/5745880009",
      "properties": {
        "timestamp": "2018-07-07T20:06:12Z",
        "version": 1,
        "changeset": 60496425,
        "name": "Açude Riachão Velho",
        "waterway": "dam",
        "id": "node/5745880009"
      },
      "geometry": {
        "type": "Point",
        "coordinates": [
          -41.3966005,
          -7.2892562
        ]
      }
    }
  ]
}
