{
  "type": "FeatureCollection",
  "features": [
    {
      "type": "Feature",
      "id": "node/5529416026",
      "properties": {
        "timestamp": "2018-04-04T23:47:18Z",
        "version": 1,
        "changeset": 57818086,
        "amenity": "doctors",
        "name": "posto de saúde",
        "id": "node/5529416026"
      },
      "geometry": {
        "type": "Point",
        "coordinates": [
          -60.2290421,
          4.4321416
        ]
      }
    },
    {
      "type": "Feature",
      "id": "node/5536389121",
      "properties": {
        "timestamp": "2019-11-04T20:21:39Z",
        "version": 2,
        "changeset": 76612339,
        "amenity": "doctors",
        "healthcare": "doctor",
        "name": "Unidade Básica de Saúde",
        "id": "node/5536389121"
      },
      "geometry": {
        "type": "Point",
        "coordinates": [
          -60.158492,
          4.5922312
        ]
      }
    }
  ]
}
