{
  "type": "FeatureCollection",
  "features": [
    {
      "type": "Feature",
      "id": "node/5618125521",
      "properties": {
        "timestamp": "2018-05-21T00:02:16Z",
        "version": 2,
        "changeset": 59135581,
        "addr:city": "Cornélio Procópio",
        "amenity": "pharmacy",
        "name": "Farmácia",
        "wheelchair": "yes",
        "id": "node/5618125521"
      },
      "geometry": {
        "type": "Point",
        "coordinates": [
          -50.654295,
          -23.18597
        ]
      }
    }
  ]
}
