{
  "type": "FeatureCollection",
  "features": [
    {
      "type": "Feature",
      "id": "node/4680309659",
      "properties": {
        "timestamp": "2017-02-11T15:42:35Z",
        "version": 1,
        "changeset": 46000723,
        "name": "Pousada do Valtinho",
        "tourism": "hotel",
        "id": "node/4680309659"
      },
      "geometry": {
        "type": "Point",
        "coordinates": [
          -43.8742469,
          -18.7844376
        ]
      }
    }
  ]
}
