{
  "type": "FeatureCollection",
  "features": [
    {
      "type": "Feature",
      "id": "node/6697531178",
      "properties": {
        "timestamp": "2019-08-22T13:37:01Z",
        "version": 2,
        "changeset": 73625206,
        "addr:housenumber": "3",
        "addr:street": "Rua Senador Robert Kennedy",
        "alt_name": "Afonso Bicicletas",
        "contact:phone": "+55 83 3341 8251",
        "name": "Afonso Bike",
        "shop": "bicycle",
        "id": "node/6697531178"
      },
      "geometry": {
        "type": "Point",
        "coordinates": [
          -35.8678844,
          -7.2220335
        ]
      }
    },
    {
      "type": "Feature",
      "id": "node/6751145596",
      "properties": {
        "timestamp": "2019-08-27T20:36:11Z",
        "version": 1,
        "changeset": 73813882,
        "name": "Well Bike",
        "shop": "bicycle",
        "id": "node/6751145596"
      },
      "geometry": {
        "type": "Point",
        "coordinates": [
          -35.8724079,
          -7.2349929
        ]
      }
    },
    {
      "type": "Feature",
      "id": "node/7234366787",
      "properties": {
        "timestamp": "2020-02-22T00:48:38Z",
        "version": 1,
        "changeset": 81336614,
        "name": "Elite Bike",
        "shop": "bicycle",
        "id": "node/7234366787"
      },
      "geometry": {
        "type": "Point",
        "coordinates": [
          -35.8682556,
          -7.222941
        ]
      }
    }
  ]
}
