{
  "type": "FeatureCollection",
  "features": [
    {
      "type": "Feature",
      "id": "node/4676590439",
      "properties": {
        "timestamp": "2017-02-09T13:20:51Z",
        "version": 1,
        "changeset": 45947063,
        "historic": "monument",
        "name": "Mural de Aimes e Jogos",
        "id": "node/4676590439"
      },
      "geometry": {
        "type": "Point",
        "coordinates": [
          -35.8773371,
          -7.2348075
        ]
      }
    }
  ]
}
