{
  "type": "FeatureCollection",
  "features": [
    {
      "type": "Feature",
      "id": "node/4330811029",
      "properties": {
        "timestamp": "2018-04-10T18:59:42Z",
        "version": 2,
        "changeset": 57982654,
        "addr:city": "Resende",
        "addr:street": "Rua Paul Harris",
        "government": "tax",
        "name": "INSS - RESENDE",
        "office": "government",
        "id": "node/4330811029"
      },
      "geometry": {
        "type": "Point",
        "coordinates": [
          -44.4492917,
          -22.4671928
        ]
      }
    },
    {
      "type": "Feature",
      "id": "node/5351067023",
      "properties": {
        "timestamp": "2024-07-30T21:47:02Z",
        "version": 4,
        "changeset": 154624765,
        "addr:postcode": "374666",
        "addr:street": "Rodovia Sebastião Alves do Nascimento",
        "government": "environment",
        "internet_access": "wlan",
        "name": "Posto do Marcão (Posto 3) - PNI",
        "name:en": "Marcão control post",
        "office": "government",
        "opening_hours": "Mo-Su 07:00-18:00",
        "phone": "+55 2433514083",
        "website": "https://pnitatiaia.com.br/",
        "id": "node/5351067023"
      },
      "geometry": {
        "type": "Point",
        "coordinates": [
          -44.7038987,
          -22.3729009
        ]
      }
    },
    {
      "type": "Feature",
      "id": "node/5543601660",
      "properties": {
        "timestamp": "2018-04-10T19:00:26Z",
        "version": 1,
        "changeset": 57982667,
        "government": "tax",
        "name": "Posto da Receita Federal de Resende",
        "office": "government",
        "id": "node/5543601660"
      },
      "geometry": {
        "type": "Point",
        "coordinates": [
          -44.4481423,
          -22.4686685
        ]
      }
    }
  ]
}
