{
  "type": "FeatureCollection",
  "features": [
    {
      "type": "Feature",
      "id": "node/4269354235",
      "properties": {
        "timestamp": "2022-12-02T14:31:59Z",
        "version": 2,
        "changeset": 129646830,
        "name": "Cascata do Moinho",
        "waterway": "waterfall",
        "id": "node/4269354235"
      },
      "geometry": {
        "type": "Point",
        "coordinates": [
          -52.2624751,
          -29.3317713
        ]
      }
    },
    {
      "type": "Feature",
      "id": "node/11933629926",
      "properties": {
        "timestamp": "2024-05-25T19:02:20Z",
        "version": 1,
        "changeset": 151824853,
        "intermittent": "yes",
        "natural": "cliff",
        "waterway": "waterfall",
        "id": "node/11933629926"
      },
      "geometry": {
        "type": "Point",
        "coordinates": [
          -52.177991,
          -29.3386777
        ]
      }
    },
    {
      "type": "Feature",
      "id": "node/11933629979",
      "properties": {
        "timestamp": "2024-05-25T19:02:20Z",
        "version": 1,
        "changeset": 151824853,
        "natural": "cliff",
        "waterway": "waterfall",
        "id": "node/11933629979"
      },
      "geometry": {
        "type": "Point",
        "coordinates": [
          -52.2047125,
          -29.3297233
        ]
      }
    },
    {
      "type": "Feature",
      "id": "node/11933630033",
      "properties": {
        "timestamp": "2024-05-25T19:02:20Z",
        "version": 1,
        "changeset": 151824853,
        "waterway": "waterfall",
        "id": "node/11933630033"
      },
      "geometry": {
        "type": "Point",
        "coordinates": [
          -52.2147989,
          -29.330426
        ]
      }
    }
  ]
}
