{
  "type": "FeatureCollection",
  "features": [
    {
      "type": "Feature",
      "id": "node/4269354235",
      "properties": {
        "timestamp": "2022-12-02T14:31:59Z",
        "version": 2,
        "changeset": 129646830,
        "name": "Cascata do Moinho",
        "waterway": "waterfall",
        "id": "node/4269354235"
      },
      "geometry": {
        "type": "Point",
        "coordinates": [
          -52.2624751,
          -29.3317713
        ]
      }
    }
  ]
}
