{
  "type": "FeatureCollection",
  "features": [
    {
      "type": "Feature",
      "id": "node/6073306935",
      "properties": {
        "timestamp": "2018-11-19T13:14:53Z",
        "version": 1,
        "changeset": 64656403,
        "name": "Hotel União",
        "tourism": "hotel",
        "id": "node/6073306935"
      },
      "geometry": {
        "type": "Point",
        "coordinates": [
          -51.3550353,
          -29.5887643
        ]
      }
    },
    {
      "type": "Feature",
      "id": "node/6073306936",
      "properties": {
        "timestamp": "2018-11-19T13:14:53Z",
        "version": 1,
        "changeset": 64656403,
        "name": "Tratoria Di Variani",
        "tourism": "hotel",
        "id": "node/6073306936"
      },
      "geometry": {
        "type": "Point",
        "coordinates": [
          -51.3665065,
          -29.5837461
        ]
      }
    },
    {
      "type": "Feature",
      "id": "node/9798757654",
      "properties": {
        "timestamp": "2022-06-06T13:45:39Z",
        "version": 1,
        "changeset": 122027092,
        "name": "Hotel Irmãos Variani",
        "tourism": "hotel",
        "id": "node/9798757654"
      },
      "geometry": {
        "type": "Point",
        "coordinates": [
          -51.3534389,
          -29.5899089
        ]
      }
    }
  ]
}
