{
  "type": "FeatureCollection",
  "features": [
    {
      "type": "Feature",
      "id": "node/11411038734",
      "properties": {
        "timestamp": "2023-12-12T00:56:24Z",
        "version": 1,
        "changeset": 145018733,
        "amenity": "veterinary",
        "fixme": "descriptive name;Presente nas Cartas Topográficas do E.B. e visível por imagem aérea, porém pode precisar confirmação extra",
        "name": "Hospital Veterinário",
        "source": "Cartas Topográficas do Exército Brasileiro",
        "id": "node/11411038734"
      },
      "geometry": {
        "type": "Point",
        "coordinates": [
          -51.3641819,
          -29.6261781
        ]
      }
    }
  ]
}
