{
  "type": "FeatureCollection",
  "features": [
    {
      "type": "Feature",
      "id": "node/5284026741",
      "properties": {
        "timestamp": "2017-12-14T13:59:08Z",
        "version": 1,
        "changeset": 54625145,
        "historic": "memorial",
        "memorial": "war_memorial",
        "name": "Memorial dos Pracinhas Fidelenses",
        "id": "node/5284026741"
      },
      "geometry": {
        "type": "Point",
        "coordinates": [
          -41.7465596,
          -21.6458863
        ]
      }
    },
    {
      "type": "Feature",
      "id": "node/5284026742",
      "properties": {
        "timestamp": "2023-06-13T15:06:33Z",
        "version": 2,
        "changeset": 137290766,
        "historic": "memorial",
        "memorial": "statue",
        "name": "Memorial dos Fundadores",
        "id": "node/5284026742"
      },
      "geometry": {
        "type": "Point",
        "coordinates": [
          -41.7464253,
          -21.6462874
        ]
      }
    }
  ]
}
