{
  "type": "FeatureCollection",
  "features": [
    {
      "type": "Feature",
      "id": "node/9220057067",
      "properties": {
        "timestamp": "2021-11-03T01:25:29Z",
        "version": 1,
        "changeset": 113307637,
        "addr:housenumber": "1035",
        "addr:street": "Avenida Emygdio Maia Santos",
        "amenity": "university",
        "name": "Faculdade Censupeg",
        "id": "node/9220057067"
      },
      "geometry": {
        "type": "Point",
        "coordinates": [
          -41.764962,
          -21.6332437
        ]
      }
    }
  ]
}
