{
  "type": "FeatureCollection",
  "features": [
    {
      "type": "Feature",
      "id": "node/3489601331",
      "properties": {
        "timestamp": "2022-10-22T17:47:07Z",
        "version": 5,
        "changeset": 127932636,
        "name": "Cachoeira da Cascata ou Macapá",
        "waterway": "waterfall",
        "id": "node/3489601331"
      },
      "geometry": {
        "type": "Point",
        "coordinates": [
          -41.9316598,
          -21.8702889
        ]
      }
    },
    {
      "type": "Feature",
      "id": "node/3510598056",
      "properties": {
        "timestamp": "2015-05-22T20:41:29Z",
        "version": 2,
        "changeset": 31383400,
        "name": "Poço",
        "waterway": "waterfall",
        "id": "node/3510598056"
      },
      "geometry": {
        "type": "Point",
        "coordinates": [
          -41.9148278,
          -21.8511202
        ]
      }
    }
  ]
}
