{
  "type": "FeatureCollection",
  "features": [
    {
      "type": "Feature",
      "id": "node/9127889379",
      "properties": {
        "timestamp": "2022-06-13T23:14:38Z",
        "version": 2,
        "changeset": 122346592,
        "access": "yes",
        "addr:city": "Botuverá",
        "addr:street": "Rua João Morelli",
        "amenity": "clinic",
        "brand": "Sistema Único de Saúde",
        "brand:short": "SUS",
        "emergency": "no",
        "healthcare": "clinic",
        "loc_name": "Posto de Saúde Willy Francisco Maestri",
        "name": "Unidade de Saúde da Família Willy Francisco Maestri",
        "operator": "Prefeitura Municipal de Botuverá",
        "operator:type": "public",
        "short_name": "USF Willy Francisco Maestri",
        "id": "node/9127889379"
      },
      "geometry": {
        "type": "Point",
        "coordinates": [
          -49.0728089,
          -27.1974856
        ]
      }
    },
    {
      "type": "Feature",
      "id": "node/9815808652",
      "properties": {
        "timestamp": "2022-06-13T21:59:34Z",
        "version": 1,
        "changeset": 122345201,
        "access": "yes",
        "amenity": "clinic",
        "brand": "Sistema Único de Saúde",
        "brand:short": "SUS",
        "healthcare": "clinic",
        "loc_name": "Posto de Saúde Vereador Onório Comandolli",
        "name": "Unidade de Estratégia de Saúde da Família Vereador Onório Comandolli",
        "opening_hours": "Mo-Fr 08:00-12:00,13:00-17:00",
        "operator": "Prefeitura Municipal de Botuverá",
        "operator:type": "public",
        "short_name": "ESF Ver. Onório Comandolli",
        "id": "node/9815808652"
      },
      "geometry": {
        "type": "Point",
        "coordinates": [
          -49.1509518,
          -27.2027227
        ]
      }
    }
  ]
}
