{
  "type": "FeatureCollection",
  "features": [
    {
      "type": "Feature",
      "id": "node/10801699874",
      "properties": {
        "timestamp": "2023-04-11T13:29:56Z",
        "version": 1,
        "changeset": 134774499,
        "government": "yes",
        "name": "Defensoria Pública da Bahia",
        "office": "government",
        "id": "node/10801699874"
      },
      "geometry": {
        "type": "Point",
        "coordinates": [
          -38.3248639,
          -12.8935537
        ]
      }
    }
  ]
}
