{
  "type": "FeatureCollection",
  "features": [
    {
      "type": "Feature",
      "id": "node/10801699873",
      "properties": {
        "timestamp": "2023-04-11T13:29:56Z",
        "version": 1,
        "changeset": 134774499,
        "amenity": "social_facility",
        "name": "Centro de Referência Especializada da Assistência Social",
        "short_name": "CREAS",
        "id": "node/10801699873"
      },
      "geometry": {
        "type": "Point",
        "coordinates": [
          -38.3256672,
          -12.8955491
        ]
      }
    }
  ]
}
