{
  "type": "FeatureCollection",
  "features": [
    {
      "type": "Feature",
      "id": "node/4791599828",
      "properties": {
        "timestamp": "2017-08-18T11:18:36Z",
        "version": 2,
        "changeset": 51230367,
        "name": "Hotel Termas do Rio do Pouso",
        "tourism": "hotel",
        "id": "node/4791599828"
      },
      "geometry": {
        "type": "Point",
        "coordinates": [
          -49.1071488,
          -28.4141911
        ]
      }
    },
    {
      "type": "Feature",
      "id": "node/7190464828",
      "properties": {
        "timestamp": "2020-02-06T10:47:51Z",
        "version": 1,
        "changeset": 80636214,
        "addr:city": "Tubarão",
        "addr:housenumber": "1663",
        "addr:postcode": "88705-000",
        "addr:street": "Avenida José Acácio Moreira",
        "addr:suburb": "Centro",
        "name": "OK inn Hotel Express",
        "tourism": "hotel",
        "id": "node/7190464828"
      },
      "geometry": {
        "type": "Point",
        "coordinates": [
          -49.0105229,
          -28.4807725
        ]
      }
    }
  ]
}
