{
  "type": "FeatureCollection",
  "features": [
    {
      "type": "Feature",
      "id": "node/4643053556",
      "properties": {
        "timestamp": "2019-01-09T00:53:58Z",
        "version": 3,
        "changeset": 66145224,
        "amenity": "clinic",
        "name": "Secretaria Municipal de Saúde",
        "id": "node/4643053556"
      },
      "geometry": {
        "type": "Point",
        "coordinates": [
          -44.999938,
          -21.2263862
        ]
      }
    },
    {
      "type": "Feature",
      "id": "node/4687663764",
      "properties": {
        "timestamp": "2019-11-07T18:10:36Z",
        "version": 2,
        "changeset": 76771957,
        "addr:city": "Lavras",
        "addr:postcode": "37200-000",
        "addr:street": "Rua Antônio Lúcio Ferreira",
        "addr:suburb": "Dona Wanda",
        "amenity": "clinic",
        "healthcare": "clinic",
        "name": "PSF 17 Dona Wanda",
        "opening_hours": "Mo-Fr 08:00-17:00",
        "operator": "Prefeitura",
        "operator:type": "public",
        "wheelchair": "yes",
        "id": "node/4687663764"
      },
      "geometry": {
        "type": "Point",
        "coordinates": [
          -44.9825746,
          -21.2404193
        ]
      }
    }
  ]
}
