{
  "type": "FeatureCollection",
  "features": [
    {
      "type": "Feature",
      "id": "node/4187331449",
      "properties": {
        "timestamp": "2016-05-15T13:57:20Z",
        "version": 1,
        "changeset": 39331576,
        "amenity": "social_facility",
        "name": "Casa do Vovô",
        "social_facility": "group_home",
        "social_facility:for": "senior",
        "id": "node/4187331449"
      },
      "geometry": {
        "type": "Point",
        "coordinates": [
          -44.9906305,
          -21.265478
        ]
      }
    },
    {
      "type": "Feature",
      "id": "node/8672069206",
      "properties": {
        "timestamp": "2021-04-30T01:48:42Z",
        "version": 2,
        "changeset": 103874765,
        "amenity": "social_facility",
        "name": "CRAS",
        "id": "node/8672069206"
      },
      "geometry": {
        "type": "Point",
        "coordinates": [
          -44.9982058,
          -21.2202191
        ]
      }
    }
  ]
}
