{
  "type": "FeatureCollection",
  "features": [
    {
      "type": "Feature",
      "id": "node/10881110070",
      "properties": {
        "timestamp": "2023-05-09T14:25:24Z",
        "version": 1,
        "changeset": 135898692,
        "addr:city": "Laranja da Terra",
        "addr:postcode": "29615-000",
        "addr:street": "Avenida Carlos Stabenow",
        "addr:suburb": "Centro",
        "amenity": "pharmacy",
        "healthcare": "pharmacy",
        "name": "Farmácia São João",
        "id": "node/10881110070"
      },
      "geometry": {
        "type": "Point",
        "coordinates": [
          -41.056901,
          -19.9009919
        ]
      }
    }
  ]
}
