{
  "type": "FeatureCollection",
  "features": [
    {
      "type": "Feature",
      "id": "node/6115538585",
      "properties": {
        "timestamp": "2024-05-01T21:12:23Z",
        "version": 2,
        "changeset": 150769488,
        "amenity": "dentist",
        "healthcare": "dentist",
        "name": "Clinicodonto Assistência Odontológica",
        "id": "node/6115538585"
      },
      "geometry": {
        "type": "Point",
        "coordinates": [
          -50.8784688,
          -29.374376
        ]
      }
    }
  ]
}
