{
  "type": "FeatureCollection",
  "features": [
    {
      "type": "Feature",
      "id": "node/6115538585",
      "properties": {
        "timestamp": "2018-12-04T11:48:15Z",
        "version": 1,
        "changeset": 65157415,
        "amenity": "dentist",
        "name": "Clinicodonto Assistência Odontológica",
        "id": "node/6115538585"
      },
      "geometry": {
        "type": "Point",
        "coordinates": [
          -50.8784688,
          -29.374376
        ]
      }
    }
  ]
}
