{
  "type": "FeatureCollection",
  "features": [
    {
      "type": "Feature",
      "id": "node/10811549461",
      "properties": {
        "timestamp": "2023-04-14T14:40:08Z",
        "version": 1,
        "changeset": 134906588,
        "historic": "memorial",
        "material": "stone",
        "memorial": "sculpture",
        "name": "Memorial da Paz Pe. Eduardo  Pegoraro",
        "id": "node/10811549461"
      },
      "geometry": {
        "type": "Point",
        "coordinates": [
          -52.8707162,
          -28.6262072
        ]
      }
    }
  ]
}
