{
  "type": "FeatureCollection",
  "features": [
    {
      "type": "Feature",
      "id": "node/12625789827",
      "properties": {
        "timestamp": "2025-02-28T14:15:25Z",
        "version": 1,
        "changeset": 163054613,
        "amenity": "hospital",
        "emergency": "yes",
        "healthcare": "hospital",
        "name": "HMSS - Hospital Municipal Senhora Santana",
        "operator": "Secretaria Municipal de Saúde",
        "operator:type": "public",
        "wheelchair": "yes",
        "id": "node/12625789827"
      },
      "geometry": {
        "type": "Point",
        "coordinates": [
          -39.4985708,
          -10.669107
        ]
      }
    }
  ]
}
