{
  "type": "FeatureCollection",
  "features": [
    {
      "type": "Feature",
      "id": "node/3899128471",
      "properties": {
        "timestamp": "2019-09-29T19:36:03Z",
        "version": 2,
        "changeset": 75070789,
        "amenity": "cinema",
        "name": "Cine Clube Sétima Arnte de Pederneiras",
        "id": "node/3899128471"
      },
      "geometry": {
        "type": "Point",
        "coordinates": [
          -48.7761651,
          -22.3525931
        ]
      }
    }
  ]
}
