{
  "type": "FeatureCollection",
  "features": [
    {
      "type": "Feature",
      "id": "node/767942055",
      "properties": {
        "timestamp": "2010-06-09T14:55:13Z",
        "version": 1,
        "changeset": 4945888,
        "name": "Pousada Vitória",
        "tourism": "guest_house",
        "id": "node/767942055"
      },
      "geometry": {
        "type": "Point",
        "coordinates": [
          -44.3035868,
          -2.5313573
        ]
      }
    },
    {
      "type": "Feature",
      "id": "node/767945568",
      "properties": {
        "timestamp": "2010-06-09T15:01:57Z",
        "version": 1,
        "changeset": 4945951,
        "name": "Pousada Colonial",
        "tourism": "guest_house",
        "id": "node/767945568"
      },
      "geometry": {
        "type": "Point",
        "coordinates": [
          -44.3036125,
          -2.5318033
        ]
      }
    },
    {
      "type": "Feature",
      "id": "node/4198954890",
      "properties": {
        "timestamp": "2019-03-23T02:56:10Z",
        "version": 2,
        "changeset": 68433329,
        "addr:housenumber": "30",
        "addr:street": "Av da universidade",
        "name": "Casa Cohafuma",
        "tourism": "guest_house",
        "id": "node/4198954890"
      },
      "geometry": {
        "type": "Point",
        "coordinates": [
          -44.2659931,
          -2.5074622
        ]
      }
    }
  ]
}
