{
  "type": "FeatureCollection",
  "features": [
    {
      "type": "Feature",
      "id": "node/12075302893",
      "properties": {
        "timestamp": "2024-07-26T13:41:32Z",
        "version": 1,
        "changeset": 154443810,
        "amenity": "veterinary",
        "name": "Saúde Animal - Assistência Veterinária",
        "id": "node/12075302893"
      },
      "geometry": {
        "type": "Point",
        "coordinates": [
          -54.2472378,
          -25.0938442
        ]
      }
    },
    {
      "type": "Feature",
      "id": "node/12075666762",
      "properties": {
        "timestamp": "2024-07-26T17:26:37Z",
        "version": 1,
        "changeset": 154453782,
        "amenity": "veterinary",
        "name": "VetClinic - Clinica Veterinária",
        "id": "node/12075666762"
      },
      "geometry": {
        "type": "Point",
        "coordinates": [
          -54.2506626,
          -25.0923841
        ]
      }
    }
  ]
}
