{
  "type": "FeatureCollection",
  "features": [
    {
      "type": "Feature",
      "id": "node/2969415992",
      "properties": {
        "timestamp": "2021-02-08T05:11:02Z",
        "version": 3,
        "changeset": 98879136,
        "amenity": "hospital",
        "healthcare": "hospital",
        "name": "Hospital Doutor Aurélio",
        "id": "node/2969415992"
      },
      "geometry": {
        "type": "Point",
        "coordinates": [
          -53.2556679,
          -24.5287251
        ]
      }
    }
  ]
}
