{
  "type": "FeatureCollection",
  "features": [
    {
      "type": "Feature",
      "id": "node/4675771292",
      "properties": {
        "timestamp": "2017-11-23T18:43:42Z",
        "version": 2,
        "changeset": 54032972,
        "amenity": "social_facility",
        "name": "Assistência Social",
        "social_facility": "outreach",
        "id": "node/4675771292"
      },
      "geometry": {
        "type": "Point",
        "coordinates": [
          -53.252685,
          -24.5274433
        ]
      }
    }
  ]
}
