{
  "type": "FeatureCollection",
  "features": [
    {
      "type": "Feature",
      "id": "node/2690700190",
      "properties": {
        "timestamp": "2024-02-21T14:29:06Z",
        "version": 2,
        "changeset": 147735530,
        "name": "Cascata Taperão",
        "waterway": "waterfall",
        "id": "node/2690700190"
      },
      "geometry": {
        "type": "Point",
        "coordinates": [
          -49.2520445,
          -20.99138
        ]
      }
    },
    {
      "type": "Feature",
      "id": "node/10152869489",
      "properties": {
        "timestamp": "2022-11-02T23:46:30Z",
        "version": 1,
        "changeset": 128414129,
        "waterway": "waterfall",
        "id": "node/10152869489"
      },
      "geometry": {
        "type": "Point",
        "coordinates": [
          -49.1638463,
          -21.1806788
        ]
      }
    },
    {
      "type": "Feature",
      "id": "node/10152869490",
      "properties": {
        "timestamp": "2022-11-02T23:46:30Z",
        "version": 1,
        "changeset": 128414129,
        "waterway": "waterfall",
        "id": "node/10152869490"
      },
      "geometry": {
        "type": "Point",
        "coordinates": [
          -49.1674159,
          -21.178578
        ]
      }
    },
    {
      "type": "Feature",
      "id": "node/11378495847",
      "properties": {
        "timestamp": "2023-11-26T21:36:46Z",
        "version": 2,
        "changeset": 144486306,
        "waterway": "waterfall",
        "id": "node/11378495847"
      },
      "geometry": {
        "type": "Point",
        "coordinates": [
          -49.2209527,
          -21.0362842
        ]
      }
    }
  ]
}
