{
  "type": "FeatureCollection",
  "features": [
    {
      "type": "Feature",
      "id": "node/10608257815",
      "properties": {
        "timestamp": "2023-02-05T14:54:03Z",
        "version": 1,
        "changeset": 132111829,
        "addr:city": "Lajedão",
        "addr:housenumber": "304",
        "addr:postcode": "45950-000",
        "addr:street": "Avenida Claudemiro Rocha Passos",
        "addr:suburb": "Centro",
        "amenity": "pharmacy",
        "drive_through": "yes",
        "healthcare": "pharmacy",
        "name": "Farmácia do Trabalhador",
        "operator": "Murilo Santos Porto",
        "phone": "+55 73 98152 7592",
        "id": "node/10608257815"
      },
      "geometry": {
        "type": "Point",
        "coordinates": [
          -40.3435471,
          -17.6157548
        ]
      }
    }
  ]
}
