{
  "type": "FeatureCollection",
  "features": [
    {
      "type": "Feature",
      "id": "node/1693148070",
      "properties": {
        "timestamp": "2012-11-21T12:23:57Z",
        "version": 2,
        "changeset": 13957932,
        "amenity": "school",
        "name": "Colégio Estadual Rachel de Queiroz",
        "id": "node/1693148070"
      },
      "geometry": {
        "type": "Point",
        "coordinates": [
          -53.366989,
          -23.4075692
        ]
      }
    },
    {
      "type": "Feature",
      "id": "node/1693148122",
      "properties": {
        "timestamp": "2012-11-21T12:23:57Z",
        "version": 2,
        "changeset": 13957932,
        "amenity": "school",
        "name": "Escola Municipal Walter Bergman",
        "id": "node/1693148122"
      },
      "geometry": {
        "type": "Point",
        "coordinates": [
          -53.3716346,
          -23.4134421
        ]
      }
    }
  ]
}
