{
  "type": "FeatureCollection",
  "features": [
    {
      "type": "Feature",
      "id": "node/4264336148",
      "properties": {
        "timestamp": "2020-04-29T01:42:40Z",
        "version": 2,
        "changeset": 84298719,
        "amenity": "pharmacy",
        "name": "Farmácia Maciel",
        "id": "node/4264336148"
      },
      "geometry": {
        "type": "Point",
        "coordinates": [
          -40.7381836,
          -18.9833174
        ]
      }
    }
  ]
}
