{
  "type": "FeatureCollection",
  "features": [
    {
      "type": "Feature",
      "id": "node/4042057792",
      "properties": {
        "timestamp": "2016-03-05T17:42:06Z",
        "version": 1,
        "changeset": 37631742,
        "name": "Pousada",
        "tourism": "hotel",
        "id": "node/4042057792"
      },
      "geometry": {
        "type": "Point",
        "coordinates": [
          -40.5440413,
          -3.5854865
        ]
      }
    }
  ]
}
