{
  "type": "FeatureCollection",
  "features": [
    {
      "type": "Feature",
      "id": "node/4042057225",
      "properties": {
        "timestamp": "2016-03-05T17:42:03Z",
        "version": 1,
        "changeset": 37631742,
        "amenity": "pharmacy",
        "name": "Farmácia Faustina",
        "id": "node/4042057225"
      },
      "geometry": {
        "type": "Point",
        "coordinates": [
          -40.5458971,
          -3.5867747
        ]
      }
    },
    {
      "type": "Feature",
      "id": "node/4042057226",
      "properties": {
        "timestamp": "2016-03-05T17:42:04Z",
        "version": 1,
        "changeset": 37631742,
        "amenity": "pharmacy",
        "name": "Farmácia Mais Saúde",
        "id": "node/4042057226"
      },
      "geometry": {
        "type": "Point",
        "coordinates": [
          -40.5457539,
          -3.5870307
        ]
      }
    },
    {
      "type": "Feature",
      "id": "node/4042057259",
      "properties": {
        "timestamp": "2016-03-05T17:42:05Z",
        "version": 1,
        "changeset": 37631742,
        "amenity": "pharmacy",
        "name": "Farmácia Nossa Senhora de Fátima",
        "id": "node/4042057259"
      },
      "geometry": {
        "type": "Point",
        "coordinates": [
          -40.545137,
          -3.586668
        ]
      }
    }
  ]
}
