{
  "type": "FeatureCollection",
  "features": [
    {
      "type": "Feature",
      "id": "node/6218472100",
      "properties": {
        "timestamp": "2019-01-18T11:38:32Z",
        "version": 1,
        "changeset": 66423639,
        "amenity": "pharmacy",
        "dispensing": "yes",
        "healthcare": "pharmacy",
        "name": "Farma Vida",
        "id": "node/6218472100"
      },
      "geometry": {
        "type": "Point",
        "coordinates": [
          -45.8866394,
          -23.3981583
        ]
      }
    }
  ]
}
