{
  "type": "FeatureCollection",
  "features": [
    {
      "type": "Feature",
      "id": "node/6900318687",
      "properties": {
        "timestamp": "2019-10-20T14:29:48Z",
        "version": 1,
        "changeset": 75955586,
        "name": "Hotel Montanhês",
        "tourism": "hotel",
        "id": "node/6900318687"
      },
      "geometry": {
        "type": "Point",
        "coordinates": [
          -43.480482,
          -22.4441234
        ]
      }
    }
  ]
}
