{
  "type": "FeatureCollection",
  "features": [
    {
      "type": "Feature",
      "id": "node/10828041028",
      "properties": {
        "timestamp": "2023-04-20T20:57:25Z",
        "version": 1,
        "changeset": 135169014,
        "amenity": "dentist",
        "healthcare": "dentist",
        "name": "Conquist Odontologia",
        "id": "node/10828041028"
      },
      "geometry": {
        "type": "Point",
        "coordinates": [
          -48.8997861,
          -27.1442583
        ]
      }
    }
  ]
}
