{
  "type": "FeatureCollection",
  "features": [
    {
      "type": "Feature",
      "id": "node/5537090883",
      "properties": {
        "timestamp": "2018-04-08T05:17:06Z",
        "version": 1,
        "changeset": 57905024,
        "historic": "memorial",
        "id": "node/5537090883"
      },
      "geometry": {
        "type": "Point",
        "coordinates": [
          -48.9067353,
          -27.0954984
        ]
      }
    },
    {
      "type": "Feature",
      "id": "node/5537091279",
      "properties": {
        "timestamp": "2018-04-08T05:17:10Z",
        "version": 1,
        "changeset": 57905024,
        "historic": "memorial",
        "id": "node/5537091279"
      },
      "geometry": {
        "type": "Point",
        "coordinates": [
          -48.9120924,
          -27.102045
        ]
      }
    },
    {
      "type": "Feature",
      "id": "node/6896666274",
      "properties": {
        "timestamp": "2019-10-18T18:48:58Z",
        "version": 1,
        "changeset": 75910215,
        "historic": "memorial",
        "memorial": "plaque",
        "id": "node/6896666274"
      },
      "geometry": {
        "type": "Point",
        "coordinates": [
          -48.8835361,
          -27.0689411
        ]
      }
    },
    {
      "type": "Feature",
      "id": "node/9306852946",
      "properties": {
        "timestamp": "2021-12-02T17:12:44Z",
        "version": 1,
        "changeset": 114491457,
        "historic": "memorial",
        "memorial": "statue",
        "name": "Carlos Renaux",
        "start_date": "1951-05-01",
        "wikipedia": "pt:Carlos Renaux",
        "id": "node/9306852946"
      },
      "geometry": {
        "type": "Point",
        "coordinates": [
          -48.9170042,
          -27.0988473
        ]
      }
    }
  ]
}
