{
  "type": "FeatureCollection",
  "features": [
    {
      "type": "Feature",
      "id": "node/4143214490",
      "properties": {
        "timestamp": "2016-04-23T18:24:08Z",
        "version": 1,
        "changeset": 38818558,
        "name": "Pousada dos viajantes",
        "tourism": "guest_house",
        "id": "node/4143214490"
      },
      "geometry": {
        "type": "Point",
        "coordinates": [
          -55.6976792,
          -22.5593325
        ]
      }
    }
  ]
}
