{
  "type": "FeatureCollection",
  "features": [
    {
      "type": "Feature",
      "id": "node/5610393021",
      "properties": {
        "timestamp": "2018-05-10T22:57:24Z",
        "version": 1,
        "changeset": 58863602,
        "name": "Pousada Shalom",
        "tourism": "guest_house",
        "id": "node/5610393021"
      },
      "geometry": {
        "type": "Point",
        "coordinates": [
          -38.5030003,
          -7.5537225
        ]
      }
    }
  ]
}
