{
  "type": "FeatureCollection",
  "features": [
    {
      "type": "Feature",
      "id": "node/4471536315",
      "properties": {
        "timestamp": "2021-01-03T23:34:17Z",
        "version": 2,
        "changeset": 96868087,
        "amenity": "pharmacy",
        "healthcare": "pharmacy",
        "name": "Big Ben",
        "name:pt": "Big Ben",
        "id": "node/4471536315"
      },
      "geometry": {
        "type": "Point",
        "coordinates": [
          -47.9194153,
          -1.2965464
        ]
      }
    }
  ]
}
