{
  "type": "FeatureCollection",
  "features": [
    {
      "type": "Feature",
      "id": "node/10698119630",
      "properties": {
        "timestamp": "2023-02-27T21:25:19Z",
        "version": 1,
        "changeset": 133104673,
        "name": "Atelier CHICO SANTEIRO",
        "tourism": "gallery",
        "id": "node/10698119630"
      },
      "geometry": {
        "type": "Point",
        "coordinates": [
          -38.0840162,
          -7.8504926
        ]
      }
    }
  ]
}
