{
  "type": "FeatureCollection",
  "features": [
    {
      "type": "Feature",
      "id": "node/6744800485",
      "properties": {
        "timestamp": "2019-09-07T21:08:51Z",
        "version": 2,
        "changeset": 74214617,
        "addr:housenumber": "249",
        "addr:postcode": "15047-220",
        "addr:street": "Rua Eduardo Barbour",
        "amenity": "nursing_home",
        "id": "node/6744800485"
      },
      "geometry": {
        "type": "Point",
        "coordinates": [
          -49.4073529,
          -20.7496582
        ]
      }
    }
  ]
}
