{
  "type": "FeatureCollection",
  "features": [
    {
      "type": "Feature",
      "id": "node/2312040787",
      "properties": {
        "timestamp": "2013-05-19T21:41:48Z",
        "version": 1,
        "changeset": 16200370,
        "name": "Hotel Fazenda Pedra do Sino",
        "source": "survey",
        "tourism": "hotel",
        "id": "node/2312040787"
      },
      "geometry": {
        "type": "Point",
        "coordinates": [
          -43.814103,
          -20.8830227
        ]
      }
    }
  ]
}
