{
  "type": "FeatureCollection",
  "features": [
    {
      "type": "Feature",
      "id": "node/2312040787",
      "properties": {
        "timestamp": "2013-05-19T21:41:48Z",
        "version": 1,
        "changeset": 16200370,
        "name": "Hotel Fazenda Pedra do Sino",
        "source": "survey",
        "tourism": "hotel",
        "id": "node/2312040787"
      },
      "geometry": {
        "type": "Point",
        "coordinates": [
          -43.814103,
          -20.8830227
        ]
      }
    },
    {
      "type": "Feature",
      "id": "node/12372576498",
      "properties": {
        "timestamp": "2024-11-25T00:37:02Z",
        "version": 1,
        "changeset": 159553824,
        "addr:city": "Carandaí",
        "addr:housenumber": "135",
        "addr:postcode": "36280-000",
        "addr:street": "Rua Presidente Vargas",
        "addr:suburb": "Centro",
        "name": "Hotel Carajás",
        "tourism": "hotel",
        "id": "node/12372576498"
      },
      "geometry": {
        "type": "Point",
        "coordinates": [
          -43.8085844,
          -20.9521513
        ]
      }
    }
  ]
}
