{
  "type": "FeatureCollection",
  "features": [
    {
      "type": "Feature",
      "id": "node/6381413410",
      "properties": {
        "timestamp": "2019-04-03T17:34:16Z",
        "version": 1,
        "changeset": 68850101,
        "amenity": "veterinary",
        "name": "Clínica Veterinaria Iguaba",
        "id": "node/6381413410"
      },
      "geometry": {
        "type": "Point",
        "coordinates": [
          -42.2191776,
          -22.8393363
        ]
      }
    }
  ]
}
