{
  "type": "FeatureCollection",
  "features": [
    {
      "type": "Feature",
      "id": "node/7721140907",
      "properties": {
        "timestamp": "2020-07-16T14:02:36Z",
        "version": 1,
        "changeset": 88092131,
        "addr:city": "Areia Branca",
        "addr:housenumber": "26",
        "addr:postcode": "59655-000",
        "addr:street": "Rua Coronel Fausto",
        "addr:suburb": "Centro",
        "amenity": "dentist",
        "healthcare": "dentist",
        "name": "Clinica Vivare",
        "operator": "Privado",
        "id": "node/7721140907"
      },
      "geometry": {
        "type": "Point",
        "coordinates": [
          -37.1359858,
          -4.9576396
        ]
      }
    },
    {
      "type": "Feature",
      "id": "node/7721232937",
      "properties": {
        "timestamp": "2020-07-16T14:20:04Z",
        "version": 1,
        "changeset": 88092809,
        "addr:city": "Areia Branca",
        "addr:housenumber": "71",
        "addr:postcode": "59655-000",
        "addr:street": "Rua Coronel Fausto",
        "addr:suburb": "Centro",
        "amenity": "dentist",
        "healthcare": "dentist",
        "name": "Saude Odonto",
        "id": "node/7721232937"
      },
      "geometry": {
        "type": "Point",
        "coordinates": [
          -37.1363241,
          -4.9572141
        ]
      }
    }
  ]
}
