{
  "type": "FeatureCollection",
  "features": [
    {
      "type": "Feature",
      "id": "node/7201421677",
      "properties": {
        "timestamp": "2020-02-11T18:05:53Z",
        "version": 2,
        "changeset": 80864467,
        "access": "yes",
        "addr:city": "Palhoça",
        "addr:postcode": "88137-270",
        "addr:street": "Rua da Universidade",
        "addr:suburb": "Pedra Branca",
        "amenity": "toilets",
        "changing_table": "yes",
        "wheelchair": "yes",
        "id": "node/7201421677"
      },
      "geometry": {
        "type": "Point",
        "coordinates": [
          -48.6777336,
          -27.6229242
        ]
      }
    }
  ]
}
