{
  "type": "FeatureCollection",
  "features": [
    {
      "type": "Feature",
      "id": "node/9588321140",
      "properties": {
        "timestamp": "2022-03-18T17:47:09Z",
        "version": 1,
        "changeset": 118642379,
        "addr:city": "Marilândia",
        "addr:postcode": "29725-000",
        "addr:suburb": "Santa Cecília",
        "email": "fem@incaper.es.gov.br",
        "government": "government",
        "name": "Fazenda Experimental de Marilândia - Fem",
        "office": "government",
        "operator": "Instituto Capixaba de Pesquisa, Assistência Técnica e Extensão Rural - Incaper",
        "phone": "+55 27 3724 1182",
        "website": "https://incaper.es.gov.br/fazendas",
        "id": "node/9588321140"
      },
      "geometry": {
        "type": "Point",
        "coordinates": [
          -40.5422638,
          -19.4070856
        ]
      }
    }
  ]
}
