{
  "type": "FeatureCollection",
  "features": [
    {
      "type": "Feature",
      "id": "node/3497472342",
      "properties": {
        "timestamp": "2015-05-04T17:46:23Z",
        "version": 1,
        "changeset": 30786131,
        "name": "Hotel Cachoeira do Gloria",
        "tourism": "hotel",
        "id": "node/3497472342"
      },
      "geometry": {
        "type": "Point",
        "coordinates": [
          -42.2997627,
          -20.7728729
        ]
      }
    }
  ]
}
