{
  "type": "FeatureCollection",
  "features": [
    {
      "type": "Feature",
      "id": "node/5358071560",
      "properties": {
        "timestamp": "2018-02-12T18:58:52Z",
        "version": 2,
        "changeset": 56302821,
        "addr:city": "Armação dos Búzios",
        "addr:housenumber": "2333",
        "addr:street": "Avenida José Bento Ribeiro Dantas",
        "addr:suburb": "Manguinhos",
        "amenity": "veterinary",
        "name": "Veterinária Búzios",
        "phone": "+55 (22) 2623-1564",
        "id": "node/5358071560"
      },
      "geometry": {
        "type": "Point",
        "coordinates": [
          -41.9130009,
          -22.7720946
        ]
      }
    },
    {
      "type": "Feature",
      "id": "node/6703576295",
      "properties": {
        "timestamp": "2019-08-12T16:18:43Z",
        "version": 2,
        "changeset": 73275744,
        "amenity": "veterinary",
        "name": "Veterinária Sheepdog",
        "id": "node/6703576295"
      },
      "geometry": {
        "type": "Point",
        "coordinates": [
          -41.970802,
          -22.7416992
        ]
      }
    },
    {
      "type": "Feature",
      "id": "node/7905885585",
      "properties": {
        "timestamp": "2020-09-14T16:40:21Z",
        "version": 1,
        "changeset": 90876666,
        "addr:street": "Avenida José Bento Ribeiro Dantas",
        "amenity": "veterinary",
        "name": "Animal Clinic",
        "phone": "+552226233340",
        "id": "node/7905885585"
      },
      "geometry": {
        "type": "Point",
        "coordinates": [
          -41.9221485,
          -22.7742372
        ]
      }
    }
  ]
}
