{
  "type": "FeatureCollection",
  "features": [
    {
      "type": "Feature",
      "id": "node/5241606121",
      "properties": {
        "timestamp": "2017-11-21T19:03:57Z",
        "version": 1,
        "changeset": 53983665,
        "amenity": "pharmacy",
        "name": "Farmácia Sta Teresinha",
        "id": "node/5241606121"
      },
      "geometry": {
        "type": "Point",
        "coordinates": [
          -37.4444897,
          -7.0853379
        ]
      }
    }
  ]
}
