{
  "type": "FeatureCollection",
  "features": [
    {
      "type": "Feature",
      "id": "node/5292013421",
      "properties": {
        "timestamp": "2017-12-18T17:10:59Z",
        "version": 1,
        "changeset": 54736700,
        "historic": "memorial",
        "name": "Quadra 110 norte",
        "id": "node/5292013421"
      },
      "geometry": {
        "type": "Point",
        "coordinates": [
          -48.3106644,
          -10.1806561
        ]
      }
    },
    {
      "type": "Feature",
      "id": "node/10245481167",
      "properties": {
        "timestamp": "2022-12-07T21:23:36Z",
        "version": 1,
        "changeset": 129836485,
        "historic": "memorial",
        "name": "Memorial Para Sempre Luz (Mortos pela COVID-19)",
        "id": "node/10245481167"
      },
      "geometry": {
        "type": "Point",
        "coordinates": [
          -48.3320937,
          -10.1991165
        ]
      }
    }
  ]
}
