{
  "type": "FeatureCollection",
  "features": [
    {
      "type": "Feature",
      "id": "node/2189745375",
      "properties": {
        "timestamp": "2018-10-30T03:40:46Z",
        "version": 4,
        "changeset": 63997808,
        "addr:city": "Custódia",
        "addr:housenumber": "1787",
        "addr:postcode": "56640-000",
        "addr:street": "Av.Gerson Gonçalves de Lima (BR-232)",
        "name": "Hotel e Restaurante Macambira",
        "phone": "+55 87 3848-1229",
        "restaurant": "yes",
        "tourism": "hotel",
        "id": "node/2189745375"
      },
      "geometry": {
        "type": "Point",
        "coordinates": [
          -37.6333823,
          -8.087806
        ]
      }
    },
    {
      "type": "Feature",
      "id": "node/3207544747",
      "properties": {
        "timestamp": "2014-11-27T12:59:52Z",
        "version": 1,
        "changeset": 27067116,
        "addr:city": "Custódia - PE",
        "addr:postcode": "56640-000",
        "addr:street": "BR-232",
        "name": "Motel Marrecas",
        "tourism": "hotel",
        "id": "node/3207544747"
      },
      "geometry": {
        "type": "Point",
        "coordinates": [
          -37.6112468,
          -8.0894805
        ]
      }
    },
    {
      "type": "Feature",
      "id": "node/11265447679",
      "properties": {
        "timestamp": "2024-12-11T18:43:47Z",
        "version": 3,
        "changeset": 160180430,
        "addr:city": "Custódia",
        "addr:street": "Avenida Presidente Kennedy",
        "internet_access": "yes",
        "name": "Hotel do Sertão",
        "nohousenumber": "yes",
        "phone": "+55 87 3848-2784",
        "tourism": "hotel",
        "website": "https://hoteldosertao.com.br/",
        "id": "node/11265447679"
      },
      "geometry": {
        "type": "Point",
        "coordinates": [
          -37.6144359,
          -8.0892358
        ]
      }
    }
  ]
}
