{
  "type": "FeatureCollection",
  "features": [
    {
      "type": "Feature",
      "id": "node/12663568518",
      "properties": {
        "timestamp": "2025-03-14T22:31:21Z",
        "version": 1,
        "changeset": 163629530,
        "amenity": "pharmacy",
        "check_date": "2025-03-14",
        "healthcare": "pharmacy",
        "internet_access": "wlan",
        "internet_access:fee": "customers",
        "name": "Panvel",
        "payment:cash": "yes",
        "payment:contactless": "yes",
        "payment:credit_cards": "yes",
        "payment:debit_cards": "yes",
        "payment:mastercard": "yes",
        "payment:pix": "yes",
        "payment:visa": "yes",
        "wheelchair": "yes",
        "id": "node/12663568518"
      },
      "geometry": {
        "type": "Point",
        "coordinates": [
          -50.8336358,
          -29.6293428
        ]
      }
    }
  ]
}
