{
  "type": "FeatureCollection",
  "features": [
    {
      "type": "Feature",
      "id": "node/8636242002",
      "properties": {
        "timestamp": "2023-06-08T02:19:56Z",
        "version": 2,
        "changeset": 137076620,
        "amenity": "library",
        "fixme": "verificar localização",
        "name": "Biblioteca Pública Municipal Getúlio Vargas",
        "id": "node/8636242002"
      },
      "geometry": {
        "type": "Point",
        "coordinates": [
          -49.888341,
          -27.365104
        ]
      }
    }
  ]
}
