{
  "type": "FeatureCollection",
  "features": [
    {
      "type": "Feature",
      "id": "node/4675730936",
      "properties": {
        "timestamp": "2023-04-18T22:38:47Z",
        "version": 3,
        "changeset": 135079263,
        "addr:street": "Rua Nossa Senhora do Bom Socorro",
        "internet_access": "yes",
        "name": "Villa Trentina Chalés",
        "tourism": "hotel",
        "id": "node/4675730936"
      },
      "geometry": {
        "type": "Point",
        "coordinates": [
          -48.9236745,
          -27.2808173
        ]
      }
    },
    {
      "type": "Feature",
      "id": "node/7519532112",
      "properties": {
        "timestamp": "2020-05-14T20:10:00Z",
        "version": 1,
        "changeset": 85221633,
        "addr:city": "Nova Trento",
        "addr:housenumber": "1",
        "addr:street": "Estrada Geral Bela Vista",
        "name": "Hotel do Santuário",
        "tourism": "hotel",
        "id": "node/7519532112"
      },
      "geometry": {
        "type": "Point",
        "coordinates": [
          -48.9439507,
          -27.2454082
        ]
      }
    }
  ]
}
