{
  "type": "FeatureCollection",
  "features": [
    {
      "type": "Feature",
      "id": "node/6382162543",
      "properties": {
        "timestamp": "2022-08-23T22:43:14Z",
        "version": 2,
        "changeset": 125291388,
        "name": "Cachoeira do Aeroporto",
        "waterway": "waterfall",
        "id": "node/6382162543"
      },
      "geometry": {
        "type": "Point",
        "coordinates": [
          -47.3630969,
          -20.5860706
        ]
      }
    }
  ]
}
