{
  "type": "FeatureCollection",
  "features": [
    {
      "type": "Feature",
      "id": "node/5830207385",
      "properties": {
        "timestamp": "2020-01-21T14:55:58Z",
        "version": 5,
        "changeset": 79862649,
        "addr:housenumber": "1111",
        "addr:street": "Rua Senador Eduardo Assmar",
        "description": "O hostel mais Haux! do Acre",
        "name": "Vivacre",
        "phone": "+556832248803",
        "tourism": "guest_house",
        "website": "www.hostalvivacre.com.br",
        "id": "node/5830207385"
      },
      "geometry": {
        "type": "Point",
        "coordinates": [
          -67.8070732,
          -9.9791929
        ]
      }
    }
  ]
}
