{
  "type": "FeatureCollection",
  "features": [
    {
      "type": "Feature",
      "id": "node/4314965437",
      "properties": {
        "timestamp": "2016-07-21T20:51:55Z",
        "version": 1,
        "changeset": 40934528,
        "historic": "memorial",
        "name": "100 Anos Imigração Japão-Brasil",
        "id": "node/4314965437"
      },
      "geometry": {
        "type": "Point",
        "coordinates": [
          -51.8400836,
          -21.8923642
        ]
      }
    }
  ]
}
