{
  "type": "FeatureCollection",
  "features": [
    {
      "type": "Feature",
      "id": "node/7613589859",
      "properties": {
        "timestamp": "2020-06-12T00:41:31Z",
        "version": 1,
        "changeset": 86538111,
        "name": "Hotel Cheiro de Mato",
        "tourism": "hotel",
        "id": "node/7613589859"
      },
      "geometry": {
        "type": "Point",
        "coordinates": [
          -46.6556055,
          -23.3320756
        ]
      }
    }
  ]
}
