{
  "type": "FeatureCollection",
  "features": [
    {
      "type": "Feature",
      "id": "node/4610868489",
      "properties": {
        "timestamp": "2017-01-16T01:51:14Z",
        "version": 1,
        "changeset": 45204658,
        "addr:street": "Rua Lino Prado",
        "name": "Rotamerica",
        "name:pt": "Rotamerica",
        "tourism": "hotel",
        "id": "node/4610868489"
      },
      "geometry": {
        "type": "Point",
        "coordinates": [
          -49.1517254,
          -14.3197008
        ]
      }
    }
  ]
}
