{
  "type": "FeatureCollection",
  "features": [
    {
      "type": "Feature",
      "id": "node/3932711383",
      "properties": {
        "timestamp": "2017-12-05T19:03:58Z",
        "version": 2,
        "changeset": 54376786,
        "name": "Cascata do Zeferino",
        "waterway": "waterfall",
        "id": "node/3932711383"
      },
      "geometry": {
        "type": "Point",
        "coordinates": [
          -51.9474966,
          -29.1031124
        ]
      }
    },
    {
      "type": "Feature",
      "id": "node/3932891011",
      "properties": {
        "timestamp": "2017-12-05T19:03:58Z",
        "version": 2,
        "changeset": 54376786,
        "waterway": "waterfall",
        "id": "node/3932891011"
      },
      "geometry": {
        "type": "Point",
        "coordinates": [
          -51.9877208,
          -29.1318363
        ]
      }
    },
    {
      "type": "Feature",
      "id": "node/5272853964",
      "properties": {
        "timestamp": "2017-12-09T00:54:37Z",
        "version": 1,
        "changeset": 54473987,
        "waterway": "waterfall",
        "id": "node/5272853964"
      },
      "geometry": {
        "type": "Point",
        "coordinates": [
          -51.9581035,
          -29.0910426
        ]
      }
    },
    {
      "type": "Feature",
      "id": "node/5272853985",
      "properties": {
        "timestamp": "2017-12-09T00:54:37Z",
        "version": 1,
        "changeset": 54473987,
        "tourism": "attraction",
        "waterway": "waterfall",
        "id": "node/5272853985"
      },
      "geometry": {
        "type": "Point",
        "coordinates": [
          -51.965104,
          -29.0933325
        ]
      }
    }
  ]
}
