{
  "type": "FeatureCollection",
  "features": [
    {
      "type": "Feature",
      "id": "node/10613422737",
      "properties": {
        "timestamp": "2023-02-07T05:40:53Z",
        "version": 1,
        "changeset": 132187557,
        "amenity": "bicycle_rental",
        "capacity": "11",
        "fee": "yes",
        "name": "Estação de Bicicletas - E6 Lago",
        "network": "Cascavel Vai De Bici",
        "operator": "Mobhis",
        "operator:type": "private",
        "payment:credit_cards": "yes",
        "id": "node/10613422737"
      },
      "geometry": {
        "type": "Point",
        "coordinates": [
          -53.4363247,
          -24.9652302
        ]
      }
    }
  ]
}
