{
  "type": "FeatureCollection",
  "features": [
    {
      "type": "Feature",
      "id": "node/8636271170",
      "properties": {
        "timestamp": "2021-04-16T18:19:53Z",
        "version": 1,
        "changeset": 103075689,
        "amenity": "library",
        "name": "Biblioteca Pública Municipal Telecentro Doutor Pedrinho",
        "id": "node/8636271170"
      },
      "geometry": {
        "type": "Point",
        "coordinates": [
          -49.4916028,
          -26.7176794
        ]
      }
    }
  ]
}
