{
  "type": "FeatureCollection",
  "features": [
    {
      "type": "Feature",
      "id": "node/8636270516",
      "properties": {
        "timestamp": "2022-09-09T22:43:46Z",
        "version": 2,
        "changeset": 125998181,
        "amenity": "library",
        "fixme": "verificar localização",
        "name": "Biblioteca Pública Municipal de Cocal do Sul",
        "id": "node/8636270516"
      },
      "geometry": {
        "type": "Point",
        "coordinates": [
          -49.3241283,
          -28.6016285
        ]
      }
    }
  ]
}
