{
  "type": "FeatureCollection",
  "features": [
    {
      "type": "Feature",
      "id": "node/5002163427",
      "properties": {
        "timestamp": "2017-07-29T21:41:53Z",
        "version": 1,
        "changeset": 50681218,
        "amenity": "library",
        "name": "Biblioteca Municipal",
        "name:pt": "Biblioteca Municipal",
        "id": "node/5002163427"
      },
      "geometry": {
        "type": "Point",
        "coordinates": [
          -37.1480024,
          -7.0327931
        ]
      }
    }
  ]
}
