{
  "type": "FeatureCollection",
  "features": [
    {
      "type": "Feature",
      "id": "node/3722200906",
      "properties": {
        "timestamp": "2022-10-22T14:14:02Z",
        "version": 3,
        "changeset": 127924141,
        "amenity": "community_centre",
        "name": "Associação Beneficiente de Sertãozinho (SOCIA)",
        "sport": "swimming",
        "id": "node/3722200906"
      },
      "geometry": {
        "type": "Point",
        "coordinates": [
          -47.9899238,
          -21.1389772
        ]
      }
    }
  ]
}
