{
  "type": "FeatureCollection",
  "features": [
    {
      "type": "Feature",
      "id": "node/3577521840",
      "properties": {
        "timestamp": "2015-08-29T01:08:53Z",
        "version": 2,
        "changeset": 33655735,
        "historic": "monument",
        "name": "Cristo Redentor",
        "id": "node/3577521840"
      },
      "geometry": {
        "type": "Point",
        "coordinates": [
          -47.9677226,
          -21.1516961
        ]
      }
    }
  ]
}
